# Bytecode dump of: calendar.cpython-313.pyc
# co_filename: D:\fluence\Github\mattbot\backend\app\api\v1\calendar.py
# co_names: ('__doc__', '__future__', 'annotations', 'logging', 'secrets', 'uuid', 'fastapi', 'APIRouter', 'Depends', 'Query', 'Request', 'fastapi.responses', 'HTMLResponse', 'sqlalchemy.ext.asyncio', 'AsyncSession', 'app.core.dependencies', 'CurrentUser', 'get_current_user', 'app.database', 'get_db', 'app.schemas.calendar', 'AvailableSlotsResponse', 'CalendarAuthUrlResponse', 'CalendarEventsResponse', 'CalendarStatusResponse', 'app.services', 'audit_service', 'calendar_service', 'getLogger', '__name__', 'logger', 'router', '_pending_oauth_states', '__annotations__', 'get', 'get_auth_url', 'oauth_callback', 'get_status', 'delete', 'disconnect', 'get_events', 'get_available_slots')
# co_consts (strings): ['Google Calendar integration endpoints: OAuth, events, available slots.', 'dict[str, uuid.UUID]', '_pending_oauth_states', '/auth-url', '/callback', '/status', '/disconnect', '/events', 'ISO 8601 datetime for range start', 'ISO 8601 datetime for range end', '/available-slots', 'Date in YYYY-MM-DD format']

# DOCSTRING: """Google Calendar integration endpoints: OAuth, events, available slots."""
# --- Nested code object: get_auth_url ---
    # DOCSTRING: """Generate a Google OAuth authorization URL for calendar access."""
    # co_names: ('secrets', 'token_urlsafe', 'user_id', '_pending_oauth_states', 'calendar_service', 'generate_auth_url', 'CalendarAuthUrlResponse')
    # co_varnames: ('current_user', 'state', 'auth_url')
      31           RETURN_GENERATOR
                   POP_TOP
           L1:     RESUME                   0
    
      36           LOAD_GLOBAL              0 (secrets)
                   LOAD_ATTR                2 (token_urlsafe)
                   PUSH_NULL
                   LOAD_CONST               1 (32)
                   CALL                     1
                   STORE_FAST               1 (state)
    
      37           LOAD_FAST                0 (current_user)
                   LOAD_ATTR                4 (user_id)
                   LOAD_GLOBAL              6 (_pending_oauth_states)
                   LOAD_FAST                1 (state)
                   STORE_SUBSCR
    
      38           LOAD_GLOBAL              8 (calendar_service)
                   LOAD_ATTR               10 (generate_auth_url)
                   PUSH_NULL
                   LOAD_FAST                1 (state)
                   CALL                     1
                   STORE_FAST               2 (auth_url)
    
      39           LOAD_GLOBAL             13 (CalendarAuthUrlResponse + NULL)
                   LOAD_FAST                2 (auth_url)
                   LOAD_CONST               2 (('auth_url',))
                   CALL_KW                  1
                   RETURN_VALUE
    
      --   L2:     CALL_INTRINSIC_1         3 (INTRINSIC_STOPITERATION_ERROR)
                   RERAISE                  1
    ExceptionTable:
      L1 to L2 -> L2 [0] lasti
    
# --- Nested code object: oauth_callback ---
    # DOCSTRING: """Handle Google OAuth callback: exchange code, store tokens, redirect to app."""
    # co_names: ('_pending_oauth_states', 'pop', 'HTMLResponse', 'calendar_service', 'exchange_code_for_tokens', 'Exception', 'logger', 'exception', 'fetch_google_email', 'warning', 'store_tokens', 'audit_service', 'log_event', 'commit')
    # co_varnames: ('request', 'code', 'state', 'db', 'user_id', 'tokens', 'google_email')
      42            RETURN_GENERATOR
                    POP_TOP
            L1:     RESUME                   0
    
      50            LOAD_GLOBAL              0 (_pending_oauth_states)
                    LOAD_ATTR                3 (pop + NULL|self)
                    LOAD_FAST                2 (state)
                    LOAD_CONST               1 (None)
                    CALL                     2
                    STORE_FAST               4 (user_id)
    
      51            LOAD_FAST                4 (user_id)
                    POP_JUMP_IF_NOT_NONE    10 (to L2)
    
      52            LOAD_GLOBAL              5 (HTMLResponse + NULL)
    
      53            LOAD_CONST               2 ('<h1>Invalid or expired OAuth state.</h1><p>Please try again from the app.</p>')
    
      54            LOAD_CONST               3 (400)
    
      52            LOAD_CONST               4 (('content', 'status_code'))
                    CALL_KW                  2
                    RETURN_VALUE
    
      57    L2:     NOP
    
      58    L3:     LOAD_GLOBAL              6 (calendar_service)
                    LOAD_ATTR                8 (exchange_code_for_tokens)
                    PUSH_NULL
                    LOAD_FAST                1 (code)
                    CALL                     1
                    GET_AWAITABLE            0
                    LOAD_CONST               1 (None)
            L4:     SEND                     3 (to L7)
            L5:     YIELD_VALUE              1
            L6:     RESUME                   3
                    JUMP_BACKWARD_NO_INTERRUPT 5 (to L4)
            L7:     END_SEND
                    STORE_FAST               5 (tokens)
    
      66    L8:     LOAD_CONST               8 ('')
                    STORE_FAST               6 (google_email)
    
      67    L9:     NOP
    
      68   L10:     LOAD_GLOBAL              6 (calendar_service)
                    LOAD_ATTR               16 (fetch_google_email)
                    PUSH_NULL
                    LOAD_FAST                5 (tokens)
                    LOAD_CONST               9 ('access_token')
                    BINARY_SUBSCR
                    CALL                     1
                    GET_AWAITABLE            0
                    LOAD_CONST               1 (None)
           L11:     SEND                     3 (to L14)
           L12:     YIELD_VALUE              1
           L13:     RESUME                   3
                    JUMP_BACKWARD_NO_INTERRUPT 5 (to L11)
           L14:     END_SEND
                    STORE_FAST               6 (google_email)
    
      72   L15:     LOAD_GLOBAL              6 (calendar_service)
                    LOAD_ATTR               20 (store_tokens)
                    PUSH_NULL
                    LOAD_FAST_LOAD_FAST     52 (db, user_id)
                    LOAD_FAST_LOAD_FAST     86 (tokens, google_email)
                    CALL                     4
                    GET_AWAITABLE            0
                    LOAD_CONST               1 (None)
           L16:     SEND                     3 (to L19)
           L17:     YIELD_VALUE              1
           L18:     RESUME                   3
                    JUMP_BACKWARD_NO_INTERRUPT 5 (to L16)
           L19:     END_SEND
                    POP_TOP
    
      74            LOAD_GLOBAL             22 (audit_service)
                    LOAD_ATTR               24 (log_event)
                    PUSH_NULL
    
      75            LOAD_FAST                3 (db)
    
      76            LOAD_FAST                4 (user_id)
    
      77            LOAD_CONST              11 ('calendar.connected')
    
      78            LOAD_CONST              12 ('user')
    
      79            LOAD_CONST              13 ('google_email')
                    LOAD_FAST                6 (google_email)
                    BUILD_MAP                1
    
      74            LOAD_CONST              14 (('owner_user_id', 'event_type', 'actor_type', 'details'))
                    CALL_KW                  5
                    GET_AWAITABLE            0
                    LOAD_CONST               1 (None)
           L20:     SEND                     3 (to L23)
           L21:     YIELD_VALUE              1
           L22:     RESUME                   3
                    JUMP_BACKWARD_NO_INTERRUPT 5 (to L20)
           L23:     END_SEND
                    POP_TOP
    
      82            LOAD_FAST                3 (db)
                    LOAD_ATTR               27 (commit + NULL|self)
                    CALL                     0
                    GET_AWAITABLE            0
                    LOAD_CONST               1 (None)
           L24:     SEND                     3 (to L27)
           L25:     YIELD_VALUE              1
           L26:     RESUME                   3
                    JUMP_BACKWARD_NO_INTERRUPT 5 (to L24)
           L27:     END_SEND
                    POP_TOP
    
      84            LOAD_GLOBAL              5 (HTMLResponse + NULL)
    
      86            LOAD_CONST              15 ('<html><head><title>Calendar Connected</title></head><body><h1>Google Calendar connected successfully!</h1><p>You can close this window and return to the app.</p><script>window.location.href="mattbot://calendar-connected";</script></body></html>')
    
      84            LOAD_CONST              16 (('content',))
                    CALL_KW                  1
                    RETURN_VALUE
    
      58   L28:     CLEANUP_THROW
           L29:     JUMP_BACKWARD_NO_INTERRUPT 138 (to L7)
    
      --   L30:     PUSH_EXC_INFO
    
      59            LOAD_GLOBAL             10 (Exception)
                    CHECK_EXC_MATCH
                    POP_JUMP_IF_FALSE       34 (to L32)
                    POP_TOP
    
      60            LOAD_GLOBAL             12 (logger)
                    LOAD_ATTR               15 (exception + NULL|self)
                    LOAD_CONST               5 ('Failed to exchange Google OAuth code')
                    CALL                     1
                    POP_TOP
    
      61            LOAD_GLOBAL              5 (HTMLResponse + NULL)
    
      62            LOAD_CONST               6 ('<h1>Failed to connect Google Calendar.</h1><p>Please try again.</p>')
    
      63            LOAD_CONST               7 (500)
    
      61            LOAD_CONST               4 (('content', 'status_code'))
                    CALL_KW                  2
                    SWAP                     2
           L31:     POP_EXCEPT
                    RETURN_VALUE
    
      59   L32:     RERAISE                  0
    
      --   L33:     COPY                     3
                    POP_EXCEPT
                    RERAISE                  1
    
      68   L34:     CLEANUP_THROW
           L35:     JUMP_BACKWARD_NO_INTERRUPT 151 (to L14)
    
      --   L36:     PUSH_EXC_INFO
    
      69            LOAD_GLOBAL             10 (Exception)
                    CHECK_EXC_MATCH
                    POP_JUMP_IF_FALSE       24 (to L38)
                    POP_TOP
    
      70            LOAD_GLOBAL             12 (logger)
                    LOAD_ATTR               19 (warning + NULL|self)
                    LOAD_CONST              10 ('Failed to fetch Google email during calendar OAuth')
                    CALL                     1
                    POP_TOP
           L37:     POP_EXCEPT
                    JUMP_BACKWARD_NO_INTERRUPT 182 (to L15)
    
      69   L38:     RERAISE                  0
    
      --   L39:     COPY                     3
                    POP_EXCEPT
                    RERAISE                  1
    
      72   L40:     CLEANUP_THROW
           L41:     JUMP_BACKWARD_NO_INTERRUPT 159 (to L19)
    
      74   L42:     CLEANUP_THROW
           L43:     JUMP_BACKWARD_NO_INTERRUPT 127 (to L23)
    
      82   L44:     CLEANUP_THROW
           L45:     JUMP_BACKWARD_NO_INTERRUPT 105 (to L27)
    
      --   L46:     CALL_INTRINSIC_1         3 (INTRINSIC_STOPITERATION_ERROR)
                    RERAISE                  1
    ExceptionTable:
      L1 to L2 -> L46 [0] lasti
      L3 to L5 -> L30 [0]
      L5 to L6 -> L28 [2]
      L6 to L8 -> L30 [0]
      L8 to L9 -> L46 [0] lasti
      L10 to L12 -> L36 [0]
      L12 to L13 -> L34 [2]
      L13 to L15 -> L36 [0]
      L15 to L17 -> L46 [0] lasti
      L17 to L18 -> L40 [2]
      L18 to L21 -> L46 [0] lasti
      L21 to L22 -> L42 [2]
      L22 to L25 -> L46 [0] lasti
      L25 to L26 -> L44 [2]
      L26 to L28 -> L46 [0] lasti
      L28 to L29 -> L30 [0]
      L30 to L31 -> L33 [1] lasti
      L31 to L32 -> L46 [0] lasti
      L32 to L33 -> L33 [1] lasti
      L33 to L34 -> L46 [0] lasti
      L34 to L35 -> L36 [0]
      L36 to L37 -> L39 [1] lasti
      L37 to L38 -> L46 [0] lasti
      L38 to L39 -> L39 [1] lasti
      L39 to L41 -> L46 [0] lasti
      L42 to L43 -> L46 [0] lasti
      L44 to L45 -> L46 [0] lasti
    
# --- Nested code object: get_status ---
    # DOCSTRING: """Check if the user has connected their Google Calendar."""
    # co_names: ('calendar_service', 'get_calendar_status', 'user_id', 'CalendarStatusResponse')
    # co_varnames: ('current_user', 'db', 'status')
      95           RETURN_GENERATOR
                   POP_TOP
           L1:     RESUME                   0
    
     101           LOAD_GLOBAL              0 (calendar_service)
                   LOAD_ATTR                2 (get_calendar_status)
                   PUSH_NULL
                   LOAD_FAST_LOAD_FAST     16 (db, current_user)
                   LOAD_ATTR                4 (user_id)
                   CALL                     2
                   GET_AWAITABLE            0
                   LOAD_CONST               1 (None)
           L2:     SEND                     3 (to L5)
           L3:     YIELD_VALUE              1
           L4:     RESUME                   3
                   JUMP_BACKWARD_NO_INTERRUPT 5 (to L2)
           L5:     END_SEND
                   STORE_FAST               2 (status)
    
     102           LOAD_GLOBAL              7 (CalendarStatusResponse + NULL)
                   LOAD_CONST               2 (())
                   BUILD_MAP                0
                   LOAD_FAST                2 (status)
                   DICT_MERGE               1
                   CALL_FUNCTION_EX         1
                   RETURN_VALUE
    
     101   L6:     CLEANUP_THROW
           L7:     JUMP_BACKWARD_NO_INTERRUPT 15 (to L5)
    
      --   L8:     CALL_INTRINSIC_1         3 (INTRINSIC_STOPITERATION_ERROR)
                   RERAISE                  1
    ExceptionTable:
      L1 to L3 -> L8 [0] lasti
      L3 to L4 -> L6 [2]
      L4 to L7 -> L8 [0] lasti
    
# --- Nested code object: disconnect ---
    # DOCSTRING: """Disconnect Google Calendar and revoke tokens."""
    # co_names: ('calendar_service', 'disconnect_calendar', 'user_id', 'app.models.user_settings', 'UserSettings', 'get', 'calendar_booking_enabled', 'revision', 'app.services', 'agent_service', 'get_or_create_default_agent', 'ensure_elevenlabs_agent', 'Exception', 'logger', 'exception', 'audit_service', 'log_event')
    # co_varnames: ('current_user', 'db', 'removed', 'UserSettings', 'settings', 'was_booking_enabled', 'agent_service', 'agent')
     105            RETURN_GENERATOR
                    POP_TOP
            L1:     RESUME                   0
    
     111            LOAD_GLOBAL              0 (calendar_service)
                    LOAD_ATTR                2 (disconnect_calendar)
                    PUSH_NULL
                    LOAD_FAST_LOAD_FAST     16 (db, current_user)
                    LOAD_ATTR                4 (user_id)
                    CALL                     2
                    GET_AWAITABLE            0
                    LOAD_CONST               1 (None)
            L2:     SEND                     3 (to L5)
            L3:     YIELD_VALUE              1
            L4:     RESUME                   3
                    JUMP_BACKWARD_NO_INTERRUPT 5 (to L2)
            L5:     END_SEND
                    STORE_FAST               2 (removed)
    
     113            LOAD_FAST                2 (removed)
                    TO_BOOL
                    POP_JUMP_IF_FALSE      240 (to L28)
    
     114            LOAD_CONST               2 (0)
                    LOAD_CONST               3 (('UserSettings',))
                    IMPORT_NAME              3 (app.models.user_settings)
                    IMPORT_FROM              4 (UserSettings)
                    STORE_FAST               3 (UserSettings)
                    POP_TOP
    
     116            LOAD_FAST                1 (db)
                    LOAD_ATTR               11 (get + NULL|self)
                    LOAD_FAST_LOAD_FAST     48 (UserSettings, current_user)
                    LOAD_ATTR                4 (user_id)
                    CALL                     2
                    GET_AWAITABLE            0
                    LOAD_CONST               1 (None)
            L6:     SEND                     3 (to L9)
            L7:     YIELD_VALUE              1
            L8:     RESUME                   3
                    JUMP_BACKWARD_NO_INTERRUPT 5 (to L6)
            L9:     END_SEND
                    STORE_FAST               4 (settings)
    
     117            LOAD_FAST                4 (settings)
                    TO_BOOL
                    POP_JUMP_IF_FALSE       12 (to L10)
                    LOAD_FAST                4 (settings)
                    LOAD_ATTR               12 (calendar_booking_enabled)
                    JUMP_FORWARD             1 (to L11)
           L10:     LOAD_CONST               4 (False)
           L11:     STORE_FAST               5 (was_booking_enabled)
    
     118            LOAD_FAST                4 (settings)
                    TO_BOOL
                    POP_JUMP_IF_FALSE       45 (to L12)
                    LOAD_FAST                4 (settings)
                    LOAD_ATTR               12 (calendar_booking_enabled)
                    TO_BOOL
                    POP_JUMP_IF_FALSE       28 (to L12)
    
     119            LOAD_CONST               4 (False)
                    LOAD_FAST                4 (settings)
                    STORE_ATTR               6 (calendar_booking_enabled)
    
     120            LOAD_FAST                4 (settings)
                    COPY                     1
                    LOAD_ATTR               14 (revision)
                    LOAD_CONST               5 (1)
                    BINARY_OP               13 (+=)
                    SWAP                     2
                    STORE_ATTR               7 (revision)
    
     122   L12:     LOAD_FAST                5 (was_booking_enabled)
                    TO_BOOL
                    POP_JUMP_IF_FALSE       78 (to L23)
    
     123   L13:     NOP
    
     124   L14:     LOAD_CONST               2 (0)
                    LOAD_CONST               6 (('agent_service',))
                    IMPORT_NAME              8 (app.services)
                    IMPORT_FROM              9 (agent_service)
                    STORE_FAST               6 (agent_service)
                    POP_TOP
    
     126            LOAD_FAST                6 (agent_service)
                    LOAD_ATTR               21 (get_or_create_default_agent + NULL|self)
    
     127            LOAD_FAST_LOAD_FAST     16 (db, current_user)
                    LOAD_ATTR                4 (user_id)
    
     126            CALL                     2
                    GET_AWAITABLE            0
                    LOAD_CONST               1 (None)
           L15:     SEND                     3 (to L18)
           L16:     YIELD_VALUE              1
           L17:     RESUME                   3
                    JUMP_BACKWARD_NO_INTERRUPT 5 (to L15)
           L18:     END_SEND
                    STORE_FAST               7 (agent)
    
     129            LOAD_FAST                6 (agent_service)
                    LOAD_ATTR               23 (ensure_elevenlabs_agent + NULL|self)
    
     130            LOAD_FAST_LOAD_FAST     23 (db, agent)
                    LOAD_FAST                0 (current_user)
                    LOAD_ATTR                4 (user_id)
    
     129            CALL                     3
                    GET_AWAITABLE            0
                    LOAD_CONST               1 (None)
           L19:     SEND                     3 (to L22)
           L20:     YIELD_VALUE              1
           L21:     RESUME                   3
                    JUMP_BACKWARD_NO_INTERRUPT 5 (to L19)
           L22:     END_SEND
                    POP_TOP
    
     137   L23:     LOAD_GLOBAL             30 (audit_service)
                    LOAD_ATTR               32 (log_event)
                    PUSH_NULL
    
     138            LOAD_FAST                1 (db)
    
     139            LOAD_FAST                0 (current_user)
                    LOAD_ATTR                4 (user_id)
    
     140            LOAD_CONST               8 ('calendar.disconnected')
    
     141            LOAD_CONST               9 ('user')
    
     137            LOAD_CONST              10 (('owner_user_id', 'event_type', 'actor_type'))
                    CALL_KW                  4
                    GET_AWAITABLE            0
                    LOAD_CONST               1 (None)
           L24:     SEND                     3 (to L27)
           L25:     YIELD_VALUE              1
           L26:     RESUME                   3
                    JUMP_BACKWARD_NO_INTERRUPT 5 (to L24)
           L27:     END_SEND
                    POP_TOP
    
     144   L28:     LOAD_CONST              11 ('disconnected')
                    LOAD_FAST                2 (removed)
                    BUILD_MAP                1
                    RETURN_VALUE
    
     111   L29:     CLEANUP_THROW
           L30:     JUMP_BACKWARD_NO_INTERRUPT 255 (to L5)
    
     116   L31:     CLEANUP_THROW
           L32:     JUMP_BACKWARD_NO_INTERRUPT 209 (to L9)
    
     126   L33:     CLEANUP_THROW
           L34:     JUMP_BACKWARD_NO_INTERRUPT 89 (to L18)
    
     129   L35:     CLEANUP_THROW
           L36:     JUMP_BACKWARD_NO_INTERRUPT 55 (to L22)
    
      --   L37:     PUSH_EXC_INFO
    
     132            LOAD_GLOBAL             24 (Exception)
                    CHECK_EXC_MATCH
                    POP_JUMP_IF_FALSE       24 (to L39)
                    POP_TOP
    
     133            LOAD_GLOBAL             26 (logger)
                    LOAD_ATTR               29 (exception + NULL|self)
    
     134            LOAD_CONST               7 ('Failed to sync ElevenLabs agent after calendar disconnect')
    
     133            CALL                     1
                    POP_TOP
           L38:     POP_EXCEPT
                    JUMP_BACKWARD_NO_INTERRUPT 86 (to L23)
    
     132   L39:     RERAISE                  0
    
      --   L40:     COPY                     3
                    POP_EXCEPT
                    RERAISE                  1
    
     137   L41:     CLEANUP_THROW
           L42:     JUMP_BACKWARD_NO_INTERRUPT 53 (to L27)
    
      --   L43:     CALL_INTRINSIC_1         3 (INTRINSIC_STOPITERATION_ERROR)
                    RERAISE                  1
    ExceptionTable:
      L1 to L3 -> L43 [0] lasti
      L3 to L4 -> L29 [2]
      L4 to L7 -> L43 [0] lasti
      L7 to L8 -> L31 [2]
      L8 to L13 -> L43 [0] lasti
      L14 to L16 -> L37 [0]
      L16 to L17 -> L33 [2]
      L17 to L20 -> L37 [0]
      L20 to L21 -> L35 [2]
      L21 to L23 -> L37 [0]
      L23 to L25 -> L43 [0] lasti
      L25 to L26 -> L41 [2]
      L26 to L30 -> L43 [0] lasti
      L31 to L32 -> L43 [0] lasti
      L33 to L34 -> L37 [0]
      L35 to L36 -> L37 [0]
      L37 to L38 -> L40 [1] lasti
      L38 to L39 -> L43 [0] lasti
      L39 to L40 -> L40 [1] lasti
      L40 to L42 -> L43 [0] lasti
    
# --- Nested code object: get_events ---
    # DOCSTRING: """List events from the user's Google Calendar within a time range."""
    # co_names: ('app.models.user_settings', 'UserSettings', 'get', 'user_id', 'timezone', 'calendar_service', 'list_events', 'CalendarEventsResponse')
    # co_varnames: ('start', 'end', 'current_user', 'db', 'UserSettings', 'settings', 'user_tz', 'events')
     147            RETURN_GENERATOR
                    POP_TOP
            L1:     RESUME                   0
    
     155            LOAD_CONST               1 (0)
                    LOAD_CONST               2 (('UserSettings',))
                    IMPORT_NAME              0 (app.models.user_settings)
                    IMPORT_FROM              1 (UserSettings)
                    STORE_FAST               4 (UserSettings)
                    POP_TOP
    
     157            LOAD_FAST                3 (db)
                    LOAD_ATTR                5 (get + NULL|self)
                    LOAD_FAST_LOAD_FAST     66 (UserSettings, current_user)
                    LOAD_ATTR                6 (user_id)
                    CALL                     2
                    GET_AWAITABLE            0
                    LOAD_CONST               3 (None)
            L2:     SEND                     3 (to L5)
            L3:     YIELD_VALUE              1
            L4:     RESUME                   3
                    JUMP_BACKWARD_NO_INTERRUPT 5 (to L2)
            L5:     END_SEND
                    STORE_FAST               5 (settings)
    
     158            LOAD_FAST                5 (settings)
                    TO_BOOL
                    POP_JUMP_IF_FALSE       29 (to L6)
                    LOAD_FAST                5 (settings)
                    LOAD_ATTR                8 (timezone)
                    TO_BOOL
                    POP_JUMP_IF_FALSE       12 (to L6)
                    LOAD_FAST                5 (settings)
                    LOAD_ATTR                8 (timezone)
                    JUMP_FORWARD             1 (to L7)
            L6:     LOAD_CONST               4 ('UTC')
            L7:     STORE_FAST               6 (user_tz)
    
     160            LOAD_GLOBAL             10 (calendar_service)
                    LOAD_ATTR               12 (list_events)
                    PUSH_NULL
    
     161            LOAD_FAST_LOAD_FAST     50 (db, current_user)
                    LOAD_ATTR                6 (user_id)
                    LOAD_FAST_LOAD_FAST      1 (start, end)
                    LOAD_FAST                6 (user_tz)
    
     160            LOAD_CONST               5 (('timezone',))
                    CALL_KW                  5
                    GET_AWAITABLE            0
                    LOAD_CONST               3 (None)
            L8:     SEND                     3 (to L11)
            L9:     YIELD_VALUE              1
           L10:     RESUME                   3
                    JUMP_BACKWARD_NO_INTERRUPT 5 (to L8)
           L11:     END_SEND
                    STORE_FAST               7 (events)
    
     163            LOAD_GLOBAL             15 (CalendarEventsResponse + NULL)
                    LOAD_FAST_LOAD_FAST    118 (events, user_tz)
                    LOAD_CONST               6 (('events', 'timezone'))
                    CALL_KW                  2
                    RETURN_VALUE
    
     157   L12:     CLEANUP_THROW
           L13:     JUMP_BACKWARD_NO_INTERRUPT 91 (to L5)
    
     160   L14:     CLEANUP_THROW
           L15:     JUMP_BACKWARD_NO_INTERRUPT 15 (to L11)
    
      --   L16:     CALL_INTRINSIC_1         3 (INTRINSIC_STOPITERATION_ERROR)
                    RERAISE                  1
    ExceptionTable:
      L1 to L3 -> L16 [0] lasti
      L3 to L4 -> L12 [2]
      L4 to L9 -> L16 [0] lasti
      L9 to L10 -> L14 [2]
      L10 to L13 -> L16 [0] lasti
      L14 to L15 -> L16 [0] lasti
    
# --- Nested code object: get_available_slots ---
    # DOCSTRING: """Find available appointment slots on a given date."""
    # co_names: ('app.models.user_settings', 'UserSettings', 'get', 'user_id', 'calendar_default_duration_minutes', 'timezone', 'business_hours_enabled', 'business_hours_start', 'business_hours_end', 'calendar_service', 'find_available_slots', 'AvailableSlotsResponse')
    # co_varnames: ('date', 'current_user', 'db', 'UserSettings', 'settings', 'duration', 'timezone', 'bh_start', 'bh_end', 'slots')
     166            RETURN_GENERATOR
                    POP_TOP
            L1:     RESUME                   0
    
     173            LOAD_CONST               1 (0)
                    LOAD_CONST               2 (('UserSettings',))
                    IMPORT_NAME              0 (app.models.user_settings)
                    IMPORT_FROM              1 (UserSettings)
                    STORE_FAST               3 (UserSettings)
                    POP_TOP
    
     175            LOAD_FAST                2 (db)
                    LOAD_ATTR                5 (get + NULL|self)
                    LOAD_FAST_LOAD_FAST     49 (UserSettings, current_user)
                    LOAD_ATTR                6 (user_id)
                    CALL                     2
                    GET_AWAITABLE            0
                    LOAD_CONST               3 (None)
            L2:     SEND                     3 (to L5)
            L3:     YIELD_VALUE              1
            L4:     RESUME                   3
                    JUMP_BACKWARD_NO_INTERRUPT 5 (to L2)
            L5:     END_SEND
                    STORE_FAST               4 (settings)
    
     176            LOAD_FAST                4 (settings)
                    TO_BOOL
                    POP_JUMP_IF_FALSE       12 (to L6)
                    LOAD_FAST                4 (settings)
                    LOAD_ATTR                8 (calendar_default_duration_minutes)
                    JUMP_FORWARD             1 (to L7)
            L6:     LOAD_CONST               4 (30)
            L7:     STORE_FAST               5 (duration)
    
     177            LOAD_FAST                4 (settings)
                    TO_BOOL
                    POP_JUMP_IF_FALSE       12 (to L8)
                    LOAD_FAST                4 (settings)
                    LOAD_ATTR               10 (timezone)
                    JUMP_FORWARD             1 (to L9)
            L8:     LOAD_CONST               5 ('UTC')
            L9:     STORE_FAST               6 (timezone)
    
     180            LOAD_FAST                4 (settings)
                    TO_BOOL
                    POP_JUMP_IF_FALSE       29 (to L10)
                    LOAD_FAST                4 (settings)
                    LOAD_ATTR               12 (business_hours_enabled)
                    TO_BOOL
                    POP_JUMP_IF_FALSE       12 (to L10)
    
     179            LOAD_FAST                4 (settings)
                    LOAD_ATTR               14 (business_hours_start)
                    JUMP_FORWARD             1 (to L11)
    
     181   L10:     LOAD_CONST               3 (None)
    
     178   L11:     STORE_FAST               7 (bh_start)
    
     185            LOAD_FAST                4 (settings)
                    TO_BOOL
                    POP_JUMP_IF_FALSE       29 (to L12)
                    LOAD_FAST                4 (settings)
                    LOAD_ATTR               12 (business_hours_enabled)
                    TO_BOOL
                    POP_JUMP_IF_FALSE       12 (to L12)
    
     184            LOAD_FAST                4 (settings)
                    LOAD_ATTR               16 (business_hours_end)
                    JUMP_FORWARD             1 (to L13)
    
     186   L12:     LOAD_CONST               3 (None)
    
     183   L13:     STORE_FAST               8 (bh_end)
    
     189            LOAD_GLOBAL             18 (calendar_service)
                    LOAD_ATTR               20 (find_available_slots)
                    PUSH_NULL
    
     190            LOAD_FAST                2 (db)
    
     191            LOAD_FAST                1 (current_user)
                    LOAD_ATTR                6 (user_id)
    
     192            LOAD_FAST                0 (date)
    
     193            LOAD_FAST                5 (duration)
    
     194            LOAD_FAST                7 (bh_start)
    
     195            LOAD_FAST                8 (bh_end)
    
     196            LOAD_FAST                6 (timezone)
    
     189            LOAD_CONST               6 (('duration_minutes', 'business_start', 'business_end', 'timezone'))
                    CALL_KW                  7
                    GET_AWAITABLE            0
                    LOAD_CONST               3 (None)
           L14:     SEND                     3 (to L17)
           L15:     YIELD_VALUE              1
           L16:     RESUME                   3
                    JUMP_BACKWARD_NO_INTERRUPT 5 (to L14)
           L17:     END_SEND
                    STORE_FAST               9 (slots)
    
     198            LOAD_GLOBAL             23 (AvailableSlotsResponse + NULL)
                    LOAD_FAST_LOAD_FAST      9 (date, slots)
                    LOAD_CONST               7 (('date', 'slots'))
                    CALL_KW                  2
                    RETURN_VALUE
    
     175   L18:     CLEANUP_THROW
           L19:     JUMP_BACKWARD_NO_INTERRUPT 175 (to L5)
    
     189   L20:     CLEANUP_THROW
           L21:     JUMP_BACKWARD_NO_INTERRUPT 15 (to L17)
    
      --   L22:     CALL_INTRINSIC_1         3 (INTRINSIC_STOPITERATION_ERROR)
                    RERAISE                  1
    ExceptionTable:
      L1 to L3 -> L22 [0] lasti
      L3 to L4 -> L18 [2]
      L4 to L15 -> L22 [0] lasti
      L15 to L16 -> L20 [2]
      L16 to L19 -> L22 [0] lasti
      L20 to L21 -> L22 [0] lasti
    
# co_names: ('__doc__', '__future__', 'annotations', 'logging', 'secrets', 'uuid', 'fastapi', 'APIRouter', 'Depends', 'Query', 'Request', 'fastapi.responses', 'HTMLResponse', 'sqlalchemy.ext.asyncio', 'AsyncSession', 'app.core.dependencies', 'CurrentUser', 'get_current_user', 'app.database', 'get_db', 'app.schemas.calendar', 'AvailableSlotsResponse', 'CalendarAuthUrlResponse', 'CalendarEventsResponse', 'CalendarStatusResponse', 'app.services', 'audit_service', 'calendar_service', 'getLogger', '__name__', 'logger', 'router', '_pending_oauth_states', '__annotations__', 'get', 'get_auth_url', 'oauth_callback', 'get_status', 'delete', 'disconnect', 'get_events', 'get_available_slots')
# co_varnames: ()
  0           RESUME                   0

  1           SETUP_ANNOTATIONS
              LOAD_CONST               0 ('Google Calendar integration endpoints: OAuth, events, available slots.')
              STORE_NAME               0 (__doc__)

  3           LOAD_CONST               1 (0)
              LOAD_CONST               2 (('annotations',))
              IMPORT_NAME              1 (__future__)
              IMPORT_FROM              2 (annotations)
              STORE_NAME               2 (annotations)
              POP_TOP

  5           LOAD_CONST               1 (0)
              LOAD_CONST               3 (None)
              IMPORT_NAME              3 (logging)
              STORE_NAME               3 (logging)

  6           LOAD_CONST               1 (0)
              LOAD_CONST               3 (None)
              IMPORT_NAME              4 (secrets)
              STORE_NAME               4 (secrets)

  7           LOAD_CONST               1 (0)
              LOAD_CONST               3 (None)
              IMPORT_NAME              5 (uuid)
              STORE_NAME               5 (uuid)

  9           LOAD_CONST               1 (0)
              LOAD_CONST               4 (('APIRouter', 'Depends', 'Query', 'Request'))
              IMPORT_NAME              6 (fastapi)
              IMPORT_FROM              7 (APIRouter)
              STORE_NAME               7 (APIRouter)
              IMPORT_FROM              8 (Depends)
              STORE_NAME               8 (Depends)
              IMPORT_FROM              9 (Query)
              STORE_NAME               9 (Query)
              IMPORT_FROM             10 (Request)
              STORE_NAME              10 (Request)
              POP_TOP

 10           LOAD_CONST               1 (0)
              LOAD_CONST               5 (('HTMLResponse',))
              IMPORT_NAME             11 (fastapi.responses)
              IMPORT_FROM             12 (HTMLResponse)
              STORE_NAME              12 (HTMLResponse)
              POP_TOP

 11           LOAD_CONST               1 (0)
              LOAD_CONST               6 (('AsyncSession',))
              IMPORT_NAME             13 (sqlalchemy.ext.asyncio)
              IMPORT_FROM             14 (AsyncSession)
              STORE_NAME              14 (AsyncSession)
              POP_TOP

 13           LOAD_CONST               1 (0)
              LOAD_CONST               7 (('CurrentUser', 'get_current_user'))
              IMPORT_NAME             15 (app.core.dependencies)
              IMPORT_FROM             16 (CurrentUser)
              STORE_NAME              16 (CurrentUser)
              IMPORT_FROM             17 (get_current_user)
              STORE_NAME              17 (get_current_user)
              POP_TOP

 14           LOAD_CONST               1 (0)
              LOAD_CONST               8 (('get_db',))
              IMPORT_NAME             18 (app.database)
              IMPORT_FROM             19 (get_db)
              STORE_NAME              19 (get_db)
              POP_TOP

 15           LOAD_CONST               1 (0)
              LOAD_CONST               9 (('AvailableSlotsResponse', 'CalendarAuthUrlResponse', 'CalendarEventsResponse', 'CalendarStatusResponse'))
              IMPORT_NAME             20 (app.schemas.calendar)
              IMPORT_FROM             21 (AvailableSlotsResponse)
              STORE_NAME              21 (AvailableSlotsResponse)
              IMPORT_FROM             22 (CalendarAuthUrlResponse)
              STORE_NAME              22 (CalendarAuthUrlResponse)
              IMPORT_FROM             23 (CalendarEventsResponse)
              STORE_NAME              23 (CalendarEventsResponse)
              IMPORT_FROM             24 (CalendarStatusResponse)
              STORE_NAME              24 (CalendarStatusResponse)
              POP_TOP

 21           LOAD_CONST               1 (0)
              LOAD_CONST              10 (('audit_service', 'calendar_service'))
              IMPORT_NAME             25 (app.services)
              IMPORT_FROM             26 (audit_service)
              STORE_NAME              26 (audit_service)
              IMPORT_FROM             27 (calendar_service)
              STORE_NAME              27 (calendar_service)
              POP_TOP

 23           LOAD_NAME                3 (logging)
              LOAD_ATTR               56 (getLogger)
              PUSH_NULL
              LOAD_NAME               29 (__name__)
              CALL                     1
              STORE_NAME              30 (logger)

 25           LOAD_NAME                7 (APIRouter)
              PUSH_NULL
              CALL                     0
              STORE_NAME              31 (router)

 28           BUILD_MAP                0
              STORE_NAME              32 (_pending_oauth_states)
              LOAD_CONST              11 ('dict[str, uuid.UUID]')
              LOAD_NAME               33 (__annotations__)
              LOAD_CONST              12 ('_pending_oauth_states')
              STORE_SUBSCR

 31           LOAD_NAME               31 (router)
              LOAD_ATTR               69 (get + NULL|self)
              LOAD_CONST              13 ('/auth-url')
              LOAD_NAME               22 (CalendarAuthUrlResponse)
              LOAD_CONST              14 (('response_model',))
              CALL_KW                  2

 33           LOAD_NAME                8 (Depends)
              PUSH_NULL
              LOAD_NAME               17 (get_current_user)
              CALL                     1

 32           BUILD_TUPLE              1

 33           NOP

 32           NOP

 34           NOP

 32           LOAD_CONST              31 (('current_user', 'CurrentUser', 'return', 'CalendarAuthUrlResponse'))
              LOAD_CONST              15 (<code object get_auth_url at 0x0000024C11435170, file "D:\fluence\Github\mattbot\backend\app\api\v1\calendar.py", line 31>)
              MAKE_FUNCTION
              SET_FUNCTION_ATTRIBUTE   4 (annotations)
              SET_FUNCTION_ATTRIBUTE   1 (defaults)

 31           CALL                     0

 32           STORE_NAME              35 (get_auth_url)

 42           LOAD_NAME               31 (router)
              LOAD_ATTR               69 (get + NULL|self)
              LOAD_CONST              16 ('/callback')
              CALL                     1

 45           LOAD_NAME                9 (Query)
              PUSH_NULL
              LOAD_CONST              17 (Ellipsis)
              CALL                     1

 46           LOAD_NAME                9 (Query)
              PUSH_NULL
              LOAD_CONST              17 (Ellipsis)
              CALL                     1

 47           LOAD_NAME                8 (Depends)
              PUSH_NULL
              LOAD_NAME               19 (get_db)
              CALL                     1

 43           BUILD_TUPLE              3

 44           NOP

 43           NOP

 45           NOP

 43           NOP

 46           NOP

 43           NOP

 47           NOP

 43           NOP

 48           NOP

 43           LOAD_CONST              32 (('request', 'Request', 'code', 'str', 'state', 'str', 'db', 'AsyncSession', 'return', 'HTMLResponse'))
              LOAD_CONST              18 (<code object oauth_callback at 0x0000024C0FBE4020, file "D:\fluence\Github\mattbot\backend\app\api\v1\calendar.py", line 42>)
              MAKE_FUNCTION
              SET_FUNCTION_ATTRIBUTE   4 (annotations)
              SET_FUNCTION_ATTRIBUTE   1 (defaults)

 42           CALL                     0

 43           STORE_NAME              36 (oauth_callback)

 95           LOAD_NAME               31 (router)
              LOAD_ATTR               69 (get + NULL|self)
              LOAD_CONST              19 ('/status')
              LOAD_NAME               24 (CalendarStatusResponse)
              LOAD_CONST              14 (('response_model',))
              CALL_KW                  2

 97           LOAD_NAME                8 (Depends)
              PUSH_NULL
              LOAD_NAME               17 (get_current_user)
              CALL                     1

 98           LOAD_NAME                8 (Depends)
              PUSH_NULL
              LOAD_NAME               19 (get_db)
              CALL                     1

 96           BUILD_TUPLE              2

 97           NOP

 96           NOP

 98           NOP

 96           NOP

 99           NOP

 96           LOAD_CONST              33 (('current_user', 'CurrentUser', 'db', 'AsyncSession', 'return', 'CalendarStatusResponse'))
              LOAD_CONST              20 (<code object get_status at 0x0000024C114988F0, file "D:\fluence\Github\mattbot\backend\app\api\v1\calendar.py", line 95>)
              MAKE_FUNCTION
              SET_FUNCTION_ATTRIBUTE   4 (annotations)
              SET_FUNCTION_ATTRIBUTE   1 (defaults)

 95           CALL                     0

 96           STORE_NAME              37 (get_status)

105           LOAD_NAME               31 (router)
              LOAD_ATTR               77 (delete + NULL|self)
              LOAD_CONST              21 ('/disconnect')
              CALL                     1

107           LOAD_NAME                8 (Depends)
              PUSH_NULL
              LOAD_NAME               17 (get_current_user)
              CALL                     1

108           LOAD_NAME                8 (Depends)
              PUSH_NULL
              LOAD_NAME               19 (get_db)
              CALL                     1

106           BUILD_TUPLE              2

107           NOP

106           NOP

108           NOP

106           NOP

109           NOP

106           LOAD_CONST              34 (('current_user', 'CurrentUser', 'db', 'AsyncSession', 'return', 'dict'))
              LOAD_CONST              22 (<code object disconnect at 0x0000024C0FB64550, file "D:\fluence\Github\mattbot\backend\app\api\v1\calendar.py", line 105>)
              MAKE_FUNCTION
              SET_FUNCTION_ATTRIBUTE   4 (annotations)
              SET_FUNCTION_ATTRIBUTE   1 (defaults)

105           CALL                     0

106           STORE_NAME              39 (disconnect)

147           LOAD_NAME               31 (router)
              LOAD_ATTR               69 (get + NULL|self)
              LOAD_CONST              23 ('/events')
              LOAD_NAME               23 (CalendarEventsResponse)
              LOAD_CONST              14 (('response_model',))
              CALL_KW                  2

149           LOAD_NAME                9 (Query)
              PUSH_NULL
              LOAD_CONST              17 (Ellipsis)
              LOAD_CONST              24 ('ISO 8601 datetime for range start')
              LOAD_CONST              25 (('description',))
              CALL_KW                  2

150           LOAD_NAME                9 (Query)
              PUSH_NULL
              LOAD_CONST              17 (Ellipsis)
              LOAD_CONST              26 ('ISO 8601 datetime for range end')
              LOAD_CONST              25 (('description',))
              CALL_KW                  2

151           LOAD_NAME                8 (Depends)
              PUSH_NULL
              LOAD_NAME               17 (get_current_user)
              CALL                     1

152           LOAD_NAME                8 (Depends)
              PUSH_NULL
              LOAD_NAME               19 (get_db)
              CALL                     1

148           BUILD_TUPLE              4

149           NOP

148           NOP

150           NOP

148           NOP

151           NOP

148           NOP

152           NOP

148           NOP

153           NOP

148           LOAD_CONST              35 (('start', 'str', 'end', 'str', 'current_user', 'CurrentUser', 'db', 'AsyncSession', 'return', 'CalendarEventsResponse'))
              LOAD_CONST              27 (<code object get_events at 0x0000024C0EC4BE10, file "D:\fluence\Github\mattbot\backend\app\api\v1\calendar.py", line 147>)
              MAKE_FUNCTION
              SET_FUNCTION_ATTRIBUTE   4 (annotations)
              SET_FUNCTION_ATTRIBUTE   1 (defaults)

147           CALL                     0

148           STORE_NAME              40 (get_events)

166           LOAD_NAME               31 (router)
              LOAD_ATTR               69 (get + NULL|self)
              LOAD_CONST              28 ('/available-slots')
              LOAD_NAME               21 (AvailableSlotsResponse)
              LOAD_CONST              14 (('response_model',))
              CALL_KW                  2

168           LOAD_NAME                9 (Query)
              PUSH_NULL
              LOAD_CONST              17 (Ellipsis)
              LOAD_CONST              29 ('Date in YYYY-MM-DD format')
              LOAD_CONST              25 (('description',))
              CALL_KW                  2

169           LOAD_NAME                8 (Depends)
              PUSH_NULL
              LOAD_NAME               17 (get_current_user)
              CALL                     1

170           LOAD_NAME                8 (Depends)
              PUSH_NULL
              LOAD_NAME               19 (get_db)
              CALL                     1

167           BUILD_TUPLE              3

168           NOP

167           NOP

169           NOP

167           NOP

170           NOP

167           NOP

171           NOP

167           LOAD_CONST              36 (('date', 'str', 'current_user', 'CurrentUser', 'db', 'AsyncSession', 'return', 'AvailableSlotsResponse'))
              LOAD_CONST              30 (<code object get_available_slots at 0x0000024C0FB629F0, file "D:\fluence\Github\mattbot\backend\app\api\v1\calendar.py", line 166>)
              MAKE_FUNCTION
              SET_FUNCTION_ATTRIBUTE   4 (annotations)
              SET_FUNCTION_ATTRIBUTE   1 (defaults)

166           CALL                     0

167           STORE_NAME              41 (get_available_slots)
              RETURN_CONST             3 (None)

Disassembly of <code object get_auth_url at 0x0000024C11435170, file "D:\fluence\Github\mattbot\backend\app\api\v1\calendar.py", line 31>:
  31           RETURN_GENERATOR
               POP_TOP
       L1:     RESUME                   0

  36           LOAD_GLOBAL              0 (secrets)
               LOAD_ATTR                2 (token_urlsafe)
               PUSH_NULL
               LOAD_CONST               1 (32)
               CALL                     1
               STORE_FAST               1 (state)

  37           LOAD_FAST                0 (current_user)
               LOAD_ATTR                4 (user_id)
               LOAD_GLOBAL              6 (_pending_oauth_states)
               LOAD_FAST                1 (state)
               STORE_SUBSCR

  38           LOAD_GLOBAL              8 (calendar_service)
               LOAD_ATTR               10 (generate_auth_url)
               PUSH_NULL
               LOAD_FAST                1 (state)
               CALL                     1
               STORE_FAST               2 (auth_url)

  39           LOAD_GLOBAL             13 (CalendarAuthUrlResponse + NULL)
               LOAD_FAST                2 (auth_url)
               LOAD_CONST               2 (('auth_url',))
               CALL_KW                  1
               RETURN_VALUE

  --   L2:     CALL_INTRINSIC_1         3 (INTRINSIC_STOPITERATION_ERROR)
               RERAISE                  1
ExceptionTable:
  L1 to L2 -> L2 [0] lasti

Disassembly of <code object oauth_callback at 0x0000024C0FBE4020, file "D:\fluence\Github\mattbot\backend\app\api\v1\calendar.py", line 42>:
  42            RETURN_GENERATOR
                POP_TOP
        L1:     RESUME                   0

  50            LOAD_GLOBAL              0 (_pending_oauth_states)
                LOAD_ATTR                3 (pop + NULL|self)
                LOAD_FAST                2 (state)
                LOAD_CONST               1 (None)
                CALL                     2
                STORE_FAST               4 (user_id)

  51            LOAD_FAST                4 (user_id)
                POP_JUMP_IF_NOT_NONE    10 (to L2)

  52            LOAD_GLOBAL              5 (HTMLResponse + NULL)

  53            LOAD_CONST               2 ('<h1>Invalid or expired OAuth state.</h1><p>Please try again from the app.</p>')

  54            LOAD_CONST               3 (400)

  52            LOAD_CONST               4 (('content', 'status_code'))
                CALL_KW                  2
                RETURN_VALUE

  57    L2:     NOP

  58    L3:     LOAD_GLOBAL              6 (calendar_service)
                LOAD_ATTR                8 (exchange_code_for_tokens)
                PUSH_NULL
                LOAD_FAST                1 (code)
                CALL                     1
                GET_AWAITABLE            0
                LOAD_CONST               1 (None)
        L4:     SEND                     3 (to L7)
        L5:     YIELD_VALUE              1
        L6:     RESUME                   3
                JUMP_BACKWARD_NO_INTERRUPT 5 (to L4)
        L7:     END_SEND
                STORE_FAST               5 (tokens)

  66    L8:     LOAD_CONST               8 ('')
                STORE_FAST               6 (google_email)

  67    L9:     NOP

  68   L10:     LOAD_GLOBAL              6 (calendar_service)
                LOAD_ATTR               16 (fetch_google_email)
                PUSH_NULL
                LOAD_FAST                5 (tokens)
                LOAD_CONST               9 ('access_token')
                BINARY_SUBSCR
                CALL                     1
                GET_AWAITABLE            0
                LOAD_CONST               1 (None)
       L11:     SEND                     3 (to L14)
       L12:     YIELD_VALUE              1
       L13:     RESUME                   3
                JUMP_BACKWARD_NO_INTERRUPT 5 (to L11)
       L14:     END_SEND
                STORE_FAST               6 (google_email)

  72   L15:     LOAD_GLOBAL              6 (calendar_service)
                LOAD_ATTR               20 (store_tokens)
                PUSH_NULL
                LOAD_FAST_LOAD_FAST     52 (db, user_id)
                LOAD_FAST_LOAD_FAST     86 (tokens, google_email)
                CALL                     4
                GET_AWAITABLE            0
                LOAD_CONST               1 (None)
       L16:     SEND                     3 (to L19)
       L17:     YIELD_VALUE              1
       L18:     RESUME                   3
                JUMP_BACKWARD_NO_INTERRUPT 5 (to L16)
       L19:     END_SEND
                POP_TOP

  74            LOAD_GLOBAL             22 (audit_service)
                LOAD_ATTR               24 (log_event)
                PUSH_NULL

  75            LOAD_FAST                3 (db)

  76            LOAD_FAST                4 (user_id)

  77            LOAD_CONST              11 ('calendar.connected')

  78            LOAD_CONST              12 ('user')

  79            LOAD_CONST              13 ('google_email')
                LOAD_FAST                6 (google_email)
                BUILD_MAP                1

  74            LOAD_CONST              14 (('owner_user_id', 'event_type', 'actor_type', 'details'))
                CALL_KW                  5
                GET_AWAITABLE            0
                LOAD_CONST               1 (None)
       L20:     SEND                     3 (to L23)
       L21:     YIELD_VALUE              1
       L22:     RESUME                   3
                JUMP_BACKWARD_NO_INTERRUPT 5 (to L20)
       L23:     END_SEND
                POP_TOP

  82            LOAD_FAST                3 (db)
                LOAD_ATTR               27 (commit + NULL|self)
                CALL                     0
                GET_AWAITABLE            0
                LOAD_CONST               1 (None)
       L24:     SEND                     3 (to L27)
       L25:     YIELD_VALUE              1
       L26:     RESUME                   3
                JUMP_BACKWARD_NO_INTERRUPT 5 (to L24)
       L27:     END_SEND
                POP_TOP

  84            LOAD_GLOBAL              5 (HTMLResponse + NULL)

  86            LOAD_CONST              15 ('<html><head><title>Calendar Connected</title></head><body><h1>Google Calendar connected successfully!</h1><p>You can close this window and return to the app.</p><script>window.location.href="mattbot://calendar-connected";</script></body></html>')

  84            LOAD_CONST              16 (('content',))
                CALL_KW                  1
                RETURN_VALUE

  58   L28:     CLEANUP_THROW
       L29:     JUMP_BACKWARD_NO_INTERRUPT 138 (to L7)

  --   L30:     PUSH_EXC_INFO

  59            LOAD_GLOBAL             10 (Exception)
                CHECK_EXC_MATCH
                POP_JUMP_IF_FALSE       34 (to L32)
                POP_TOP

  60            LOAD_GLOBAL             12 (logger)
                LOAD_ATTR               15 (exception + NULL|self)
                LOAD_CONST               5 ('Failed to exchange Google OAuth code')
                CALL                     1
                POP_TOP

  61            LOAD_GLOBAL              5 (HTMLResponse + NULL)

  62            LOAD_CONST               6 ('<h1>Failed to connect Google Calendar.</h1><p>Please try again.</p>')

  63            LOAD_CONST               7 (500)

  61            LOAD_CONST               4 (('content', 'status_code'))
                CALL_KW                  2
                SWAP                     2
       L31:     POP_EXCEPT
                RETURN_VALUE

  59   L32:     RERAISE                  0

  --   L33:     COPY                     3
                POP_EXCEPT
                RERAISE                  1

  68   L34:     CLEANUP_THROW
       L35:     JUMP_BACKWARD_NO_INTERRUPT 151 (to L14)

  --   L36:     PUSH_EXC_INFO

  69            LOAD_GLOBAL             10 (Exception)
                CHECK_EXC_MATCH
                POP_JUMP_IF_FALSE       24 (to L38)
                POP_TOP

  70            LOAD_GLOBAL             12 (logger)
                LOAD_ATTR               19 (warning + NULL|self)
                LOAD_CONST              10 ('Failed to fetch Google email during calendar OAuth')
                CALL                     1
                POP_TOP
       L37:     POP_EXCEPT
                JUMP_BACKWARD_NO_INTERRUPT 182 (to L15)

  69   L38:     RERAISE                  0

  --   L39:     COPY                     3
                POP_EXCEPT
                RERAISE                  1

  72   L40:     CLEANUP_THROW
       L41:     JUMP_BACKWARD_NO_INTERRUPT 159 (to L19)

  74   L42:     CLEANUP_THROW
       L43:     JUMP_BACKWARD_NO_INTERRUPT 127 (to L23)

  82   L44:     CLEANUP_THROW
       L45:     JUMP_BACKWARD_NO_INTERRUPT 105 (to L27)

  --   L46:     CALL_INTRINSIC_1         3 (INTRINSIC_STOPITERATION_ERROR)
                RERAISE                  1
ExceptionTable:
  L1 to L2 -> L46 [0] lasti
  L3 to L5 -> L30 [0]
  L5 to L6 -> L28 [2]
  L6 to L8 -> L30 [0]
  L8 to L9 -> L46 [0] lasti
  L10 to L12 -> L36 [0]
  L12 to L13 -> L34 [2]
  L13 to L15 -> L36 [0]
  L15 to L17 -> L46 [0] lasti
  L17 to L18 -> L40 [2]
  L18 to L21 -> L46 [0] lasti
  L21 to L22 -> L42 [2]
  L22 to L25 -> L46 [0] lasti
  L25 to L26 -> L44 [2]
  L26 to L28 -> L46 [0] lasti
  L28 to L29 -> L30 [0]
  L30 to L31 -> L33 [1] lasti
  L31 to L32 -> L46 [0] lasti
  L32 to L33 -> L33 [1] lasti
  L33 to L34 -> L46 [0] lasti
  L34 to L35 -> L36 [0]
  L36 to L37 -> L39 [1] lasti
  L37 to L38 -> L46 [0] lasti
  L38 to L39 -> L39 [1] lasti
  L39 to L41 -> L46 [0] lasti
  L42 to L43 -> L46 [0] lasti
  L44 to L45 -> L46 [0] lasti

Disassembly of <code object get_status at 0x0000024C114988F0, file "D:\fluence\Github\mattbot\backend\app\api\v1\calendar.py", line 95>:
  95           RETURN_GENERATOR
               POP_TOP
       L1:     RESUME                   0

 101           LOAD_GLOBAL              0 (calendar_service)
               LOAD_ATTR                2 (get_calendar_status)
               PUSH_NULL
               LOAD_FAST_LOAD_FAST     16 (db, current_user)
               LOAD_ATTR                4 (user_id)
               CALL                     2
               GET_AWAITABLE            0
               LOAD_CONST               1 (None)
       L2:     SEND                     3 (to L5)
       L3:     YIELD_VALUE              1
       L4:     RESUME                   3
               JUMP_BACKWARD_NO_INTERRUPT 5 (to L2)
       L5:     END_SEND
               STORE_FAST               2 (status)

 102           LOAD_GLOBAL              7 (CalendarStatusResponse + NULL)
               LOAD_CONST               2 (())
               BUILD_MAP                0
               LOAD_FAST                2 (status)
               DICT_MERGE               1
               CALL_FUNCTION_EX         1
               RETURN_VALUE

 101   L6:     CLEANUP_THROW
       L7:     JUMP_BACKWARD_NO_INTERRUPT 15 (to L5)

  --   L8:     CALL_INTRINSIC_1         3 (INTRINSIC_STOPITERATION_ERROR)
               RERAISE                  1
ExceptionTable:
  L1 to L3 -> L8 [0] lasti
  L3 to L4 -> L6 [2]
  L4 to L7 -> L8 [0] lasti

Disassembly of <code object disconnect at 0x0000024C0FB64550, file "D:\fluence\Github\mattbot\backend\app\api\v1\calendar.py", line 105>:
 105            RETURN_GENERATOR
                POP_TOP
        L1:     RESUME                   0

 111            LOAD_GLOBAL              0 (calendar_service)
                LOAD_ATTR                2 (disconnect_calendar)
                PUSH_NULL
                LOAD_FAST_LOAD_FAST     16 (db, current_user)
                LOAD_ATTR                4 (user_id)
                CALL                     2
                GET_AWAITABLE            0
                LOAD_CONST               1 (None)
        L2:     SEND                     3 (to L5)
        L3:     YIELD_VALUE              1
        L4:     RESUME                   3
                JUMP_BACKWARD_NO_INTERRUPT 5 (to L2)
        L5:     END_SEND
                STORE_FAST               2 (removed)

 113            LOAD_FAST                2 (removed)
                TO_BOOL
                POP_JUMP_IF_FALSE      240 (to L28)

 114            LOAD_CONST               2 (0)
                LOAD_CONST               3 (('UserSettings',))
                IMPORT_NAME              3 (app.models.user_settings)
                IMPORT_FROM              4 (UserSettings)
                STORE_FAST               3 (UserSettings)
                POP_TOP

 116            LOAD_FAST                1 (db)
                LOAD_ATTR               11 (get + NULL|self)
                LOAD_FAST_LOAD_FAST     48 (UserSettings, current_user)
                LOAD_ATTR                4 (user_id)
                CALL                     2
                GET_AWAITABLE            0
                LOAD_CONST               1 (None)
        L6:     SEND                     3 (to L9)
        L7:     YIELD_VALUE              1
        L8:     RESUME                   3
                JUMP_BACKWARD_NO_INTERRUPT 5 (to L6)
        L9:     END_SEND
                STORE_FAST               4 (settings)

 117            LOAD_FAST                4 (settings)
                TO_BOOL
                POP_JUMP_IF_FALSE       12 (to L10)
                LOAD_FAST                4 (settings)
                LOAD_ATTR               12 (calendar_booking_enabled)
                JUMP_FORWARD             1 (to L11)
       L10:     LOAD_CONST               4 (False)
       L11:     STORE_FAST               5 (was_booking_enabled)

 118            LOAD_FAST                4 (settings)
                TO_BOOL
                POP_JUMP_IF_FALSE       45 (to L12)
                LOAD_FAST                4 (settings)
                LOAD_ATTR               12 (calendar_booking_enabled)
                TO_BOOL
                POP_JUMP_IF_FALSE       28 (to L12)

 119            LOAD_CONST               4 (False)
                LOAD_FAST                4 (settings)
                STORE_ATTR               6 (calendar_booking_enabled)

 120            LOAD_FAST                4 (settings)
                COPY                     1
                LOAD_ATTR               14 (revision)
                LOAD_CONST               5 (1)
                BINARY_OP               13 (+=)
                SWAP                     2
                STORE_ATTR               7 (revision)

 122   L12:     LOAD_FAST                5 (was_booking_enabled)
                TO_BOOL
                POP_JUMP_IF_FALSE       78 (to L23)

 123   L13:     NOP

 124   L14:     LOAD_CONST               2 (0)
                LOAD_CONST               6 (('agent_service',))
                IMPORT_NAME              8 (app.services)
                IMPORT_FROM              9 (agent_service)
                STORE_FAST               6 (agent_service)
                POP_TOP

 126            LOAD_FAST                6 (agent_service)
                LOAD_ATTR               21 (get_or_create_default_agent + NULL|self)

 127            LOAD_FAST_LOAD_FAST     16 (db, current_user)
                LOAD_ATTR                4 (user_id)

 126            CALL                     2
                GET_AWAITABLE            0
                LOAD_CONST               1 (None)
       L15:     SEND                     3 (to L18)
       L16:     YIELD_VALUE              1
       L17:     RESUME                   3
                JUMP_BACKWARD_NO_INTERRUPT 5 (to L15)
       L18:     END_SEND
                STORE_FAST               7 (agent)

 129            LOAD_FAST                6 (agent_service)
                LOAD_ATTR               23 (ensure_elevenlabs_agent + NULL|self)

 130            LOAD_FAST_LOAD_FAST     23 (db, agent)
                LOAD_FAST                0 (current_user)
                LOAD_ATTR                4 (user_id)

 129            CALL                     3
                GET_AWAITABLE            0
                LOAD_CONST               1 (None)
       L19:     SEND                     3 (to L22)
       L20:     YIELD_VALUE              1
       L21:     RESUME                   3
                JUMP_BACKWARD_NO_INTERRUPT 5 (to L19)
       L22:     END_SEND
                POP_TOP

 137   L23:     LOAD_GLOBAL             30 (audit_service)
                LOAD_ATTR               32 (log_event)
                PUSH_NULL

 138            LOAD_FAST                1 (db)

 139            LOAD_FAST                0 (current_user)
                LOAD_ATTR                4 (user_id)

 140            LOAD_CONST               8 ('calendar.disconnected')

 141            LOAD_CONST               9 ('user')

 137            LOAD_CONST              10 (('owner_user_id', 'event_type', 'actor_type'))
                CALL_KW                  4
                GET_AWAITABLE            0
                LOAD_CONST               1 (None)
       L24:     SEND                     3 (to L27)
       L25:     YIELD_VALUE              1
       L26:     RESUME                   3
                JUMP_BACKWARD_NO_INTERRUPT 5 (to L24)
       L27:     END_SEND
                POP_TOP

 144   L28:     LOAD_CONST              11 ('disconnected')
                LOAD_FAST                2 (removed)
                BUILD_MAP                1
                RETURN_VALUE

 111   L29:     CLEANUP_THROW
       L30:     JUMP_BACKWARD_NO_INTERRUPT 255 (to L5)

 116   L31:     CLEANUP_THROW
       L32:     JUMP_BACKWARD_NO_INTERRUPT 209 (to L9)

 126   L33:     CLEANUP_THROW
       L34:     JUMP_BACKWARD_NO_INTERRUPT 89 (to L18)

 129   L35:     CLEANUP_THROW
       L36:     JUMP_BACKWARD_NO_INTERRUPT 55 (to L22)

  --   L37:     PUSH_EXC_INFO

 132            LOAD_GLOBAL             24 (Exception)
                CHECK_EXC_MATCH
                POP_JUMP_IF_FALSE       24 (to L39)
                POP_TOP

 133            LOAD_GLOBAL             26 (logger)
                LOAD_ATTR               29 (exception + NULL|self)

 134            LOAD_CONST               7 ('Failed to sync ElevenLabs agent after calendar disconnect')

 133            CALL                     1
                POP_TOP
       L38:     POP_EXCEPT
                JUMP_BACKWARD_NO_INTERRUPT 86 (to L23)

 132   L39:     RERAISE                  0

  --   L40:     COPY                     3
                POP_EXCEPT
                RERAISE                  1

 137   L41:     CLEANUP_THROW
       L42:     JUMP_BACKWARD_NO_INTERRUPT 53 (to L27)

  --   L43:     CALL_INTRINSIC_1         3 (INTRINSIC_STOPITERATION_ERROR)
                RERAISE                  1
ExceptionTable:
  L1 to L3 -> L43 [0] lasti
  L3 to L4 -> L29 [2]
  L4 to L7 -> L43 [0] lasti
  L7 to L8 -> L31 [2]
  L8 to L13 -> L43 [0] lasti
  L14 to L16 -> L37 [0]
  L16 to L17 -> L33 [2]
  L17 to L20 -> L37 [0]
  L20 to L21 -> L35 [2]
  L21 to L23 -> L37 [0]
  L23 to L25 -> L43 [0] lasti
  L25 to L26 -> L41 [2]
  L26 to L30 -> L43 [0] lasti
  L31 to L32 -> L43 [0] lasti
  L33 to L34 -> L37 [0]
  L35 to L36 -> L37 [0]
  L37 to L38 -> L40 [1] lasti
  L38 to L39 -> L43 [0] lasti
  L39 to L40 -> L40 [1] lasti
  L40 to L42 -> L43 [0] lasti

Disassembly of <code object get_events at 0x0000024C0EC4BE10, file "D:\fluence\Github\mattbot\backend\app\api\v1\calendar.py", line 147>:
 147            RETURN_GENERATOR
                POP_TOP
        L1:     RESUME                   0

 155            LOAD_CONST               1 (0)
                LOAD_CONST               2 (('UserSettings',))
                IMPORT_NAME              0 (app.models.user_settings)
                IMPORT_FROM              1 (UserSettings)
                STORE_FAST               4 (UserSettings)
                POP_TOP

 157            LOAD_FAST                3 (db)
                LOAD_ATTR                5 (get + NULL|self)
                LOAD_FAST_LOAD_FAST     66 (UserSettings, current_user)
                LOAD_ATTR                6 (user_id)
                CALL                     2
                GET_AWAITABLE            0
                LOAD_CONST               3 (None)
        L2:     SEND                     3 (to L5)
        L3:     YIELD_VALUE              1
        L4:     RESUME                   3
                JUMP_BACKWARD_NO_INTERRUPT 5 (to L2)
        L5:     END_SEND
                STORE_FAST               5 (settings)

 158            LOAD_FAST                5 (settings)
                TO_BOOL
                POP_JUMP_IF_FALSE       29 (to L6)
                LOAD_FAST                5 (settings)
                LOAD_ATTR                8 (timezone)
                TO_BOOL
                POP_JUMP_IF_FALSE       12 (to L6)
                LOAD_FAST                5 (settings)
                LOAD_ATTR                8 (timezone)
                JUMP_FORWARD             1 (to L7)
        L6:     LOAD_CONST               4 ('UTC')
        L7:     STORE_FAST               6 (user_tz)

 160            LOAD_GLOBAL             10 (calendar_service)
                LOAD_ATTR               12 (list_events)
                PUSH_NULL

 161            LOAD_FAST_LOAD_FAST     50 (db, current_user)
                LOAD_ATTR                6 (user_id)
                LOAD_FAST_LOAD_FAST      1 (start, end)
                LOAD_FAST                6 (user_tz)

 160            LOAD_CONST               5 (('timezone',))
                CALL_KW                  5
                GET_AWAITABLE            0
                LOAD_CONST               3 (None)
        L8:     SEND                     3 (to L11)
        L9:     YIELD_VALUE              1
       L10:     RESUME                   3
                JUMP_BACKWARD_NO_INTERRUPT 5 (to L8)
       L11:     END_SEND
                STORE_FAST               7 (events)

 163            LOAD_GLOBAL             15 (CalendarEventsResponse + NULL)
                LOAD_FAST_LOAD_FAST    118 (events, user_tz)
                LOAD_CONST               6 (('events', 'timezone'))
                CALL_KW                  2
                RETURN_VALUE

 157   L12:     CLEANUP_THROW
       L13:     JUMP_BACKWARD_NO_INTERRUPT 91 (to L5)

 160   L14:     CLEANUP_THROW
       L15:     JUMP_BACKWARD_NO_INTERRUPT 15 (to L11)

  --   L16:     CALL_INTRINSIC_1         3 (INTRINSIC_STOPITERATION_ERROR)
                RERAISE                  1
ExceptionTable:
  L1 to L3 -> L16 [0] lasti
  L3 to L4 -> L12 [2]
  L4 to L9 -> L16 [0] lasti
  L9 to L10 -> L14 [2]
  L10 to L13 -> L16 [0] lasti
  L14 to L15 -> L16 [0] lasti

Disassembly of <code object get_available_slots at 0x0000024C0FB629F0, file "D:\fluence\Github\mattbot\backend\app\api\v1\calendar.py", line 166>:
 166            RETURN_GENERATOR
                POP_TOP
        L1:     RESUME                   0

 173            LOAD_CONST               1 (0)
                LOAD_CONST               2 (('UserSettings',))
                IMPORT_NAME              0 (app.models.user_settings)
                IMPORT_FROM              1 (UserSettings)
                STORE_FAST               3 (UserSettings)
                POP_TOP

 175            LOAD_FAST                2 (db)
                LOAD_ATTR                5 (get + NULL|self)
                LOAD_FAST_LOAD_FAST     49 (UserSettings, current_user)
                LOAD_ATTR                6 (user_id)
                CALL                     2
                GET_AWAITABLE            0
                LOAD_CONST               3 (None)
        L2:     SEND                     3 (to L5)
        L3:     YIELD_VALUE              1
        L4:     RESUME                   3
                JUMP_BACKWARD_NO_INTERRUPT 5 (to L2)
        L5:     END_SEND
                STORE_FAST               4 (settings)

 176            LOAD_FAST                4 (settings)
                TO_BOOL
                POP_JUMP_IF_FALSE       12 (to L6)
                LOAD_FAST                4 (settings)
                LOAD_ATTR                8 (calendar_default_duration_minutes)
                JUMP_FORWARD             1 (to L7)
        L6:     LOAD_CONST               4 (30)
        L7:     STORE_FAST               5 (duration)

 177            LOAD_FAST                4 (settings)
                TO_BOOL
                POP_JUMP_IF_FALSE       12 (to L8)
                LOAD_FAST                4 (settings)
                LOAD_ATTR               10 (timezone)
                JUMP_FORWARD             1 (to L9)
        L8:     LOAD_CONST               5 ('UTC')
        L9:     STORE_FAST               6 (timezone)

 180            LOAD_FAST                4 (settings)
                TO_BOOL
                POP_JUMP_IF_FALSE       29 (to L10)
                LOAD_FAST                4 (settings)
                LOAD_ATTR               12 (business_hours_enabled)
                TO_BOOL
                POP_JUMP_IF_FALSE       12 (to L10)

 179            LOAD_FAST                4 (settings)
                LOAD_ATTR               14 (business_hours_start)
                JUMP_FORWARD             1 (to L11)

 181   L10:     LOAD_CONST               3 (None)

 178   L11:     STORE_FAST               7 (bh_start)

 185            LOAD_FAST                4 (settings)
                TO_BOOL
                POP_JUMP_IF_FALSE       29 (to L12)
                LOAD_FAST                4 (settings)
                LOAD_ATTR               12 (business_hours_enabled)
                TO_BOOL
                POP_JUMP_IF_FALSE       12 (to L12)

 184            LOAD_FAST                4 (settings)
                LOAD_ATTR               16 (business_hours_end)
                JUMP_FORWARD             1 (to L13)

 186   L12:     LOAD_CONST               3 (None)

 183   L13:     STORE_FAST               8 (bh_end)

 189            LOAD_GLOBAL             18 (calendar_service)
                LOAD_ATTR               20 (find_available_slots)
                PUSH_NULL

 190            LOAD_FAST                2 (db)

 191            LOAD_FAST                1 (current_user)
                LOAD_ATTR                6 (user_id)

 192            LOAD_FAST                0 (date)

 193            LOAD_FAST                5 (duration)

 194            LOAD_FAST                7 (bh_start)

 195            LOAD_FAST                8 (bh_end)

 196            LOAD_FAST                6 (timezone)

 189            LOAD_CONST               6 (('duration_minutes', 'business_start', 'business_end', 'timezone'))
                CALL_KW                  7
                GET_AWAITABLE            0
                LOAD_CONST               3 (None)
       L14:     SEND                     3 (to L17)
       L15:     YIELD_VALUE              1
       L16:     RESUME                   3
                JUMP_BACKWARD_NO_INTERRUPT 5 (to L14)
       L17:     END_SEND
                STORE_FAST               9 (slots)

 198            LOAD_GLOBAL             23 (AvailableSlotsResponse + NULL)
                LOAD_FAST_LOAD_FAST      9 (date, slots)
                LOAD_CONST               7 (('date', 'slots'))
                CALL_KW                  2
                RETURN_VALUE

 175   L18:     CLEANUP_THROW
       L19:     JUMP_BACKWARD_NO_INTERRUPT 175 (to L5)

 189   L20:     CLEANUP_THROW
       L21:     JUMP_BACKWARD_NO_INTERRUPT 15 (to L17)

  --   L22:     CALL_INTRINSIC_1         3 (INTRINSIC_STOPITERATION_ERROR)
                RERAISE                  1
ExceptionTable:
  L1 to L3 -> L22 [0] lasti
  L3 to L4 -> L18 [2]
  L4 to L15 -> L22 [0] lasti
  L15 to L16 -> L20 [2]
  L16 to L19 -> L22 [0] lasti
  L20 to L21 -> L22 [0] lasti
