# Bytecode dump of: contacts.cpython-313.pyc
# co_filename: D:\fluence\Github\mattbot\backend\app\api\v1\contacts.py
# co_names: ('__doc__', '__future__', 'annotations', 'uuid', 'datetime', 'UTC', 'fastapi', 'APIRouter', 'Depends', 'Query', 'sqlalchemy', 'func', 'select', 'update', 'sqlalchemy.ext.asyncio', 'AsyncSession', 'app.config', 'settings', 'app.core.dependencies', 'CurrentUser', 'get_current_user', 'app.core.encryption', 'encrypt_field', 'app.core.rate_limiter', 'check_rate_limit', 'app.core.twilio_utils', 'extract_last4', 'hash_phone', 'app.database', 'get_db', 'app.middleware.error_handler', 'AppError', 'app.models.contact_profile', 'ContactProfile', 'app.models.user_settings', 'UserSettings', 'app.schemas.contacts', 'CategoriesListResponse', 'CategoryDefaultsRequest', 'CategoryDefaultsResponse', 'CategoryItem', 'ContactCreateRequest', 'ContactListResponse', 'ContactResponse', 'ContactUpdateRequest', 'CustomCategoryCreateRequest', 'DEFAULT_CATEGORIES', 'app.services.audit_service', 'log_event', 'router', '_DEFAULT_LABELS', '__annotations__', '_get_valid_categories', '_validate_contact_category', '_to_response', 'get', 'list_contacts', 'post', 'create_contact', 'list_categories', 'create_custom_category', 'delete', 'delete_custom_category', 'get_category_defaults', 'put', 'update_category_defaults', 'get_contact', 'patch', 'update_contact', 'delete_contact')
# co_consts (strings): ['Contact profiles API: CRUD + category defaults + custom categories.', 'Business', 'Clients', 'Colleagues', 'Friends', 'Family', 'Healthcare', 'Vendors', 'Acquaintances', 'Other', 'dict[str, str]', '_DEFAULT_LABELS', '', '/categories', '/categories/{slug}', '/categories/defaults', '/{contact_id}']

# DOCSTRING: """Contact profiles API: CRUD + category defaults + custom categories."""
# --- Nested code object: _get_valid_categories ---
    # DOCSTRING: """Return the full set of valid category slugs for a user."""
    # co_names: ('get', 'UserSettings', 'custom_contact_categories', 'DEFAULT_CATEGORIES', 'isinstance', 'dict')
    # co_varnames: ('db', 'user_id', 'row', 'custom', 'entry')
      50            RETURN_GENERATOR
                    POP_TOP
            L1:     RESUME                   0
    
      52            LOAD_FAST                0 (db)
                    LOAD_ATTR                1 (get + NULL|self)
                    LOAD_GLOBAL              2 (UserSettings)
                    LOAD_FAST                1 (user_id)
                    CALL                     2
                    GET_AWAITABLE            0
                    LOAD_CONST               1 (None)
            L2:     SEND                     3 (to L5)
            L3:     YIELD_VALUE              1
            L4:     RESUME                   3
                    JUMP_BACKWARD_NO_INTERRUPT 5 (to L2)
            L5:     END_SEND
                    STORE_FAST               2 (row)
    
      53            LOAD_FAST                2 (row)
                    TO_BOOL
                    POP_JUMP_IF_FALSE       12 (to L6)
                    LOAD_FAST                2 (row)
                    LOAD_ATTR                4 (custom_contact_categories)
                    JUMP_FORWARD             1 (to L7)
            L6:     BUILD_LIST               0
            L7:     STORE_FAST               3 (custom)
    
      54            LOAD_GLOBAL              6 (DEFAULT_CATEGORIES)
                    LOAD_FAST                3 (custom)
                    GET_ITER
                    LOAD_FAST_AND_CLEAR      4 (entry)
                    SWAP                     2
            L8:     BUILD_SET                0
                    SWAP                     2
                    GET_ITER
            L9:     FOR_ITER                39 (to L14)
                    STORE_FAST               4 (entry)
                    LOAD_GLOBAL              9 (isinstance + NULL)
                    LOAD_FAST                4 (entry)
                    LOAD_GLOBAL             10 (dict)
                    CALL                     2
                    TO_BOOL
           L10:     POP_JUMP_IF_TRUE         2 (to L11)
                    JUMP_BACKWARD           26 (to L9)
           L11:     LOAD_CONST               2 ('slug')
                    LOAD_FAST                4 (entry)
                    CONTAINS_OP              0
           L12:     POP_JUMP_IF_TRUE         2 (to L13)
                    JUMP_BACKWARD           34 (to L9)
           L13:     LOAD_FAST                4 (entry)
                    LOAD_CONST               2 ('slug')
                    BINARY_SUBSCR
                    SET_ADD                  2
                    JUMP_BACKWARD           41 (to L9)
           L14:     END_FOR
                    POP_TOP
           L15:     SWAP                     2
                    STORE_FAST               4 (entry)
                    BINARY_OP                7 (|)
                    RETURN_VALUE
    
      52   L16:     CLEANUP_THROW
           L17:     JUMP_BACKWARD_NO_INTERRUPT 85 (to L5)
    
      --   L18:     SWAP                     2
                    POP_TOP
    
      54            SWAP                     2
                    STORE_FAST               4 (entry)
                    RERAISE                  0
    
      --   L19:     CALL_INTRINSIC_1         3 (INTRINSIC_STOPITERATION_ERROR)
                    RERAISE                  1
    ExceptionTable:
      L1 to L3 -> L19 [0] lasti
      L3 to L4 -> L16 [2]
      L4 to L8 -> L19 [0] lasti
      L8 to L10 -> L18 [3]
      L11 to L12 -> L18 [3]
      L13 to L15 -> L18 [3]
      L15 to L17 -> L19 [0] lasti
      L18 to L19 -> L19 [0] lasti
    
# --- Nested code object: _validate_contact_category ---
    # co_names: ('_get_valid_categories', 'AppError')
    # co_varnames: ('db', 'user_id', 'category', 'valid')
      57           RETURN_GENERATOR
                   POP_TOP
           L1:     RESUME                   0
    
      60           LOAD_GLOBAL              1 (_get_valid_categories + NULL)
                   LOAD_FAST_LOAD_FAST      1 (db, user_id)
                   CALL                     2
                   GET_AWAITABLE            0
                   LOAD_CONST               0 (None)
           L2:     SEND                     3 (to L5)
           L3:     YIELD_VALUE              1
           L4:     RESUME                   3
                   JUMP_BACKWARD_NO_INTERRUPT 5 (to L2)
           L5:     END_SEND
                   STORE_FAST               3 (valid)
    
      61           LOAD_FAST_LOAD_FAST     35 (category, valid)
                   CONTAINS_OP              1
                   POP_JUMP_IF_FALSE       15 (to L6)
    
      62           LOAD_GLOBAL              3 (AppError + NULL)
    
      63           LOAD_CONST               1 ('UNKNOWN_CATEGORY')
    
      64           LOAD_CONST               2 ("Unknown category '")
                   LOAD_FAST                2 (category)
                   FORMAT_SIMPLE
                   LOAD_CONST               3 ("'. Create it first or use one of the defaults.")
                   BUILD_STRING             3
    
      65           LOAD_CONST               4 (409)
    
      62           LOAD_CONST               5 (('code', 'message', 'status_code'))
                   CALL_KW                  3
                   RAISE_VARARGS            1
    
      61   L6:     RETURN_CONST             0 (None)
    
      60   L7:     CLEANUP_THROW
           L8:     JUMP_BACKWARD_NO_INTERRUPT 25 (to L5)
    
      --   L9:     CALL_INTRINSIC_1         3 (INTRINSIC_STOPITERATION_ERROR)
                   RERAISE                  1
    ExceptionTable:
      L1 to L3 -> L9 [0] lasti
      L3 to L4 -> L7 [2]
      L4 to L8 -> L9 [0] lasti
    
# --- Nested code object: _to_response ---
    # co_names: ('ContactResponse', 'str', 'id', 'phone_last4', 'display_name', 'company', 'relationship', 'email', 'notes', 'category', 'is_vip', 'is_blocked', 'block_reason', 'ai_temperament_preset', 'ai_greeting_template', 'ai_swearing_rule', 'ai_max_call_length_seconds', 'ai_greeting_instructions_ciphertext', 'ai_custom_instructions_ciphertext', 'created_at', 'updated_at')
    # co_varnames: ('c',)
     69           RESUME                   0
    
     70           LOAD_GLOBAL              1 (ContactResponse + NULL)
                  LOAD_CONST              20 (())
                  BUILD_MAP                0
                  LOAD_CONST               1 ('id')
    
     71           LOAD_GLOBAL              3 (str + NULL)
                  LOAD_FAST                0 (c)
                  LOAD_ATTR                4 (id)
                  CALL                     1
                  MAP_ADD                  1
    
     70           LOAD_CONST               2 ('phone_last4')
    
     72           LOAD_FAST                0 (c)
                  LOAD_ATTR                6 (phone_last4)
                  MAP_ADD                  1
    
     70           LOAD_CONST               3 ('display_name')
    
     73           LOAD_FAST                0 (c)
                  LOAD_ATTR                8 (display_name)
                  MAP_ADD                  1
    
     70           LOAD_CONST               4 ('company')
    
     74           LOAD_FAST                0 (c)
                  LOAD_ATTR               10 (company)
                  MAP_ADD                  1
    
     70           LOAD_CONST               5 ('relationship')
    
     75           LOAD_FAST                0 (c)
                  LOAD_ATTR               12 (relationship)
                  MAP_ADD                  1
    
     70           LOAD_CONST               6 ('email')
    
     76           LOAD_FAST                0 (c)
                  LOAD_ATTR               14 (email)
                  MAP_ADD                  1
    
     70           LOAD_CONST               7 ('notes')
    
     77           LOAD_FAST                0 (c)
                  LOAD_ATTR               16 (notes)
                  MAP_ADD                  1
    
     70           LOAD_CONST               8 ('category')
    
     78           LOAD_FAST                0 (c)
                  LOAD_ATTR               18 (category)
                  MAP_ADD                  1
    
     70           LOAD_CONST               9 ('is_vip')
    
     79           LOAD_FAST                0 (c)
                  LOAD_ATTR               20 (is_vip)
                  MAP_ADD                  1
    
     70           LOAD_CONST              10 ('is_blocked')
    
     80           LOAD_FAST                0 (c)
                  LOAD_ATTR               22 (is_blocked)
                  MAP_ADD                  1
    
     70           LOAD_CONST              11 ('block_reason')
    
     81           LOAD_FAST                0 (c)
                  LOAD_ATTR               24 (block_reason)
                  MAP_ADD                  1
    
     70           LOAD_CONST              12 ('ai_temperament_preset')
    
     82           LOAD_FAST                0 (c)
                  LOAD_ATTR               26 (ai_temperament_preset)
                  MAP_ADD                  1
    
     70           LOAD_CONST              13 ('ai_greeting_template')
    
     83           LOAD_FAST                0 (c)
                  LOAD_ATTR               28 (ai_greeting_template)
                  MAP_ADD                  1
    
     70           LOAD_CONST              14 ('ai_swearing_rule')
    
     84           LOAD_FAST                0 (c)
                  LOAD_ATTR               30 (ai_swearing_rule)
                  MAP_ADD                  1
    
     70           LOAD_CONST              15 ('ai_max_call_length_seconds')
    
     85           LOAD_FAST                0 (c)
                  LOAD_ATTR               32 (ai_max_call_length_seconds)
                  MAP_ADD                  1
    
     70           LOAD_CONST              16 ('has_custom_greeting')
    
     86           LOAD_FAST                0 (c)
                  LOAD_ATTR               34 (ai_greeting_instructions_ciphertext)
                  LOAD_CONST               0 (None)
                  IS_OP                    1
                  MAP_ADD                  1
    
     70           LOAD_CONST              17 ('has_custom_instructions')
    
     87           LOAD_FAST                0 (c)
                  LOAD_ATTR               36 (ai_custom_instructions_ciphertext)
                  LOAD_CONST               0 (None)
                  IS_OP                    1
                  MAP_ADD                  1
    
     70           LOAD_CONST              18 ('created_at')
    
     88           LOAD_FAST                0 (c)
                  LOAD_ATTR               38 (created_at)
                  MAP_ADD                  1
    
     70           LOAD_CONST              19 ('updated_at')
    
     89           LOAD_FAST                0 (c)
                  LOAD_ATTR               40 (updated_at)
                  MAP_ADD                  1
    
     70           CALL_FUNCTION_EX         1
                  RETURN_VALUE
    
# --- Nested code object: list_contacts ---
    # co_names: ('check_rate_limit', 'user', 'id', 'settings', 'RATE_LIMIT_API_STANDARD_MAX', 'RATE_LIMIT_API_STANDARD_WINDOW', 'AppError', 'ContactProfile', 'owner_user_id', 'deleted_at', 'is_', 'append', 'category', 'is_vip', 'is_blocked', 'execute', 'select', 'func', 'count', 'select_from', 'where', 'scalar', 'order_by', 'display_name', 'asc', 'nulls_last', 'created_at', 'desc', 'scalars', 'all', '_to_response', 'ContactListResponse')
    # co_varnames: ('category', 'is_vip', 'is_blocked', 'current_user', 'db', 'allowed', '_', 'filters', 'count_result', 'total', 'stmt', 'result', 'c', 'items')
      93            RETURN_GENERATOR
                    POP_TOP
            L1:     RESUME                   0
    
     101            LOAD_GLOBAL              1 (check_rate_limit + NULL)
    
     102            LOAD_CONST               1 ('contacts:list:')
                    LOAD_FAST                3 (current_user)
                    LOAD_ATTR                2 (user)
                    LOAD_ATTR                4 (id)
                    FORMAT_SIMPLE
                    BUILD_STRING             2
    
     103            LOAD_GLOBAL              6 (settings)
                    LOAD_ATTR                8 (RATE_LIMIT_API_STANDARD_MAX)
    
     104            LOAD_GLOBAL              6 (settings)
                    LOAD_ATTR               10 (RATE_LIMIT_API_STANDARD_WINDOW)
    
     101            LOAD_CONST               2 (('max_requests', 'window_seconds'))
                    CALL_KW                  3
                    GET_AWAITABLE            0
                    LOAD_CONST               0 (None)
            L2:     SEND                     3 (to L5)
            L3:     YIELD_VALUE              1
            L4:     RESUME                   3
                    JUMP_BACKWARD_NO_INTERRUPT 5 (to L2)
            L5:     END_SEND
                    UNPACK_SEQUENCE          2
                    STORE_FAST_STORE_FAST   86 (allowed, _)
    
     106            LOAD_FAST                5 (allowed)
                    TO_BOOL
                    POP_JUMP_IF_TRUE        11 (to L6)
    
     107            LOAD_GLOBAL             13 (AppError + NULL)
                    LOAD_CONST               3 ('RATE_LIMITED')
                    LOAD_CONST               4 ('Too many requests')
                    LOAD_CONST               5 (429)
                    LOAD_CONST               6 (('code', 'message', 'status_code'))
                    CALL_KW                  3
                    RAISE_VARARGS            1
    
     110    L6:     LOAD_GLOBAL             14 (ContactProfile)
                    LOAD_ATTR               16 (owner_user_id)
                    LOAD_FAST                3 (current_user)
                    LOAD_ATTR                2 (user)
                    LOAD_ATTR                4 (id)
                    COMPARE_OP              72 (==)
    
     111            LOAD_GLOBAL             14 (ContactProfile)
                    LOAD_ATTR               18 (deleted_at)
                    LOAD_ATTR               21 (is_ + NULL|self)
                    LOAD_CONST               0 (None)
                    CALL                     1
    
     109            BUILD_LIST               2
                    STORE_FAST               7 (filters)
    
     113            LOAD_FAST                0 (category)
                    POP_JUMP_IF_NONE        34 (to L7)
    
     114            LOAD_FAST                7 (filters)
                    LOAD_ATTR               23 (append + NULL|self)
                    LOAD_GLOBAL             14 (ContactProfile)
                    LOAD_ATTR               24 (category)
                    LOAD_FAST                0 (category)
                    COMPARE_OP              72 (==)
                    CALL                     1
                    POP_TOP
    
     115    L7:     LOAD_FAST                1 (is_vip)
                    POP_JUMP_IF_NONE        34 (to L8)
    
     116            LOAD_FAST                7 (filters)
                    LOAD_ATTR               23 (append + NULL|self)
                    LOAD_GLOBAL             14 (ContactProfile)
                    LOAD_ATTR               26 (is_vip)
                    LOAD_FAST                1 (is_vip)
                    COMPARE_OP              72 (==)
                    CALL                     1
                    POP_TOP
    
     117    L8:     LOAD_FAST                2 (is_blocked)
                    POP_JUMP_IF_NONE        34 (to L9)
    
     118            LOAD_FAST                7 (filters)
                    LOAD_ATTR               23 (append + NULL|self)
                    LOAD_GLOBAL             14 (ContactProfile)
                    LOAD_ATTR               28 (is_blocked)
                    LOAD_FAST                2 (is_blocked)
                    COMPARE_OP              72 (==)
                    CALL                     1
                    POP_TOP
    
     120    L9:     LOAD_FAST                4 (db)
                    LOAD_ATTR               31 (execute + NULL|self)
    
     121            LOAD_GLOBAL             33 (select + NULL)
                    LOAD_GLOBAL             34 (func)
                    LOAD_ATTR               36 (count)
                    PUSH_NULL
                    CALL                     0
                    CALL                     1
                    LOAD_ATTR               39 (select_from + NULL|self)
                    LOAD_GLOBAL             14 (ContactProfile)
                    CALL                     1
                    LOAD_ATTR               40 (where)
                    PUSH_NULL
                    LOAD_FAST                7 (filters)
                    CALL_FUNCTION_EX         0
    
     120            CALL                     1
                    GET_AWAITABLE            0
                    LOAD_CONST               0 (None)
           L10:     SEND                     3 (to L13)
           L11:     YIELD_VALUE              1
           L12:     RESUME                   3
                    JUMP_BACKWARD_NO_INTERRUPT 5 (to L10)
           L13:     END_SEND
                    STORE_FAST               8 (count_result)
    
     123            LOAD_FAST                8 (count_result)
                    LOAD_ATTR               43 (scalar + NULL|self)
                    CALL                     0
                    COPY                     1
                    TO_BOOL
                    POP_JUMP_IF_TRUE         2 (to L14)
                    POP_TOP
                    LOAD_CONST               7 (0)
           L14:     STORE_FAST               9 (total)
    
     126            LOAD_GLOBAL             33 (select + NULL)
                    LOAD_GLOBAL             14 (ContactProfile)
                    CALL                     1
                    LOAD_ATTR               40 (where)
                    PUSH_NULL
                    LOAD_FAST                7 (filters)
                    CALL_FUNCTION_EX         0
    
     127            LOAD_ATTR               45 (order_by + NULL|self)
                    LOAD_GLOBAL             14 (ContactProfile)
                    LOAD_ATTR               46 (display_name)
                    LOAD_ATTR               49 (asc + NULL|self)
                    CALL                     0
                    LOAD_ATTR               51 (nulls_last + NULL|self)
                    CALL                     0
                    LOAD_GLOBAL             14 (ContactProfile)
                    LOAD_ATTR               52 (created_at)
                    LOAD_ATTR               55 (desc + NULL|self)
                    CALL                     0
                    CALL                     2
    
     125            STORE_FAST              10 (stmt)
    
     129            LOAD_FAST                4 (db)
                    LOAD_ATTR               31 (execute + NULL|self)
                    LOAD_FAST               10 (stmt)
                    CALL                     1
                    GET_AWAITABLE            0
                    LOAD_CONST               0 (None)
           L15:     SEND                     3 (to L18)
           L16:     YIELD_VALUE              1
           L17:     RESUME                   3
                    JUMP_BACKWARD_NO_INTERRUPT 5 (to L15)
           L18:     END_SEND
                    STORE_FAST              11 (result)
    
     130            LOAD_FAST               11 (result)
                    LOAD_ATTR               57 (scalars + NULL|self)
                    CALL                     0
                    LOAD_ATTR               59 (all + NULL|self)
                    CALL                     0
                    GET_ITER
                    LOAD_FAST_AND_CLEAR     12 (c)
                    SWAP                     2
           L19:     BUILD_LIST               0
                    SWAP                     2
                    GET_ITER
           L20:     FOR_ITER                14 (to L21)
                    STORE_FAST              12 (c)
                    LOAD_GLOBAL             61 (_to_response + NULL)
                    LOAD_FAST               12 (c)
                    CALL                     1
                    LIST_APPEND              2
                    JUMP_BACKWARD           16 (to L20)
           L21:     END_FOR
                    POP_TOP
           L22:     STORE_FAST              13 (items)
                    STORE_FAST              12 (c)
    
     132            LOAD_GLOBAL             63 (ContactListResponse + NULL)
                    LOAD_FAST_LOAD_FAST    217 (items, total)
                    LOAD_CONST               8 (('items', 'total'))
                    CALL_KW                  2
                    RETURN_VALUE
    
     101   L23:     CLEANUP_THROW
           L24:     EXTENDED_ARG             2
                    JUMP_BACKWARD_NO_INTERRUPT 519 (to L5)
    
     120   L25:     CLEANUP_THROW
           L26:     JUMP_BACKWARD_NO_INTERRUPT 235 (to L13)
    
     129   L27:     CLEANUP_THROW
           L28:     JUMP_BACKWARD_NO_INTERRUPT 73 (to L18)
    
      --   L29:     SWAP                     2
                    POP_TOP
    
     130            SWAP                     2
                    STORE_FAST              12 (c)
                    RERAISE                  0
    
      --   L30:     CALL_INTRINSIC_1         3 (INTRINSIC_STOPITERATION_ERROR)
                    RERAISE                  1
    ExceptionTable:
      L1 to L3 -> L30 [0] lasti
      L3 to L4 -> L23 [2]
      L4 to L11 -> L30 [0] lasti
      L11 to L12 -> L25 [2]
      L12 to L16 -> L30 [0] lasti
      L16 to L17 -> L27 [2]
      L17 to L19 -> L30 [0] lasti
      L19 to L22 -> L29 [2]
      L22 to L24 -> L30 [0] lasti
      L25 to L26 -> L30 [0] lasti
      L27 to L28 -> L30 [0] lasti
      L29 to L30 -> L30 [0] lasti
    
# --- Nested code object: create_contact ---
    # co_names: ('check_rate_limit', 'user', 'id', 'settings', 'RATE_LIMIT_API_WRITE_MAX', 'RATE_LIMIT_API_WRITE_WINDOW', 'AppError', '_validate_contact_category', 'category', 'hash_phone', 'phone_number', 'execute', 'select', 'ContactProfile', 'where', 'owner_user_id', 'phone_hash', 'deleted_at', 'is_', 'scalar_one_or_none', 'encrypt_field', 'encode', 'extract_last4', 'display_name', 'company', 'relationship', 'email', 'notes', 'is_vip', 'is_blocked', 'block_reason', 'ai_temperament_preset', 'ai_greeting_template', 'ai_swearing_rule', 'ai_max_call_length_seconds', 'ai_greeting_instructions', 'ai_greeting_instructions_ciphertext', 'ai_greeting_instructions_nonce', 'ai_greeting_instructions_key_version', 'ai_custom_instructions', 'ai_custom_instructions_ciphertext', 'ai_custom_instructions_nonce', 'ai_custom_instructions_key_version', 'add', 'log_event', 'flush', '_to_response')
    # co_varnames: ('body', 'current_user', 'db', 'allowed', '_', 'ph', 'existing', 'ct', 'nonce', 'kv', 'contact', 'g_ct', 'g_n', 'g_kv', 'i_ct', 'i_n', 'i_kv')
     135            RETURN_GENERATOR
                    POP_TOP
            L1:     RESUME                   0
    
     141            LOAD_GLOBAL              1 (check_rate_limit + NULL)
    
     142            LOAD_CONST               1 ('contacts:create:')
                    LOAD_FAST                1 (current_user)
                    LOAD_ATTR                2 (user)
                    LOAD_ATTR                4 (id)
                    FORMAT_SIMPLE
                    BUILD_STRING             2
    
     143            LOAD_GLOBAL              6 (settings)
                    LOAD_ATTR                8 (RATE_LIMIT_API_WRITE_MAX)
    
     144            LOAD_GLOBAL              6 (settings)
                    LOAD_ATTR               10 (RATE_LIMIT_API_WRITE_WINDOW)
    
     141            LOAD_CONST               2 (('max_requests', 'window_seconds'))
                    CALL_KW                  3
                    GET_AWAITABLE            0
                    LOAD_CONST               0 (None)
            L2:     SEND                     3 (to L5)
            L3:     YIELD_VALUE              1
            L4:     RESUME                   3
                    JUMP_BACKWARD_NO_INTERRUPT 5 (to L2)
            L5:     END_SEND
                    UNPACK_SEQUENCE          2
                    STORE_FAST_STORE_FAST   52 (allowed, _)
    
     146            LOAD_FAST                3 (allowed)
                    TO_BOOL
                    POP_JUMP_IF_TRUE        11 (to L6)
    
     147            LOAD_GLOBAL             13 (AppError + NULL)
                    LOAD_CONST               3 ('RATE_LIMITED')
                    LOAD_CONST               4 ('Too many requests')
                    LOAD_CONST               5 (429)
                    LOAD_CONST               6 (('code', 'message', 'status_code'))
                    CALL_KW                  3
                    RAISE_VARARGS            1
    
     149    L6:     LOAD_GLOBAL             15 (_validate_contact_category + NULL)
                    LOAD_FAST_LOAD_FAST     33 (db, current_user)
                    LOAD_ATTR                2 (user)
                    LOAD_ATTR                4 (id)
                    LOAD_FAST                0 (body)
                    LOAD_ATTR               16 (category)
                    CALL                     3
                    GET_AWAITABLE            0
                    LOAD_CONST               0 (None)
            L7:     SEND                     3 (to L10)
            L8:     YIELD_VALUE              1
            L9:     RESUME                   3
                    JUMP_BACKWARD_NO_INTERRUPT 5 (to L7)
           L10:     END_SEND
                    POP_TOP
    
     151            LOAD_GLOBAL             19 (hash_phone + NULL)
                    LOAD_FAST                0 (body)
                    LOAD_ATTR               20 (phone_number)
                    CALL                     1
                    STORE_FAST               5 (ph)
    
     152            LOAD_FAST                2 (db)
                    LOAD_ATTR               23 (execute + NULL|self)
    
     153            LOAD_GLOBAL             25 (select + NULL)
                    LOAD_GLOBAL             26 (ContactProfile)
                    CALL                     1
                    LOAD_ATTR               29 (where + NULL|self)
    
     154            LOAD_GLOBAL             26 (ContactProfile)
                    LOAD_ATTR               30 (owner_user_id)
                    LOAD_FAST                1 (current_user)
                    LOAD_ATTR                2 (user)
                    LOAD_ATTR                4 (id)
                    COMPARE_OP              72 (==)
    
     155            LOAD_GLOBAL             26 (ContactProfile)
                    LOAD_ATTR               32 (phone_hash)
                    LOAD_FAST                5 (ph)
                    COMPARE_OP              72 (==)
    
     156            LOAD_GLOBAL             26 (ContactProfile)
                    LOAD_ATTR               34 (deleted_at)
                    LOAD_ATTR               37 (is_ + NULL|self)
                    LOAD_CONST               0 (None)
                    CALL                     1
    
     153            CALL                     3
    
     152            CALL                     1
                    GET_AWAITABLE            0
                    LOAD_CONST               0 (None)
           L11:     SEND                     3 (to L14)
           L12:     YIELD_VALUE              1
           L13:     RESUME                   3
                    JUMP_BACKWARD_NO_INTERRUPT 5 (to L11)
           L14:     END_SEND
    
     158            LOAD_ATTR               39 (scalar_one_or_none + NULL|self)
                    CALL                     0
    
     152            STORE_FAST               6 (existing)
    
     160            LOAD_FAST                6 (existing)
                    POP_JUMP_IF_NONE        11 (to L15)
    
     161            LOAD_GLOBAL             13 (AppError + NULL)
    
     162            LOAD_CONST               7 ('CONTACT_DUPLICATE')
    
     163            LOAD_CONST               8 ('This number already has a contact profile')
    
     164            LOAD_CONST               9 (409)
    
     161            LOAD_CONST               6 (('code', 'message', 'status_code'))
                    CALL_KW                  3
                    RAISE_VARARGS            1
    
     167   L15:     LOAD_GLOBAL             41 (encrypt_field + NULL)
                    LOAD_FAST                0 (body)
                    LOAD_ATTR               20 (phone_number)
                    LOAD_ATTR               43 (encode + NULL|self)
                    LOAD_CONST              10 ('utf-8')
                    CALL                     1
                    CALL                     1
                    UNPACK_SEQUENCE          3
                    STORE_FAST_STORE_FAST  120 (ct, nonce)
                    STORE_FAST               9 (kv)
    
     169            LOAD_GLOBAL             27 (ContactProfile + NULL)
                    LOAD_CONST              33 (())
                    BUILD_MAP                0
                    LOAD_CONST              11 ('owner_user_id')
    
     170            LOAD_FAST                1 (current_user)
                    LOAD_ATTR                2 (user)
                    LOAD_ATTR                4 (id)
                    MAP_ADD                  1
    
     169            LOAD_CONST              12 ('phone_ciphertext')
    
     171            LOAD_FAST                7 (ct)
                    MAP_ADD                  1
    
     169            LOAD_CONST              13 ('phone_nonce')
    
     172            LOAD_FAST                8 (nonce)
                    MAP_ADD                  1
    
     169            LOAD_CONST              14 ('phone_key_version')
    
     173            LOAD_FAST                9 (kv)
                    MAP_ADD                  1
    
     169            LOAD_CONST              15 ('phone_hash')
    
     174            LOAD_FAST                5 (ph)
                    MAP_ADD                  1
    
     169            LOAD_CONST              16 ('phone_last4')
    
     175            LOAD_GLOBAL             45 (extract_last4 + NULL)
                    LOAD_FAST                0 (body)
                    LOAD_ATTR               20 (phone_number)
                    CALL                     1
                    MAP_ADD                  1
    
     169            LOAD_CONST              17 ('display_name')
    
     176            LOAD_FAST                0 (body)
                    LOAD_ATTR               46 (display_name)
                    MAP_ADD                  1
    
     169            LOAD_CONST              18 ('company')
    
     177            LOAD_FAST                0 (body)
                    LOAD_ATTR               48 (company)
                    MAP_ADD                  1
    
     169            LOAD_CONST              19 ('relationship')
    
     178            LOAD_FAST                0 (body)
                    LOAD_ATTR               50 (relationship)
                    MAP_ADD                  1
    
     169            LOAD_CONST              20 ('email')
    
     179            LOAD_FAST                0 (body)
                    LOAD_ATTR               52 (email)
                    MAP_ADD                  1
    
     169            LOAD_CONST              21 ('notes')
    
     180            LOAD_FAST                0 (body)
                    LOAD_ATTR               54 (notes)
                    MAP_ADD                  1
    
     169            LOAD_CONST              22 ('category')
    
     181            LOAD_FAST                0 (body)
                    LOAD_ATTR               16 (category)
                    MAP_ADD                  1
    
     169            LOAD_CONST              23 ('is_vip')
    
     182            LOAD_FAST                0 (body)
                    LOAD_ATTR               56 (is_vip)
                    MAP_ADD                  1
    
     169            LOAD_CONST              24 ('is_blocked')
    
     183            LOAD_FAST                0 (body)
                    LOAD_ATTR               58 (is_blocked)
                    MAP_ADD                  1
    
     169            LOAD_CONST              25 ('block_reason')
    
     184            LOAD_FAST                0 (body)
                    LOAD_ATTR               60 (block_reason)
                    MAP_ADD                  1
    
     169            LOAD_CONST              26 ('ai_temperament_preset')
    
     185            LOAD_FAST                0 (body)
                    LOAD_ATTR               62 (ai_temperament_preset)
                    MAP_ADD                  1
    
     169            LOAD_CONST              27 ('ai_greeting_template')
    
     186            LOAD_FAST                0 (body)
                    LOAD_ATTR               64 (ai_greeting_template)
                    MAP_ADD                  1
    
     169            LOAD_CONST              28 ('ai_swearing_rule')
    
     187            LOAD_FAST                0 (body)
                    LOAD_ATTR               66 (ai_swearing_rule)
                    MAP_ADD                  1
    
     169            LOAD_CONST              29 ('ai_max_call_length_seconds')
    
     188            LOAD_FAST                0 (body)
                    LOAD_ATTR               68 (ai_max_call_length_seconds)
                    MAP_ADD                  1
    
     169            CALL_FUNCTION_EX         1
                    STORE_FAST              10 (contact)
    
     191            LOAD_FAST                0 (body)
                    LOAD_ATTR               70 (ai_greeting_instructions)
                    TO_BOOL
                    POP_JUMP_IF_FALSE       57 (to L16)
    
     192            LOAD_GLOBAL             41 (encrypt_field + NULL)
                    LOAD_FAST                0 (body)
                    LOAD_ATTR               70 (ai_greeting_instructions)
                    LOAD_ATTR               43 (encode + NULL|self)
                    LOAD_CONST              10 ('utf-8')
                    CALL                     1
                    CALL                     1
                    UNPACK_SEQUENCE          3
                    STORE_FAST_STORE_FAST  188 (g_ct, g_n)
                    STORE_FAST              13 (g_kv)
    
     193            LOAD_FAST_LOAD_FAST    186 (g_ct, contact)
                    STORE_ATTR              36 (ai_greeting_instructions_ciphertext)
    
     194            LOAD_FAST_LOAD_FAST    202 (g_n, contact)
                    STORE_ATTR              37 (ai_greeting_instructions_nonce)
    
     195            LOAD_FAST_LOAD_FAST    218 (g_kv, contact)
                    STORE_ATTR              38 (ai_greeting_instructions_key_version)
    
     197   L16:     LOAD_FAST                0 (body)
                    LOAD_ATTR               78 (ai_custom_instructions)
                    TO_BOOL
                    POP_JUMP_IF_FALSE       58 (to L17)
    
     198            LOAD_GLOBAL             41 (encrypt_field + NULL)
                    LOAD_FAST                0 (body)
                    LOAD_ATTR               78 (ai_custom_instructions)
                    LOAD_ATTR               43 (encode + NULL|self)
                    LOAD_CONST              10 ('utf-8')
                    CALL                     1
                    CALL                     1
                    UNPACK_SEQUENCE          3
                    STORE_FAST_STORE_FAST  239 (i_ct, i_n)
                    STORE_FAST              16 (i_kv)
    
     199            LOAD_FAST_LOAD_FAST    234 (i_ct, contact)
                    STORE_ATTR              40 (ai_custom_instructions_ciphertext)
    
     200            LOAD_FAST_LOAD_FAST    250 (i_n, contact)
                    STORE_ATTR              41 (ai_custom_instructions_nonce)
    
     201            LOAD_FAST               16 (i_kv)
                    LOAD_FAST               10 (contact)
                    STORE_ATTR              42 (ai_custom_instructions_key_version)
    
     203   L17:     LOAD_FAST                2 (db)
                    LOAD_ATTR               87 (add + NULL|self)
                    LOAD_FAST               10 (contact)
                    CALL                     1
                    POP_TOP
    
     204            LOAD_GLOBAL             89 (log_event + NULL)
    
     205            LOAD_FAST                2 (db)
    
     206            LOAD_FAST                1 (current_user)
                    LOAD_ATTR                2 (user)
                    LOAD_ATTR                4 (id)
    
     207            LOAD_CONST              30 ('contact_created')
    
     208            LOAD_FAST                1 (current_user)
                    LOAD_ATTR                2 (user)
                    LOAD_ATTR                4 (id)
    
     209            LOAD_CONST              31 ('contact_profile')
    
     210            LOAD_FAST               10 (contact)
                    LOAD_ATTR                4 (id)
    
     204            LOAD_CONST              32 (('owner_user_id', 'event_type', 'actor_id', 'target_type', 'target_id'))
                    CALL_KW                  6
                    GET_AWAITABLE            0
                    LOAD_CONST               0 (None)
           L18:     SEND                     3 (to L21)
           L19:     YIELD_VALUE              1
           L20:     RESUME                   3
                    JUMP_BACKWARD_NO_INTERRUPT 5 (to L18)
           L21:     END_SEND
                    POP_TOP
    
     212            LOAD_FAST                2 (db)
                    LOAD_ATTR               91 (flush + NULL|self)
                    CALL                     0
                    GET_AWAITABLE            0
                    LOAD_CONST               0 (None)
           L22:     SEND                     3 (to L25)
           L23:     YIELD_VALUE              1
           L24:     RESUME                   3
                    JUMP_BACKWARD_NO_INTERRUPT 5 (to L22)
           L25:     END_SEND
                    POP_TOP
    
     214            LOAD_GLOBAL             93 (_to_response + NULL)
                    LOAD_FAST               10 (contact)
                    CALL                     1
                    RETURN_VALUE
    
     141   L26:     CLEANUP_THROW
           L27:     EXTENDED_ARG             3
                    JUMP_BACKWARD_NO_INTERRUPT 809 (to L5)
    
     149   L28:     CLEANUP_THROW
           L29:     EXTENDED_ARG             2
                    JUMP_BACKWARD_NO_INTERRUPT 742 (to L10)
    
     152   L30:     CLEANUP_THROW
           L31:     EXTENDED_ARG             2
                    JUMP_BACKWARD_NO_INTERRUPT 586 (to L14)
    
     204   L32:     CLEANUP_THROW
           L33:     JUMP_BACKWARD_NO_INTERRUPT 48 (to L21)
    
     212   L34:     CLEANUP_THROW
           L35:     JUMP_BACKWARD_NO_INTERRUPT 26 (to L25)
    
      --   L36:     CALL_INTRINSIC_1         3 (INTRINSIC_STOPITERATION_ERROR)
                    RERAISE                  1
    ExceptionTable:
      L1 to L3 -> L36 [0] lasti
      L3 to L4 -> L26 [2]
      L4 to L8 -> L36 [0] lasti
      L8 to L9 -> L28 [2]
      L9 to L12 -> L36 [0] lasti
      L12 to L13 -> L30 [2]
      L13 to L19 -> L36 [0] lasti
      L19 to L20 -> L32 [2]
      L20 to L23 -> L36 [0] lasti
      L23 to L24 -> L34 [2]
      L24 to L27 -> L36 [0] lasti
      L28 to L29 -> L36 [0] lasti
      L30 to L31 -> L36 [0] lasti
      L32 to L33 -> L36 [0] lasti
      L34 to L35 -> L36 [0] lasti
    
# --- Nested code object: list_categories ---
    # co_names: ('get', 'UserSettings', 'user', 'id', 'custom_contact_categories', 'sorted', 'DEFAULT_CATEGORIES', 'append', 'CategoryItem', '_DEFAULT_LABELS', 'replace', 'title', 'isinstance', 'dict', 'CategoriesListResponse')
    # co_varnames: ('current_user', 'db', 'row', 'custom', 'items', 'slug', 'entry')
     221            RETURN_GENERATOR
                    POP_TOP
            L1:     RESUME                   0
    
     226            LOAD_FAST                1 (db)
                    LOAD_ATTR                1 (get + NULL|self)
                    LOAD_GLOBAL              2 (UserSettings)
                    LOAD_FAST                0 (current_user)
                    LOAD_ATTR                4 (user)
                    LOAD_ATTR                6 (id)
                    CALL                     2
                    GET_AWAITABLE            0
                    LOAD_CONST               0 (None)
            L2:     SEND                     3 (to L5)
            L3:     YIELD_VALUE              1
            L4:     RESUME                   3
                    JUMP_BACKWARD_NO_INTERRUPT 5 (to L2)
            L5:     END_SEND
                    STORE_FAST               2 (row)
    
     227            LOAD_FAST                2 (row)
                    TO_BOOL
                    POP_JUMP_IF_FALSE       12 (to L6)
                    LOAD_FAST                2 (row)
                    LOAD_ATTR                8 (custom_contact_categories)
                    JUMP_FORWARD             1 (to L7)
            L6:     BUILD_LIST               0
            L7:     STORE_FAST               3 (custom)
    
     229            BUILD_LIST               0
                    STORE_FAST               4 (items)
    
     230            LOAD_GLOBAL             11 (sorted + NULL)
                    LOAD_GLOBAL             12 (DEFAULT_CATEGORIES)
                    CALL                     1
                    GET_ITER
            L8:     FOR_ITER                78 (to L9)
                    STORE_FAST               5 (slug)
    
     231            LOAD_FAST                4 (items)
                    LOAD_ATTR               15 (append + NULL|self)
                    LOAD_GLOBAL             17 (CategoryItem + NULL)
    
     232            LOAD_FAST                5 (slug)
    
     233            LOAD_GLOBAL             18 (_DEFAULT_LABELS)
                    LOAD_ATTR                1 (get + NULL|self)
                    LOAD_FAST_LOAD_FAST     85 (slug, slug)
                    LOAD_ATTR               21 (replace + NULL|self)
                    LOAD_CONST               1 ('_')
                    LOAD_CONST               2 (' ')
                    CALL                     2
                    LOAD_ATTR               23 (title + NULL|self)
                    CALL                     0
                    CALL                     2
    
     234            LOAD_CONST               3 (True)
    
     231            LOAD_CONST               4 (('slug', 'label', 'is_default'))
                    CALL_KW                  3
                    CALL                     1
                    POP_TOP
                    JUMP_BACKWARD           80 (to L8)
    
     230    L9:     END_FOR
                    POP_TOP
    
     236            LOAD_FAST                3 (custom)
                    GET_ITER
           L10:     FOR_ITER               112 (to L15)
                    STORE_FAST               6 (entry)
    
     237            LOAD_GLOBAL             25 (isinstance + NULL)
                    LOAD_FAST                6 (entry)
                    LOAD_GLOBAL             26 (dict)
                    CALL                     2
                    TO_BOOL
           L11:     POP_JUMP_IF_TRUE         2 (to L12)
                    JUMP_BACKWARD           26 (to L10)
           L12:     LOAD_CONST               5 ('slug')
                    LOAD_FAST                6 (entry)
                    CONTAINS_OP              0
           L13:     POP_JUMP_IF_TRUE         2 (to L14)
                    JUMP_BACKWARD           34 (to L10)
    
     238   L14:     LOAD_FAST                4 (items)
                    LOAD_ATTR               15 (append + NULL|self)
                    LOAD_GLOBAL             17 (CategoryItem + NULL)
    
     239            LOAD_FAST                6 (entry)
                    LOAD_CONST               5 ('slug')
                    BINARY_SUBSCR
    
     240            LOAD_FAST                6 (entry)
                    LOAD_ATTR                1 (get + NULL|self)
                    LOAD_CONST               6 ('label')
                    LOAD_FAST                6 (entry)
                    LOAD_CONST               5 ('slug')
                    BINARY_SUBSCR
                    LOAD_ATTR               21 (replace + NULL|self)
                    LOAD_CONST               1 ('_')
                    LOAD_CONST               2 (' ')
                    CALL                     2
                    LOAD_ATTR               23 (title + NULL|self)
                    CALL                     0
                    CALL                     2
    
     241            LOAD_CONST               7 (False)
    
     238            LOAD_CONST               4 (('slug', 'label', 'is_default'))
                    CALL_KW                  3
                    CALL                     1
                    POP_TOP
                    JUMP_BACKWARD          114 (to L10)
    
     236   L15:     END_FOR
                    POP_TOP
    
     244            LOAD_GLOBAL             29 (CategoriesListResponse + NULL)
                    LOAD_FAST                4 (items)
                    LOAD_CONST               8 (('categories',))
                    CALL_KW                  1
                    RETURN_VALUE
    
     226   L16:     CLEANUP_THROW
           L17:     JUMP_BACKWARD_NO_INTERRUPT 251 (to L5)
    
      --   L18:     CALL_INTRINSIC_1         3 (INTRINSIC_STOPITERATION_ERROR)
                    RERAISE                  1
    ExceptionTable:
      L1 to L3 -> L18 [0] lasti
      L3 to L4 -> L16 [2]
      L4 to L11 -> L18 [0] lasti
      L12 to L13 -> L18 [0] lasti
      L14 to L17 -> L18 [0] lasti
    
# --- Nested code object: create_custom_category ---
    # co_names: ('check_rate_limit', 'user', 'id', 'settings', 'RATE_LIMIT_API_WRITE_MAX', 'RATE_LIMIT_API_WRITE_WINDOW', 'AppError', 'slug', 'DEFAULT_CATEGORIES', 'get', 'UserSettings', 'list', 'custom_contact_categories', 'isinstance', 'dict', 'len', 'append', 'label', 'flush', 'CategoryItem')
    # co_varnames: ('body', 'current_user', 'db', 'allowed', '_', 'row', 'custom', 'e', 'existing_slugs')
     247            RETURN_GENERATOR
                    POP_TOP
            L1:     RESUME                   0
    
     253            LOAD_GLOBAL              1 (check_rate_limit + NULL)
    
     254            LOAD_CONST               1 ('contacts:catcreate:')
                    LOAD_FAST                1 (current_user)
                    LOAD_ATTR                2 (user)
                    LOAD_ATTR                4 (id)
                    FORMAT_SIMPLE
                    BUILD_STRING             2
    
     255            LOAD_GLOBAL              6 (settings)
                    LOAD_ATTR                8 (RATE_LIMIT_API_WRITE_MAX)
    
     256            LOAD_GLOBAL              6 (settings)
                    LOAD_ATTR               10 (RATE_LIMIT_API_WRITE_WINDOW)
    
     253            LOAD_CONST               2 (('max_requests', 'window_seconds'))
                    CALL_KW                  3
                    GET_AWAITABLE            0
                    LOAD_CONST               0 (None)
            L2:     SEND                     3 (to L5)
            L3:     YIELD_VALUE              1
            L4:     RESUME                   3
                    JUMP_BACKWARD_NO_INTERRUPT 5 (to L2)
            L5:     END_SEND
                    UNPACK_SEQUENCE          2
                    STORE_FAST_STORE_FAST   52 (allowed, _)
    
     258            LOAD_FAST                3 (allowed)
                    TO_BOOL
                    POP_JUMP_IF_TRUE        11 (to L6)
    
     259            LOAD_GLOBAL             13 (AppError + NULL)
                    LOAD_CONST               3 ('RATE_LIMITED')
                    LOAD_CONST               4 ('Too many requests')
                    LOAD_CONST               5 (429)
                    LOAD_CONST               6 (('code', 'message', 'status_code'))
                    CALL_KW                  3
                    RAISE_VARARGS            1
    
     261    L6:     LOAD_FAST                0 (body)
                    LOAD_ATTR               14 (slug)
                    LOAD_GLOBAL             16 (DEFAULT_CATEGORIES)
                    CONTAINS_OP              0
                    POP_JUMP_IF_FALSE       25 (to L7)
    
     262            LOAD_GLOBAL             13 (AppError + NULL)
    
     263            LOAD_CONST               7 ('CATEGORY_IS_DEFAULT')
    
     264            LOAD_CONST               8 ("'")
                    LOAD_FAST                0 (body)
                    LOAD_ATTR               14 (slug)
                    FORMAT_SIMPLE
                    LOAD_CONST               9 ("' is a built-in category and cannot be created")
                    BUILD_STRING             3
    
     265            LOAD_CONST              10 (409)
    
     262            LOAD_CONST               6 (('code', 'message', 'status_code'))
                    CALL_KW                  3
                    RAISE_VARARGS            1
    
     268    L7:     LOAD_FAST                2 (db)
                    LOAD_ATTR               19 (get + NULL|self)
                    LOAD_GLOBAL             20 (UserSettings)
                    LOAD_FAST                1 (current_user)
                    LOAD_ATTR                2 (user)
                    LOAD_ATTR                4 (id)
                    CALL                     2
                    GET_AWAITABLE            0
                    LOAD_CONST               0 (None)
            L8:     SEND                     3 (to L11)
            L9:     YIELD_VALUE              1
           L10:     RESUME                   3
                    JUMP_BACKWARD_NO_INTERRUPT 5 (to L8)
           L11:     END_SEND
                    STORE_FAST               5 (row)
    
     269            LOAD_FAST                5 (row)
                    POP_JUMP_IF_NOT_NONE    11 (to L12)
    
     270            LOAD_GLOBAL             13 (AppError + NULL)
                    LOAD_CONST              11 ('SETTINGS_NOT_FOUND')
                    LOAD_CONST              12 ('User settings not found')
                    LOAD_CONST              13 (404)
                    LOAD_CONST               6 (('code', 'message', 'status_code'))
                    CALL_KW                  3
                    RAISE_VARARGS            1
    
     272   L12:     LOAD_GLOBAL             23 (list + NULL)
                    LOAD_FAST                5 (row)
                    LOAD_ATTR               24 (custom_contact_categories)
                    COPY                     1
                    TO_BOOL
                    POP_JUMP_IF_TRUE         2 (to L13)
                    POP_TOP
                    BUILD_LIST               0
           L13:     CALL                     1
                    STORE_FAST               6 (custom)
    
     273            LOAD_FAST                6 (custom)
                    GET_ITER
                    LOAD_FAST_AND_CLEAR      7 (e)
                    SWAP                     2
           L14:     BUILD_SET                0
                    SWAP                     2
                    GET_ITER
           L15:     FOR_ITER                39 (to L20)
                    STORE_FAST               7 (e)
                    LOAD_GLOBAL             27 (isinstance + NULL)
                    LOAD_FAST                7 (e)
                    LOAD_GLOBAL             28 (dict)
                    CALL                     2
                    TO_BOOL
           L16:     POP_JUMP_IF_TRUE         2 (to L17)
                    JUMP_BACKWARD           26 (to L15)
           L17:     LOAD_CONST              14 ('slug')
                    LOAD_FAST                7 (e)
                    CONTAINS_OP              0
           L18:     POP_JUMP_IF_TRUE         2 (to L19)
                    JUMP_BACKWARD           34 (to L15)
           L19:     LOAD_FAST                7 (e)
                    LOAD_CONST              14 ('slug')
                    BINARY_SUBSCR
                    SET_ADD                  2
                    JUMP_BACKWARD           41 (to L15)
           L20:     END_FOR
                    POP_TOP
           L21:     STORE_FAST               8 (existing_slugs)
                    STORE_FAST               7 (e)
    
     274            LOAD_FAST                0 (body)
                    LOAD_ATTR               14 (slug)
                    LOAD_FAST                8 (existing_slugs)
                    CONTAINS_OP              0
                    POP_JUMP_IF_FALSE       25 (to L22)
    
     275            LOAD_GLOBAL             13 (AppError + NULL)
    
     276            LOAD_CONST              15 ('CATEGORY_DUPLICATE')
    
     277            LOAD_CONST              16 ("Custom category '")
                    LOAD_FAST                0 (body)
                    LOAD_ATTR               14 (slug)
                    FORMAT_SIMPLE
                    LOAD_CONST              17 ("' already exists")
                    BUILD_STRING             3
    
     278            LOAD_CONST              10 (409)
    
     275            LOAD_CONST               6 (('code', 'message', 'status_code'))
                    CALL_KW                  3
                    RAISE_VARARGS            1
    
     281   L22:     LOAD_GLOBAL             31 (len + NULL)
                    LOAD_FAST                6 (custom)
                    CALL                     1
                    LOAD_CONST              18 (20)
                    COMPARE_OP             188 (bool(>=))
                    POP_JUMP_IF_FALSE       11 (to L23)
    
     282            LOAD_GLOBAL             13 (AppError + NULL)
    
     283            LOAD_CONST              19 ('CATEGORY_LIMIT')
    
     284            LOAD_CONST              20 ('Maximum of 20 custom categories allowed')
    
     285            LOAD_CONST              21 (400)
    
     282            LOAD_CONST               6 (('code', 'message', 'status_code'))
                    CALL_KW                  3
                    RAISE_VARARGS            1
    
     288   L23:     LOAD_FAST                6 (custom)
                    LOAD_ATTR               33 (append + NULL|self)
                    LOAD_FAST                0 (body)
                    LOAD_ATTR               14 (slug)
                    LOAD_FAST                0 (body)
                    LOAD_ATTR               34 (label)
                    LOAD_CONST              22 (('slug', 'label'))
                    BUILD_CONST_KEY_MAP      2
                    CALL                     1
                    POP_TOP
    
     289            LOAD_FAST_LOAD_FAST    101 (custom, row)
                    STORE_ATTR              12 (custom_contact_categories)
    
     290            LOAD_FAST                2 (db)
                    LOAD_ATTR               37 (flush + NULL|self)
                    CALL                     0
                    GET_AWAITABLE            0
                    LOAD_CONST               0 (None)
           L24:     SEND                     3 (to L27)
           L25:     YIELD_VALUE              1
           L26:     RESUME                   3
                    JUMP_BACKWARD_NO_INTERRUPT 5 (to L24)
           L27:     END_SEND
                    POP_TOP
    
     292            LOAD_GLOBAL             39 (CategoryItem + NULL)
                    LOAD_FAST                0 (body)
                    LOAD_ATTR               14 (slug)
                    LOAD_FAST                0 (body)
                    LOAD_ATTR               34 (label)
                    LOAD_CONST              23 (False)
                    LOAD_CONST              24 (('slug', 'label', 'is_default'))
                    CALL_KW                  3
                    RETURN_VALUE
    
     253   L28:     CLEANUP_THROW
           L29:     EXTENDED_ARG             1
                    JUMP_BACKWARD_NO_INTERRUPT 384 (to L5)
    
     268   L30:     CLEANUP_THROW
           L31:     EXTENDED_ARG             1
                    JUMP_BACKWARD_NO_INTERRUPT 272 (to L11)
    
      --   L32:     SWAP                     2
                    POP_TOP
    
     273            SWAP                     2
                    STORE_FAST               7 (e)
                    RERAISE                  0
    
     290   L33:     CLEANUP_THROW
           L34:     JUMP_BACKWARD_NO_INTERRUPT 46 (to L27)
    
      --   L35:     CALL_INTRINSIC_1         3 (INTRINSIC_STOPITERATION_ERROR)
                    RERAISE                  1
    ExceptionTable:
      L1 to L3 -> L35 [0] lasti
      L3 to L4 -> L28 [2]
      L4 to L9 -> L35 [0] lasti
      L9 to L10 -> L30 [2]
      L10 to L14 -> L35 [0] lasti
      L14 to L16 -> L32 [2]
      L17 to L18 -> L32 [2]
      L19 to L21 -> L32 [2]
      L21 to L25 -> L35 [0] lasti
      L25 to L26 -> L33 [2]
      L26 to L29 -> L35 [0] lasti
      L30 to L31 -> L35 [0] lasti
      L32 to L34 -> L35 [0] lasti
    
# --- Nested code object: delete_custom_category ---
    # co_names: ('check_rate_limit', 'user', 'id', 'settings', 'RATE_LIMIT_API_WRITE_MAX', 'RATE_LIMIT_API_WRITE_WINDOW', 'AppError', 'DEFAULT_CATEGORIES', 'get', 'UserSettings', 'list', 'custom_contact_categories', 'isinstance', 'dict', 'len', 'execute', 'update', 'ContactProfile', 'where', 'owner_user_id', 'category', 'deleted_at', 'is_', 'values', 'contact_category_defaults', 'pop', 'flush')
    # co_varnames: ('slug', 'current_user', 'db', 'allowed', '_', 'row', 'custom', 'e', 'new_custom', 'cat_defaults')
     295            RETURN_GENERATOR
                    POP_TOP
            L1:     RESUME                   0
    
     301            LOAD_GLOBAL              1 (check_rate_limit + NULL)
    
     302            LOAD_CONST               1 ('contacts:catdelete:')
                    LOAD_FAST                1 (current_user)
                    LOAD_ATTR                2 (user)
                    LOAD_ATTR                4 (id)
                    FORMAT_SIMPLE
                    BUILD_STRING             2
    
     303            LOAD_GLOBAL              6 (settings)
                    LOAD_ATTR                8 (RATE_LIMIT_API_WRITE_MAX)
    
     304            LOAD_GLOBAL              6 (settings)
                    LOAD_ATTR               10 (RATE_LIMIT_API_WRITE_WINDOW)
    
     301            LOAD_CONST               2 (('max_requests', 'window_seconds'))
                    CALL_KW                  3
                    GET_AWAITABLE            0
                    LOAD_CONST               0 (None)
            L2:     SEND                     3 (to L5)
            L3:     YIELD_VALUE              1
            L4:     RESUME                   3
                    JUMP_BACKWARD_NO_INTERRUPT 5 (to L2)
            L5:     END_SEND
                    UNPACK_SEQUENCE          2
                    STORE_FAST_STORE_FAST   52 (allowed, _)
    
     306            LOAD_FAST                3 (allowed)
                    TO_BOOL
                    POP_JUMP_IF_TRUE        11 (to L6)
    
     307            LOAD_GLOBAL             13 (AppError + NULL)
                    LOAD_CONST               3 ('RATE_LIMITED')
                    LOAD_CONST               4 ('Too many requests')
                    LOAD_CONST               5 (429)
                    LOAD_CONST               6 (('code', 'message', 'status_code'))
                    CALL_KW                  3
                    RAISE_VARARGS            1
    
     309    L6:     LOAD_FAST                0 (slug)
                    LOAD_GLOBAL             14 (DEFAULT_CATEGORIES)
                    CONTAINS_OP              0
                    POP_JUMP_IF_FALSE       11 (to L7)
    
     310            LOAD_GLOBAL             13 (AppError + NULL)
    
     311            LOAD_CONST               7 ('CATEGORY_IS_DEFAULT')
    
     312            LOAD_CONST               8 ('Cannot delete a built-in category')
    
     313            LOAD_CONST               9 (400)
    
     310            LOAD_CONST               6 (('code', 'message', 'status_code'))
                    CALL_KW                  3
                    RAISE_VARARGS            1
    
     316    L7:     LOAD_FAST                2 (db)
                    LOAD_ATTR               17 (get + NULL|self)
                    LOAD_GLOBAL             18 (UserSettings)
                    LOAD_FAST                1 (current_user)
                    LOAD_ATTR                2 (user)
                    LOAD_ATTR                4 (id)
                    CALL                     2
                    GET_AWAITABLE            0
                    LOAD_CONST               0 (None)
            L8:     SEND                     3 (to L11)
            L9:     YIELD_VALUE              1
           L10:     RESUME                   3
                    JUMP_BACKWARD_NO_INTERRUPT 5 (to L8)
           L11:     END_SEND
                    STORE_FAST               5 (row)
    
     317            LOAD_FAST                5 (row)
                    POP_JUMP_IF_NOT_NONE    11 (to L12)
    
     318            LOAD_GLOBAL             13 (AppError + NULL)
                    LOAD_CONST              10 ('SETTINGS_NOT_FOUND')
                    LOAD_CONST              11 ('User settings not found')
                    LOAD_CONST              12 (404)
                    LOAD_CONST               6 (('code', 'message', 'status_code'))
                    CALL_KW                  3
                    RAISE_VARARGS            1
    
     320   L12:     LOAD_GLOBAL             21 (list + NULL)
                    LOAD_FAST                5 (row)
                    LOAD_ATTR               22 (custom_contact_categories)
                    COPY                     1
                    TO_BOOL
                    POP_JUMP_IF_TRUE         2 (to L13)
                    POP_TOP
                    BUILD_LIST               0
           L13:     CALL                     1
                    STORE_FAST               6 (custom)
    
     321            LOAD_FAST                6 (custom)
                    GET_ITER
                    LOAD_FAST_AND_CLEAR      7 (e)
                    SWAP                     2
           L14:     BUILD_LIST               0
                    SWAP                     2
                    GET_ITER
           L15:     FOR_ITER                49 (to L18)
                    STORE_FAST               7 (e)
                    LOAD_GLOBAL             25 (isinstance + NULL)
                    LOAD_FAST                7 (e)
                    LOAD_GLOBAL             26 (dict)
                    CALL                     2
                    TO_BOOL
                    POP_JUMP_IF_FALSE       23 (to L17)
                    LOAD_FAST                7 (e)
                    LOAD_ATTR               17 (get + NULL|self)
                    LOAD_CONST              13 ('slug')
                    CALL                     1
                    LOAD_FAST                0 (slug)
                    COMPARE_OP              88 (bool(==))
           L16:     POP_JUMP_IF_FALSE        2 (to L17)
                    JUMP_BACKWARD           47 (to L15)
           L17:     LOAD_FAST                7 (e)
                    LIST_APPEND              2
                    JUMP_BACKWARD           51 (to L15)
           L18:     END_FOR
                    POP_TOP
           L19:     STORE_FAST               8 (new_custom)
                    STORE_FAST               7 (e)
    
     322            LOAD_GLOBAL             29 (len + NULL)
                    LOAD_FAST                8 (new_custom)
                    CALL                     1
                    LOAD_GLOBAL             29 (len + NULL)
                    LOAD_FAST                6 (custom)
                    CALL                     1
                    COMPARE_OP              88 (bool(==))
                    POP_JUMP_IF_FALSE       15 (to L20)
    
     323            LOAD_GLOBAL             13 (AppError + NULL)
    
     324            LOAD_CONST              14 ('CATEGORY_NOT_FOUND')
    
     325            LOAD_CONST              15 ("Custom category '")
                    LOAD_FAST                0 (slug)
                    FORMAT_SIMPLE
                    LOAD_CONST              16 ("' not found")
                    BUILD_STRING             3
    
     326            LOAD_CONST              12 (404)
    
     323            LOAD_CONST               6 (('code', 'message', 'status_code'))
                    CALL_KW                  3
                    RAISE_VARARGS            1
    
     329   L20:     LOAD_FAST_LOAD_FAST    133 (new_custom, row)
                    STORE_ATTR              11 (custom_contact_categories)
    
     332            LOAD_FAST                2 (db)
                    LOAD_ATTR               31 (execute + NULL|self)
    
     333            LOAD_GLOBAL             33 (update + NULL)
                    LOAD_GLOBAL             34 (ContactProfile)
                    CALL                     1
    
     334            LOAD_ATTR               37 (where + NULL|self)
    
     335            LOAD_GLOBAL             34 (ContactProfile)
                    LOAD_ATTR               38 (owner_user_id)
                    LOAD_FAST                1 (current_user)
                    LOAD_ATTR                2 (user)
                    LOAD_ATTR                4 (id)
                    COMPARE_OP              72 (==)
    
     336            LOAD_GLOBAL             34 (ContactProfile)
                    LOAD_ATTR               40 (category)
                    LOAD_FAST                0 (slug)
                    COMPARE_OP              72 (==)
    
     337            LOAD_GLOBAL             34 (ContactProfile)
                    LOAD_ATTR               42 (deleted_at)
                    LOAD_ATTR               45 (is_ + NULL|self)
                    LOAD_CONST               0 (None)
                    CALL                     1
    
     334            CALL                     3
    
     339            LOAD_ATTR               47 (values + NULL|self)
                    LOAD_CONST              17 ('other')
                    LOAD_CONST              18 (('category',))
                    CALL_KW                  1
    
     332            CALL                     1
                    GET_AWAITABLE            0
                    LOAD_CONST               0 (None)
           L21:     SEND                     3 (to L24)
           L22:     YIELD_VALUE              1
           L23:     RESUME                   3
                    JUMP_BACKWARD_NO_INTERRUPT 5 (to L21)
           L24:     END_SEND
                    POP_TOP
    
     343            LOAD_GLOBAL             27 (dict + NULL)
                    LOAD_FAST                5 (row)
                    LOAD_ATTR               48 (contact_category_defaults)
                    COPY                     1
                    TO_BOOL
                    POP_JUMP_IF_TRUE         2 (to L25)
                    POP_TOP
                    BUILD_MAP                0
           L25:     CALL                     1
                    STORE_FAST               9 (cat_defaults)
    
     344            LOAD_FAST                9 (cat_defaults)
                    LOAD_ATTR               51 (pop + NULL|self)
                    LOAD_FAST                0 (slug)
                    LOAD_CONST               0 (None)
                    CALL                     2
                    POP_TOP
    
     345            LOAD_FAST_LOAD_FAST    149 (cat_defaults, row)
                    STORE_ATTR              24 (contact_category_defaults)
    
     347            LOAD_FAST                2 (db)
                    LOAD_ATTR               53 (flush + NULL|self)
                    CALL                     0
                    GET_AWAITABLE            0
                    LOAD_CONST               0 (None)
           L26:     SEND                     3 (to L29)
           L27:     YIELD_VALUE              1
           L28:     RESUME                   3
                    JUMP_BACKWARD_NO_INTERRUPT 5 (to L26)
           L29:     END_SEND
                    POP_TOP
    
     348            LOAD_CONST              19 (True)
                    LOAD_CONST              17 ('other')
                    LOAD_CONST              20 (('deleted', 'reassigned_to'))
                    BUILD_CONST_KEY_MAP      2
                    RETURN_VALUE
    
     301   L30:     CLEANUP_THROW
           L31:     EXTENDED_ARG             1
                    JUMP_BACKWARD_NO_INTERRUPT 481 (to L5)
    
     316   L32:     CLEANUP_THROW
           L33:     EXTENDED_ARG             1
                    JUMP_BACKWARD_NO_INTERRUPT 393 (to L11)
    
      --   L34:     SWAP                     2
                    POP_TOP
    
     321            SWAP                     2
                    STORE_FAST               7 (e)
                    RERAISE                  0
    
     332   L35:     CLEANUP_THROW
           L36:     JUMP_BACKWARD_NO_INTERRUPT 98 (to L24)
    
     347   L37:     CLEANUP_THROW
           L38:     JUMP_BACKWARD_NO_INTERRUPT 22 (to L29)
    
      --   L39:     CALL_INTRINSIC_1         3 (INTRINSIC_STOPITERATION_ERROR)
                    RERAISE                  1
    ExceptionTable:
      L1 to L3 -> L39 [0] lasti
      L3 to L4 -> L30 [2]
      L4 to L9 -> L39 [0] lasti
      L9 to L10 -> L32 [2]
      L10 to L14 -> L39 [0] lasti
      L14 to L16 -> L34 [2]
      L17 to L19 -> L34 [2]
      L19 to L22 -> L39 [0] lasti
      L22 to L23 -> L35 [2]
      L23 to L27 -> L39 [0] lasti
      L27 to L28 -> L37 [2]
      L28 to L31 -> L39 [0] lasti
      L32 to L33 -> L39 [0] lasti
      L34 to L36 -> L39 [0] lasti
      L37 to L38 -> L39 [0] lasti
    
# --- Nested code object: get_category_defaults ---
    # co_names: ('get', 'UserSettings', 'user', 'id', 'contact_category_defaults', 'CategoryDefaultsResponse')
    # co_varnames: ('current_user', 'db', 'row', 'defaults')
     355            RETURN_GENERATOR
                    POP_TOP
            L1:     RESUME                   0
    
     360            LOAD_FAST                1 (db)
                    LOAD_ATTR                1 (get + NULL|self)
                    LOAD_GLOBAL              2 (UserSettings)
                    LOAD_FAST                0 (current_user)
                    LOAD_ATTR                4 (user)
                    LOAD_ATTR                6 (id)
                    CALL                     2
                    GET_AWAITABLE            0
                    LOAD_CONST               0 (None)
            L2:     SEND                     3 (to L5)
            L3:     YIELD_VALUE              1
            L4:     RESUME                   3
                    JUMP_BACKWARD_NO_INTERRUPT 5 (to L2)
            L5:     END_SEND
                    STORE_FAST               2 (row)
    
     361            LOAD_FAST                2 (row)
                    TO_BOOL
                    POP_JUMP_IF_FALSE       12 (to L6)
                    LOAD_FAST                2 (row)
                    LOAD_ATTR                8 (contact_category_defaults)
                    JUMP_FORWARD             1 (to L7)
            L6:     BUILD_MAP                0
            L7:     STORE_FAST               3 (defaults)
    
     362            LOAD_GLOBAL             11 (CategoryDefaultsResponse + NULL)
                    LOAD_FAST                3 (defaults)
                    LOAD_CONST               1 (('defaults',))
                    CALL_KW                  1
                    RETURN_VALUE
    
     360    L8:     CLEANUP_THROW
            L9:     JUMP_BACKWARD_NO_INTERRUPT 34 (to L5)
    
      --   L10:     CALL_INTRINSIC_1         3 (INTRINSIC_STOPITERATION_ERROR)
                    RERAISE                  1
    ExceptionTable:
      L1 to L3 -> L10 [0] lasti
      L3 to L4 -> L8 [2]
      L4 to L9 -> L10 [0] lasti
    
# --- Nested code object: update_category_defaults ---
    # co_names: ('check_rate_limit', 'user', 'id', 'settings', 'RATE_LIMIT_API_WRITE_MAX', 'RATE_LIMIT_API_WRITE_WINDOW', 'AppError', 'get', 'UserSettings', '_get_valid_categories', 'defaults', 'contact_category_defaults', 'flush', 'CategoryDefaultsResponse')
    # co_varnames: ('body', 'current_user', 'db', 'allowed', '_', 'row', 'valid', 'cat_key')
     365            RETURN_GENERATOR
                    POP_TOP
            L1:     RESUME                   0
    
     371            LOAD_GLOBAL              1 (check_rate_limit + NULL)
    
     372            LOAD_CONST               1 ('contacts:catdef:')
                    LOAD_FAST                1 (current_user)
                    LOAD_ATTR                2 (user)
                    LOAD_ATTR                4 (id)
                    FORMAT_SIMPLE
                    BUILD_STRING             2
    
     373            LOAD_GLOBAL              6 (settings)
                    LOAD_ATTR                8 (RATE_LIMIT_API_WRITE_MAX)
    
     374            LOAD_GLOBAL              6 (settings)
                    LOAD_ATTR               10 (RATE_LIMIT_API_WRITE_WINDOW)
    
     371            LOAD_CONST               2 (('max_requests', 'window_seconds'))
                    CALL_KW                  3
                    GET_AWAITABLE            0
                    LOAD_CONST               0 (None)
            L2:     SEND                     3 (to L5)
            L3:     YIELD_VALUE              1
            L4:     RESUME                   3
                    JUMP_BACKWARD_NO_INTERRUPT 5 (to L2)
            L5:     END_SEND
                    UNPACK_SEQUENCE          2
                    STORE_FAST_STORE_FAST   52 (allowed, _)
    
     376            LOAD_FAST                3 (allowed)
                    TO_BOOL
                    POP_JUMP_IF_TRUE        11 (to L6)
    
     377            LOAD_GLOBAL             13 (AppError + NULL)
                    LOAD_CONST               3 ('RATE_LIMITED')
                    LOAD_CONST               4 ('Too many requests')
                    LOAD_CONST               5 (429)
                    LOAD_CONST               6 (('code', 'message', 'status_code'))
                    CALL_KW                  3
                    RAISE_VARARGS            1
    
     379    L6:     LOAD_FAST                2 (db)
                    LOAD_ATTR               15 (get + NULL|self)
                    LOAD_GLOBAL             16 (UserSettings)
                    LOAD_FAST                1 (current_user)
                    LOAD_ATTR                2 (user)
                    LOAD_ATTR                4 (id)
                    CALL                     2
                    GET_AWAITABLE            0
                    LOAD_CONST               0 (None)
            L7:     SEND                     3 (to L10)
            L8:     YIELD_VALUE              1
            L9:     RESUME                   3
                    JUMP_BACKWARD_NO_INTERRUPT 5 (to L7)
           L10:     END_SEND
                    STORE_FAST               5 (row)
    
     380            LOAD_FAST                5 (row)
                    POP_JUMP_IF_NOT_NONE    11 (to L11)
    
     381            LOAD_GLOBAL             13 (AppError + NULL)
                    LOAD_CONST               7 ('SETTINGS_NOT_FOUND')
                    LOAD_CONST               8 ('User settings not found')
                    LOAD_CONST               9 (404)
                    LOAD_CONST               6 (('code', 'message', 'status_code'))
                    CALL_KW                  3
                    RAISE_VARARGS            1
    
     383   L11:     LOAD_GLOBAL             19 (_get_valid_categories + NULL)
                    LOAD_FAST_LOAD_FAST     33 (db, current_user)
                    LOAD_ATTR                2 (user)
                    LOAD_ATTR                4 (id)
                    CALL                     2
                    GET_AWAITABLE            0
                    LOAD_CONST               0 (None)
           L12:     SEND                     3 (to L15)
           L13:     YIELD_VALUE              1
           L14:     RESUME                   3
                    JUMP_BACKWARD_NO_INTERRUPT 5 (to L12)
           L15:     END_SEND
                    STORE_FAST               6 (valid)
    
     384            LOAD_FAST                0 (body)
                    LOAD_ATTR               20 (defaults)
                    GET_ITER
           L16:     FOR_ITER                23 (to L19)
                    STORE_FAST               7 (cat_key)
    
     385            LOAD_FAST_LOAD_FAST    118 (cat_key, valid)
                    CONTAINS_OP              1
           L17:     POP_JUMP_IF_TRUE         2 (to L18)
                    JUMP_BACKWARD           10 (to L16)
    
     386   L18:     LOAD_GLOBAL             13 (AppError + NULL)
    
     387            LOAD_CONST              10 ('UNKNOWN_CATEGORY')
    
     388            LOAD_CONST              11 ("Unknown category '")
                    LOAD_FAST                7 (cat_key)
                    FORMAT_SIMPLE
                    LOAD_CONST              12 ("' in defaults")
                    BUILD_STRING             3
    
     389            LOAD_CONST              13 (409)
    
     386            LOAD_CONST               6 (('code', 'message', 'status_code'))
                    CALL_KW                  3
                    RAISE_VARARGS            1
    
     384   L19:     END_FOR
                    POP_TOP
    
     392            LOAD_FAST                0 (body)
                    LOAD_ATTR               20 (defaults)
                    LOAD_FAST                5 (row)
                    STORE_ATTR              11 (contact_category_defaults)
    
     393            LOAD_FAST                2 (db)
                    LOAD_ATTR               25 (flush + NULL|self)
                    CALL                     0
                    GET_AWAITABLE            0
                    LOAD_CONST               0 (None)
           L20:     SEND                     3 (to L23)
           L21:     YIELD_VALUE              1
           L22:     RESUME                   3
                    JUMP_BACKWARD_NO_INTERRUPT 5 (to L20)
           L23:     END_SEND
                    POP_TOP
    
     394            LOAD_GLOBAL             27 (CategoryDefaultsResponse + NULL)
                    LOAD_FAST                5 (row)
                    LOAD_ATTR               22 (contact_category_defaults)
                    LOAD_CONST              14 (('defaults',))
                    CALL_KW                  1
                    RETURN_VALUE
    
     371   L24:     CLEANUP_THROW
           L25:     JUMP_BACKWARD_NO_INTERRUPT 226 (to L5)
    
     379   L26:     CLEANUP_THROW
           L27:     JUMP_BACKWARD_NO_INTERRUPT 158 (to L10)
    
     383   L28:     CLEANUP_THROW
           L29:     JUMP_BACKWARD_NO_INTERRUPT 107 (to L15)
    
     393   L30:     CLEANUP_THROW
           L31:     JUMP_BACKWARD_NO_INTERRUPT 29 (to L23)
    
      --   L32:     CALL_INTRINSIC_1         3 (INTRINSIC_STOPITERATION_ERROR)
                    RERAISE                  1
    ExceptionTable:
      L1 to L3 -> L32 [0] lasti
      L3 to L4 -> L24 [2]
      L4 to L8 -> L32 [0] lasti
      L8 to L9 -> L26 [2]
      L9 to L13 -> L32 [0] lasti
      L13 to L14 -> L28 [2]
      L14 to L17 -> L32 [0] lasti
      L18 to L21 -> L32 [0] lasti
      L21 to L22 -> L30 [2]
      L22 to L25 -> L32 [0] lasti
      L26 to L27 -> L32 [0] lasti
      L28 to L29 -> L32 [0] lasti
      L30 to L31 -> L32 [0] lasti
    
# --- Nested code object: get_contact ---
    # co_names: ('execute', 'select', 'ContactProfile', 'where', 'id', 'owner_user_id', 'user', 'deleted_at', 'is_', 'scalar_one_or_none', 'AppError', '_to_response')
    # co_varnames: ('contact_id', 'current_user', 'db', 'contact')
     401           RETURN_GENERATOR
                   POP_TOP
           L1:     RESUME                   0
    
     407           LOAD_FAST                2 (db)
                   LOAD_ATTR                1 (execute + NULL|self)
    
     408           LOAD_GLOBAL              3 (select + NULL)
                   LOAD_GLOBAL              4 (ContactProfile)
                   CALL                     1
                   LOAD_ATTR                7 (where + NULL|self)
    
     409           LOAD_GLOBAL              4 (ContactProfile)
                   LOAD_ATTR                8 (id)
                   LOAD_FAST                0 (contact_id)
                   COMPARE_OP              72 (==)
    
     410           LOAD_GLOBAL              4 (ContactProfile)
                   LOAD_ATTR               10 (owner_user_id)
                   LOAD_FAST                1 (current_user)
                   LOAD_ATTR               12 (user)
                   LOAD_ATTR                8 (id)
                   COMPARE_OP              72 (==)
    
     411           LOAD_GLOBAL              4 (ContactProfile)
                   LOAD_ATTR               14 (deleted_at)
                   LOAD_ATTR               17 (is_ + NULL|self)
                   LOAD_CONST               0 (None)
                   CALL                     1
    
     408           CALL                     3
    
     407           CALL                     1
                   GET_AWAITABLE            0
                   LOAD_CONST               0 (None)
           L2:     SEND                     3 (to L5)
           L3:     YIELD_VALUE              1
           L4:     RESUME                   3
                   JUMP_BACKWARD_NO_INTERRUPT 5 (to L2)
           L5:     END_SEND
    
     413           LOAD_ATTR               19 (scalar_one_or_none + NULL|self)
                   CALL                     0
    
     407           STORE_FAST               3 (contact)
    
     415           LOAD_FAST                3 (contact)
                   POP_JUMP_IF_NOT_NONE    11 (to L6)
    
     416           LOAD_GLOBAL             21 (AppError + NULL)
                   LOAD_CONST               1 ('CONTACT_NOT_FOUND')
                   LOAD_CONST               2 ('Contact not found')
                   LOAD_CONST               3 (404)
                   LOAD_CONST               4 (('code', 'message', 'status_code'))
                   CALL_KW                  3
                   RAISE_VARARGS            1
    
     418   L6:     LOAD_GLOBAL             23 (_to_response + NULL)
                   LOAD_FAST                3 (contact)
                   CALL                     1
                   RETURN_VALUE
    
     407   L7:     CLEANUP_THROW
           L8:     JUMP_BACKWARD_NO_INTERRUPT 43 (to L5)
    
      --   L9:     CALL_INTRINSIC_1         3 (INTRINSIC_STOPITERATION_ERROR)
                   RERAISE                  1
    ExceptionTable:
      L1 to L3 -> L9 [0] lasti
      L3 to L4 -> L7 [2]
      L4 to L8 -> L9 [0] lasti
    
# --- Nested code object: update_contact ---
    # co_names: ('check_rate_limit', 'user', 'id', 'settings', 'RATE_LIMIT_API_WRITE_MAX', 'RATE_LIMIT_API_WRITE_WINDOW', 'AppError', 'execute', 'select', 'ContactProfile', 'where', 'owner_user_id', 'deleted_at', 'is_', 'scalar_one_or_none', 'model_dump', '_validate_contact_category', 'setattr', 'get', 'encrypt_field', 'encode', 'ai_greeting_instructions_ciphertext', 'ai_greeting_instructions_nonce', 'ai_greeting_instructions_key_version', 'ai_custom_instructions_ciphertext', 'ai_custom_instructions_nonce', 'ai_custom_instructions_key_version', 'clear_ai_temperament', 'ai_temperament_preset', 'clear_ai_greeting_template', 'ai_greeting_template', 'clear_ai_greeting_instructions', 'clear_ai_swearing_rule', 'ai_swearing_rule', 'clear_ai_max_call_length', 'ai_max_call_length_seconds', 'clear_ai_custom_instructions', 'flush', '_to_response')
    # co_varnames: ('contact_id', 'body', 'current_user', 'db', 'allowed', '_', 'contact', 'data', 'plain_fields', 'field', 'g_ct', 'g_n', 'g_kv', 'i_ct', 'i_n', 'i_kv')
     421            RETURN_GENERATOR
                    POP_TOP
            L1:     RESUME                   0
    
     428            LOAD_GLOBAL              1 (check_rate_limit + NULL)
    
     429            LOAD_CONST               1 ('contacts:update:')
                    LOAD_FAST                2 (current_user)
                    LOAD_ATTR                2 (user)
                    LOAD_ATTR                4 (id)
                    FORMAT_SIMPLE
                    BUILD_STRING             2
    
     430            LOAD_GLOBAL              6 (settings)
                    LOAD_ATTR                8 (RATE_LIMIT_API_WRITE_MAX)
    
     431            LOAD_GLOBAL              6 (settings)
                    LOAD_ATTR               10 (RATE_LIMIT_API_WRITE_WINDOW)
    
     428            LOAD_CONST               2 (('max_requests', 'window_seconds'))
                    CALL_KW                  3
                    GET_AWAITABLE            0
                    LOAD_CONST               0 (None)
            L2:     SEND                     3 (to L5)
            L3:     YIELD_VALUE              1
            L4:     RESUME                   3
                    JUMP_BACKWARD_NO_INTERRUPT 5 (to L2)
            L5:     END_SEND
                    UNPACK_SEQUENCE          2
                    STORE_FAST_STORE_FAST   69 (allowed, _)
    
     433            LOAD_FAST                4 (allowed)
                    TO_BOOL
                    POP_JUMP_IF_TRUE        11 (to L6)
    
     434            LOAD_GLOBAL             13 (AppError + NULL)
                    LOAD_CONST               3 ('RATE_LIMITED')
                    LOAD_CONST               4 ('Too many requests')
                    LOAD_CONST               5 (429)
                    LOAD_CONST               6 (('code', 'message', 'status_code'))
                    CALL_KW                  3
                    RAISE_VARARGS            1
    
     436    L6:     LOAD_FAST                3 (db)
                    LOAD_ATTR               15 (execute + NULL|self)
    
     437            LOAD_GLOBAL             17 (select + NULL)
                    LOAD_GLOBAL             18 (ContactProfile)
                    CALL                     1
                    LOAD_ATTR               21 (where + NULL|self)
    
     438            LOAD_GLOBAL             18 (ContactProfile)
                    LOAD_ATTR                4 (id)
                    LOAD_FAST                0 (contact_id)
                    COMPARE_OP              72 (==)
    
     439            LOAD_GLOBAL             18 (ContactProfile)
                    LOAD_ATTR               22 (owner_user_id)
                    LOAD_FAST                2 (current_user)
                    LOAD_ATTR                2 (user)
                    LOAD_ATTR                4 (id)
                    COMPARE_OP              72 (==)
    
     440            LOAD_GLOBAL             18 (ContactProfile)
                    LOAD_ATTR               24 (deleted_at)
                    LOAD_ATTR               27 (is_ + NULL|self)
                    LOAD_CONST               0 (None)
                    CALL                     1
    
     437            CALL                     3
    
     436            CALL                     1
                    GET_AWAITABLE            0
                    LOAD_CONST               0 (None)
            L7:     SEND                     3 (to L10)
            L8:     YIELD_VALUE              1
            L9:     RESUME                   3
                    JUMP_BACKWARD_NO_INTERRUPT 5 (to L7)
           L10:     END_SEND
    
     442            LOAD_ATTR               29 (scalar_one_or_none + NULL|self)
                    CALL                     0
    
     436            STORE_FAST               6 (contact)
    
     444            LOAD_FAST                6 (contact)
                    POP_JUMP_IF_NOT_NONE    11 (to L11)
    
     445            LOAD_GLOBAL             13 (AppError + NULL)
                    LOAD_CONST               7 ('CONTACT_NOT_FOUND')
                    LOAD_CONST               8 ('Contact not found')
                    LOAD_CONST               9 (404)
                    LOAD_CONST               6 (('code', 'message', 'status_code'))
                    CALL_KW                  3
                    RAISE_VARARGS            1
    
     447   L11:     LOAD_FAST                1 (body)
                    LOAD_ATTR               31 (model_dump + NULL|self)
                    LOAD_CONST              10 (True)
                    LOAD_CONST              11 (('exclude_unset',))
                    CALL_KW                  1
                    STORE_FAST               7 (data)
    
     449            LOAD_CONST              12 ('category')
                    LOAD_FAST                7 (data)
                    CONTAINS_OP              0
                    POP_JUMP_IF_FALSE       49 (to L16)
                    LOAD_FAST                7 (data)
                    LOAD_CONST              12 ('category')
                    BINARY_SUBSCR
                    POP_JUMP_IF_NONE        43 (to L16)
    
     450            LOAD_GLOBAL             33 (_validate_contact_category + NULL)
                    LOAD_FAST_LOAD_FAST     50 (db, current_user)
                    LOAD_ATTR                2 (user)
                    LOAD_ATTR                4 (id)
                    LOAD_FAST                7 (data)
                    LOAD_CONST              12 ('category')
                    BINARY_SUBSCR
                    CALL                     3
                    GET_AWAITABLE            0
                    LOAD_CONST               0 (None)
           L12:     SEND                     3 (to L15)
           L13:     YIELD_VALUE              1
           L14:     RESUME                   3
                    JUMP_BACKWARD_NO_INTERRUPT 5 (to L12)
           L15:     END_SEND
                    POP_TOP
    
     452   L16:     BUILD_SET                0
                    LOAD_CONST              13 (frozenset({'is_vip', 'ai_temperament_preset', 'category', 'ai_greeting_template', 'notes', 'email', 'relationship', 'display_name', 'is_blocked', 'ai_max_call_length_seconds', 'ai_swearing_rule', 'company', 'block_reason'}))
                    SET_UPDATE               1
                    STORE_FAST               8 (plain_fields)
    
     458            LOAD_FAST                8 (plain_fields)
                    GET_ITER
           L17:     FOR_ITER                31 (to L22)
                    STORE_FAST               9 (field)
    
     459            LOAD_FAST_LOAD_FAST    151 (field, data)
                    CONTAINS_OP              0
           L18:     POP_JUMP_IF_TRUE         2 (to L19)
                    JUMP_BACKWARD           10 (to L17)
           L19:     LOAD_FAST_LOAD_FAST    121 (data, field)
                    BINARY_SUBSCR
           L20:     POP_JUMP_IF_NOT_NONE     2 (to L21)
                    JUMP_BACKWARD           17 (to L17)
    
     460   L21:     LOAD_GLOBAL             35 (setattr + NULL)
                    LOAD_FAST_LOAD_FAST    105 (contact, field)
                    LOAD_FAST_LOAD_FAST    121 (data, field)
                    BINARY_SUBSCR
                    CALL                     3
                    POP_TOP
                    JUMP_BACKWARD           33 (to L17)
    
     458   L22:     END_FOR
                    POP_TOP
    
     462            LOAD_FAST                7 (data)
                    LOAD_ATTR               37 (get + NULL|self)
                    LOAD_CONST              14 ('ai_greeting_instructions')
                    CALL                     1
                    TO_BOOL
                    POP_JUMP_IF_FALSE       50 (to L23)
    
     463            LOAD_GLOBAL             39 (encrypt_field + NULL)
                    LOAD_FAST                7 (data)
                    LOAD_CONST              14 ('ai_greeting_instructions')
                    BINARY_SUBSCR
                    LOAD_ATTR               41 (encode + NULL|self)
                    LOAD_CONST              15 ('utf-8')
                    CALL                     1
                    CALL                     1
                    UNPACK_SEQUENCE          3
                    STORE_FAST_STORE_FAST  171 (g_ct, g_n)
                    STORE_FAST              12 (g_kv)
    
     464            LOAD_FAST_LOAD_FAST    166 (g_ct, contact)
                    STORE_ATTR              21 (ai_greeting_instructions_ciphertext)
    
     465            LOAD_FAST_LOAD_FAST    182 (g_n, contact)
                    STORE_ATTR              22 (ai_greeting_instructions_nonce)
    
     466            LOAD_FAST_LOAD_FAST    198 (g_kv, contact)
                    STORE_ATTR              23 (ai_greeting_instructions_key_version)
    
     468   L23:     LOAD_FAST                7 (data)
                    LOAD_ATTR               37 (get + NULL|self)
                    LOAD_CONST              16 ('ai_custom_instructions')
                    CALL                     1
                    TO_BOOL
                    POP_JUMP_IF_FALSE       50 (to L24)
    
     469            LOAD_GLOBAL             39 (encrypt_field + NULL)
                    LOAD_FAST                7 (data)
                    LOAD_CONST              16 ('ai_custom_instructions')
                    BINARY_SUBSCR
                    LOAD_ATTR               41 (encode + NULL|self)
                    LOAD_CONST              15 ('utf-8')
                    CALL                     1
                    CALL                     1
                    UNPACK_SEQUENCE          3
                    STORE_FAST_STORE_FAST  222 (i_ct, i_n)
                    STORE_FAST              15 (i_kv)
    
     470            LOAD_FAST_LOAD_FAST    214 (i_ct, contact)
                    STORE_ATTR              24 (ai_custom_instructions_ciphertext)
    
     471            LOAD_FAST_LOAD_FAST    230 (i_n, contact)
                    STORE_ATTR              25 (ai_custom_instructions_nonce)
    
     472            LOAD_FAST_LOAD_FAST    246 (i_kv, contact)
                    STORE_ATTR              26 (ai_custom_instructions_key_version)
    
     474   L24:     LOAD_FAST                1 (body)
                    LOAD_ATTR               54 (clear_ai_temperament)
                    TO_BOOL
                    POP_JUMP_IF_FALSE        7 (to L25)
    
     475            LOAD_CONST               0 (None)
                    LOAD_FAST                6 (contact)
                    STORE_ATTR              28 (ai_temperament_preset)
    
     476   L25:     LOAD_FAST                1 (body)
                    LOAD_ATTR               58 (clear_ai_greeting_template)
                    TO_BOOL
                    POP_JUMP_IF_FALSE        7 (to L26)
    
     477            LOAD_CONST               0 (None)
                    LOAD_FAST                6 (contact)
                    STORE_ATTR              30 (ai_greeting_template)
    
     478   L26:     LOAD_FAST                1 (body)
                    LOAD_ATTR               62 (clear_ai_greeting_instructions)
                    TO_BOOL
                    POP_JUMP_IF_FALSE       21 (to L27)
    
     479            LOAD_CONST               0 (None)
                    LOAD_FAST                6 (contact)
                    STORE_ATTR              21 (ai_greeting_instructions_ciphertext)
    
     480            LOAD_CONST               0 (None)
                    LOAD_FAST                6 (contact)
                    STORE_ATTR              22 (ai_greeting_instructions_nonce)
    
     481            LOAD_CONST               0 (None)
                    LOAD_FAST                6 (contact)
                    STORE_ATTR              23 (ai_greeting_instructions_key_version)
    
     482   L27:     LOAD_FAST                1 (body)
                    LOAD_ATTR               64 (clear_ai_swearing_rule)
                    TO_BOOL
                    POP_JUMP_IF_FALSE        7 (to L28)
    
     483            LOAD_CONST               0 (None)
                    LOAD_FAST                6 (contact)
                    STORE_ATTR              33 (ai_swearing_rule)
    
     484   L28:     LOAD_FAST                1 (body)
                    LOAD_ATTR               68 (clear_ai_max_call_length)
                    TO_BOOL
                    POP_JUMP_IF_FALSE        7 (to L29)
    
     485            LOAD_CONST               0 (None)
                    LOAD_FAST                6 (contact)
                    STORE_ATTR              35 (ai_max_call_length_seconds)
    
     486   L29:     LOAD_FAST                1 (body)
                    LOAD_ATTR               72 (clear_ai_custom_instructions)
                    TO_BOOL
                    POP_JUMP_IF_FALSE       21 (to L30)
    
     487            LOAD_CONST               0 (None)
                    LOAD_FAST                6 (contact)
                    STORE_ATTR              24 (ai_custom_instructions_ciphertext)
    
     488            LOAD_CONST               0 (None)
                    LOAD_FAST                6 (contact)
                    STORE_ATTR              25 (ai_custom_instructions_nonce)
    
     489            LOAD_CONST               0 (None)
                    LOAD_FAST                6 (contact)
                    STORE_ATTR              26 (ai_custom_instructions_key_version)
    
     491   L30:     LOAD_FAST                3 (db)
                    LOAD_ATTR               75 (flush + NULL|self)
                    CALL                     0
                    GET_AWAITABLE            0
                    LOAD_CONST               0 (None)
           L31:     SEND                     3 (to L34)
           L32:     YIELD_VALUE              1
           L33:     RESUME                   3
                    JUMP_BACKWARD_NO_INTERRUPT 5 (to L31)
           L34:     END_SEND
                    POP_TOP
    
     492            LOAD_GLOBAL             77 (_to_response + NULL)
                    LOAD_FAST                6 (contact)
                    CALL                     1
                    RETURN_VALUE
    
     428   L35:     CLEANUP_THROW
           L36:     EXTENDED_ARG             2
                    JUMP_BACKWARD_NO_INTERRUPT 653 (to L5)
    
     436   L37:     CLEANUP_THROW
           L38:     EXTENDED_ARG             1
                    JUMP_BACKWARD_NO_INTERRUPT 498 (to L10)
    
     450   L39:     CLEANUP_THROW
           L40:     EXTENDED_ARG             1
                    JUMP_BACKWARD_NO_INTERRUPT 403 (to L15)
    
     491   L41:     CLEANUP_THROW
           L42:     JUMP_BACKWARD_NO_INTERRUPT 24 (to L34)
    
      --   L43:     CALL_INTRINSIC_1         3 (INTRINSIC_STOPITERATION_ERROR)
                    RERAISE                  1
    ExceptionTable:
      L1 to L3 -> L43 [0] lasti
      L3 to L4 -> L35 [2]
      L4 to L8 -> L43 [0] lasti
      L8 to L9 -> L37 [2]
      L9 to L13 -> L43 [0] lasti
      L13 to L14 -> L39 [2]
      L14 to L18 -> L43 [0] lasti
      L19 to L20 -> L43 [0] lasti
      L21 to L32 -> L43 [0] lasti
      L32 to L33 -> L41 [2]
      L33 to L36 -> L43 [0] lasti
      L37 to L38 -> L43 [0] lasti
      L39 to L40 -> L43 [0] lasti
      L41 to L42 -> L43 [0] lasti
    
# --- Nested code object: delete_contact ---
    # co_names: ('check_rate_limit', 'user', 'id', 'settings', 'RATE_LIMIT_API_WRITE_MAX', 'RATE_LIMIT_API_WRITE_WINDOW', 'AppError', 'execute', 'select', 'ContactProfile', 'where', 'owner_user_id', 'deleted_at', 'is_', 'scalar_one_or_none', 'datetime', 'now', 'UTC', 'log_event', 'flush')
    # co_varnames: ('contact_id', 'current_user', 'db', 'allowed', '_', 'contact')
     495            RETURN_GENERATOR
                    POP_TOP
            L1:     RESUME                   0
    
     501            LOAD_GLOBAL              1 (check_rate_limit + NULL)
    
     502            LOAD_CONST               1 ('contacts:delete:')
                    LOAD_FAST                1 (current_user)
                    LOAD_ATTR                2 (user)
                    LOAD_ATTR                4 (id)
                    FORMAT_SIMPLE
                    BUILD_STRING             2
    
     503            LOAD_GLOBAL              6 (settings)
                    LOAD_ATTR                8 (RATE_LIMIT_API_WRITE_MAX)
    
     504            LOAD_GLOBAL              6 (settings)
                    LOAD_ATTR               10 (RATE_LIMIT_API_WRITE_WINDOW)
    
     501            LOAD_CONST               2 (('max_requests', 'window_seconds'))
                    CALL_KW                  3
                    GET_AWAITABLE            0
                    LOAD_CONST               0 (None)
            L2:     SEND                     3 (to L5)
            L3:     YIELD_VALUE              1
            L4:     RESUME                   3
                    JUMP_BACKWARD_NO_INTERRUPT 5 (to L2)
            L5:     END_SEND
                    UNPACK_SEQUENCE          2
                    STORE_FAST_STORE_FAST   52 (allowed, _)
    
     506            LOAD_FAST                3 (allowed)
                    TO_BOOL
                    POP_JUMP_IF_TRUE        11 (to L6)
    
     507            LOAD_GLOBAL             13 (AppError + NULL)
                    LOAD_CONST               3 ('RATE_LIMITED')
                    LOAD_CONST               4 ('Too many requests')
                    LOAD_CONST               5 (429)
                    LOAD_CONST               6 (('code', 'message', 'status_code'))
                    CALL_KW                  3
                    RAISE_VARARGS            1
    
     509    L6:     LOAD_FAST                2 (db)
                    LOAD_ATTR               15 (execute + NULL|self)
    
     510            LOAD_GLOBAL             17 (select + NULL)
                    LOAD_GLOBAL             18 (ContactProfile)
                    CALL                     1
                    LOAD_ATTR               21 (where + NULL|self)
    
     511            LOAD_GLOBAL             18 (ContactProfile)
                    LOAD_ATTR                4 (id)
                    LOAD_FAST                0 (contact_id)
                    COMPARE_OP              72 (==)
    
     512            LOAD_GLOBAL             18 (ContactProfile)
                    LOAD_ATTR               22 (owner_user_id)
                    LOAD_FAST                1 (current_user)
                    LOAD_ATTR                2 (user)
                    LOAD_ATTR                4 (id)
                    COMPARE_OP              72 (==)
    
     513            LOAD_GLOBAL             18 (ContactProfile)
                    LOAD_ATTR               24 (deleted_at)
                    LOAD_ATTR               27 (is_ + NULL|self)
                    LOAD_CONST               0 (None)
                    CALL                     1
    
     510            CALL                     3
    
     509            CALL                     1
                    GET_AWAITABLE            0
                    LOAD_CONST               0 (None)
            L7:     SEND                     3 (to L10)
            L8:     YIELD_VALUE              1
            L9:     RESUME                   3
                    JUMP_BACKWARD_NO_INTERRUPT 5 (to L7)
           L10:     END_SEND
    
     515            LOAD_ATTR               29 (scalar_one_or_none + NULL|self)
                    CALL                     0
    
     509            STORE_FAST               5 (contact)
    
     517            LOAD_FAST                5 (contact)
                    POP_JUMP_IF_NOT_NONE    11 (to L11)
    
     518            LOAD_GLOBAL             13 (AppError + NULL)
                    LOAD_CONST               7 ('CONTACT_NOT_FOUND')
                    LOAD_CONST               8 ('Contact not found')
                    LOAD_CONST               9 (404)
                    LOAD_CONST               6 (('code', 'message', 'status_code'))
                    CALL_KW                  3
                    RAISE_VARARGS            1
    
     520   L11:     LOAD_GLOBAL             30 (datetime)
                    LOAD_ATTR               32 (now)
                    PUSH_NULL
                    LOAD_GLOBAL             34 (UTC)
                    CALL                     1
                    LOAD_FAST                5 (contact)
                    STORE_ATTR              12 (deleted_at)
    
     521            LOAD_GLOBAL             37 (log_event + NULL)
    
     522            LOAD_FAST                2 (db)
    
     523            LOAD_FAST                1 (current_user)
                    LOAD_ATTR                2 (user)
                    LOAD_ATTR                4 (id)
    
     524            LOAD_CONST              10 ('contact_deleted')
    
     525            LOAD_FAST                1 (current_user)
                    LOAD_ATTR                2 (user)
                    LOAD_ATTR                4 (id)
    
     526            LOAD_CONST              11 ('contact_profile')
    
     527            LOAD_FAST                5 (contact)
                    LOAD_ATTR                4 (id)
    
     521            LOAD_CONST              12 (('owner_user_id', 'event_type', 'actor_id', 'target_type', 'target_id'))
                    CALL_KW                  6
                    GET_AWAITABLE            0
                    LOAD_CONST               0 (None)
           L12:     SEND                     3 (to L15)
           L13:     YIELD_VALUE              1
           L14:     RESUME                   3
                    JUMP_BACKWARD_NO_INTERRUPT 5 (to L12)
           L15:     END_SEND
                    POP_TOP
    
     529            LOAD_FAST                2 (db)
                    LOAD_ATTR               39 (flush + NULL|self)
                    CALL                     0
                    GET_AWAITABLE            0
                    LOAD_CONST               0 (None)
           L16:     SEND                     3 (to L19)
           L17:     YIELD_VALUE              1
           L18:     RESUME                   3
                    JUMP_BACKWARD_NO_INTERRUPT 5 (to L16)
           L19:     END_SEND
                    POP_TOP
    
     530            LOAD_CONST              13 ('deleted')
                    LOAD_CONST              14 (True)
                    BUILD_MAP                1
                    RETURN_VALUE
    
     501   L20:     CLEANUP_THROW
           L21:     EXTENDED_ARG             1
                    JUMP_BACKWARD_NO_INTERRUPT 322 (to L5)
    
     509   L22:     CLEANUP_THROW
           L23:     JUMP_BACKWARD_NO_INTERRUPT 166 (to L10)
    
     521   L24:     CLEANUP_THROW
           L25:     JUMP_BACKWARD_NO_INTERRUPT 37 (to L15)
    
     529   L26:     CLEANUP_THROW
           L27:     JUMP_BACKWARD_NO_INTERRUPT 15 (to L19)
    
      --   L28:     CALL_INTRINSIC_1         3 (INTRINSIC_STOPITERATION_ERROR)
                    RERAISE                  1
    ExceptionTable:
      L1 to L3 -> L28 [0] lasti
      L3 to L4 -> L20 [2]
      L4 to L8 -> L28 [0] lasti
      L8 to L9 -> L22 [2]
      L9 to L13 -> L28 [0] lasti
      L13 to L14 -> L24 [2]
      L14 to L17 -> L28 [0] lasti
      L17 to L18 -> L26 [2]
      L18 to L21 -> L28 [0] lasti
      L22 to L23 -> L28 [0] lasti
      L24 to L25 -> L28 [0] lasti
      L26 to L27 -> L28 [0] lasti
    
# co_names: ('__doc__', '__future__', 'annotations', 'uuid', 'datetime', 'UTC', 'fastapi', 'APIRouter', 'Depends', 'Query', 'sqlalchemy', 'func', 'select', 'update', 'sqlalchemy.ext.asyncio', 'AsyncSession', 'app.config', 'settings', 'app.core.dependencies', 'CurrentUser', 'get_current_user', 'app.core.encryption', 'encrypt_field', 'app.core.rate_limiter', 'check_rate_limit', 'app.core.twilio_utils', 'extract_last4', 'hash_phone', 'app.database', 'get_db', 'app.middleware.error_handler', 'AppError', 'app.models.contact_profile', 'ContactProfile', 'app.models.user_settings', 'UserSettings', 'app.schemas.contacts', 'CategoriesListResponse', 'CategoryDefaultsRequest', 'CategoryDefaultsResponse', 'CategoryItem', 'ContactCreateRequest', 'ContactListResponse', 'ContactResponse', 'ContactUpdateRequest', 'CustomCategoryCreateRequest', 'DEFAULT_CATEGORIES', 'app.services.audit_service', 'log_event', 'router', '_DEFAULT_LABELS', '__annotations__', '_get_valid_categories', '_validate_contact_category', '_to_response', 'get', 'list_contacts', 'post', 'create_contact', 'list_categories', 'create_custom_category', 'delete', 'delete_custom_category', 'get_category_defaults', 'put', 'update_category_defaults', 'get_contact', 'patch', 'update_contact', 'delete_contact')
# co_varnames: ()
  0           RESUME                   0

  1           SETUP_ANNOTATIONS
              LOAD_CONST               0 ('Contact profiles API: CRUD + category defaults + custom categories.')
              STORE_NAME               0 (__doc__)

  3           LOAD_CONST               1 (0)
              LOAD_CONST               2 (('annotations',))
              IMPORT_NAME              1 (__future__)
              IMPORT_FROM              2 (annotations)
              STORE_NAME               2 (annotations)
              POP_TOP

  5           LOAD_CONST               1 (0)
              LOAD_CONST               3 (None)
              IMPORT_NAME              3 (uuid)
              STORE_NAME               3 (uuid)

  6           LOAD_CONST               1 (0)
              LOAD_CONST               4 (('UTC', 'datetime'))
              IMPORT_NAME              4 (datetime)
              IMPORT_FROM              5 (UTC)
              STORE_NAME               5 (UTC)
              IMPORT_FROM              4 (datetime)
              STORE_NAME               4 (datetime)
              POP_TOP

  8           LOAD_CONST               1 (0)
              LOAD_CONST               5 (('APIRouter', 'Depends', 'Query'))
              IMPORT_NAME              6 (fastapi)
              IMPORT_FROM              7 (APIRouter)
              STORE_NAME               7 (APIRouter)
              IMPORT_FROM              8 (Depends)
              STORE_NAME               8 (Depends)
              IMPORT_FROM              9 (Query)
              STORE_NAME               9 (Query)
              POP_TOP

  9           LOAD_CONST               1 (0)
              LOAD_CONST               6 (('func', 'select', 'update'))
              IMPORT_NAME             10 (sqlalchemy)
              IMPORT_FROM             11 (func)
              STORE_NAME              11 (func)
              IMPORT_FROM             12 (select)
              STORE_NAME              12 (select)
              IMPORT_FROM             13 (update)
              STORE_NAME              13 (update)
              POP_TOP

 10           LOAD_CONST               1 (0)
              LOAD_CONST               7 (('AsyncSession',))
              IMPORT_NAME             14 (sqlalchemy.ext.asyncio)
              IMPORT_FROM             15 (AsyncSession)
              STORE_NAME              15 (AsyncSession)
              POP_TOP

 12           LOAD_CONST               1 (0)
              LOAD_CONST               8 (('settings',))
              IMPORT_NAME             16 (app.config)
              IMPORT_FROM             17 (settings)
              STORE_NAME              17 (settings)
              POP_TOP

 13           LOAD_CONST               1 (0)
              LOAD_CONST               9 (('CurrentUser', 'get_current_user'))
              IMPORT_NAME             18 (app.core.dependencies)
              IMPORT_FROM             19 (CurrentUser)
              STORE_NAME              19 (CurrentUser)
              IMPORT_FROM             20 (get_current_user)
              STORE_NAME              20 (get_current_user)
              POP_TOP

 14           LOAD_CONST               1 (0)
              LOAD_CONST              10 (('encrypt_field',))
              IMPORT_NAME             21 (app.core.encryption)
              IMPORT_FROM             22 (encrypt_field)
              STORE_NAME              22 (encrypt_field)
              POP_TOP

 15           LOAD_CONST               1 (0)
              LOAD_CONST              11 (('check_rate_limit',))
              IMPORT_NAME             23 (app.core.rate_limiter)
              IMPORT_FROM             24 (check_rate_limit)
              STORE_NAME              24 (check_rate_limit)
              POP_TOP

 16           LOAD_CONST               1 (0)
              LOAD_CONST              12 (('extract_last4', 'hash_phone'))
              IMPORT_NAME             25 (app.core.twilio_utils)
              IMPORT_FROM             26 (extract_last4)
              STORE_NAME              26 (extract_last4)
              IMPORT_FROM             27 (hash_phone)
              STORE_NAME              27 (hash_phone)
              POP_TOP

 17           LOAD_CONST               1 (0)
              LOAD_CONST              13 (('get_db',))
              IMPORT_NAME             28 (app.database)
              IMPORT_FROM             29 (get_db)
              STORE_NAME              29 (get_db)
              POP_TOP

 18           LOAD_CONST               1 (0)
              LOAD_CONST              14 (('AppError',))
              IMPORT_NAME             30 (app.middleware.error_handler)
              IMPORT_FROM             31 (AppError)
              STORE_NAME              31 (AppError)
              POP_TOP

 19           LOAD_CONST               1 (0)
              LOAD_CONST              15 (('ContactProfile',))
              IMPORT_NAME             32 (app.models.contact_profile)
              IMPORT_FROM             33 (ContactProfile)
              STORE_NAME              33 (ContactProfile)
              POP_TOP

 20           LOAD_CONST               1 (0)
              LOAD_CONST              16 (('UserSettings',))
              IMPORT_NAME             34 (app.models.user_settings)
              IMPORT_FROM             35 (UserSettings)
              STORE_NAME              35 (UserSettings)
              POP_TOP

 21           LOAD_CONST               1 (0)
              LOAD_CONST              17 (('CategoriesListResponse', 'CategoryDefaultsRequest', 'CategoryDefaultsResponse', 'CategoryItem', 'ContactCreateRequest', 'ContactListResponse', 'ContactResponse', 'ContactUpdateRequest', 'CustomCategoryCreateRequest', 'DEFAULT_CATEGORIES'))
              IMPORT_NAME             36 (app.schemas.contacts)
              IMPORT_FROM             37 (CategoriesListResponse)
              STORE_NAME              37 (CategoriesListResponse)
              IMPORT_FROM             38 (CategoryDefaultsRequest)
              STORE_NAME              38 (CategoryDefaultsRequest)
              IMPORT_FROM             39 (CategoryDefaultsResponse)
              STORE_NAME              39 (CategoryDefaultsResponse)
              IMPORT_FROM             40 (CategoryItem)
              STORE_NAME              40 (CategoryItem)
              IMPORT_FROM             41 (ContactCreateRequest)
              STORE_NAME              41 (ContactCreateRequest)
              IMPORT_FROM             42 (ContactListResponse)
              STORE_NAME              42 (ContactListResponse)
              IMPORT_FROM             43 (ContactResponse)
              STORE_NAME              43 (ContactResponse)
              IMPORT_FROM             44 (ContactUpdateRequest)
              STORE_NAME              44 (ContactUpdateRequest)
              IMPORT_FROM             45 (CustomCategoryCreateRequest)
              STORE_NAME              45 (CustomCategoryCreateRequest)
              IMPORT_FROM             46 (DEFAULT_CATEGORIES)
              STORE_NAME              46 (DEFAULT_CATEGORIES)
              POP_TOP

 33           LOAD_CONST               1 (0)
              LOAD_CONST              18 (('log_event',))
              IMPORT_NAME             47 (app.services.audit_service)
              IMPORT_FROM             48 (log_event)
              STORE_NAME              48 (log_event)
              POP_TOP

 35           LOAD_NAME                7 (APIRouter)
              PUSH_NULL
              CALL                     0
              STORE_NAME              49 (router)

 38           LOAD_CONST              19 ('Business')

 39           LOAD_CONST              20 ('Clients')

 40           LOAD_CONST              21 ('Colleagues')

 41           LOAD_CONST              22 ('Friends')

 42           LOAD_CONST              23 ('Family')

 43           LOAD_CONST              24 ('Healthcare')

 44           LOAD_CONST              25 ('Vendors')

 45           LOAD_CONST              26 ('Acquaintances')

 46           LOAD_CONST              27 ('Other')

 37           LOAD_CONST              28 (('business', 'clients', 'colleagues', 'friends', 'family', 'healthcare', 'vendors', 'acquaintances', 'other'))
              BUILD_CONST_KEY_MAP      9
              STORE_NAME              50 (_DEFAULT_LABELS)
              LOAD_CONST              29 ('dict[str, str]')
              LOAD_NAME               51 (__annotations__)
              LOAD_CONST              30 ('_DEFAULT_LABELS')
              STORE_SUBSCR

 50           LOAD_CONST              52 (('db', 'AsyncSession', 'user_id', 'uuid.UUID', 'return', 'set[str]'))
              LOAD_CONST              31 (<code object _get_valid_categories at 0x0000024C0EC2F830, file "D:\fluence\Github\mattbot\backend\app\api\v1\contacts.py", line 50>)
              MAKE_FUNCTION
              SET_FUNCTION_ATTRIBUTE   4 (annotations)
              STORE_NAME              52 (_get_valid_categories)

 57           NOP

 58           NOP

 57           NOP

 58           NOP

 57           NOP

 58           NOP

 57           NOP

 59           NOP

 57           LOAD_CONST              53 (('db', 'AsyncSession', 'user_id', 'uuid.UUID', 'category', 'str', 'return', 'None'))
              LOAD_CONST              32 (<code object _validate_contact_category at 0x0000024C0EF13CC0, file "D:\fluence\Github\mattbot\backend\app\api\v1\contacts.py", line 57>)
              MAKE_FUNCTION
              SET_FUNCTION_ATTRIBUTE   4 (annotations)
              STORE_NAME              53 (_validate_contact_category)

 69           LOAD_CONST              54 (('c', 'ContactProfile', 'return', 'ContactResponse'))
              LOAD_CONST              33 (<code object _to_response at 0x0000024C0F1FD920, file "D:\fluence\Github\mattbot\backend\app\api\v1\contacts.py", line 69>)
              MAKE_FUNCTION
              SET_FUNCTION_ATTRIBUTE   4 (annotations)
              STORE_NAME              54 (_to_response)

 93           LOAD_NAME               49 (router)
              LOAD_ATTR              111 (get + NULL|self)
              LOAD_CONST              34 ('')
              LOAD_NAME               42 (ContactListResponse)
              LOAD_CONST              35 (('response_model',))
              CALL_KW                  2

 95           LOAD_NAME                9 (Query)
              PUSH_NULL
              LOAD_CONST               3 (None)
              CALL                     1

 96           LOAD_NAME                9 (Query)
              PUSH_NULL
              LOAD_CONST               3 (None)
              CALL                     1

 97           LOAD_NAME                9 (Query)
              PUSH_NULL
              LOAD_CONST               3 (None)
              CALL                     1

 98           LOAD_NAME                8 (Depends)
              PUSH_NULL
              LOAD_NAME               20 (get_current_user)
              CALL                     1

 99           LOAD_NAME                8 (Depends)
              PUSH_NULL
              LOAD_NAME               29 (get_db)
              CALL                     1

 94           BUILD_TUPLE              5

 95           NOP

 94           NOP

 96           NOP

 94           NOP

 97           NOP

 94           NOP

 98           NOP

 94           NOP

 99           NOP

 94           NOP

100           NOP

 94           LOAD_CONST              55 (('category', 'str | None', 'is_vip', 'bool | None', 'is_blocked', 'bool | None', 'current_user', 'CurrentUser', 'db', 'AsyncSession', 'return', 'ContactListResponse'))
              LOAD_CONST              36 (<code object list_contacts at 0x0000024C0FB5D6D0, file "D:\fluence\Github\mattbot\backend\app\api\v1\contacts.py", line 93>)
              MAKE_FUNCTION
              SET_FUNCTION_ATTRIBUTE   4 (annotations)
              SET_FUNCTION_ATTRIBUTE   1 (defaults)

 93           CALL                     0

 94           STORE_NAME              56 (list_contacts)

135           LOAD_NAME               49 (router)
              LOAD_ATTR              115 (post + NULL|self)
              LOAD_CONST              34 ('')
              LOAD_NAME               43 (ContactResponse)
              LOAD_CONST              37 (201)
              LOAD_CONST              38 (('response_model', 'status_code'))
              CALL_KW                  3

138           LOAD_NAME                8 (Depends)
              PUSH_NULL
              LOAD_NAME               20 (get_current_user)
              CALL                     1

139           LOAD_NAME                8 (Depends)
              PUSH_NULL
              LOAD_NAME               29 (get_db)
              CALL                     1

136           BUILD_TUPLE              2

137           NOP

136           NOP

138           NOP

136           NOP

139           NOP

136           NOP

140           NOP

136           LOAD_CONST              56 (('body', 'ContactCreateRequest', 'current_user', 'CurrentUser', 'db', 'AsyncSession', 'return', 'ContactResponse'))
              LOAD_CONST              39 (<code object create_contact at 0x0000024C0FBE3190, file "D:\fluence\Github\mattbot\backend\app\api\v1\contacts.py", line 135>)
              MAKE_FUNCTION
              SET_FUNCTION_ATTRIBUTE   4 (annotations)
              SET_FUNCTION_ATTRIBUTE   1 (defaults)

135           CALL                     0

136           STORE_NAME              58 (create_contact)

221           LOAD_NAME               49 (router)
              LOAD_ATTR              111 (get + NULL|self)
              LOAD_CONST              40 ('/categories')
              LOAD_NAME               37 (CategoriesListResponse)
              LOAD_CONST              35 (('response_model',))
              CALL_KW                  2

223           LOAD_NAME                8 (Depends)
              PUSH_NULL
              LOAD_NAME               20 (get_current_user)
              CALL                     1

224           LOAD_NAME                8 (Depends)
              PUSH_NULL
              LOAD_NAME               29 (get_db)
              CALL                     1

222           BUILD_TUPLE              2

223           NOP

222           NOP

224           NOP

222           NOP

225           NOP

222           LOAD_CONST              57 (('current_user', 'CurrentUser', 'db', 'AsyncSession', 'return', 'CategoriesListResponse'))
              LOAD_CONST              41 (<code object list_categories at 0x0000024C0FBE4020, file "D:\fluence\Github\mattbot\backend\app\api\v1\contacts.py", line 221>)
              MAKE_FUNCTION
              SET_FUNCTION_ATTRIBUTE   4 (annotations)
              SET_FUNCTION_ATTRIBUTE   1 (defaults)

221           CALL                     0

222           STORE_NAME              59 (list_categories)

247           LOAD_NAME               49 (router)
              LOAD_ATTR              115 (post + NULL|self)
              LOAD_CONST              40 ('/categories')
              LOAD_NAME               40 (CategoryItem)
              LOAD_CONST              37 (201)
              LOAD_CONST              38 (('response_model', 'status_code'))
              CALL_KW                  3

250           LOAD_NAME                8 (Depends)
              PUSH_NULL
              LOAD_NAME               20 (get_current_user)
              CALL                     1

251           LOAD_NAME                8 (Depends)
              PUSH_NULL
              LOAD_NAME               29 (get_db)
              CALL                     1

248           BUILD_TUPLE              2

249           NOP

248           NOP

250           NOP

248           NOP

251           NOP

248           NOP

252           NOP

248           LOAD_CONST              58 (('body', 'CustomCategoryCreateRequest', 'current_user', 'CurrentUser', 'db', 'AsyncSession', 'return', 'CategoryItem'))
              LOAD_CONST              42 (<code object create_custom_category at 0x0000024C0FB40D60, file "D:\fluence\Github\mattbot\backend\app\api\v1\contacts.py", line 247>)
              MAKE_FUNCTION
              SET_FUNCTION_ATTRIBUTE   4 (annotations)
              SET_FUNCTION_ATTRIBUTE   1 (defaults)

247           CALL                     0

248           STORE_NAME              60 (create_custom_category)

295           LOAD_NAME               49 (router)
              LOAD_ATTR              123 (delete + NULL|self)
              LOAD_CONST              43 ('/categories/{slug}')
              CALL                     1

298           LOAD_NAME                8 (Depends)
              PUSH_NULL
              LOAD_NAME               20 (get_current_user)
              CALL                     1

299           LOAD_NAME                8 (Depends)
              PUSH_NULL
              LOAD_NAME               29 (get_db)
              CALL                     1

296           BUILD_TUPLE              2

297           NOP

296           NOP

298           NOP

296           NOP

299           NOP

296           NOP

300           NOP

296           LOAD_CONST              59 (('slug', 'str', 'current_user', 'CurrentUser', 'db', 'AsyncSession', 'return', 'dict'))
              LOAD_CONST              44 (<code object delete_custom_category at 0x0000024C0FBDD460, file "D:\fluence\Github\mattbot\backend\app\api\v1\contacts.py", line 295>)
              MAKE_FUNCTION
              SET_FUNCTION_ATTRIBUTE   4 (annotations)
              SET_FUNCTION_ATTRIBUTE   1 (defaults)

295           CALL                     0

296           STORE_NAME              62 (delete_custom_category)

355           LOAD_NAME               49 (router)
              LOAD_ATTR              111 (get + NULL|self)
              LOAD_CONST              45 ('/categories/defaults')
              LOAD_NAME               39 (CategoryDefaultsResponse)
              LOAD_CONST              35 (('response_model',))
              CALL_KW                  2

357           LOAD_NAME                8 (Depends)
              PUSH_NULL
              LOAD_NAME               20 (get_current_user)
              CALL                     1

358           LOAD_NAME                8 (Depends)
              PUSH_NULL
              LOAD_NAME               29 (get_db)
              CALL                     1

356           BUILD_TUPLE              2

357           NOP

356           NOP

358           NOP

356           NOP

359           NOP

356           LOAD_CONST              60 (('current_user', 'CurrentUser', 'db', 'AsyncSession', 'return', 'CategoryDefaultsResponse'))
              LOAD_CONST              46 (<code object get_category_defaults at 0x0000024C0EC47330, file "D:\fluence\Github\mattbot\backend\app\api\v1\contacts.py", line 355>)
              MAKE_FUNCTION
              SET_FUNCTION_ATTRIBUTE   4 (annotations)
              SET_FUNCTION_ATTRIBUTE   1 (defaults)

355           CALL                     0

356           STORE_NAME              63 (get_category_defaults)

365           LOAD_NAME               49 (router)
              LOAD_ATTR              129 (put + NULL|self)
              LOAD_CONST              45 ('/categories/defaults')
              LOAD_NAME               39 (CategoryDefaultsResponse)
              LOAD_CONST              35 (('response_model',))
              CALL_KW                  2

368           LOAD_NAME                8 (Depends)
              PUSH_NULL
              LOAD_NAME               20 (get_current_user)
              CALL                     1

369           LOAD_NAME                8 (Depends)
              PUSH_NULL
              LOAD_NAME               29 (get_db)
              CALL                     1

366           BUILD_TUPLE              2

367           NOP

366           NOP

368           NOP

366           NOP

369           NOP

366           NOP

370           NOP

366           LOAD_CONST              61 (('body', 'CategoryDefaultsRequest', 'current_user', 'CurrentUser', 'db', 'AsyncSession', 'return', 'CategoryDefaultsResponse'))
              LOAD_CONST              47 (<code object update_category_defaults at 0x0000024C0FBDD9B0, file "D:\fluence\Github\mattbot\backend\app\api\v1\contacts.py", line 365>)
              MAKE_FUNCTION
              SET_FUNCTION_ATTRIBUTE   4 (annotations)
              SET_FUNCTION_ATTRIBUTE   1 (defaults)

365           CALL                     0

366           STORE_NAME              65 (update_category_defaults)

401           LOAD_NAME               49 (router)
              LOAD_ATTR              111 (get + NULL|self)
              LOAD_CONST              48 ('/{contact_id}')
              LOAD_NAME               43 (ContactResponse)
              LOAD_CONST              35 (('response_model',))
              CALL_KW                  2

404           LOAD_NAME                8 (Depends)
              PUSH_NULL
              LOAD_NAME               20 (get_current_user)
              CALL                     1

405           LOAD_NAME                8 (Depends)
              PUSH_NULL
              LOAD_NAME               29 (get_db)
              CALL                     1

402           BUILD_TUPLE              2

403           NOP

402           NOP

404           NOP

402           NOP

405           NOP

402           NOP

406           NOP

402           LOAD_CONST              62 (('contact_id', 'uuid.UUID', 'current_user', 'CurrentUser', 'db', 'AsyncSession', 'return', 'ContactResponse'))
              LOAD_CONST              49 (<code object get_contact at 0x0000024C0FBC7910, file "D:\fluence\Github\mattbot\backend\app\api\v1\contacts.py", line 401>)
              MAKE_FUNCTION
              SET_FUNCTION_ATTRIBUTE   4 (annotations)
              SET_FUNCTION_ATTRIBUTE   1 (defaults)

401           CALL                     0

402           STORE_NAME              66 (get_contact)

421           LOAD_NAME               49 (router)
              LOAD_ATTR              135 (patch + NULL|self)
              LOAD_CONST              48 ('/{contact_id}')
              LOAD_NAME               43 (ContactResponse)
              LOAD_CONST              35 (('response_model',))
              CALL_KW                  2

425           LOAD_NAME                8 (Depends)
              PUSH_NULL
              LOAD_NAME               20 (get_current_user)
              CALL                     1

426           LOAD_NAME                8 (Depends)
              PUSH_NULL
              LOAD_NAME               29 (get_db)
              CALL                     1

422           BUILD_TUPLE              2

423           NOP

422           NOP

424           NOP

422           NOP

425           NOP

422           NOP

426           NOP

422           NOP

427           NOP

422           LOAD_CONST              63 (('contact_id', 'uuid.UUID', 'body', 'ContactUpdateRequest', 'current_user', 'CurrentUser', 'db', 'AsyncSession', 'return', 'ContactResponse'))
              LOAD_CONST              50 (<code object update_contact at 0x0000024C0FBDCD10, file "D:\fluence\Github\mattbot\backend\app\api\v1\contacts.py", line 421>)
              MAKE_FUNCTION
              SET_FUNCTION_ATTRIBUTE   4 (annotations)
              SET_FUNCTION_ATTRIBUTE   1 (defaults)

421           CALL                     0

422           STORE_NAME              68 (update_contact)

495           LOAD_NAME               49 (router)
              LOAD_ATTR              123 (delete + NULL|self)
              LOAD_CONST              48 ('/{contact_id}')
              CALL                     1

498           LOAD_NAME                8 (Depends)
              PUSH_NULL
              LOAD_NAME               20 (get_current_user)
              CALL                     1

499           LOAD_NAME                8 (Depends)
              PUSH_NULL
              LOAD_NAME               29 (get_db)
              CALL                     1

496           BUILD_TUPLE              2

497           NOP

496           NOP

498           NOP

496           NOP

499           NOP

496           NOP

500           NOP

496           LOAD_CONST              64 (('contact_id', 'uuid.UUID', 'current_user', 'CurrentUser', 'db', 'AsyncSession', 'return', 'dict'))
              LOAD_CONST              51 (<code object delete_contact at 0x0000024C0FA8F3A0, file "D:\fluence\Github\mattbot\backend\app\api\v1\contacts.py", line 495>)
              MAKE_FUNCTION
              SET_FUNCTION_ATTRIBUTE   4 (annotations)
              SET_FUNCTION_ATTRIBUTE   1 (defaults)

495           CALL                     0

496           STORE_NAME              69 (delete_contact)
              RETURN_CONST             3 (None)

Disassembly of <code object _get_valid_categories at 0x0000024C0EC2F830, file "D:\fluence\Github\mattbot\backend\app\api\v1\contacts.py", line 50>:
  50            RETURN_GENERATOR
                POP_TOP
        L1:     RESUME                   0

  52            LOAD_FAST                0 (db)
                LOAD_ATTR                1 (get + NULL|self)
                LOAD_GLOBAL              2 (UserSettings)
                LOAD_FAST                1 (user_id)
                CALL                     2
                GET_AWAITABLE            0
                LOAD_CONST               1 (None)
        L2:     SEND                     3 (to L5)
        L3:     YIELD_VALUE              1
        L4:     RESUME                   3
                JUMP_BACKWARD_NO_INTERRUPT 5 (to L2)
        L5:     END_SEND
                STORE_FAST               2 (row)

  53            LOAD_FAST                2 (row)
                TO_BOOL
                POP_JUMP_IF_FALSE       12 (to L6)
                LOAD_FAST                2 (row)
                LOAD_ATTR                4 (custom_contact_categories)
                JUMP_FORWARD             1 (to L7)
        L6:     BUILD_LIST               0
        L7:     STORE_FAST               3 (custom)

  54            LOAD_GLOBAL              6 (DEFAULT_CATEGORIES)
                LOAD_FAST                3 (custom)
                GET_ITER
                LOAD_FAST_AND_CLEAR      4 (entry)
                SWAP                     2
        L8:     BUILD_SET                0
                SWAP                     2
                GET_ITER
        L9:     FOR_ITER                39 (to L14)
                STORE_FAST               4 (entry)
                LOAD_GLOBAL              9 (isinstance + NULL)
                LOAD_FAST                4 (entry)
                LOAD_GLOBAL             10 (dict)
                CALL                     2
                TO_BOOL
       L10:     POP_JUMP_IF_TRUE         2 (to L11)
                JUMP_BACKWARD           26 (to L9)
       L11:     LOAD_CONST               2 ('slug')
                LOAD_FAST                4 (entry)
                CONTAINS_OP              0
       L12:     POP_JUMP_IF_TRUE         2 (to L13)
                JUMP_BACKWARD           34 (to L9)
       L13:     LOAD_FAST                4 (entry)
                LOAD_CONST               2 ('slug')
                BINARY_SUBSCR
                SET_ADD                  2
                JUMP_BACKWARD           41 (to L9)
       L14:     END_FOR
                POP_TOP
       L15:     SWAP                     2
                STORE_FAST               4 (entry)
                BINARY_OP                7 (|)
                RETURN_VALUE

  52   L16:     CLEANUP_THROW
       L17:     JUMP_BACKWARD_NO_INTERRUPT 85 (to L5)

  --   L18:     SWAP                     2
                POP_TOP

  54            SWAP                     2
                STORE_FAST               4 (entry)
                RERAISE                  0

  --   L19:     CALL_INTRINSIC_1         3 (INTRINSIC_STOPITERATION_ERROR)
                RERAISE                  1
ExceptionTable:
  L1 to L3 -> L19 [0] lasti
  L3 to L4 -> L16 [2]
  L4 to L8 -> L19 [0] lasti
  L8 to L10 -> L18 [3]
  L11 to L12 -> L18 [3]
  L13 to L15 -> L18 [3]
  L15 to L17 -> L19 [0] lasti
  L18 to L19 -> L19 [0] lasti

Disassembly of <code object _validate_contact_category at 0x0000024C0EF13CC0, file "D:\fluence\Github\mattbot\backend\app\api\v1\contacts.py", line 57>:
  57           RETURN_GENERATOR
               POP_TOP
       L1:     RESUME                   0

  60           LOAD_GLOBAL              1 (_get_valid_categories + NULL)
               LOAD_FAST_LOAD_FAST      1 (db, user_id)
               CALL                     2
               GET_AWAITABLE            0
               LOAD_CONST               0 (None)
       L2:     SEND                     3 (to L5)
       L3:     YIELD_VALUE              1
       L4:     RESUME                   3
               JUMP_BACKWARD_NO_INTERRUPT 5 (to L2)
       L5:     END_SEND
               STORE_FAST               3 (valid)

  61           LOAD_FAST_LOAD_FAST     35 (category, valid)
               CONTAINS_OP              1
               POP_JUMP_IF_FALSE       15 (to L6)

  62           LOAD_GLOBAL              3 (AppError + NULL)

  63           LOAD_CONST               1 ('UNKNOWN_CATEGORY')

  64           LOAD_CONST               2 ("Unknown category '")
               LOAD_FAST                2 (category)
               FORMAT_SIMPLE
               LOAD_CONST               3 ("'. Create it first or use one of the defaults.")
               BUILD_STRING             3

  65           LOAD_CONST               4 (409)

  62           LOAD_CONST               5 (('code', 'message', 'status_code'))
               CALL_KW                  3
               RAISE_VARARGS            1

  61   L6:     RETURN_CONST             0 (None)

  60   L7:     CLEANUP_THROW
       L8:     JUMP_BACKWARD_NO_INTERRUPT 25 (to L5)

  --   L9:     CALL_INTRINSIC_1         3 (INTRINSIC_STOPITERATION_ERROR)
               RERAISE                  1
ExceptionTable:
  L1 to L3 -> L9 [0] lasti
  L3 to L4 -> L7 [2]
  L4 to L8 -> L9 [0] lasti

Disassembly of <code object _to_response at 0x0000024C0F1FD920, file "D:\fluence\Github\mattbot\backend\app\api\v1\contacts.py", line 69>:
 69           RESUME                   0

 70           LOAD_GLOBAL              1 (ContactResponse + NULL)
              LOAD_CONST              20 (())
              BUILD_MAP                0
              LOAD_CONST               1 ('id')

 71           LOAD_GLOBAL              3 (str + NULL)
              LOAD_FAST                0 (c)
              LOAD_ATTR                4 (id)
              CALL                     1
              MAP_ADD                  1

 70           LOAD_CONST               2 ('phone_last4')

 72           LOAD_FAST                0 (c)
              LOAD_ATTR                6 (phone_last4)
              MAP_ADD                  1

 70           LOAD_CONST               3 ('display_name')

 73           LOAD_FAST                0 (c)
              LOAD_ATTR                8 (display_name)
              MAP_ADD                  1

 70           LOAD_CONST               4 ('company')

 74           LOAD_FAST                0 (c)
              LOAD_ATTR               10 (company)
              MAP_ADD                  1

 70           LOAD_CONST               5 ('relationship')

 75           LOAD_FAST                0 (c)
              LOAD_ATTR               12 (relationship)
              MAP_ADD                  1

 70           LOAD_CONST               6 ('email')

 76           LOAD_FAST                0 (c)
              LOAD_ATTR               14 (email)
              MAP_ADD                  1

 70           LOAD_CONST               7 ('notes')

 77           LOAD_FAST                0 (c)
              LOAD_ATTR               16 (notes)
              MAP_ADD                  1

 70           LOAD_CONST               8 ('category')

 78           LOAD_FAST                0 (c)
              LOAD_ATTR               18 (category)
              MAP_ADD                  1

 70           LOAD_CONST               9 ('is_vip')

 79           LOAD_FAST                0 (c)
              LOAD_ATTR               20 (is_vip)
              MAP_ADD                  1

 70           LOAD_CONST              10 ('is_blocked')

 80           LOAD_FAST                0 (c)
              LOAD_ATTR               22 (is_blocked)
              MAP_ADD                  1

 70           LOAD_CONST              11 ('block_reason')

 81           LOAD_FAST                0 (c)
              LOAD_ATTR               24 (block_reason)
              MAP_ADD                  1

 70           LOAD_CONST              12 ('ai_temperament_preset')

 82           LOAD_FAST                0 (c)
              LOAD_ATTR               26 (ai_temperament_preset)
              MAP_ADD                  1

 70           LOAD_CONST              13 ('ai_greeting_template')

 83           LOAD_FAST                0 (c)
              LOAD_ATTR               28 (ai_greeting_template)
              MAP_ADD                  1

 70           LOAD_CONST              14 ('ai_swearing_rule')

 84           LOAD_FAST                0 (c)
              LOAD_ATTR               30 (ai_swearing_rule)
              MAP_ADD                  1

 70           LOAD_CONST              15 ('ai_max_call_length_seconds')

 85           LOAD_FAST                0 (c)
              LOAD_ATTR               32 (ai_max_call_length_seconds)
              MAP_ADD                  1

 70           LOAD_CONST              16 ('has_custom_greeting')

 86           LOAD_FAST                0 (c)
              LOAD_ATTR               34 (ai_greeting_instructions_ciphertext)
              LOAD_CONST               0 (None)
              IS_OP                    1
              MAP_ADD                  1

 70           LOAD_CONST              17 ('has_custom_instructions')

 87           LOAD_FAST                0 (c)
              LOAD_ATTR               36 (ai_custom_instructions_ciphertext)
              LOAD_CONST               0 (None)
              IS_OP                    1
              MAP_ADD                  1

 70           LOAD_CONST              18 ('created_at')

 88           LOAD_FAST                0 (c)
              LOAD_ATTR               38 (created_at)
              MAP_ADD                  1

 70           LOAD_CONST              19 ('updated_at')

 89           LOAD_FAST                0 (c)
              LOAD_ATTR               40 (updated_at)
              MAP_ADD                  1

 70           CALL_FUNCTION_EX         1
              RETURN_VALUE

Disassembly of <code object list_contacts at 0x0000024C0FB5D6D0, file "D:\fluence\Github\mattbot\backend\app\api\v1\contacts.py", line 93>:
  93            RETURN_GENERATOR
                POP_TOP
        L1:     RESUME                   0

 101            LOAD_GLOBAL              1 (check_rate_limit + NULL)

 102            LOAD_CONST               1 ('contacts:list:')
                LOAD_FAST                3 (current_user)
                LOAD_ATTR                2 (user)
                LOAD_ATTR                4 (id)
                FORMAT_SIMPLE
                BUILD_STRING             2

 103            LOAD_GLOBAL              6 (settings)
                LOAD_ATTR                8 (RATE_LIMIT_API_STANDARD_MAX)

 104            LOAD_GLOBAL              6 (settings)
                LOAD_ATTR               10 (RATE_LIMIT_API_STANDARD_WINDOW)

 101            LOAD_CONST               2 (('max_requests', 'window_seconds'))
                CALL_KW                  3
                GET_AWAITABLE            0
                LOAD_CONST               0 (None)
        L2:     SEND                     3 (to L5)
        L3:     YIELD_VALUE              1
        L4:     RESUME                   3
                JUMP_BACKWARD_NO_INTERRUPT 5 (to L2)
        L5:     END_SEND
                UNPACK_SEQUENCE          2
                STORE_FAST_STORE_FAST   86 (allowed, _)

 106            LOAD_FAST                5 (allowed)
                TO_BOOL
                POP_JUMP_IF_TRUE        11 (to L6)

 107            LOAD_GLOBAL             13 (AppError + NULL)
                LOAD_CONST               3 ('RATE_LIMITED')
                LOAD_CONST               4 ('Too many requests')
                LOAD_CONST               5 (429)
                LOAD_CONST               6 (('code', 'message', 'status_code'))
                CALL_KW                  3
                RAISE_VARARGS            1

 110    L6:     LOAD_GLOBAL             14 (ContactProfile)
                LOAD_ATTR               16 (owner_user_id)
                LOAD_FAST                3 (current_user)
                LOAD_ATTR                2 (user)
                LOAD_ATTR                4 (id)
                COMPARE_OP              72 (==)

 111            LOAD_GLOBAL             14 (ContactProfile)
                LOAD_ATTR               18 (deleted_at)
                LOAD_ATTR               21 (is_ + NULL|self)
                LOAD_CONST               0 (None)
                CALL                     1

 109            BUILD_LIST               2
                STORE_FAST               7 (filters)

 113            LOAD_FAST                0 (category)
                POP_JUMP_IF_NONE        34 (to L7)

 114            LOAD_FAST                7 (filters)
                LOAD_ATTR               23 (append + NULL|self)
                LOAD_GLOBAL             14 (ContactProfile)
                LOAD_ATTR               24 (category)
                LOAD_FAST                0 (category)
                COMPARE_OP              72 (==)
                CALL                     1
                POP_TOP

 115    L7:     LOAD_FAST                1 (is_vip)
                POP_JUMP_IF_NONE        34 (to L8)

 116            LOAD_FAST                7 (filters)
                LOAD_ATTR               23 (append + NULL|self)
                LOAD_GLOBAL             14 (ContactProfile)
                LOAD_ATTR               26 (is_vip)
                LOAD_FAST                1 (is_vip)
                COMPARE_OP              72 (==)
                CALL                     1
                POP_TOP

 117    L8:     LOAD_FAST                2 (is_blocked)
                POP_JUMP_IF_NONE        34 (to L9)

 118            LOAD_FAST                7 (filters)
                LOAD_ATTR               23 (append + NULL|self)
                LOAD_GLOBAL             14 (ContactProfile)
                LOAD_ATTR               28 (is_blocked)
                LOAD_FAST                2 (is_blocked)
                COMPARE_OP              72 (==)
                CALL                     1
                POP_TOP

 120    L9:     LOAD_FAST                4 (db)
                LOAD_ATTR               31 (execute + NULL|self)

 121            LOAD_GLOBAL             33 (select + NULL)
                LOAD_GLOBAL             34 (func)
                LOAD_ATTR               36 (count)
                PUSH_NULL
                CALL                     0
                CALL                     1
                LOAD_ATTR               39 (select_from + NULL|self)
                LOAD_GLOBAL             14 (ContactProfile)
                CALL                     1
                LOAD_ATTR               40 (where)
                PUSH_NULL
                LOAD_FAST                7 (filters)
                CALL_FUNCTION_EX         0

 120            CALL                     1
                GET_AWAITABLE            0
                LOAD_CONST               0 (None)
       L10:     SEND                     3 (to L13)
       L11:     YIELD_VALUE              1
       L12:     RESUME                   3
                JUMP_BACKWARD_NO_INTERRUPT 5 (to L10)
       L13:     END_SEND
                STORE_FAST               8 (count_result)

 123            LOAD_FAST                8 (count_result)
                LOAD_ATTR               43 (scalar + NULL|self)
                CALL                     0
                COPY                     1
                TO_BOOL
                POP_JUMP_IF_TRUE         2 (to L14)
                POP_TOP
                LOAD_CONST               7 (0)
       L14:     STORE_FAST               9 (total)

 126            LOAD_GLOBAL             33 (select + NULL)
                LOAD_GLOBAL             14 (ContactProfile)
                CALL                     1
                LOAD_ATTR               40 (where)
                PUSH_NULL
                LOAD_FAST                7 (filters)
                CALL_FUNCTION_EX         0

 127            LOAD_ATTR               45 (order_by + NULL|self)
                LOAD_GLOBAL             14 (ContactProfile)
                LOAD_ATTR               46 (display_name)
                LOAD_ATTR               49 (asc + NULL|self)
                CALL                     0
                LOAD_ATTR               51 (nulls_last + NULL|self)
                CALL                     0
                LOAD_GLOBAL             14 (ContactProfile)
                LOAD_ATTR               52 (created_at)
                LOAD_ATTR               55 (desc + NULL|self)
                CALL                     0
                CALL                     2

 125            STORE_FAST              10 (stmt)

 129            LOAD_FAST                4 (db)
                LOAD_ATTR               31 (execute + NULL|self)
                LOAD_FAST               10 (stmt)
                CALL                     1
                GET_AWAITABLE            0
                LOAD_CONST               0 (None)
       L15:     SEND                     3 (to L18)
       L16:     YIELD_VALUE              1
       L17:     RESUME                   3
                JUMP_BACKWARD_NO_INTERRUPT 5 (to L15)
       L18:     END_SEND
                STORE_FAST              11 (result)

 130            LOAD_FAST               11 (result)
                LOAD_ATTR               57 (scalars + NULL|self)
                CALL                     0
                LOAD_ATTR               59 (all + NULL|self)
                CALL                     0
                GET_ITER
                LOAD_FAST_AND_CLEAR     12 (c)
                SWAP                     2
       L19:     BUILD_LIST               0
                SWAP                     2
                GET_ITER
       L20:     FOR_ITER                14 (to L21)
                STORE_FAST              12 (c)
                LOAD_GLOBAL             61 (_to_response + NULL)
                LOAD_FAST               12 (c)
                CALL                     1
                LIST_APPEND              2
                JUMP_BACKWARD           16 (to L20)
       L21:     END_FOR
                POP_TOP
       L22:     STORE_FAST              13 (items)
                STORE_FAST              12 (c)

 132            LOAD_GLOBAL             63 (ContactListResponse + NULL)
                LOAD_FAST_LOAD_FAST    217 (items, total)
                LOAD_CONST               8 (('items', 'total'))
                CALL_KW                  2
                RETURN_VALUE

 101   L23:     CLEANUP_THROW
       L24:     EXTENDED_ARG             2
                JUMP_BACKWARD_NO_INTERRUPT 519 (to L5)

 120   L25:     CLEANUP_THROW
       L26:     JUMP_BACKWARD_NO_INTERRUPT 235 (to L13)

 129   L27:     CLEANUP_THROW
       L28:     JUMP_BACKWARD_NO_INTERRUPT 73 (to L18)

  --   L29:     SWAP                     2
                POP_TOP

 130            SWAP                     2
                STORE_FAST              12 (c)
                RERAISE                  0

  --   L30:     CALL_INTRINSIC_1         3 (INTRINSIC_STOPITERATION_ERROR)
                RERAISE                  1
ExceptionTable:
  L1 to L3 -> L30 [0] lasti
  L3 to L4 -> L23 [2]
  L4 to L11 -> L30 [0] lasti
  L11 to L12 -> L25 [2]
  L12 to L16 -> L30 [0] lasti
  L16 to L17 -> L27 [2]
  L17 to L19 -> L30 [0] lasti
  L19 to L22 -> L29 [2]
  L22 to L24 -> L30 [0] lasti
  L25 to L26 -> L30 [0] lasti
  L27 to L28 -> L30 [0] lasti
  L29 to L30 -> L30 [0] lasti

Disassembly of <code object create_contact at 0x0000024C0FBE3190, file "D:\fluence\Github\mattbot\backend\app\api\v1\contacts.py", line 135>:
 135            RETURN_GENERATOR
                POP_TOP
        L1:     RESUME                   0

 141            LOAD_GLOBAL              1 (check_rate_limit + NULL)

 142            LOAD_CONST               1 ('contacts:create:')
                LOAD_FAST                1 (current_user)
                LOAD_ATTR                2 (user)
                LOAD_ATTR                4 (id)
                FORMAT_SIMPLE
                BUILD_STRING             2

 143            LOAD_GLOBAL              6 (settings)
                LOAD_ATTR                8 (RATE_LIMIT_API_WRITE_MAX)

 144            LOAD_GLOBAL              6 (settings)
                LOAD_ATTR               10 (RATE_LIMIT_API_WRITE_WINDOW)

 141            LOAD_CONST               2 (('max_requests', 'window_seconds'))
                CALL_KW                  3
                GET_AWAITABLE            0
                LOAD_CONST               0 (None)
        L2:     SEND                     3 (to L5)
        L3:     YIELD_VALUE              1
        L4:     RESUME                   3
                JUMP_BACKWARD_NO_INTERRUPT 5 (to L2)
        L5:     END_SEND
                UNPACK_SEQUENCE          2
                STORE_FAST_STORE_FAST   52 (allowed, _)

 146            LOAD_FAST                3 (allowed)
                TO_BOOL
                POP_JUMP_IF_TRUE        11 (to L6)

 147            LOAD_GLOBAL             13 (AppError + NULL)
                LOAD_CONST               3 ('RATE_LIMITED')
                LOAD_CONST               4 ('Too many requests')
                LOAD_CONST               5 (429)
                LOAD_CONST               6 (('code', 'message', 'status_code'))
                CALL_KW                  3
                RAISE_VARARGS            1

 149    L6:     LOAD_GLOBAL             15 (_validate_contact_category + NULL)
                LOAD_FAST_LOAD_FAST     33 (db, current_user)
                LOAD_ATTR                2 (user)
                LOAD_ATTR                4 (id)
                LOAD_FAST                0 (body)
                LOAD_ATTR               16 (category)
                CALL                     3
                GET_AWAITABLE            0
                LOAD_CONST               0 (None)
        L7:     SEND                     3 (to L10)
        L8:     YIELD_VALUE              1
        L9:     RESUME                   3
                JUMP_BACKWARD_NO_INTERRUPT 5 (to L7)
       L10:     END_SEND
                POP_TOP

 151            LOAD_GLOBAL             19 (hash_phone + NULL)
                LOAD_FAST                0 (body)
                LOAD_ATTR               20 (phone_number)
                CALL                     1
                STORE_FAST               5 (ph)

 152            LOAD_FAST                2 (db)
                LOAD_ATTR               23 (execute + NULL|self)

 153            LOAD_GLOBAL             25 (select + NULL)
                LOAD_GLOBAL             26 (ContactProfile)
                CALL                     1
                LOAD_ATTR               29 (where + NULL|self)

 154            LOAD_GLOBAL             26 (ContactProfile)
                LOAD_ATTR               30 (owner_user_id)
                LOAD_FAST                1 (current_user)
                LOAD_ATTR                2 (user)
                LOAD_ATTR                4 (id)
                COMPARE_OP              72 (==)

 155            LOAD_GLOBAL             26 (ContactProfile)
                LOAD_ATTR               32 (phone_hash)
                LOAD_FAST                5 (ph)
                COMPARE_OP              72 (==)

 156            LOAD_GLOBAL             26 (ContactProfile)
                LOAD_ATTR               34 (deleted_at)
                LOAD_ATTR               37 (is_ + NULL|self)
                LOAD_CONST               0 (None)
                CALL                     1

 153            CALL                     3

 152            CALL                     1
                GET_AWAITABLE            0
                LOAD_CONST               0 (None)
       L11:     SEND                     3 (to L14)
       L12:     YIELD_VALUE              1
       L13:     RESUME                   3
                JUMP_BACKWARD_NO_INTERRUPT 5 (to L11)
       L14:     END_SEND

 158            LOAD_ATTR               39 (scalar_one_or_none + NULL|self)
                CALL                     0

 152            STORE_FAST               6 (existing)

 160            LOAD_FAST                6 (existing)
                POP_JUMP_IF_NONE        11 (to L15)

 161            LOAD_GLOBAL             13 (AppError + NULL)

 162            LOAD_CONST               7 ('CONTACT_DUPLICATE')

 163            LOAD_CONST               8 ('This number already has a contact profile')

 164            LOAD_CONST               9 (409)

 161            LOAD_CONST               6 (('code', 'message', 'status_code'))
                CALL_KW                  3
                RAISE_VARARGS            1

 167   L15:     LOAD_GLOBAL             41 (encrypt_field + NULL)
                LOAD_FAST                0 (body)
                LOAD_ATTR               20 (phone_number)
                LOAD_ATTR               43 (encode + NULL|self)
                LOAD_CONST              10 ('utf-8')
                CALL                     1
                CALL                     1
                UNPACK_SEQUENCE          3
                STORE_FAST_STORE_FAST  120 (ct, nonce)
                STORE_FAST               9 (kv)

 169            LOAD_GLOBAL             27 (ContactProfile + NULL)
                LOAD_CONST              33 (())
                BUILD_MAP                0
                LOAD_CONST              11 ('owner_user_id')

 170            LOAD_FAST                1 (current_user)
                LOAD_ATTR                2 (user)
                LOAD_ATTR                4 (id)
                MAP_ADD                  1

 169            LOAD_CONST              12 ('phone_ciphertext')

 171            LOAD_FAST                7 (ct)
                MAP_ADD                  1

 169            LOAD_CONST              13 ('phone_nonce')

 172            LOAD_FAST                8 (nonce)
                MAP_ADD                  1

 169            LOAD_CONST              14 ('phone_key_version')

 173            LOAD_FAST                9 (kv)
                MAP_ADD                  1

 169            LOAD_CONST              15 ('phone_hash')

 174            LOAD_FAST                5 (ph)
                MAP_ADD                  1

 169            LOAD_CONST              16 ('phone_last4')

 175            LOAD_GLOBAL             45 (extract_last4 + NULL)
                LOAD_FAST                0 (body)
                LOAD_ATTR               20 (phone_number)
                CALL                     1
                MAP_ADD                  1

 169            LOAD_CONST              17 ('display_name')

 176            LOAD_FAST                0 (body)
                LOAD_ATTR               46 (display_name)
                MAP_ADD                  1

 169            LOAD_CONST              18 ('company')

 177            LOAD_FAST                0 (body)
                LOAD_ATTR               48 (company)
                MAP_ADD                  1

 169            LOAD_CONST              19 ('relationship')

 178            LOAD_FAST                0 (body)
                LOAD_ATTR               50 (relationship)
                MAP_ADD                  1

 169            LOAD_CONST              20 ('email')

 179            LOAD_FAST                0 (body)
                LOAD_ATTR               52 (email)
                MAP_ADD                  1

 169            LOAD_CONST              21 ('notes')

 180            LOAD_FAST                0 (body)
                LOAD_ATTR               54 (notes)
                MAP_ADD                  1

 169            LOAD_CONST              22 ('category')

 181            LOAD_FAST                0 (body)
                LOAD_ATTR               16 (category)
                MAP_ADD                  1

 169            LOAD_CONST              23 ('is_vip')

 182            LOAD_FAST                0 (body)
                LOAD_ATTR               56 (is_vip)
                MAP_ADD                  1

 169            LOAD_CONST              24 ('is_blocked')

 183            LOAD_FAST                0 (body)
                LOAD_ATTR               58 (is_blocked)
                MAP_ADD                  1

 169            LOAD_CONST              25 ('block_reason')

 184            LOAD_FAST                0 (body)
                LOAD_ATTR               60 (block_reason)
                MAP_ADD                  1

 169            LOAD_CONST              26 ('ai_temperament_preset')

 185            LOAD_FAST                0 (body)
                LOAD_ATTR               62 (ai_temperament_preset)
                MAP_ADD                  1

 169            LOAD_CONST              27 ('ai_greeting_template')

 186            LOAD_FAST                0 (body)
                LOAD_ATTR               64 (ai_greeting_template)
                MAP_ADD                  1

 169            LOAD_CONST              28 ('ai_swearing_rule')

 187            LOAD_FAST                0 (body)
                LOAD_ATTR               66 (ai_swearing_rule)
                MAP_ADD                  1

 169            LOAD_CONST              29 ('ai_max_call_length_seconds')

 188            LOAD_FAST                0 (body)
                LOAD_ATTR               68 (ai_max_call_length_seconds)
                MAP_ADD                  1

 169            CALL_FUNCTION_EX         1
                STORE_FAST              10 (contact)

 191            LOAD_FAST                0 (body)
                LOAD_ATTR               70 (ai_greeting_instructions)
                TO_BOOL
                POP_JUMP_IF_FALSE       57 (to L16)

 192            LOAD_GLOBAL             41 (encrypt_field + NULL)
                LOAD_FAST                0 (body)
                LOAD_ATTR               70 (ai_greeting_instructions)
                LOAD_ATTR               43 (encode + NULL|self)
                LOAD_CONST              10 ('utf-8')
                CALL                     1
                CALL                     1
                UNPACK_SEQUENCE          3
                STORE_FAST_STORE_FAST  188 (g_ct, g_n)
                STORE_FAST              13 (g_kv)

 193            LOAD_FAST_LOAD_FAST    186 (g_ct, contact)
                STORE_ATTR              36 (ai_greeting_instructions_ciphertext)

 194            LOAD_FAST_LOAD_FAST    202 (g_n, contact)
                STORE_ATTR              37 (ai_greeting_instructions_nonce)

 195            LOAD_FAST_LOAD_FAST    218 (g_kv, contact)
                STORE_ATTR              38 (ai_greeting_instructions_key_version)

 197   L16:     LOAD_FAST                0 (body)
                LOAD_ATTR               78 (ai_custom_instructions)
                TO_BOOL
                POP_JUMP_IF_FALSE       58 (to L17)

 198            LOAD_GLOBAL             41 (encrypt_field + NULL)
                LOAD_FAST                0 (body)
                LOAD_ATTR               78 (ai_custom_instructions)
                LOAD_ATTR               43 (encode + NULL|self)
                LOAD_CONST              10 ('utf-8')
                CALL                     1
                CALL                     1
                UNPACK_SEQUENCE          3
                STORE_FAST_STORE_FAST  239 (i_ct, i_n)
                STORE_FAST              16 (i_kv)

 199            LOAD_FAST_LOAD_FAST    234 (i_ct, contact)
                STORE_ATTR              40 (ai_custom_instructions_ciphertext)

 200            LOAD_FAST_LOAD_FAST    250 (i_n, contact)
                STORE_ATTR              41 (ai_custom_instructions_nonce)

 201            LOAD_FAST               16 (i_kv)
                LOAD_FAST               10 (contact)
                STORE_ATTR              42 (ai_custom_instructions_key_version)

 203   L17:     LOAD_FAST                2 (db)
                LOAD_ATTR               87 (add + NULL|self)
                LOAD_FAST               10 (contact)
                CALL                     1
                POP_TOP

 204            LOAD_GLOBAL             89 (log_event + NULL)

 205            LOAD_FAST                2 (db)

 206            LOAD_FAST                1 (current_user)
                LOAD_ATTR                2 (user)
                LOAD_ATTR                4 (id)

 207            LOAD_CONST              30 ('contact_created')

 208            LOAD_FAST                1 (current_user)
                LOAD_ATTR                2 (user)
                LOAD_ATTR                4 (id)

 209            LOAD_CONST              31 ('contact_profile')

 210            LOAD_FAST               10 (contact)
                LOAD_ATTR                4 (id)

 204            LOAD_CONST              32 (('owner_user_id', 'event_type', 'actor_id', 'target_type', 'target_id'))
                CALL_KW                  6
                GET_AWAITABLE            0
                LOAD_CONST               0 (None)
       L18:     SEND                     3 (to L21)
       L19:     YIELD_VALUE              1
       L20:     RESUME                   3
                JUMP_BACKWARD_NO_INTERRUPT 5 (to L18)
       L21:     END_SEND
                POP_TOP

 212            LOAD_FAST                2 (db)
                LOAD_ATTR               91 (flush + NULL|self)
                CALL                     0
                GET_AWAITABLE            0
                LOAD_CONST               0 (None)
       L22:     SEND                     3 (to L25)
       L23:     YIELD_VALUE              1
       L24:     RESUME                   3
                JUMP_BACKWARD_NO_INTERRUPT 5 (to L22)
       L25:     END_SEND
                POP_TOP

 214            LOAD_GLOBAL             93 (_to_response + NULL)
                LOAD_FAST               10 (contact)
                CALL                     1
                RETURN_VALUE

 141   L26:     CLEANUP_THROW
       L27:     EXTENDED_ARG             3
                JUMP_BACKWARD_NO_INTERRUPT 809 (to L5)

 149   L28:     CLEANUP_THROW
       L29:     EXTENDED_ARG             2
                JUMP_BACKWARD_NO_INTERRUPT 742 (to L10)

 152   L30:     CLEANUP_THROW
       L31:     EXTENDED_ARG             2
                JUMP_BACKWARD_NO_INTERRUPT 586 (to L14)

 204   L32:     CLEANUP_THROW
       L33:     JUMP_BACKWARD_NO_INTERRUPT 48 (to L21)

 212   L34:     CLEANUP_THROW
       L35:     JUMP_BACKWARD_NO_INTERRUPT 26 (to L25)

  --   L36:     CALL_INTRINSIC_1         3 (INTRINSIC_STOPITERATION_ERROR)
                RERAISE                  1
ExceptionTable:
  L1 to L3 -> L36 [0] lasti
  L3 to L4 -> L26 [2]
  L4 to L8 -> L36 [0] lasti
  L8 to L9 -> L28 [2]
  L9 to L12 -> L36 [0] lasti
  L12 to L13 -> L30 [2]
  L13 to L19 -> L36 [0] lasti
  L19 to L20 -> L32 [2]
  L20 to L23 -> L36 [0] lasti
  L23 to L24 -> L34 [2]
  L24 to L27 -> L36 [0] lasti
  L28 to L29 -> L36 [0] lasti
  L30 to L31 -> L36 [0] lasti
  L32 to L33 -> L36 [0] lasti
  L34 to L35 -> L36 [0] lasti

Disassembly of <code object list_categories at 0x0000024C0FBE4020, file "D:\fluence\Github\mattbot\backend\app\api\v1\contacts.py", line 221>:
 221            RETURN_GENERATOR
                POP_TOP
        L1:     RESUME                   0

 226            LOAD_FAST                1 (db)
                LOAD_ATTR                1 (get + NULL|self)
                LOAD_GLOBAL              2 (UserSettings)
                LOAD_FAST                0 (current_user)
                LOAD_ATTR                4 (user)
                LOAD_ATTR                6 (id)
                CALL                     2
                GET_AWAITABLE            0
                LOAD_CONST               0 (None)
        L2:     SEND                     3 (to L5)
        L3:     YIELD_VALUE              1
        L4:     RESUME                   3
                JUMP_BACKWARD_NO_INTERRUPT 5 (to L2)
        L5:     END_SEND
                STORE_FAST               2 (row)

 227            LOAD_FAST                2 (row)
                TO_BOOL
                POP_JUMP_IF_FALSE       12 (to L6)
                LOAD_FAST                2 (row)
                LOAD_ATTR                8 (custom_contact_categories)
                JUMP_FORWARD             1 (to L7)
        L6:     BUILD_LIST               0
        L7:     STORE_FAST               3 (custom)

 229            BUILD_LIST               0
                STORE_FAST               4 (items)

 230            LOAD_GLOBAL             11 (sorted + NULL)
                LOAD_GLOBAL             12 (DEFAULT_CATEGORIES)
                CALL                     1
                GET_ITER
        L8:     FOR_ITER                78 (to L9)
                STORE_FAST               5 (slug)

 231            LOAD_FAST                4 (items)
                LOAD_ATTR               15 (append + NULL|self)
                LOAD_GLOBAL             17 (CategoryItem + NULL)

 232            LOAD_FAST                5 (slug)

 233            LOAD_GLOBAL             18 (_DEFAULT_LABELS)
                LOAD_ATTR                1 (get + NULL|self)
                LOAD_FAST_LOAD_FAST     85 (slug, slug)
                LOAD_ATTR               21 (replace + NULL|self)
                LOAD_CONST               1 ('_')
                LOAD_CONST               2 (' ')
                CALL                     2
                LOAD_ATTR               23 (title + NULL|self)
                CALL                     0
                CALL                     2

 234            LOAD_CONST               3 (True)

 231            LOAD_CONST               4 (('slug', 'label', 'is_default'))
                CALL_KW                  3
                CALL                     1
                POP_TOP
                JUMP_BACKWARD           80 (to L8)

 230    L9:     END_FOR
                POP_TOP

 236            LOAD_FAST                3 (custom)
                GET_ITER
       L10:     FOR_ITER               112 (to L15)
                STORE_FAST               6 (entry)

 237            LOAD_GLOBAL             25 (isinstance + NULL)
                LOAD_FAST                6 (entry)
                LOAD_GLOBAL             26 (dict)
                CALL                     2
                TO_BOOL
       L11:     POP_JUMP_IF_TRUE         2 (to L12)
                JUMP_BACKWARD           26 (to L10)
       L12:     LOAD_CONST               5 ('slug')
                LOAD_FAST                6 (entry)
                CONTAINS_OP              0
       L13:     POP_JUMP_IF_TRUE         2 (to L14)
                JUMP_BACKWARD           34 (to L10)

 238   L14:     LOAD_FAST                4 (items)
                LOAD_ATTR               15 (append + NULL|self)
                LOAD_GLOBAL             17 (CategoryItem + NULL)

 239            LOAD_FAST                6 (entry)
                LOAD_CONST               5 ('slug')
                BINARY_SUBSCR

 240            LOAD_FAST                6 (entry)
                LOAD_ATTR                1 (get + NULL|self)
                LOAD_CONST               6 ('label')
                LOAD_FAST                6 (entry)
                LOAD_CONST               5 ('slug')
                BINARY_SUBSCR
                LOAD_ATTR               21 (replace + NULL|self)
                LOAD_CONST               1 ('_')
                LOAD_CONST               2 (' ')
                CALL                     2
                LOAD_ATTR               23 (title + NULL|self)
                CALL                     0
                CALL                     2

 241            LOAD_CONST               7 (False)

 238            LOAD_CONST               4 (('slug', 'label', 'is_default'))
                CALL_KW                  3
                CALL                     1
                POP_TOP
                JUMP_BACKWARD          114 (to L10)

 236   L15:     END_FOR
                POP_TOP

 244            LOAD_GLOBAL             29 (CategoriesListResponse + NULL)
                LOAD_FAST                4 (items)
                LOAD_CONST               8 (('categories',))
                CALL_KW                  1
                RETURN_VALUE

 226   L16:     CLEANUP_THROW
       L17:     JUMP_BACKWARD_NO_INTERRUPT 251 (to L5)

  --   L18:     CALL_INTRINSIC_1         3 (INTRINSIC_STOPITERATION_ERROR)
                RERAISE                  1
ExceptionTable:
  L1 to L3 -> L18 [0] lasti
  L3 to L4 -> L16 [2]
  L4 to L11 -> L18 [0] lasti
  L12 to L13 -> L18 [0] lasti
  L14 to L17 -> L18 [0] lasti

Disassembly of <code object create_custom_category at 0x0000024C0FB40D60, file "D:\fluence\Github\mattbot\backend\app\api\v1\contacts.py", line 247>:
 247            RETURN_GENERATOR
                POP_TOP
        L1:     RESUME                   0

 253            LOAD_GLOBAL              1 (check_rate_limit + NULL)

 254            LOAD_CONST               1 ('contacts:catcreate:')
                LOAD_FAST                1 (current_user)
                LOAD_ATTR                2 (user)
                LOAD_ATTR                4 (id)
                FORMAT_SIMPLE
                BUILD_STRING             2

 255            LOAD_GLOBAL              6 (settings)
                LOAD_ATTR                8 (RATE_LIMIT_API_WRITE_MAX)

 256            LOAD_GLOBAL              6 (settings)
                LOAD_ATTR               10 (RATE_LIMIT_API_WRITE_WINDOW)

 253            LOAD_CONST               2 (('max_requests', 'window_seconds'))
                CALL_KW                  3
                GET_AWAITABLE            0
                LOAD_CONST               0 (None)
        L2:     SEND                     3 (to L5)
        L3:     YIELD_VALUE              1
        L4:     RESUME                   3
                JUMP_BACKWARD_NO_INTERRUPT 5 (to L2)
        L5:     END_SEND
                UNPACK_SEQUENCE          2
                STORE_FAST_STORE_FAST   52 (allowed, _)

 258            LOAD_FAST                3 (allowed)
                TO_BOOL
                POP_JUMP_IF_TRUE        11 (to L6)

 259            LOAD_GLOBAL             13 (AppError + NULL)
                LOAD_CONST               3 ('RATE_LIMITED')
                LOAD_CONST               4 ('Too many requests')
                LOAD_CONST               5 (429)
                LOAD_CONST               6 (('code', 'message', 'status_code'))
                CALL_KW                  3
                RAISE_VARARGS            1

 261    L6:     LOAD_FAST                0 (body)
                LOAD_ATTR               14 (slug)
                LOAD_GLOBAL             16 (DEFAULT_CATEGORIES)
                CONTAINS_OP              0
                POP_JUMP_IF_FALSE       25 (to L7)

 262            LOAD_GLOBAL             13 (AppError + NULL)

 263            LOAD_CONST               7 ('CATEGORY_IS_DEFAULT')

 264            LOAD_CONST               8 ("'")
                LOAD_FAST                0 (body)
                LOAD_ATTR               14 (slug)
                FORMAT_SIMPLE
                LOAD_CONST               9 ("' is a built-in category and cannot be created")
                BUILD_STRING             3

 265            LOAD_CONST              10 (409)

 262            LOAD_CONST               6 (('code', 'message', 'status_code'))
                CALL_KW                  3
                RAISE_VARARGS            1

 268    L7:     LOAD_FAST                2 (db)
                LOAD_ATTR               19 (get + NULL|self)
                LOAD_GLOBAL             20 (UserSettings)
                LOAD_FAST                1 (current_user)
                LOAD_ATTR                2 (user)
                LOAD_ATTR                4 (id)
                CALL                     2
                GET_AWAITABLE            0
                LOAD_CONST               0 (None)
        L8:     SEND                     3 (to L11)
        L9:     YIELD_VALUE              1
       L10:     RESUME                   3
                JUMP_BACKWARD_NO_INTERRUPT 5 (to L8)
       L11:     END_SEND
                STORE_FAST               5 (row)

 269            LOAD_FAST                5 (row)
                POP_JUMP_IF_NOT_NONE    11 (to L12)

 270            LOAD_GLOBAL             13 (AppError + NULL)
                LOAD_CONST              11 ('SETTINGS_NOT_FOUND')
                LOAD_CONST              12 ('User settings not found')
                LOAD_CONST              13 (404)
                LOAD_CONST               6 (('code', 'message', 'status_code'))
                CALL_KW                  3
                RAISE_VARARGS            1

 272   L12:     LOAD_GLOBAL             23 (list + NULL)
                LOAD_FAST                5 (row)
                LOAD_ATTR               24 (custom_contact_categories)
                COPY                     1
                TO_BOOL
                POP_JUMP_IF_TRUE         2 (to L13)
                POP_TOP
                BUILD_LIST               0
       L13:     CALL                     1
                STORE_FAST               6 (custom)

 273            LOAD_FAST                6 (custom)
                GET_ITER
                LOAD_FAST_AND_CLEAR      7 (e)
                SWAP                     2
       L14:     BUILD_SET                0
                SWAP                     2
                GET_ITER
       L15:     FOR_ITER                39 (to L20)
                STORE_FAST               7 (e)
                LOAD_GLOBAL             27 (isinstance + NULL)
                LOAD_FAST                7 (e)
                LOAD_GLOBAL             28 (dict)
                CALL                     2
                TO_BOOL
       L16:     POP_JUMP_IF_TRUE         2 (to L17)
                JUMP_BACKWARD           26 (to L15)
       L17:     LOAD_CONST              14 ('slug')
                LOAD_FAST                7 (e)
                CONTAINS_OP              0
       L18:     POP_JUMP_IF_TRUE         2 (to L19)
                JUMP_BACKWARD           34 (to L15)
       L19:     LOAD_FAST                7 (e)
                LOAD_CONST              14 ('slug')
                BINARY_SUBSCR
                SET_ADD                  2
                JUMP_BACKWARD           41 (to L15)
       L20:     END_FOR
                POP_TOP
       L21:     STORE_FAST               8 (existing_slugs)
                STORE_FAST               7 (e)

 274            LOAD_FAST                0 (body)
                LOAD_ATTR               14 (slug)
                LOAD_FAST                8 (existing_slugs)
                CONTAINS_OP              0
                POP_JUMP_IF_FALSE       25 (to L22)

 275            LOAD_GLOBAL             13 (AppError + NULL)

 276            LOAD_CONST              15 ('CATEGORY_DUPLICATE')

 277            LOAD_CONST              16 ("Custom category '")
                LOAD_FAST                0 (body)
                LOAD_ATTR               14 (slug)
                FORMAT_SIMPLE
                LOAD_CONST              17 ("' already exists")
                BUILD_STRING             3

 278            LOAD_CONST              10 (409)

 275            LOAD_CONST               6 (('code', 'message', 'status_code'))
                CALL_KW                  3
                RAISE_VARARGS            1

 281   L22:     LOAD_GLOBAL             31 (len + NULL)
                LOAD_FAST                6 (custom)
                CALL                     1
                LOAD_CONST              18 (20)
                COMPARE_OP             188 (bool(>=))
                POP_JUMP_IF_FALSE       11 (to L23)

 282            LOAD_GLOBAL             13 (AppError + NULL)

 283            LOAD_CONST              19 ('CATEGORY_LIMIT')

 284            LOAD_CONST              20 ('Maximum of 20 custom categories allowed')

 285            LOAD_CONST              21 (400)

 282            LOAD_CONST               6 (('code', 'message', 'status_code'))
                CALL_KW                  3
                RAISE_VARARGS            1

 288   L23:     LOAD_FAST                6 (custom)
                LOAD_ATTR               33 (append + NULL|self)
                LOAD_FAST                0 (body)
                LOAD_ATTR               14 (slug)
                LOAD_FAST                0 (body)
                LOAD_ATTR               34 (label)
                LOAD_CONST              22 (('slug', 'label'))
                BUILD_CONST_KEY_MAP      2
                CALL                     1
                POP_TOP

 289            LOAD_FAST_LOAD_FAST    101 (custom, row)
                STORE_ATTR              12 (custom_contact_categories)

 290            LOAD_FAST                2 (db)
                LOAD_ATTR               37 (flush + NULL|self)
                CALL                     0
                GET_AWAITABLE            0
                LOAD_CONST               0 (None)
       L24:     SEND                     3 (to L27)
       L25:     YIELD_VALUE              1
       L26:     RESUME                   3
                JUMP_BACKWARD_NO_INTERRUPT 5 (to L24)
       L27:     END_SEND
                POP_TOP

 292            LOAD_GLOBAL             39 (CategoryItem + NULL)
                LOAD_FAST                0 (body)
                LOAD_ATTR               14 (slug)
                LOAD_FAST                0 (body)
                LOAD_ATTR               34 (label)
                LOAD_CONST              23 (False)
                LOAD_CONST              24 (('slug', 'label', 'is_default'))
                CALL_KW                  3
                RETURN_VALUE

 253   L28:     CLEANUP_THROW
       L29:     EXTENDED_ARG             1
                JUMP_BACKWARD_NO_INTERRUPT 384 (to L5)

 268   L30:     CLEANUP_THROW
       L31:     EXTENDED_ARG             1
                JUMP_BACKWARD_NO_INTERRUPT 272 (to L11)

  --   L32:     SWAP                     2
                POP_TOP

 273            SWAP                     2
                STORE_FAST               7 (e)
                RERAISE                  0

 290   L33:     CLEANUP_THROW
       L34:     JUMP_BACKWARD_NO_INTERRUPT 46 (to L27)

  --   L35:     CALL_INTRINSIC_1         3 (INTRINSIC_STOPITERATION_ERROR)
                RERAISE                  1
ExceptionTable:
  L1 to L3 -> L35 [0] lasti
  L3 to L4 -> L28 [2]
  L4 to L9 -> L35 [0] lasti
  L9 to L10 -> L30 [2]
  L10 to L14 -> L35 [0] lasti
  L14 to L16 -> L32 [2]
  L17 to L18 -> L32 [2]
  L19 to L21 -> L32 [2]
  L21 to L25 -> L35 [0] lasti
  L25 to L26 -> L33 [2]
  L26 to L29 -> L35 [0] lasti
  L30 to L31 -> L35 [0] lasti
  L32 to L34 -> L35 [0] lasti

Disassembly of <code object delete_custom_category at 0x0000024C0FBDD460, file "D:\fluence\Github\mattbot\backend\app\api\v1\contacts.py", line 295>:
 295            RETURN_GENERATOR
                POP_TOP
        L1:     RESUME                   0

 301            LOAD_GLOBAL              1 (check_rate_limit + NULL)

 302            LOAD_CONST               1 ('contacts:catdelete:')
                LOAD_FAST                1 (current_user)
                LOAD_ATTR                2 (user)
                LOAD_ATTR                4 (id)
                FORMAT_SIMPLE
                BUILD_STRING             2

 303            LOAD_GLOBAL              6 (settings)
                LOAD_ATTR                8 (RATE_LIMIT_API_WRITE_MAX)

 304            LOAD_GLOBAL              6 (settings)
                LOAD_ATTR               10 (RATE_LIMIT_API_WRITE_WINDOW)

 301            LOAD_CONST               2 (('max_requests', 'window_seconds'))
                CALL_KW                  3
                GET_AWAITABLE            0
                LOAD_CONST               0 (None)
        L2:     SEND                     3 (to L5)
        L3:     YIELD_VALUE              1
        L4:     RESUME                   3
                JUMP_BACKWARD_NO_INTERRUPT 5 (to L2)
        L5:     END_SEND
                UNPACK_SEQUENCE          2
                STORE_FAST_STORE_FAST   52 (allowed, _)

 306            LOAD_FAST                3 (allowed)
                TO_BOOL
                POP_JUMP_IF_TRUE        11 (to L6)

 307            LOAD_GLOBAL             13 (AppError + NULL)
                LOAD_CONST               3 ('RATE_LIMITED')
                LOAD_CONST               4 ('Too many requests')
                LOAD_CONST               5 (429)
                LOAD_CONST               6 (('code', 'message', 'status_code'))
                CALL_KW                  3
                RAISE_VARARGS            1

 309    L6:     LOAD_FAST                0 (slug)
                LOAD_GLOBAL             14 (DEFAULT_CATEGORIES)
                CONTAINS_OP              0
                POP_JUMP_IF_FALSE       11 (to L7)

 310            LOAD_GLOBAL             13 (AppError + NULL)

 311            LOAD_CONST               7 ('CATEGORY_IS_DEFAULT')

 312            LOAD_CONST               8 ('Cannot delete a built-in category')

 313            LOAD_CONST               9 (400)

 310            LOAD_CONST               6 (('code', 'message', 'status_code'))
                CALL_KW                  3
                RAISE_VARARGS            1

 316    L7:     LOAD_FAST                2 (db)
                LOAD_ATTR               17 (get + NULL|self)
                LOAD_GLOBAL             18 (UserSettings)
                LOAD_FAST                1 (current_user)
                LOAD_ATTR                2 (user)
                LOAD_ATTR                4 (id)
                CALL                     2
                GET_AWAITABLE            0
                LOAD_CONST               0 (None)
        L8:     SEND                     3 (to L11)
        L9:     YIELD_VALUE              1
       L10:     RESUME                   3
                JUMP_BACKWARD_NO_INTERRUPT 5 (to L8)
       L11:     END_SEND
                STORE_FAST               5 (row)

 317            LOAD_FAST                5 (row)
                POP_JUMP_IF_NOT_NONE    11 (to L12)

 318            LOAD_GLOBAL             13 (AppError + NULL)
                LOAD_CONST              10 ('SETTINGS_NOT_FOUND')
                LOAD_CONST              11 ('User settings not found')
                LOAD_CONST              12 (404)
                LOAD_CONST               6 (('code', 'message', 'status_code'))
                CALL_KW                  3
                RAISE_VARARGS            1

 320   L12:     LOAD_GLOBAL             21 (list + NULL)
                LOAD_FAST                5 (row)
                LOAD_ATTR               22 (custom_contact_categories)
                COPY                     1
                TO_BOOL
                POP_JUMP_IF_TRUE         2 (to L13)
                POP_TOP
                BUILD_LIST               0
       L13:     CALL                     1
                STORE_FAST               6 (custom)

 321            LOAD_FAST                6 (custom)
                GET_ITER
                LOAD_FAST_AND_CLEAR      7 (e)
                SWAP                     2
       L14:     BUILD_LIST               0
                SWAP                     2
                GET_ITER
       L15:     FOR_ITER                49 (to L18)
                STORE_FAST               7 (e)
                LOAD_GLOBAL             25 (isinstance + NULL)
                LOAD_FAST                7 (e)
                LOAD_GLOBAL             26 (dict)
                CALL                     2
                TO_BOOL
                POP_JUMP_IF_FALSE       23 (to L17)
                LOAD_FAST                7 (e)
                LOAD_ATTR               17 (get + NULL|self)
                LOAD_CONST              13 ('slug')
                CALL                     1
                LOAD_FAST                0 (slug)
                COMPARE_OP              88 (bool(==))
       L16:     POP_JUMP_IF_FALSE        2 (to L17)
                JUMP_BACKWARD           47 (to L15)
       L17:     LOAD_FAST                7 (e)
                LIST_APPEND              2
                JUMP_BACKWARD           51 (to L15)
       L18:     END_FOR
                POP_TOP
       L19:     STORE_FAST               8 (new_custom)
                STORE_FAST               7 (e)

 322            LOAD_GLOBAL             29 (len + NULL)
                LOAD_FAST                8 (new_custom)
                CALL                     1
                LOAD_GLOBAL             29 (len + NULL)
                LOAD_FAST                6 (custom)
                CALL                     1
                COMPARE_OP              88 (bool(==))
                POP_JUMP_IF_FALSE       15 (to L20)

 323            LOAD_GLOBAL             13 (AppError + NULL)

 324            LOAD_CONST              14 ('CATEGORY_NOT_FOUND')

 325            LOAD_CONST              15 ("Custom category '")
                LOAD_FAST                0 (slug)
                FORMAT_SIMPLE
                LOAD_CONST              16 ("' not found")
                BUILD_STRING             3

 326            LOAD_CONST              12 (404)

 323            LOAD_CONST               6 (('code', 'message', 'status_code'))
                CALL_KW                  3
                RAISE_VARARGS            1

 329   L20:     LOAD_FAST_LOAD_FAST    133 (new_custom, row)
                STORE_ATTR              11 (custom_contact_categories)

 332            LOAD_FAST                2 (db)
                LOAD_ATTR               31 (execute + NULL|self)

 333            LOAD_GLOBAL             33 (update + NULL)
                LOAD_GLOBAL             34 (ContactProfile)
                CALL                     1

 334            LOAD_ATTR               37 (where + NULL|self)

 335            LOAD_GLOBAL             34 (ContactProfile)
                LOAD_ATTR               38 (owner_user_id)
                LOAD_FAST                1 (current_user)
                LOAD_ATTR                2 (user)
                LOAD_ATTR                4 (id)
                COMPARE_OP              72 (==)

 336            LOAD_GLOBAL             34 (ContactProfile)
                LOAD_ATTR               40 (category)
                LOAD_FAST                0 (slug)
                COMPARE_OP              72 (==)

 337            LOAD_GLOBAL             34 (ContactProfile)
                LOAD_ATTR               42 (deleted_at)
                LOAD_ATTR               45 (is_ + NULL|self)
                LOAD_CONST               0 (None)
                CALL                     1

 334            CALL                     3

 339            LOAD_ATTR               47 (values + NULL|self)
                LOAD_CONST              17 ('other')
                LOAD_CONST              18 (('category',))
                CALL_KW                  1

 332            CALL                     1
                GET_AWAITABLE            0
                LOAD_CONST               0 (None)
       L21:     SEND                     3 (to L24)
       L22:     YIELD_VALUE              1
       L23:     RESUME                   3
                JUMP_BACKWARD_NO_INTERRUPT 5 (to L21)
       L24:     END_SEND
                POP_TOP

 343            LOAD_GLOBAL             27 (dict + NULL)
                LOAD_FAST                5 (row)
                LOAD_ATTR               48 (contact_category_defaults)
                COPY                     1
                TO_BOOL
                POP_JUMP_IF_TRUE         2 (to L25)
                POP_TOP
                BUILD_MAP                0
       L25:     CALL                     1
                STORE_FAST               9 (cat_defaults)

 344            LOAD_FAST                9 (cat_defaults)
                LOAD_ATTR               51 (pop + NULL|self)
                LOAD_FAST                0 (slug)
                LOAD_CONST               0 (None)
                CALL                     2
                POP_TOP

 345            LOAD_FAST_LOAD_FAST    149 (cat_defaults, row)
                STORE_ATTR              24 (contact_category_defaults)

 347            LOAD_FAST                2 (db)
                LOAD_ATTR               53 (flush + NULL|self)
                CALL                     0
                GET_AWAITABLE            0
                LOAD_CONST               0 (None)
       L26:     SEND                     3 (to L29)
       L27:     YIELD_VALUE              1
       L28:     RESUME                   3
                JUMP_BACKWARD_NO_INTERRUPT 5 (to L26)
       L29:     END_SEND
                POP_TOP

 348            LOAD_CONST              19 (True)
                LOAD_CONST              17 ('other')
                LOAD_CONST              20 (('deleted', 'reassigned_to'))
                BUILD_CONST_KEY_MAP      2
                RETURN_VALUE

 301   L30:     CLEANUP_THROW
       L31:     EXTENDED_ARG             1
                JUMP_BACKWARD_NO_INTERRUPT 481 (to L5)

 316   L32:     CLEANUP_THROW
       L33:     EXTENDED_ARG             1
                JUMP_BACKWARD_NO_INTERRUPT 393 (to L11)

  --   L34:     SWAP                     2
                POP_TOP

 321            SWAP                     2
                STORE_FAST               7 (e)
                RERAISE                  0

 332   L35:     CLEANUP_THROW
       L36:     JUMP_BACKWARD_NO_INTERRUPT 98 (to L24)

 347   L37:     CLEANUP_THROW
       L38:     JUMP_BACKWARD_NO_INTERRUPT 22 (to L29)

  --   L39:     CALL_INTRINSIC_1         3 (INTRINSIC_STOPITERATION_ERROR)
                RERAISE                  1
ExceptionTable:
  L1 to L3 -> L39 [0] lasti
  L3 to L4 -> L30 [2]
  L4 to L9 -> L39 [0] lasti
  L9 to L10 -> L32 [2]
  L10 to L14 -> L39 [0] lasti
  L14 to L16 -> L34 [2]
  L17 to L19 -> L34 [2]
  L19 to L22 -> L39 [0] lasti
  L22 to L23 -> L35 [2]
  L23 to L27 -> L39 [0] lasti
  L27 to L28 -> L37 [2]
  L28 to L31 -> L39 [0] lasti
  L32 to L33 -> L39 [0] lasti
  L34 to L36 -> L39 [0] lasti
  L37 to L38 -> L39 [0] lasti

Disassembly of <code object get_category_defaults at 0x0000024C0EC47330, file "D:\fluence\Github\mattbot\backend\app\api\v1\contacts.py", line 355>:
 355            RETURN_GENERATOR
                POP_TOP
        L1:     RESUME                   0

 360            LOAD_FAST                1 (db)
                LOAD_ATTR                1 (get + NULL|self)
                LOAD_GLOBAL              2 (UserSettings)
                LOAD_FAST                0 (current_user)
                LOAD_ATTR                4 (user)
                LOAD_ATTR                6 (id)
                CALL                     2
                GET_AWAITABLE            0
                LOAD_CONST               0 (None)
        L2:     SEND                     3 (to L5)
        L3:     YIELD_VALUE              1
        L4:     RESUME                   3
                JUMP_BACKWARD_NO_INTERRUPT 5 (to L2)
        L5:     END_SEND
                STORE_FAST               2 (row)

 361            LOAD_FAST                2 (row)
                TO_BOOL
                POP_JUMP_IF_FALSE       12 (to L6)
                LOAD_FAST                2 (row)
                LOAD_ATTR                8 (contact_category_defaults)
                JUMP_FORWARD             1 (to L7)
        L6:     BUILD_MAP                0
        L7:     STORE_FAST               3 (defaults)

 362            LOAD_GLOBAL             11 (CategoryDefaultsResponse + NULL)
                LOAD_FAST                3 (defaults)
                LOAD_CONST               1 (('defaults',))
                CALL_KW                  1
                RETURN_VALUE

 360    L8:     CLEANUP_THROW
        L9:     JUMP_BACKWARD_NO_INTERRUPT 34 (to L5)

  --   L10:     CALL_INTRINSIC_1         3 (INTRINSIC_STOPITERATION_ERROR)
                RERAISE                  1
ExceptionTable:
  L1 to L3 -> L10 [0] lasti
  L3 to L4 -> L8 [2]
  L4 to L9 -> L10 [0] lasti

Disassembly of <code object update_category_defaults at 0x0000024C0FBDD9B0, file "D:\fluence\Github\mattbot\backend\app\api\v1\contacts.py", line 365>:
 365            RETURN_GENERATOR
                POP_TOP
        L1:     RESUME                   0

 371            LOAD_GLOBAL              1 (check_rate_limit + NULL)

 372            LOAD_CONST               1 ('contacts:catdef:')
                LOAD_FAST                1 (current_user)
                LOAD_ATTR                2 (user)
                LOAD_ATTR                4 (id)
                FORMAT_SIMPLE
                BUILD_STRING             2

 373            LOAD_GLOBAL              6 (settings)
                LOAD_ATTR                8 (RATE_LIMIT_API_WRITE_MAX)

 374            LOAD_GLOBAL              6 (settings)
                LOAD_ATTR               10 (RATE_LIMIT_API_WRITE_WINDOW)

 371            LOAD_CONST               2 (('max_requests', 'window_seconds'))
                CALL_KW                  3
                GET_AWAITABLE            0
                LOAD_CONST               0 (None)
        L2:     SEND                     3 (to L5)
        L3:     YIELD_VALUE              1
        L4:     RESUME                   3
                JUMP_BACKWARD_NO_INTERRUPT 5 (to L2)
        L5:     END_SEND
                UNPACK_SEQUENCE          2
                STORE_FAST_STORE_FAST   52 (allowed, _)

 376            LOAD_FAST                3 (allowed)
                TO_BOOL
                POP_JUMP_IF_TRUE        11 (to L6)

 377            LOAD_GLOBAL             13 (AppError + NULL)
                LOAD_CONST               3 ('RATE_LIMITED')
                LOAD_CONST               4 ('Too many requests')
                LOAD_CONST               5 (429)
                LOAD_CONST               6 (('code', 'message', 'status_code'))
                CALL_KW                  3
                RAISE_VARARGS            1

 379    L6:     LOAD_FAST                2 (db)
                LOAD_ATTR               15 (get + NULL|self)
                LOAD_GLOBAL             16 (UserSettings)
                LOAD_FAST                1 (current_user)
                LOAD_ATTR                2 (user)
                LOAD_ATTR                4 (id)
                CALL                     2
                GET_AWAITABLE            0
                LOAD_CONST               0 (None)
        L7:     SEND                     3 (to L10)
        L8:     YIELD_VALUE              1
        L9:     RESUME                   3
                JUMP_BACKWARD_NO_INTERRUPT 5 (to L7)
       L10:     END_SEND
                STORE_FAST               5 (row)

 380            LOAD_FAST                5 (row)
                POP_JUMP_IF_NOT_NONE    11 (to L11)

 381            LOAD_GLOBAL             13 (AppError + NULL)
                LOAD_CONST               7 ('SETTINGS_NOT_FOUND')
                LOAD_CONST               8 ('User settings not found')
                LOAD_CONST               9 (404)
                LOAD_CONST               6 (('code', 'message', 'status_code'))
                CALL_KW                  3
                RAISE_VARARGS            1

 383   L11:     LOAD_GLOBAL             19 (_get_valid_categories + NULL)
                LOAD_FAST_LOAD_FAST     33 (db, current_user)
                LOAD_ATTR                2 (user)
                LOAD_ATTR                4 (id)
                CALL                     2
                GET_AWAITABLE            0
                LOAD_CONST               0 (None)
       L12:     SEND                     3 (to L15)
       L13:     YIELD_VALUE              1
       L14:     RESUME                   3
                JUMP_BACKWARD_NO_INTERRUPT 5 (to L12)
       L15:     END_SEND
                STORE_FAST               6 (valid)

 384            LOAD_FAST                0 (body)
                LOAD_ATTR               20 (defaults)
                GET_ITER
       L16:     FOR_ITER                23 (to L19)
                STORE_FAST               7 (cat_key)

 385            LOAD_FAST_LOAD_FAST    118 (cat_key, valid)
                CONTAINS_OP              1
       L17:     POP_JUMP_IF_TRUE         2 (to L18)
                JUMP_BACKWARD           10 (to L16)

 386   L18:     LOAD_GLOBAL             13 (AppError + NULL)

 387            LOAD_CONST              10 ('UNKNOWN_CATEGORY')

 388            LOAD_CONST              11 ("Unknown category '")
                LOAD_FAST                7 (cat_key)
                FORMAT_SIMPLE
                LOAD_CONST              12 ("' in defaults")
                BUILD_STRING             3

 389            LOAD_CONST              13 (409)

 386            LOAD_CONST               6 (('code', 'message', 'status_code'))
                CALL_KW                  3
                RAISE_VARARGS            1

 384   L19:     END_FOR
                POP_TOP

 392            LOAD_FAST                0 (body)
                LOAD_ATTR               20 (defaults)
                LOAD_FAST                5 (row)
                STORE_ATTR              11 (contact_category_defaults)

 393            LOAD_FAST                2 (db)
                LOAD_ATTR               25 (flush + NULL|self)
                CALL                     0
                GET_AWAITABLE            0
                LOAD_CONST               0 (None)
       L20:     SEND                     3 (to L23)
       L21:     YIELD_VALUE              1
       L22:     RESUME                   3
                JUMP_BACKWARD_NO_INTERRUPT 5 (to L20)
       L23:     END_SEND
                POP_TOP

 394            LOAD_GLOBAL             27 (CategoryDefaultsResponse + NULL)
                LOAD_FAST                5 (row)
                LOAD_ATTR               22 (contact_category_defaults)
                LOAD_CONST              14 (('defaults',))
                CALL_KW                  1
                RETURN_VALUE

 371   L24:     CLEANUP_THROW
       L25:     JUMP_BACKWARD_NO_INTERRUPT 226 (to L5)

 379   L26:     CLEANUP_THROW
       L27:     JUMP_BACKWARD_NO_INTERRUPT 158 (to L10)

 383   L28:     CLEANUP_THROW
       L29:     JUMP_BACKWARD_NO_INTERRUPT 107 (to L15)

 393   L30:     CLEANUP_THROW
       L31:     JUMP_BACKWARD_NO_INTERRUPT 29 (to L23)

  --   L32:     CALL_INTRINSIC_1         3 (INTRINSIC_STOPITERATION_ERROR)
                RERAISE                  1
ExceptionTable:
  L1 to L3 -> L32 [0] lasti
  L3 to L4 -> L24 [2]
  L4 to L8 -> L32 [0] lasti
  L8 to L9 -> L26 [2]
  L9 to L13 -> L32 [0] lasti
  L13 to L14 -> L28 [2]
  L14 to L17 -> L32 [0] lasti
  L18 to L21 -> L32 [0] lasti
  L21 to L22 -> L30 [2]
  L22 to L25 -> L32 [0] lasti
  L26 to L27 -> L32 [0] lasti
  L28 to L29 -> L32 [0] lasti
  L30 to L31 -> L32 [0] lasti

Disassembly of <code object get_contact at 0x0000024C0FBC7910, file "D:\fluence\Github\mattbot\backend\app\api\v1\contacts.py", line 401>:
 401           RETURN_GENERATOR
               POP_TOP
       L1:     RESUME                   0

 407           LOAD_FAST                2 (db)
               LOAD_ATTR                1 (execute + NULL|self)

 408           LOAD_GLOBAL              3 (select + NULL)
               LOAD_GLOBAL              4 (ContactProfile)
               CALL                     1
               LOAD_ATTR                7 (where + NULL|self)

 409           LOAD_GLOBAL              4 (ContactProfile)
               LOAD_ATTR                8 (id)
               LOAD_FAST                0 (contact_id)
               COMPARE_OP              72 (==)

 410           LOAD_GLOBAL              4 (ContactProfile)
               LOAD_ATTR               10 (owner_user_id)
               LOAD_FAST                1 (current_user)
               LOAD_ATTR               12 (user)
               LOAD_ATTR                8 (id)
               COMPARE_OP              72 (==)

 411           LOAD_GLOBAL              4 (ContactProfile)
               LOAD_ATTR               14 (deleted_at)
               LOAD_ATTR               17 (is_ + NULL|self)
               LOAD_CONST               0 (None)
               CALL                     1

 408           CALL                     3

 407           CALL                     1
               GET_AWAITABLE            0
               LOAD_CONST               0 (None)
       L2:     SEND                     3 (to L5)
       L3:     YIELD_VALUE              1
       L4:     RESUME                   3
               JUMP_BACKWARD_NO_INTERRUPT 5 (to L2)
       L5:     END_SEND

 413           LOAD_ATTR               19 (scalar_one_or_none + NULL|self)
               CALL                     0

 407           STORE_FAST               3 (contact)

 415           LOAD_FAST                3 (contact)
               POP_JUMP_IF_NOT_NONE    11 (to L6)

 416           LOAD_GLOBAL             21 (AppError + NULL)
               LOAD_CONST               1 ('CONTACT_NOT_FOUND')
               LOAD_CONST               2 ('Contact not found')
               LOAD_CONST               3 (404)
               LOAD_CONST               4 (('code', 'message', 'status_code'))
               CALL_KW                  3
               RAISE_VARARGS            1

 418   L6:     LOAD_GLOBAL             23 (_to_response + NULL)
               LOAD_FAST                3 (contact)
               CALL                     1
               RETURN_VALUE

 407   L7:     CLEANUP_THROW
       L8:     JUMP_BACKWARD_NO_INTERRUPT 43 (to L5)

  --   L9:     CALL_INTRINSIC_1         3 (INTRINSIC_STOPITERATION_ERROR)
               RERAISE                  1
ExceptionTable:
  L1 to L3 -> L9 [0] lasti
  L3 to L4 -> L7 [2]
  L4 to L8 -> L9 [0] lasti

Disassembly of <code object update_contact at 0x0000024C0FBDCD10, file "D:\fluence\Github\mattbot\backend\app\api\v1\contacts.py", line 421>:
 421            RETURN_GENERATOR
                POP_TOP
        L1:     RESUME                   0

 428            LOAD_GLOBAL              1 (check_rate_limit + NULL)

 429            LOAD_CONST               1 ('contacts:update:')
                LOAD_FAST                2 (current_user)
                LOAD_ATTR                2 (user)
                LOAD_ATTR                4 (id)
                FORMAT_SIMPLE
                BUILD_STRING             2

 430            LOAD_GLOBAL              6 (settings)
                LOAD_ATTR                8 (RATE_LIMIT_API_WRITE_MAX)

 431            LOAD_GLOBAL              6 (settings)
                LOAD_ATTR               10 (RATE_LIMIT_API_WRITE_WINDOW)

 428            LOAD_CONST               2 (('max_requests', 'window_seconds'))
                CALL_KW                  3
                GET_AWAITABLE            0
                LOAD_CONST               0 (None)
        L2:     SEND                     3 (to L5)
        L3:     YIELD_VALUE              1
        L4:     RESUME                   3
                JUMP_BACKWARD_NO_INTERRUPT 5 (to L2)
        L5:     END_SEND
                UNPACK_SEQUENCE          2
                STORE_FAST_STORE_FAST   69 (allowed, _)

 433            LOAD_FAST                4 (allowed)
                TO_BOOL
                POP_JUMP_IF_TRUE        11 (to L6)

 434            LOAD_GLOBAL             13 (AppError + NULL)
                LOAD_CONST               3 ('RATE_LIMITED')
                LOAD_CONST               4 ('Too many requests')
                LOAD_CONST               5 (429)
                LOAD_CONST               6 (('code', 'message', 'status_code'))
                CALL_KW                  3
                RAISE_VARARGS            1

 436    L6:     LOAD_FAST                3 (db)
                LOAD_ATTR               15 (execute + NULL|self)

 437            LOAD_GLOBAL             17 (select + NULL)
                LOAD_GLOBAL             18 (ContactProfile)
                CALL                     1
                LOAD_ATTR               21 (where + NULL|self)

 438            LOAD_GLOBAL             18 (ContactProfile)
                LOAD_ATTR                4 (id)
                LOAD_FAST                0 (contact_id)
                COMPARE_OP              72 (==)

 439            LOAD_GLOBAL             18 (ContactProfile)
                LOAD_ATTR               22 (owner_user_id)
                LOAD_FAST                2 (current_user)
                LOAD_ATTR                2 (user)
                LOAD_ATTR                4 (id)
                COMPARE_OP              72 (==)

 440            LOAD_GLOBAL             18 (ContactProfile)
                LOAD_ATTR               24 (deleted_at)
                LOAD_ATTR               27 (is_ + NULL|self)
                LOAD_CONST               0 (None)
                CALL                     1

 437            CALL                     3

 436            CALL                     1
                GET_AWAITABLE            0
                LOAD_CONST               0 (None)
        L7:     SEND                     3 (to L10)
        L8:     YIELD_VALUE              1
        L9:     RESUME                   3
                JUMP_BACKWARD_NO_INTERRUPT 5 (to L7)
       L10:     END_SEND

 442            LOAD_ATTR               29 (scalar_one_or_none + NULL|self)
                CALL                     0

 436            STORE_FAST               6 (contact)

 444            LOAD_FAST                6 (contact)
                POP_JUMP_IF_NOT_NONE    11 (to L11)

 445            LOAD_GLOBAL             13 (AppError + NULL)
                LOAD_CONST               7 ('CONTACT_NOT_FOUND')
                LOAD_CONST               8 ('Contact not found')
                LOAD_CONST               9 (404)
                LOAD_CONST               6 (('code', 'message', 'status_code'))
                CALL_KW                  3
                RAISE_VARARGS            1

 447   L11:     LOAD_FAST                1 (body)
                LOAD_ATTR               31 (model_dump + NULL|self)
                LOAD_CONST              10 (True)
                LOAD_CONST              11 (('exclude_unset',))
                CALL_KW                  1
                STORE_FAST               7 (data)

 449            LOAD_CONST              12 ('category')
                LOAD_FAST                7 (data)
                CONTAINS_OP              0
                POP_JUMP_IF_FALSE       49 (to L16)
                LOAD_FAST                7 (data)
                LOAD_CONST              12 ('category')
                BINARY_SUBSCR
                POP_JUMP_IF_NONE        43 (to L16)

 450            LOAD_GLOBAL             33 (_validate_contact_category + NULL)
                LOAD_FAST_LOAD_FAST     50 (db, current_user)
                LOAD_ATTR                2 (user)
                LOAD_ATTR                4 (id)
                LOAD_FAST                7 (data)
                LOAD_CONST              12 ('category')
                BINARY_SUBSCR
                CALL                     3
                GET_AWAITABLE            0
                LOAD_CONST               0 (None)
       L12:     SEND                     3 (to L15)
       L13:     YIELD_VALUE              1
       L14:     RESUME                   3
                JUMP_BACKWARD_NO_INTERRUPT 5 (to L12)
       L15:     END_SEND
                POP_TOP

 452   L16:     BUILD_SET                0
                LOAD_CONST              13 (frozenset({'is_vip', 'ai_temperament_preset', 'category', 'ai_greeting_template', 'notes', 'email', 'relationship', 'display_name', 'is_blocked', 'ai_max_call_length_seconds', 'ai_swearing_rule', 'company', 'block_reason'}))
                SET_UPDATE               1
                STORE_FAST               8 (plain_fields)

 458            LOAD_FAST                8 (plain_fields)
                GET_ITER
       L17:     FOR_ITER                31 (to L22)
                STORE_FAST               9 (field)

 459            LOAD_FAST_LOAD_FAST    151 (field, data)
                CONTAINS_OP              0
       L18:     POP_JUMP_IF_TRUE         2 (to L19)
                JUMP_BACKWARD           10 (to L17)
       L19:     LOAD_FAST_LOAD_FAST    121 (data, field)
                BINARY_SUBSCR
       L20:     POP_JUMP_IF_NOT_NONE     2 (to L21)
                JUMP_BACKWARD           17 (to L17)

 460   L21:     LOAD_GLOBAL             35 (setattr + NULL)
                LOAD_FAST_LOAD_FAST    105 (contact, field)
                LOAD_FAST_LOAD_FAST    121 (data, field)
                BINARY_SUBSCR
                CALL                     3
                POP_TOP
                JUMP_BACKWARD           33 (to L17)

 458   L22:     END_FOR
                POP_TOP

 462            LOAD_FAST                7 (data)
                LOAD_ATTR               37 (get + NULL|self)
                LOAD_CONST              14 ('ai_greeting_instructions')
                CALL                     1
                TO_BOOL
                POP_JUMP_IF_FALSE       50 (to L23)

 463            LOAD_GLOBAL             39 (encrypt_field + NULL)
                LOAD_FAST                7 (data)
                LOAD_CONST              14 ('ai_greeting_instructions')
                BINARY_SUBSCR
                LOAD_ATTR               41 (encode + NULL|self)
                LOAD_CONST              15 ('utf-8')
                CALL                     1
                CALL                     1
                UNPACK_SEQUENCE          3
                STORE_FAST_STORE_FAST  171 (g_ct, g_n)
                STORE_FAST              12 (g_kv)

 464            LOAD_FAST_LOAD_FAST    166 (g_ct, contact)
                STORE_ATTR              21 (ai_greeting_instructions_ciphertext)

 465            LOAD_FAST_LOAD_FAST    182 (g_n, contact)
                STORE_ATTR              22 (ai_greeting_instructions_nonce)

 466            LOAD_FAST_LOAD_FAST    198 (g_kv, contact)
                STORE_ATTR              23 (ai_greeting_instructions_key_version)

 468   L23:     LOAD_FAST                7 (data)
                LOAD_ATTR               37 (get + NULL|self)
                LOAD_CONST              16 ('ai_custom_instructions')
                CALL                     1
                TO_BOOL
                POP_JUMP_IF_FALSE       50 (to L24)

 469            LOAD_GLOBAL             39 (encrypt_field + NULL)
                LOAD_FAST                7 (data)
                LOAD_CONST              16 ('ai_custom_instructions')
                BINARY_SUBSCR
                LOAD_ATTR               41 (encode + NULL|self)
                LOAD_CONST              15 ('utf-8')
                CALL                     1
                CALL                     1
                UNPACK_SEQUENCE          3
                STORE_FAST_STORE_FAST  222 (i_ct, i_n)
                STORE_FAST              15 (i_kv)

 470            LOAD_FAST_LOAD_FAST    214 (i_ct, contact)
                STORE_ATTR              24 (ai_custom_instructions_ciphertext)

 471            LOAD_FAST_LOAD_FAST    230 (i_n, contact)
                STORE_ATTR              25 (ai_custom_instructions_nonce)

 472            LOAD_FAST_LOAD_FAST    246 (i_kv, contact)
                STORE_ATTR              26 (ai_custom_instructions_key_version)

 474   L24:     LOAD_FAST                1 (body)
                LOAD_ATTR               54 (clear_ai_temperament)
                TO_BOOL
                POP_JUMP_IF_FALSE        7 (to L25)

 475            LOAD_CONST               0 (None)
                LOAD_FAST                6 (contact)
                STORE_ATTR              28 (ai_temperament_preset)

 476   L25:     LOAD_FAST                1 (body)
                LOAD_ATTR               58 (clear_ai_greeting_template)
                TO_BOOL
                POP_JUMP_IF_FALSE        7 (to L26)

 477            LOAD_CONST               0 (None)
                LOAD_FAST                6 (contact)
                STORE_ATTR              30 (ai_greeting_template)

 478   L26:     LOAD_FAST                1 (body)
                LOAD_ATTR               62 (clear_ai_greeting_instructions)
                TO_BOOL
                POP_JUMP_IF_FALSE       21 (to L27)

 479            LOAD_CONST               0 (None)
                LOAD_FAST                6 (contact)
                STORE_ATTR              21 (ai_greeting_instructions_ciphertext)

 480            LOAD_CONST               0 (None)
                LOAD_FAST                6 (contact)
                STORE_ATTR              22 (ai_greeting_instructions_nonce)

 481            LOAD_CONST               0 (None)
                LOAD_FAST                6 (contact)
                STORE_ATTR              23 (ai_greeting_instructions_key_version)

 482   L27:     LOAD_FAST                1 (body)
                LOAD_ATTR               64 (clear_ai_swearing_rule)
                TO_BOOL
                POP_JUMP_IF_FALSE        7 (to L28)

 483            LOAD_CONST               0 (None)
                LOAD_FAST                6 (contact)
                STORE_ATTR              33 (ai_swearing_rule)

 484   L28:     LOAD_FAST                1 (body)
                LOAD_ATTR               68 (clear_ai_max_call_length)
                TO_BOOL
                POP_JUMP_IF_FALSE        7 (to L29)

 485            LOAD_CONST               0 (None)
                LOAD_FAST                6 (contact)
                STORE_ATTR              35 (ai_max_call_length_seconds)

 486   L29:     LOAD_FAST                1 (body)
                LOAD_ATTR               72 (clear_ai_custom_instructions)
                TO_BOOL
                POP_JUMP_IF_FALSE       21 (to L30)

 487            LOAD_CONST               0 (None)
                LOAD_FAST                6 (contact)
                STORE_ATTR              24 (ai_custom_instructions_ciphertext)

 488            LOAD_CONST               0 (None)
                LOAD_FAST                6 (contact)
                STORE_ATTR              25 (ai_custom_instructions_nonce)

 489            LOAD_CONST               0 (None)
                LOAD_FAST                6 (contact)
                STORE_ATTR              26 (ai_custom_instructions_key_version)

 491   L30:     LOAD_FAST                3 (db)
                LOAD_ATTR               75 (flush + NULL|self)
                CALL                     0
                GET_AWAITABLE            0
                LOAD_CONST               0 (None)
       L31:     SEND                     3 (to L34)
       L32:     YIELD_VALUE              1
       L33:     RESUME                   3
                JUMP_BACKWARD_NO_INTERRUPT 5 (to L31)
       L34:     END_SEND
                POP_TOP

 492            LOAD_GLOBAL             77 (_to_response + NULL)
                LOAD_FAST                6 (contact)
                CALL                     1
                RETURN_VALUE

 428   L35:     CLEANUP_THROW
       L36:     EXTENDED_ARG             2
                JUMP_BACKWARD_NO_INTERRUPT 653 (to L5)

 436   L37:     CLEANUP_THROW
       L38:     EXTENDED_ARG             1
                JUMP_BACKWARD_NO_INTERRUPT 498 (to L10)

 450   L39:     CLEANUP_THROW
       L40:     EXTENDED_ARG             1
                JUMP_BACKWARD_NO_INTERRUPT 403 (to L15)

 491   L41:     CLEANUP_THROW
       L42:     JUMP_BACKWARD_NO_INTERRUPT 24 (to L34)

  --   L43:     CALL_INTRINSIC_1         3 (INTRINSIC_STOPITERATION_ERROR)
                RERAISE                  1
ExceptionTable:
  L1 to L3 -> L43 [0] lasti
  L3 to L4 -> L35 [2]
  L4 to L8 -> L43 [0] lasti
  L8 to L9 -> L37 [2]
  L9 to L13 -> L43 [0] lasti
  L13 to L14 -> L39 [2]
  L14 to L18 -> L43 [0] lasti
  L19 to L20 -> L43 [0] lasti
  L21 to L32 -> L43 [0] lasti
  L32 to L33 -> L41 [2]
  L33 to L36 -> L43 [0] lasti
  L37 to L38 -> L43 [0] lasti
  L39 to L40 -> L43 [0] lasti
  L41 to L42 -> L43 [0] lasti

Disassembly of <code object delete_contact at 0x0000024C0FA8F3A0, file "D:\fluence\Github\mattbot\backend\app\api\v1\contacts.py", line 495>:
 495            RETURN_GENERATOR
                POP_TOP
        L1:     RESUME                   0

 501            LOAD_GLOBAL              1 (check_rate_limit + NULL)

 502            LOAD_CONST               1 ('contacts:delete:')
                LOAD_FAST                1 (current_user)
                LOAD_ATTR                2 (user)
                LOAD_ATTR                4 (id)
                FORMAT_SIMPLE
                BUILD_STRING             2

 503            LOAD_GLOBAL              6 (settings)
                LOAD_ATTR                8 (RATE_LIMIT_API_WRITE_MAX)

 504            LOAD_GLOBAL              6 (settings)
                LOAD_ATTR               10 (RATE_LIMIT_API_WRITE_WINDOW)

 501            LOAD_CONST               2 (('max_requests', 'window_seconds'))
                CALL_KW                  3
                GET_AWAITABLE            0
                LOAD_CONST               0 (None)
        L2:     SEND                     3 (to L5)
        L3:     YIELD_VALUE              1
        L4:     RESUME                   3
                JUMP_BACKWARD_NO_INTERRUPT 5 (to L2)
        L5:     END_SEND
                UNPACK_SEQUENCE          2
                STORE_FAST_STORE_FAST   52 (allowed, _)

 506            LOAD_FAST                3 (allowed)
                TO_BOOL
                POP_JUMP_IF_TRUE        11 (to L6)

 507            LOAD_GLOBAL             13 (AppError + NULL)
                LOAD_CONST               3 ('RATE_LIMITED')
                LOAD_CONST               4 ('Too many requests')
                LOAD_CONST               5 (429)
                LOAD_CONST               6 (('code', 'message', 'status_code'))
                CALL_KW                  3
                RAISE_VARARGS            1

 509    L6:     LOAD_FAST                2 (db)
                LOAD_ATTR               15 (execute + NULL|self)

 510            LOAD_GLOBAL             17 (select + NULL)
                LOAD_GLOBAL             18 (ContactProfile)
                CALL                     1
                LOAD_ATTR               21 (where + NULL|self)

 511            LOAD_GLOBAL             18 (ContactProfile)
                LOAD_ATTR                4 (id)
                LOAD_FAST                0 (contact_id)
                COMPARE_OP              72 (==)

 512            LOAD_GLOBAL             18 (ContactProfile)
                LOAD_ATTR               22 (owner_user_id)
                LOAD_FAST                1 (current_user)
                LOAD_ATTR                2 (user)
                LOAD_ATTR                4 (id)
                COMPARE_OP              72 (==)

 513            LOAD_GLOBAL             18 (ContactProfile)
                LOAD_ATTR               24 (deleted_at)
                LOAD_ATTR               27 (is_ + NULL|self)
                LOAD_CONST               0 (None)
                CALL                     1

 510            CALL                     3

 509            CALL                     1
                GET_AWAITABLE            0
                LOAD_CONST               0 (None)
        L7:     SEND                     3 (to L10)
        L8:     YIELD_VALUE              1
        L9:     RESUME                   3
                JUMP_BACKWARD_NO_INTERRUPT 5 (to L7)
       L10:     END_SEND

 515            LOAD_ATTR               29 (scalar_one_or_none + NULL|self)
                CALL                     0

 509            STORE_FAST               5 (contact)

 517            LOAD_FAST                5 (contact)
                POP_JUMP_IF_NOT_NONE    11 (to L11)

 518            LOAD_GLOBAL             13 (AppError + NULL)
                LOAD_CONST               7 ('CONTACT_NOT_FOUND')
                LOAD_CONST               8 ('Contact not found')
                LOAD_CONST               9 (404)
                LOAD_CONST               6 (('code', 'message', 'status_code'))
                CALL_KW                  3
                RAISE_VARARGS            1

 520   L11:     LOAD_GLOBAL             30 (datetime)
                LOAD_ATTR               32 (now)
                PUSH_NULL
                LOAD_GLOBAL             34 (UTC)
                CALL                     1
                LOAD_FAST                5 (contact)
                STORE_ATTR              12 (deleted_at)

 521            LOAD_GLOBAL             37 (log_event + NULL)

 522            LOAD_FAST                2 (db)

 523            LOAD_FAST                1 (current_user)
                LOAD_ATTR                2 (user)
                LOAD_ATTR                4 (id)

 524            LOAD_CONST              10 ('contact_deleted')

 525            LOAD_FAST                1 (current_user)
                LOAD_ATTR                2 (user)
                LOAD_ATTR                4 (id)

 526            LOAD_CONST              11 ('contact_profile')

 527            LOAD_FAST                5 (contact)
                LOAD_ATTR                4 (id)

 521            LOAD_CONST              12 (('owner_user_id', 'event_type', 'actor_id', 'target_type', 'target_id'))
                CALL_KW                  6
                GET_AWAITABLE            0
                LOAD_CONST               0 (None)
       L12:     SEND                     3 (to L15)
       L13:     YIELD_VALUE              1
       L14:     RESUME                   3
                JUMP_BACKWARD_NO_INTERRUPT 5 (to L12)
       L15:     END_SEND
                POP_TOP

 529            LOAD_FAST                2 (db)
                LOAD_ATTR               39 (flush + NULL|self)
                CALL                     0
                GET_AWAITABLE            0
                LOAD_CONST               0 (None)
       L16:     SEND                     3 (to L19)
       L17:     YIELD_VALUE              1
       L18:     RESUME                   3
                JUMP_BACKWARD_NO_INTERRUPT 5 (to L16)
       L19:     END_SEND
                POP_TOP

 530            LOAD_CONST              13 ('deleted')
                LOAD_CONST              14 (True)
                BUILD_MAP                1
                RETURN_VALUE

 501   L20:     CLEANUP_THROW
       L21:     EXTENDED_ARG             1
                JUMP_BACKWARD_NO_INTERRUPT 322 (to L5)

 509   L22:     CLEANUP_THROW
       L23:     JUMP_BACKWARD_NO_INTERRUPT 166 (to L10)

 521   L24:     CLEANUP_THROW
       L25:     JUMP_BACKWARD_NO_INTERRUPT 37 (to L15)

 529   L26:     CLEANUP_THROW
       L27:     JUMP_BACKWARD_NO_INTERRUPT 15 (to L19)

  --   L28:     CALL_INTRINSIC_1         3 (INTRINSIC_STOPITERATION_ERROR)
                RERAISE                  1
ExceptionTable:
  L1 to L3 -> L28 [0] lasti
  L3 to L4 -> L20 [2]
  L4 to L8 -> L28 [0] lasti
  L8 to L9 -> L22 [2]
  L9 to L13 -> L28 [0] lasti
  L13 to L14 -> L24 [2]
  L14 to L17 -> L28 [0] lasti
  L17 to L18 -> L26 [2]
  L18 to L21 -> L28 [0] lasti
  L22 to L23 -> L28 [0] lasti
  L24 to L25 -> L28 [0] lasti
  L26 to L27 -> L28 [0] lasti
