# Bytecode dump of: 004_billing_telephony_theme.pyc
# co_filename: D:\fluence\Github\mattbot\backend\alembic\versions\004_billing_telephony_theme.py
# co_names: ('__doc__', 'collections.abc', 'Sequence', 'sqlalchemy', 'sa', 'sqlalchemy.dialects', 'postgresql', 'alembic', 'op', 'revision', 'str', '__annotations__', 'down_revision', 'branch_labels', 'depends_on', 'upgrade', 'downgrade')
# co_consts (strings): ['Add billing, telephony, and theme_preference\n\nRevision ID: 004\nRevises: 003\nCreate Date: 2026-02-23\n', '004', 'revision', '003', 'down_revision', 'branch_labels', 'depends_on']

# --- Nested code object: upgrade ---
    # co_names: ('op', 'add_column', 'sa', 'Column', 'String', 'text', 'create_check_constraint', 'create_table', 'postgresql', 'UUID', 'ForeignKey', 'Text', 'DateTime', 'Boolean', 'Integer', 'CheckConstraint', 'create_index', 'JSONB', 'LargeBinary')
    # co_varnames: ()
    # co_consts (strings): ['user_settings', 'theme_preference', "'system'", 'ck_user_settings_theme_preference', "theme_preference IN ('system', 'light', 'dark')", 'billing_customers', 'owner_user_id', 'users.id', 'CASCADE', 'stripe_customer_id', 'created_at', 'now()', 'updated_at', 'billing_subscriptions', 'id', 'gen_random_uuid()', 'plan', 'status', 'stripe_subscription_id', 'stripe_price_id', 'current_period_start', 'current_period_end', 'cancel_at_period_end', 'false', 'canceled_at', 'minutes_included', "plan IN ('free', 'standard', 'pro')", 'ck_billing_subscriptions_plan', "status IN ('active', 'past_due', 'canceled', 'incomplete', 'trialing')", 'ck_billing_subscriptions_status', 'ix_billing_subscriptions_owner', 'billing_payment_methods', 'stripe_payment_method_id', 'brand', 'last4', 'exp_month', 'exp_year', 'is_default', 'true', 'ix_billing_payment_methods_owner', 'billing_usage', 'minutes_used', '0', 'last_usage_source', 'billing_events', 'provider_event_id', 'event_type', 'payload_redacted', 'processed_at', 'ix_billing_events_event_type', 'user_numbers', 'twilio_number_sid', 'e164', 'provisioned_at', 'released_at', "status IN ('provisioning', 'active', 'released', 'failed')", 'ck_user_numbers_status', 'call_mode_configs', 'mode_a_enabled', 'mode_b_enabled', 'access_control', "'everyone'", 'personal_number_e164_hash', 'personal_number_e164_ciphertext', 'personal_number_nonce', 'personal_number_key_version', 'last_verified_at', 'verification_status', "'unverified'", "access_control IN ('everyone', 'contacts', 'vip')", 'ck_call_mode_configs_access_control', "verification_status IN ('unverified', 'pending', 'verified', 'failed')", 'ck_call_mode_configs_verification_status', 'forwarding_verification_attempts', 'verification_code', 'initiated_at', 'completed_at', 'twilio_call_sid', 'details_redacted', "status IN ('pending', 'passed', 'failed', 'expired')", 'ck_fwd_verification_status', 'ix_fwd_verification_user_status']
 20           RESUME                   0

 22           LOAD_GLOBAL              0 (op)
              LOAD_ATTR                2 (add_column)
              PUSH_NULL

 23           LOAD_CONST               1 ('user_settings')

 24           LOAD_GLOBAL              4 (sa)
              LOAD_ATTR                6 (Column)
              PUSH_NULL

 25           LOAD_CONST               2 ('theme_preference')

 26           LOAD_GLOBAL              4 (sa)
              LOAD_ATTR                8 (String)
              PUSH_NULL
              LOAD_CONST               3 (10)
              CALL                     1

 27           LOAD_CONST               4 (False)

 28           LOAD_GLOBAL              4 (sa)
              LOAD_ATTR               10 (text)
              PUSH_NULL
              LOAD_CONST               5 ("'system'")
              CALL                     1

 24           LOAD_CONST               6 (('nullable', 'server_default'))
              CALL_KW                  4

 22           CALL                     2
              POP_TOP

 31           LOAD_GLOBAL              0 (op)
              LOAD_ATTR               12 (create_check_constraint)
              PUSH_NULL

 32           LOAD_CONST               7 ('ck_user_settings_theme_preference')

 33           LOAD_CONST               1 ('user_settings')

 34           LOAD_CONST               8 ("theme_preference IN ('system', 'light', 'dark')")

 31           CALL                     3
              POP_TOP

 38           LOAD_GLOBAL              0 (op)
              LOAD_ATTR               14 (create_table)
              PUSH_NULL

 39           LOAD_CONST               9 ('billing_customers')

 40           LOAD_GLOBAL              4 (sa)
              LOAD_ATTR                6 (Column)
              PUSH_NULL

 41           LOAD_CONST              10 ('owner_user_id')

 42           LOAD_GLOBAL             16 (postgresql)
              LOAD_ATTR               18 (UUID)
              PUSH_NULL
              LOAD_CONST              11 (True)
              LOAD_CONST              12 (('as_uuid',))
              CALL_KW                  1

 43           LOAD_GLOBAL              4 (sa)
              LOAD_ATTR               20 (ForeignKey)
              PUSH_NULL
              LOAD_CONST              13 ('users.id')
              LOAD_CONST              14 ('CASCADE')
              LOAD_CONST              15 (('ondelete',))
              CALL_KW                  2

 44           LOAD_CONST              11 (True)

 40           LOAD_CONST              16 (('primary_key',))
              CALL_KW                  4

 46           LOAD_GLOBAL              4 (sa)
              LOAD_ATTR                6 (Column)
              PUSH_NULL
              LOAD_CONST              17 ('stripe_customer_id')
              LOAD_GLOBAL              4 (sa)
              LOAD_ATTR               22 (Text)
              PUSH_NULL
              CALL                     0
              LOAD_CONST              11 (True)
              LOAD_CONST              11 (True)
              LOAD_CONST              18 (('nullable', 'unique'))
              CALL_KW                  4

 47           LOAD_GLOBAL              4 (sa)
              LOAD_ATTR                6 (Column)
              PUSH_NULL

 48           LOAD_CONST              19 ('created_at')

 49           LOAD_GLOBAL              4 (sa)
              LOAD_ATTR               24 (DateTime)
              PUSH_NULL
              LOAD_CONST              11 (True)
              LOAD_CONST              20 (('timezone',))
              CALL_KW                  1

 50           LOAD_CONST               4 (False)

 51           LOAD_GLOBAL              4 (sa)
              LOAD_ATTR               10 (text)
              PUSH_NULL
              LOAD_CONST              21 ('now()')
              CALL                     1

 47           LOAD_CONST               6 (('nullable', 'server_default'))
              CALL_KW                  4

 53           LOAD_GLOBAL              4 (sa)
              LOAD_ATTR                6 (Column)
              PUSH_NULL

 54           LOAD_CONST              22 ('updated_at')

 55           LOAD_GLOBAL              4 (sa)
              LOAD_ATTR               24 (DateTime)
              PUSH_NULL
              LOAD_CONST              11 (True)
              LOAD_CONST              20 (('timezone',))
              CALL_KW                  1

 56           LOAD_CONST               4 (False)

 57           LOAD_GLOBAL              4 (sa)
              LOAD_ATTR               10 (text)
              PUSH_NULL
              LOAD_CONST              21 ('now()')
              CALL                     1

 53           LOAD_CONST               6 (('nullable', 'server_default'))
              CALL_KW                  4

 38           CALL                     5
              POP_TOP

 62           LOAD_GLOBAL              0 (op)
              LOAD_ATTR               14 (create_table)
              PUSH_NULL

 63           LOAD_CONST              23 ('billing_subscriptions')

 64           LOAD_GLOBAL              4 (sa)
              LOAD_ATTR                6 (Column)
              PUSH_NULL

 65           LOAD_CONST              24 ('id')

 66           LOAD_GLOBAL             16 (postgresql)
              LOAD_ATTR               18 (UUID)
              PUSH_NULL
              LOAD_CONST              11 (True)
              LOAD_CONST              12 (('as_uuid',))
              CALL_KW                  1

 67           LOAD_CONST              11 (True)

 68           LOAD_GLOBAL              4 (sa)
              LOAD_ATTR               10 (text)
              PUSH_NULL
              LOAD_CONST              25 ('gen_random_uuid()')
              CALL                     1

 64           LOAD_CONST              26 (('primary_key', 'server_default'))
              CALL_KW                  4

 70           LOAD_GLOBAL              4 (sa)
              LOAD_ATTR                6 (Column)
              PUSH_NULL

 71           LOAD_CONST              10 ('owner_user_id')

 72           LOAD_GLOBAL             16 (postgresql)
              LOAD_ATTR               18 (UUID)
              PUSH_NULL
              LOAD_CONST              11 (True)
              LOAD_CONST              12 (('as_uuid',))
              CALL_KW                  1

 73           LOAD_GLOBAL              4 (sa)
              LOAD_ATTR               20 (ForeignKey)
              PUSH_NULL
              LOAD_CONST              13 ('users.id')
              LOAD_CONST              14 ('CASCADE')
              LOAD_CONST              15 (('ondelete',))
              CALL_KW                  2

 74           LOAD_CONST               4 (False)

 75           LOAD_CONST              11 (True)

 70           LOAD_CONST              18 (('nullable', 'unique'))
              CALL_KW                  5

 77           LOAD_GLOBAL              4 (sa)
              LOAD_ATTR                6 (Column)
              PUSH_NULL
              LOAD_CONST              27 ('plan')
              LOAD_GLOBAL              4 (sa)
              LOAD_ATTR                8 (String)
              PUSH_NULL
              LOAD_CONST              28 (20)
              CALL                     1
              LOAD_CONST               4 (False)
              LOAD_CONST              29 (('nullable',))
              CALL_KW                  3

 78           LOAD_GLOBAL              4 (sa)
              LOAD_ATTR                6 (Column)
              PUSH_NULL
              LOAD_CONST              30 ('status')
              LOAD_GLOBAL              4 (sa)
              LOAD_ATTR                8 (String)
              PUSH_NULL
              LOAD_CONST              28 (20)
              CALL                     1
              LOAD_CONST               4 (False)
              LOAD_CONST              29 (('nullable',))
              CALL_KW                  3

 79           LOAD_GLOBAL              4 (sa)
              LOAD_ATTR                6 (Column)
              PUSH_NULL
              LOAD_CONST              31 ('stripe_subscription_id')
              LOAD_GLOBAL              4 (sa)
              LOAD_ATTR               22 (Text)
              PUSH_NULL
              CALL                     0
              LOAD_CONST              11 (True)
              LOAD_CONST              11 (True)
              LOAD_CONST              18 (('nullable', 'unique'))
              CALL_KW                  4

 80           LOAD_GLOBAL              4 (sa)
              LOAD_ATTR                6 (Column)
              PUSH_NULL
              LOAD_CONST              32 ('stripe_price_id')
              LOAD_GLOBAL              4 (sa)
              LOAD_ATTR               22 (Text)
              PUSH_NULL
              CALL                     0
              LOAD_CONST              11 (True)
              LOAD_CONST              29 (('nullable',))
              CALL_KW                  3

 81           LOAD_GLOBAL              4 (sa)
              LOAD_ATTR                6 (Column)
              PUSH_NULL
              LOAD_CONST              33 ('current_period_start')
              LOAD_GLOBAL              4 (sa)
              LOAD_ATTR               24 (DateTime)
              PUSH_NULL
              LOAD_CONST              11 (True)
              LOAD_CONST              20 (('timezone',))
              CALL_KW                  1
              LOAD_CONST              11 (True)
              LOAD_CONST              29 (('nullable',))
              CALL_KW                  3

 82           LOAD_GLOBAL              4 (sa)
              LOAD_ATTR                6 (Column)
              PUSH_NULL
              LOAD_CONST              34 ('current_period_end')
              LOAD_GLOBAL              4 (sa)
              LOAD_ATTR               24 (DateTime)
              PUSH_NULL
              LOAD_CONST              11 (True)
              LOAD_CONST              20 (('timezone',))
              CALL_KW                  1
              LOAD_CONST              11 (True)
              LOAD_CONST              29 (('nullable',))
              CALL_KW                  3

 83           LOAD_GLOBAL              4 (sa)
              LOAD_ATTR                6 (Column)
              PUSH_NULL

 84           LOAD_CONST              35 ('cancel_at_period_end')

 85           LOAD_GLOBAL              4 (sa)
              LOAD_ATTR               26 (Boolean)
              PUSH_NULL
              CALL                     0

 86           LOAD_CONST               4 (False)

 87           LOAD_GLOBAL              4 (sa)
              LOAD_ATTR               10 (text)
              PUSH_NULL
              LOAD_CONST              36 ('false')
              CALL                     1

 83           LOAD_CONST               6 (('nullable', 'server_default'))
              CALL_KW                  4

 89           LOAD_GLOBAL              4 (sa)
              LOAD_ATTR                6 (Column)
              PUSH_NULL
              LOAD_CONST              37 ('canceled_at')
              LOAD_GLOBAL              4 (sa)
              LOAD_ATTR               24 (DateTime)
              PUSH_NULL
              LOAD_CONST              11 (True)
              LOAD_CONST              20 (('timezone',))
              CALL_KW                  1
              LOAD_CONST              11 (True)
              LOAD_CONST              29 (('nullable',))
              CALL_KW                  3

 90           LOAD_GLOBAL              4 (sa)
              LOAD_ATTR                6 (Column)
              PUSH_NULL
              LOAD_CONST              38 ('minutes_included')
              LOAD_GLOBAL              4 (sa)
              LOAD_ATTR               28 (Integer)
              PUSH_NULL
              CALL                     0
              LOAD_CONST               4 (False)
              LOAD_CONST              29 (('nullable',))
              CALL_KW                  3

 91           LOAD_GLOBAL              4 (sa)
              LOAD_ATTR                6 (Column)
              PUSH_NULL

 92           LOAD_CONST              19 ('created_at')

 93           LOAD_GLOBAL              4 (sa)
              LOAD_ATTR               24 (DateTime)
              PUSH_NULL
              LOAD_CONST              11 (True)
              LOAD_CONST              20 (('timezone',))
              CALL_KW                  1

 94           LOAD_CONST               4 (False)

 95           LOAD_GLOBAL              4 (sa)
              LOAD_ATTR               10 (text)
              PUSH_NULL
              LOAD_CONST              21 ('now()')
              CALL                     1

 91           LOAD_CONST               6 (('nullable', 'server_default'))
              CALL_KW                  4

 97           LOAD_GLOBAL              4 (sa)
              LOAD_ATTR                6 (Column)
              PUSH_NULL

 98           LOAD_CONST              22 ('updated_at')

 99           LOAD_GLOBAL              4 (sa)
              LOAD_ATTR               24 (DateTime)
              PUSH_NULL
              LOAD_CONST              11 (True)
              LOAD_CONST              20 (('timezone',))
              CALL_KW                  1

100           LOAD_CONST               4 (False)

101           LOAD_GLOBAL              4 (sa)
              LOAD_ATTR               10 (text)
              PUSH_NULL
              LOAD_CONST              21 ('now()')
              CALL                     1

 97           LOAD_CONST               6 (('nullable', 'server_default'))
              CALL_KW                  4

103           LOAD_GLOBAL              4 (sa)
              LOAD_ATTR               30 (CheckConstraint)
              PUSH_NULL

104           LOAD_CONST              39 ("plan IN ('free', 'standard', 'pro')")

105           LOAD_CONST              40 ('ck_billing_subscriptions_plan')

103           LOAD_CONST              41 (('name',))
              CALL_KW                  2

107           LOAD_GLOBAL              4 (sa)
              LOAD_ATTR               30 (CheckConstraint)
              PUSH_NULL

108           LOAD_CONST              42 ("status IN ('active', 'past_due', 'canceled', 'incomplete', 'trialing')")

109           LOAD_CONST              43 ('ck_billing_subscriptions_status')

107           LOAD_CONST              41 (('name',))
              CALL_KW                  2

 62           CALL                    16
              POP_TOP

112           LOAD_GLOBAL              0 (op)
              LOAD_ATTR               32 (create_index)
              PUSH_NULL

113           LOAD_CONST              44 ('ix_billing_subscriptions_owner')

114           LOAD_CONST              23 ('billing_subscriptions')

115           LOAD_CONST              10 ('owner_user_id')
              BUILD_LIST               1

112           CALL                     3
              POP_TOP

119           LOAD_GLOBAL              0 (op)
              LOAD_ATTR               14 (create_table)
              PUSH_NULL

120           LOAD_CONST              45 ('billing_payment_methods')

121           LOAD_GLOBAL              4 (sa)
              LOAD_ATTR                6 (Column)
              PUSH_NULL

122           LOAD_CONST              24 ('id')

123           LOAD_GLOBAL             16 (postgresql)
              LOAD_ATTR               18 (UUID)
              PUSH_NULL
              LOAD_CONST              11 (True)
              LOAD_CONST              12 (('as_uuid',))
              CALL_KW                  1

124           LOAD_CONST              11 (True)

125           LOAD_GLOBAL              4 (sa)
              LOAD_ATTR               10 (text)
              PUSH_NULL
              LOAD_CONST              25 ('gen_random_uuid()')
              CALL                     1

121           LOAD_CONST              26 (('primary_key', 'server_default'))
              CALL_KW                  4

127           LOAD_GLOBAL              4 (sa)
              LOAD_ATTR                6 (Column)
              PUSH_NULL

128           LOAD_CONST              10 ('owner_user_id')

129           LOAD_GLOBAL             16 (postgresql)
              LOAD_ATTR               18 (UUID)
              PUSH_NULL
              LOAD_CONST              11 (True)
              LOAD_CONST              12 (('as_uuid',))
              CALL_KW                  1

130           LOAD_GLOBAL              4 (sa)
              LOAD_ATTR               20 (ForeignKey)
              PUSH_NULL
              LOAD_CONST              13 ('users.id')
              LOAD_CONST              14 ('CASCADE')
              LOAD_CONST              15 (('ondelete',))
              CALL_KW                  2

131           LOAD_CONST               4 (False)

127           LOAD_CONST              29 (('nullable',))
              CALL_KW                  4

133           LOAD_GLOBAL              4 (sa)
              LOAD_ATTR                6 (Column)
              PUSH_NULL

134           LOAD_CONST              46 ('stripe_payment_method_id')
              LOAD_GLOBAL              4 (sa)
              LOAD_ATTR               22 (Text)
              PUSH_NULL
              CALL                     0
              LOAD_CONST              11 (True)
              LOAD_CONST              11 (True)

133           LOAD_CONST              18 (('nullable', 'unique'))
              CALL_KW                  4

136           LOAD_GLOBAL              4 (sa)
              LOAD_ATTR                6 (Column)
              PUSH_NULL
              LOAD_CONST              47 ('brand')
              LOAD_GLOBAL              4 (sa)
              LOAD_ATTR               22 (Text)
              PUSH_NULL
              CALL                     0
              LOAD_CONST              11 (True)
              LOAD_CONST              29 (('nullable',))
              CALL_KW                  3

137           LOAD_GLOBAL              4 (sa)
              LOAD_ATTR                6 (Column)
              PUSH_NULL
              LOAD_CONST              48 ('last4')
              LOAD_GLOBAL              4 (sa)
              LOAD_ATTR               22 (Text)
              PUSH_NULL
              CALL                     0
              LOAD_CONST              11 (True)
              LOAD_CONST              29 (('nullable',))
              CALL_KW                  3

138           LOAD_GLOBAL              4 (sa)
              LOAD_ATTR                6 (Column)
              PUSH_NULL
              LOAD_CONST              49 ('exp_month')
              LOAD_GLOBAL              4 (sa)
              LOAD_ATTR               28 (Integer)
              PUSH_NULL
              CALL                     0
              LOAD_CONST              11 (True)
              LOAD_CONST              29 (('nullable',))
              CALL_KW                  3

139           LOAD_GLOBAL              4 (sa)
              LOAD_ATTR                6 (Column)
              PUSH_NULL
              LOAD_CONST              50 ('exp_year')
              LOAD_GLOBAL              4 (sa)
              LOAD_ATTR               28 (Integer)
              PUSH_NULL
              CALL                     0
              LOAD_CONST              11 (True)
              LOAD_CONST              29 (('nullable',))
              CALL_KW                  3

140           LOAD_GLOBAL              4 (sa)
              LOAD_ATTR                6 (Column)
              PUSH_NULL

141           LOAD_CONST              51 ('is_default')

142           LOAD_GLOBAL              4 (sa)
              LOAD_ATTR               26 (Boolean)
              PUSH_NULL
              CALL                     0

143           LOAD_CONST               4 (False)

144           LOAD_GLOBAL              4 (sa)
              LOAD_ATTR               10 (text)
              PUSH_NULL
              LOAD_CONST              52 ('true')
              CALL                     1

140           LOAD_CONST               6 (('nullable', 'server_default'))
              CALL_KW                  4

146           LOAD_GLOBAL              4 (sa)
              LOAD_ATTR                6 (Column)
              PUSH_NULL

147           LOAD_CONST              19 ('created_at')

148           LOAD_GLOBAL              4 (sa)
              LOAD_ATTR               24 (DateTime)
              PUSH_NULL
              LOAD_CONST              11 (True)
              LOAD_CONST              20 (('timezone',))
              CALL_KW                  1

149           LOAD_CONST               4 (False)

150           LOAD_GLOBAL              4 (sa)
              LOAD_ATTR               10 (text)
              PUSH_NULL
              LOAD_CONST              21 ('now()')
              CALL                     1

146           LOAD_CONST               6 (('nullable', 'server_default'))
              CALL_KW                  4

152           LOAD_GLOBAL              4 (sa)
              LOAD_ATTR                6 (Column)
              PUSH_NULL

153           LOAD_CONST              22 ('updated_at')

154           LOAD_GLOBAL              4 (sa)
              LOAD_ATTR               24 (DateTime)
              PUSH_NULL
              LOAD_CONST              11 (True)
              LOAD_CONST              20 (('timezone',))
              CALL_KW                  1

155           LOAD_CONST               4 (False)

156           LOAD_GLOBAL              4 (sa)
              LOAD_ATTR               10 (text)
              PUSH_NULL
              LOAD_CONST              21 ('now()')
              CALL                     1

152           LOAD_CONST               6 (('nullable', 'server_default'))
              CALL_KW                  4

119           CALL                    11
              POP_TOP

159           LOAD_GLOBAL              0 (op)
              LOAD_ATTR               32 (create_index)
              PUSH_NULL

160           LOAD_CONST              53 ('ix_billing_payment_methods_owner')

161           LOAD_CONST              45 ('billing_payment_methods')

162           LOAD_CONST              10 ('owner_user_id')
              BUILD_LIST               1

159           CALL                     3
              POP_TOP

166           LOAD_GLOBAL              0 (op)
              LOAD_ATTR               14 (create_table)
              PUSH_NULL

167           LOAD_CONST              54 ('billing_usage')

168           LOAD_GLOBAL              4 (sa)
              LOAD_ATTR                6 (Column)
              PUSH_NULL

169           LOAD_CONST              10 ('owner_user_id')

170           LOAD_GLOBAL             16 (postgresql)
              LOAD_ATTR               18 (UUID)
              PUSH_NULL
              LOAD_CONST              11 (True)
              LOAD_CONST              12 (('as_uuid',))
              CALL_KW                  1

171           LOAD_GLOBAL              4 (sa)
              LOAD_ATTR               20 (ForeignKey)
              PUSH_NULL
              LOAD_CONST              13 ('users.id')
              LOAD_CONST              14 ('CASCADE')
              LOAD_CONST              15 (('ondelete',))
              CALL_KW                  2

172           LOAD_CONST              11 (True)

168           LOAD_CONST              16 (('primary_key',))
              CALL_KW                  4

174           LOAD_GLOBAL              4 (sa)
              LOAD_ATTR                6 (Column)
              PUSH_NULL

175           LOAD_CONST              55 ('minutes_used')

176           LOAD_GLOBAL              4 (sa)
              LOAD_ATTR               28 (Integer)
              PUSH_NULL
              CALL                     0

177           LOAD_CONST               4 (False)

178           LOAD_GLOBAL              4 (sa)
              LOAD_ATTR               10 (text)
              PUSH_NULL
              LOAD_CONST              56 ('0')
              CALL                     1

174           LOAD_CONST               6 (('nullable', 'server_default'))
              CALL_KW                  4

180           LOAD_GLOBAL              4 (sa)
              LOAD_ATTR                6 (Column)
              PUSH_NULL
              LOAD_CONST              57 ('last_usage_source')
              LOAD_GLOBAL              4 (sa)
              LOAD_ATTR               22 (Text)
              PUSH_NULL
              CALL                     0
              LOAD_CONST              11 (True)
              LOAD_CONST              29 (('nullable',))
              CALL_KW                  3

181           LOAD_GLOBAL              4 (sa)
              LOAD_ATTR                6 (Column)
              PUSH_NULL

182           LOAD_CONST              22 ('updated_at')

183           LOAD_GLOBAL              4 (sa)
              LOAD_ATTR               24 (DateTime)
              PUSH_NULL
              LOAD_CONST              11 (True)
              LOAD_CONST              20 (('timezone',))
              CALL_KW                  1

184           LOAD_CONST               4 (False)

185           LOAD_GLOBAL              4 (sa)
              LOAD_ATTR               10 (text)
              PUSH_NULL
              LOAD_CONST              21 ('now()')
              CALL                     1

181           LOAD_CONST               6 (('nullable', 'server_default'))
              CALL_KW                  4

166           CALL                     5
              POP_TOP

190           LOAD_GLOBAL              0 (op)
              LOAD_ATTR               14 (create_table)
              PUSH_NULL

191           LOAD_CONST              58 ('billing_events')

192           LOAD_GLOBAL              4 (sa)
              LOAD_ATTR                6 (Column)
              PUSH_NULL

193           LOAD_CONST              24 ('id')

194           LOAD_GLOBAL             16 (postgresql)
              LOAD_ATTR               18 (UUID)
              PUSH_NULL
              LOAD_CONST              11 (True)
              LOAD_CONST              12 (('as_uuid',))
              CALL_KW                  1

195           LOAD_CONST              11 (True)

196           LOAD_GLOBAL              4 (sa)
              LOAD_ATTR               10 (text)
              PUSH_NULL
              LOAD_CONST              25 ('gen_random_uuid()')
              CALL                     1

192           LOAD_CONST              26 (('primary_key', 'server_default'))
              CALL_KW                  4

198           LOAD_GLOBAL              4 (sa)
              LOAD_ATTR                6 (Column)
              PUSH_NULL
              LOAD_CONST              59 ('provider_event_id')
              LOAD_GLOBAL              4 (sa)
              LOAD_ATTR               22 (Text)
              PUSH_NULL
              CALL                     0
              LOAD_CONST               4 (False)
              LOAD_CONST              11 (True)
              LOAD_CONST              18 (('nullable', 'unique'))
              CALL_KW                  4

199           LOAD_GLOBAL              4 (sa)
              LOAD_ATTR                6 (Column)
              PUSH_NULL
              LOAD_CONST              60 ('event_type')
              LOAD_GLOBAL              4 (sa)
              LOAD_ATTR               22 (Text)
              PUSH_NULL
              CALL                     0
              LOAD_CONST               4 (False)
              LOAD_CONST              29 (('nullable',))
              CALL_KW                  3

200           LOAD_GLOBAL              4 (sa)
              LOAD_ATTR                6 (Column)
              PUSH_NULL
              LOAD_CONST              61 ('payload_redacted')
              LOAD_GLOBAL             16 (postgresql)
              LOAD_ATTR               34 (JSONB)
              PUSH_NULL
              CALL                     0
              LOAD_CONST              11 (True)
              LOAD_CONST              29 (('nullable',))
              CALL_KW                  3

201           LOAD_GLOBAL              4 (sa)
              LOAD_ATTR                6 (Column)
              PUSH_NULL
              LOAD_CONST              62 ('processed_at')
              LOAD_GLOBAL              4 (sa)
              LOAD_ATTR               24 (DateTime)
              PUSH_NULL
              LOAD_CONST              11 (True)
              LOAD_CONST              20 (('timezone',))
              CALL_KW                  1
              LOAD_CONST              11 (True)
              LOAD_CONST              29 (('nullable',))
              CALL_KW                  3

202           LOAD_GLOBAL              4 (sa)
              LOAD_ATTR                6 (Column)
              PUSH_NULL

203           LOAD_CONST              19 ('created_at')

204           LOAD_GLOBAL              4 (sa)
              LOAD_ATTR               24 (DateTime)
              PUSH_NULL
              LOAD_CONST              11 (True)
              LOAD_CONST              20 (('timezone',))
              CALL_KW                  1

205           LOAD_CONST               4 (False)

206           LOAD_GLOBAL              4 (sa)
              LOAD_ATTR               10 (text)
              PUSH_NULL
              LOAD_CONST              21 ('now()')
              CALL                     1

202           LOAD_CONST               6 (('nullable', 'server_default'))
              CALL_KW                  4

190           CALL                     7
              POP_TOP

209           LOAD_GLOBAL              0 (op)
              LOAD_ATTR               32 (create_index)
              PUSH_NULL

210           LOAD_CONST              63 ('ix_billing_events_event_type')
              LOAD_CONST              58 ('billing_events')
              LOAD_CONST              60 ('event_type')
              BUILD_LIST               1

209           CALL                     3
              POP_TOP

214           LOAD_GLOBAL              0 (op)
              LOAD_ATTR               14 (create_table)
              PUSH_NULL

215           LOAD_CONST              64 ('user_numbers')

216           LOAD_GLOBAL              4 (sa)
              LOAD_ATTR                6 (Column)
              PUSH_NULL

217           LOAD_CONST              24 ('id')

218           LOAD_GLOBAL             16 (postgresql)
              LOAD_ATTR               18 (UUID)
              PUSH_NULL
              LOAD_CONST              11 (True)
              LOAD_CONST              12 (('as_uuid',))
              CALL_KW                  1

219           LOAD_CONST              11 (True)

220           LOAD_GLOBAL              4 (sa)
              LOAD_ATTR               10 (text)
              PUSH_NULL
              LOAD_CONST              25 ('gen_random_uuid()')
              CALL                     1

216           LOAD_CONST              26 (('primary_key', 'server_default'))
              CALL_KW                  4

222           LOAD_GLOBAL              4 (sa)
              LOAD_ATTR                6 (Column)
              PUSH_NULL

223           LOAD_CONST              10 ('owner_user_id')

224           LOAD_GLOBAL             16 (postgresql)
              LOAD_ATTR               18 (UUID)
              PUSH_NULL
              LOAD_CONST              11 (True)
              LOAD_CONST              12 (('as_uuid',))
              CALL_KW                  1

225           LOAD_GLOBAL              4 (sa)
              LOAD_ATTR               20 (ForeignKey)
              PUSH_NULL
              LOAD_CONST              13 ('users.id')
              LOAD_CONST              14 ('CASCADE')
              LOAD_CONST              15 (('ondelete',))
              CALL_KW                  2

226           LOAD_CONST               4 (False)

227           LOAD_CONST              11 (True)

222           LOAD_CONST              18 (('nullable', 'unique'))
              CALL_KW                  5

229           LOAD_GLOBAL              4 (sa)
              LOAD_ATTR                6 (Column)
              PUSH_NULL
              LOAD_CONST              65 ('twilio_number_sid')
              LOAD_GLOBAL              4 (sa)
              LOAD_ATTR               22 (Text)
              PUSH_NULL
              CALL                     0
              LOAD_CONST              11 (True)
              LOAD_CONST              11 (True)
              LOAD_CONST              18 (('nullable', 'unique'))
              CALL_KW                  4

230           LOAD_GLOBAL              4 (sa)
              LOAD_ATTR                6 (Column)
              PUSH_NULL
              LOAD_CONST              66 ('e164')
              LOAD_GLOBAL              4 (sa)
              LOAD_ATTR               22 (Text)
              PUSH_NULL
              CALL                     0
              LOAD_CONST               4 (False)
              LOAD_CONST              29 (('nullable',))
              CALL_KW                  3

231           LOAD_GLOBAL              4 (sa)
              LOAD_ATTR                6 (Column)
              PUSH_NULL
              LOAD_CONST              30 ('status')
              LOAD_GLOBAL              4 (sa)
              LOAD_ATTR                8 (String)
              PUSH_NULL
              LOAD_CONST              28 (20)
              CALL                     1
              LOAD_CONST               4 (False)
              LOAD_CONST              29 (('nullable',))
              CALL_KW                  3

232           LOAD_GLOBAL              4 (sa)
              LOAD_ATTR                6 (Column)
              PUSH_NULL
              LOAD_CONST              67 ('provisioned_at')
              LOAD_GLOBAL              4 (sa)
              LOAD_ATTR               24 (DateTime)
              PUSH_NULL
              LOAD_CONST              11 (True)
              LOAD_CONST              20 (('timezone',))
              CALL_KW                  1
              LOAD_CONST              11 (True)
              LOAD_CONST              29 (('nullable',))
              CALL_KW                  3

233           LOAD_GLOBAL              4 (sa)
              LOAD_ATTR                6 (Column)
              PUSH_NULL
              LOAD_CONST              68 ('released_at')
              LOAD_GLOBAL              4 (sa)
              LOAD_ATTR               24 (DateTime)
              PUSH_NULL
              LOAD_CONST              11 (True)
              LOAD_CONST              20 (('timezone',))
              CALL_KW                  1
              LOAD_CONST              11 (True)
              LOAD_CONST              29 (('nullable',))
              CALL_KW                  3

234           LOAD_GLOBAL              4 (sa)
              LOAD_ATTR                6 (Column)
              PUSH_NULL

235           LOAD_CONST              19 ('created_at')

236           LOAD_GLOBAL              4 (sa)
              LOAD_ATTR               24 (DateTime)
              PUSH_NULL
              LOAD_CONST              11 (True)
              LOAD_CONST              20 (('timezone',))
              CALL_KW                  1

237           LOAD_CONST               4 (False)

238           LOAD_GLOBAL              4 (sa)
              LOAD_ATTR               10 (text)
              PUSH_NULL
              LOAD_CONST              21 ('now()')
              CALL                     1

234           LOAD_CONST               6 (('nullable', 'server_default'))
              CALL_KW                  4

240           LOAD_GLOBAL              4 (sa)
              LOAD_ATTR                6 (Column)
              PUSH_NULL

241           LOAD_CONST              22 ('updated_at')

242           LOAD_GLOBAL              4 (sa)
              LOAD_ATTR               24 (DateTime)
              PUSH_NULL
              LOAD_CONST              11 (True)
              LOAD_CONST              20 (('timezone',))
              CALL_KW                  1

243           LOAD_CONST               4 (False)

244           LOAD_GLOBAL              4 (sa)
              LOAD_ATTR               10 (text)
              PUSH_NULL
              LOAD_CONST              21 ('now()')
              CALL                     1

240           LOAD_CONST               6 (('nullable', 'server_default'))
              CALL_KW                  4

246           LOAD_GLOBAL              4 (sa)
              LOAD_ATTR               30 (CheckConstraint)
              PUSH_NULL

247           LOAD_CONST              69 ("status IN ('provisioning', 'active', 'released', 'failed')")

248           LOAD_CONST              70 ('ck_user_numbers_status')

246           LOAD_CONST              41 (('name',))
              CALL_KW                  2

214           CALL                    11
              POP_TOP

253           LOAD_GLOBAL              0 (op)
              LOAD_ATTR               14 (create_table)
              PUSH_NULL

254           LOAD_CONST              71 ('call_mode_configs')

255           LOAD_GLOBAL              4 (sa)
              LOAD_ATTR                6 (Column)
              PUSH_NULL

256           LOAD_CONST              10 ('owner_user_id')

257           LOAD_GLOBAL             16 (postgresql)
              LOAD_ATTR               18 (UUID)
              PUSH_NULL
              LOAD_CONST              11 (True)
              LOAD_CONST              12 (('as_uuid',))
              CALL_KW                  1

258           LOAD_GLOBAL              4 (sa)
              LOAD_ATTR               20 (ForeignKey)
              PUSH_NULL
              LOAD_CONST              13 ('users.id')
              LOAD_CONST              14 ('CASCADE')
              LOAD_CONST              15 (('ondelete',))
              CALL_KW                  2

259           LOAD_CONST              11 (True)

255           LOAD_CONST              16 (('primary_key',))
              CALL_KW                  4

261           LOAD_GLOBAL              4 (sa)
              LOAD_ATTR                6 (Column)
              PUSH_NULL

262           LOAD_CONST              72 ('mode_a_enabled')

263           LOAD_GLOBAL              4 (sa)
              LOAD_ATTR               26 (Boolean)
              PUSH_NULL
              CALL                     0

264           LOAD_CONST               4 (False)

265           LOAD_GLOBAL              4 (sa)
              LOAD_ATTR               10 (text)
              PUSH_NULL
              LOAD_CONST              52 ('true')
              CALL                     1

261           LOAD_CONST               6 (('nullable', 'server_default'))
              CALL_KW                  4

267           LOAD_GLOBAL              4 (sa)
              LOAD_ATTR                6 (Column)
              PUSH_NULL

268           LOAD_CONST              73 ('mode_b_enabled')

269           LOAD_GLOBAL              4 (sa)
              LOAD_ATTR               26 (Boolean)
              PUSH_NULL
              CALL                     0

270           LOAD_CONST               4 (False)

271           LOAD_GLOBAL              4 (sa)
              LOAD_ATTR               10 (text)
              PUSH_NULL
              LOAD_CONST              36 ('false')
              CALL                     1

267           LOAD_CONST               6 (('nullable', 'server_default'))
              CALL_KW                  4

273           LOAD_GLOBAL              4 (sa)
              LOAD_ATTR                6 (Column)
              PUSH_NULL

274           LOAD_CONST              74 ('access_control')

275           LOAD_GLOBAL              4 (sa)
              LOAD_ATTR                8 (String)
              PUSH_NULL
              LOAD_CONST              28 (20)
              CALL                     1

276           LOAD_CONST               4 (False)

277           LOAD_GLOBAL              4 (sa)
              LOAD_ATTR               10 (text)
              PUSH_NULL
              LOAD_CONST              75 ("'everyone'")
              CALL                     1

273           LOAD_CONST               6 (('nullable', 'server_default'))
              CALL_KW                  4

279           LOAD_GLOBAL              4 (sa)
              LOAD_ATTR                6 (Column)
              PUSH_NULL
              LOAD_CONST              76 ('personal_number_e164_hash')
              LOAD_GLOBAL              4 (sa)
              LOAD_ATTR               22 (Text)
              PUSH_NULL
              CALL                     0
              LOAD_CONST              11 (True)
              LOAD_CONST              29 (('nullable',))
              CALL_KW                  3

280           LOAD_GLOBAL              4 (sa)
              LOAD_ATTR                6 (Column)
              PUSH_NULL
              LOAD_CONST              77 ('personal_number_e164_ciphertext')
              LOAD_GLOBAL              4 (sa)
              LOAD_ATTR               36 (LargeBinary)
              PUSH_NULL
              CALL                     0
              LOAD_CONST              11 (True)
              LOAD_CONST              29 (('nullable',))
              CALL_KW                  3

281           LOAD_GLOBAL              4 (sa)
              LOAD_ATTR                6 (Column)
              PUSH_NULL
              LOAD_CONST              78 ('personal_number_nonce')
              LOAD_GLOBAL              4 (sa)
              LOAD_ATTR               36 (LargeBinary)
              PUSH_NULL
              CALL                     0
              LOAD_CONST              11 (True)
              LOAD_CONST              29 (('nullable',))
              CALL_KW                  3

282           LOAD_GLOBAL              4 (sa)
              LOAD_ATTR                6 (Column)
              PUSH_NULL
              LOAD_CONST              79 ('personal_number_key_version')
              LOAD_GLOBAL              4 (sa)
              LOAD_ATTR               28 (Integer)
              PUSH_NULL
              CALL                     0
              LOAD_CONST              11 (True)
              LOAD_CONST              29 (('nullable',))
              CALL_KW                  3

283           LOAD_GLOBAL              4 (sa)
              LOAD_ATTR                6 (Column)
              PUSH_NULL
              LOAD_CONST              80 ('last_verified_at')
              LOAD_GLOBAL              4 (sa)
              LOAD_ATTR               24 (DateTime)
              PUSH_NULL
              LOAD_CONST              11 (True)
              LOAD_CONST              20 (('timezone',))
              CALL_KW                  1
              LOAD_CONST              11 (True)
              LOAD_CONST              29 (('nullable',))
              CALL_KW                  3

284           LOAD_GLOBAL              4 (sa)
              LOAD_ATTR                6 (Column)
              PUSH_NULL

285           LOAD_CONST              81 ('verification_status')

286           LOAD_GLOBAL              4 (sa)
              LOAD_ATTR                8 (String)
              PUSH_NULL
              LOAD_CONST              28 (20)
              CALL                     1

287           LOAD_CONST               4 (False)

288           LOAD_GLOBAL              4 (sa)
              LOAD_ATTR               10 (text)
              PUSH_NULL
              LOAD_CONST              82 ("'unverified'")
              CALL                     1

284           LOAD_CONST               6 (('nullable', 'server_default'))
              CALL_KW                  4

290           LOAD_GLOBAL              4 (sa)
              LOAD_ATTR                6 (Column)
              PUSH_NULL

291           LOAD_CONST              19 ('created_at')

292           LOAD_GLOBAL              4 (sa)
              LOAD_ATTR               24 (DateTime)
              PUSH_NULL
              LOAD_CONST              11 (True)
              LOAD_CONST              20 (('timezone',))
              CALL_KW                  1

293           LOAD_CONST               4 (False)

294           LOAD_GLOBAL              4 (sa)
              LOAD_ATTR               10 (text)
              PUSH_NULL
              LOAD_CONST              21 ('now()')
              CALL                     1

290           LOAD_CONST               6 (('nullable', 'server_default'))
              CALL_KW                  4

296           LOAD_GLOBAL              4 (sa)
              LOAD_ATTR                6 (Column)
              PUSH_NULL

297           LOAD_CONST              22 ('updated_at')

298           LOAD_GLOBAL              4 (sa)
              LOAD_ATTR               24 (DateTime)
              PUSH_NULL
              LOAD_CONST              11 (True)
              LOAD_CONST              20 (('timezone',))
              CALL_KW                  1

299           LOAD_CONST               4 (False)

300           LOAD_GLOBAL              4 (sa)
              LOAD_ATTR               10 (text)
              PUSH_NULL
              LOAD_CONST              21 ('now()')
              CALL                     1

296           LOAD_CONST               6 (('nullable', 'server_default'))
              CALL_KW                  4

302           LOAD_GLOBAL              4 (sa)
              LOAD_ATTR               30 (CheckConstraint)
              PUSH_NULL

303           LOAD_CONST              83 ("access_control IN ('everyone', 'contacts', 'vip')")

304           LOAD_CONST              84 ('ck_call_mode_configs_access_control')

302           LOAD_CONST              41 (('name',))
              CALL_KW                  2

306           LOAD_GLOBAL              4 (sa)
              LOAD_ATTR               30 (CheckConstraint)
              PUSH_NULL

307           LOAD_CONST              85 ("verification_status IN ('unverified', 'pending', 'verified', 'failed')")

308           LOAD_CONST              86 ('ck_call_mode_configs_verification_status')

306           LOAD_CONST              41 (('name',))
              CALL_KW                  2

253           CALL                    15
              POP_TOP

313           LOAD_GLOBAL              0 (op)
              LOAD_ATTR               14 (create_table)
              PUSH_NULL

314           LOAD_CONST              87 ('forwarding_verification_attempts')

315           LOAD_GLOBAL              4 (sa)
              LOAD_ATTR                6 (Column)
              PUSH_NULL

316           LOAD_CONST              24 ('id')

317           LOAD_GLOBAL             16 (postgresql)
              LOAD_ATTR               18 (UUID)
              PUSH_NULL
              LOAD_CONST              11 (True)
              LOAD_CONST              12 (('as_uuid',))
              CALL_KW                  1

318           LOAD_CONST              11 (True)

319           LOAD_GLOBAL              4 (sa)
              LOAD_ATTR               10 (text)
              PUSH_NULL
              LOAD_CONST              25 ('gen_random_uuid()')
              CALL                     1

315           LOAD_CONST              26 (('primary_key', 'server_default'))
              CALL_KW                  4

321           LOAD_GLOBAL              4 (sa)
              LOAD_ATTR                6 (Column)
              PUSH_NULL

322           LOAD_CONST              10 ('owner_user_id')

323           LOAD_GLOBAL             16 (postgresql)
              LOAD_ATTR               18 (UUID)
              PUSH_NULL
              LOAD_CONST              11 (True)
              LOAD_CONST              12 (('as_uuid',))
              CALL_KW                  1

324           LOAD_GLOBAL              4 (sa)
              LOAD_ATTR               20 (ForeignKey)
              PUSH_NULL
              LOAD_CONST              13 ('users.id')
              LOAD_CONST              14 ('CASCADE')
              LOAD_CONST              15 (('ondelete',))
              CALL_KW                  2

325           LOAD_CONST               4 (False)

321           LOAD_CONST              29 (('nullable',))
              CALL_KW                  4

327           LOAD_GLOBAL              4 (sa)
              LOAD_ATTR                6 (Column)
              PUSH_NULL
              LOAD_CONST              88 ('verification_code')
              LOAD_GLOBAL              4 (sa)
              LOAD_ATTR               22 (Text)
              PUSH_NULL
              CALL                     0
              LOAD_CONST               4 (False)
              LOAD_CONST              29 (('nullable',))
              CALL_KW                  3

328           LOAD_GLOBAL              4 (sa)
              LOAD_ATTR                6 (Column)
              PUSH_NULL
              LOAD_CONST              30 ('status')
              LOAD_GLOBAL              4 (sa)
              LOAD_ATTR                8 (String)
              PUSH_NULL
              LOAD_CONST              28 (20)
              CALL                     1
              LOAD_CONST               4 (False)
              LOAD_CONST              29 (('nullable',))
              CALL_KW                  3

329           LOAD_GLOBAL              4 (sa)
              LOAD_ATTR                6 (Column)
              PUSH_NULL
              LOAD_CONST              89 ('initiated_at')
              LOAD_GLOBAL              4 (sa)
              LOAD_ATTR               24 (DateTime)
              PUSH_NULL
              LOAD_CONST              11 (True)
              LOAD_CONST              20 (('timezone',))
              CALL_KW                  1
              LOAD_CONST               4 (False)
              LOAD_CONST              29 (('nullable',))
              CALL_KW                  3

330           LOAD_GLOBAL              4 (sa)
              LOAD_ATTR                6 (Column)
              PUSH_NULL
              LOAD_CONST              90 ('completed_at')
              LOAD_GLOBAL              4 (sa)
              LOAD_ATTR               24 (DateTime)
              PUSH_NULL
              LOAD_CONST              11 (True)
              LOAD_CONST              20 (('timezone',))
              CALL_KW                  1
              LOAD_CONST              11 (True)
              LOAD_CONST              29 (('nullable',))
              CALL_KW                  3

331           LOAD_GLOBAL              4 (sa)
              LOAD_ATTR                6 (Column)
              PUSH_NULL
              LOAD_CONST              91 ('twilio_call_sid')
              LOAD_GLOBAL              4 (sa)
              LOAD_ATTR               22 (Text)
              PUSH_NULL
              CALL                     0
              LOAD_CONST              11 (True)
              LOAD_CONST              29 (('nullable',))
              CALL_KW                  3

332           LOAD_GLOBAL              4 (sa)
              LOAD_ATTR                6 (Column)
              PUSH_NULL
              LOAD_CONST              92 ('details_redacted')
              LOAD_GLOBAL             16 (postgresql)
              LOAD_ATTR               34 (JSONB)
              PUSH_NULL
              CALL                     0
              LOAD_CONST              11 (True)
              LOAD_CONST              29 (('nullable',))
              CALL_KW                  3

333           LOAD_GLOBAL              4 (sa)
              LOAD_ATTR                6 (Column)
              PUSH_NULL

334           LOAD_CONST              19 ('created_at')

335           LOAD_GLOBAL              4 (sa)
              LOAD_ATTR               24 (DateTime)
              PUSH_NULL
              LOAD_CONST              11 (True)
              LOAD_CONST              20 (('timezone',))
              CALL_KW                  1

336           LOAD_CONST               4 (False)

337           LOAD_GLOBAL              4 (sa)
              LOAD_ATTR               10 (text)
              PUSH_NULL
              LOAD_CONST              21 ('now()')
              CALL                     1

333           LOAD_CONST               6 (('nullable', 'server_default'))
              CALL_KW                  4

339           LOAD_GLOBAL              4 (sa)
              LOAD_ATTR               30 (CheckConstraint)
              PUSH_NULL

340           LOAD_CONST              93 ("status IN ('pending', 'passed', 'failed', 'expired')")

341           LOAD_CONST              94 ('ck_fwd_verification_status')

339           LOAD_CONST              41 (('name',))
              CALL_KW                  2

313           CALL                    11
              POP_TOP

344           LOAD_GLOBAL              0 (op)
              LOAD_ATTR               32 (create_index)
              PUSH_NULL

345           LOAD_CONST              95 ('ix_fwd_verification_user_status')

346           LOAD_CONST              87 ('forwarding_verification_attempts')

347           LOAD_CONST              10 ('owner_user_id')
              LOAD_CONST              30 ('status')
              BUILD_LIST               2

344           CALL                     3
              POP_TOP
              RETURN_CONST             0 (None)

# --- Nested code object: downgrade ---
    # co_names: ('op', 'drop_table', 'drop_constraint', 'drop_column')
    # co_varnames: ()
    # co_consts (strings): ['forwarding_verification_attempts', 'call_mode_configs', 'user_numbers', 'billing_events', 'billing_usage', 'billing_payment_methods', 'billing_subscriptions', 'billing_customers', 'ck_user_settings_theme_preference', 'user_settings', 'check', 'theme_preference']
351           RESUME                   0

352           LOAD_GLOBAL              0 (op)
              LOAD_ATTR                2 (drop_table)
              PUSH_NULL
              LOAD_CONST               1 ('forwarding_verification_attempts')
              CALL                     1
              POP_TOP

353           LOAD_GLOBAL              0 (op)
              LOAD_ATTR                2 (drop_table)
              PUSH_NULL
              LOAD_CONST               2 ('call_mode_configs')
              CALL                     1
              POP_TOP

354           LOAD_GLOBAL              0 (op)
              LOAD_ATTR                2 (drop_table)
              PUSH_NULL
              LOAD_CONST               3 ('user_numbers')
              CALL                     1
              POP_TOP

355           LOAD_GLOBAL              0 (op)
              LOAD_ATTR                2 (drop_table)
              PUSH_NULL
              LOAD_CONST               4 ('billing_events')
              CALL                     1
              POP_TOP

356           LOAD_GLOBAL              0 (op)
              LOAD_ATTR                2 (drop_table)
              PUSH_NULL
              LOAD_CONST               5 ('billing_usage')
              CALL                     1
              POP_TOP

357           LOAD_GLOBAL              0 (op)
              LOAD_ATTR                2 (drop_table)
              PUSH_NULL
              LOAD_CONST               6 ('billing_payment_methods')
              CALL                     1
              POP_TOP

358           LOAD_GLOBAL              0 (op)
              LOAD_ATTR                2 (drop_table)
              PUSH_NULL
              LOAD_CONST               7 ('billing_subscriptions')
              CALL                     1
              POP_TOP

359           LOAD_GLOBAL              0 (op)
              LOAD_ATTR                2 (drop_table)
              PUSH_NULL
              LOAD_CONST               8 ('billing_customers')
              CALL                     1
              POP_TOP

360           LOAD_GLOBAL              0 (op)
              LOAD_ATTR                4 (drop_constraint)
              PUSH_NULL

361           LOAD_CONST               9 ('ck_user_settings_theme_preference')
              LOAD_CONST              10 ('user_settings')
              LOAD_CONST              11 ('check')

360           LOAD_CONST              12 (('type_',))
              CALL_KW                  3
              POP_TOP

363           LOAD_GLOBAL              0 (op)
              LOAD_ATTR                6 (drop_column)
              PUSH_NULL
              LOAD_CONST              10 ('user_settings')
              LOAD_CONST              13 ('theme_preference')
              CALL                     2
              POP_TOP
              RETURN_CONST             0 (None)

# --- Module-level bytecode ---
  0           RESUME                   0

  1           SETUP_ANNOTATIONS
              LOAD_CONST               0 ('Add billing, telephony, and theme_preference\n\nRevision ID: 004\nRevises: 003\nCreate Date: 2026-02-23\n')
              STORE_NAME               0 (__doc__)

  7           LOAD_CONST               1 (0)
              LOAD_CONST               2 (('Sequence',))
              IMPORT_NAME              1 (collections.abc)
              IMPORT_FROM              2 (Sequence)
              STORE_NAME               2 (Sequence)
              POP_TOP

  9           LOAD_CONST               1 (0)
              LOAD_CONST               3 (None)
              IMPORT_NAME              3 (sqlalchemy)
              STORE_NAME               4 (sa)

 10           LOAD_CONST               1 (0)
              LOAD_CONST               4 (('postgresql',))
              IMPORT_NAME              5 (sqlalchemy.dialects)
              IMPORT_FROM              6 (postgresql)
              STORE_NAME               6 (postgresql)
              POP_TOP

 12           LOAD_CONST               1 (0)
              LOAD_CONST               5 (('op',))
              IMPORT_NAME              7 (alembic)
              IMPORT_FROM              8 (op)
              STORE_NAME               8 (op)
              POP_TOP

 14           LOAD_CONST               6 ('004')
              STORE_NAME               9 (revision)
              LOAD_NAME               10 (str)
              LOAD_NAME               11 (__annotations__)
              LOAD_CONST               7 ('revision')
              STORE_SUBSCR

 15           LOAD_CONST               8 ('003')
              STORE_NAME              12 (down_revision)
              LOAD_NAME               10 (str)
              LOAD_CONST               3 (None)
              BINARY_OP                7 (|)
              LOAD_NAME               11 (__annotations__)
              LOAD_CONST               9 ('down_revision')
              STORE_SUBSCR

 16           LOAD_CONST               3 (None)
              STORE_NAME              13 (branch_labels)
              LOAD_NAME               10 (str)
              LOAD_NAME                2 (Sequence)
              LOAD_NAME               10 (str)
              BINARY_SUBSCR
              BINARY_OP                7 (|)
              LOAD_CONST               3 (None)
              BINARY_OP                7 (|)
              LOAD_NAME               11 (__annotations__)
              LOAD_CONST              10 ('branch_labels')
              STORE_SUBSCR

 17           LOAD_CONST               3 (None)
              STORE_NAME              14 (depends_on)
              LOAD_NAME               10 (str)
              LOAD_NAME                2 (Sequence)
              LOAD_NAME               10 (str)
              BINARY_SUBSCR
              BINARY_OP                7 (|)
              LOAD_CONST               3 (None)
              BINARY_OP                7 (|)
              LOAD_NAME               11 (__annotations__)
              LOAD_CONST              11 ('depends_on')
              STORE_SUBSCR

 20           LOAD_CONST              14 (('return', None))
              LOAD_CONST              12 (<code object upgrade at 0x00000185C9B24E00, file "D:\fluence\Github\mattbot\backend\alembic\versions\004_billing_telephony_theme.py", line 20>)
              MAKE_FUNCTION
              SET_FUNCTION_ATTRIBUTE   4 (annotations)
              STORE_NAME              15 (upgrade)

351           LOAD_CONST              14 (('return', None))
              LOAD_CONST              13 (<code object downgrade at 0x00000185C9ADC8C0, file "D:\fluence\Github\mattbot\backend\alembic\versions\004_billing_telephony_theme.py", line 351>)
              MAKE_FUNCTION
              SET_FUNCTION_ATTRIBUTE   4 (annotations)
              STORE_NAME              16 (downgrade)
              RETURN_CONST             3 (None)

Disassembly of <code object upgrade at 0x00000185C9B24E00, file "D:\fluence\Github\mattbot\backend\alembic\versions\004_billing_telephony_theme.py", line 20>:
 20           RESUME                   0

 22           LOAD_GLOBAL              0 (op)
              LOAD_ATTR                2 (add_column)
              PUSH_NULL

 23           LOAD_CONST               1 ('user_settings')

 24           LOAD_GLOBAL              4 (sa)
              LOAD_ATTR                6 (Column)
              PUSH_NULL

 25           LOAD_CONST               2 ('theme_preference')

 26           LOAD_GLOBAL              4 (sa)
              LOAD_ATTR                8 (String)
              PUSH_NULL
              LOAD_CONST               3 (10)
              CALL                     1

 27           LOAD_CONST               4 (False)

 28           LOAD_GLOBAL              4 (sa)
              LOAD_ATTR               10 (text)
              PUSH_NULL
              LOAD_CONST               5 ("'system'")
              CALL                     1

 24           LOAD_CONST               6 (('nullable', 'server_default'))
              CALL_KW                  4

 22           CALL                     2
              POP_TOP

 31           LOAD_GLOBAL              0 (op)
              LOAD_ATTR               12 (create_check_constraint)
              PUSH_NULL

 32           LOAD_CONST               7 ('ck_user_settings_theme_preference')

 33           LOAD_CONST               1 ('user_settings')

 34           LOAD_CONST               8 ("theme_preference IN ('system', 'light', 'dark')")

 31           CALL                     3
              POP_TOP

 38           LOAD_GLOBAL              0 (op)
              LOAD_ATTR               14 (create_table)
              PUSH_NULL

 39           LOAD_CONST               9 ('billing_customers')

 40           LOAD_GLOBAL              4 (sa)
              LOAD_ATTR                6 (Column)
              PUSH_NULL

 41           LOAD_CONST              10 ('owner_user_id')

 42           LOAD_GLOBAL             16 (postgresql)
              LOAD_ATTR               18 (UUID)
              PUSH_NULL
              LOAD_CONST              11 (True)
              LOAD_CONST              12 (('as_uuid',))
              CALL_KW                  1

 43           LOAD_GLOBAL              4 (sa)
              LOAD_ATTR               20 (ForeignKey)
              PUSH_NULL
              LOAD_CONST              13 ('users.id')
              LOAD_CONST              14 ('CASCADE')
              LOAD_CONST              15 (('ondelete',))
              CALL_KW                  2

 44           LOAD_CONST              11 (True)

 40           LOAD_CONST              16 (('primary_key',))
              CALL_KW                  4

 46           LOAD_GLOBAL              4 (sa)
              LOAD_ATTR                6 (Column)
              PUSH_NULL
              LOAD_CONST              17 ('stripe_customer_id')
              LOAD_GLOBAL              4 (sa)
              LOAD_ATTR               22 (Text)
              PUSH_NULL
              CALL                     0
              LOAD_CONST              11 (True)
              LOAD_CONST              11 (True)
              LOAD_CONST              18 (('nullable', 'unique'))
              CALL_KW                  4

 47           LOAD_GLOBAL              4 (sa)
              LOAD_ATTR                6 (Column)
              PUSH_NULL

 48           LOAD_CONST              19 ('created_at')

 49           LOAD_GLOBAL              4 (sa)
              LOAD_ATTR               24 (DateTime)
              PUSH_NULL
              LOAD_CONST              11 (True)
              LOAD_CONST              20 (('timezone',))
              CALL_KW                  1

 50           LOAD_CONST               4 (False)

 51           LOAD_GLOBAL              4 (sa)
              LOAD_ATTR               10 (text)
              PUSH_NULL
              LOAD_CONST              21 ('now()')
              CALL                     1

 47           LOAD_CONST               6 (('nullable', 'server_default'))
              CALL_KW                  4

 53           LOAD_GLOBAL              4 (sa)
              LOAD_ATTR                6 (Column)
              PUSH_NULL

 54           LOAD_CONST              22 ('updated_at')

 55           LOAD_GLOBAL              4 (sa)
              LOAD_ATTR               24 (DateTime)
              PUSH_NULL
              LOAD_CONST              11 (True)
              LOAD_CONST              20 (('timezone',))
              CALL_KW                  1

 56           LOAD_CONST               4 (False)

 57           LOAD_GLOBAL              4 (sa)
              LOAD_ATTR               10 (text)
              PUSH_NULL
              LOAD_CONST              21 ('now()')
              CALL                     1

 53           LOAD_CONST               6 (('nullable', 'server_default'))
              CALL_KW                  4

 38           CALL                     5
              POP_TOP

 62           LOAD_GLOBAL              0 (op)
              LOAD_ATTR               14 (create_table)
              PUSH_NULL

 63           LOAD_CONST              23 ('billing_subscriptions')

 64           LOAD_GLOBAL              4 (sa)
              LOAD_ATTR                6 (Column)
              PUSH_NULL

 65           LOAD_CONST              24 ('id')

 66           LOAD_GLOBAL             16 (postgresql)
              LOAD_ATTR               18 (UUID)
              PUSH_NULL
              LOAD_CONST              11 (True)
              LOAD_CONST              12 (('as_uuid',))
              CALL_KW                  1

 67           LOAD_CONST              11 (True)

 68           LOAD_GLOBAL              4 (sa)
              LOAD_ATTR               10 (text)
              PUSH_NULL
              LOAD_CONST              25 ('gen_random_uuid()')
              CALL                     1

 64           LOAD_CONST              26 (('primary_key', 'server_default'))
              CALL_KW                  4

 70           LOAD_GLOBAL              4 (sa)
              LOAD_ATTR                6 (Column)
              PUSH_NULL

 71           LOAD_CONST              10 ('owner_user_id')

 72           LOAD_GLOBAL             16 (postgresql)
              LOAD_ATTR               18 (UUID)
              PUSH_NULL
              LOAD_CONST              11 (True)
              LOAD_CONST              12 (('as_uuid',))
              CALL_KW                  1

 73           LOAD_GLOBAL              4 (sa)
              LOAD_ATTR               20 (ForeignKey)
              PUSH_NULL
              LOAD_CONST              13 ('users.id')
              LOAD_CONST              14 ('CASCADE')
              LOAD_CONST              15 (('ondelete',))
              CALL_KW                  2

 74           LOAD_CONST               4 (False)

 75           LOAD_CONST              11 (True)

 70           LOAD_CONST              18 (('nullable', 'unique'))
              CALL_KW                  5

 77           LOAD_GLOBAL              4 (sa)
              LOAD_ATTR                6 (Column)
              PUSH_NULL
              LOAD_CONST              27 ('plan')
              LOAD_GLOBAL              4 (sa)
              LOAD_ATTR                8 (String)
              PUSH_NULL
              LOAD_CONST              28 (20)
              CALL                     1
              LOAD_CONST               4 (False)
              LOAD_CONST              29 (('nullable',))
              CALL_KW                  3

 78           LOAD_GLOBAL              4 (sa)
              LOAD_ATTR                6 (Column)
              PUSH_NULL
              LOAD_CONST              30 ('status')
              LOAD_GLOBAL              4 (sa)
              LOAD_ATTR                8 (String)
              PUSH_NULL
              LOAD_CONST              28 (20)
              CALL                     1
              LOAD_CONST               4 (False)
              LOAD_CONST              29 (('nullable',))
              CALL_KW                  3

 79           LOAD_GLOBAL              4 (sa)
              LOAD_ATTR                6 (Column)
              PUSH_NULL
              LOAD_CONST              31 ('stripe_subscription_id')
              LOAD_GLOBAL              4 (sa)
              LOAD_ATTR               22 (Text)
              PUSH_NULL
              CALL                     0
              LOAD_CONST              11 (True)
              LOAD_CONST              11 (True)
              LOAD_CONST              18 (('nullable', 'unique'))
              CALL_KW                  4

 80           LOAD_GLOBAL              4 (sa)
              LOAD_ATTR                6 (Column)
              PUSH_NULL
              LOAD_CONST              32 ('stripe_price_id')
              LOAD_GLOBAL              4 (sa)
              LOAD_ATTR               22 (Text)
              PUSH_NULL
              CALL                     0
              LOAD_CONST              11 (True)
              LOAD_CONST              29 (('nullable',))
              CALL_KW                  3

 81           LOAD_GLOBAL              4 (sa)
              LOAD_ATTR                6 (Column)
              PUSH_NULL
              LOAD_CONST              33 ('current_period_start')
              LOAD_GLOBAL              4 (sa)
              LOAD_ATTR               24 (DateTime)
              PUSH_NULL
              LOAD_CONST              11 (True)
              LOAD_CONST              20 (('timezone',))
              CALL_KW                  1
              LOAD_CONST              11 (True)
              LOAD_CONST              29 (('nullable',))
              CALL_KW                  3

 82           LOAD_GLOBAL              4 (sa)
              LOAD_ATTR                6 (Column)
              PUSH_NULL
              LOAD_CONST              34 ('current_period_end')
              LOAD_GLOBAL              4 (sa)
              LOAD_ATTR               24 (DateTime)
              PUSH_NULL
              LOAD_CONST              11 (True)
              LOAD_CONST              20 (('timezone',))
              CALL_KW                  1
              LOAD_CONST              11 (True)
              LOAD_CONST              29 (('nullable',))
              CALL_KW                  3

 83           LOAD_GLOBAL              4 (sa)
              LOAD_ATTR                6 (Column)
              PUSH_NULL

 84           LOAD_CONST              35 ('cancel_at_period_end')

 85           LOAD_GLOBAL              4 (sa)
              LOAD_ATTR               26 (Boolean)
              PUSH_NULL
              CALL                     0

 86           LOAD_CONST               4 (False)

 87           LOAD_GLOBAL              4 (sa)
              LOAD_ATTR               10 (text)
              PUSH_NULL
              LOAD_CONST              36 ('false')
              CALL                     1

 83           LOAD_CONST               6 (('nullable', 'server_default'))
              CALL_KW                  4

 89           LOAD_GLOBAL              4 (sa)
              LOAD_ATTR                6 (Column)
              PUSH_NULL
              LOAD_CONST              37 ('canceled_at')
              LOAD_GLOBAL              4 (sa)
              LOAD_ATTR               24 (DateTime)
              PUSH_NULL
              LOAD_CONST              11 (True)
              LOAD_CONST              20 (('timezone',))
              CALL_KW                  1
              LOAD_CONST              11 (True)
              LOAD_CONST              29 (('nullable',))
              CALL_KW                  3

 90           LOAD_GLOBAL              4 (sa)
              LOAD_ATTR                6 (Column)
              PUSH_NULL
              LOAD_CONST              38 ('minutes_included')
              LOAD_GLOBAL              4 (sa)
              LOAD_ATTR               28 (Integer)
              PUSH_NULL
              CALL                     0
              LOAD_CONST               4 (False)
              LOAD_CONST              29 (('nullable',))
              CALL_KW                  3

 91           LOAD_GLOBAL              4 (sa)
              LOAD_ATTR                6 (Column)
              PUSH_NULL

 92           LOAD_CONST              19 ('created_at')

 93           LOAD_GLOBAL              4 (sa)
              LOAD_ATTR               24 (DateTime)
              PUSH_NULL
              LOAD_CONST              11 (True)
              LOAD_CONST              20 (('timezone',))
              CALL_KW                  1

 94           LOAD_CONST               4 (False)

 95           LOAD_GLOBAL              4 (sa)
              LOAD_ATTR               10 (text)
              PUSH_NULL
              LOAD_CONST              21 ('now()')
              CALL                     1

 91           LOAD_CONST               6 (('nullable', 'server_default'))
              CALL_KW                  4

 97           LOAD_GLOBAL              4 (sa)
              LOAD_ATTR                6 (Column)
              PUSH_NULL

 98           LOAD_CONST              22 ('updated_at')

 99           LOAD_GLOBAL              4 (sa)
              LOAD_ATTR               24 (DateTime)
              PUSH_NULL
              LOAD_CONST              11 (True)
              LOAD_CONST              20 (('timezone',))
              CALL_KW                  1

100           LOAD_CONST               4 (False)

101           LOAD_GLOBAL              4 (sa)
              LOAD_ATTR               10 (text)
              PUSH_NULL
              LOAD_CONST              21 ('now()')
              CALL                     1

 97           LOAD_CONST               6 (('nullable', 'server_default'))
              CALL_KW                  4

103           LOAD_GLOBAL              4 (sa)
              LOAD_ATTR               30 (CheckConstraint)
              PUSH_NULL

104           LOAD_CONST              39 ("plan IN ('free', 'standard', 'pro')")

105           LOAD_CONST              40 ('ck_billing_subscriptions_plan')

103           LOAD_CONST              41 (('name',))
              CALL_KW                  2

107           LOAD_GLOBAL              4 (sa)
              LOAD_ATTR               30 (CheckConstraint)
              PUSH_NULL

108           LOAD_CONST              42 ("status IN ('active', 'past_due', 'canceled', 'incomplete', 'trialing')")

109           LOAD_CONST              43 ('ck_billing_subscriptions_status')

107           LOAD_CONST              41 (('name',))
              CALL_KW                  2

 62           CALL                    16
              POP_TOP

112           LOAD_GLOBAL              0 (op)
              LOAD_ATTR               32 (create_index)
              PUSH_NULL

113           LOAD_CONST              44 ('ix_billing_subscriptions_owner')

114           LOAD_CONST              23 ('billing_subscriptions')

115           LOAD_CONST              10 ('owner_user_id')
              BUILD_LIST               1

112           CALL                     3
              POP_TOP

119           LOAD_GLOBAL              0 (op)
              LOAD_ATTR               14 (create_table)
              PUSH_NULL

120           LOAD_CONST              45 ('billing_payment_methods')

121           LOAD_GLOBAL              4 (sa)
              LOAD_ATTR                6 (Column)
              PUSH_NULL

122           LOAD_CONST              24 ('id')

123           LOAD_GLOBAL             16 (postgresql)
              LOAD_ATTR               18 (UUID)
              PUSH_NULL
              LOAD_CONST              11 (True)
              LOAD_CONST              12 (('as_uuid',))
              CALL_KW                  1

124           LOAD_CONST              11 (True)

125           LOAD_GLOBAL              4 (sa)
              LOAD_ATTR               10 (text)
              PUSH_NULL
              LOAD_CONST              25 ('gen_random_uuid()')
              CALL                     1

121           LOAD_CONST              26 (('primary_key', 'server_default'))
              CALL_KW                  4

127           LOAD_GLOBAL              4 (sa)
              LOAD_ATTR                6 (Column)
              PUSH_NULL

128           LOAD_CONST              10 ('owner_user_id')

129           LOAD_GLOBAL             16 (postgresql)
              LOAD_ATTR               18 (UUID)
              PUSH_NULL
              LOAD_CONST              11 (True)
              LOAD_CONST              12 (('as_uuid',))
              CALL_KW                  1

130           LOAD_GLOBAL              4 (sa)
              LOAD_ATTR               20 (ForeignKey)
              PUSH_NULL
              LOAD_CONST              13 ('users.id')
              LOAD_CONST              14 ('CASCADE')
              LOAD_CONST              15 (('ondelete',))
              CALL_KW                  2

131           LOAD_CONST               4 (False)

127           LOAD_CONST              29 (('nullable',))
              CALL_KW                  4

133           LOAD_GLOBAL              4 (sa)
              LOAD_ATTR                6 (Column)
              PUSH_NULL

134           LOAD_CONST              46 ('stripe_payment_method_id')
              LOAD_GLOBAL              4 (sa)
              LOAD_ATTR               22 (Text)
              PUSH_NULL
              CALL                     0
              LOAD_CONST              11 (True)
              LOAD_CONST              11 (True)

133           LOAD_CONST              18 (('nullable', 'unique'))
              CALL_KW                  4

136           LOAD_GLOBAL              4 (sa)
              LOAD_ATTR                6 (Column)
              PUSH_NULL
              LOAD_CONST              47 ('brand')
              LOAD_GLOBAL              4 (sa)
              LOAD_ATTR               22 (Text)
              PUSH_NULL
              CALL                     0
              LOAD_CONST              11 (True)
              LOAD_CONST              29 (('nullable',))
              CALL_KW                  3

137           LOAD_GLOBAL              4 (sa)
              LOAD_ATTR                6 (Column)
              PUSH_NULL
              LOAD_CONST              48 ('last4')
              LOAD_GLOBAL              4 (sa)
              LOAD_ATTR               22 (Text)
              PUSH_NULL
              CALL                     0
              LOAD_CONST              11 (True)
              LOAD_CONST              29 (('nullable',))
              CALL_KW                  3

138           LOAD_GLOBAL              4 (sa)
              LOAD_ATTR                6 (Column)
              PUSH_NULL
              LOAD_CONST              49 ('exp_month')
              LOAD_GLOBAL              4 (sa)
              LOAD_ATTR               28 (Integer)
              PUSH_NULL
              CALL                     0
              LOAD_CONST              11 (True)
              LOAD_CONST              29 (('nullable',))
              CALL_KW                  3

139           LOAD_GLOBAL              4 (sa)
              LOAD_ATTR                6 (Column)
              PUSH_NULL
              LOAD_CONST              50 ('exp_year')
              LOAD_GLOBAL              4 (sa)
              LOAD_ATTR               28 (Integer)
              PUSH_NULL
              CALL                     0
              LOAD_CONST              11 (True)
              LOAD_CONST              29 (('nullable',))
              CALL_KW                  3

140           LOAD_GLOBAL              4 (sa)
              LOAD_ATTR                6 (Column)
              PUSH_NULL

141           LOAD_CONST              51 ('is_default')

142           LOAD_GLOBAL              4 (sa)
              LOAD_ATTR               26 (Boolean)
              PUSH_NULL
              CALL                     0

143           LOAD_CONST               4 (False)

144           LOAD_GLOBAL              4 (sa)
              LOAD_ATTR               10 (text)
              PUSH_NULL
              LOAD_CONST              52 ('true')
              CALL                     1

140           LOAD_CONST               6 (('nullable', 'server_default'))
              CALL_KW                  4

146           LOAD_GLOBAL              4 (sa)
              LOAD_ATTR                6 (Column)
              PUSH_NULL

147           LOAD_CONST              19 ('created_at')

148           LOAD_GLOBAL              4 (sa)
              LOAD_ATTR               24 (DateTime)
              PUSH_NULL
              LOAD_CONST              11 (True)
              LOAD_CONST              20 (('timezone',))
              CALL_KW                  1

149           LOAD_CONST               4 (False)

150           LOAD_GLOBAL              4 (sa)
              LOAD_ATTR               10 (text)
              PUSH_NULL
              LOAD_CONST              21 ('now()')
              CALL                     1

146           LOAD_CONST               6 (('nullable', 'server_default'))
              CALL_KW                  4

152           LOAD_GLOBAL              4 (sa)
              LOAD_ATTR                6 (Column)
              PUSH_NULL

153           LOAD_CONST              22 ('updated_at')

154           LOAD_GLOBAL              4 (sa)
              LOAD_ATTR               24 (DateTime)
              PUSH_NULL
              LOAD_CONST              11 (True)
              LOAD_CONST              20 (('timezone',))
              CALL_KW                  1

155           LOAD_CONST               4 (False)

156           LOAD_GLOBAL              4 (sa)
              LOAD_ATTR               10 (text)
              PUSH_NULL
              LOAD_CONST              21 ('now()')
              CALL                     1

152           LOAD_CONST               6 (('nullable', 'server_default'))
              CALL_KW                  4

119           CALL                    11
              POP_TOP

159           LOAD_GLOBAL              0 (op)
              LOAD_ATTR               32 (create_index)
              PUSH_NULL

160           LOAD_CONST              53 ('ix_billing_payment_methods_owner')

161           LOAD_CONST              45 ('billing_payment_methods')

162           LOAD_CONST              10 ('owner_user_id')
              BUILD_LIST               1

159           CALL                     3
              POP_TOP

166           LOAD_GLOBAL              0 (op)
              LOAD_ATTR               14 (create_table)
              PUSH_NULL

167           LOAD_CONST              54 ('billing_usage')

168           LOAD_GLOBAL              4 (sa)
              LOAD_ATTR                6 (Column)
              PUSH_NULL

169           LOAD_CONST              10 ('owner_user_id')

170           LOAD_GLOBAL             16 (postgresql)
              LOAD_ATTR               18 (UUID)
              PUSH_NULL
              LOAD_CONST              11 (True)
              LOAD_CONST              12 (('as_uuid',))
              CALL_KW                  1

171           LOAD_GLOBAL              4 (sa)
              LOAD_ATTR               20 (ForeignKey)
              PUSH_NULL
              LOAD_CONST              13 ('users.id')
              LOAD_CONST              14 ('CASCADE')
              LOAD_CONST              15 (('ondelete',))
              CALL_KW                  2

172           LOAD_CONST              11 (True)

168           LOAD_CONST              16 (('primary_key',))
              CALL_KW                  4

174           LOAD_GLOBAL              4 (sa)
              LOAD_ATTR                6 (Column)
              PUSH_NULL

175           LOAD_CONST              55 ('minutes_used')

176           LOAD_GLOBAL              4 (sa)
              LOAD_ATTR               28 (Integer)
              PUSH_NULL
              CALL                     0

177           LOAD_CONST               4 (False)

178           LOAD_GLOBAL              4 (sa)
              LOAD_ATTR               10 (text)
              PUSH_NULL
              LOAD_CONST              56 ('0')
              CALL                     1

174           LOAD_CONST               6 (('nullable', 'server_default'))
              CALL_KW                  4

180           LOAD_GLOBAL              4 (sa)
              LOAD_ATTR                6 (Column)
              PUSH_NULL
              LOAD_CONST              57 ('last_usage_source')
              LOAD_GLOBAL              4 (sa)
              LOAD_ATTR               22 (Text)
              PUSH_NULL
              CALL                     0
              LOAD_CONST              11 (True)
              LOAD_CONST              29 (('nullable',))
              CALL_KW                  3

181           LOAD_GLOBAL              4 (sa)
              LOAD_ATTR                6 (Column)
              PUSH_NULL

182           LOAD_CONST              22 ('updated_at')

183           LOAD_GLOBAL              4 (sa)
              LOAD_ATTR               24 (DateTime)
              PUSH_NULL
              LOAD_CONST              11 (True)
              LOAD_CONST              20 (('timezone',))
              CALL_KW                  1

184           LOAD_CONST               4 (False)

185           LOAD_GLOBAL              4 (sa)
              LOAD_ATTR               10 (text)
              PUSH_NULL
              LOAD_CONST              21 ('now()')
              CALL                     1

181           LOAD_CONST               6 (('nullable', 'server_default'))
              CALL_KW                  4

166           CALL                     5
              POP_TOP

190           LOAD_GLOBAL              0 (op)
              LOAD_ATTR               14 (create_table)
              PUSH_NULL

191           LOAD_CONST              58 ('billing_events')

192           LOAD_GLOBAL              4 (sa)
              LOAD_ATTR                6 (Column)
              PUSH_NULL

193           LOAD_CONST              24 ('id')

194           LOAD_GLOBAL             16 (postgresql)
              LOAD_ATTR               18 (UUID)
              PUSH_NULL
              LOAD_CONST              11 (True)
              LOAD_CONST              12 (('as_uuid',))
              CALL_KW                  1

195           LOAD_CONST              11 (True)

196           LOAD_GLOBAL              4 (sa)
              LOAD_ATTR               10 (text)
              PUSH_NULL
              LOAD_CONST              25 ('gen_random_uuid()')
              CALL                     1

192           LOAD_CONST              26 (('primary_key', 'server_default'))
              CALL_KW                  4

198           LOAD_GLOBAL              4 (sa)
              LOAD_ATTR                6 (Column)
              PUSH_NULL
              LOAD_CONST              59 ('provider_event_id')
              LOAD_GLOBAL              4 (sa)
              LOAD_ATTR               22 (Text)
              PUSH_NULL
              CALL                     0
              LOAD_CONST               4 (False)
              LOAD_CONST              11 (True)
              LOAD_CONST              18 (('nullable', 'unique'))
              CALL_KW                  4

199           LOAD_GLOBAL              4 (sa)
              LOAD_ATTR                6 (Column)
              PUSH_NULL
              LOAD_CONST              60 ('event_type')
              LOAD_GLOBAL              4 (sa)
              LOAD_ATTR               22 (Text)
              PUSH_NULL
              CALL                     0
              LOAD_CONST               4 (False)
              LOAD_CONST              29 (('nullable',))
              CALL_KW                  3

200           LOAD_GLOBAL              4 (sa)
              LOAD_ATTR                6 (Column)
              PUSH_NULL
              LOAD_CONST              61 ('payload_redacted')
              LOAD_GLOBAL             16 (postgresql)
              LOAD_ATTR               34 (JSONB)
              PUSH_NULL
              CALL                     0
              LOAD_CONST              11 (True)
              LOAD_CONST              29 (('nullable',))
              CALL_KW                  3

201           LOAD_GLOBAL              4 (sa)
              LOAD_ATTR                6 (Column)
              PUSH_NULL
              LOAD_CONST              62 ('processed_at')
              LOAD_GLOBAL              4 (sa)
              LOAD_ATTR               24 (DateTime)
              PUSH_NULL
              LOAD_CONST              11 (True)
              LOAD_CONST              20 (('timezone',))
              CALL_KW                  1
              LOAD_CONST              11 (True)
              LOAD_CONST              29 (('nullable',))
              CALL_KW                  3

202           LOAD_GLOBAL              4 (sa)
              LOAD_ATTR                6 (Column)
              PUSH_NULL

203           LOAD_CONST              19 ('created_at')

204           LOAD_GLOBAL              4 (sa)
              LOAD_ATTR               24 (DateTime)
              PUSH_NULL
              LOAD_CONST              11 (True)
              LOAD_CONST              20 (('timezone',))
              CALL_KW                  1

205           LOAD_CONST               4 (False)

206           LOAD_GLOBAL              4 (sa)
              LOAD_ATTR               10 (text)
              PUSH_NULL
              LOAD_CONST              21 ('now()')
              CALL                     1

202           LOAD_CONST               6 (('nullable', 'server_default'))
              CALL_KW                  4

190           CALL                     7
              POP_TOP

209           LOAD_GLOBAL              0 (op)
              LOAD_ATTR               32 (create_index)
              PUSH_NULL

210           LOAD_CONST              63 ('ix_billing_events_event_type')
              LOAD_CONST              58 ('billing_events')
              LOAD_CONST              60 ('event_type')
              BUILD_LIST               1

209           CALL                     3
              POP_TOP

214           LOAD_GLOBAL              0 (op)
              LOAD_ATTR               14 (create_table)
              PUSH_NULL

215           LOAD_CONST              64 ('user_numbers')

216           LOAD_GLOBAL              4 (sa)
              LOAD_ATTR                6 (Column)
              PUSH_NULL

217           LOAD_CONST              24 ('id')

218           LOAD_GLOBAL             16 (postgresql)
              LOAD_ATTR               18 (UUID)
              PUSH_NULL
              LOAD_CONST              11 (True)
              LOAD_CONST              12 (('as_uuid',))
              CALL_KW                  1

219           LOAD_CONST              11 (True)

220           LOAD_GLOBAL              4 (sa)
              LOAD_ATTR               10 (text)
              PUSH_NULL
              LOAD_CONST              25 ('gen_random_uuid()')
              CALL                     1

216           LOAD_CONST              26 (('primary_key', 'server_default'))
              CALL_KW                  4

222           LOAD_GLOBAL              4 (sa)
              LOAD_ATTR                6 (Column)
              PUSH_NULL

223           LOAD_CONST              10 ('owner_user_id')

224           LOAD_GLOBAL             16 (postgresql)
              LOAD_ATTR               18 (UUID)
              PUSH_NULL
              LOAD_CONST              11 (True)
              LOAD_CONST              12 (('as_uuid',))
              CALL_KW                  1

225           LOAD_GLOBAL              4 (sa)
              LOAD_ATTR               20 (ForeignKey)
              PUSH_NULL
              LOAD_CONST              13 ('users.id')
              LOAD_CONST              14 ('CASCADE')
              LOAD_CONST              15 (('ondelete',))
              CALL_KW                  2

226           LOAD_CONST               4 (False)

227           LOAD_CONST              11 (True)

222           LOAD_CONST              18 (('nullable', 'unique'))
              CALL_KW                  5

229           LOAD_GLOBAL              4 (sa)
              LOAD_ATTR                6 (Column)
              PUSH_NULL
              LOAD_CONST              65 ('twilio_number_sid')
              LOAD_GLOBAL              4 (sa)
              LOAD_ATTR               22 (Text)
              PUSH_NULL
              CALL                     0
              LOAD_CONST              11 (True)
              LOAD_CONST              11 (True)
              LOAD_CONST              18 (('nullable', 'unique'))
              CALL_KW                  4

230           LOAD_GLOBAL              4 (sa)
              LOAD_ATTR                6 (Column)
              PUSH_NULL
              LOAD_CONST              66 ('e164')
              LOAD_GLOBAL              4 (sa)
              LOAD_ATTR               22 (Text)
              PUSH_NULL
              CALL                     0
              LOAD_CONST               4 (False)
              LOAD_CONST              29 (('nullable',))
              CALL_KW                  3

231           LOAD_GLOBAL              4 (sa)
              LOAD_ATTR                6 (Column)
              PUSH_NULL
              LOAD_CONST              30 ('status')
              LOAD_GLOBAL              4 (sa)
              LOAD_ATTR                8 (String)
              PUSH_NULL
              LOAD_CONST              28 (20)
              CALL                     1
              LOAD_CONST               4 (False)
              LOAD_CONST              29 (('nullable',))
              CALL_KW                  3

232           LOAD_GLOBAL              4 (sa)
              LOAD_ATTR                6 (Column)
              PUSH_NULL
              LOAD_CONST              67 ('provisioned_at')
              LOAD_GLOBAL              4 (sa)
              LOAD_ATTR               24 (DateTime)
              PUSH_NULL
              LOAD_CONST              11 (True)
              LOAD_CONST              20 (('timezone',))
              CALL_KW                  1
              LOAD_CONST              11 (True)
              LOAD_CONST              29 (('nullable',))
              CALL_KW                  3

233           LOAD_GLOBAL              4 (sa)
              LOAD_ATTR                6 (Column)
              PUSH_NULL
              LOAD_CONST              68 ('released_at')
              LOAD_GLOBAL              4 (sa)
              LOAD_ATTR               24 (DateTime)
              PUSH_NULL
              LOAD_CONST              11 (True)
              LOAD_CONST              20 (('timezone',))
              CALL_KW                  1
              LOAD_CONST              11 (True)
              LOAD_CONST              29 (('nullable',))
              CALL_KW                  3

234           LOAD_GLOBAL              4 (sa)
              LOAD_ATTR                6 (Column)
              PUSH_NULL

235           LOAD_CONST              19 ('created_at')

236           LOAD_GLOBAL              4 (sa)
              LOAD_ATTR               24 (DateTime)
              PUSH_NULL
              LOAD_CONST              11 (True)
              LOAD_CONST              20 (('timezone',))
              CALL_KW                  1

237           LOAD_CONST               4 (False)

238           LOAD_GLOBAL              4 (sa)
              LOAD_ATTR               10 (text)
              PUSH_NULL
              LOAD_CONST              21 ('now()')
              CALL                     1

234           LOAD_CONST               6 (('nullable', 'server_default'))
              CALL_KW                  4

240           LOAD_GLOBAL              4 (sa)
              LOAD_ATTR                6 (Column)
              PUSH_NULL

241           LOAD_CONST              22 ('updated_at')

242           LOAD_GLOBAL              4 (sa)
              LOAD_ATTR               24 (DateTime)
              PUSH_NULL
              LOAD_CONST              11 (True)
              LOAD_CONST              20 (('timezone',))
              CALL_KW                  1

243           LOAD_CONST               4 (False)

244           LOAD_GLOBAL              4 (sa)
              LOAD_ATTR               10 (text)
              PUSH_NULL
              LOAD_CONST              21 ('now()')
              CALL                     1

240           LOAD_CONST               6 (('nullable', 'server_default'))
              CALL_KW                  4

246           LOAD_GLOBAL              4 (sa)
              LOAD_ATTR               30 (CheckConstraint)
              PUSH_NULL

247           LOAD_CONST              69 ("status IN ('provisioning', 'active', 'released', 'failed')")

248           LOAD_CONST              70 ('ck_user_numbers_status')

246           LOAD_CONST              41 (('name',))
              CALL_KW                  2

214           CALL                    11
              POP_TOP

253           LOAD_GLOBAL              0 (op)
              LOAD_ATTR               14 (create_table)
              PUSH_NULL

254           LOAD_CONST              71 ('call_mode_configs')

255           LOAD_GLOBAL              4 (sa)
              LOAD_ATTR                6 (Column)
              PUSH_NULL

256           LOAD_CONST              10 ('owner_user_id')

257           LOAD_GLOBAL             16 (postgresql)
              LOAD_ATTR               18 (UUID)
              PUSH_NULL
              LOAD_CONST              11 (True)
              LOAD_CONST              12 (('as_uuid',))
              CALL_KW                  1

258           LOAD_GLOBAL              4 (sa)
              LOAD_ATTR               20 (ForeignKey)
              PUSH_NULL
              LOAD_CONST              13 ('users.id')
              LOAD_CONST              14 ('CASCADE')
              LOAD_CONST              15 (('ondelete',))
              CALL_KW                  2

259           LOAD_CONST              11 (True)

255           LOAD_CONST              16 (('primary_key',))
              CALL_KW                  4

261           LOAD_GLOBAL              4 (sa)
              LOAD_ATTR                6 (Column)
              PUSH_NULL

262           LOAD_CONST              72 ('mode_a_enabled')

263           LOAD_GLOBAL              4 (sa)
              LOAD_ATTR               26 (Boolean)
              PUSH_NULL
              CALL                     0

264           LOAD_CONST               4 (False)

265           LOAD_GLOBAL              4 (sa)
              LOAD_ATTR               10 (text)
              PUSH_NULL
              LOAD_CONST              52 ('true')
              CALL                     1

261           LOAD_CONST               6 (('nullable', 'server_default'))
              CALL_KW                  4

267           LOAD_GLOBAL              4 (sa)
              LOAD_ATTR                6 (Column)
              PUSH_NULL

268           LOAD_CONST              73 ('mode_b_enabled')

269           LOAD_GLOBAL              4 (sa)
              LOAD_ATTR               26 (Boolean)
              PUSH_NULL
              CALL                     0

270           LOAD_CONST               4 (False)

271           LOAD_GLOBAL              4 (sa)
              LOAD_ATTR               10 (text)
              PUSH_NULL
              LOAD_CONST              36 ('false')
              CALL                     1

267           LOAD_CONST               6 (('nullable', 'server_default'))
              CALL_KW                  4

273           LOAD_GLOBAL              4 (sa)
              LOAD_ATTR                6 (Column)
              PUSH_NULL

274           LOAD_CONST              74 ('access_control')

275           LOAD_GLOBAL              4 (sa)
              LOAD_ATTR                8 (String)
              PUSH_NULL
              LOAD_CONST              28 (20)
              CALL                     1

276           LOAD_CONST               4 (False)

277           LOAD_GLOBAL              4 (sa)
              LOAD_ATTR               10 (text)
              PUSH_NULL
              LOAD_CONST              75 ("'everyone'")
              CALL                     1

273           LOAD_CONST               6 (('nullable', 'server_default'))
              CALL_KW                  4

279           LOAD_GLOBAL              4 (sa)
              LOAD_ATTR                6 (Column)
              PUSH_NULL
              LOAD_CONST              76 ('personal_number_e164_hash')
              LOAD_GLOBAL              4 (sa)
              LOAD_ATTR               22 (Text)
              PUSH_NULL
              CALL                     0
              LOAD_CONST              11 (True)
              LOAD_CONST              29 (('nullable',))
              CALL_KW                  3

280           LOAD_GLOBAL              4 (sa)
              LOAD_ATTR                6 (Column)
              PUSH_NULL
              LOAD_CONST              77 ('personal_number_e164_ciphertext')
              LOAD_GLOBAL              4 (sa)
              LOAD_ATTR               36 (LargeBinary)
              PUSH_NULL
              CALL                     0
              LOAD_CONST              11 (True)
              LOAD_CONST              29 (('nullable',))
              CALL_KW                  3

281           LOAD_GLOBAL              4 (sa)
              LOAD_ATTR                6 (Column)
              PUSH_NULL
              LOAD_CONST              78 ('personal_number_nonce')
              LOAD_GLOBAL              4 (sa)
              LOAD_ATTR               36 (LargeBinary)
              PUSH_NULL
              CALL                     0
              LOAD_CONST              11 (True)
              LOAD_CONST              29 (('nullable',))
              CALL_KW                  3

282           LOAD_GLOBAL              4 (sa)
              LOAD_ATTR                6 (Column)
              PUSH_NULL
              LOAD_CONST              79 ('personal_number_key_version')
              LOAD_GLOBAL              4 (sa)
              LOAD_ATTR               28 (Integer)
              PUSH_NULL
              CALL                     0
              LOAD_CONST              11 (True)
              LOAD_CONST              29 (('nullable',))
              CALL_KW                  3

283           LOAD_GLOBAL              4 (sa)
              LOAD_ATTR                6 (Column)
              PUSH_NULL
              LOAD_CONST              80 ('last_verified_at')
              LOAD_GLOBAL              4 (sa)
              LOAD_ATTR               24 (DateTime)
              PUSH_NULL
              LOAD_CONST              11 (True)
              LOAD_CONST              20 (('timezone',))
              CALL_KW                  1
              LOAD_CONST              11 (True)
              LOAD_CONST              29 (('nullable',))
              CALL_KW                  3

284           LOAD_GLOBAL              4 (sa)
              LOAD_ATTR                6 (Column)
              PUSH_NULL

285           LOAD_CONST              81 ('verification_status')

286           LOAD_GLOBAL              4 (sa)
              LOAD_ATTR                8 (String)
              PUSH_NULL
              LOAD_CONST              28 (20)
              CALL                     1

287           LOAD_CONST               4 (False)

288           LOAD_GLOBAL              4 (sa)
              LOAD_ATTR               10 (text)
              PUSH_NULL
              LOAD_CONST              82 ("'unverified'")
              CALL                     1

284           LOAD_CONST               6 (('nullable', 'server_default'))
              CALL_KW                  4

290           LOAD_GLOBAL              4 (sa)
              LOAD_ATTR                6 (Column)
              PUSH_NULL

291           LOAD_CONST              19 ('created_at')

292           LOAD_GLOBAL              4 (sa)
              LOAD_ATTR               24 (DateTime)
              PUSH_NULL
              LOAD_CONST              11 (True)
              LOAD_CONST              20 (('timezone',))
              CALL_KW                  1

293           LOAD_CONST               4 (False)

294           LOAD_GLOBAL              4 (sa)
              LOAD_ATTR               10 (text)
              PUSH_NULL
              LOAD_CONST              21 ('now()')
              CALL                     1

290           LOAD_CONST               6 (('nullable', 'server_default'))
              CALL_KW                  4

296           LOAD_GLOBAL              4 (sa)
              LOAD_ATTR                6 (Column)
              PUSH_NULL

297           LOAD_CONST              22 ('updated_at')

298           LOAD_GLOBAL              4 (sa)
              LOAD_ATTR               24 (DateTime)
              PUSH_NULL
              LOAD_CONST              11 (True)
              LOAD_CONST              20 (('timezone',))
              CALL_KW                  1

299           LOAD_CONST               4 (False)

300           LOAD_GLOBAL              4 (sa)
              LOAD_ATTR               10 (text)
              PUSH_NULL
              LOAD_CONST              21 ('now()')
              CALL                     1

296           LOAD_CONST               6 (('nullable', 'server_default'))
              CALL_KW                  4

302           LOAD_GLOBAL              4 (sa)
              LOAD_ATTR               30 (CheckConstraint)
              PUSH_NULL

303           LOAD_CONST              83 ("access_control IN ('everyone', 'contacts', 'vip')")

304           LOAD_CONST              84 ('ck_call_mode_configs_access_control')

302           LOAD_CONST              41 (('name',))
              CALL_KW                  2

306           LOAD_GLOBAL              4 (sa)
              LOAD_ATTR               30 (CheckConstraint)
              PUSH_NULL

307           LOAD_CONST              85 ("verification_status IN ('unverified', 'pending', 'verified', 'failed')")

308           LOAD_CONST              86 ('ck_call_mode_configs_verification_status')

306           LOAD_CONST              41 (('name',))
              CALL_KW                  2

253           CALL                    15
              POP_TOP

313           LOAD_GLOBAL              0 (op)
              LOAD_ATTR               14 (create_table)
              PUSH_NULL

314           LOAD_CONST              87 ('forwarding_verification_attempts')

315           LOAD_GLOBAL              4 (sa)
              LOAD_ATTR                6 (Column)
              PUSH_NULL

316           LOAD_CONST              24 ('id')

317           LOAD_GLOBAL             16 (postgresql)
              LOAD_ATTR               18 (UUID)
              PUSH_NULL
              LOAD_CONST              11 (True)
              LOAD_CONST              12 (('as_uuid',))
              CALL_KW                  1

318           LOAD_CONST              11 (True)

319           LOAD_GLOBAL              4 (sa)
              LOAD_ATTR               10 (text)
              PUSH_NULL
              LOAD_CONST              25 ('gen_random_uuid()')
              CALL                     1

315           LOAD_CONST              26 (('primary_key', 'server_default'))
              CALL_KW                  4

321           LOAD_GLOBAL              4 (sa)
              LOAD_ATTR                6 (Column)
              PUSH_NULL

322           LOAD_CONST              10 ('owner_user_id')

323           LOAD_GLOBAL             16 (postgresql)
              LOAD_ATTR               18 (UUID)
              PUSH_NULL
              LOAD_CONST              11 (True)
              LOAD_CONST              12 (('as_uuid',))
              CALL_KW                  1

324           LOAD_GLOBAL              4 (sa)
              LOAD_ATTR               20 (ForeignKey)
              PUSH_NULL
              LOAD_CONST              13 ('users.id')
              LOAD_CONST              14 ('CASCADE')
              LOAD_CONST              15 (('ondelete',))
              CALL_KW                  2

325           LOAD_CONST               4 (False)

321           LOAD_CONST              29 (('nullable',))
              CALL_KW                  4

327           LOAD_GLOBAL              4 (sa)
              LOAD_ATTR                6 (Column)
              PUSH_NULL
              LOAD_CONST              88 ('verification_code')
              LOAD_GLOBAL              4 (sa)
              LOAD_ATTR               22 (Text)
              PUSH_NULL
              CALL                     0
              LOAD_CONST               4 (False)
              LOAD_CONST              29 (('nullable',))
              CALL_KW                  3

328           LOAD_GLOBAL              4 (sa)
              LOAD_ATTR                6 (Column)
              PUSH_NULL
              LOAD_CONST              30 ('status')
              LOAD_GLOBAL              4 (sa)
              LOAD_ATTR                8 (String)
              PUSH_NULL
              LOAD_CONST              28 (20)
              CALL                     1
              LOAD_CONST               4 (False)
              LOAD_CONST              29 (('nullable',))
              CALL_KW                  3

329           LOAD_GLOBAL              4 (sa)
              LOAD_ATTR                6 (Column)
              PUSH_NULL
              LOAD_CONST              89 ('initiated_at')
              LOAD_GLOBAL              4 (sa)
              LOAD_ATTR               24 (DateTime)
              PUSH_NULL
              LOAD_CONST              11 (True)
              LOAD_CONST              20 (('timezone',))
              CALL_KW                  1
              LOAD_CONST               4 (False)
              LOAD_CONST              29 (('nullable',))
              CALL_KW                  3

330           LOAD_GLOBAL              4 (sa)
              LOAD_ATTR                6 (Column)
              PUSH_NULL
              LOAD_CONST              90 ('completed_at')
              LOAD_GLOBAL              4 (sa)
              LOAD_ATTR               24 (DateTime)
              PUSH_NULL
              LOAD_CONST              11 (True)
              LOAD_CONST              20 (('timezone',))
              CALL_KW                  1
              LOAD_CONST              11 (True)
              LOAD_CONST              29 (('nullable',))
              CALL_KW                  3

331           LOAD_GLOBAL              4 (sa)
              LOAD_ATTR                6 (Column)
              PUSH_NULL
              LOAD_CONST              91 ('twilio_call_sid')
              LOAD_GLOBAL              4 (sa)
              LOAD_ATTR               22 (Text)
              PUSH_NULL
              CALL                     0
              LOAD_CONST              11 (True)
              LOAD_CONST              29 (('nullable',))
              CALL_KW                  3

332           LOAD_GLOBAL              4 (sa)
              LOAD_ATTR                6 (Column)
              PUSH_NULL
              LOAD_CONST              92 ('details_redacted')
              LOAD_GLOBAL             16 (postgresql)
              LOAD_ATTR               34 (JSONB)
              PUSH_NULL
              CALL                     0
              LOAD_CONST              11 (True)
              LOAD_CONST              29 (('nullable',))
              CALL_KW                  3

333           LOAD_GLOBAL              4 (sa)
              LOAD_ATTR                6 (Column)
              PUSH_NULL

334           LOAD_CONST              19 ('created_at')

335           LOAD_GLOBAL              4 (sa)
              LOAD_ATTR               24 (DateTime)
              PUSH_NULL
              LOAD_CONST              11 (True)
              LOAD_CONST              20 (('timezone',))
              CALL_KW                  1

336           LOAD_CONST               4 (False)

337           LOAD_GLOBAL              4 (sa)
              LOAD_ATTR               10 (text)
              PUSH_NULL
              LOAD_CONST              21 ('now()')
              CALL                     1

333           LOAD_CONST               6 (('nullable', 'server_default'))
              CALL_KW                  4

339           LOAD_GLOBAL              4 (sa)
              LOAD_ATTR               30 (CheckConstraint)
              PUSH_NULL

340           LOAD_CONST              93 ("status IN ('pending', 'passed', 'failed', 'expired')")

341           LOAD_CONST              94 ('ck_fwd_verification_status')

339           LOAD_CONST              41 (('name',))
              CALL_KW                  2

313           CALL                    11
              POP_TOP

344           LOAD_GLOBAL              0 (op)
              LOAD_ATTR               32 (create_index)
              PUSH_NULL

345           LOAD_CONST              95 ('ix_fwd_verification_user_status')

346           LOAD_CONST              87 ('forwarding_verification_attempts')

347           LOAD_CONST              10 ('owner_user_id')
              LOAD_CONST              30 ('status')
              BUILD_LIST               2

344           CALL                     3
              POP_TOP
              RETURN_CONST             0 (None)

Disassembly of <code object downgrade at 0x00000185C9ADC8C0, file "D:\fluence\Github\mattbot\backend\alembic\versions\004_billing_telephony_theme.py", line 351>:
351           RESUME                   0

352           LOAD_GLOBAL              0 (op)
              LOAD_ATTR                2 (drop_table)
              PUSH_NULL
              LOAD_CONST               1 ('forwarding_verification_attempts')
              CALL                     1
              POP_TOP

353           LOAD_GLOBAL              0 (op)
              LOAD_ATTR                2 (drop_table)
              PUSH_NULL
              LOAD_CONST               2 ('call_mode_configs')
              CALL                     1
              POP_TOP

354           LOAD_GLOBAL              0 (op)
              LOAD_ATTR                2 (drop_table)
              PUSH_NULL
              LOAD_CONST               3 ('user_numbers')
              CALL                     1
              POP_TOP

355           LOAD_GLOBAL              0 (op)
              LOAD_ATTR                2 (drop_table)
              PUSH_NULL
              LOAD_CONST               4 ('billing_events')
              CALL                     1
              POP_TOP

356           LOAD_GLOBAL              0 (op)
              LOAD_ATTR                2 (drop_table)
              PUSH_NULL
              LOAD_CONST               5 ('billing_usage')
              CALL                     1
              POP_TOP

357           LOAD_GLOBAL              0 (op)
              LOAD_ATTR                2 (drop_table)
              PUSH_NULL
              LOAD_CONST               6 ('billing_payment_methods')
              CALL                     1
              POP_TOP

358           LOAD_GLOBAL              0 (op)
              LOAD_ATTR                2 (drop_table)
              PUSH_NULL
              LOAD_CONST               7 ('billing_subscriptions')
              CALL                     1
              POP_TOP

359           LOAD_GLOBAL              0 (op)
              LOAD_ATTR                2 (drop_table)
              PUSH_NULL
              LOAD_CONST               8 ('billing_customers')
              CALL                     1
              POP_TOP

360           LOAD_GLOBAL              0 (op)
              LOAD_ATTR                4 (drop_constraint)
              PUSH_NULL

361           LOAD_CONST               9 ('ck_user_settings_theme_preference')
              LOAD_CONST              10 ('user_settings')
              LOAD_CONST              11 ('check')

360           LOAD_CONST              12 (('type_',))
              CALL_KW                  3
              POP_TOP

363           LOAD_GLOBAL              0 (op)
              LOAD_ATTR                6 (drop_column)
              PUSH_NULL
              LOAD_CONST              10 ('user_settings')
              LOAD_CONST              13 ('theme_preference')
              CALL                     2
              POP_TOP
              RETURN_CONST             0 (None)
