# Bytecode dump of: 012_agent_model_voice_prompt.pyc
# co_filename: D:\fluence\Github\mattbot\backend\alembic\versions\012_agent_model_voice_prompt.py
# co_names: ('__doc__', 'collections.abc', 'Sequence', 'sqlalchemy', 'sa', 'alembic', 'op', 'revision', 'str', '__annotations__', 'down_revision', 'branch_labels', 'depends_on', 'upgrade', 'downgrade')
# co_consts (strings): ['Agent model, voice catalog, prompt suggestions, prompt layering\n\nRevision ID: 012\nRevises: 011\nCreate Date: 2026-02-25\n\n', '012', 'revision', '011', 'down_revision', 'branch_labels', 'depends_on']

# --- Nested code object: upgrade ---
    # co_names: ('op', 'create_table', 'sa', 'Column', 'dialects', 'postgresql', 'UUID', 'String', 'Text', 'Boolean', 'Integer', 'DateTime', 'text', 'create_index', 'ForeignKey', 'CheckConstraint', 'add_column', 'create_foreign_key', 'drop_column', 'table', 'column', 'bulk_insert')
    # co_varnames: ('voices_table', 'suggestions_table')
    # co_consts (strings): ['voice_catalog', 'id', 'provider_voice_id', 'display_name', 'locale', 'en', 'gender_tag', 'preview_url', 'is_active', 'true', 'sort_order', '0', 'created_at', 'now()', 'voice_catalog_active_idx', 'prompt_suggestions', 'title', 'text', 'prompt_suggestions_active_idx', 'agents', 'owner_user_id', 'users.id', 'CASCADE', 'Call Screener', 'function_type', 'call_screener', 'is_default', 'status', 'active', 'updated_at', "status IN ('active', 'archived')", 'ck_agents_status', 'uq_agents_user_default', 'is_default = true', 'agents_owner_user_id_idx', 'agent_configs', 'agent_id', 'agents.id', 'voice_id', 'voice_catalog.id', 'SET NULL', 'user_instructions', 'system_prompt_key', 'default_v1', 'revision', '1', 'calls', 'fk_calls_agent_id', 'fk_calls_voice_id', 'call_ai_sessions', 'fk_call_ai_sessions_agent_id', '00000000-0000-4000-a000-000000000001', '21m00Tcm4TlvDq8ikWAM', 'Rachel', 'female', '00000000-0000-4000-a000-000000000002', 'pNInz6obpgDQGcFmaJgB', 'Adam', 'male', '00000000-0000-4000-a000-000000000003', 'EXAVITQu4vr4xnSDxMaL', 'Bella', '00000000-0000-4000-a000-000000000004', 'ErXwobaYiN019PkySvjV', 'Antoni', '00000000-0000-4000-a000-000000000005', 'MF3mGyEYCl7XYWbV9V6O', 'Elli', '00000000-0000-4000-a000-000000000006', 'TxGEqnHWrfWFTfGW9XjX', 'Josh', '00000000-0000-4000-b000-000000000001', 'Professional tone', 'Always maintain a professional and polite tone when speaking with callers.', '00000000-0000-4000-b000-000000000002', 'Take messages', 'If the caller wants to leave a message, collect their name, number, and a brief message.', '00000000-0000-4000-b000-000000000003', 'Screen for urgency', 'Ask the caller how urgent their matter is and whether it can wait until the next business day.', '00000000-0000-4000-b000-000000000004', 'No commitments', 'Do not make promises or commitments on my behalf. Let the caller know I will get back to them.', '00000000-0000-4000-b000-000000000005', 'Short and concise', 'Keep responses short and to the point. Do not engage in lengthy conversations.', '00000000-0000-4000-b000-000000000006', 'Business context', 'I run a small business. Callers may be clients, vendors, or potential customers.']
 20           RESUME                   0

 24           LOAD_GLOBAL              0 (op)
              LOAD_ATTR                2 (create_table)
              PUSH_NULL

 25           LOAD_CONST               1 ('voice_catalog')

 26           LOAD_GLOBAL              4 (sa)
              LOAD_ATTR                6 (Column)
              PUSH_NULL
              LOAD_CONST               2 ('id')
              LOAD_GLOBAL              4 (sa)
              LOAD_ATTR                8 (dialects)
              LOAD_ATTR               10 (postgresql)
              LOAD_ATTR               13 (UUID + NULL|self)
              LOAD_CONST               3 (True)
              LOAD_CONST               4 (('as_uuid',))
              CALL_KW                  1
              LOAD_CONST               3 (True)
              LOAD_CONST               5 (('primary_key',))
              CALL_KW                  3

 27           LOAD_GLOBAL              4 (sa)
              LOAD_ATTR                6 (Column)
              PUSH_NULL
              LOAD_CONST               6 ('provider_voice_id')
              LOAD_GLOBAL              4 (sa)
              LOAD_ATTR               14 (String)
              PUSH_NULL
              LOAD_CONST               7 (100)
              CALL                     1
              LOAD_CONST               8 (False)
              LOAD_CONST               9 (('nullable',))
              CALL_KW                  3

 28           LOAD_GLOBAL              4 (sa)
              LOAD_ATTR                6 (Column)
              PUSH_NULL
              LOAD_CONST              10 ('display_name')
              LOAD_GLOBAL              4 (sa)
              LOAD_ATTR               14 (String)
              PUSH_NULL
              LOAD_CONST               7 (100)
              CALL                     1
              LOAD_CONST               8 (False)
              LOAD_CONST               9 (('nullable',))
              CALL_KW                  3

 29           LOAD_GLOBAL              4 (sa)
              LOAD_ATTR                6 (Column)
              PUSH_NULL
              LOAD_CONST              11 ('locale')
              LOAD_GLOBAL              4 (sa)
              LOAD_ATTR               14 (String)
              PUSH_NULL
              LOAD_CONST              12 (10)
              CALL                     1
              LOAD_CONST               8 (False)
              LOAD_CONST              13 ('en')
              LOAD_CONST              14 (('nullable', 'server_default'))
              CALL_KW                  4

 30           LOAD_GLOBAL              4 (sa)
              LOAD_ATTR                6 (Column)
              PUSH_NULL
              LOAD_CONST              15 ('gender_tag')
              LOAD_GLOBAL              4 (sa)
              LOAD_ATTR               14 (String)
              PUSH_NULL
              LOAD_CONST              16 (20)
              CALL                     1
              LOAD_CONST               3 (True)
              LOAD_CONST               9 (('nullable',))
              CALL_KW                  3

 31           LOAD_GLOBAL              4 (sa)
              LOAD_ATTR                6 (Column)
              PUSH_NULL
              LOAD_CONST              17 ('preview_url')
              LOAD_GLOBAL              4 (sa)
              LOAD_ATTR               16 (Text)
              PUSH_NULL
              CALL                     0
              LOAD_CONST               3 (True)
              LOAD_CONST               9 (('nullable',))
              CALL_KW                  3

 32           LOAD_GLOBAL              4 (sa)
              LOAD_ATTR                6 (Column)
              PUSH_NULL
              LOAD_CONST              18 ('is_active')
              LOAD_GLOBAL              4 (sa)
              LOAD_ATTR               18 (Boolean)
              PUSH_NULL
              CALL                     0
              LOAD_CONST               8 (False)
              LOAD_CONST              19 ('true')
              LOAD_CONST              14 (('nullable', 'server_default'))
              CALL_KW                  4

 33           LOAD_GLOBAL              4 (sa)
              LOAD_ATTR                6 (Column)
              PUSH_NULL
              LOAD_CONST              20 ('sort_order')
              LOAD_GLOBAL              4 (sa)
              LOAD_ATTR               20 (Integer)
              PUSH_NULL
              CALL                     0
              LOAD_CONST               8 (False)
              LOAD_CONST              21 ('0')
              LOAD_CONST              14 (('nullable', 'server_default'))
              CALL_KW                  4

 34           LOAD_GLOBAL              4 (sa)
              LOAD_ATTR                6 (Column)
              PUSH_NULL

 35           LOAD_CONST              22 ('created_at')

 36           LOAD_GLOBAL              4 (sa)
              LOAD_ATTR               22 (DateTime)
              PUSH_NULL
              LOAD_CONST               3 (True)
              LOAD_CONST              23 (('timezone',))
              CALL_KW                  1

 37           LOAD_CONST               8 (False)

 38           LOAD_GLOBAL              4 (sa)
              LOAD_ATTR               24 (text)
              PUSH_NULL
              LOAD_CONST              24 ('now()')
              CALL                     1

 34           LOAD_CONST              14 (('nullable', 'server_default'))
              CALL_KW                  4

 24           CALL                    10
              POP_TOP

 41           LOAD_GLOBAL              0 (op)
              LOAD_ATTR               26 (create_index)
              PUSH_NULL

 42           LOAD_CONST              25 ('voice_catalog_active_idx')

 43           LOAD_CONST               1 ('voice_catalog')

 44           LOAD_CONST              18 ('is_active')
              LOAD_CONST              20 ('sort_order')
              BUILD_LIST               2

 41           CALL                     3
              POP_TOP

 50           LOAD_GLOBAL              0 (op)
              LOAD_ATTR                2 (create_table)
              PUSH_NULL

 51           LOAD_CONST              26 ('prompt_suggestions')

 52           LOAD_GLOBAL              4 (sa)
              LOAD_ATTR                6 (Column)
              PUSH_NULL
              LOAD_CONST               2 ('id')
              LOAD_GLOBAL              4 (sa)
              LOAD_ATTR                8 (dialects)
              LOAD_ATTR               10 (postgresql)
              LOAD_ATTR               13 (UUID + NULL|self)
              LOAD_CONST               3 (True)
              LOAD_CONST               4 (('as_uuid',))
              CALL_KW                  1
              LOAD_CONST               3 (True)
              LOAD_CONST               5 (('primary_key',))
              CALL_KW                  3

 53           LOAD_GLOBAL              4 (sa)
              LOAD_ATTR                6 (Column)
              PUSH_NULL
              LOAD_CONST              27 ('title')
              LOAD_GLOBAL              4 (sa)
              LOAD_ATTR               14 (String)
              PUSH_NULL
              LOAD_CONST               7 (100)
              CALL                     1
              LOAD_CONST               8 (False)
              LOAD_CONST               9 (('nullable',))
              CALL_KW                  3

 54           LOAD_GLOBAL              4 (sa)
              LOAD_ATTR                6 (Column)
              PUSH_NULL
              LOAD_CONST              28 ('text')
              LOAD_GLOBAL              4 (sa)
              LOAD_ATTR               16 (Text)
              PUSH_NULL
              CALL                     0
              LOAD_CONST               8 (False)
              LOAD_CONST               9 (('nullable',))
              CALL_KW                  3

 55           LOAD_GLOBAL              4 (sa)
              LOAD_ATTR                6 (Column)
              PUSH_NULL
              LOAD_CONST              20 ('sort_order')
              LOAD_GLOBAL              4 (sa)
              LOAD_ATTR               20 (Integer)
              PUSH_NULL
              CALL                     0
              LOAD_CONST               8 (False)
              LOAD_CONST              21 ('0')
              LOAD_CONST              14 (('nullable', 'server_default'))
              CALL_KW                  4

 56           LOAD_GLOBAL              4 (sa)
              LOAD_ATTR                6 (Column)
              PUSH_NULL
              LOAD_CONST              18 ('is_active')
              LOAD_GLOBAL              4 (sa)
              LOAD_ATTR               18 (Boolean)
              PUSH_NULL
              CALL                     0
              LOAD_CONST               8 (False)
              LOAD_CONST              19 ('true')
              LOAD_CONST              14 (('nullable', 'server_default'))
              CALL_KW                  4

 57           LOAD_GLOBAL              4 (sa)
              LOAD_ATTR                6 (Column)
              PUSH_NULL

 58           LOAD_CONST              22 ('created_at')

 59           LOAD_GLOBAL              4 (sa)
              LOAD_ATTR               22 (DateTime)
              PUSH_NULL
              LOAD_CONST               3 (True)
              LOAD_CONST              23 (('timezone',))
              CALL_KW                  1

 60           LOAD_CONST               8 (False)

 61           LOAD_GLOBAL              4 (sa)
              LOAD_ATTR               24 (text)
              PUSH_NULL
              LOAD_CONST              24 ('now()')
              CALL                     1

 57           LOAD_CONST              14 (('nullable', 'server_default'))
              CALL_KW                  4

 50           CALL                     7
              POP_TOP

 64           LOAD_GLOBAL              0 (op)
              LOAD_ATTR               26 (create_index)
              PUSH_NULL

 65           LOAD_CONST              29 ('prompt_suggestions_active_idx')

 66           LOAD_CONST              26 ('prompt_suggestions')

 67           LOAD_CONST              18 ('is_active')
              LOAD_CONST              20 ('sort_order')
              BUILD_LIST               2

 64           CALL                     3
              POP_TOP

 73           LOAD_GLOBAL              0 (op)
              LOAD_ATTR                2 (create_table)
              PUSH_NULL

 74           LOAD_CONST              30 ('agents')

 75           LOAD_GLOBAL              4 (sa)
              LOAD_ATTR                6 (Column)
              PUSH_NULL
              LOAD_CONST               2 ('id')
              LOAD_GLOBAL              4 (sa)
              LOAD_ATTR                8 (dialects)
              LOAD_ATTR               10 (postgresql)
              LOAD_ATTR               13 (UUID + NULL|self)
              LOAD_CONST               3 (True)
              LOAD_CONST               4 (('as_uuid',))
              CALL_KW                  1
              LOAD_CONST               3 (True)
              LOAD_CONST               5 (('primary_key',))
              CALL_KW                  3

 76           LOAD_GLOBAL              4 (sa)
              LOAD_ATTR                6 (Column)
              PUSH_NULL

 77           LOAD_CONST              31 ('owner_user_id')

 78           LOAD_GLOBAL              4 (sa)
              LOAD_ATTR                8 (dialects)
              LOAD_ATTR               10 (postgresql)
              LOAD_ATTR               13 (UUID + NULL|self)
              LOAD_CONST               3 (True)
              LOAD_CONST               4 (('as_uuid',))
              CALL_KW                  1

 79           LOAD_GLOBAL              4 (sa)
              LOAD_ATTR               28 (ForeignKey)
              PUSH_NULL
              LOAD_CONST              32 ('users.id')
              LOAD_CONST              33 ('CASCADE')
              LOAD_CONST              34 (('ondelete',))
              CALL_KW                  2

 80           LOAD_CONST               8 (False)

 76           LOAD_CONST               9 (('nullable',))
              CALL_KW                  4

 82           LOAD_GLOBAL              4 (sa)
              LOAD_ATTR                6 (Column)
              PUSH_NULL

 83           LOAD_CONST              10 ('display_name')
              LOAD_GLOBAL              4 (sa)
              LOAD_ATTR               16 (Text)
              PUSH_NULL
              CALL                     0
              LOAD_CONST               8 (False)
              LOAD_CONST              35 ('Call Screener')

 82           LOAD_CONST              14 (('nullable', 'server_default'))
              CALL_KW                  4

 85           LOAD_GLOBAL              4 (sa)
              LOAD_ATTR                6 (Column)
              PUSH_NULL

 86           LOAD_CONST              36 ('function_type')
              LOAD_GLOBAL              4 (sa)
              LOAD_ATTR               14 (String)
              PUSH_NULL
              LOAD_CONST              37 (40)
              CALL                     1
              LOAD_CONST               8 (False)
              LOAD_CONST              38 ('call_screener')

 85           LOAD_CONST              14 (('nullable', 'server_default'))
              CALL_KW                  4

 88           LOAD_GLOBAL              4 (sa)
              LOAD_ATTR                6 (Column)
              PUSH_NULL
              LOAD_CONST              39 ('is_default')
              LOAD_GLOBAL              4 (sa)
              LOAD_ATTR               18 (Boolean)
              PUSH_NULL
              CALL                     0
              LOAD_CONST               8 (False)
              LOAD_CONST              19 ('true')
              LOAD_CONST              14 (('nullable', 'server_default'))
              CALL_KW                  4

 89           LOAD_GLOBAL              4 (sa)
              LOAD_ATTR                6 (Column)
              PUSH_NULL

 90           LOAD_CONST              40 ('status')
              LOAD_GLOBAL              4 (sa)
              LOAD_ATTR               14 (String)
              PUSH_NULL
              LOAD_CONST              16 (20)
              CALL                     1
              LOAD_CONST               8 (False)
              LOAD_CONST              41 ('active')

 89           LOAD_CONST              14 (('nullable', 'server_default'))
              CALL_KW                  4

 92           LOAD_GLOBAL              4 (sa)
              LOAD_ATTR                6 (Column)
              PUSH_NULL

 93           LOAD_CONST              22 ('created_at')

 94           LOAD_GLOBAL              4 (sa)
              LOAD_ATTR               22 (DateTime)
              PUSH_NULL
              LOAD_CONST               3 (True)
              LOAD_CONST              23 (('timezone',))
              CALL_KW                  1

 95           LOAD_CONST               8 (False)

 96           LOAD_GLOBAL              4 (sa)
              LOAD_ATTR               24 (text)
              PUSH_NULL
              LOAD_CONST              24 ('now()')
              CALL                     1

 92           LOAD_CONST              14 (('nullable', 'server_default'))
              CALL_KW                  4

 98           LOAD_GLOBAL              4 (sa)
              LOAD_ATTR                6 (Column)
              PUSH_NULL

 99           LOAD_CONST              42 ('updated_at')

100           LOAD_GLOBAL              4 (sa)
              LOAD_ATTR               22 (DateTime)
              PUSH_NULL
              LOAD_CONST               3 (True)
              LOAD_CONST              23 (('timezone',))
              CALL_KW                  1

101           LOAD_CONST               8 (False)

102           LOAD_GLOBAL              4 (sa)
              LOAD_ATTR               24 (text)
              PUSH_NULL
              LOAD_CONST              24 ('now()')
              CALL                     1

 98           LOAD_CONST              14 (('nullable', 'server_default'))
              CALL_KW                  4

104           LOAD_GLOBAL              4 (sa)
              LOAD_ATTR               30 (CheckConstraint)
              PUSH_NULL

105           LOAD_CONST              43 ("status IN ('active', 'archived')")
              LOAD_CONST              44 ('ck_agents_status')

104           LOAD_CONST              45 (('name',))
              CALL_KW                  2

 73           CALL                    10
              POP_TOP

108           LOAD_GLOBAL              0 (op)
              LOAD_ATTR               26 (create_index)
              PUSH_NULL

109           LOAD_CONST              46 ('uq_agents_user_default')

110           LOAD_CONST              30 ('agents')

111           LOAD_CONST              31 ('owner_user_id')
              BUILD_LIST               1

112           LOAD_CONST               3 (True)

113           LOAD_GLOBAL              4 (sa)
              LOAD_ATTR               24 (text)
              PUSH_NULL
              LOAD_CONST              47 ('is_default = true')
              CALL                     1

108           LOAD_CONST              48 (('unique', 'postgresql_where'))
              CALL_KW                  5
              POP_TOP

115           LOAD_GLOBAL              0 (op)
              LOAD_ATTR               26 (create_index)
              PUSH_NULL
              LOAD_CONST              49 ('agents_owner_user_id_idx')
              LOAD_CONST              30 ('agents')
              LOAD_CONST              31 ('owner_user_id')
              BUILD_LIST               1
              CALL                     3
              POP_TOP

120           LOAD_GLOBAL              0 (op)
              LOAD_ATTR                2 (create_table)
              PUSH_NULL

121           LOAD_CONST              50 ('agent_configs')

122           LOAD_GLOBAL              4 (sa)
              LOAD_ATTR                6 (Column)
              PUSH_NULL
              LOAD_CONST               2 ('id')
              LOAD_GLOBAL              4 (sa)
              LOAD_ATTR                8 (dialects)
              LOAD_ATTR               10 (postgresql)
              LOAD_ATTR               13 (UUID + NULL|self)
              LOAD_CONST               3 (True)
              LOAD_CONST               4 (('as_uuid',))
              CALL_KW                  1
              LOAD_CONST               3 (True)
              LOAD_CONST               5 (('primary_key',))
              CALL_KW                  3

123           LOAD_GLOBAL              4 (sa)
              LOAD_ATTR                6 (Column)
              PUSH_NULL

124           LOAD_CONST              51 ('agent_id')

125           LOAD_GLOBAL              4 (sa)
              LOAD_ATTR                8 (dialects)
              LOAD_ATTR               10 (postgresql)
              LOAD_ATTR               13 (UUID + NULL|self)
              LOAD_CONST               3 (True)
              LOAD_CONST               4 (('as_uuid',))
              CALL_KW                  1

126           LOAD_GLOBAL              4 (sa)
              LOAD_ATTR               28 (ForeignKey)
              PUSH_NULL
              LOAD_CONST              52 ('agents.id')
              LOAD_CONST              33 ('CASCADE')
              LOAD_CONST              34 (('ondelete',))
              CALL_KW                  2

127           LOAD_CONST               3 (True)

128           LOAD_CONST               8 (False)

123           LOAD_CONST              53 (('unique', 'nullable'))
              CALL_KW                  5

130           LOAD_GLOBAL              4 (sa)
              LOAD_ATTR                6 (Column)
              PUSH_NULL

131           LOAD_CONST              54 ('voice_id')

132           LOAD_GLOBAL              4 (sa)
              LOAD_ATTR                8 (dialects)
              LOAD_ATTR               10 (postgresql)
              LOAD_ATTR               13 (UUID + NULL|self)
              LOAD_CONST               3 (True)
              LOAD_CONST               4 (('as_uuid',))
              CALL_KW                  1

133           LOAD_GLOBAL              4 (sa)
              LOAD_ATTR               28 (ForeignKey)
              PUSH_NULL
              LOAD_CONST              55 ('voice_catalog.id')
              LOAD_CONST              56 ('SET NULL')
              LOAD_CONST              34 (('ondelete',))
              CALL_KW                  2

134           LOAD_CONST               3 (True)

130           LOAD_CONST               9 (('nullable',))
              CALL_KW                  4

136           LOAD_GLOBAL              4 (sa)
              LOAD_ATTR                6 (Column)
              PUSH_NULL
              LOAD_CONST              57 ('user_instructions')
              LOAD_GLOBAL              4 (sa)
              LOAD_ATTR               16 (Text)
              PUSH_NULL
              CALL                     0
              LOAD_CONST               3 (True)
              LOAD_CONST               9 (('nullable',))
              CALL_KW                  3

137           LOAD_GLOBAL              4 (sa)
              LOAD_ATTR                6 (Column)
              PUSH_NULL

138           LOAD_CONST              58 ('system_prompt_key')

139           LOAD_GLOBAL              4 (sa)
              LOAD_ATTR               14 (String)
              PUSH_NULL
              LOAD_CONST              37 (40)
              CALL                     1

140           LOAD_CONST               8 (False)

141           LOAD_CONST              59 ('default_v1')

137           LOAD_CONST              14 (('nullable', 'server_default'))
              CALL_KW                  4

143           LOAD_GLOBAL              4 (sa)
              LOAD_ATTR                6 (Column)
              PUSH_NULL
              LOAD_CONST              60 ('revision')
              LOAD_GLOBAL              4 (sa)
              LOAD_ATTR               20 (Integer)
              PUSH_NULL
              CALL                     0
              LOAD_CONST               8 (False)
              LOAD_CONST              61 ('1')
              LOAD_CONST              14 (('nullable', 'server_default'))
              CALL_KW                  4

144           LOAD_GLOBAL              4 (sa)
              LOAD_ATTR                6 (Column)
              PUSH_NULL

145           LOAD_CONST              22 ('created_at')

146           LOAD_GLOBAL              4 (sa)
              LOAD_ATTR               22 (DateTime)
              PUSH_NULL
              LOAD_CONST               3 (True)
              LOAD_CONST              23 (('timezone',))
              CALL_KW                  1

147           LOAD_CONST               8 (False)

148           LOAD_GLOBAL              4 (sa)
              LOAD_ATTR               24 (text)
              PUSH_NULL
              LOAD_CONST              24 ('now()')
              CALL                     1

144           LOAD_CONST              14 (('nullable', 'server_default'))
              CALL_KW                  4

150           LOAD_GLOBAL              4 (sa)
              LOAD_ATTR                6 (Column)
              PUSH_NULL

151           LOAD_CONST              42 ('updated_at')

152           LOAD_GLOBAL              4 (sa)
              LOAD_ATTR               22 (DateTime)
              PUSH_NULL
              LOAD_CONST               3 (True)
              LOAD_CONST              23 (('timezone',))
              CALL_KW                  1

153           LOAD_CONST               8 (False)

154           LOAD_GLOBAL              4 (sa)
              LOAD_ATTR               24 (text)
              PUSH_NULL
              LOAD_CONST              24 ('now()')
              CALL                     1

150           LOAD_CONST              14 (('nullable', 'server_default'))
              CALL_KW                  4

120           CALL                     9
              POP_TOP

161           LOAD_GLOBAL              0 (op)
              LOAD_ATTR               32 (add_column)
              PUSH_NULL

162           LOAD_CONST              62 ('calls')

163           LOAD_GLOBAL              4 (sa)
              LOAD_ATTR                6 (Column)
              PUSH_NULL

164           LOAD_CONST              51 ('agent_id')

165           LOAD_GLOBAL              4 (sa)
              LOAD_ATTR                8 (dialects)
              LOAD_ATTR               10 (postgresql)
              LOAD_ATTR               13 (UUID + NULL|self)
              LOAD_CONST               3 (True)
              LOAD_CONST               4 (('as_uuid',))
              CALL_KW                  1

166           LOAD_CONST               3 (True)

163           LOAD_CONST               9 (('nullable',))
              CALL_KW                  3

161           CALL                     2
              POP_TOP

169           LOAD_GLOBAL              0 (op)
              LOAD_ATTR               32 (add_column)
              PUSH_NULL

170           LOAD_CONST              62 ('calls')

171           LOAD_GLOBAL              4 (sa)
              LOAD_ATTR                6 (Column)
              PUSH_NULL

172           LOAD_CONST              54 ('voice_id')

173           LOAD_GLOBAL              4 (sa)
              LOAD_ATTR                8 (dialects)
              LOAD_ATTR               10 (postgresql)
              LOAD_ATTR               13 (UUID + NULL|self)
              LOAD_CONST               3 (True)
              LOAD_CONST               4 (('as_uuid',))
              CALL_KW                  1

174           LOAD_CONST               3 (True)

171           LOAD_CONST               9 (('nullable',))
              CALL_KW                  3

169           CALL                     2
              POP_TOP

177           LOAD_GLOBAL              0 (op)
              LOAD_ATTR               34 (create_foreign_key)
              PUSH_NULL

178           LOAD_CONST              63 ('fk_calls_agent_id')

179           LOAD_CONST              62 ('calls')

180           LOAD_CONST              30 ('agents')

181           LOAD_CONST              51 ('agent_id')
              BUILD_LIST               1

182           LOAD_CONST               2 ('id')
              BUILD_LIST               1

183           LOAD_CONST              56 ('SET NULL')

177           LOAD_CONST              34 (('ondelete',))
              CALL_KW                  6
              POP_TOP

185           LOAD_GLOBAL              0 (op)
              LOAD_ATTR               34 (create_foreign_key)
              PUSH_NULL

186           LOAD_CONST              64 ('fk_calls_voice_id')

187           LOAD_CONST              62 ('calls')

188           LOAD_CONST               1 ('voice_catalog')

189           LOAD_CONST              54 ('voice_id')
              BUILD_LIST               1

190           LOAD_CONST               2 ('id')
              BUILD_LIST               1

191           LOAD_CONST              56 ('SET NULL')

185           LOAD_CONST              34 (('ondelete',))
              CALL_KW                  6
              POP_TOP

197           LOAD_GLOBAL              0 (op)
              LOAD_ATTR               36 (drop_column)
              PUSH_NULL
              LOAD_CONST              65 ('call_ai_sessions')
              LOAD_CONST              51 ('agent_id')
              CALL                     2
              POP_TOP

198           LOAD_GLOBAL              0 (op)
              LOAD_ATTR               32 (add_column)
              PUSH_NULL

199           LOAD_CONST              65 ('call_ai_sessions')

200           LOAD_GLOBAL              4 (sa)
              LOAD_ATTR                6 (Column)
              PUSH_NULL

201           LOAD_CONST              51 ('agent_id')

202           LOAD_GLOBAL              4 (sa)
              LOAD_ATTR                8 (dialects)
              LOAD_ATTR               10 (postgresql)
              LOAD_ATTR               13 (UUID + NULL|self)
              LOAD_CONST               3 (True)
              LOAD_CONST               4 (('as_uuid',))
              CALL_KW                  1

203           LOAD_CONST               3 (True)

200           LOAD_CONST               9 (('nullable',))
              CALL_KW                  3

198           CALL                     2
              POP_TOP

206           LOAD_GLOBAL              0 (op)
              LOAD_ATTR               34 (create_foreign_key)
              PUSH_NULL

207           LOAD_CONST              66 ('fk_call_ai_sessions_agent_id')

208           LOAD_CONST              65 ('call_ai_sessions')

209           LOAD_CONST              30 ('agents')

210           LOAD_CONST              51 ('agent_id')
              BUILD_LIST               1

211           LOAD_CONST               2 ('id')
              BUILD_LIST               1

212           LOAD_CONST              56 ('SET NULL')

206           LOAD_CONST              34 (('ondelete',))
              CALL_KW                  6
              POP_TOP

218           LOAD_GLOBAL              4 (sa)
              LOAD_ATTR               38 (table)
              PUSH_NULL

219           LOAD_CONST               1 ('voice_catalog')

220           LOAD_GLOBAL              4 (sa)
              LOAD_ATTR               40 (column)
              PUSH_NULL
              LOAD_CONST               2 ('id')
              LOAD_GLOBAL              4 (sa)
              LOAD_ATTR                8 (dialects)
              LOAD_ATTR               10 (postgresql)
              LOAD_ATTR               13 (UUID + NULL|self)
              LOAD_CONST               3 (True)
              LOAD_CONST               4 (('as_uuid',))
              CALL_KW                  1
              CALL                     2

221           LOAD_GLOBAL              4 (sa)
              LOAD_ATTR               40 (column)
              PUSH_NULL
              LOAD_CONST               6 ('provider_voice_id')
              LOAD_GLOBAL              4 (sa)
              LOAD_ATTR               14 (String)
              CALL                     2

222           LOAD_GLOBAL              4 (sa)
              LOAD_ATTR               40 (column)
              PUSH_NULL
              LOAD_CONST              10 ('display_name')
              LOAD_GLOBAL              4 (sa)
              LOAD_ATTR               14 (String)
              CALL                     2

223           LOAD_GLOBAL              4 (sa)
              LOAD_ATTR               40 (column)
              PUSH_NULL
              LOAD_CONST              11 ('locale')
              LOAD_GLOBAL              4 (sa)
              LOAD_ATTR               14 (String)
              CALL                     2

224           LOAD_GLOBAL              4 (sa)
              LOAD_ATTR               40 (column)
              PUSH_NULL
              LOAD_CONST              15 ('gender_tag')
              LOAD_GLOBAL              4 (sa)
              LOAD_ATTR               14 (String)
              CALL                     2

225           LOAD_GLOBAL              4 (sa)
              LOAD_ATTR               40 (column)
              PUSH_NULL
              LOAD_CONST              20 ('sort_order')
              LOAD_GLOBAL              4 (sa)
              LOAD_ATTR               20 (Integer)
              CALL                     2

226           LOAD_GLOBAL              4 (sa)
              LOAD_ATTR               40 (column)
              PUSH_NULL
              LOAD_CONST              18 ('is_active')
              LOAD_GLOBAL              4 (sa)
              LOAD_ATTR               18 (Boolean)
              CALL                     2

218           CALL                     8
              STORE_FAST               0 (voices_table)

228           LOAD_GLOBAL              0 (op)
              LOAD_ATTR               42 (bulk_insert)
              PUSH_NULL

229           LOAD_FAST                0 (voices_table)

232           LOAD_CONST              67 ('00000000-0000-4000-a000-000000000001')

233           LOAD_CONST              68 ('21m00Tcm4TlvDq8ikWAM')

234           LOAD_CONST              69 ('Rachel')

235           LOAD_CONST              13 ('en')

236           LOAD_CONST              70 ('female')

237           LOAD_CONST              71 (0)

238           LOAD_CONST               3 (True)

231           LOAD_CONST              72 (('id', 'provider_voice_id', 'display_name', 'locale', 'gender_tag', 'sort_order', 'is_active'))
              BUILD_CONST_KEY_MAP      7

241           LOAD_CONST              73 ('00000000-0000-4000-a000-000000000002')

242           LOAD_CONST              74 ('pNInz6obpgDQGcFmaJgB')

243           LOAD_CONST              75 ('Adam')

244           LOAD_CONST              13 ('en')

245           LOAD_CONST              76 ('male')

246           LOAD_CONST              77 (1)

247           LOAD_CONST               3 (True)

240           LOAD_CONST              72 (('id', 'provider_voice_id', 'display_name', 'locale', 'gender_tag', 'sort_order', 'is_active'))
              BUILD_CONST_KEY_MAP      7

250           LOAD_CONST              78 ('00000000-0000-4000-a000-000000000003')

251           LOAD_CONST              79 ('EXAVITQu4vr4xnSDxMaL')

252           LOAD_CONST              80 ('Bella')

253           LOAD_CONST              13 ('en')

254           LOAD_CONST              70 ('female')

255           LOAD_CONST              81 (2)

256           LOAD_CONST               3 (True)

249           LOAD_CONST              72 (('id', 'provider_voice_id', 'display_name', 'locale', 'gender_tag', 'sort_order', 'is_active'))
              BUILD_CONST_KEY_MAP      7

259           LOAD_CONST              82 ('00000000-0000-4000-a000-000000000004')

260           LOAD_CONST              83 ('ErXwobaYiN019PkySvjV')

261           LOAD_CONST              84 ('Antoni')

262           LOAD_CONST              13 ('en')

263           LOAD_CONST              76 ('male')

264           LOAD_CONST              85 (3)

265           LOAD_CONST               3 (True)

258           LOAD_CONST              72 (('id', 'provider_voice_id', 'display_name', 'locale', 'gender_tag', 'sort_order', 'is_active'))
              BUILD_CONST_KEY_MAP      7

268           LOAD_CONST              86 ('00000000-0000-4000-a000-000000000005')

269           LOAD_CONST              87 ('MF3mGyEYCl7XYWbV9V6O')

270           LOAD_CONST              88 ('Elli')

271           LOAD_CONST              13 ('en')

272           LOAD_CONST              70 ('female')

273           LOAD_CONST              89 (4)

274           LOAD_CONST               3 (True)

267           LOAD_CONST              72 (('id', 'provider_voice_id', 'display_name', 'locale', 'gender_tag', 'sort_order', 'is_active'))
              BUILD_CONST_KEY_MAP      7

277           LOAD_CONST              90 ('00000000-0000-4000-a000-000000000006')

278           LOAD_CONST              91 ('TxGEqnHWrfWFTfGW9XjX')

279           LOAD_CONST              92 ('Josh')

280           LOAD_CONST              13 ('en')

281           LOAD_CONST              76 ('male')

282           LOAD_CONST              93 (5)

283           LOAD_CONST               3 (True)

276           LOAD_CONST              72 (('id', 'provider_voice_id', 'display_name', 'locale', 'gender_tag', 'sort_order', 'is_active'))
              BUILD_CONST_KEY_MAP      7

230           BUILD_LIST               6

228           CALL                     2
              POP_TOP

291           LOAD_GLOBAL              4 (sa)
              LOAD_ATTR               38 (table)
              PUSH_NULL

292           LOAD_CONST              26 ('prompt_suggestions')

293           LOAD_GLOBAL              4 (sa)
              LOAD_ATTR               40 (column)
              PUSH_NULL
              LOAD_CONST               2 ('id')
              LOAD_GLOBAL              4 (sa)
              LOAD_ATTR                8 (dialects)
              LOAD_ATTR               10 (postgresql)
              LOAD_ATTR               13 (UUID + NULL|self)
              LOAD_CONST               3 (True)
              LOAD_CONST               4 (('as_uuid',))
              CALL_KW                  1
              CALL                     2

294           LOAD_GLOBAL              4 (sa)
              LOAD_ATTR               40 (column)
              PUSH_NULL
              LOAD_CONST              27 ('title')
              LOAD_GLOBAL              4 (sa)
              LOAD_ATTR               14 (String)
              CALL                     2

295           LOAD_GLOBAL              4 (sa)
              LOAD_ATTR               40 (column)
              PUSH_NULL
              LOAD_CONST              28 ('text')
              LOAD_GLOBAL              4 (sa)
              LOAD_ATTR               16 (Text)
              CALL                     2

296           LOAD_GLOBAL              4 (sa)
              LOAD_ATTR               40 (column)
              PUSH_NULL
              LOAD_CONST              20 ('sort_order')
              LOAD_GLOBAL              4 (sa)
              LOAD_ATTR               20 (Integer)
              CALL                     2

297           LOAD_GLOBAL              4 (sa)
              LOAD_ATTR               40 (column)
              PUSH_NULL
              LOAD_CONST              18 ('is_active')
              LOAD_GLOBAL              4 (sa)
              LOAD_ATTR               18 (Boolean)
              CALL                     2

291           CALL                     6
              STORE_FAST               1 (suggestions_table)

299           LOAD_GLOBAL              0 (op)
              LOAD_ATTR               42 (bulk_insert)
              PUSH_NULL

300           LOAD_FAST                1 (suggestions_table)

303           LOAD_CONST              94 ('00000000-0000-4000-b000-000000000001')

304           LOAD_CONST              95 ('Professional tone')

306           LOAD_CONST              96 ('Always maintain a professional and polite tone when speaking with callers.')

309           LOAD_CONST              71 (0)

310           LOAD_CONST               3 (True)

302           LOAD_CONST              97 (('id', 'title', 'text', 'sort_order', 'is_active'))
              BUILD_CONST_KEY_MAP      5

313           LOAD_CONST              98 ('00000000-0000-4000-b000-000000000002')

314           LOAD_CONST              99 ('Take messages')

316           LOAD_CONST             100 ('If the caller wants to leave a message, collect their name, number, and a brief message.')

320           LOAD_CONST              77 (1)

321           LOAD_CONST               3 (True)

312           LOAD_CONST              97 (('id', 'title', 'text', 'sort_order', 'is_active'))
              BUILD_CONST_KEY_MAP      5

324           LOAD_CONST             101 ('00000000-0000-4000-b000-000000000003')

325           LOAD_CONST             102 ('Screen for urgency')

327           LOAD_CONST             103 ('Ask the caller how urgent their matter is and whether it can wait until the next business day.')

331           LOAD_CONST              81 (2)

332           LOAD_CONST               3 (True)

323           LOAD_CONST              97 (('id', 'title', 'text', 'sort_order', 'is_active'))
              BUILD_CONST_KEY_MAP      5

335           LOAD_CONST             104 ('00000000-0000-4000-b000-000000000004')

336           LOAD_CONST             105 ('No commitments')

338           LOAD_CONST             106 ('Do not make promises or commitments on my behalf. Let the caller know I will get back to them.')

342           LOAD_CONST              85 (3)

343           LOAD_CONST               3 (True)

334           LOAD_CONST              97 (('id', 'title', 'text', 'sort_order', 'is_active'))
              BUILD_CONST_KEY_MAP      5

346           LOAD_CONST             107 ('00000000-0000-4000-b000-000000000005')

347           LOAD_CONST             108 ('Short and concise')

349           LOAD_CONST             109 ('Keep responses short and to the point. Do not engage in lengthy conversations.')

352           LOAD_CONST              89 (4)

353           LOAD_CONST               3 (True)

345           LOAD_CONST              97 (('id', 'title', 'text', 'sort_order', 'is_active'))
              BUILD_CONST_KEY_MAP      5

356           LOAD_CONST             110 ('00000000-0000-4000-b000-000000000006')

357           LOAD_CONST             111 ('Business context')

359           LOAD_CONST             112 ('I run a small business. Callers may be clients, vendors, or potential customers.')

362           LOAD_CONST              93 (5)

363           LOAD_CONST               3 (True)

355           LOAD_CONST              97 (('id', 'title', 'text', 'sort_order', 'is_active'))
              BUILD_CONST_KEY_MAP      5

301           BUILD_LIST               6

299           CALL                     2
              POP_TOP
              RETURN_CONST             0 (None)

# --- Nested code object: downgrade ---
    # co_names: ('op', 'drop_constraint', 'drop_column', 'add_column', 'sa', 'Column', 'Text', 'drop_table', 'drop_index')
    # co_varnames: ()
    # co_consts (strings): ['fk_call_ai_sessions_agent_id', 'call_ai_sessions', 'foreignkey', 'agent_id', 'fk_calls_voice_id', 'calls', 'fk_calls_agent_id', 'voice_id', 'agent_configs', 'agents', 'prompt_suggestions_active_idx', 'prompt_suggestions', 'voice_catalog_active_idx', 'voice_catalog']
369           RESUME                   0

371           LOAD_GLOBAL              0 (op)
              LOAD_ATTR                2 (drop_constraint)
              PUSH_NULL

372           LOAD_CONST               1 ('fk_call_ai_sessions_agent_id')
              LOAD_CONST               2 ('call_ai_sessions')
              LOAD_CONST               3 ('foreignkey')

371           LOAD_CONST               4 (('type_',))
              CALL_KW                  3
              POP_TOP

374           LOAD_GLOBAL              0 (op)
              LOAD_ATTR                4 (drop_column)
              PUSH_NULL
              LOAD_CONST               2 ('call_ai_sessions')
              LOAD_CONST               5 ('agent_id')
              CALL                     2
              POP_TOP

375           LOAD_GLOBAL              0 (op)
              LOAD_ATTR                6 (add_column)
              PUSH_NULL

376           LOAD_CONST               2 ('call_ai_sessions')
              LOAD_GLOBAL              8 (sa)
              LOAD_ATTR               10 (Column)
              PUSH_NULL
              LOAD_CONST               5 ('agent_id')
              LOAD_GLOBAL              8 (sa)
              LOAD_ATTR               12 (Text)
              PUSH_NULL
              CALL                     0
              LOAD_CONST               6 (True)
              LOAD_CONST               7 (('nullable',))
              CALL_KW                  3

375           CALL                     2
              POP_TOP

380           LOAD_GLOBAL              0 (op)
              LOAD_ATTR                2 (drop_constraint)
              PUSH_NULL
              LOAD_CONST               8 ('fk_calls_voice_id')
              LOAD_CONST               9 ('calls')
              LOAD_CONST               3 ('foreignkey')
              LOAD_CONST               4 (('type_',))
              CALL_KW                  3
              POP_TOP

381           LOAD_GLOBAL              0 (op)
              LOAD_ATTR                2 (drop_constraint)
              PUSH_NULL
              LOAD_CONST              10 ('fk_calls_agent_id')
              LOAD_CONST               9 ('calls')
              LOAD_CONST               3 ('foreignkey')
              LOAD_CONST               4 (('type_',))
              CALL_KW                  3
              POP_TOP

382           LOAD_GLOBAL              0 (op)
              LOAD_ATTR                4 (drop_column)
              PUSH_NULL
              LOAD_CONST               9 ('calls')
              LOAD_CONST              11 ('voice_id')
              CALL                     2
              POP_TOP

383           LOAD_GLOBAL              0 (op)
              LOAD_ATTR                4 (drop_column)
              PUSH_NULL
              LOAD_CONST               9 ('calls')
              LOAD_CONST               5 ('agent_id')
              CALL                     2
              POP_TOP

385           LOAD_GLOBAL              0 (op)
              LOAD_ATTR               14 (drop_table)
              PUSH_NULL
              LOAD_CONST              12 ('agent_configs')
              CALL                     1
              POP_TOP

386           LOAD_GLOBAL              0 (op)
              LOAD_ATTR               14 (drop_table)
              PUSH_NULL
              LOAD_CONST              13 ('agents')
              CALL                     1
              POP_TOP

387           LOAD_GLOBAL              0 (op)
              LOAD_ATTR               16 (drop_index)
              PUSH_NULL
              LOAD_CONST              14 ('prompt_suggestions_active_idx')
              LOAD_CONST              15 ('prompt_suggestions')
              LOAD_CONST              16 (('table_name',))
              CALL_KW                  2
              POP_TOP

388           LOAD_GLOBAL              0 (op)
              LOAD_ATTR               14 (drop_table)
              PUSH_NULL
              LOAD_CONST              15 ('prompt_suggestions')
              CALL                     1
              POP_TOP

389           LOAD_GLOBAL              0 (op)
              LOAD_ATTR               16 (drop_index)
              PUSH_NULL
              LOAD_CONST              17 ('voice_catalog_active_idx')
              LOAD_CONST              18 ('voice_catalog')
              LOAD_CONST              16 (('table_name',))
              CALL_KW                  2
              POP_TOP

390           LOAD_GLOBAL              0 (op)
              LOAD_ATTR               14 (drop_table)
              PUSH_NULL
              LOAD_CONST              18 ('voice_catalog')
              CALL                     1
              POP_TOP
              RETURN_CONST             0 (None)

# --- Module-level bytecode ---
  0           RESUME                   0

  1           SETUP_ANNOTATIONS
              LOAD_CONST               0 ('Agent model, voice catalog, prompt suggestions, prompt layering\n\nRevision ID: 012\nRevises: 011\nCreate Date: 2026-02-25\n\n')
              STORE_NAME               0 (__doc__)

  8           LOAD_CONST               1 (0)
              LOAD_CONST               2 (('Sequence',))
              IMPORT_NAME              1 (collections.abc)
              IMPORT_FROM              2 (Sequence)
              STORE_NAME               2 (Sequence)
              POP_TOP

 10           LOAD_CONST               1 (0)
              LOAD_CONST               3 (None)
              IMPORT_NAME              3 (sqlalchemy)
              STORE_NAME               4 (sa)

 12           LOAD_CONST               1 (0)
              LOAD_CONST               4 (('op',))
              IMPORT_NAME              5 (alembic)
              IMPORT_FROM              6 (op)
              STORE_NAME               6 (op)
              POP_TOP

 14           LOAD_CONST               5 ('012')
              STORE_NAME               7 (revision)
              LOAD_NAME                8 (str)
              LOAD_NAME                9 (__annotations__)
              LOAD_CONST               6 ('revision')
              STORE_SUBSCR

 15           LOAD_CONST               7 ('011')
              STORE_NAME              10 (down_revision)
              LOAD_NAME                8 (str)
              LOAD_CONST               3 (None)
              BINARY_OP                7 (|)
              LOAD_NAME                9 (__annotations__)
              LOAD_CONST               8 ('down_revision')
              STORE_SUBSCR

 16           LOAD_CONST               3 (None)
              STORE_NAME              11 (branch_labels)
              LOAD_NAME                8 (str)
              LOAD_NAME                2 (Sequence)
              LOAD_NAME                8 (str)
              BINARY_SUBSCR
              BINARY_OP                7 (|)
              LOAD_CONST               3 (None)
              BINARY_OP                7 (|)
              LOAD_NAME                9 (__annotations__)
              LOAD_CONST               9 ('branch_labels')
              STORE_SUBSCR

 17           LOAD_CONST               3 (None)
              STORE_NAME              12 (depends_on)
              LOAD_NAME                8 (str)
              LOAD_NAME                2 (Sequence)
              LOAD_NAME                8 (str)
              BINARY_SUBSCR
              BINARY_OP                7 (|)
              LOAD_CONST               3 (None)
              BINARY_OP                7 (|)
              LOAD_NAME                9 (__annotations__)
              LOAD_CONST              10 ('depends_on')
              STORE_SUBSCR

 20           LOAD_CONST              13 (('return', None))
              LOAD_CONST              11 (<code object upgrade at 0x00000185C9B27830, file "D:\fluence\Github\mattbot\backend\alembic\versions\012_agent_model_voice_prompt.py", line 20>)
              MAKE_FUNCTION
              SET_FUNCTION_ATTRIBUTE   4 (annotations)
              STORE_NAME              13 (upgrade)

369           LOAD_CONST              13 (('return', None))
              LOAD_CONST              12 (<code object downgrade at 0x00000185C9B33050, file "D:\fluence\Github\mattbot\backend\alembic\versions\012_agent_model_voice_prompt.py", line 369>)
              MAKE_FUNCTION
              SET_FUNCTION_ATTRIBUTE   4 (annotations)
              STORE_NAME              14 (downgrade)
              RETURN_CONST             3 (None)

Disassembly of <code object upgrade at 0x00000185C9B27830, file "D:\fluence\Github\mattbot\backend\alembic\versions\012_agent_model_voice_prompt.py", line 20>:
 20           RESUME                   0

 24           LOAD_GLOBAL              0 (op)
              LOAD_ATTR                2 (create_table)
              PUSH_NULL

 25           LOAD_CONST               1 ('voice_catalog')

 26           LOAD_GLOBAL              4 (sa)
              LOAD_ATTR                6 (Column)
              PUSH_NULL
              LOAD_CONST               2 ('id')
              LOAD_GLOBAL              4 (sa)
              LOAD_ATTR                8 (dialects)
              LOAD_ATTR               10 (postgresql)
              LOAD_ATTR               13 (UUID + NULL|self)
              LOAD_CONST               3 (True)
              LOAD_CONST               4 (('as_uuid',))
              CALL_KW                  1
              LOAD_CONST               3 (True)
              LOAD_CONST               5 (('primary_key',))
              CALL_KW                  3

 27           LOAD_GLOBAL              4 (sa)
              LOAD_ATTR                6 (Column)
              PUSH_NULL
              LOAD_CONST               6 ('provider_voice_id')
              LOAD_GLOBAL              4 (sa)
              LOAD_ATTR               14 (String)
              PUSH_NULL
              LOAD_CONST               7 (100)
              CALL                     1
              LOAD_CONST               8 (False)
              LOAD_CONST               9 (('nullable',))
              CALL_KW                  3

 28           LOAD_GLOBAL              4 (sa)
              LOAD_ATTR                6 (Column)
              PUSH_NULL
              LOAD_CONST              10 ('display_name')
              LOAD_GLOBAL              4 (sa)
              LOAD_ATTR               14 (String)
              PUSH_NULL
              LOAD_CONST               7 (100)
              CALL                     1
              LOAD_CONST               8 (False)
              LOAD_CONST               9 (('nullable',))
              CALL_KW                  3

 29           LOAD_GLOBAL              4 (sa)
              LOAD_ATTR                6 (Column)
              PUSH_NULL
              LOAD_CONST              11 ('locale')
              LOAD_GLOBAL              4 (sa)
              LOAD_ATTR               14 (String)
              PUSH_NULL
              LOAD_CONST              12 (10)
              CALL                     1
              LOAD_CONST               8 (False)
              LOAD_CONST              13 ('en')
              LOAD_CONST              14 (('nullable', 'server_default'))
              CALL_KW                  4

 30           LOAD_GLOBAL              4 (sa)
              LOAD_ATTR                6 (Column)
              PUSH_NULL
              LOAD_CONST              15 ('gender_tag')
              LOAD_GLOBAL              4 (sa)
              LOAD_ATTR               14 (String)
              PUSH_NULL
              LOAD_CONST              16 (20)
              CALL                     1
              LOAD_CONST               3 (True)
              LOAD_CONST               9 (('nullable',))
              CALL_KW                  3

 31           LOAD_GLOBAL              4 (sa)
              LOAD_ATTR                6 (Column)
              PUSH_NULL
              LOAD_CONST              17 ('preview_url')
              LOAD_GLOBAL              4 (sa)
              LOAD_ATTR               16 (Text)
              PUSH_NULL
              CALL                     0
              LOAD_CONST               3 (True)
              LOAD_CONST               9 (('nullable',))
              CALL_KW                  3

 32           LOAD_GLOBAL              4 (sa)
              LOAD_ATTR                6 (Column)
              PUSH_NULL
              LOAD_CONST              18 ('is_active')
              LOAD_GLOBAL              4 (sa)
              LOAD_ATTR               18 (Boolean)
              PUSH_NULL
              CALL                     0
              LOAD_CONST               8 (False)
              LOAD_CONST              19 ('true')
              LOAD_CONST              14 (('nullable', 'server_default'))
              CALL_KW                  4

 33           LOAD_GLOBAL              4 (sa)
              LOAD_ATTR                6 (Column)
              PUSH_NULL
              LOAD_CONST              20 ('sort_order')
              LOAD_GLOBAL              4 (sa)
              LOAD_ATTR               20 (Integer)
              PUSH_NULL
              CALL                     0
              LOAD_CONST               8 (False)
              LOAD_CONST              21 ('0')
              LOAD_CONST              14 (('nullable', 'server_default'))
              CALL_KW                  4

 34           LOAD_GLOBAL              4 (sa)
              LOAD_ATTR                6 (Column)
              PUSH_NULL

 35           LOAD_CONST              22 ('created_at')

 36           LOAD_GLOBAL              4 (sa)
              LOAD_ATTR               22 (DateTime)
              PUSH_NULL
              LOAD_CONST               3 (True)
              LOAD_CONST              23 (('timezone',))
              CALL_KW                  1

 37           LOAD_CONST               8 (False)

 38           LOAD_GLOBAL              4 (sa)
              LOAD_ATTR               24 (text)
              PUSH_NULL
              LOAD_CONST              24 ('now()')
              CALL                     1

 34           LOAD_CONST              14 (('nullable', 'server_default'))
              CALL_KW                  4

 24           CALL                    10
              POP_TOP

 41           LOAD_GLOBAL              0 (op)
              LOAD_ATTR               26 (create_index)
              PUSH_NULL

 42           LOAD_CONST              25 ('voice_catalog_active_idx')

 43           LOAD_CONST               1 ('voice_catalog')

 44           LOAD_CONST              18 ('is_active')
              LOAD_CONST              20 ('sort_order')
              BUILD_LIST               2

 41           CALL                     3
              POP_TOP

 50           LOAD_GLOBAL              0 (op)
              LOAD_ATTR                2 (create_table)
              PUSH_NULL

 51           LOAD_CONST              26 ('prompt_suggestions')

 52           LOAD_GLOBAL              4 (sa)
              LOAD_ATTR                6 (Column)
              PUSH_NULL
              LOAD_CONST               2 ('id')
              LOAD_GLOBAL              4 (sa)
              LOAD_ATTR                8 (dialects)
              LOAD_ATTR               10 (postgresql)
              LOAD_ATTR               13 (UUID + NULL|self)
              LOAD_CONST               3 (True)
              LOAD_CONST               4 (('as_uuid',))
              CALL_KW                  1
              LOAD_CONST               3 (True)
              LOAD_CONST               5 (('primary_key',))
              CALL_KW                  3

 53           LOAD_GLOBAL              4 (sa)
              LOAD_ATTR                6 (Column)
              PUSH_NULL
              LOAD_CONST              27 ('title')
              LOAD_GLOBAL              4 (sa)
              LOAD_ATTR               14 (String)
              PUSH_NULL
              LOAD_CONST               7 (100)
              CALL                     1
              LOAD_CONST               8 (False)
              LOAD_CONST               9 (('nullable',))
              CALL_KW                  3

 54           LOAD_GLOBAL              4 (sa)
              LOAD_ATTR                6 (Column)
              PUSH_NULL
              LOAD_CONST              28 ('text')
              LOAD_GLOBAL              4 (sa)
              LOAD_ATTR               16 (Text)
              PUSH_NULL
              CALL                     0
              LOAD_CONST               8 (False)
              LOAD_CONST               9 (('nullable',))
              CALL_KW                  3

 55           LOAD_GLOBAL              4 (sa)
              LOAD_ATTR                6 (Column)
              PUSH_NULL
              LOAD_CONST              20 ('sort_order')
              LOAD_GLOBAL              4 (sa)
              LOAD_ATTR               20 (Integer)
              PUSH_NULL
              CALL                     0
              LOAD_CONST               8 (False)
              LOAD_CONST              21 ('0')
              LOAD_CONST              14 (('nullable', 'server_default'))
              CALL_KW                  4

 56           LOAD_GLOBAL              4 (sa)
              LOAD_ATTR                6 (Column)
              PUSH_NULL
              LOAD_CONST              18 ('is_active')
              LOAD_GLOBAL              4 (sa)
              LOAD_ATTR               18 (Boolean)
              PUSH_NULL
              CALL                     0
              LOAD_CONST               8 (False)
              LOAD_CONST              19 ('true')
              LOAD_CONST              14 (('nullable', 'server_default'))
              CALL_KW                  4

 57           LOAD_GLOBAL              4 (sa)
              LOAD_ATTR                6 (Column)
              PUSH_NULL

 58           LOAD_CONST              22 ('created_at')

 59           LOAD_GLOBAL              4 (sa)
              LOAD_ATTR               22 (DateTime)
              PUSH_NULL
              LOAD_CONST               3 (True)
              LOAD_CONST              23 (('timezone',))
              CALL_KW                  1

 60           LOAD_CONST               8 (False)

 61           LOAD_GLOBAL              4 (sa)
              LOAD_ATTR               24 (text)
              PUSH_NULL
              LOAD_CONST              24 ('now()')
              CALL                     1

 57           LOAD_CONST              14 (('nullable', 'server_default'))
              CALL_KW                  4

 50           CALL                     7
              POP_TOP

 64           LOAD_GLOBAL              0 (op)
              LOAD_ATTR               26 (create_index)
              PUSH_NULL

 65           LOAD_CONST              29 ('prompt_suggestions_active_idx')

 66           LOAD_CONST              26 ('prompt_suggestions')

 67           LOAD_CONST              18 ('is_active')
              LOAD_CONST              20 ('sort_order')
              BUILD_LIST               2

 64           CALL                     3
              POP_TOP

 73           LOAD_GLOBAL              0 (op)
              LOAD_ATTR                2 (create_table)
              PUSH_NULL

 74           LOAD_CONST              30 ('agents')

 75           LOAD_GLOBAL              4 (sa)
              LOAD_ATTR                6 (Column)
              PUSH_NULL
              LOAD_CONST               2 ('id')
              LOAD_GLOBAL              4 (sa)
              LOAD_ATTR                8 (dialects)
              LOAD_ATTR               10 (postgresql)
              LOAD_ATTR               13 (UUID + NULL|self)
              LOAD_CONST               3 (True)
              LOAD_CONST               4 (('as_uuid',))
              CALL_KW                  1
              LOAD_CONST               3 (True)
              LOAD_CONST               5 (('primary_key',))
              CALL_KW                  3

 76           LOAD_GLOBAL              4 (sa)
              LOAD_ATTR                6 (Column)
              PUSH_NULL

 77           LOAD_CONST              31 ('owner_user_id')

 78           LOAD_GLOBAL              4 (sa)
              LOAD_ATTR                8 (dialects)
              LOAD_ATTR               10 (postgresql)
              LOAD_ATTR               13 (UUID + NULL|self)
              LOAD_CONST               3 (True)
              LOAD_CONST               4 (('as_uuid',))
              CALL_KW                  1

 79           LOAD_GLOBAL              4 (sa)
              LOAD_ATTR               28 (ForeignKey)
              PUSH_NULL
              LOAD_CONST              32 ('users.id')
              LOAD_CONST              33 ('CASCADE')
              LOAD_CONST              34 (('ondelete',))
              CALL_KW                  2

 80           LOAD_CONST               8 (False)

 76           LOAD_CONST               9 (('nullable',))
              CALL_KW                  4

 82           LOAD_GLOBAL              4 (sa)
              LOAD_ATTR                6 (Column)
              PUSH_NULL

 83           LOAD_CONST              10 ('display_name')
              LOAD_GLOBAL              4 (sa)
              LOAD_ATTR               16 (Text)
              PUSH_NULL
              CALL                     0
              LOAD_CONST               8 (False)
              LOAD_CONST              35 ('Call Screener')

 82           LOAD_CONST              14 (('nullable', 'server_default'))
              CALL_KW                  4

 85           LOAD_GLOBAL              4 (sa)
              LOAD_ATTR                6 (Column)
              PUSH_NULL

 86           LOAD_CONST              36 ('function_type')
              LOAD_GLOBAL              4 (sa)
              LOAD_ATTR               14 (String)
              PUSH_NULL
              LOAD_CONST              37 (40)
              CALL                     1
              LOAD_CONST               8 (False)
              LOAD_CONST              38 ('call_screener')

 85           LOAD_CONST              14 (('nullable', 'server_default'))
              CALL_KW                  4

 88           LOAD_GLOBAL              4 (sa)
              LOAD_ATTR                6 (Column)
              PUSH_NULL
              LOAD_CONST              39 ('is_default')
              LOAD_GLOBAL              4 (sa)
              LOAD_ATTR               18 (Boolean)
              PUSH_NULL
              CALL                     0
              LOAD_CONST               8 (False)
              LOAD_CONST              19 ('true')
              LOAD_CONST              14 (('nullable', 'server_default'))
              CALL_KW                  4

 89           LOAD_GLOBAL              4 (sa)
              LOAD_ATTR                6 (Column)
              PUSH_NULL

 90           LOAD_CONST              40 ('status')
              LOAD_GLOBAL              4 (sa)
              LOAD_ATTR               14 (String)
              PUSH_NULL
              LOAD_CONST              16 (20)
              CALL                     1
              LOAD_CONST               8 (False)
              LOAD_CONST              41 ('active')

 89           LOAD_CONST              14 (('nullable', 'server_default'))
              CALL_KW                  4

 92           LOAD_GLOBAL              4 (sa)
              LOAD_ATTR                6 (Column)
              PUSH_NULL

 93           LOAD_CONST              22 ('created_at')

 94           LOAD_GLOBAL              4 (sa)
              LOAD_ATTR               22 (DateTime)
              PUSH_NULL
              LOAD_CONST               3 (True)
              LOAD_CONST              23 (('timezone',))
              CALL_KW                  1

 95           LOAD_CONST               8 (False)

 96           LOAD_GLOBAL              4 (sa)
              LOAD_ATTR               24 (text)
              PUSH_NULL
              LOAD_CONST              24 ('now()')
              CALL                     1

 92           LOAD_CONST              14 (('nullable', 'server_default'))
              CALL_KW                  4

 98           LOAD_GLOBAL              4 (sa)
              LOAD_ATTR                6 (Column)
              PUSH_NULL

 99           LOAD_CONST              42 ('updated_at')

100           LOAD_GLOBAL              4 (sa)
              LOAD_ATTR               22 (DateTime)
              PUSH_NULL
              LOAD_CONST               3 (True)
              LOAD_CONST              23 (('timezone',))
              CALL_KW                  1

101           LOAD_CONST               8 (False)

102           LOAD_GLOBAL              4 (sa)
              LOAD_ATTR               24 (text)
              PUSH_NULL
              LOAD_CONST              24 ('now()')
              CALL                     1

 98           LOAD_CONST              14 (('nullable', 'server_default'))
              CALL_KW                  4

104           LOAD_GLOBAL              4 (sa)
              LOAD_ATTR               30 (CheckConstraint)
              PUSH_NULL

105           LOAD_CONST              43 ("status IN ('active', 'archived')")
              LOAD_CONST              44 ('ck_agents_status')

104           LOAD_CONST              45 (('name',))
              CALL_KW                  2

 73           CALL                    10
              POP_TOP

108           LOAD_GLOBAL              0 (op)
              LOAD_ATTR               26 (create_index)
              PUSH_NULL

109           LOAD_CONST              46 ('uq_agents_user_default')

110           LOAD_CONST              30 ('agents')

111           LOAD_CONST              31 ('owner_user_id')
              BUILD_LIST               1

112           LOAD_CONST               3 (True)

113           LOAD_GLOBAL              4 (sa)
              LOAD_ATTR               24 (text)
              PUSH_NULL
              LOAD_CONST              47 ('is_default = true')
              CALL                     1

108           LOAD_CONST              48 (('unique', 'postgresql_where'))
              CALL_KW                  5
              POP_TOP

115           LOAD_GLOBAL              0 (op)
              LOAD_ATTR               26 (create_index)
              PUSH_NULL
              LOAD_CONST              49 ('agents_owner_user_id_idx')
              LOAD_CONST              30 ('agents')
              LOAD_CONST              31 ('owner_user_id')
              BUILD_LIST               1
              CALL                     3
              POP_TOP

120           LOAD_GLOBAL              0 (op)
              LOAD_ATTR                2 (create_table)
              PUSH_NULL

121           LOAD_CONST              50 ('agent_configs')

122           LOAD_GLOBAL              4 (sa)
              LOAD_ATTR                6 (Column)
              PUSH_NULL
              LOAD_CONST               2 ('id')
              LOAD_GLOBAL              4 (sa)
              LOAD_ATTR                8 (dialects)
              LOAD_ATTR               10 (postgresql)
              LOAD_ATTR               13 (UUID + NULL|self)
              LOAD_CONST               3 (True)
              LOAD_CONST               4 (('as_uuid',))
              CALL_KW                  1
              LOAD_CONST               3 (True)
              LOAD_CONST               5 (('primary_key',))
              CALL_KW                  3

123           LOAD_GLOBAL              4 (sa)
              LOAD_ATTR                6 (Column)
              PUSH_NULL

124           LOAD_CONST              51 ('agent_id')

125           LOAD_GLOBAL              4 (sa)
              LOAD_ATTR                8 (dialects)
              LOAD_ATTR               10 (postgresql)
              LOAD_ATTR               13 (UUID + NULL|self)
              LOAD_CONST               3 (True)
              LOAD_CONST               4 (('as_uuid',))
              CALL_KW                  1

126           LOAD_GLOBAL              4 (sa)
              LOAD_ATTR               28 (ForeignKey)
              PUSH_NULL
              LOAD_CONST              52 ('agents.id')
              LOAD_CONST              33 ('CASCADE')
              LOAD_CONST              34 (('ondelete',))
              CALL_KW                  2

127           LOAD_CONST               3 (True)

128           LOAD_CONST               8 (False)

123           LOAD_CONST              53 (('unique', 'nullable'))
              CALL_KW                  5

130           LOAD_GLOBAL              4 (sa)
              LOAD_ATTR                6 (Column)
              PUSH_NULL

131           LOAD_CONST              54 ('voice_id')

132           LOAD_GLOBAL              4 (sa)
              LOAD_ATTR                8 (dialects)
              LOAD_ATTR               10 (postgresql)
              LOAD_ATTR               13 (UUID + NULL|self)
              LOAD_CONST               3 (True)
              LOAD_CONST               4 (('as_uuid',))
              CALL_KW                  1

133           LOAD_GLOBAL              4 (sa)
              LOAD_ATTR               28 (ForeignKey)
              PUSH_NULL
              LOAD_CONST              55 ('voice_catalog.id')
              LOAD_CONST              56 ('SET NULL')
              LOAD_CONST              34 (('ondelete',))
              CALL_KW                  2

134           LOAD_CONST               3 (True)

130           LOAD_CONST               9 (('nullable',))
              CALL_KW                  4

136           LOAD_GLOBAL              4 (sa)
              LOAD_ATTR                6 (Column)
              PUSH_NULL
              LOAD_CONST              57 ('user_instructions')
              LOAD_GLOBAL              4 (sa)
              LOAD_ATTR               16 (Text)
              PUSH_NULL
              CALL                     0
              LOAD_CONST               3 (True)
              LOAD_CONST               9 (('nullable',))
              CALL_KW                  3

137           LOAD_GLOBAL              4 (sa)
              LOAD_ATTR                6 (Column)
              PUSH_NULL

138           LOAD_CONST              58 ('system_prompt_key')

139           LOAD_GLOBAL              4 (sa)
              LOAD_ATTR               14 (String)
              PUSH_NULL
              LOAD_CONST              37 (40)
              CALL                     1

140           LOAD_CONST               8 (False)

141           LOAD_CONST              59 ('default_v1')

137           LOAD_CONST              14 (('nullable', 'server_default'))
              CALL_KW                  4

143           LOAD_GLOBAL              4 (sa)
              LOAD_ATTR                6 (Column)
              PUSH_NULL
              LOAD_CONST              60 ('revision')
              LOAD_GLOBAL              4 (sa)
              LOAD_ATTR               20 (Integer)
              PUSH_NULL
              CALL                     0
              LOAD_CONST               8 (False)
              LOAD_CONST              61 ('1')
              LOAD_CONST              14 (('nullable', 'server_default'))
              CALL_KW                  4

144           LOAD_GLOBAL              4 (sa)
              LOAD_ATTR                6 (Column)
              PUSH_NULL

145           LOAD_CONST              22 ('created_at')

146           LOAD_GLOBAL              4 (sa)
              LOAD_ATTR               22 (DateTime)
              PUSH_NULL
              LOAD_CONST               3 (True)
              LOAD_CONST              23 (('timezone',))
              CALL_KW                  1

147           LOAD_CONST               8 (False)

148           LOAD_GLOBAL              4 (sa)
              LOAD_ATTR               24 (text)
              PUSH_NULL
              LOAD_CONST              24 ('now()')
              CALL                     1

144           LOAD_CONST              14 (('nullable', 'server_default'))
              CALL_KW                  4

150           LOAD_GLOBAL              4 (sa)
              LOAD_ATTR                6 (Column)
              PUSH_NULL

151           LOAD_CONST              42 ('updated_at')

152           LOAD_GLOBAL              4 (sa)
              LOAD_ATTR               22 (DateTime)
              PUSH_NULL
              LOAD_CONST               3 (True)
              LOAD_CONST              23 (('timezone',))
              CALL_KW                  1

153           LOAD_CONST               8 (False)

154           LOAD_GLOBAL              4 (sa)
              LOAD_ATTR               24 (text)
              PUSH_NULL
              LOAD_CONST              24 ('now()')
              CALL                     1

150           LOAD_CONST              14 (('nullable', 'server_default'))
              CALL_KW                  4

120           CALL                     9
              POP_TOP

161           LOAD_GLOBAL              0 (op)
              LOAD_ATTR               32 (add_column)
              PUSH_NULL

162           LOAD_CONST              62 ('calls')

163           LOAD_GLOBAL              4 (sa)
              LOAD_ATTR                6 (Column)
              PUSH_NULL

164           LOAD_CONST              51 ('agent_id')

165           LOAD_GLOBAL              4 (sa)
              LOAD_ATTR                8 (dialects)
              LOAD_ATTR               10 (postgresql)
              LOAD_ATTR               13 (UUID + NULL|self)
              LOAD_CONST               3 (True)
              LOAD_CONST               4 (('as_uuid',))
              CALL_KW                  1

166           LOAD_CONST               3 (True)

163           LOAD_CONST               9 (('nullable',))
              CALL_KW                  3

161           CALL                     2
              POP_TOP

169           LOAD_GLOBAL              0 (op)
              LOAD_ATTR               32 (add_column)
              PUSH_NULL

170           LOAD_CONST              62 ('calls')

171           LOAD_GLOBAL              4 (sa)
              LOAD_ATTR                6 (Column)
              PUSH_NULL

172           LOAD_CONST              54 ('voice_id')

173           LOAD_GLOBAL              4 (sa)
              LOAD_ATTR                8 (dialects)
              LOAD_ATTR               10 (postgresql)
              LOAD_ATTR               13 (UUID + NULL|self)
              LOAD_CONST               3 (True)
              LOAD_CONST               4 (('as_uuid',))
              CALL_KW                  1

174           LOAD_CONST               3 (True)

171           LOAD_CONST               9 (('nullable',))
              CALL_KW                  3

169           CALL                     2
              POP_TOP

177           LOAD_GLOBAL              0 (op)
              LOAD_ATTR               34 (create_foreign_key)
              PUSH_NULL

178           LOAD_CONST              63 ('fk_calls_agent_id')

179           LOAD_CONST              62 ('calls')

180           LOAD_CONST              30 ('agents')

181           LOAD_CONST              51 ('agent_id')
              BUILD_LIST               1

182           LOAD_CONST               2 ('id')
              BUILD_LIST               1

183           LOAD_CONST              56 ('SET NULL')

177           LOAD_CONST              34 (('ondelete',))
              CALL_KW                  6
              POP_TOP

185           LOAD_GLOBAL              0 (op)
              LOAD_ATTR               34 (create_foreign_key)
              PUSH_NULL

186           LOAD_CONST              64 ('fk_calls_voice_id')

187           LOAD_CONST              62 ('calls')

188           LOAD_CONST               1 ('voice_catalog')

189           LOAD_CONST              54 ('voice_id')
              BUILD_LIST               1

190           LOAD_CONST               2 ('id')
              BUILD_LIST               1

191           LOAD_CONST              56 ('SET NULL')

185           LOAD_CONST              34 (('ondelete',))
              CALL_KW                  6
              POP_TOP

197           LOAD_GLOBAL              0 (op)
              LOAD_ATTR               36 (drop_column)
              PUSH_NULL
              LOAD_CONST              65 ('call_ai_sessions')
              LOAD_CONST              51 ('agent_id')
              CALL                     2
              POP_TOP

198           LOAD_GLOBAL              0 (op)
              LOAD_ATTR               32 (add_column)
              PUSH_NULL

199           LOAD_CONST              65 ('call_ai_sessions')

200           LOAD_GLOBAL              4 (sa)
              LOAD_ATTR                6 (Column)
              PUSH_NULL

201           LOAD_CONST              51 ('agent_id')

202           LOAD_GLOBAL              4 (sa)
              LOAD_ATTR                8 (dialects)
              LOAD_ATTR               10 (postgresql)
              LOAD_ATTR               13 (UUID + NULL|self)
              LOAD_CONST               3 (True)
              LOAD_CONST               4 (('as_uuid',))
              CALL_KW                  1

203           LOAD_CONST               3 (True)

200           LOAD_CONST               9 (('nullable',))
              CALL_KW                  3

198           CALL                     2
              POP_TOP

206           LOAD_GLOBAL              0 (op)
              LOAD_ATTR               34 (create_foreign_key)
              PUSH_NULL

207           LOAD_CONST              66 ('fk_call_ai_sessions_agent_id')

208           LOAD_CONST              65 ('call_ai_sessions')

209           LOAD_CONST              30 ('agents')

210           LOAD_CONST              51 ('agent_id')
              BUILD_LIST               1

211           LOAD_CONST               2 ('id')
              BUILD_LIST               1

212           LOAD_CONST              56 ('SET NULL')

206           LOAD_CONST              34 (('ondelete',))
              CALL_KW                  6
              POP_TOP

218           LOAD_GLOBAL              4 (sa)
              LOAD_ATTR               38 (table)
              PUSH_NULL

219           LOAD_CONST               1 ('voice_catalog')

220           LOAD_GLOBAL              4 (sa)
              LOAD_ATTR               40 (column)
              PUSH_NULL
              LOAD_CONST               2 ('id')
              LOAD_GLOBAL              4 (sa)
              LOAD_ATTR                8 (dialects)
              LOAD_ATTR               10 (postgresql)
              LOAD_ATTR               13 (UUID + NULL|self)
              LOAD_CONST               3 (True)
              LOAD_CONST               4 (('as_uuid',))
              CALL_KW                  1
              CALL                     2

221           LOAD_GLOBAL              4 (sa)
              LOAD_ATTR               40 (column)
              PUSH_NULL
              LOAD_CONST               6 ('provider_voice_id')
              LOAD_GLOBAL              4 (sa)
              LOAD_ATTR               14 (String)
              CALL                     2

222           LOAD_GLOBAL              4 (sa)
              LOAD_ATTR               40 (column)
              PUSH_NULL
              LOAD_CONST              10 ('display_name')
              LOAD_GLOBAL              4 (sa)
              LOAD_ATTR               14 (String)
              CALL                     2

223           LOAD_GLOBAL              4 (sa)
              LOAD_ATTR               40 (column)
              PUSH_NULL
              LOAD_CONST              11 ('locale')
              LOAD_GLOBAL              4 (sa)
              LOAD_ATTR               14 (String)
              CALL                     2

224           LOAD_GLOBAL              4 (sa)
              LOAD_ATTR               40 (column)
              PUSH_NULL
              LOAD_CONST              15 ('gender_tag')
              LOAD_GLOBAL              4 (sa)
              LOAD_ATTR               14 (String)
              CALL                     2

225           LOAD_GLOBAL              4 (sa)
              LOAD_ATTR               40 (column)
              PUSH_NULL
              LOAD_CONST              20 ('sort_order')
              LOAD_GLOBAL              4 (sa)
              LOAD_ATTR               20 (Integer)
              CALL                     2

226           LOAD_GLOBAL              4 (sa)
              LOAD_ATTR               40 (column)
              PUSH_NULL
              LOAD_CONST              18 ('is_active')
              LOAD_GLOBAL              4 (sa)
              LOAD_ATTR               18 (Boolean)
              CALL                     2

218           CALL                     8
              STORE_FAST               0 (voices_table)

228           LOAD_GLOBAL              0 (op)
              LOAD_ATTR               42 (bulk_insert)
              PUSH_NULL

229           LOAD_FAST                0 (voices_table)

232           LOAD_CONST              67 ('00000000-0000-4000-a000-000000000001')

233           LOAD_CONST              68 ('21m00Tcm4TlvDq8ikWAM')

234           LOAD_CONST              69 ('Rachel')

235           LOAD_CONST              13 ('en')

236           LOAD_CONST              70 ('female')

237           LOAD_CONST              71 (0)

238           LOAD_CONST               3 (True)

231           LOAD_CONST              72 (('id', 'provider_voice_id', 'display_name', 'locale', 'gender_tag', 'sort_order', 'is_active'))
              BUILD_CONST_KEY_MAP      7

241           LOAD_CONST              73 ('00000000-0000-4000-a000-000000000002')

242           LOAD_CONST              74 ('pNInz6obpgDQGcFmaJgB')

243           LOAD_CONST              75 ('Adam')

244           LOAD_CONST              13 ('en')

245           LOAD_CONST              76 ('male')

246           LOAD_CONST              77 (1)

247           LOAD_CONST               3 (True)

240           LOAD_CONST              72 (('id', 'provider_voice_id', 'display_name', 'locale', 'gender_tag', 'sort_order', 'is_active'))
              BUILD_CONST_KEY_MAP      7

250           LOAD_CONST              78 ('00000000-0000-4000-a000-000000000003')

251           LOAD_CONST              79 ('EXAVITQu4vr4xnSDxMaL')

252           LOAD_CONST              80 ('Bella')

253           LOAD_CONST              13 ('en')

254           LOAD_CONST              70 ('female')

255           LOAD_CONST              81 (2)

256           LOAD_CONST               3 (True)

249           LOAD_CONST              72 (('id', 'provider_voice_id', 'display_name', 'locale', 'gender_tag', 'sort_order', 'is_active'))
              BUILD_CONST_KEY_MAP      7

259           LOAD_CONST              82 ('00000000-0000-4000-a000-000000000004')

260           LOAD_CONST              83 ('ErXwobaYiN019PkySvjV')

261           LOAD_CONST              84 ('Antoni')

262           LOAD_CONST              13 ('en')

263           LOAD_CONST              76 ('male')

264           LOAD_CONST              85 (3)

265           LOAD_CONST               3 (True)

258           LOAD_CONST              72 (('id', 'provider_voice_id', 'display_name', 'locale', 'gender_tag', 'sort_order', 'is_active'))
              BUILD_CONST_KEY_MAP      7

268           LOAD_CONST              86 ('00000000-0000-4000-a000-000000000005')

269           LOAD_CONST              87 ('MF3mGyEYCl7XYWbV9V6O')

270           LOAD_CONST              88 ('Elli')

271           LOAD_CONST              13 ('en')

272           LOAD_CONST              70 ('female')

273           LOAD_CONST              89 (4)

274           LOAD_CONST               3 (True)

267           LOAD_CONST              72 (('id', 'provider_voice_id', 'display_name', 'locale', 'gender_tag', 'sort_order', 'is_active'))
              BUILD_CONST_KEY_MAP      7

277           LOAD_CONST              90 ('00000000-0000-4000-a000-000000000006')

278           LOAD_CONST              91 ('TxGEqnHWrfWFTfGW9XjX')

279           LOAD_CONST              92 ('Josh')

280           LOAD_CONST              13 ('en')

281           LOAD_CONST              76 ('male')

282           LOAD_CONST              93 (5)

283           LOAD_CONST               3 (True)

276           LOAD_CONST              72 (('id', 'provider_voice_id', 'display_name', 'locale', 'gender_tag', 'sort_order', 'is_active'))
              BUILD_CONST_KEY_MAP      7

230           BUILD_LIST               6

228           CALL                     2
              POP_TOP

291           LOAD_GLOBAL              4 (sa)
              LOAD_ATTR               38 (table)
              PUSH_NULL

292           LOAD_CONST              26 ('prompt_suggestions')

293           LOAD_GLOBAL              4 (sa)
              LOAD_ATTR               40 (column)
              PUSH_NULL
              LOAD_CONST               2 ('id')
              LOAD_GLOBAL              4 (sa)
              LOAD_ATTR                8 (dialects)
              LOAD_ATTR               10 (postgresql)
              LOAD_ATTR               13 (UUID + NULL|self)
              LOAD_CONST               3 (True)
              LOAD_CONST               4 (('as_uuid',))
              CALL_KW                  1
              CALL                     2

294           LOAD_GLOBAL              4 (sa)
              LOAD_ATTR               40 (column)
              PUSH_NULL
              LOAD_CONST              27 ('title')
              LOAD_GLOBAL              4 (sa)
              LOAD_ATTR               14 (String)
              CALL                     2

295           LOAD_GLOBAL              4 (sa)
              LOAD_ATTR               40 (column)
              PUSH_NULL
              LOAD_CONST              28 ('text')
              LOAD_GLOBAL              4 (sa)
              LOAD_ATTR               16 (Text)
              CALL                     2

296           LOAD_GLOBAL              4 (sa)
              LOAD_ATTR               40 (column)
              PUSH_NULL
              LOAD_CONST              20 ('sort_order')
              LOAD_GLOBAL              4 (sa)
              LOAD_ATTR               20 (Integer)
              CALL                     2

297           LOAD_GLOBAL              4 (sa)
              LOAD_ATTR               40 (column)
              PUSH_NULL
              LOAD_CONST              18 ('is_active')
              LOAD_GLOBAL              4 (sa)
              LOAD_ATTR               18 (Boolean)
              CALL                     2

291           CALL                     6
              STORE_FAST               1 (suggestions_table)

299           LOAD_GLOBAL              0 (op)
              LOAD_ATTR               42 (bulk_insert)
              PUSH_NULL

300           LOAD_FAST                1 (suggestions_table)

303           LOAD_CONST              94 ('00000000-0000-4000-b000-000000000001')

304           LOAD_CONST              95 ('Professional tone')

306           LOAD_CONST              96 ('Always maintain a professional and polite tone when speaking with callers.')

309           LOAD_CONST              71 (0)

310           LOAD_CONST               3 (True)

302           LOAD_CONST              97 (('id', 'title', 'text', 'sort_order', 'is_active'))
              BUILD_CONST_KEY_MAP      5

313           LOAD_CONST              98 ('00000000-0000-4000-b000-000000000002')

314           LOAD_CONST              99 ('Take messages')

316           LOAD_CONST             100 ('If the caller wants to leave a message, collect their name, number, and a brief message.')

320           LOAD_CONST              77 (1)

321           LOAD_CONST               3 (True)

312           LOAD_CONST              97 (('id', 'title', 'text', 'sort_order', 'is_active'))
              BUILD_CONST_KEY_MAP      5

324           LOAD_CONST             101 ('00000000-0000-4000-b000-000000000003')

325           LOAD_CONST             102 ('Screen for urgency')

327           LOAD_CONST             103 ('Ask the caller how urgent their matter is and whether it can wait until the next business day.')

331           LOAD_CONST              81 (2)

332           LOAD_CONST               3 (True)

323           LOAD_CONST              97 (('id', 'title', 'text', 'sort_order', 'is_active'))
              BUILD_CONST_KEY_MAP      5

335           LOAD_CONST             104 ('00000000-0000-4000-b000-000000000004')

336           LOAD_CONST             105 ('No commitments')

338           LOAD_CONST             106 ('Do not make promises or commitments on my behalf. Let the caller know I will get back to them.')

342           LOAD_CONST              85 (3)

343           LOAD_CONST               3 (True)

334           LOAD_CONST              97 (('id', 'title', 'text', 'sort_order', 'is_active'))
              BUILD_CONST_KEY_MAP      5

346           LOAD_CONST             107 ('00000000-0000-4000-b000-000000000005')

347           LOAD_CONST             108 ('Short and concise')

349           LOAD_CONST             109 ('Keep responses short and to the point. Do not engage in lengthy conversations.')

352           LOAD_CONST              89 (4)

353           LOAD_CONST               3 (True)

345           LOAD_CONST              97 (('id', 'title', 'text', 'sort_order', 'is_active'))
              BUILD_CONST_KEY_MAP      5

356           LOAD_CONST             110 ('00000000-0000-4000-b000-000000000006')

357           LOAD_CONST             111 ('Business context')

359           LOAD_CONST             112 ('I run a small business. Callers may be clients, vendors, or potential customers.')

362           LOAD_CONST              93 (5)

363           LOAD_CONST               3 (True)

355           LOAD_CONST              97 (('id', 'title', 'text', 'sort_order', 'is_active'))
              BUILD_CONST_KEY_MAP      5

301           BUILD_LIST               6

299           CALL                     2
              POP_TOP
              RETURN_CONST             0 (None)

Disassembly of <code object downgrade at 0x00000185C9B33050, file "D:\fluence\Github\mattbot\backend\alembic\versions\012_agent_model_voice_prompt.py", line 369>:
369           RESUME                   0

371           LOAD_GLOBAL              0 (op)
              LOAD_ATTR                2 (drop_constraint)
              PUSH_NULL

372           LOAD_CONST               1 ('fk_call_ai_sessions_agent_id')
              LOAD_CONST               2 ('call_ai_sessions')
              LOAD_CONST               3 ('foreignkey')

371           LOAD_CONST               4 (('type_',))
              CALL_KW                  3
              POP_TOP

374           LOAD_GLOBAL              0 (op)
              LOAD_ATTR                4 (drop_column)
              PUSH_NULL
              LOAD_CONST               2 ('call_ai_sessions')
              LOAD_CONST               5 ('agent_id')
              CALL                     2
              POP_TOP

375           LOAD_GLOBAL              0 (op)
              LOAD_ATTR                6 (add_column)
              PUSH_NULL

376           LOAD_CONST               2 ('call_ai_sessions')
              LOAD_GLOBAL              8 (sa)
              LOAD_ATTR               10 (Column)
              PUSH_NULL
              LOAD_CONST               5 ('agent_id')
              LOAD_GLOBAL              8 (sa)
              LOAD_ATTR               12 (Text)
              PUSH_NULL
              CALL                     0
              LOAD_CONST               6 (True)
              LOAD_CONST               7 (('nullable',))
              CALL_KW                  3

375           CALL                     2
              POP_TOP

380           LOAD_GLOBAL              0 (op)
              LOAD_ATTR                2 (drop_constraint)
              PUSH_NULL
              LOAD_CONST               8 ('fk_calls_voice_id')
              LOAD_CONST               9 ('calls')
              LOAD_CONST               3 ('foreignkey')
              LOAD_CONST               4 (('type_',))
              CALL_KW                  3
              POP_TOP

381           LOAD_GLOBAL              0 (op)
              LOAD_ATTR                2 (drop_constraint)
              PUSH_NULL
              LOAD_CONST              10 ('fk_calls_agent_id')
              LOAD_CONST               9 ('calls')
              LOAD_CONST               3 ('foreignkey')
              LOAD_CONST               4 (('type_',))
              CALL_KW                  3
              POP_TOP

382           LOAD_GLOBAL              0 (op)
              LOAD_ATTR                4 (drop_column)
              PUSH_NULL
              LOAD_CONST               9 ('calls')
              LOAD_CONST              11 ('voice_id')
              CALL                     2
              POP_TOP

383           LOAD_GLOBAL              0 (op)
              LOAD_ATTR                4 (drop_column)
              PUSH_NULL
              LOAD_CONST               9 ('calls')
              LOAD_CONST               5 ('agent_id')
              CALL                     2
              POP_TOP

385           LOAD_GLOBAL              0 (op)
              LOAD_ATTR               14 (drop_table)
              PUSH_NULL
              LOAD_CONST              12 ('agent_configs')
              CALL                     1
              POP_TOP

386           LOAD_GLOBAL              0 (op)
              LOAD_ATTR               14 (drop_table)
              PUSH_NULL
              LOAD_CONST              13 ('agents')
              CALL                     1
              POP_TOP

387           LOAD_GLOBAL              0 (op)
              LOAD_ATTR               16 (drop_index)
              PUSH_NULL
              LOAD_CONST              14 ('prompt_suggestions_active_idx')
              LOAD_CONST              15 ('prompt_suggestions')
              LOAD_CONST              16 (('table_name',))
              CALL_KW                  2
              POP_TOP

388           LOAD_GLOBAL              0 (op)
              LOAD_ATTR               14 (drop_table)
              PUSH_NULL
              LOAD_CONST              15 ('prompt_suggestions')
              CALL                     1
              POP_TOP

389           LOAD_GLOBAL              0 (op)
              LOAD_ATTR               16 (drop_index)
              PUSH_NULL
              LOAD_CONST              17 ('voice_catalog_active_idx')
              LOAD_CONST              18 ('voice_catalog')
              LOAD_CONST              16 (('table_name',))
              CALL_KW                  2
              POP_TOP

390           LOAD_GLOBAL              0 (op)
              LOAD_ATTR               14 (drop_table)
              PUSH_NULL
              LOAD_CONST              18 ('voice_catalog')
              CALL                     1
              POP_TOP
              RETURN_CONST             0 (None)
