# Bytecode dump of: 015_phase1_completion.pyc
# co_filename: D:\fluence\Github\mattbot\backend\alembic\versions\015_phase1_completion.py
# co_names: ('__doc__', 'collections.abc', 'Sequence', 'sqlalchemy', 'sa', 'sqlalchemy.dialects.postgresql', 'JSONB', 'UUID', 'alembic', 'op', 'revision', 'str', '__annotations__', 'down_revision', 'branch_labels', 'depends_on', 'upgrade', 'downgrade')
# co_consts (strings): ['Phase 1 completion: VIP/block lists, reminders, notifications, handoff,\nand expanded user_settings columns.\n\nRevision ID: 015\nRevises: 014\nCreate Date: 2026-02-27\n\n', '015', 'revision', '014', 'down_revision', 'branch_labels', 'depends_on']

# --- Nested code object: upgrade ---
    # co_names: ('op', 'create_table', 'sa', 'Column', 'UUID', 'ForeignKey', 'LargeBinary', 'Integer', 'String', 'Text', 'DateTime', 'text', 'UniqueConstraint', 'create_index', 'CheckConstraint', 'JSONB', 'add_column', 'Boolean', 'create_check_constraint', 'Time')
    # co_varnames: ()
    # co_consts (strings): ['vip_entries', 'id', 'owner_user_id', 'users.id', 'CASCADE', 'phone_ciphertext', 'phone_nonce', 'phone_key_version', 'phone_hash', 'phone_last4', 'display_name', 'created_at', 'now()', 'updated_at', 'uq_vip_entries_user_phone', 'vip_entries_user_idx', 'block_entries', 'reason', 'uq_block_entries_user_phone', 'block_entries_user_idx', 'reminders', 'call_id', 'calls.id', 'SET NULL', 'title', 'due_at', 'timezone_at_creation', 'status', 'created_by_device_id', "status IN ('scheduled', 'triggered', 'completed', 'cancelled')", 'ck_reminders_status', 'reminders_user_due_idx', 'reminders_scheduled_due_idx', "status = 'scheduled'", 'notifications', 'type', 'priority', "'normal'", 'source_entity_type', 'source_entity_id', 'privacy_mode_applied', 'quiet_hours_applied', "'none'", 'content_hash', "type IN ('call_screened_created', 'call_important_detected', 'handoff_available', 'call_processing_error', 'reminder_due')", 'ck_notifications_type', "priority IN ('low', 'normal', 'high', 'critical')", 'ck_notifications_priority', "source_entity_type IN ('call', 'handoff_offer', 'reminder', 'system_error') OR source_entity_type IS NULL", 'ck_notifications_source_entity_type', "privacy_mode_applied IN ('private', 'preview')", 'ck_notifications_privacy_mode', "quiet_hours_applied IN ('none', 'silent', 'suppressed')", 'ck_notifications_quiet_hours', 'notifications_user_created_idx', 'created_at DESC', 'notification_deliveries', 'notification_id', 'notifications.id', 'device_id', 'devices.id', 'provider', "'queued'", 'attempt_count', '0', 'next_attempt_at', 'last_attempt_at', 'provider_message_id', 'last_error_code', 'last_error_message_short', "provider IN ('apns', 'fcm')", 'ck_notification_deliveries_provider', "status IN ('queued', 'sending', 'provider_accepted', 'provider_rejected', 'delivered_ack', 'expired', 'cancelled')", 'ck_notification_deliveries_status', 'uq_notification_deliveries_notif_device', 'handoff_offers', "'offered'", 'offer_reason', 'expires_at', 'selected_device_id', 'accepted_at', 'declined_at', 'preview_payload', 'uq_handoff_offers_call', "status IN ('offered', 'accepted', 'declined', 'expired')", 'ck_handoff_offers_status', "offer_reason IS NULL OR offer_reason IN ('vip', 'urgent', 'vip_and_urgent')", 'ck_handoff_offers_reason', 'handoff_offers_user_idx', 'handoff_offers_pending_idx', "status = 'offered'", 'handoff_suppressions', 'destination_phone_hash', 'suppression_expires_at', 'handoff_suppressions_user_dest_idx', 'calls', 'handoff_eligible', 'false', 'handoff_status', 'handoff_offered_at', 'handoff_offer_expires_at', 'handoff_accepted_at', 'handoff_selected_device_id', 'handoff_attempt_count', 'handoff_failure_reason', 'handoff_loop_detected', 'ck_calls_handoff_status', "handoff_status IS NULL OR handoff_status IN ('not_applicable', 'eligible_pending_minimum_data', 'offered', 'accepted', 'declined', 'expired', 'transfer_starting', 'transfer_connected', 'transfer_failed', 'transfer_cancelled')", 'calls_retention_idx', 'retention_expires_at', 'deleted_at IS NULL', 'user_settings', 'handoff_enabled', 'handoff_trigger', "'vip_only'", 'handoff_offer_timeout_seconds', '20', 'business_hours_enabled', 'business_hours_start', 'business_hours_end', 'business_hours_days', "'[]'::jsonb", 'after_hours_behavior', "'screen_normally'", 'temperament_preset', "'professional_polite'", 'swearing_rule', "'no_swearing'", 'language_primary', "'en'", 'language_secondary', 'vip_calls_mark_important', 'true', 'vip_notification_intensity', 'blocked_caller_behavior', "'end_immediately'", 'log_blocked_attempts', 'notify_on_blocked', 'spam_labeling_enabled', 'block_suggestions_enabled', 'repeat_caller_threshold', '3', 'text_approval_mode', "'always_approve'", 'assistant_name', "'Alex'", 'greeting_template', "'standard'", 'transcript_disclosure_mode', "'ai_says_it'", 'recording_announcement_required', 'important_rule', "'vip_and_urgent'", 'biometric_policy', "'gate_call_details'", 'ck_user_settings_handoff_trigger', "handoff_trigger IN ('vip_only', 'always', 'never')", 'ck_user_settings_handoff_timeout', 'handoff_offer_timeout_seconds BETWEEN 10 AND 60', 'ck_user_settings_after_hours', "after_hours_behavior IN ('screen_normally', 'voicemail_only', 'reject')", 'ck_user_settings_temperament', "temperament_preset IN ('professional_polite', 'casual_friendly', 'formal', 'custom')", 'ck_user_settings_swearing', "swearing_rule IN ('no_swearing', 'mirror_caller', 'allow')", 'ck_user_settings_vip_notif', "vip_notification_intensity IN ('normal', 'high', 'urgent')", 'ck_user_settings_blocked_behavior', "blocked_caller_behavior IN ('end_immediately', 'play_message', 'silent_drop')", 'ck_user_settings_repeat_threshold', 'repeat_caller_threshold BETWEEN 1 AND 10', 'ck_user_settings_text_approval', "text_approval_mode IN ('always_approve', 'auto_send', 'never')", 'ck_user_settings_greeting', "greeting_template IN ('standard', 'brief', 'formal', 'custom')", 'ck_user_settings_disclosure', "transcript_disclosure_mode IN ('ai_says_it', 'silent', 'beep')", 'ck_user_settings_important_rule', "important_rule IN ('vip_and_urgent', 'vip_only', 'urgent_only', 'all')", 'ck_user_settings_biometric_policy', "biometric_policy IN ('gate_call_details', 'gate_all', 'off')"]
 22           RESUME                   0

 26           LOAD_GLOBAL              0 (op)
              LOAD_ATTR                2 (create_table)
              PUSH_NULL

 27           LOAD_CONST               1 ('vip_entries')

 28           LOAD_GLOBAL              4 (sa)
              LOAD_ATTR                6 (Column)
              PUSH_NULL
              LOAD_CONST               2 ('id')
              LOAD_GLOBAL              9 (UUID + NULL)
              LOAD_CONST               3 (True)
              LOAD_CONST               4 (('as_uuid',))
              CALL_KW                  1
              LOAD_CONST               3 (True)
              LOAD_CONST               5 (('primary_key',))
              CALL_KW                  3

 29           LOAD_GLOBAL              4 (sa)
              LOAD_ATTR                6 (Column)
              PUSH_NULL

 30           LOAD_CONST               6 ('owner_user_id')

 31           LOAD_GLOBAL              9 (UUID + NULL)
              LOAD_CONST               3 (True)
              LOAD_CONST               4 (('as_uuid',))
              CALL_KW                  1

 32           LOAD_GLOBAL              4 (sa)
              LOAD_ATTR               10 (ForeignKey)
              PUSH_NULL
              LOAD_CONST               7 ('users.id')
              LOAD_CONST               8 ('CASCADE')
              LOAD_CONST               9 (('ondelete',))
              CALL_KW                  2

 33           LOAD_CONST              10 (False)

 29           LOAD_CONST              11 (('nullable',))
              CALL_KW                  4

 35           LOAD_GLOBAL              4 (sa)
              LOAD_ATTR                6 (Column)
              PUSH_NULL
              LOAD_CONST              12 ('phone_ciphertext')
              LOAD_GLOBAL              4 (sa)
              LOAD_ATTR               12 (LargeBinary)
              PUSH_NULL
              CALL                     0
              LOAD_CONST              10 (False)
              LOAD_CONST              11 (('nullable',))
              CALL_KW                  3

 36           LOAD_GLOBAL              4 (sa)
              LOAD_ATTR                6 (Column)
              PUSH_NULL
              LOAD_CONST              13 ('phone_nonce')
              LOAD_GLOBAL              4 (sa)
              LOAD_ATTR               12 (LargeBinary)
              PUSH_NULL
              CALL                     0
              LOAD_CONST              10 (False)
              LOAD_CONST              11 (('nullable',))
              CALL_KW                  3

 37           LOAD_GLOBAL              4 (sa)
              LOAD_ATTR                6 (Column)
              PUSH_NULL
              LOAD_CONST              14 ('phone_key_version')
              LOAD_GLOBAL              4 (sa)
              LOAD_ATTR               14 (Integer)
              PUSH_NULL
              CALL                     0
              LOAD_CONST              10 (False)
              LOAD_CONST              11 (('nullable',))
              CALL_KW                  3

 38           LOAD_GLOBAL              4 (sa)
              LOAD_ATTR                6 (Column)
              PUSH_NULL
              LOAD_CONST              15 ('phone_hash')
              LOAD_GLOBAL              4 (sa)
              LOAD_ATTR               16 (String)
              PUSH_NULL
              LOAD_CONST              16 (64)
              CALL                     1
              LOAD_CONST              10 (False)
              LOAD_CONST              11 (('nullable',))
              CALL_KW                  3

 39           LOAD_GLOBAL              4 (sa)
              LOAD_ATTR                6 (Column)
              PUSH_NULL
              LOAD_CONST              17 ('phone_last4')
              LOAD_GLOBAL              4 (sa)
              LOAD_ATTR               16 (String)
              PUSH_NULL
              LOAD_CONST              18 (4)
              CALL                     1
              LOAD_CONST              10 (False)
              LOAD_CONST              11 (('nullable',))
              CALL_KW                  3

 40           LOAD_GLOBAL              4 (sa)
              LOAD_ATTR                6 (Column)
              PUSH_NULL
              LOAD_CONST              19 ('display_name')
              LOAD_GLOBAL              4 (sa)
              LOAD_ATTR               18 (Text)
              PUSH_NULL
              CALL                     0
              LOAD_CONST               3 (True)
              LOAD_CONST              11 (('nullable',))
              CALL_KW                  3

 41           LOAD_GLOBAL              4 (sa)
              LOAD_ATTR                6 (Column)
              PUSH_NULL

 42           LOAD_CONST              20 ('created_at')

 43           LOAD_GLOBAL              4 (sa)
              LOAD_ATTR               20 (DateTime)
              PUSH_NULL
              LOAD_CONST               3 (True)
              LOAD_CONST              21 (('timezone',))
              CALL_KW                  1

 44           LOAD_CONST              10 (False)

 45           LOAD_GLOBAL              4 (sa)
              LOAD_ATTR               22 (text)
              PUSH_NULL
              LOAD_CONST              22 ('now()')
              CALL                     1

 41           LOAD_CONST              23 (('nullable', 'server_default'))
              CALL_KW                  4

 47           LOAD_GLOBAL              4 (sa)
              LOAD_ATTR                6 (Column)
              PUSH_NULL

 48           LOAD_CONST              24 ('updated_at')

 49           LOAD_GLOBAL              4 (sa)
              LOAD_ATTR               20 (DateTime)
              PUSH_NULL
              LOAD_CONST               3 (True)
              LOAD_CONST              21 (('timezone',))
              CALL_KW                  1

 50           LOAD_CONST              10 (False)

 51           LOAD_GLOBAL              4 (sa)
              LOAD_ATTR               22 (text)
              PUSH_NULL
              LOAD_CONST              22 ('now()')
              CALL                     1

 47           LOAD_CONST              23 (('nullable', 'server_default'))
              CALL_KW                  4

 53           LOAD_GLOBAL              4 (sa)
              LOAD_ATTR               24 (UniqueConstraint)
              PUSH_NULL

 54           LOAD_CONST               6 ('owner_user_id')
              LOAD_CONST              15 ('phone_hash')
              LOAD_CONST              25 ('uq_vip_entries_user_phone')

 53           LOAD_CONST              26 (('name',))
              CALL_KW                  3

 26           CALL                    12
              POP_TOP

 57           LOAD_GLOBAL              0 (op)
              LOAD_ATTR               26 (create_index)
              PUSH_NULL
              LOAD_CONST              27 ('vip_entries_user_idx')
              LOAD_CONST               1 ('vip_entries')
              LOAD_CONST               6 ('owner_user_id')
              BUILD_LIST               1
              CALL                     3
              POP_TOP

 62           LOAD_GLOBAL              0 (op)
              LOAD_ATTR                2 (create_table)
              PUSH_NULL

 63           LOAD_CONST              28 ('block_entries')

 64           LOAD_GLOBAL              4 (sa)
              LOAD_ATTR                6 (Column)
              PUSH_NULL
              LOAD_CONST               2 ('id')
              LOAD_GLOBAL              9 (UUID + NULL)
              LOAD_CONST               3 (True)
              LOAD_CONST               4 (('as_uuid',))
              CALL_KW                  1
              LOAD_CONST               3 (True)
              LOAD_CONST               5 (('primary_key',))
              CALL_KW                  3

 65           LOAD_GLOBAL              4 (sa)
              LOAD_ATTR                6 (Column)
              PUSH_NULL

 66           LOAD_CONST               6 ('owner_user_id')

 67           LOAD_GLOBAL              9 (UUID + NULL)
              LOAD_CONST               3 (True)
              LOAD_CONST               4 (('as_uuid',))
              CALL_KW                  1

 68           LOAD_GLOBAL              4 (sa)
              LOAD_ATTR               10 (ForeignKey)
              PUSH_NULL
              LOAD_CONST               7 ('users.id')
              LOAD_CONST               8 ('CASCADE')
              LOAD_CONST               9 (('ondelete',))
              CALL_KW                  2

 69           LOAD_CONST              10 (False)

 65           LOAD_CONST              11 (('nullable',))
              CALL_KW                  4

 71           LOAD_GLOBAL              4 (sa)
              LOAD_ATTR                6 (Column)
              PUSH_NULL
              LOAD_CONST              12 ('phone_ciphertext')
              LOAD_GLOBAL              4 (sa)
              LOAD_ATTR               12 (LargeBinary)
              PUSH_NULL
              CALL                     0
              LOAD_CONST              10 (False)
              LOAD_CONST              11 (('nullable',))
              CALL_KW                  3

 72           LOAD_GLOBAL              4 (sa)
              LOAD_ATTR                6 (Column)
              PUSH_NULL
              LOAD_CONST              13 ('phone_nonce')
              LOAD_GLOBAL              4 (sa)
              LOAD_ATTR               12 (LargeBinary)
              PUSH_NULL
              CALL                     0
              LOAD_CONST              10 (False)
              LOAD_CONST              11 (('nullable',))
              CALL_KW                  3

 73           LOAD_GLOBAL              4 (sa)
              LOAD_ATTR                6 (Column)
              PUSH_NULL
              LOAD_CONST              14 ('phone_key_version')
              LOAD_GLOBAL              4 (sa)
              LOAD_ATTR               14 (Integer)
              PUSH_NULL
              CALL                     0
              LOAD_CONST              10 (False)
              LOAD_CONST              11 (('nullable',))
              CALL_KW                  3

 74           LOAD_GLOBAL              4 (sa)
              LOAD_ATTR                6 (Column)
              PUSH_NULL
              LOAD_CONST              15 ('phone_hash')
              LOAD_GLOBAL              4 (sa)
              LOAD_ATTR               16 (String)
              PUSH_NULL
              LOAD_CONST              16 (64)
              CALL                     1
              LOAD_CONST              10 (False)
              LOAD_CONST              11 (('nullable',))
              CALL_KW                  3

 75           LOAD_GLOBAL              4 (sa)
              LOAD_ATTR                6 (Column)
              PUSH_NULL
              LOAD_CONST              17 ('phone_last4')
              LOAD_GLOBAL              4 (sa)
              LOAD_ATTR               16 (String)
              PUSH_NULL
              LOAD_CONST              18 (4)
              CALL                     1
              LOAD_CONST              10 (False)
              LOAD_CONST              11 (('nullable',))
              CALL_KW                  3

 76           LOAD_GLOBAL              4 (sa)
              LOAD_ATTR                6 (Column)
              PUSH_NULL
              LOAD_CONST              19 ('display_name')
              LOAD_GLOBAL              4 (sa)
              LOAD_ATTR               18 (Text)
              PUSH_NULL
              CALL                     0
              LOAD_CONST               3 (True)
              LOAD_CONST              11 (('nullable',))
              CALL_KW                  3

 77           LOAD_GLOBAL              4 (sa)
              LOAD_ATTR                6 (Column)
              PUSH_NULL
              LOAD_CONST              29 ('reason')
              LOAD_GLOBAL              4 (sa)
              LOAD_ATTR               18 (Text)
              PUSH_NULL
              CALL                     0
              LOAD_CONST               3 (True)
              LOAD_CONST              11 (('nullable',))
              CALL_KW                  3

 78           LOAD_GLOBAL              4 (sa)
              LOAD_ATTR                6 (Column)
              PUSH_NULL

 79           LOAD_CONST              20 ('created_at')

 80           LOAD_GLOBAL              4 (sa)
              LOAD_ATTR               20 (DateTime)
              PUSH_NULL
              LOAD_CONST               3 (True)
              LOAD_CONST              21 (('timezone',))
              CALL_KW                  1

 81           LOAD_CONST              10 (False)

 82           LOAD_GLOBAL              4 (sa)
              LOAD_ATTR               22 (text)
              PUSH_NULL
              LOAD_CONST              22 ('now()')
              CALL                     1

 78           LOAD_CONST              23 (('nullable', 'server_default'))
              CALL_KW                  4

 84           LOAD_GLOBAL              4 (sa)
              LOAD_ATTR                6 (Column)
              PUSH_NULL

 85           LOAD_CONST              24 ('updated_at')

 86           LOAD_GLOBAL              4 (sa)
              LOAD_ATTR               20 (DateTime)
              PUSH_NULL
              LOAD_CONST               3 (True)
              LOAD_CONST              21 (('timezone',))
              CALL_KW                  1

 87           LOAD_CONST              10 (False)

 88           LOAD_GLOBAL              4 (sa)
              LOAD_ATTR               22 (text)
              PUSH_NULL
              LOAD_CONST              22 ('now()')
              CALL                     1

 84           LOAD_CONST              23 (('nullable', 'server_default'))
              CALL_KW                  4

 90           LOAD_GLOBAL              4 (sa)
              LOAD_ATTR               24 (UniqueConstraint)
              PUSH_NULL

 91           LOAD_CONST               6 ('owner_user_id')
              LOAD_CONST              15 ('phone_hash')
              LOAD_CONST              30 ('uq_block_entries_user_phone')

 90           LOAD_CONST              26 (('name',))
              CALL_KW                  3

 62           CALL                    13
              POP_TOP

 94           LOAD_GLOBAL              0 (op)
              LOAD_ATTR               26 (create_index)
              PUSH_NULL
              LOAD_CONST              31 ('block_entries_user_idx')
              LOAD_CONST              28 ('block_entries')
              LOAD_CONST               6 ('owner_user_id')
              BUILD_LIST               1
              CALL                     3
              POP_TOP

 99           LOAD_GLOBAL              0 (op)
              LOAD_ATTR                2 (create_table)
              PUSH_NULL

100           LOAD_CONST              32 ('reminders')

101           LOAD_GLOBAL              4 (sa)
              LOAD_ATTR                6 (Column)
              PUSH_NULL
              LOAD_CONST               2 ('id')
              LOAD_GLOBAL              9 (UUID + NULL)
              LOAD_CONST               3 (True)
              LOAD_CONST               4 (('as_uuid',))
              CALL_KW                  1
              LOAD_CONST               3 (True)
              LOAD_CONST               5 (('primary_key',))
              CALL_KW                  3

102           LOAD_GLOBAL              4 (sa)
              LOAD_ATTR                6 (Column)
              PUSH_NULL

103           LOAD_CONST               6 ('owner_user_id')

104           LOAD_GLOBAL              9 (UUID + NULL)
              LOAD_CONST               3 (True)
              LOAD_CONST               4 (('as_uuid',))
              CALL_KW                  1

105           LOAD_GLOBAL              4 (sa)
              LOAD_ATTR               10 (ForeignKey)
              PUSH_NULL
              LOAD_CONST               7 ('users.id')
              LOAD_CONST               8 ('CASCADE')
              LOAD_CONST               9 (('ondelete',))
              CALL_KW                  2

106           LOAD_CONST              10 (False)

102           LOAD_CONST              11 (('nullable',))
              CALL_KW                  4

108           LOAD_GLOBAL              4 (sa)
              LOAD_ATTR                6 (Column)
              PUSH_NULL

109           LOAD_CONST              33 ('call_id')

110           LOAD_GLOBAL              9 (UUID + NULL)
              LOAD_CONST               3 (True)
              LOAD_CONST               4 (('as_uuid',))
              CALL_KW                  1

111           LOAD_GLOBAL              4 (sa)
              LOAD_ATTR               10 (ForeignKey)
              PUSH_NULL
              LOAD_CONST              34 ('calls.id')
              LOAD_CONST              35 ('SET NULL')
              LOAD_CONST               9 (('ondelete',))
              CALL_KW                  2

112           LOAD_CONST               3 (True)

108           LOAD_CONST              11 (('nullable',))
              CALL_KW                  4

114           LOAD_GLOBAL              4 (sa)
              LOAD_ATTR                6 (Column)
              PUSH_NULL
              LOAD_CONST              36 ('title')
              LOAD_GLOBAL              4 (sa)
              LOAD_ATTR               16 (String)
              PUSH_NULL
              LOAD_CONST              37 (200)
              CALL                     1
              LOAD_CONST              10 (False)
              LOAD_CONST              11 (('nullable',))
              CALL_KW                  3

115           LOAD_GLOBAL              4 (sa)
              LOAD_ATTR                6 (Column)
              PUSH_NULL
              LOAD_CONST              38 ('due_at')
              LOAD_GLOBAL              4 (sa)
              LOAD_ATTR               20 (DateTime)
              PUSH_NULL
              LOAD_CONST               3 (True)
              LOAD_CONST              21 (('timezone',))
              CALL_KW                  1
              LOAD_CONST              10 (False)
              LOAD_CONST              11 (('nullable',))
              CALL_KW                  3

116           LOAD_GLOBAL              4 (sa)
              LOAD_ATTR                6 (Column)
              PUSH_NULL
              LOAD_CONST              39 ('timezone_at_creation')
              LOAD_GLOBAL              4 (sa)
              LOAD_ATTR               18 (Text)
              PUSH_NULL
              CALL                     0
              LOAD_CONST               3 (True)
              LOAD_CONST              11 (('nullable',))
              CALL_KW                  3

117           LOAD_GLOBAL              4 (sa)
              LOAD_ATTR                6 (Column)
              PUSH_NULL
              LOAD_CONST              40 ('status')
              LOAD_GLOBAL              4 (sa)
              LOAD_ATTR               16 (String)
              PUSH_NULL
              LOAD_CONST              41 (20)
              CALL                     1
              LOAD_CONST              10 (False)
              LOAD_CONST              11 (('nullable',))
              CALL_KW                  3

118           LOAD_GLOBAL              4 (sa)
              LOAD_ATTR                6 (Column)
              PUSH_NULL

119           LOAD_CONST              20 ('created_at')

120           LOAD_GLOBAL              4 (sa)
              LOAD_ATTR               20 (DateTime)
              PUSH_NULL
              LOAD_CONST               3 (True)
              LOAD_CONST              21 (('timezone',))
              CALL_KW                  1

121           LOAD_CONST              10 (False)

122           LOAD_GLOBAL              4 (sa)
              LOAD_ATTR               22 (text)
              PUSH_NULL
              LOAD_CONST              22 ('now()')
              CALL                     1

118           LOAD_CONST              23 (('nullable', 'server_default'))
              CALL_KW                  4

124           LOAD_GLOBAL              4 (sa)
              LOAD_ATTR                6 (Column)
              PUSH_NULL

125           LOAD_CONST              24 ('updated_at')

126           LOAD_GLOBAL              4 (sa)
              LOAD_ATTR               20 (DateTime)
              PUSH_NULL
              LOAD_CONST               3 (True)
              LOAD_CONST              21 (('timezone',))
              CALL_KW                  1

127           LOAD_CONST              10 (False)

128           LOAD_GLOBAL              4 (sa)
              LOAD_ATTR               22 (text)
              PUSH_NULL
              LOAD_CONST              22 ('now()')
              CALL                     1

124           LOAD_CONST              23 (('nullable', 'server_default'))
              CALL_KW                  4

130           LOAD_GLOBAL              4 (sa)
              LOAD_ATTR                6 (Column)
              PUSH_NULL
              LOAD_CONST              42 ('created_by_device_id')
              LOAD_GLOBAL              9 (UUID + NULL)
              LOAD_CONST               3 (True)
              LOAD_CONST               4 (('as_uuid',))
              CALL_KW                  1
              LOAD_CONST               3 (True)
              LOAD_CONST              11 (('nullable',))
              CALL_KW                  3

131           LOAD_GLOBAL              4 (sa)
              LOAD_ATTR               28 (CheckConstraint)
              PUSH_NULL

132           LOAD_CONST              43 ("status IN ('scheduled', 'triggered', 'completed', 'cancelled')")

133           LOAD_CONST              44 ('ck_reminders_status')

131           LOAD_CONST              26 (('name',))
              CALL_KW                  2

 99           CALL                    12
              POP_TOP

136           LOAD_GLOBAL              0 (op)
              LOAD_ATTR               26 (create_index)
              PUSH_NULL

137           LOAD_CONST              45 ('reminders_user_due_idx')
              LOAD_CONST              32 ('reminders')
              LOAD_CONST               6 ('owner_user_id')
              LOAD_CONST              38 ('due_at')
              BUILD_LIST               2

136           CALL                     3
              POP_TOP

139           LOAD_GLOBAL              0 (op)
              LOAD_ATTR               26 (create_index)
              PUSH_NULL

140           LOAD_CONST              46 ('reminders_scheduled_due_idx')

141           LOAD_CONST              32 ('reminders')

142           LOAD_CONST              38 ('due_at')
              BUILD_LIST               1

143           LOAD_GLOBAL              4 (sa)
              LOAD_ATTR               22 (text)
              PUSH_NULL
              LOAD_CONST              47 ("status = 'scheduled'")
              CALL                     1

139           LOAD_CONST              48 (('postgresql_where',))
              CALL_KW                  4
              POP_TOP

149           LOAD_GLOBAL              0 (op)
              LOAD_ATTR                2 (create_table)
              PUSH_NULL

150           LOAD_CONST              49 ('notifications')

151           LOAD_GLOBAL              4 (sa)
              LOAD_ATTR                6 (Column)
              PUSH_NULL
              LOAD_CONST               2 ('id')
              LOAD_GLOBAL              9 (UUID + NULL)
              LOAD_CONST               3 (True)
              LOAD_CONST               4 (('as_uuid',))
              CALL_KW                  1
              LOAD_CONST               3 (True)
              LOAD_CONST               5 (('primary_key',))
              CALL_KW                  3

152           LOAD_GLOBAL              4 (sa)
              LOAD_ATTR                6 (Column)
              PUSH_NULL

153           LOAD_CONST               6 ('owner_user_id')

154           LOAD_GLOBAL              9 (UUID + NULL)
              LOAD_CONST               3 (True)
              LOAD_CONST               4 (('as_uuid',))
              CALL_KW                  1

155           LOAD_GLOBAL              4 (sa)
              LOAD_ATTR               10 (ForeignKey)
              PUSH_NULL
              LOAD_CONST               7 ('users.id')
              LOAD_CONST               8 ('CASCADE')
              LOAD_CONST               9 (('ondelete',))
              CALL_KW                  2

156           LOAD_CONST              10 (False)

152           LOAD_CONST              11 (('nullable',))
              CALL_KW                  4

158           LOAD_GLOBAL              4 (sa)
              LOAD_ATTR                6 (Column)
              PUSH_NULL
              LOAD_CONST              50 ('type')
              LOAD_GLOBAL              4 (sa)
              LOAD_ATTR               18 (Text)
              PUSH_NULL
              CALL                     0
              LOAD_CONST              10 (False)
              LOAD_CONST              11 (('nullable',))
              CALL_KW                  3

159           LOAD_GLOBAL              4 (sa)
              LOAD_ATTR                6 (Column)
              PUSH_NULL

160           LOAD_CONST              51 ('priority')

161           LOAD_GLOBAL              4 (sa)
              LOAD_ATTR               18 (Text)
              PUSH_NULL
              CALL                     0

162           LOAD_CONST              10 (False)

163           LOAD_GLOBAL              4 (sa)
              LOAD_ATTR               22 (text)
              PUSH_NULL
              LOAD_CONST              52 ("'normal'")
              CALL                     1

159           LOAD_CONST              23 (('nullable', 'server_default'))
              CALL_KW                  4

165           LOAD_GLOBAL              4 (sa)
              LOAD_ATTR                6 (Column)
              PUSH_NULL
              LOAD_CONST              53 ('source_entity_type')
              LOAD_GLOBAL              4 (sa)
              LOAD_ATTR               18 (Text)
              PUSH_NULL
              CALL                     0
              LOAD_CONST               3 (True)
              LOAD_CONST              11 (('nullable',))
              CALL_KW                  3

166           LOAD_GLOBAL              4 (sa)
              LOAD_ATTR                6 (Column)
              PUSH_NULL
              LOAD_CONST              54 ('source_entity_id')
              LOAD_GLOBAL              9 (UUID + NULL)
              LOAD_CONST               3 (True)
              LOAD_CONST               4 (('as_uuid',))
              CALL_KW                  1
              LOAD_CONST               3 (True)
              LOAD_CONST              11 (('nullable',))
              CALL_KW                  3

167           LOAD_GLOBAL              4 (sa)
              LOAD_ATTR                6 (Column)
              PUSH_NULL
              LOAD_CONST              55 ('privacy_mode_applied')
              LOAD_GLOBAL              4 (sa)
              LOAD_ATTR               18 (Text)
              PUSH_NULL
              CALL                     0
              LOAD_CONST              10 (False)
              LOAD_CONST              11 (('nullable',))
              CALL_KW                  3

168           LOAD_GLOBAL              4 (sa)
              LOAD_ATTR                6 (Column)
              PUSH_NULL

169           LOAD_CONST              56 ('quiet_hours_applied')

170           LOAD_GLOBAL              4 (sa)
              LOAD_ATTR               18 (Text)
              PUSH_NULL
              CALL                     0

171           LOAD_CONST              10 (False)

172           LOAD_GLOBAL              4 (sa)
              LOAD_ATTR               22 (text)
              PUSH_NULL
              LOAD_CONST              57 ("'none'")
              CALL                     1

168           LOAD_CONST              23 (('nullable', 'server_default'))
              CALL_KW                  4

174           LOAD_GLOBAL              4 (sa)
              LOAD_ATTR                6 (Column)
              PUSH_NULL
              LOAD_CONST              58 ('content_hash')
              LOAD_GLOBAL              4 (sa)
              LOAD_ATTR               16 (String)
              PUSH_NULL
              LOAD_CONST              16 (64)
              CALL                     1
              LOAD_CONST               3 (True)
              LOAD_CONST              11 (('nullable',))
              CALL_KW                  3

175           LOAD_GLOBAL              4 (sa)
              LOAD_ATTR                6 (Column)
              PUSH_NULL

176           LOAD_CONST              20 ('created_at')

177           LOAD_GLOBAL              4 (sa)
              LOAD_ATTR               20 (DateTime)
              PUSH_NULL
              LOAD_CONST               3 (True)
              LOAD_CONST              21 (('timezone',))
              CALL_KW                  1

178           LOAD_CONST              10 (False)

179           LOAD_GLOBAL              4 (sa)
              LOAD_ATTR               22 (text)
              PUSH_NULL
              LOAD_CONST              22 ('now()')
              CALL                     1

175           LOAD_CONST              23 (('nullable', 'server_default'))
              CALL_KW                  4

181           LOAD_GLOBAL              4 (sa)
              LOAD_ATTR               28 (CheckConstraint)
              PUSH_NULL

182           LOAD_CONST              59 ("type IN ('call_screened_created', 'call_important_detected', 'handoff_available', 'call_processing_error', 'reminder_due')")

184           LOAD_CONST              60 ('ck_notifications_type')

181           LOAD_CONST              26 (('name',))
              CALL_KW                  2

186           LOAD_GLOBAL              4 (sa)
              LOAD_ATTR               28 (CheckConstraint)
              PUSH_NULL

187           LOAD_CONST              61 ("priority IN ('low', 'normal', 'high', 'critical')")

188           LOAD_CONST              62 ('ck_notifications_priority')

186           LOAD_CONST              26 (('name',))
              CALL_KW                  2

190           LOAD_GLOBAL              4 (sa)
              LOAD_ATTR               28 (CheckConstraint)
              PUSH_NULL

191           LOAD_CONST              63 ("source_entity_type IN ('call', 'handoff_offer', 'reminder', 'system_error') OR source_entity_type IS NULL")

193           LOAD_CONST              64 ('ck_notifications_source_entity_type')

190           LOAD_CONST              26 (('name',))
              CALL_KW                  2

195           LOAD_GLOBAL              4 (sa)
              LOAD_ATTR               28 (CheckConstraint)
              PUSH_NULL

196           LOAD_CONST              65 ("privacy_mode_applied IN ('private', 'preview')")

197           LOAD_CONST              66 ('ck_notifications_privacy_mode')

195           LOAD_CONST              26 (('name',))
              CALL_KW                  2

199           LOAD_GLOBAL              4 (sa)
              LOAD_ATTR               28 (CheckConstraint)
              PUSH_NULL

200           LOAD_CONST              67 ("quiet_hours_applied IN ('none', 'silent', 'suppressed')")

201           LOAD_CONST              68 ('ck_notifications_quiet_hours')

199           LOAD_CONST              26 (('name',))
              CALL_KW                  2

149           CALL                    16
              POP_TOP

204           LOAD_GLOBAL              0 (op)
              LOAD_ATTR               26 (create_index)
              PUSH_NULL

205           LOAD_CONST              69 ('notifications_user_created_idx')

206           LOAD_CONST              49 ('notifications')

207           LOAD_CONST               6 ('owner_user_id')
              LOAD_GLOBAL              4 (sa)
              LOAD_ATTR               22 (text)
              PUSH_NULL
              LOAD_CONST              70 ('created_at DESC')
              CALL                     1
              BUILD_LIST               2

204           CALL                     3
              POP_TOP

213           LOAD_GLOBAL              0 (op)
              LOAD_ATTR                2 (create_table)
              PUSH_NULL

214           LOAD_CONST              71 ('notification_deliveries')

215           LOAD_GLOBAL              4 (sa)
              LOAD_ATTR                6 (Column)
              PUSH_NULL
              LOAD_CONST               2 ('id')
              LOAD_GLOBAL              9 (UUID + NULL)
              LOAD_CONST               3 (True)
              LOAD_CONST               4 (('as_uuid',))
              CALL_KW                  1
              LOAD_CONST               3 (True)
              LOAD_CONST               5 (('primary_key',))
              CALL_KW                  3

216           LOAD_GLOBAL              4 (sa)
              LOAD_ATTR                6 (Column)
              PUSH_NULL

217           LOAD_CONST              72 ('notification_id')

218           LOAD_GLOBAL              9 (UUID + NULL)
              LOAD_CONST               3 (True)
              LOAD_CONST               4 (('as_uuid',))
              CALL_KW                  1

219           LOAD_GLOBAL              4 (sa)
              LOAD_ATTR               10 (ForeignKey)
              PUSH_NULL
              LOAD_CONST              73 ('notifications.id')
              LOAD_CONST               8 ('CASCADE')
              LOAD_CONST               9 (('ondelete',))
              CALL_KW                  2

220           LOAD_CONST              10 (False)

216           LOAD_CONST              11 (('nullable',))
              CALL_KW                  4

222           LOAD_GLOBAL              4 (sa)
              LOAD_ATTR                6 (Column)
              PUSH_NULL

223           LOAD_CONST              74 ('device_id')

224           LOAD_GLOBAL              9 (UUID + NULL)
              LOAD_CONST               3 (True)
              LOAD_CONST               4 (('as_uuid',))
              CALL_KW                  1

225           LOAD_GLOBAL              4 (sa)
              LOAD_ATTR               10 (ForeignKey)
              PUSH_NULL
              LOAD_CONST              75 ('devices.id')
              LOAD_CONST              35 ('SET NULL')
              LOAD_CONST               9 (('ondelete',))
              CALL_KW                  2

226           LOAD_CONST               3 (True)

222           LOAD_CONST              11 (('nullable',))
              CALL_KW                  4

228           LOAD_GLOBAL              4 (sa)
              LOAD_ATTR                6 (Column)
              PUSH_NULL
              LOAD_CONST              76 ('provider')
              LOAD_GLOBAL              4 (sa)
              LOAD_ATTR               18 (Text)
              PUSH_NULL
              CALL                     0
              LOAD_CONST              10 (False)
              LOAD_CONST              11 (('nullable',))
              CALL_KW                  3

229           LOAD_GLOBAL              4 (sa)
              LOAD_ATTR                6 (Column)
              PUSH_NULL

230           LOAD_CONST              40 ('status')

231           LOAD_GLOBAL              4 (sa)
              LOAD_ATTR               18 (Text)
              PUSH_NULL
              CALL                     0

232           LOAD_CONST              10 (False)

233           LOAD_GLOBAL              4 (sa)
              LOAD_ATTR               22 (text)
              PUSH_NULL
              LOAD_CONST              77 ("'queued'")
              CALL                     1

229           LOAD_CONST              23 (('nullable', 'server_default'))
              CALL_KW                  4

235           LOAD_GLOBAL              4 (sa)
              LOAD_ATTR                6 (Column)
              PUSH_NULL

236           LOAD_CONST              78 ('attempt_count')

237           LOAD_GLOBAL              4 (sa)
              LOAD_ATTR               14 (Integer)
              PUSH_NULL
              CALL                     0

238           LOAD_CONST              10 (False)

239           LOAD_GLOBAL              4 (sa)
              LOAD_ATTR               22 (text)
              PUSH_NULL
              LOAD_CONST              79 ('0')
              CALL                     1

235           LOAD_CONST              23 (('nullable', 'server_default'))
              CALL_KW                  4

241           LOAD_GLOBAL              4 (sa)
              LOAD_ATTR                6 (Column)
              PUSH_NULL
              LOAD_CONST              80 ('next_attempt_at')
              LOAD_GLOBAL              4 (sa)
              LOAD_ATTR               20 (DateTime)
              PUSH_NULL
              LOAD_CONST               3 (True)
              LOAD_CONST              21 (('timezone',))
              CALL_KW                  1
              LOAD_CONST               3 (True)
              LOAD_CONST              11 (('nullable',))
              CALL_KW                  3

242           LOAD_GLOBAL              4 (sa)
              LOAD_ATTR                6 (Column)
              PUSH_NULL
              LOAD_CONST              81 ('last_attempt_at')
              LOAD_GLOBAL              4 (sa)
              LOAD_ATTR               20 (DateTime)
              PUSH_NULL
              LOAD_CONST               3 (True)
              LOAD_CONST              21 (('timezone',))
              CALL_KW                  1
              LOAD_CONST               3 (True)
              LOAD_CONST              11 (('nullable',))
              CALL_KW                  3

243           LOAD_GLOBAL              4 (sa)
              LOAD_ATTR                6 (Column)
              PUSH_NULL
              LOAD_CONST              82 ('provider_message_id')
              LOAD_GLOBAL              4 (sa)
              LOAD_ATTR               18 (Text)
              PUSH_NULL
              CALL                     0
              LOAD_CONST               3 (True)
              LOAD_CONST              11 (('nullable',))
              CALL_KW                  3

244           LOAD_GLOBAL              4 (sa)
              LOAD_ATTR                6 (Column)
              PUSH_NULL
              LOAD_CONST              83 ('last_error_code')
              LOAD_GLOBAL              4 (sa)
              LOAD_ATTR               18 (Text)
              PUSH_NULL
              CALL                     0
              LOAD_CONST               3 (True)
              LOAD_CONST              11 (('nullable',))
              CALL_KW                  3

245           LOAD_GLOBAL              4 (sa)
              LOAD_ATTR                6 (Column)
              PUSH_NULL
              LOAD_CONST              84 ('last_error_message_short')
              LOAD_GLOBAL              4 (sa)
              LOAD_ATTR               18 (Text)
              PUSH_NULL
              CALL                     0
              LOAD_CONST               3 (True)
              LOAD_CONST              11 (('nullable',))
              CALL_KW                  3

246           LOAD_GLOBAL              4 (sa)
              LOAD_ATTR                6 (Column)
              PUSH_NULL

247           LOAD_CONST              20 ('created_at')

248           LOAD_GLOBAL              4 (sa)
              LOAD_ATTR               20 (DateTime)
              PUSH_NULL
              LOAD_CONST               3 (True)
              LOAD_CONST              21 (('timezone',))
              CALL_KW                  1

249           LOAD_CONST              10 (False)

250           LOAD_GLOBAL              4 (sa)
              LOAD_ATTR               22 (text)
              PUSH_NULL
              LOAD_CONST              22 ('now()')
              CALL                     1

246           LOAD_CONST              23 (('nullable', 'server_default'))
              CALL_KW                  4

252           LOAD_GLOBAL              4 (sa)
              LOAD_ATTR               28 (CheckConstraint)
              PUSH_NULL

253           LOAD_CONST              85 ("provider IN ('apns', 'fcm')")

254           LOAD_CONST              86 ('ck_notification_deliveries_provider')

252           LOAD_CONST              26 (('name',))
              CALL_KW                  2

256           LOAD_GLOBAL              4 (sa)
              LOAD_ATTR               28 (CheckConstraint)
              PUSH_NULL

257           LOAD_CONST              87 ("status IN ('queued', 'sending', 'provider_accepted', 'provider_rejected', 'delivered_ack', 'expired', 'cancelled')")

259           LOAD_CONST              88 ('ck_notification_deliveries_status')

256           LOAD_CONST              26 (('name',))
              CALL_KW                  2

261           LOAD_GLOBAL              4 (sa)
              LOAD_ATTR               24 (UniqueConstraint)
              PUSH_NULL

262           LOAD_CONST              72 ('notification_id')

263           LOAD_CONST              74 ('device_id')

264           LOAD_CONST              89 ('uq_notification_deliveries_notif_device')

261           LOAD_CONST              26 (('name',))
              CALL_KW                  3

213           CALL                    16
              POP_TOP

271           LOAD_GLOBAL              0 (op)
              LOAD_ATTR                2 (create_table)
              PUSH_NULL

272           LOAD_CONST              90 ('handoff_offers')

273           LOAD_GLOBAL              4 (sa)
              LOAD_ATTR                6 (Column)
              PUSH_NULL
              LOAD_CONST               2 ('id')
              LOAD_GLOBAL              9 (UUID + NULL)
              LOAD_CONST               3 (True)
              LOAD_CONST               4 (('as_uuid',))
              CALL_KW                  1
              LOAD_CONST               3 (True)
              LOAD_CONST               5 (('primary_key',))
              CALL_KW                  3

274           LOAD_GLOBAL              4 (sa)
              LOAD_ATTR                6 (Column)
              PUSH_NULL

275           LOAD_CONST              33 ('call_id')

276           LOAD_GLOBAL              9 (UUID + NULL)
              LOAD_CONST               3 (True)
              LOAD_CONST               4 (('as_uuid',))
              CALL_KW                  1

277           LOAD_GLOBAL              4 (sa)
              LOAD_ATTR               10 (ForeignKey)
              PUSH_NULL
              LOAD_CONST              34 ('calls.id')
              LOAD_CONST               8 ('CASCADE')
              LOAD_CONST               9 (('ondelete',))
              CALL_KW                  2

278           LOAD_CONST              10 (False)

274           LOAD_CONST              11 (('nullable',))
              CALL_KW                  4

280           LOAD_GLOBAL              4 (sa)
              LOAD_ATTR                6 (Column)
              PUSH_NULL

281           LOAD_CONST               6 ('owner_user_id')

282           LOAD_GLOBAL              9 (UUID + NULL)
              LOAD_CONST               3 (True)
              LOAD_CONST               4 (('as_uuid',))
              CALL_KW                  1

283           LOAD_GLOBAL              4 (sa)
              LOAD_ATTR               10 (ForeignKey)
              PUSH_NULL
              LOAD_CONST               7 ('users.id')
              LOAD_CONST               8 ('CASCADE')
              LOAD_CONST               9 (('ondelete',))
              CALL_KW                  2

284           LOAD_CONST              10 (False)

280           LOAD_CONST              11 (('nullable',))
              CALL_KW                  4

286           LOAD_GLOBAL              4 (sa)
              LOAD_ATTR                6 (Column)
              PUSH_NULL

287           LOAD_CONST              40 ('status')

288           LOAD_GLOBAL              4 (sa)
              LOAD_ATTR               18 (Text)
              PUSH_NULL
              CALL                     0

289           LOAD_CONST              10 (False)

290           LOAD_GLOBAL              4 (sa)
              LOAD_ATTR               22 (text)
              PUSH_NULL
              LOAD_CONST              91 ("'offered'")
              CALL                     1

286           LOAD_CONST              23 (('nullable', 'server_default'))
              CALL_KW                  4

292           LOAD_GLOBAL              4 (sa)
              LOAD_ATTR                6 (Column)
              PUSH_NULL
              LOAD_CONST              92 ('offer_reason')
              LOAD_GLOBAL              4 (sa)
              LOAD_ATTR               18 (Text)
              PUSH_NULL
              CALL                     0
              LOAD_CONST               3 (True)
              LOAD_CONST              11 (('nullable',))
              CALL_KW                  3

293           LOAD_GLOBAL              4 (sa)
              LOAD_ATTR                6 (Column)
              PUSH_NULL
              LOAD_CONST              93 ('expires_at')
              LOAD_GLOBAL              4 (sa)
              LOAD_ATTR               20 (DateTime)
              PUSH_NULL
              LOAD_CONST               3 (True)
              LOAD_CONST              21 (('timezone',))
              CALL_KW                  1
              LOAD_CONST              10 (False)
              LOAD_CONST              11 (('nullable',))
              CALL_KW                  3

294           LOAD_GLOBAL              4 (sa)
              LOAD_ATTR                6 (Column)
              PUSH_NULL

295           LOAD_CONST              94 ('selected_device_id')

296           LOAD_GLOBAL              9 (UUID + NULL)
              LOAD_CONST               3 (True)
              LOAD_CONST               4 (('as_uuid',))
              CALL_KW                  1

297           LOAD_GLOBAL              4 (sa)
              LOAD_ATTR               10 (ForeignKey)
              PUSH_NULL
              LOAD_CONST              75 ('devices.id')
              LOAD_CONST              35 ('SET NULL')
              LOAD_CONST               9 (('ondelete',))
              CALL_KW                  2

298           LOAD_CONST               3 (True)

294           LOAD_CONST              11 (('nullable',))
              CALL_KW                  4

300           LOAD_GLOBAL              4 (sa)
              LOAD_ATTR                6 (Column)
              PUSH_NULL
              LOAD_CONST              95 ('accepted_at')
              LOAD_GLOBAL              4 (sa)
              LOAD_ATTR               20 (DateTime)
              PUSH_NULL
              LOAD_CONST               3 (True)
              LOAD_CONST              21 (('timezone',))
              CALL_KW                  1
              LOAD_CONST               3 (True)
              LOAD_CONST              11 (('nullable',))
              CALL_KW                  3

301           LOAD_GLOBAL              4 (sa)
              LOAD_ATTR                6 (Column)
              PUSH_NULL
              LOAD_CONST              96 ('declined_at')
              LOAD_GLOBAL              4 (sa)
              LOAD_ATTR               20 (DateTime)
              PUSH_NULL
              LOAD_CONST               3 (True)
              LOAD_CONST              21 (('timezone',))
              CALL_KW                  1
              LOAD_CONST               3 (True)
              LOAD_CONST              11 (('nullable',))
              CALL_KW                  3

302           LOAD_GLOBAL              4 (sa)
              LOAD_ATTR                6 (Column)
              PUSH_NULL
              LOAD_CONST              97 ('preview_payload')
              LOAD_GLOBAL             31 (JSONB + NULL)
              CALL                     0
              LOAD_CONST               3 (True)
              LOAD_CONST              11 (('nullable',))
              CALL_KW                  3

303           LOAD_GLOBAL              4 (sa)
              LOAD_ATTR                6 (Column)
              PUSH_NULL

304           LOAD_CONST              20 ('created_at')

305           LOAD_GLOBAL              4 (sa)
              LOAD_ATTR               20 (DateTime)
              PUSH_NULL
              LOAD_CONST               3 (True)
              LOAD_CONST              21 (('timezone',))
              CALL_KW                  1

306           LOAD_CONST              10 (False)

307           LOAD_GLOBAL              4 (sa)
              LOAD_ATTR               22 (text)
              PUSH_NULL
              LOAD_CONST              22 ('now()')
              CALL                     1

303           LOAD_CONST              23 (('nullable', 'server_default'))
              CALL_KW                  4

309           LOAD_GLOBAL              4 (sa)
              LOAD_ATTR               24 (UniqueConstraint)
              PUSH_NULL
              LOAD_CONST              33 ('call_id')
              LOAD_CONST              98 ('uq_handoff_offers_call')
              LOAD_CONST              26 (('name',))
              CALL_KW                  2

310           LOAD_GLOBAL              4 (sa)
              LOAD_ATTR               28 (CheckConstraint)
              PUSH_NULL

311           LOAD_CONST              99 ("status IN ('offered', 'accepted', 'declined', 'expired')")

312           LOAD_CONST             100 ('ck_handoff_offers_status')

310           LOAD_CONST              26 (('name',))
              CALL_KW                  2

314           LOAD_GLOBAL              4 (sa)
              LOAD_ATTR               28 (CheckConstraint)
              PUSH_NULL

315           LOAD_CONST             101 ("offer_reason IS NULL OR offer_reason IN ('vip', 'urgent', 'vip_and_urgent')")

316           LOAD_CONST             102 ('ck_handoff_offers_reason')

314           LOAD_CONST              26 (('name',))
              CALL_KW                  2

271           CALL                    15
              POP_TOP

319           LOAD_GLOBAL              0 (op)
              LOAD_ATTR               26 (create_index)
              PUSH_NULL

320           LOAD_CONST             103 ('handoff_offers_user_idx')
              LOAD_CONST              90 ('handoff_offers')
              LOAD_CONST               6 ('owner_user_id')
              BUILD_LIST               1

319           CALL                     3
              POP_TOP

322           LOAD_GLOBAL              0 (op)
              LOAD_ATTR               26 (create_index)
              PUSH_NULL

323           LOAD_CONST             104 ('handoff_offers_pending_idx')

324           LOAD_CONST              90 ('handoff_offers')

325           LOAD_CONST              40 ('status')
              LOAD_CONST              93 ('expires_at')
              BUILD_LIST               2

326           LOAD_GLOBAL              4 (sa)
              LOAD_ATTR               22 (text)
              PUSH_NULL
              LOAD_CONST             105 ("status = 'offered'")
              CALL                     1

322           LOAD_CONST              48 (('postgresql_where',))
              CALL_KW                  4
              POP_TOP

332           LOAD_GLOBAL              0 (op)
              LOAD_ATTR                2 (create_table)
              PUSH_NULL

333           LOAD_CONST             106 ('handoff_suppressions')

334           LOAD_GLOBAL              4 (sa)
              LOAD_ATTR                6 (Column)
              PUSH_NULL
              LOAD_CONST               2 ('id')
              LOAD_GLOBAL              9 (UUID + NULL)
              LOAD_CONST               3 (True)
              LOAD_CONST               4 (('as_uuid',))
              CALL_KW                  1
              LOAD_CONST               3 (True)
              LOAD_CONST               5 (('primary_key',))
              CALL_KW                  3

335           LOAD_GLOBAL              4 (sa)
              LOAD_ATTR                6 (Column)
              PUSH_NULL

336           LOAD_CONST               6 ('owner_user_id')

337           LOAD_GLOBAL              9 (UUID + NULL)
              LOAD_CONST               3 (True)
              LOAD_CONST               4 (('as_uuid',))
              CALL_KW                  1

338           LOAD_GLOBAL              4 (sa)
              LOAD_ATTR               10 (ForeignKey)
              PUSH_NULL
              LOAD_CONST               7 ('users.id')
              LOAD_CONST               8 ('CASCADE')
              LOAD_CONST               9 (('ondelete',))
              CALL_KW                  2

339           LOAD_CONST              10 (False)

335           LOAD_CONST              11 (('nullable',))
              CALL_KW                  4

341           LOAD_GLOBAL              4 (sa)
              LOAD_ATTR                6 (Column)
              PUSH_NULL
              LOAD_CONST             107 ('destination_phone_hash')
              LOAD_GLOBAL              4 (sa)
              LOAD_ATTR               16 (String)
              PUSH_NULL
              LOAD_CONST              16 (64)
              CALL                     1
              LOAD_CONST              10 (False)
              LOAD_CONST              11 (('nullable',))
              CALL_KW                  3

342           LOAD_GLOBAL              4 (sa)
              LOAD_ATTR                6 (Column)
              PUSH_NULL

343           LOAD_CONST             108 ('suppression_expires_at')

344           LOAD_GLOBAL              4 (sa)
              LOAD_ATTR               20 (DateTime)
              PUSH_NULL
              LOAD_CONST               3 (True)
              LOAD_CONST              21 (('timezone',))
              CALL_KW                  1

345           LOAD_CONST              10 (False)

342           LOAD_CONST              11 (('nullable',))
              CALL_KW                  3

347           LOAD_GLOBAL              4 (sa)
              LOAD_ATTR                6 (Column)
              PUSH_NULL
              LOAD_CONST              29 ('reason')
              LOAD_GLOBAL              4 (sa)
              LOAD_ATTR               18 (Text)
              PUSH_NULL
              CALL                     0
              LOAD_CONST               3 (True)
              LOAD_CONST              11 (('nullable',))
              CALL_KW                  3

348           LOAD_GLOBAL              4 (sa)
              LOAD_ATTR                6 (Column)
              PUSH_NULL

349           LOAD_CONST              20 ('created_at')

350           LOAD_GLOBAL              4 (sa)
              LOAD_ATTR               20 (DateTime)
              PUSH_NULL
              LOAD_CONST               3 (True)
              LOAD_CONST              21 (('timezone',))
              CALL_KW                  1

351           LOAD_CONST              10 (False)

352           LOAD_GLOBAL              4 (sa)
              LOAD_ATTR               22 (text)
              PUSH_NULL
              LOAD_CONST              22 ('now()')
              CALL                     1

348           LOAD_CONST              23 (('nullable', 'server_default'))
              CALL_KW                  4

332           CALL                     7
              POP_TOP

355           LOAD_GLOBAL              0 (op)
              LOAD_ATTR               26 (create_index)
              PUSH_NULL

356           LOAD_CONST             109 ('handoff_suppressions_user_dest_idx')

357           LOAD_CONST             106 ('handoff_suppressions')

358           LOAD_CONST               6 ('owner_user_id')
              LOAD_CONST             107 ('destination_phone_hash')
              BUILD_LIST               2

355           CALL                     3
              POP_TOP

364           LOAD_GLOBAL              0 (op)
              LOAD_ATTR               32 (add_column)
              PUSH_NULL

365           LOAD_CONST             110 ('calls')

366           LOAD_GLOBAL              4 (sa)
              LOAD_ATTR                6 (Column)
              PUSH_NULL

367           LOAD_CONST             111 ('handoff_eligible')

368           LOAD_GLOBAL              4 (sa)
              LOAD_ATTR               34 (Boolean)
              PUSH_NULL
              CALL                     0

369           LOAD_CONST              10 (False)

370           LOAD_GLOBAL              4 (sa)
              LOAD_ATTR               22 (text)
              PUSH_NULL
              LOAD_CONST             112 ('false')
              CALL                     1

366           LOAD_CONST              23 (('nullable', 'server_default'))
              CALL_KW                  4

364           CALL                     2
              POP_TOP

373           LOAD_GLOBAL              0 (op)
              LOAD_ATTR               32 (add_column)
              PUSH_NULL

374           LOAD_CONST             110 ('calls')

375           LOAD_GLOBAL              4 (sa)
              LOAD_ATTR                6 (Column)
              PUSH_NULL
              LOAD_CONST             113 ('handoff_status')
              LOAD_GLOBAL              4 (sa)
              LOAD_ATTR               18 (Text)
              PUSH_NULL
              CALL                     0
              LOAD_CONST               3 (True)
              LOAD_CONST              11 (('nullable',))
              CALL_KW                  3

373           CALL                     2
              POP_TOP

377           LOAD_GLOBAL              0 (op)
              LOAD_ATTR               32 (add_column)
              PUSH_NULL

378           LOAD_CONST             110 ('calls')

379           LOAD_GLOBAL              4 (sa)
              LOAD_ATTR                6 (Column)
              PUSH_NULL
              LOAD_CONST             114 ('handoff_offered_at')
              LOAD_GLOBAL              4 (sa)
              LOAD_ATTR               20 (DateTime)
              PUSH_NULL
              LOAD_CONST               3 (True)
              LOAD_CONST              21 (('timezone',))
              CALL_KW                  1
              LOAD_CONST               3 (True)
              LOAD_CONST              11 (('nullable',))
              CALL_KW                  3

377           CALL                     2
              POP_TOP

381           LOAD_GLOBAL              0 (op)
              LOAD_ATTR               32 (add_column)
              PUSH_NULL

382           LOAD_CONST             110 ('calls')

383           LOAD_GLOBAL              4 (sa)
              LOAD_ATTR                6 (Column)
              PUSH_NULL

384           LOAD_CONST             115 ('handoff_offer_expires_at')

385           LOAD_GLOBAL              4 (sa)
              LOAD_ATTR               20 (DateTime)
              PUSH_NULL
              LOAD_CONST               3 (True)
              LOAD_CONST              21 (('timezone',))
              CALL_KW                  1

386           LOAD_CONST               3 (True)

383           LOAD_CONST              11 (('nullable',))
              CALL_KW                  3

381           CALL                     2
              POP_TOP

389           LOAD_GLOBAL              0 (op)
              LOAD_ATTR               32 (add_column)
              PUSH_NULL

390           LOAD_CONST             110 ('calls')

391           LOAD_GLOBAL              4 (sa)
              LOAD_ATTR                6 (Column)
              PUSH_NULL
              LOAD_CONST             116 ('handoff_accepted_at')
              LOAD_GLOBAL              4 (sa)
              LOAD_ATTR               20 (DateTime)
              PUSH_NULL
              LOAD_CONST               3 (True)
              LOAD_CONST              21 (('timezone',))
              CALL_KW                  1
              LOAD_CONST               3 (True)
              LOAD_CONST              11 (('nullable',))
              CALL_KW                  3

389           CALL                     2
              POP_TOP

393           LOAD_GLOBAL              0 (op)
              LOAD_ATTR               32 (add_column)
              PUSH_NULL

394           LOAD_CONST             110 ('calls')

395           LOAD_GLOBAL              4 (sa)
              LOAD_ATTR                6 (Column)
              PUSH_NULL
              LOAD_CONST             117 ('handoff_selected_device_id')
              LOAD_GLOBAL              9 (UUID + NULL)
              LOAD_CONST               3 (True)
              LOAD_CONST               4 (('as_uuid',))
              CALL_KW                  1
              LOAD_CONST               3 (True)
              LOAD_CONST              11 (('nullable',))
              CALL_KW                  3

393           CALL                     2
              POP_TOP

397           LOAD_GLOBAL              0 (op)
              LOAD_ATTR               32 (add_column)
              PUSH_NULL

398           LOAD_CONST             110 ('calls')

399           LOAD_GLOBAL              4 (sa)
              LOAD_ATTR                6 (Column)
              PUSH_NULL

400           LOAD_CONST             118 ('handoff_attempt_count')

401           LOAD_GLOBAL              4 (sa)
              LOAD_ATTR               14 (Integer)
              PUSH_NULL
              CALL                     0

402           LOAD_CONST              10 (False)

403           LOAD_GLOBAL              4 (sa)
              LOAD_ATTR               22 (text)
              PUSH_NULL
              LOAD_CONST              79 ('0')
              CALL                     1

399           LOAD_CONST              23 (('nullable', 'server_default'))
              CALL_KW                  4

397           CALL                     2
              POP_TOP

406           LOAD_GLOBAL              0 (op)
              LOAD_ATTR               32 (add_column)
              PUSH_NULL

407           LOAD_CONST             110 ('calls')

408           LOAD_GLOBAL              4 (sa)
              LOAD_ATTR                6 (Column)
              PUSH_NULL
              LOAD_CONST             119 ('handoff_failure_reason')
              LOAD_GLOBAL              4 (sa)
              LOAD_ATTR               18 (Text)
              PUSH_NULL
              CALL                     0
              LOAD_CONST               3 (True)
              LOAD_CONST              11 (('nullable',))
              CALL_KW                  3

406           CALL                     2
              POP_TOP

410           LOAD_GLOBAL              0 (op)
              LOAD_ATTR               32 (add_column)
              PUSH_NULL

411           LOAD_CONST             110 ('calls')

412           LOAD_GLOBAL              4 (sa)
              LOAD_ATTR                6 (Column)
              PUSH_NULL

413           LOAD_CONST             120 ('handoff_loop_detected')

414           LOAD_GLOBAL              4 (sa)
              LOAD_ATTR               34 (Boolean)
              PUSH_NULL
              CALL                     0

415           LOAD_CONST              10 (False)

416           LOAD_GLOBAL              4 (sa)
              LOAD_ATTR               22 (text)
              PUSH_NULL
              LOAD_CONST             112 ('false')
              CALL                     1

412           LOAD_CONST              23 (('nullable', 'server_default'))
              CALL_KW                  4

410           CALL                     2
              POP_TOP

419           LOAD_GLOBAL              0 (op)
              LOAD_ATTR               36 (create_check_constraint)
              PUSH_NULL

420           LOAD_CONST             121 ('ck_calls_handoff_status')

421           LOAD_CONST             110 ('calls')

422           LOAD_CONST             122 ("handoff_status IS NULL OR handoff_status IN ('not_applicable', 'eligible_pending_minimum_data', 'offered', 'accepted', 'declined', 'expired', 'transfer_starting', 'transfer_connected', 'transfer_failed', 'transfer_cancelled')")

419           CALL                     3
              POP_TOP

427           LOAD_GLOBAL              0 (op)
              LOAD_ATTR               26 (create_index)
              PUSH_NULL

428           LOAD_CONST             123 ('calls_retention_idx')

429           LOAD_CONST             110 ('calls')

430           LOAD_CONST             124 ('retention_expires_at')
              BUILD_LIST               1

431           LOAD_GLOBAL              4 (sa)
              LOAD_ATTR               22 (text)
              PUSH_NULL
              LOAD_CONST             125 ('deleted_at IS NULL')
              CALL                     1

427           LOAD_CONST              48 (('postgresql_where',))
              CALL_KW                  4
              POP_TOP

437           LOAD_GLOBAL              0 (op)
              LOAD_ATTR               32 (add_column)
              PUSH_NULL

438           LOAD_CONST             126 ('user_settings')

439           LOAD_GLOBAL              4 (sa)
              LOAD_ATTR                6 (Column)
              PUSH_NULL

440           LOAD_CONST             127 ('handoff_enabled')

441           LOAD_GLOBAL              4 (sa)
              LOAD_ATTR               34 (Boolean)
              PUSH_NULL
              CALL                     0

442           LOAD_CONST              10 (False)

443           LOAD_GLOBAL              4 (sa)
              LOAD_ATTR               22 (text)
              PUSH_NULL
              LOAD_CONST             112 ('false')
              CALL                     1

439           LOAD_CONST              23 (('nullable', 'server_default'))
              CALL_KW                  4

437           CALL                     2
              POP_TOP

446           LOAD_GLOBAL              0 (op)
              LOAD_ATTR               32 (add_column)
              PUSH_NULL

447           LOAD_CONST             126 ('user_settings')

448           LOAD_GLOBAL              4 (sa)
              LOAD_ATTR                6 (Column)
              PUSH_NULL

449           LOAD_CONST             128 ('handoff_trigger')

450           LOAD_GLOBAL              4 (sa)
              LOAD_ATTR               16 (String)
              PUSH_NULL
              LOAD_CONST              41 (20)
              CALL                     1

451           LOAD_CONST              10 (False)

452           LOAD_GLOBAL              4 (sa)
              LOAD_ATTR               22 (text)
              PUSH_NULL
              LOAD_CONST             129 ("'vip_only'")
              CALL                     1

448           LOAD_CONST              23 (('nullable', 'server_default'))
              CALL_KW                  4

446           CALL                     2
              POP_TOP

455           LOAD_GLOBAL              0 (op)
              LOAD_ATTR               32 (add_column)
              PUSH_NULL

456           LOAD_CONST             126 ('user_settings')

457           LOAD_GLOBAL              4 (sa)
              LOAD_ATTR                6 (Column)
              PUSH_NULL

458           LOAD_CONST             130 ('handoff_offer_timeout_seconds')

459           LOAD_GLOBAL              4 (sa)
              LOAD_ATTR               14 (Integer)
              PUSH_NULL
              CALL                     0

460           LOAD_CONST              10 (False)

461           LOAD_GLOBAL              4 (sa)
              LOAD_ATTR               22 (text)
              PUSH_NULL
              LOAD_CONST             131 ('20')
              CALL                     1

457           LOAD_CONST              23 (('nullable', 'server_default'))
              CALL_KW                  4

455           CALL                     2
              POP_TOP

464           LOAD_GLOBAL              0 (op)
              LOAD_ATTR               32 (add_column)
              PUSH_NULL

465           LOAD_CONST             126 ('user_settings')

466           LOAD_GLOBAL              4 (sa)
              LOAD_ATTR                6 (Column)
              PUSH_NULL

467           LOAD_CONST             132 ('business_hours_enabled')

468           LOAD_GLOBAL              4 (sa)
              LOAD_ATTR               34 (Boolean)
              PUSH_NULL
              CALL                     0

469           LOAD_CONST              10 (False)

470           LOAD_GLOBAL              4 (sa)
              LOAD_ATTR               22 (text)
              PUSH_NULL
              LOAD_CONST             112 ('false')
              CALL                     1

466           LOAD_CONST              23 (('nullable', 'server_default'))
              CALL_KW                  4

464           CALL                     2
              POP_TOP

473           LOAD_GLOBAL              0 (op)
              LOAD_ATTR               32 (add_column)
              PUSH_NULL

474           LOAD_CONST             126 ('user_settings')

475           LOAD_GLOBAL              4 (sa)
              LOAD_ATTR                6 (Column)
              PUSH_NULL
              LOAD_CONST             133 ('business_hours_start')
              LOAD_GLOBAL              4 (sa)
              LOAD_ATTR               38 (Time)
              PUSH_NULL
              CALL                     0
              LOAD_CONST               3 (True)
              LOAD_CONST              11 (('nullable',))
              CALL_KW                  3

473           CALL                     2
              POP_TOP

477           LOAD_GLOBAL              0 (op)
              LOAD_ATTR               32 (add_column)
              PUSH_NULL

478           LOAD_CONST             126 ('user_settings')

479           LOAD_GLOBAL              4 (sa)
              LOAD_ATTR                6 (Column)
              PUSH_NULL
              LOAD_CONST             134 ('business_hours_end')
              LOAD_GLOBAL              4 (sa)
              LOAD_ATTR               38 (Time)
              PUSH_NULL
              CALL                     0
              LOAD_CONST               3 (True)
              LOAD_CONST              11 (('nullable',))
              CALL_KW                  3

477           CALL                     2
              POP_TOP

481           LOAD_GLOBAL              0 (op)
              LOAD_ATTR               32 (add_column)
              PUSH_NULL

482           LOAD_CONST             126 ('user_settings')

483           LOAD_GLOBAL              4 (sa)
              LOAD_ATTR                6 (Column)
              PUSH_NULL

484           LOAD_CONST             135 ('business_hours_days')

485           LOAD_GLOBAL             31 (JSONB + NULL)
              CALL                     0

486           LOAD_CONST              10 (False)

487           LOAD_GLOBAL              4 (sa)
              LOAD_ATTR               22 (text)
              PUSH_NULL
              LOAD_CONST             136 ("'[]'::jsonb")
              CALL                     1

483           LOAD_CONST              23 (('nullable', 'server_default'))
              CALL_KW                  4

481           CALL                     2
              POP_TOP

490           LOAD_GLOBAL              0 (op)
              LOAD_ATTR               32 (add_column)
              PUSH_NULL

491           LOAD_CONST             126 ('user_settings')

492           LOAD_GLOBAL              4 (sa)
              LOAD_ATTR                6 (Column)
              PUSH_NULL

493           LOAD_CONST             137 ('after_hours_behavior')

494           LOAD_GLOBAL              4 (sa)
              LOAD_ATTR               16 (String)
              PUSH_NULL
              LOAD_CONST             138 (40)
              CALL                     1

495           LOAD_CONST              10 (False)

496           LOAD_GLOBAL              4 (sa)
              LOAD_ATTR               22 (text)
              PUSH_NULL
              LOAD_CONST             139 ("'screen_normally'")
              CALL                     1

492           LOAD_CONST              23 (('nullable', 'server_default'))
              CALL_KW                  4

490           CALL                     2
              POP_TOP

499           LOAD_GLOBAL              0 (op)
              LOAD_ATTR               32 (add_column)
              PUSH_NULL

500           LOAD_CONST             126 ('user_settings')

501           LOAD_GLOBAL              4 (sa)
              LOAD_ATTR                6 (Column)
              PUSH_NULL

502           LOAD_CONST             140 ('temperament_preset')

503           LOAD_GLOBAL              4 (sa)
              LOAD_ATTR               16 (String)
              PUSH_NULL
              LOAD_CONST             138 (40)
              CALL                     1

504           LOAD_CONST              10 (False)

505           LOAD_GLOBAL              4 (sa)
              LOAD_ATTR               22 (text)
              PUSH_NULL
              LOAD_CONST             141 ("'professional_polite'")
              CALL                     1

501           LOAD_CONST              23 (('nullable', 'server_default'))
              CALL_KW                  4

499           CALL                     2
              POP_TOP

508           LOAD_GLOBAL              0 (op)
              LOAD_ATTR               32 (add_column)
              PUSH_NULL

509           LOAD_CONST             126 ('user_settings')

510           LOAD_GLOBAL              4 (sa)
              LOAD_ATTR                6 (Column)
              PUSH_NULL

511           LOAD_CONST             142 ('swearing_rule')

512           LOAD_GLOBAL              4 (sa)
              LOAD_ATTR               16 (String)
              PUSH_NULL
              LOAD_CONST              41 (20)
              CALL                     1

513           LOAD_CONST              10 (False)

514           LOAD_GLOBAL              4 (sa)
              LOAD_ATTR               22 (text)
              PUSH_NULL
              LOAD_CONST             143 ("'no_swearing'")
              CALL                     1

510           LOAD_CONST              23 (('nullable', 'server_default'))
              CALL_KW                  4

508           CALL                     2
              POP_TOP

517           LOAD_GLOBAL              0 (op)
              LOAD_ATTR               32 (add_column)
              PUSH_NULL

518           LOAD_CONST             126 ('user_settings')

519           LOAD_GLOBAL              4 (sa)
              LOAD_ATTR                6 (Column)
              PUSH_NULL

520           LOAD_CONST             144 ('language_primary')

521           LOAD_GLOBAL              4 (sa)
              LOAD_ATTR               16 (String)
              PUSH_NULL
              LOAD_CONST             145 (10)
              CALL                     1

522           LOAD_CONST              10 (False)

523           LOAD_GLOBAL              4 (sa)
              LOAD_ATTR               22 (text)
              PUSH_NULL
              LOAD_CONST             146 ("'en'")
              CALL                     1

519           LOAD_CONST              23 (('nullable', 'server_default'))
              CALL_KW                  4

517           CALL                     2
              POP_TOP

526           LOAD_GLOBAL              0 (op)
              LOAD_ATTR               32 (add_column)
              PUSH_NULL

527           LOAD_CONST             126 ('user_settings')

528           LOAD_GLOBAL              4 (sa)
              LOAD_ATTR                6 (Column)
              PUSH_NULL
              LOAD_CONST             147 ('language_secondary')
              LOAD_GLOBAL              4 (sa)
              LOAD_ATTR               16 (String)
              PUSH_NULL
              LOAD_CONST             145 (10)
              CALL                     1
              LOAD_CONST               3 (True)
              LOAD_CONST              11 (('nullable',))
              CALL_KW                  3

526           CALL                     2
              POP_TOP

530           LOAD_GLOBAL              0 (op)
              LOAD_ATTR               32 (add_column)
              PUSH_NULL

531           LOAD_CONST             126 ('user_settings')

532           LOAD_GLOBAL              4 (sa)
              LOAD_ATTR                6 (Column)
              PUSH_NULL

533           LOAD_CONST             148 ('vip_calls_mark_important')

534           LOAD_GLOBAL              4 (sa)
              LOAD_ATTR               34 (Boolean)
              PUSH_NULL
              CALL                     0

535           LOAD_CONST              10 (False)

536           LOAD_GLOBAL              4 (sa)
              LOAD_ATTR               22 (text)
              PUSH_NULL
              LOAD_CONST             149 ('true')
              CALL                     1

532           LOAD_CONST              23 (('nullable', 'server_default'))
              CALL_KW                  4

530           CALL                     2
              POP_TOP

539           LOAD_GLOBAL              0 (op)
              LOAD_ATTR               32 (add_column)
              PUSH_NULL

540           LOAD_CONST             126 ('user_settings')

541           LOAD_GLOBAL              4 (sa)
              LOAD_ATTR                6 (Column)
              PUSH_NULL

542           LOAD_CONST             150 ('vip_notification_intensity')

543           LOAD_GLOBAL              4 (sa)
              LOAD_ATTR               16 (String)
              PUSH_NULL
              LOAD_CONST             145 (10)
              CALL                     1

544           LOAD_CONST              10 (False)

545           LOAD_GLOBAL              4 (sa)
              LOAD_ATTR               22 (text)
              PUSH_NULL
              LOAD_CONST              52 ("'normal'")
              CALL                     1

541           LOAD_CONST              23 (('nullable', 'server_default'))
              CALL_KW                  4

539           CALL                     2
              POP_TOP

548           LOAD_GLOBAL              0 (op)
              LOAD_ATTR               32 (add_column)
              PUSH_NULL

549           LOAD_CONST             126 ('user_settings')

550           LOAD_GLOBAL              4 (sa)
              LOAD_ATTR                6 (Column)
              PUSH_NULL

551           LOAD_CONST             151 ('blocked_caller_behavior')

552           LOAD_GLOBAL              4 (sa)
              LOAD_ATTR               16 (String)
              PUSH_NULL
              LOAD_CONST             152 (30)
              CALL                     1

553           LOAD_CONST              10 (False)

554           LOAD_GLOBAL              4 (sa)
              LOAD_ATTR               22 (text)
              PUSH_NULL
              LOAD_CONST             153 ("'end_immediately'")
              CALL                     1

550           LOAD_CONST              23 (('nullable', 'server_default'))
              CALL_KW                  4

548           CALL                     2
              POP_TOP

557           LOAD_GLOBAL              0 (op)
              LOAD_ATTR               32 (add_column)
              PUSH_NULL

558           LOAD_CONST             126 ('user_settings')

559           LOAD_GLOBAL              4 (sa)
              LOAD_ATTR                6 (Column)
              PUSH_NULL

560           LOAD_CONST             154 ('log_blocked_attempts')

561           LOAD_GLOBAL              4 (sa)
              LOAD_ATTR               34 (Boolean)
              PUSH_NULL
              CALL                     0

562           LOAD_CONST              10 (False)

563           LOAD_GLOBAL              4 (sa)
              LOAD_ATTR               22 (text)
              PUSH_NULL
              LOAD_CONST             112 ('false')
              CALL                     1

559           LOAD_CONST              23 (('nullable', 'server_default'))
              CALL_KW                  4

557           CALL                     2
              POP_TOP

566           LOAD_GLOBAL              0 (op)
              LOAD_ATTR               32 (add_column)
              PUSH_NULL

567           LOAD_CONST             126 ('user_settings')

568           LOAD_GLOBAL              4 (sa)
              LOAD_ATTR                6 (Column)
              PUSH_NULL

569           LOAD_CONST             155 ('notify_on_blocked')

570           LOAD_GLOBAL              4 (sa)
              LOAD_ATTR               34 (Boolean)
              PUSH_NULL
              CALL                     0

571           LOAD_CONST              10 (False)

572           LOAD_GLOBAL              4 (sa)
              LOAD_ATTR               22 (text)
              PUSH_NULL
              LOAD_CONST             112 ('false')
              CALL                     1

568           LOAD_CONST              23 (('nullable', 'server_default'))
              CALL_KW                  4

566           CALL                     2
              POP_TOP

575           LOAD_GLOBAL              0 (op)
              LOAD_ATTR               32 (add_column)
              PUSH_NULL

576           LOAD_CONST             126 ('user_settings')

577           LOAD_GLOBAL              4 (sa)
              LOAD_ATTR                6 (Column)
              PUSH_NULL

578           LOAD_CONST             156 ('spam_labeling_enabled')

579           LOAD_GLOBAL              4 (sa)
              LOAD_ATTR               34 (Boolean)
              PUSH_NULL
              CALL                     0

580           LOAD_CONST              10 (False)

581           LOAD_GLOBAL              4 (sa)
              LOAD_ATTR               22 (text)
              PUSH_NULL
              LOAD_CONST             149 ('true')
              CALL                     1

577           LOAD_CONST              23 (('nullable', 'server_default'))
              CALL_KW                  4

575           CALL                     2
              POP_TOP

584           LOAD_GLOBAL              0 (op)
              LOAD_ATTR               32 (add_column)
              PUSH_NULL

585           LOAD_CONST             126 ('user_settings')

586           LOAD_GLOBAL              4 (sa)
              LOAD_ATTR                6 (Column)
              PUSH_NULL

587           LOAD_CONST             157 ('block_suggestions_enabled')

588           LOAD_GLOBAL              4 (sa)
              LOAD_ATTR               34 (Boolean)
              PUSH_NULL
              CALL                     0

589           LOAD_CONST              10 (False)

590           LOAD_GLOBAL              4 (sa)
              LOAD_ATTR               22 (text)
              PUSH_NULL
              LOAD_CONST             149 ('true')
              CALL                     1

586           LOAD_CONST              23 (('nullable', 'server_default'))
              CALL_KW                  4

584           CALL                     2
              POP_TOP

593           LOAD_GLOBAL              0 (op)
              LOAD_ATTR               32 (add_column)
              PUSH_NULL

594           LOAD_CONST             126 ('user_settings')

595           LOAD_GLOBAL              4 (sa)
              LOAD_ATTR                6 (Column)
              PUSH_NULL

596           LOAD_CONST             158 ('repeat_caller_threshold')

597           LOAD_GLOBAL              4 (sa)
              LOAD_ATTR               14 (Integer)
              PUSH_NULL
              CALL                     0

598           LOAD_CONST              10 (False)

599           LOAD_GLOBAL              4 (sa)
              LOAD_ATTR               22 (text)
              PUSH_NULL
              LOAD_CONST             159 ('3')
              CALL                     1

595           LOAD_CONST              23 (('nullable', 'server_default'))
              CALL_KW                  4

593           CALL                     2
              POP_TOP

602           LOAD_GLOBAL              0 (op)
              LOAD_ATTR               32 (add_column)
              PUSH_NULL

603           LOAD_CONST             126 ('user_settings')

604           LOAD_GLOBAL              4 (sa)
              LOAD_ATTR                6 (Column)
              PUSH_NULL

605           LOAD_CONST             160 ('text_approval_mode')

606           LOAD_GLOBAL              4 (sa)
              LOAD_ATTR               16 (String)
              PUSH_NULL
              LOAD_CONST              41 (20)
              CALL                     1

607           LOAD_CONST              10 (False)

608           LOAD_GLOBAL              4 (sa)
              LOAD_ATTR               22 (text)
              PUSH_NULL
              LOAD_CONST             161 ("'always_approve'")
              CALL                     1

604           LOAD_CONST              23 (('nullable', 'server_default'))
              CALL_KW                  4

602           CALL                     2
              POP_TOP

611           LOAD_GLOBAL              0 (op)
              LOAD_ATTR               32 (add_column)
              PUSH_NULL

612           LOAD_CONST             126 ('user_settings')

613           LOAD_GLOBAL              4 (sa)
              LOAD_ATTR                6 (Column)
              PUSH_NULL

614           LOAD_CONST             162 ('assistant_name')

615           LOAD_GLOBAL              4 (sa)
              LOAD_ATTR               16 (String)
              PUSH_NULL
              LOAD_CONST             163 (60)
              CALL                     1

616           LOAD_CONST              10 (False)

617           LOAD_GLOBAL              4 (sa)
              LOAD_ATTR               22 (text)
              PUSH_NULL
              LOAD_CONST             164 ("'Alex'")
              CALL                     1

613           LOAD_CONST              23 (('nullable', 'server_default'))
              CALL_KW                  4

611           CALL                     2
              POP_TOP

620           LOAD_GLOBAL              0 (op)
              LOAD_ATTR               32 (add_column)
              PUSH_NULL

621           LOAD_CONST             126 ('user_settings')

622           LOAD_GLOBAL              4 (sa)
              LOAD_ATTR                6 (Column)
              PUSH_NULL

623           LOAD_CONST             165 ('greeting_template')

624           LOAD_GLOBAL              4 (sa)
              LOAD_ATTR               16 (String)
              PUSH_NULL
              LOAD_CONST             138 (40)
              CALL                     1

625           LOAD_CONST              10 (False)

626           LOAD_GLOBAL              4 (sa)
              LOAD_ATTR               22 (text)
              PUSH_NULL
              LOAD_CONST             166 ("'standard'")
              CALL                     1

622           LOAD_CONST              23 (('nullable', 'server_default'))
              CALL_KW                  4

620           CALL                     2
              POP_TOP

629           LOAD_GLOBAL              0 (op)
              LOAD_ATTR               32 (add_column)
              PUSH_NULL

630           LOAD_CONST             126 ('user_settings')

631           LOAD_GLOBAL              4 (sa)
              LOAD_ATTR                6 (Column)
              PUSH_NULL

632           LOAD_CONST             167 ('transcript_disclosure_mode')

633           LOAD_GLOBAL              4 (sa)
              LOAD_ATTR               16 (String)
              PUSH_NULL
              LOAD_CONST              41 (20)
              CALL                     1

634           LOAD_CONST              10 (False)

635           LOAD_GLOBAL              4 (sa)
              LOAD_ATTR               22 (text)
              PUSH_NULL
              LOAD_CONST             168 ("'ai_says_it'")
              CALL                     1

631           LOAD_CONST              23 (('nullable', 'server_default'))
              CALL_KW                  4

629           CALL                     2
              POP_TOP

638           LOAD_GLOBAL              0 (op)
              LOAD_ATTR               32 (add_column)
              PUSH_NULL

639           LOAD_CONST             126 ('user_settings')

640           LOAD_GLOBAL              4 (sa)
              LOAD_ATTR                6 (Column)
              PUSH_NULL

641           LOAD_CONST             169 ('recording_announcement_required')

642           LOAD_GLOBAL              4 (sa)
              LOAD_ATTR               34 (Boolean)
              PUSH_NULL
              CALL                     0

643           LOAD_CONST              10 (False)

644           LOAD_GLOBAL              4 (sa)
              LOAD_ATTR               22 (text)
              PUSH_NULL
              LOAD_CONST             149 ('true')
              CALL                     1

640           LOAD_CONST              23 (('nullable', 'server_default'))
              CALL_KW                  4

638           CALL                     2
              POP_TOP

647           LOAD_GLOBAL              0 (op)
              LOAD_ATTR               32 (add_column)
              PUSH_NULL

648           LOAD_CONST             126 ('user_settings')

649           LOAD_GLOBAL              4 (sa)
              LOAD_ATTR                6 (Column)
              PUSH_NULL

650           LOAD_CONST             170 ('important_rule')

651           LOAD_GLOBAL              4 (sa)
              LOAD_ATTR               16 (String)
              PUSH_NULL
              LOAD_CONST              41 (20)
              CALL                     1

652           LOAD_CONST              10 (False)

653           LOAD_GLOBAL              4 (sa)
              LOAD_ATTR               22 (text)
              PUSH_NULL
              LOAD_CONST             171 ("'vip_and_urgent'")
              CALL                     1

649           LOAD_CONST              23 (('nullable', 'server_default'))
              CALL_KW                  4

647           CALL                     2
              POP_TOP

656           LOAD_GLOBAL              0 (op)
              LOAD_ATTR               32 (add_column)
              PUSH_NULL

657           LOAD_CONST             126 ('user_settings')

658           LOAD_GLOBAL              4 (sa)
              LOAD_ATTR                6 (Column)
              PUSH_NULL

659           LOAD_CONST             172 ('biometric_policy')

660           LOAD_GLOBAL              4 (sa)
              LOAD_ATTR               16 (String)
              PUSH_NULL
              LOAD_CONST             152 (30)
              CALL                     1

661           LOAD_CONST              10 (False)

662           LOAD_GLOBAL              4 (sa)
              LOAD_ATTR               22 (text)
              PUSH_NULL
              LOAD_CONST             173 ("'gate_call_details'")
              CALL                     1

658           LOAD_CONST              23 (('nullable', 'server_default'))
              CALL_KW                  4

656           CALL                     2
              POP_TOP

667           LOAD_GLOBAL              0 (op)
              LOAD_ATTR               36 (create_check_constraint)
              PUSH_NULL

668           LOAD_CONST             174 ('ck_user_settings_handoff_trigger')

669           LOAD_CONST             126 ('user_settings')

670           LOAD_CONST             175 ("handoff_trigger IN ('vip_only', 'always', 'never')")

667           CALL                     3
              POP_TOP

672           LOAD_GLOBAL              0 (op)
              LOAD_ATTR               36 (create_check_constraint)
              PUSH_NULL

673           LOAD_CONST             176 ('ck_user_settings_handoff_timeout')

674           LOAD_CONST             126 ('user_settings')

675           LOAD_CONST             177 ('handoff_offer_timeout_seconds BETWEEN 10 AND 60')

672           CALL                     3
              POP_TOP

677           LOAD_GLOBAL              0 (op)
              LOAD_ATTR               36 (create_check_constraint)
              PUSH_NULL

678           LOAD_CONST             178 ('ck_user_settings_after_hours')

679           LOAD_CONST             126 ('user_settings')

680           LOAD_CONST             179 ("after_hours_behavior IN ('screen_normally', 'voicemail_only', 'reject')")

677           CALL                     3
              POP_TOP

682           LOAD_GLOBAL              0 (op)
              LOAD_ATTR               36 (create_check_constraint)
              PUSH_NULL

683           LOAD_CONST             180 ('ck_user_settings_temperament')

684           LOAD_CONST             126 ('user_settings')

685           LOAD_CONST             181 ("temperament_preset IN ('professional_polite', 'casual_friendly', 'formal', 'custom')")

682           CALL                     3
              POP_TOP

687           LOAD_GLOBAL              0 (op)
              LOAD_ATTR               36 (create_check_constraint)
              PUSH_NULL

688           LOAD_CONST             182 ('ck_user_settings_swearing')

689           LOAD_CONST             126 ('user_settings')

690           LOAD_CONST             183 ("swearing_rule IN ('no_swearing', 'mirror_caller', 'allow')")

687           CALL                     3
              POP_TOP

692           LOAD_GLOBAL              0 (op)
              LOAD_ATTR               36 (create_check_constraint)
              PUSH_NULL

693           LOAD_CONST             184 ('ck_user_settings_vip_notif')

694           LOAD_CONST             126 ('user_settings')

695           LOAD_CONST             185 ("vip_notification_intensity IN ('normal', 'high', 'urgent')")

692           CALL                     3
              POP_TOP

697           LOAD_GLOBAL              0 (op)
              LOAD_ATTR               36 (create_check_constraint)
              PUSH_NULL

698           LOAD_CONST             186 ('ck_user_settings_blocked_behavior')

699           LOAD_CONST             126 ('user_settings')

700           LOAD_CONST             187 ("blocked_caller_behavior IN ('end_immediately', 'play_message', 'silent_drop')")

697           CALL                     3
              POP_TOP

702           LOAD_GLOBAL              0 (op)
              LOAD_ATTR               36 (create_check_constraint)
              PUSH_NULL

703           LOAD_CONST             188 ('ck_user_settings_repeat_threshold')

704           LOAD_CONST             126 ('user_settings')

705           LOAD_CONST             189 ('repeat_caller_threshold BETWEEN 1 AND 10')

702           CALL                     3
              POP_TOP

707           LOAD_GLOBAL              0 (op)
              LOAD_ATTR               36 (create_check_constraint)
              PUSH_NULL

708           LOAD_CONST             190 ('ck_user_settings_text_approval')

709           LOAD_CONST             126 ('user_settings')

710           LOAD_CONST             191 ("text_approval_mode IN ('always_approve', 'auto_send', 'never')")

707           CALL                     3
              POP_TOP

712           LOAD_GLOBAL              0 (op)
              LOAD_ATTR               36 (create_check_constraint)
              PUSH_NULL

713           LOAD_CONST             192 ('ck_user_settings_greeting')

714           LOAD_CONST             126 ('user_settings')

715           LOAD_CONST             193 ("greeting_template IN ('standard', 'brief', 'formal', 'custom')")

712           CALL                     3
              POP_TOP

717           LOAD_GLOBAL              0 (op)
              LOAD_ATTR               36 (create_check_constraint)
              PUSH_NULL

718           LOAD_CONST             194 ('ck_user_settings_disclosure')

719           LOAD_CONST             126 ('user_settings')

720           LOAD_CONST             195 ("transcript_disclosure_mode IN ('ai_says_it', 'silent', 'beep')")

717           CALL                     3
              POP_TOP

722           LOAD_GLOBAL              0 (op)
              LOAD_ATTR               36 (create_check_constraint)
              PUSH_NULL

723           LOAD_CONST             196 ('ck_user_settings_important_rule')

724           LOAD_CONST             126 ('user_settings')

725           LOAD_CONST             197 ("important_rule IN ('vip_and_urgent', 'vip_only', 'urgent_only', 'all')")

722           CALL                     3
              POP_TOP

727           LOAD_GLOBAL              0 (op)
              LOAD_ATTR               36 (create_check_constraint)
              PUSH_NULL

728           LOAD_CONST             198 ('ck_user_settings_biometric_policy')

729           LOAD_CONST             126 ('user_settings')

730           LOAD_CONST             199 ("biometric_policy IN ('gate_call_details', 'gate_all', 'off')")

727           CALL                     3
              POP_TOP
              RETURN_CONST             0 (None)

# --- Nested code object: downgrade ---
    # co_names: ('op', 'drop_constraint', 'drop_column', 'drop_index', 'drop_table')
    # co_varnames: ()
    # co_consts (strings): ['ck_user_settings_biometric_policy', 'user_settings', 'check', 'ck_user_settings_important_rule', 'ck_user_settings_disclosure', 'ck_user_settings_greeting', 'ck_user_settings_text_approval', 'ck_user_settings_repeat_threshold', 'ck_user_settings_blocked_behavior', 'ck_user_settings_vip_notif', 'ck_user_settings_swearing', 'ck_user_settings_temperament', 'ck_user_settings_after_hours', 'ck_user_settings_handoff_timeout', 'ck_user_settings_handoff_trigger', 'biometric_policy', 'important_rule', 'recording_announcement_required', 'transcript_disclosure_mode', 'greeting_template', 'assistant_name', 'text_approval_mode', 'repeat_caller_threshold', 'block_suggestions_enabled', 'spam_labeling_enabled', 'notify_on_blocked', 'log_blocked_attempts', 'blocked_caller_behavior', 'vip_notification_intensity', 'vip_calls_mark_important', 'language_secondary', 'language_primary', 'swearing_rule', 'temperament_preset', 'after_hours_behavior', 'business_hours_days', 'business_hours_end', 'business_hours_start', 'business_hours_enabled', 'handoff_offer_timeout_seconds', 'handoff_trigger', 'handoff_enabled', 'calls_retention_idx', 'calls', 'ck_calls_handoff_status', 'handoff_loop_detected', 'handoff_failure_reason', 'handoff_attempt_count', 'handoff_selected_device_id', 'handoff_accepted_at', 'handoff_offer_expires_at', 'handoff_offered_at', 'handoff_status', 'handoff_eligible', 'handoff_suppressions', 'handoff_offers', 'notification_deliveries', 'notifications', 'reminders', 'block_entries', 'vip_entries']
734           RESUME                   0

736           LOAD_GLOBAL              0 (op)
              LOAD_ATTR                2 (drop_constraint)
              PUSH_NULL
              LOAD_CONST               1 ('ck_user_settings_biometric_policy')
              LOAD_CONST               2 ('user_settings')
              LOAD_CONST               3 ('check')
              LOAD_CONST               4 (('type_',))
              CALL_KW                  3
              POP_TOP

737           LOAD_GLOBAL              0 (op)
              LOAD_ATTR                2 (drop_constraint)
              PUSH_NULL
              LOAD_CONST               5 ('ck_user_settings_important_rule')
              LOAD_CONST               2 ('user_settings')
              LOAD_CONST               3 ('check')
              LOAD_CONST               4 (('type_',))
              CALL_KW                  3
              POP_TOP

738           LOAD_GLOBAL              0 (op)
              LOAD_ATTR                2 (drop_constraint)
              PUSH_NULL
              LOAD_CONST               6 ('ck_user_settings_disclosure')
              LOAD_CONST               2 ('user_settings')
              LOAD_CONST               3 ('check')
              LOAD_CONST               4 (('type_',))
              CALL_KW                  3
              POP_TOP

739           LOAD_GLOBAL              0 (op)
              LOAD_ATTR                2 (drop_constraint)
              PUSH_NULL
              LOAD_CONST               7 ('ck_user_settings_greeting')
              LOAD_CONST               2 ('user_settings')
              LOAD_CONST               3 ('check')
              LOAD_CONST               4 (('type_',))
              CALL_KW                  3
              POP_TOP

740           LOAD_GLOBAL              0 (op)
              LOAD_ATTR                2 (drop_constraint)
              PUSH_NULL
              LOAD_CONST               8 ('ck_user_settings_text_approval')
              LOAD_CONST               2 ('user_settings')
              LOAD_CONST               3 ('check')
              LOAD_CONST               4 (('type_',))
              CALL_KW                  3
              POP_TOP

741           LOAD_GLOBAL              0 (op)
              LOAD_ATTR                2 (drop_constraint)
              PUSH_NULL
              LOAD_CONST               9 ('ck_user_settings_repeat_threshold')
              LOAD_CONST               2 ('user_settings')
              LOAD_CONST               3 ('check')
              LOAD_CONST               4 (('type_',))
              CALL_KW                  3
              POP_TOP

742           LOAD_GLOBAL              0 (op)
              LOAD_ATTR                2 (drop_constraint)
              PUSH_NULL
              LOAD_CONST              10 ('ck_user_settings_blocked_behavior')
              LOAD_CONST               2 ('user_settings')
              LOAD_CONST               3 ('check')
              LOAD_CONST               4 (('type_',))
              CALL_KW                  3
              POP_TOP

743           LOAD_GLOBAL              0 (op)
              LOAD_ATTR                2 (drop_constraint)
              PUSH_NULL
              LOAD_CONST              11 ('ck_user_settings_vip_notif')
              LOAD_CONST               2 ('user_settings')
              LOAD_CONST               3 ('check')
              LOAD_CONST               4 (('type_',))
              CALL_KW                  3
              POP_TOP

744           LOAD_GLOBAL              0 (op)
              LOAD_ATTR                2 (drop_constraint)
              PUSH_NULL
              LOAD_CONST              12 ('ck_user_settings_swearing')
              LOAD_CONST               2 ('user_settings')
              LOAD_CONST               3 ('check')
              LOAD_CONST               4 (('type_',))
              CALL_KW                  3
              POP_TOP

745           LOAD_GLOBAL              0 (op)
              LOAD_ATTR                2 (drop_constraint)
              PUSH_NULL
              LOAD_CONST              13 ('ck_user_settings_temperament')
              LOAD_CONST               2 ('user_settings')
              LOAD_CONST               3 ('check')
              LOAD_CONST               4 (('type_',))
              CALL_KW                  3
              POP_TOP

746           LOAD_GLOBAL              0 (op)
              LOAD_ATTR                2 (drop_constraint)
              PUSH_NULL
              LOAD_CONST              14 ('ck_user_settings_after_hours')
              LOAD_CONST               2 ('user_settings')
              LOAD_CONST               3 ('check')
              LOAD_CONST               4 (('type_',))
              CALL_KW                  3
              POP_TOP

747           LOAD_GLOBAL              0 (op)
              LOAD_ATTR                2 (drop_constraint)
              PUSH_NULL
              LOAD_CONST              15 ('ck_user_settings_handoff_timeout')
              LOAD_CONST               2 ('user_settings')
              LOAD_CONST               3 ('check')
              LOAD_CONST               4 (('type_',))
              CALL_KW                  3
              POP_TOP

748           LOAD_GLOBAL              0 (op)
              LOAD_ATTR                2 (drop_constraint)
              PUSH_NULL
              LOAD_CONST              16 ('ck_user_settings_handoff_trigger')
              LOAD_CONST               2 ('user_settings')
              LOAD_CONST               3 ('check')
              LOAD_CONST               4 (('type_',))
              CALL_KW                  3
              POP_TOP

751           LOAD_GLOBAL              0 (op)
              LOAD_ATTR                4 (drop_column)
              PUSH_NULL
              LOAD_CONST               2 ('user_settings')
              LOAD_CONST              17 ('biometric_policy')
              CALL                     2
              POP_TOP

752           LOAD_GLOBAL              0 (op)
              LOAD_ATTR                4 (drop_column)
              PUSH_NULL
              LOAD_CONST               2 ('user_settings')
              LOAD_CONST              18 ('important_rule')
              CALL                     2
              POP_TOP

753           LOAD_GLOBAL              0 (op)
              LOAD_ATTR                4 (drop_column)
              PUSH_NULL
              LOAD_CONST               2 ('user_settings')
              LOAD_CONST              19 ('recording_announcement_required')
              CALL                     2
              POP_TOP

754           LOAD_GLOBAL              0 (op)
              LOAD_ATTR                4 (drop_column)
              PUSH_NULL
              LOAD_CONST               2 ('user_settings')
              LOAD_CONST              20 ('transcript_disclosure_mode')
              CALL                     2
              POP_TOP

755           LOAD_GLOBAL              0 (op)
              LOAD_ATTR                4 (drop_column)
              PUSH_NULL
              LOAD_CONST               2 ('user_settings')
              LOAD_CONST              21 ('greeting_template')
              CALL                     2
              POP_TOP

756           LOAD_GLOBAL              0 (op)
              LOAD_ATTR                4 (drop_column)
              PUSH_NULL
              LOAD_CONST               2 ('user_settings')
              LOAD_CONST              22 ('assistant_name')
              CALL                     2
              POP_TOP

757           LOAD_GLOBAL              0 (op)
              LOAD_ATTR                4 (drop_column)
              PUSH_NULL
              LOAD_CONST               2 ('user_settings')
              LOAD_CONST              23 ('text_approval_mode')
              CALL                     2
              POP_TOP

758           LOAD_GLOBAL              0 (op)
              LOAD_ATTR                4 (drop_column)
              PUSH_NULL
              LOAD_CONST               2 ('user_settings')
              LOAD_CONST              24 ('repeat_caller_threshold')
              CALL                     2
              POP_TOP

759           LOAD_GLOBAL              0 (op)
              LOAD_ATTR                4 (drop_column)
              PUSH_NULL
              LOAD_CONST               2 ('user_settings')
              LOAD_CONST              25 ('block_suggestions_enabled')
              CALL                     2
              POP_TOP

760           LOAD_GLOBAL              0 (op)
              LOAD_ATTR                4 (drop_column)
              PUSH_NULL
              LOAD_CONST               2 ('user_settings')
              LOAD_CONST              26 ('spam_labeling_enabled')
              CALL                     2
              POP_TOP

761           LOAD_GLOBAL              0 (op)
              LOAD_ATTR                4 (drop_column)
              PUSH_NULL
              LOAD_CONST               2 ('user_settings')
              LOAD_CONST              27 ('notify_on_blocked')
              CALL                     2
              POP_TOP

762           LOAD_GLOBAL              0 (op)
              LOAD_ATTR                4 (drop_column)
              PUSH_NULL
              LOAD_CONST               2 ('user_settings')
              LOAD_CONST              28 ('log_blocked_attempts')
              CALL                     2
              POP_TOP

763           LOAD_GLOBAL              0 (op)
              LOAD_ATTR                4 (drop_column)
              PUSH_NULL
              LOAD_CONST               2 ('user_settings')
              LOAD_CONST              29 ('blocked_caller_behavior')
              CALL                     2
              POP_TOP

764           LOAD_GLOBAL              0 (op)
              LOAD_ATTR                4 (drop_column)
              PUSH_NULL
              LOAD_CONST               2 ('user_settings')
              LOAD_CONST              30 ('vip_notification_intensity')
              CALL                     2
              POP_TOP

765           LOAD_GLOBAL              0 (op)
              LOAD_ATTR                4 (drop_column)
              PUSH_NULL
              LOAD_CONST               2 ('user_settings')
              LOAD_CONST              31 ('vip_calls_mark_important')
              CALL                     2
              POP_TOP

766           LOAD_GLOBAL              0 (op)
              LOAD_ATTR                4 (drop_column)
              PUSH_NULL
              LOAD_CONST               2 ('user_settings')
              LOAD_CONST              32 ('language_secondary')
              CALL                     2
              POP_TOP

767           LOAD_GLOBAL              0 (op)
              LOAD_ATTR                4 (drop_column)
              PUSH_NULL
              LOAD_CONST               2 ('user_settings')
              LOAD_CONST              33 ('language_primary')
              CALL                     2
              POP_TOP

768           LOAD_GLOBAL              0 (op)
              LOAD_ATTR                4 (drop_column)
              PUSH_NULL
              LOAD_CONST               2 ('user_settings')
              LOAD_CONST              34 ('swearing_rule')
              CALL                     2
              POP_TOP

769           LOAD_GLOBAL              0 (op)
              LOAD_ATTR                4 (drop_column)
              PUSH_NULL
              LOAD_CONST               2 ('user_settings')
              LOAD_CONST              35 ('temperament_preset')
              CALL                     2
              POP_TOP

770           LOAD_GLOBAL              0 (op)
              LOAD_ATTR                4 (drop_column)
              PUSH_NULL
              LOAD_CONST               2 ('user_settings')
              LOAD_CONST              36 ('after_hours_behavior')
              CALL                     2
              POP_TOP

771           LOAD_GLOBAL              0 (op)
              LOAD_ATTR                4 (drop_column)
              PUSH_NULL
              LOAD_CONST               2 ('user_settings')
              LOAD_CONST              37 ('business_hours_days')
              CALL                     2
              POP_TOP

772           LOAD_GLOBAL              0 (op)
              LOAD_ATTR                4 (drop_column)
              PUSH_NULL
              LOAD_CONST               2 ('user_settings')
              LOAD_CONST              38 ('business_hours_end')
              CALL                     2
              POP_TOP

773           LOAD_GLOBAL              0 (op)
              LOAD_ATTR                4 (drop_column)
              PUSH_NULL
              LOAD_CONST               2 ('user_settings')
              LOAD_CONST              39 ('business_hours_start')
              CALL                     2
              POP_TOP

774           LOAD_GLOBAL              0 (op)
              LOAD_ATTR                4 (drop_column)
              PUSH_NULL
              LOAD_CONST               2 ('user_settings')
              LOAD_CONST              40 ('business_hours_enabled')
              CALL                     2
              POP_TOP

775           LOAD_GLOBAL              0 (op)
              LOAD_ATTR                4 (drop_column)
              PUSH_NULL
              LOAD_CONST               2 ('user_settings')
              LOAD_CONST              41 ('handoff_offer_timeout_seconds')
              CALL                     2
              POP_TOP

776           LOAD_GLOBAL              0 (op)
              LOAD_ATTR                4 (drop_column)
              PUSH_NULL
              LOAD_CONST               2 ('user_settings')
              LOAD_CONST              42 ('handoff_trigger')
              CALL                     2
              POP_TOP

777           LOAD_GLOBAL              0 (op)
              LOAD_ATTR                4 (drop_column)
              PUSH_NULL
              LOAD_CONST               2 ('user_settings')
              LOAD_CONST              43 ('handoff_enabled')
              CALL                     2
              POP_TOP

780           LOAD_GLOBAL              0 (op)
              LOAD_ATTR                6 (drop_index)
              PUSH_NULL
              LOAD_CONST              44 ('calls_retention_idx')
              LOAD_CONST              45 ('calls')
              LOAD_CONST              46 (('table_name',))
              CALL_KW                  2
              POP_TOP

781           LOAD_GLOBAL              0 (op)
              LOAD_ATTR                2 (drop_constraint)
              PUSH_NULL
              LOAD_CONST              47 ('ck_calls_handoff_status')
              LOAD_CONST              45 ('calls')
              LOAD_CONST               3 ('check')
              LOAD_CONST               4 (('type_',))
              CALL_KW                  3
              POP_TOP

782           LOAD_GLOBAL              0 (op)
              LOAD_ATTR                4 (drop_column)
              PUSH_NULL
              LOAD_CONST              45 ('calls')
              LOAD_CONST              48 ('handoff_loop_detected')
              CALL                     2
              POP_TOP

783           LOAD_GLOBAL              0 (op)
              LOAD_ATTR                4 (drop_column)
              PUSH_NULL
              LOAD_CONST              45 ('calls')
              LOAD_CONST              49 ('handoff_failure_reason')
              CALL                     2
              POP_TOP

784           LOAD_GLOBAL              0 (op)
              LOAD_ATTR                4 (drop_column)
              PUSH_NULL
              LOAD_CONST              45 ('calls')
              LOAD_CONST              50 ('handoff_attempt_count')
              CALL                     2
              POP_TOP

785           LOAD_GLOBAL              0 (op)
              LOAD_ATTR                4 (drop_column)
              PUSH_NULL
              LOAD_CONST              45 ('calls')
              LOAD_CONST              51 ('handoff_selected_device_id')
              CALL                     2
              POP_TOP

786           LOAD_GLOBAL              0 (op)
              LOAD_ATTR                4 (drop_column)
              PUSH_NULL
              LOAD_CONST              45 ('calls')
              LOAD_CONST              52 ('handoff_accepted_at')
              CALL                     2
              POP_TOP

787           LOAD_GLOBAL              0 (op)
              LOAD_ATTR                4 (drop_column)
              PUSH_NULL
              LOAD_CONST              45 ('calls')
              LOAD_CONST              53 ('handoff_offer_expires_at')
              CALL                     2
              POP_TOP

788           LOAD_GLOBAL              0 (op)
              LOAD_ATTR                4 (drop_column)
              PUSH_NULL
              LOAD_CONST              45 ('calls')
              LOAD_CONST              54 ('handoff_offered_at')
              CALL                     2
              POP_TOP

789           LOAD_GLOBAL              0 (op)
              LOAD_ATTR                4 (drop_column)
              PUSH_NULL
              LOAD_CONST              45 ('calls')
              LOAD_CONST              55 ('handoff_status')
              CALL                     2
              POP_TOP

790           LOAD_GLOBAL              0 (op)
              LOAD_ATTR                4 (drop_column)
              PUSH_NULL
              LOAD_CONST              45 ('calls')
              LOAD_CONST              56 ('handoff_eligible')
              CALL                     2
              POP_TOP

793           LOAD_GLOBAL              0 (op)
              LOAD_ATTR                8 (drop_table)
              PUSH_NULL
              LOAD_CONST              57 ('handoff_suppressions')
              CALL                     1
              POP_TOP

794           LOAD_GLOBAL              0 (op)
              LOAD_ATTR                8 (drop_table)
              PUSH_NULL
              LOAD_CONST              58 ('handoff_offers')
              CALL                     1
              POP_TOP

795           LOAD_GLOBAL              0 (op)
              LOAD_ATTR                8 (drop_table)
              PUSH_NULL
              LOAD_CONST              59 ('notification_deliveries')
              CALL                     1
              POP_TOP

796           LOAD_GLOBAL              0 (op)
              LOAD_ATTR                8 (drop_table)
              PUSH_NULL
              LOAD_CONST              60 ('notifications')
              CALL                     1
              POP_TOP

797           LOAD_GLOBAL              0 (op)
              LOAD_ATTR                8 (drop_table)
              PUSH_NULL
              LOAD_CONST              61 ('reminders')
              CALL                     1
              POP_TOP

798           LOAD_GLOBAL              0 (op)
              LOAD_ATTR                8 (drop_table)
              PUSH_NULL
              LOAD_CONST              62 ('block_entries')
              CALL                     1
              POP_TOP

799           LOAD_GLOBAL              0 (op)
              LOAD_ATTR                8 (drop_table)
              PUSH_NULL
              LOAD_CONST              63 ('vip_entries')
              CALL                     1
              POP_TOP
              RETURN_CONST             0 (None)

# --- Module-level bytecode ---
  0           RESUME                   0

  1           SETUP_ANNOTATIONS
              LOAD_CONST               0 ('Phase 1 completion: VIP/block lists, reminders, notifications, handoff,\nand expanded user_settings columns.\n\nRevision ID: 015\nRevises: 014\nCreate Date: 2026-02-27\n\n')
              STORE_NAME               0 (__doc__)

  9           LOAD_CONST               1 (0)
              LOAD_CONST               2 (('Sequence',))
              IMPORT_NAME              1 (collections.abc)
              IMPORT_FROM              2 (Sequence)
              STORE_NAME               2 (Sequence)
              POP_TOP

 11           LOAD_CONST               1 (0)
              LOAD_CONST               3 (None)
              IMPORT_NAME              3 (sqlalchemy)
              STORE_NAME               4 (sa)

 12           LOAD_CONST               1 (0)
              LOAD_CONST               4 (('JSONB', 'UUID'))
              IMPORT_NAME              5 (sqlalchemy.dialects.postgresql)
              IMPORT_FROM              6 (JSONB)
              STORE_NAME               6 (JSONB)
              IMPORT_FROM              7 (UUID)
              STORE_NAME               7 (UUID)
              POP_TOP

 14           LOAD_CONST               1 (0)
              LOAD_CONST               5 (('op',))
              IMPORT_NAME              8 (alembic)
              IMPORT_FROM              9 (op)
              STORE_NAME               9 (op)
              POP_TOP

 16           LOAD_CONST               6 ('015')
              STORE_NAME              10 (revision)
              LOAD_NAME               11 (str)
              LOAD_NAME               12 (__annotations__)
              LOAD_CONST               7 ('revision')
              STORE_SUBSCR

 17           LOAD_CONST               8 ('014')
              STORE_NAME              13 (down_revision)
              LOAD_NAME               11 (str)
              LOAD_CONST               3 (None)
              BINARY_OP                7 (|)
              LOAD_NAME               12 (__annotations__)
              LOAD_CONST               9 ('down_revision')
              STORE_SUBSCR

 18           LOAD_CONST               3 (None)
              STORE_NAME              14 (branch_labels)
              LOAD_NAME               11 (str)
              LOAD_NAME                2 (Sequence)
              LOAD_NAME               11 (str)
              BINARY_SUBSCR
              BINARY_OP                7 (|)
              LOAD_CONST               3 (None)
              BINARY_OP                7 (|)
              LOAD_NAME               12 (__annotations__)
              LOAD_CONST              10 ('branch_labels')
              STORE_SUBSCR

 19           LOAD_CONST               3 (None)
              STORE_NAME              15 (depends_on)
              LOAD_NAME               11 (str)
              LOAD_NAME                2 (Sequence)
              LOAD_NAME               11 (str)
              BINARY_SUBSCR
              BINARY_OP                7 (|)
              LOAD_CONST               3 (None)
              BINARY_OP                7 (|)
              LOAD_NAME               12 (__annotations__)
              LOAD_CONST              11 ('depends_on')
              STORE_SUBSCR

 22           LOAD_CONST              14 (('return', None))
              LOAD_CONST              12 (<code object upgrade at 0x00000185C9B2A050, file "D:\fluence\Github\mattbot\backend\alembic\versions\015_phase1_completion.py", line 22>)
              MAKE_FUNCTION
              SET_FUNCTION_ATTRIBUTE   4 (annotations)
              STORE_NAME              16 (upgrade)

734           LOAD_CONST              14 (('return', None))
              LOAD_CONST              13 (<code object downgrade at 0x00000185C9A4A180, file "D:\fluence\Github\mattbot\backend\alembic\versions\015_phase1_completion.py", line 734>)
              MAKE_FUNCTION
              SET_FUNCTION_ATTRIBUTE   4 (annotations)
              STORE_NAME              17 (downgrade)
              RETURN_CONST             3 (None)

Disassembly of <code object upgrade at 0x00000185C9B2A050, file "D:\fluence\Github\mattbot\backend\alembic\versions\015_phase1_completion.py", line 22>:
 22           RESUME                   0

 26           LOAD_GLOBAL              0 (op)
              LOAD_ATTR                2 (create_table)
              PUSH_NULL

 27           LOAD_CONST               1 ('vip_entries')

 28           LOAD_GLOBAL              4 (sa)
              LOAD_ATTR                6 (Column)
              PUSH_NULL
              LOAD_CONST               2 ('id')
              LOAD_GLOBAL              9 (UUID + NULL)
              LOAD_CONST               3 (True)
              LOAD_CONST               4 (('as_uuid',))
              CALL_KW                  1
              LOAD_CONST               3 (True)
              LOAD_CONST               5 (('primary_key',))
              CALL_KW                  3

 29           LOAD_GLOBAL              4 (sa)
              LOAD_ATTR                6 (Column)
              PUSH_NULL

 30           LOAD_CONST               6 ('owner_user_id')

 31           LOAD_GLOBAL              9 (UUID + NULL)
              LOAD_CONST               3 (True)
              LOAD_CONST               4 (('as_uuid',))
              CALL_KW                  1

 32           LOAD_GLOBAL              4 (sa)
              LOAD_ATTR               10 (ForeignKey)
              PUSH_NULL
              LOAD_CONST               7 ('users.id')
              LOAD_CONST               8 ('CASCADE')
              LOAD_CONST               9 (('ondelete',))
              CALL_KW                  2

 33           LOAD_CONST              10 (False)

 29           LOAD_CONST              11 (('nullable',))
              CALL_KW                  4

 35           LOAD_GLOBAL              4 (sa)
              LOAD_ATTR                6 (Column)
              PUSH_NULL
              LOAD_CONST              12 ('phone_ciphertext')
              LOAD_GLOBAL              4 (sa)
              LOAD_ATTR               12 (LargeBinary)
              PUSH_NULL
              CALL                     0
              LOAD_CONST              10 (False)
              LOAD_CONST              11 (('nullable',))
              CALL_KW                  3

 36           LOAD_GLOBAL              4 (sa)
              LOAD_ATTR                6 (Column)
              PUSH_NULL
              LOAD_CONST              13 ('phone_nonce')
              LOAD_GLOBAL              4 (sa)
              LOAD_ATTR               12 (LargeBinary)
              PUSH_NULL
              CALL                     0
              LOAD_CONST              10 (False)
              LOAD_CONST              11 (('nullable',))
              CALL_KW                  3

 37           LOAD_GLOBAL              4 (sa)
              LOAD_ATTR                6 (Column)
              PUSH_NULL
              LOAD_CONST              14 ('phone_key_version')
              LOAD_GLOBAL              4 (sa)
              LOAD_ATTR               14 (Integer)
              PUSH_NULL
              CALL                     0
              LOAD_CONST              10 (False)
              LOAD_CONST              11 (('nullable',))
              CALL_KW                  3

 38           LOAD_GLOBAL              4 (sa)
              LOAD_ATTR                6 (Column)
              PUSH_NULL
              LOAD_CONST              15 ('phone_hash')
              LOAD_GLOBAL              4 (sa)
              LOAD_ATTR               16 (String)
              PUSH_NULL
              LOAD_CONST              16 (64)
              CALL                     1
              LOAD_CONST              10 (False)
              LOAD_CONST              11 (('nullable',))
              CALL_KW                  3

 39           LOAD_GLOBAL              4 (sa)
              LOAD_ATTR                6 (Column)
              PUSH_NULL
              LOAD_CONST              17 ('phone_last4')
              LOAD_GLOBAL              4 (sa)
              LOAD_ATTR               16 (String)
              PUSH_NULL
              LOAD_CONST              18 (4)
              CALL                     1
              LOAD_CONST              10 (False)
              LOAD_CONST              11 (('nullable',))
              CALL_KW                  3

 40           LOAD_GLOBAL              4 (sa)
              LOAD_ATTR                6 (Column)
              PUSH_NULL
              LOAD_CONST              19 ('display_name')
              LOAD_GLOBAL              4 (sa)
              LOAD_ATTR               18 (Text)
              PUSH_NULL
              CALL                     0
              LOAD_CONST               3 (True)
              LOAD_CONST              11 (('nullable',))
              CALL_KW                  3

 41           LOAD_GLOBAL              4 (sa)
              LOAD_ATTR                6 (Column)
              PUSH_NULL

 42           LOAD_CONST              20 ('created_at')

 43           LOAD_GLOBAL              4 (sa)
              LOAD_ATTR               20 (DateTime)
              PUSH_NULL
              LOAD_CONST               3 (True)
              LOAD_CONST              21 (('timezone',))
              CALL_KW                  1

 44           LOAD_CONST              10 (False)

 45           LOAD_GLOBAL              4 (sa)
              LOAD_ATTR               22 (text)
              PUSH_NULL
              LOAD_CONST              22 ('now()')
              CALL                     1

 41           LOAD_CONST              23 (('nullable', 'server_default'))
              CALL_KW                  4

 47           LOAD_GLOBAL              4 (sa)
              LOAD_ATTR                6 (Column)
              PUSH_NULL

 48           LOAD_CONST              24 ('updated_at')

 49           LOAD_GLOBAL              4 (sa)
              LOAD_ATTR               20 (DateTime)
              PUSH_NULL
              LOAD_CONST               3 (True)
              LOAD_CONST              21 (('timezone',))
              CALL_KW                  1

 50           LOAD_CONST              10 (False)

 51           LOAD_GLOBAL              4 (sa)
              LOAD_ATTR               22 (text)
              PUSH_NULL
              LOAD_CONST              22 ('now()')
              CALL                     1

 47           LOAD_CONST              23 (('nullable', 'server_default'))
              CALL_KW                  4

 53           LOAD_GLOBAL              4 (sa)
              LOAD_ATTR               24 (UniqueConstraint)
              PUSH_NULL

 54           LOAD_CONST               6 ('owner_user_id')
              LOAD_CONST              15 ('phone_hash')
              LOAD_CONST              25 ('uq_vip_entries_user_phone')

 53           LOAD_CONST              26 (('name',))
              CALL_KW                  3

 26           CALL                    12
              POP_TOP

 57           LOAD_GLOBAL              0 (op)
              LOAD_ATTR               26 (create_index)
              PUSH_NULL
              LOAD_CONST              27 ('vip_entries_user_idx')
              LOAD_CONST               1 ('vip_entries')
              LOAD_CONST               6 ('owner_user_id')
              BUILD_LIST               1
              CALL                     3
              POP_TOP

 62           LOAD_GLOBAL              0 (op)
              LOAD_ATTR                2 (create_table)
              PUSH_NULL

 63           LOAD_CONST              28 ('block_entries')

 64           LOAD_GLOBAL              4 (sa)
              LOAD_ATTR                6 (Column)
              PUSH_NULL
              LOAD_CONST               2 ('id')
              LOAD_GLOBAL              9 (UUID + NULL)
              LOAD_CONST               3 (True)
              LOAD_CONST               4 (('as_uuid',))
              CALL_KW                  1
              LOAD_CONST               3 (True)
              LOAD_CONST               5 (('primary_key',))
              CALL_KW                  3

 65           LOAD_GLOBAL              4 (sa)
              LOAD_ATTR                6 (Column)
              PUSH_NULL

 66           LOAD_CONST               6 ('owner_user_id')

 67           LOAD_GLOBAL              9 (UUID + NULL)
              LOAD_CONST               3 (True)
              LOAD_CONST               4 (('as_uuid',))
              CALL_KW                  1

 68           LOAD_GLOBAL              4 (sa)
              LOAD_ATTR               10 (ForeignKey)
              PUSH_NULL
              LOAD_CONST               7 ('users.id')
              LOAD_CONST               8 ('CASCADE')
              LOAD_CONST               9 (('ondelete',))
              CALL_KW                  2

 69           LOAD_CONST              10 (False)

 65           LOAD_CONST              11 (('nullable',))
              CALL_KW                  4

 71           LOAD_GLOBAL              4 (sa)
              LOAD_ATTR                6 (Column)
              PUSH_NULL
              LOAD_CONST              12 ('phone_ciphertext')
              LOAD_GLOBAL              4 (sa)
              LOAD_ATTR               12 (LargeBinary)
              PUSH_NULL
              CALL                     0
              LOAD_CONST              10 (False)
              LOAD_CONST              11 (('nullable',))
              CALL_KW                  3

 72           LOAD_GLOBAL              4 (sa)
              LOAD_ATTR                6 (Column)
              PUSH_NULL
              LOAD_CONST              13 ('phone_nonce')
              LOAD_GLOBAL              4 (sa)
              LOAD_ATTR               12 (LargeBinary)
              PUSH_NULL
              CALL                     0
              LOAD_CONST              10 (False)
              LOAD_CONST              11 (('nullable',))
              CALL_KW                  3

 73           LOAD_GLOBAL              4 (sa)
              LOAD_ATTR                6 (Column)
              PUSH_NULL
              LOAD_CONST              14 ('phone_key_version')
              LOAD_GLOBAL              4 (sa)
              LOAD_ATTR               14 (Integer)
              PUSH_NULL
              CALL                     0
              LOAD_CONST              10 (False)
              LOAD_CONST              11 (('nullable',))
              CALL_KW                  3

 74           LOAD_GLOBAL              4 (sa)
              LOAD_ATTR                6 (Column)
              PUSH_NULL
              LOAD_CONST              15 ('phone_hash')
              LOAD_GLOBAL              4 (sa)
              LOAD_ATTR               16 (String)
              PUSH_NULL
              LOAD_CONST              16 (64)
              CALL                     1
              LOAD_CONST              10 (False)
              LOAD_CONST              11 (('nullable',))
              CALL_KW                  3

 75           LOAD_GLOBAL              4 (sa)
              LOAD_ATTR                6 (Column)
              PUSH_NULL
              LOAD_CONST              17 ('phone_last4')
              LOAD_GLOBAL              4 (sa)
              LOAD_ATTR               16 (String)
              PUSH_NULL
              LOAD_CONST              18 (4)
              CALL                     1
              LOAD_CONST              10 (False)
              LOAD_CONST              11 (('nullable',))
              CALL_KW                  3

 76           LOAD_GLOBAL              4 (sa)
              LOAD_ATTR                6 (Column)
              PUSH_NULL
              LOAD_CONST              19 ('display_name')
              LOAD_GLOBAL              4 (sa)
              LOAD_ATTR               18 (Text)
              PUSH_NULL
              CALL                     0
              LOAD_CONST               3 (True)
              LOAD_CONST              11 (('nullable',))
              CALL_KW                  3

 77           LOAD_GLOBAL              4 (sa)
              LOAD_ATTR                6 (Column)
              PUSH_NULL
              LOAD_CONST              29 ('reason')
              LOAD_GLOBAL              4 (sa)
              LOAD_ATTR               18 (Text)
              PUSH_NULL
              CALL                     0
              LOAD_CONST               3 (True)
              LOAD_CONST              11 (('nullable',))
              CALL_KW                  3

 78           LOAD_GLOBAL              4 (sa)
              LOAD_ATTR                6 (Column)
              PUSH_NULL

 79           LOAD_CONST              20 ('created_at')

 80           LOAD_GLOBAL              4 (sa)
              LOAD_ATTR               20 (DateTime)
              PUSH_NULL
              LOAD_CONST               3 (True)
              LOAD_CONST              21 (('timezone',))
              CALL_KW                  1

 81           LOAD_CONST              10 (False)

 82           LOAD_GLOBAL              4 (sa)
              LOAD_ATTR               22 (text)
              PUSH_NULL
              LOAD_CONST              22 ('now()')
              CALL                     1

 78           LOAD_CONST              23 (('nullable', 'server_default'))
              CALL_KW                  4

 84           LOAD_GLOBAL              4 (sa)
              LOAD_ATTR                6 (Column)
              PUSH_NULL

 85           LOAD_CONST              24 ('updated_at')

 86           LOAD_GLOBAL              4 (sa)
              LOAD_ATTR               20 (DateTime)
              PUSH_NULL
              LOAD_CONST               3 (True)
              LOAD_CONST              21 (('timezone',))
              CALL_KW                  1

 87           LOAD_CONST              10 (False)

 88           LOAD_GLOBAL              4 (sa)
              LOAD_ATTR               22 (text)
              PUSH_NULL
              LOAD_CONST              22 ('now()')
              CALL                     1

 84           LOAD_CONST              23 (('nullable', 'server_default'))
              CALL_KW                  4

 90           LOAD_GLOBAL              4 (sa)
              LOAD_ATTR               24 (UniqueConstraint)
              PUSH_NULL

 91           LOAD_CONST               6 ('owner_user_id')
              LOAD_CONST              15 ('phone_hash')
              LOAD_CONST              30 ('uq_block_entries_user_phone')

 90           LOAD_CONST              26 (('name',))
              CALL_KW                  3

 62           CALL                    13
              POP_TOP

 94           LOAD_GLOBAL              0 (op)
              LOAD_ATTR               26 (create_index)
              PUSH_NULL
              LOAD_CONST              31 ('block_entries_user_idx')
              LOAD_CONST              28 ('block_entries')
              LOAD_CONST               6 ('owner_user_id')
              BUILD_LIST               1
              CALL                     3
              POP_TOP

 99           LOAD_GLOBAL              0 (op)
              LOAD_ATTR                2 (create_table)
              PUSH_NULL

100           LOAD_CONST              32 ('reminders')

101           LOAD_GLOBAL              4 (sa)
              LOAD_ATTR                6 (Column)
              PUSH_NULL
              LOAD_CONST               2 ('id')
              LOAD_GLOBAL              9 (UUID + NULL)
              LOAD_CONST               3 (True)
              LOAD_CONST               4 (('as_uuid',))
              CALL_KW                  1
              LOAD_CONST               3 (True)
              LOAD_CONST               5 (('primary_key',))
              CALL_KW                  3

102           LOAD_GLOBAL              4 (sa)
              LOAD_ATTR                6 (Column)
              PUSH_NULL

103           LOAD_CONST               6 ('owner_user_id')

104           LOAD_GLOBAL              9 (UUID + NULL)
              LOAD_CONST               3 (True)
              LOAD_CONST               4 (('as_uuid',))
              CALL_KW                  1

105           LOAD_GLOBAL              4 (sa)
              LOAD_ATTR               10 (ForeignKey)
              PUSH_NULL
              LOAD_CONST               7 ('users.id')
              LOAD_CONST               8 ('CASCADE')
              LOAD_CONST               9 (('ondelete',))
              CALL_KW                  2

106           LOAD_CONST              10 (False)

102           LOAD_CONST              11 (('nullable',))
              CALL_KW                  4

108           LOAD_GLOBAL              4 (sa)
              LOAD_ATTR                6 (Column)
              PUSH_NULL

109           LOAD_CONST              33 ('call_id')

110           LOAD_GLOBAL              9 (UUID + NULL)
              LOAD_CONST               3 (True)
              LOAD_CONST               4 (('as_uuid',))
              CALL_KW                  1

111           LOAD_GLOBAL              4 (sa)
              LOAD_ATTR               10 (ForeignKey)
              PUSH_NULL
              LOAD_CONST              34 ('calls.id')
              LOAD_CONST              35 ('SET NULL')
              LOAD_CONST               9 (('ondelete',))
              CALL_KW                  2

112           LOAD_CONST               3 (True)

108           LOAD_CONST              11 (('nullable',))
              CALL_KW                  4

114           LOAD_GLOBAL              4 (sa)
              LOAD_ATTR                6 (Column)
              PUSH_NULL
              LOAD_CONST              36 ('title')
              LOAD_GLOBAL              4 (sa)
              LOAD_ATTR               16 (String)
              PUSH_NULL
              LOAD_CONST              37 (200)
              CALL                     1
              LOAD_CONST              10 (False)
              LOAD_CONST              11 (('nullable',))
              CALL_KW                  3

115           LOAD_GLOBAL              4 (sa)
              LOAD_ATTR                6 (Column)
              PUSH_NULL
              LOAD_CONST              38 ('due_at')
              LOAD_GLOBAL              4 (sa)
              LOAD_ATTR               20 (DateTime)
              PUSH_NULL
              LOAD_CONST               3 (True)
              LOAD_CONST              21 (('timezone',))
              CALL_KW                  1
              LOAD_CONST              10 (False)
              LOAD_CONST              11 (('nullable',))
              CALL_KW                  3

116           LOAD_GLOBAL              4 (sa)
              LOAD_ATTR                6 (Column)
              PUSH_NULL
              LOAD_CONST              39 ('timezone_at_creation')
              LOAD_GLOBAL              4 (sa)
              LOAD_ATTR               18 (Text)
              PUSH_NULL
              CALL                     0
              LOAD_CONST               3 (True)
              LOAD_CONST              11 (('nullable',))
              CALL_KW                  3

117           LOAD_GLOBAL              4 (sa)
              LOAD_ATTR                6 (Column)
              PUSH_NULL
              LOAD_CONST              40 ('status')
              LOAD_GLOBAL              4 (sa)
              LOAD_ATTR               16 (String)
              PUSH_NULL
              LOAD_CONST              41 (20)
              CALL                     1
              LOAD_CONST              10 (False)
              LOAD_CONST              11 (('nullable',))
              CALL_KW                  3

118           LOAD_GLOBAL              4 (sa)
              LOAD_ATTR                6 (Column)
              PUSH_NULL

119           LOAD_CONST              20 ('created_at')

120           LOAD_GLOBAL              4 (sa)
              LOAD_ATTR               20 (DateTime)
              PUSH_NULL
              LOAD_CONST               3 (True)
              LOAD_CONST              21 (('timezone',))
              CALL_KW                  1

121           LOAD_CONST              10 (False)

122           LOAD_GLOBAL              4 (sa)
              LOAD_ATTR               22 (text)
              PUSH_NULL
              LOAD_CONST              22 ('now()')
              CALL                     1

118           LOAD_CONST              23 (('nullable', 'server_default'))
              CALL_KW                  4

124           LOAD_GLOBAL              4 (sa)
              LOAD_ATTR                6 (Column)
              PUSH_NULL

125           LOAD_CONST              24 ('updated_at')

126           LOAD_GLOBAL              4 (sa)
              LOAD_ATTR               20 (DateTime)
              PUSH_NULL
              LOAD_CONST               3 (True)
              LOAD_CONST              21 (('timezone',))
              CALL_KW                  1

127           LOAD_CONST              10 (False)

128           LOAD_GLOBAL              4 (sa)
              LOAD_ATTR               22 (text)
              PUSH_NULL
              LOAD_CONST              22 ('now()')
              CALL                     1

124           LOAD_CONST              23 (('nullable', 'server_default'))
              CALL_KW                  4

130           LOAD_GLOBAL              4 (sa)
              LOAD_ATTR                6 (Column)
              PUSH_NULL
              LOAD_CONST              42 ('created_by_device_id')
              LOAD_GLOBAL              9 (UUID + NULL)
              LOAD_CONST               3 (True)
              LOAD_CONST               4 (('as_uuid',))
              CALL_KW                  1
              LOAD_CONST               3 (True)
              LOAD_CONST              11 (('nullable',))
              CALL_KW                  3

131           LOAD_GLOBAL              4 (sa)
              LOAD_ATTR               28 (CheckConstraint)
              PUSH_NULL

132           LOAD_CONST              43 ("status IN ('scheduled', 'triggered', 'completed', 'cancelled')")

133           LOAD_CONST              44 ('ck_reminders_status')

131           LOAD_CONST              26 (('name',))
              CALL_KW                  2

 99           CALL                    12
              POP_TOP

136           LOAD_GLOBAL              0 (op)
              LOAD_ATTR               26 (create_index)
              PUSH_NULL

137           LOAD_CONST              45 ('reminders_user_due_idx')
              LOAD_CONST              32 ('reminders')
              LOAD_CONST               6 ('owner_user_id')
              LOAD_CONST              38 ('due_at')
              BUILD_LIST               2

136           CALL                     3
              POP_TOP

139           LOAD_GLOBAL              0 (op)
              LOAD_ATTR               26 (create_index)
              PUSH_NULL

140           LOAD_CONST              46 ('reminders_scheduled_due_idx')

141           LOAD_CONST              32 ('reminders')

142           LOAD_CONST              38 ('due_at')
              BUILD_LIST               1

143           LOAD_GLOBAL              4 (sa)
              LOAD_ATTR               22 (text)
              PUSH_NULL
              LOAD_CONST              47 ("status = 'scheduled'")
              CALL                     1

139           LOAD_CONST              48 (('postgresql_where',))
              CALL_KW                  4
              POP_TOP

149           LOAD_GLOBAL              0 (op)
              LOAD_ATTR                2 (create_table)
              PUSH_NULL

150           LOAD_CONST              49 ('notifications')

151           LOAD_GLOBAL              4 (sa)
              LOAD_ATTR                6 (Column)
              PUSH_NULL
              LOAD_CONST               2 ('id')
              LOAD_GLOBAL              9 (UUID + NULL)
              LOAD_CONST               3 (True)
              LOAD_CONST               4 (('as_uuid',))
              CALL_KW                  1
              LOAD_CONST               3 (True)
              LOAD_CONST               5 (('primary_key',))
              CALL_KW                  3

152           LOAD_GLOBAL              4 (sa)
              LOAD_ATTR                6 (Column)
              PUSH_NULL

153           LOAD_CONST               6 ('owner_user_id')

154           LOAD_GLOBAL              9 (UUID + NULL)
              LOAD_CONST               3 (True)
              LOAD_CONST               4 (('as_uuid',))
              CALL_KW                  1

155           LOAD_GLOBAL              4 (sa)
              LOAD_ATTR               10 (ForeignKey)
              PUSH_NULL
              LOAD_CONST               7 ('users.id')
              LOAD_CONST               8 ('CASCADE')
              LOAD_CONST               9 (('ondelete',))
              CALL_KW                  2

156           LOAD_CONST              10 (False)

152           LOAD_CONST              11 (('nullable',))
              CALL_KW                  4

158           LOAD_GLOBAL              4 (sa)
              LOAD_ATTR                6 (Column)
              PUSH_NULL
              LOAD_CONST              50 ('type')
              LOAD_GLOBAL              4 (sa)
              LOAD_ATTR               18 (Text)
              PUSH_NULL
              CALL                     0
              LOAD_CONST              10 (False)
              LOAD_CONST              11 (('nullable',))
              CALL_KW                  3

159           LOAD_GLOBAL              4 (sa)
              LOAD_ATTR                6 (Column)
              PUSH_NULL

160           LOAD_CONST              51 ('priority')

161           LOAD_GLOBAL              4 (sa)
              LOAD_ATTR               18 (Text)
              PUSH_NULL
              CALL                     0

162           LOAD_CONST              10 (False)

163           LOAD_GLOBAL              4 (sa)
              LOAD_ATTR               22 (text)
              PUSH_NULL
              LOAD_CONST              52 ("'normal'")
              CALL                     1

159           LOAD_CONST              23 (('nullable', 'server_default'))
              CALL_KW                  4

165           LOAD_GLOBAL              4 (sa)
              LOAD_ATTR                6 (Column)
              PUSH_NULL
              LOAD_CONST              53 ('source_entity_type')
              LOAD_GLOBAL              4 (sa)
              LOAD_ATTR               18 (Text)
              PUSH_NULL
              CALL                     0
              LOAD_CONST               3 (True)
              LOAD_CONST              11 (('nullable',))
              CALL_KW                  3

166           LOAD_GLOBAL              4 (sa)
              LOAD_ATTR                6 (Column)
              PUSH_NULL
              LOAD_CONST              54 ('source_entity_id')
              LOAD_GLOBAL              9 (UUID + NULL)
              LOAD_CONST               3 (True)
              LOAD_CONST               4 (('as_uuid',))
              CALL_KW                  1
              LOAD_CONST               3 (True)
              LOAD_CONST              11 (('nullable',))
              CALL_KW                  3

167           LOAD_GLOBAL              4 (sa)
              LOAD_ATTR                6 (Column)
              PUSH_NULL
              LOAD_CONST              55 ('privacy_mode_applied')
              LOAD_GLOBAL              4 (sa)
              LOAD_ATTR               18 (Text)
              PUSH_NULL
              CALL                     0
              LOAD_CONST              10 (False)
              LOAD_CONST              11 (('nullable',))
              CALL_KW                  3

168           LOAD_GLOBAL              4 (sa)
              LOAD_ATTR                6 (Column)
              PUSH_NULL

169           LOAD_CONST              56 ('quiet_hours_applied')

170           LOAD_GLOBAL              4 (sa)
              LOAD_ATTR               18 (Text)
              PUSH_NULL
              CALL                     0

171           LOAD_CONST              10 (False)

172           LOAD_GLOBAL              4 (sa)
              LOAD_ATTR               22 (text)
              PUSH_NULL
              LOAD_CONST              57 ("'none'")
              CALL                     1

168           LOAD_CONST              23 (('nullable', 'server_default'))
              CALL_KW                  4

174           LOAD_GLOBAL              4 (sa)
              LOAD_ATTR                6 (Column)
              PUSH_NULL
              LOAD_CONST              58 ('content_hash')
              LOAD_GLOBAL              4 (sa)
              LOAD_ATTR               16 (String)
              PUSH_NULL
              LOAD_CONST              16 (64)
              CALL                     1
              LOAD_CONST               3 (True)
              LOAD_CONST              11 (('nullable',))
              CALL_KW                  3

175           LOAD_GLOBAL              4 (sa)
              LOAD_ATTR                6 (Column)
              PUSH_NULL

176           LOAD_CONST              20 ('created_at')

177           LOAD_GLOBAL              4 (sa)
              LOAD_ATTR               20 (DateTime)
              PUSH_NULL
              LOAD_CONST               3 (True)
              LOAD_CONST              21 (('timezone',))
              CALL_KW                  1

178           LOAD_CONST              10 (False)

179           LOAD_GLOBAL              4 (sa)
              LOAD_ATTR               22 (text)
              PUSH_NULL
              LOAD_CONST              22 ('now()')
              CALL                     1

175           LOAD_CONST              23 (('nullable', 'server_default'))
              CALL_KW                  4

181           LOAD_GLOBAL              4 (sa)
              LOAD_ATTR               28 (CheckConstraint)
              PUSH_NULL

182           LOAD_CONST              59 ("type IN ('call_screened_created', 'call_important_detected', 'handoff_available', 'call_processing_error', 'reminder_due')")

184           LOAD_CONST              60 ('ck_notifications_type')

181           LOAD_CONST              26 (('name',))
              CALL_KW                  2

186           LOAD_GLOBAL              4 (sa)
              LOAD_ATTR               28 (CheckConstraint)
              PUSH_NULL

187           LOAD_CONST              61 ("priority IN ('low', 'normal', 'high', 'critical')")

188           LOAD_CONST              62 ('ck_notifications_priority')

186           LOAD_CONST              26 (('name',))
              CALL_KW                  2

190           LOAD_GLOBAL              4 (sa)
              LOAD_ATTR               28 (CheckConstraint)
              PUSH_NULL

191           LOAD_CONST              63 ("source_entity_type IN ('call', 'handoff_offer', 'reminder', 'system_error') OR source_entity_type IS NULL")

193           LOAD_CONST              64 ('ck_notifications_source_entity_type')

190           LOAD_CONST              26 (('name',))
              CALL_KW                  2

195           LOAD_GLOBAL              4 (sa)
              LOAD_ATTR               28 (CheckConstraint)
              PUSH_NULL

196           LOAD_CONST              65 ("privacy_mode_applied IN ('private', 'preview')")

197           LOAD_CONST              66 ('ck_notifications_privacy_mode')

195           LOAD_CONST              26 (('name',))
              CALL_KW                  2

199           LOAD_GLOBAL              4 (sa)
              LOAD_ATTR               28 (CheckConstraint)
              PUSH_NULL

200           LOAD_CONST              67 ("quiet_hours_applied IN ('none', 'silent', 'suppressed')")

201           LOAD_CONST              68 ('ck_notifications_quiet_hours')

199           LOAD_CONST              26 (('name',))
              CALL_KW                  2

149           CALL                    16
              POP_TOP

204           LOAD_GLOBAL              0 (op)
              LOAD_ATTR               26 (create_index)
              PUSH_NULL

205           LOAD_CONST              69 ('notifications_user_created_idx')

206           LOAD_CONST              49 ('notifications')

207           LOAD_CONST               6 ('owner_user_id')
              LOAD_GLOBAL              4 (sa)
              LOAD_ATTR               22 (text)
              PUSH_NULL
              LOAD_CONST              70 ('created_at DESC')
              CALL                     1
              BUILD_LIST               2

204           CALL                     3
              POP_TOP

213           LOAD_GLOBAL              0 (op)
              LOAD_ATTR                2 (create_table)
              PUSH_NULL

214           LOAD_CONST              71 ('notification_deliveries')

215           LOAD_GLOBAL              4 (sa)
              LOAD_ATTR                6 (Column)
              PUSH_NULL
              LOAD_CONST               2 ('id')
              LOAD_GLOBAL              9 (UUID + NULL)
              LOAD_CONST               3 (True)
              LOAD_CONST               4 (('as_uuid',))
              CALL_KW                  1
              LOAD_CONST               3 (True)
              LOAD_CONST               5 (('primary_key',))
              CALL_KW                  3

216           LOAD_GLOBAL              4 (sa)
              LOAD_ATTR                6 (Column)
              PUSH_NULL

217           LOAD_CONST              72 ('notification_id')

218           LOAD_GLOBAL              9 (UUID + NULL)
              LOAD_CONST               3 (True)
              LOAD_CONST               4 (('as_uuid',))
              CALL_KW                  1

219           LOAD_GLOBAL              4 (sa)
              LOAD_ATTR               10 (ForeignKey)
              PUSH_NULL
              LOAD_CONST              73 ('notifications.id')
              LOAD_CONST               8 ('CASCADE')
              LOAD_CONST               9 (('ondelete',))
              CALL_KW                  2

220           LOAD_CONST              10 (False)

216           LOAD_CONST              11 (('nullable',))
              CALL_KW                  4

222           LOAD_GLOBAL              4 (sa)
              LOAD_ATTR                6 (Column)
              PUSH_NULL

223           LOAD_CONST              74 ('device_id')

224           LOAD_GLOBAL              9 (UUID + NULL)
              LOAD_CONST               3 (True)
              LOAD_CONST               4 (('as_uuid',))
              CALL_KW                  1

225           LOAD_GLOBAL              4 (sa)
              LOAD_ATTR               10 (ForeignKey)
              PUSH_NULL
              LOAD_CONST              75 ('devices.id')
              LOAD_CONST              35 ('SET NULL')
              LOAD_CONST               9 (('ondelete',))
              CALL_KW                  2

226           LOAD_CONST               3 (True)

222           LOAD_CONST              11 (('nullable',))
              CALL_KW                  4

228           LOAD_GLOBAL              4 (sa)
              LOAD_ATTR                6 (Column)
              PUSH_NULL
              LOAD_CONST              76 ('provider')
              LOAD_GLOBAL              4 (sa)
              LOAD_ATTR               18 (Text)
              PUSH_NULL
              CALL                     0
              LOAD_CONST              10 (False)
              LOAD_CONST              11 (('nullable',))
              CALL_KW                  3

229           LOAD_GLOBAL              4 (sa)
              LOAD_ATTR                6 (Column)
              PUSH_NULL

230           LOAD_CONST              40 ('status')

231           LOAD_GLOBAL              4 (sa)
              LOAD_ATTR               18 (Text)
              PUSH_NULL
              CALL                     0

232           LOAD_CONST              10 (False)

233           LOAD_GLOBAL              4 (sa)
              LOAD_ATTR               22 (text)
              PUSH_NULL
              LOAD_CONST              77 ("'queued'")
              CALL                     1

229           LOAD_CONST              23 (('nullable', 'server_default'))
              CALL_KW                  4

235           LOAD_GLOBAL              4 (sa)
              LOAD_ATTR                6 (Column)
              PUSH_NULL

236           LOAD_CONST              78 ('attempt_count')

237           LOAD_GLOBAL              4 (sa)
              LOAD_ATTR               14 (Integer)
              PUSH_NULL
              CALL                     0

238           LOAD_CONST              10 (False)

239           LOAD_GLOBAL              4 (sa)
              LOAD_ATTR               22 (text)
              PUSH_NULL
              LOAD_CONST              79 ('0')
              CALL                     1

235           LOAD_CONST              23 (('nullable', 'server_default'))
              CALL_KW                  4

241           LOAD_GLOBAL              4 (sa)
              LOAD_ATTR                6 (Column)
              PUSH_NULL
              LOAD_CONST              80 ('next_attempt_at')
              LOAD_GLOBAL              4 (sa)
              LOAD_ATTR               20 (DateTime)
              PUSH_NULL
              LOAD_CONST               3 (True)
              LOAD_CONST              21 (('timezone',))
              CALL_KW                  1
              LOAD_CONST               3 (True)
              LOAD_CONST              11 (('nullable',))
              CALL_KW                  3

242           LOAD_GLOBAL              4 (sa)
              LOAD_ATTR                6 (Column)
              PUSH_NULL
              LOAD_CONST              81 ('last_attempt_at')
              LOAD_GLOBAL              4 (sa)
              LOAD_ATTR               20 (DateTime)
              PUSH_NULL
              LOAD_CONST               3 (True)
              LOAD_CONST              21 (('timezone',))
              CALL_KW                  1
              LOAD_CONST               3 (True)
              LOAD_CONST              11 (('nullable',))
              CALL_KW                  3

243           LOAD_GLOBAL              4 (sa)
              LOAD_ATTR                6 (Column)
              PUSH_NULL
              LOAD_CONST              82 ('provider_message_id')
              LOAD_GLOBAL              4 (sa)
              LOAD_ATTR               18 (Text)
              PUSH_NULL
              CALL                     0
              LOAD_CONST               3 (True)
              LOAD_CONST              11 (('nullable',))
              CALL_KW                  3

244           LOAD_GLOBAL              4 (sa)
              LOAD_ATTR                6 (Column)
              PUSH_NULL
              LOAD_CONST              83 ('last_error_code')
              LOAD_GLOBAL              4 (sa)
              LOAD_ATTR               18 (Text)
              PUSH_NULL
              CALL                     0
              LOAD_CONST               3 (True)
              LOAD_CONST              11 (('nullable',))
              CALL_KW                  3

245           LOAD_GLOBAL              4 (sa)
              LOAD_ATTR                6 (Column)
              PUSH_NULL
              LOAD_CONST              84 ('last_error_message_short')
              LOAD_GLOBAL              4 (sa)
              LOAD_ATTR               18 (Text)
              PUSH_NULL
              CALL                     0
              LOAD_CONST               3 (True)
              LOAD_CONST              11 (('nullable',))
              CALL_KW                  3

246           LOAD_GLOBAL              4 (sa)
              LOAD_ATTR                6 (Column)
              PUSH_NULL

247           LOAD_CONST              20 ('created_at')

248           LOAD_GLOBAL              4 (sa)
              LOAD_ATTR               20 (DateTime)
              PUSH_NULL
              LOAD_CONST               3 (True)
              LOAD_CONST              21 (('timezone',))
              CALL_KW                  1

249           LOAD_CONST              10 (False)

250           LOAD_GLOBAL              4 (sa)
              LOAD_ATTR               22 (text)
              PUSH_NULL
              LOAD_CONST              22 ('now()')
              CALL                     1

246           LOAD_CONST              23 (('nullable', 'server_default'))
              CALL_KW                  4

252           LOAD_GLOBAL              4 (sa)
              LOAD_ATTR               28 (CheckConstraint)
              PUSH_NULL

253           LOAD_CONST              85 ("provider IN ('apns', 'fcm')")

254           LOAD_CONST              86 ('ck_notification_deliveries_provider')

252           LOAD_CONST              26 (('name',))
              CALL_KW                  2

256           LOAD_GLOBAL              4 (sa)
              LOAD_ATTR               28 (CheckConstraint)
              PUSH_NULL

257           LOAD_CONST              87 ("status IN ('queued', 'sending', 'provider_accepted', 'provider_rejected', 'delivered_ack', 'expired', 'cancelled')")

259           LOAD_CONST              88 ('ck_notification_deliveries_status')

256           LOAD_CONST              26 (('name',))
              CALL_KW                  2

261           LOAD_GLOBAL              4 (sa)
              LOAD_ATTR               24 (UniqueConstraint)
              PUSH_NULL

262           LOAD_CONST              72 ('notification_id')

263           LOAD_CONST              74 ('device_id')

264           LOAD_CONST              89 ('uq_notification_deliveries_notif_device')

261           LOAD_CONST              26 (('name',))
              CALL_KW                  3

213           CALL                    16
              POP_TOP

271           LOAD_GLOBAL              0 (op)
              LOAD_ATTR                2 (create_table)
              PUSH_NULL

272           LOAD_CONST              90 ('handoff_offers')

273           LOAD_GLOBAL              4 (sa)
              LOAD_ATTR                6 (Column)
              PUSH_NULL
              LOAD_CONST               2 ('id')
              LOAD_GLOBAL              9 (UUID + NULL)
              LOAD_CONST               3 (True)
              LOAD_CONST               4 (('as_uuid',))
              CALL_KW                  1
              LOAD_CONST               3 (True)
              LOAD_CONST               5 (('primary_key',))
              CALL_KW                  3

274           LOAD_GLOBAL              4 (sa)
              LOAD_ATTR                6 (Column)
              PUSH_NULL

275           LOAD_CONST              33 ('call_id')

276           LOAD_GLOBAL              9 (UUID + NULL)
              LOAD_CONST               3 (True)
              LOAD_CONST               4 (('as_uuid',))
              CALL_KW                  1

277           LOAD_GLOBAL              4 (sa)
              LOAD_ATTR               10 (ForeignKey)
              PUSH_NULL
              LOAD_CONST              34 ('calls.id')
              LOAD_CONST               8 ('CASCADE')
              LOAD_CONST               9 (('ondelete',))
              CALL_KW                  2

278           LOAD_CONST              10 (False)

274           LOAD_CONST              11 (('nullable',))
              CALL_KW                  4

280           LOAD_GLOBAL              4 (sa)
              LOAD_ATTR                6 (Column)
              PUSH_NULL

281           LOAD_CONST               6 ('owner_user_id')

282           LOAD_GLOBAL              9 (UUID + NULL)
              LOAD_CONST               3 (True)
              LOAD_CONST               4 (('as_uuid',))
              CALL_KW                  1

283           LOAD_GLOBAL              4 (sa)
              LOAD_ATTR               10 (ForeignKey)
              PUSH_NULL
              LOAD_CONST               7 ('users.id')
              LOAD_CONST               8 ('CASCADE')
              LOAD_CONST               9 (('ondelete',))
              CALL_KW                  2

284           LOAD_CONST              10 (False)

280           LOAD_CONST              11 (('nullable',))
              CALL_KW                  4

286           LOAD_GLOBAL              4 (sa)
              LOAD_ATTR                6 (Column)
              PUSH_NULL

287           LOAD_CONST              40 ('status')

288           LOAD_GLOBAL              4 (sa)
              LOAD_ATTR               18 (Text)
              PUSH_NULL
              CALL                     0

289           LOAD_CONST              10 (False)

290           LOAD_GLOBAL              4 (sa)
              LOAD_ATTR               22 (text)
              PUSH_NULL
              LOAD_CONST              91 ("'offered'")
              CALL                     1

286           LOAD_CONST              23 (('nullable', 'server_default'))
              CALL_KW                  4

292           LOAD_GLOBAL              4 (sa)
              LOAD_ATTR                6 (Column)
              PUSH_NULL
              LOAD_CONST              92 ('offer_reason')
              LOAD_GLOBAL              4 (sa)
              LOAD_ATTR               18 (Text)
              PUSH_NULL
              CALL                     0
              LOAD_CONST               3 (True)
              LOAD_CONST              11 (('nullable',))
              CALL_KW                  3

293           LOAD_GLOBAL              4 (sa)
              LOAD_ATTR                6 (Column)
              PUSH_NULL
              LOAD_CONST              93 ('expires_at')
              LOAD_GLOBAL              4 (sa)
              LOAD_ATTR               20 (DateTime)
              PUSH_NULL
              LOAD_CONST               3 (True)
              LOAD_CONST              21 (('timezone',))
              CALL_KW                  1
              LOAD_CONST              10 (False)
              LOAD_CONST              11 (('nullable',))
              CALL_KW                  3

294           LOAD_GLOBAL              4 (sa)
              LOAD_ATTR                6 (Column)
              PUSH_NULL

295           LOAD_CONST              94 ('selected_device_id')

296           LOAD_GLOBAL              9 (UUID + NULL)
              LOAD_CONST               3 (True)
              LOAD_CONST               4 (('as_uuid',))
              CALL_KW                  1

297           LOAD_GLOBAL              4 (sa)
              LOAD_ATTR               10 (ForeignKey)
              PUSH_NULL
              LOAD_CONST              75 ('devices.id')
              LOAD_CONST              35 ('SET NULL')
              LOAD_CONST               9 (('ondelete',))
              CALL_KW                  2

298           LOAD_CONST               3 (True)

294           LOAD_CONST              11 (('nullable',))
              CALL_KW                  4

300           LOAD_GLOBAL              4 (sa)
              LOAD_ATTR                6 (Column)
              PUSH_NULL
              LOAD_CONST              95 ('accepted_at')
              LOAD_GLOBAL              4 (sa)
              LOAD_ATTR               20 (DateTime)
              PUSH_NULL
              LOAD_CONST               3 (True)
              LOAD_CONST              21 (('timezone',))
              CALL_KW                  1
              LOAD_CONST               3 (True)
              LOAD_CONST              11 (('nullable',))
              CALL_KW                  3

301           LOAD_GLOBAL              4 (sa)
              LOAD_ATTR                6 (Column)
              PUSH_NULL
              LOAD_CONST              96 ('declined_at')
              LOAD_GLOBAL              4 (sa)
              LOAD_ATTR               20 (DateTime)
              PUSH_NULL
              LOAD_CONST               3 (True)
              LOAD_CONST              21 (('timezone',))
              CALL_KW                  1
              LOAD_CONST               3 (True)
              LOAD_CONST              11 (('nullable',))
              CALL_KW                  3

302           LOAD_GLOBAL              4 (sa)
              LOAD_ATTR                6 (Column)
              PUSH_NULL
              LOAD_CONST              97 ('preview_payload')
              LOAD_GLOBAL             31 (JSONB + NULL)
              CALL                     0
              LOAD_CONST               3 (True)
              LOAD_CONST              11 (('nullable',))
              CALL_KW                  3

303           LOAD_GLOBAL              4 (sa)
              LOAD_ATTR                6 (Column)
              PUSH_NULL

304           LOAD_CONST              20 ('created_at')

305           LOAD_GLOBAL              4 (sa)
              LOAD_ATTR               20 (DateTime)
              PUSH_NULL
              LOAD_CONST               3 (True)
              LOAD_CONST              21 (('timezone',))
              CALL_KW                  1

306           LOAD_CONST              10 (False)

307           LOAD_GLOBAL              4 (sa)
              LOAD_ATTR               22 (text)
              PUSH_NULL
              LOAD_CONST              22 ('now()')
              CALL                     1

303           LOAD_CONST              23 (('nullable', 'server_default'))
              CALL_KW                  4

309           LOAD_GLOBAL              4 (sa)
              LOAD_ATTR               24 (UniqueConstraint)
              PUSH_NULL
              LOAD_CONST              33 ('call_id')
              LOAD_CONST              98 ('uq_handoff_offers_call')
              LOAD_CONST              26 (('name',))
              CALL_KW                  2

310           LOAD_GLOBAL              4 (sa)
              LOAD_ATTR               28 (CheckConstraint)
              PUSH_NULL

311           LOAD_CONST              99 ("status IN ('offered', 'accepted', 'declined', 'expired')")

312           LOAD_CONST             100 ('ck_handoff_offers_status')

310           LOAD_CONST              26 (('name',))
              CALL_KW                  2

314           LOAD_GLOBAL              4 (sa)
              LOAD_ATTR               28 (CheckConstraint)
              PUSH_NULL

315           LOAD_CONST             101 ("offer_reason IS NULL OR offer_reason IN ('vip', 'urgent', 'vip_and_urgent')")

316           LOAD_CONST             102 ('ck_handoff_offers_reason')

314           LOAD_CONST              26 (('name',))
              CALL_KW                  2

271           CALL                    15
              POP_TOP

319           LOAD_GLOBAL              0 (op)
              LOAD_ATTR               26 (create_index)
              PUSH_NULL

320           LOAD_CONST             103 ('handoff_offers_user_idx')
              LOAD_CONST              90 ('handoff_offers')
              LOAD_CONST               6 ('owner_user_id')
              BUILD_LIST               1

319           CALL                     3
              POP_TOP

322           LOAD_GLOBAL              0 (op)
              LOAD_ATTR               26 (create_index)
              PUSH_NULL

323           LOAD_CONST             104 ('handoff_offers_pending_idx')

324           LOAD_CONST              90 ('handoff_offers')

325           LOAD_CONST              40 ('status')
              LOAD_CONST              93 ('expires_at')
              BUILD_LIST               2

326           LOAD_GLOBAL              4 (sa)
              LOAD_ATTR               22 (text)
              PUSH_NULL
              LOAD_CONST             105 ("status = 'offered'")
              CALL                     1

322           LOAD_CONST              48 (('postgresql_where',))
              CALL_KW                  4
              POP_TOP

332           LOAD_GLOBAL              0 (op)
              LOAD_ATTR                2 (create_table)
              PUSH_NULL

333           LOAD_CONST             106 ('handoff_suppressions')

334           LOAD_GLOBAL              4 (sa)
              LOAD_ATTR                6 (Column)
              PUSH_NULL
              LOAD_CONST               2 ('id')
              LOAD_GLOBAL              9 (UUID + NULL)
              LOAD_CONST               3 (True)
              LOAD_CONST               4 (('as_uuid',))
              CALL_KW                  1
              LOAD_CONST               3 (True)
              LOAD_CONST               5 (('primary_key',))
              CALL_KW                  3

335           LOAD_GLOBAL              4 (sa)
              LOAD_ATTR                6 (Column)
              PUSH_NULL

336           LOAD_CONST               6 ('owner_user_id')

337           LOAD_GLOBAL              9 (UUID + NULL)
              LOAD_CONST               3 (True)
              LOAD_CONST               4 (('as_uuid',))
              CALL_KW                  1

338           LOAD_GLOBAL              4 (sa)
              LOAD_ATTR               10 (ForeignKey)
              PUSH_NULL
              LOAD_CONST               7 ('users.id')
              LOAD_CONST               8 ('CASCADE')
              LOAD_CONST               9 (('ondelete',))
              CALL_KW                  2

339           LOAD_CONST              10 (False)

335           LOAD_CONST              11 (('nullable',))
              CALL_KW                  4

341           LOAD_GLOBAL              4 (sa)
              LOAD_ATTR                6 (Column)
              PUSH_NULL
              LOAD_CONST             107 ('destination_phone_hash')
              LOAD_GLOBAL              4 (sa)
              LOAD_ATTR               16 (String)
              PUSH_NULL
              LOAD_CONST              16 (64)
              CALL                     1
              LOAD_CONST              10 (False)
              LOAD_CONST              11 (('nullable',))
              CALL_KW                  3

342           LOAD_GLOBAL              4 (sa)
              LOAD_ATTR                6 (Column)
              PUSH_NULL

343           LOAD_CONST             108 ('suppression_expires_at')

344           LOAD_GLOBAL              4 (sa)
              LOAD_ATTR               20 (DateTime)
              PUSH_NULL
              LOAD_CONST               3 (True)
              LOAD_CONST              21 (('timezone',))
              CALL_KW                  1

345           LOAD_CONST              10 (False)

342           LOAD_CONST              11 (('nullable',))
              CALL_KW                  3

347           LOAD_GLOBAL              4 (sa)
              LOAD_ATTR                6 (Column)
              PUSH_NULL
              LOAD_CONST              29 ('reason')
              LOAD_GLOBAL              4 (sa)
              LOAD_ATTR               18 (Text)
              PUSH_NULL
              CALL                     0
              LOAD_CONST               3 (True)
              LOAD_CONST              11 (('nullable',))
              CALL_KW                  3

348           LOAD_GLOBAL              4 (sa)
              LOAD_ATTR                6 (Column)
              PUSH_NULL

349           LOAD_CONST              20 ('created_at')

350           LOAD_GLOBAL              4 (sa)
              LOAD_ATTR               20 (DateTime)
              PUSH_NULL
              LOAD_CONST               3 (True)
              LOAD_CONST              21 (('timezone',))
              CALL_KW                  1

351           LOAD_CONST              10 (False)

352           LOAD_GLOBAL              4 (sa)
              LOAD_ATTR               22 (text)
              PUSH_NULL
              LOAD_CONST              22 ('now()')
              CALL                     1

348           LOAD_CONST              23 (('nullable', 'server_default'))
              CALL_KW                  4

332           CALL                     7
              POP_TOP

355           LOAD_GLOBAL              0 (op)
              LOAD_ATTR               26 (create_index)
              PUSH_NULL

356           LOAD_CONST             109 ('handoff_suppressions_user_dest_idx')

357           LOAD_CONST             106 ('handoff_suppressions')

358           LOAD_CONST               6 ('owner_user_id')
              LOAD_CONST             107 ('destination_phone_hash')
              BUILD_LIST               2

355           CALL                     3
              POP_TOP

364           LOAD_GLOBAL              0 (op)
              LOAD_ATTR               32 (add_column)
              PUSH_NULL

365           LOAD_CONST             110 ('calls')

366           LOAD_GLOBAL              4 (sa)
              LOAD_ATTR                6 (Column)
              PUSH_NULL

367           LOAD_CONST             111 ('handoff_eligible')

368           LOAD_GLOBAL              4 (sa)
              LOAD_ATTR               34 (Boolean)
              PUSH_NULL
              CALL                     0

369           LOAD_CONST              10 (False)

370           LOAD_GLOBAL              4 (sa)
              LOAD_ATTR               22 (text)
              PUSH_NULL
              LOAD_CONST             112 ('false')
              CALL                     1

366           LOAD_CONST              23 (('nullable', 'server_default'))
              CALL_KW                  4

364           CALL                     2
              POP_TOP

373           LOAD_GLOBAL              0 (op)
              LOAD_ATTR               32 (add_column)
              PUSH_NULL

374           LOAD_CONST             110 ('calls')

375           LOAD_GLOBAL              4 (sa)
              LOAD_ATTR                6 (Column)
              PUSH_NULL
              LOAD_CONST             113 ('handoff_status')
              LOAD_GLOBAL              4 (sa)
              LOAD_ATTR               18 (Text)
              PUSH_NULL
              CALL                     0
              LOAD_CONST               3 (True)
              LOAD_CONST              11 (('nullable',))
              CALL_KW                  3

373           CALL                     2
              POP_TOP

377           LOAD_GLOBAL              0 (op)
              LOAD_ATTR               32 (add_column)
              PUSH_NULL

378           LOAD_CONST             110 ('calls')

379           LOAD_GLOBAL              4 (sa)
              LOAD_ATTR                6 (Column)
              PUSH_NULL
              LOAD_CONST             114 ('handoff_offered_at')
              LOAD_GLOBAL              4 (sa)
              LOAD_ATTR               20 (DateTime)
              PUSH_NULL
              LOAD_CONST               3 (True)
              LOAD_CONST              21 (('timezone',))
              CALL_KW                  1
              LOAD_CONST               3 (True)
              LOAD_CONST              11 (('nullable',))
              CALL_KW                  3

377           CALL                     2
              POP_TOP

381           LOAD_GLOBAL              0 (op)
              LOAD_ATTR               32 (add_column)
              PUSH_NULL

382           LOAD_CONST             110 ('calls')

383           LOAD_GLOBAL              4 (sa)
              LOAD_ATTR                6 (Column)
              PUSH_NULL

384           LOAD_CONST             115 ('handoff_offer_expires_at')

385           LOAD_GLOBAL              4 (sa)
              LOAD_ATTR               20 (DateTime)
              PUSH_NULL
              LOAD_CONST               3 (True)
              LOAD_CONST              21 (('timezone',))
              CALL_KW                  1

386           LOAD_CONST               3 (True)

383           LOAD_CONST              11 (('nullable',))
              CALL_KW                  3

381           CALL                     2
              POP_TOP

389           LOAD_GLOBAL              0 (op)
              LOAD_ATTR               32 (add_column)
              PUSH_NULL

390           LOAD_CONST             110 ('calls')

391           LOAD_GLOBAL              4 (sa)
              LOAD_ATTR                6 (Column)
              PUSH_NULL
              LOAD_CONST             116 ('handoff_accepted_at')
              LOAD_GLOBAL              4 (sa)
              LOAD_ATTR               20 (DateTime)
              PUSH_NULL
              LOAD_CONST               3 (True)
              LOAD_CONST              21 (('timezone',))
              CALL_KW                  1
              LOAD_CONST               3 (True)
              LOAD_CONST              11 (('nullable',))
              CALL_KW                  3

389           CALL                     2
              POP_TOP

393           LOAD_GLOBAL              0 (op)
              LOAD_ATTR               32 (add_column)
              PUSH_NULL

394           LOAD_CONST             110 ('calls')

395           LOAD_GLOBAL              4 (sa)
              LOAD_ATTR                6 (Column)
              PUSH_NULL
              LOAD_CONST             117 ('handoff_selected_device_id')
              LOAD_GLOBAL              9 (UUID + NULL)
              LOAD_CONST               3 (True)
              LOAD_CONST               4 (('as_uuid',))
              CALL_KW                  1
              LOAD_CONST               3 (True)
              LOAD_CONST              11 (('nullable',))
              CALL_KW                  3

393           CALL                     2
              POP_TOP

397           LOAD_GLOBAL              0 (op)
              LOAD_ATTR               32 (add_column)
              PUSH_NULL

398           LOAD_CONST             110 ('calls')

399           LOAD_GLOBAL              4 (sa)
              LOAD_ATTR                6 (Column)
              PUSH_NULL

400           LOAD_CONST             118 ('handoff_attempt_count')

401           LOAD_GLOBAL              4 (sa)
              LOAD_ATTR               14 (Integer)
              PUSH_NULL
              CALL                     0

402           LOAD_CONST              10 (False)

403           LOAD_GLOBAL              4 (sa)
              LOAD_ATTR               22 (text)
              PUSH_NULL
              LOAD_CONST              79 ('0')
              CALL                     1

399           LOAD_CONST              23 (('nullable', 'server_default'))
              CALL_KW                  4

397           CALL                     2
              POP_TOP

406           LOAD_GLOBAL              0 (op)
              LOAD_ATTR               32 (add_column)
              PUSH_NULL

407           LOAD_CONST             110 ('calls')

408           LOAD_GLOBAL              4 (sa)
              LOAD_ATTR                6 (Column)
              PUSH_NULL
              LOAD_CONST             119 ('handoff_failure_reason')
              LOAD_GLOBAL              4 (sa)
              LOAD_ATTR               18 (Text)
              PUSH_NULL
              CALL                     0
              LOAD_CONST               3 (True)
              LOAD_CONST              11 (('nullable',))
              CALL_KW                  3

406           CALL                     2
              POP_TOP

410           LOAD_GLOBAL              0 (op)
              LOAD_ATTR               32 (add_column)
              PUSH_NULL

411           LOAD_CONST             110 ('calls')

412           LOAD_GLOBAL              4 (sa)
              LOAD_ATTR                6 (Column)
              PUSH_NULL

413           LOAD_CONST             120 ('handoff_loop_detected')

414           LOAD_GLOBAL              4 (sa)
              LOAD_ATTR               34 (Boolean)
              PUSH_NULL
              CALL                     0

415           LOAD_CONST              10 (False)

416           LOAD_GLOBAL              4 (sa)
              LOAD_ATTR               22 (text)
              PUSH_NULL
              LOAD_CONST             112 ('false')
              CALL                     1

412           LOAD_CONST              23 (('nullable', 'server_default'))
              CALL_KW                  4

410           CALL                     2
              POP_TOP

419           LOAD_GLOBAL              0 (op)
              LOAD_ATTR               36 (create_check_constraint)
              PUSH_NULL

420           LOAD_CONST             121 ('ck_calls_handoff_status')

421           LOAD_CONST             110 ('calls')

422           LOAD_CONST             122 ("handoff_status IS NULL OR handoff_status IN ('not_applicable', 'eligible_pending_minimum_data', 'offered', 'accepted', 'declined', 'expired', 'transfer_starting', 'transfer_connected', 'transfer_failed', 'transfer_cancelled')")

419           CALL                     3
              POP_TOP

427           LOAD_GLOBAL              0 (op)
              LOAD_ATTR               26 (create_index)
              PUSH_NULL

428           LOAD_CONST             123 ('calls_retention_idx')

429           LOAD_CONST             110 ('calls')

430           LOAD_CONST             124 ('retention_expires_at')
              BUILD_LIST               1

431           LOAD_GLOBAL              4 (sa)
              LOAD_ATTR               22 (text)
              PUSH_NULL
              LOAD_CONST             125 ('deleted_at IS NULL')
              CALL                     1

427           LOAD_CONST              48 (('postgresql_where',))
              CALL_KW                  4
              POP_TOP

437           LOAD_GLOBAL              0 (op)
              LOAD_ATTR               32 (add_column)
              PUSH_NULL

438           LOAD_CONST             126 ('user_settings')

439           LOAD_GLOBAL              4 (sa)
              LOAD_ATTR                6 (Column)
              PUSH_NULL

440           LOAD_CONST             127 ('handoff_enabled')

441           LOAD_GLOBAL              4 (sa)
              LOAD_ATTR               34 (Boolean)
              PUSH_NULL
              CALL                     0

442           LOAD_CONST              10 (False)

443           LOAD_GLOBAL              4 (sa)
              LOAD_ATTR               22 (text)
              PUSH_NULL
              LOAD_CONST             112 ('false')
              CALL                     1

439           LOAD_CONST              23 (('nullable', 'server_default'))
              CALL_KW                  4

437           CALL                     2
              POP_TOP

446           LOAD_GLOBAL              0 (op)
              LOAD_ATTR               32 (add_column)
              PUSH_NULL

447           LOAD_CONST             126 ('user_settings')

448           LOAD_GLOBAL              4 (sa)
              LOAD_ATTR                6 (Column)
              PUSH_NULL

449           LOAD_CONST             128 ('handoff_trigger')

450           LOAD_GLOBAL              4 (sa)
              LOAD_ATTR               16 (String)
              PUSH_NULL
              LOAD_CONST              41 (20)
              CALL                     1

451           LOAD_CONST              10 (False)

452           LOAD_GLOBAL              4 (sa)
              LOAD_ATTR               22 (text)
              PUSH_NULL
              LOAD_CONST             129 ("'vip_only'")
              CALL                     1

448           LOAD_CONST              23 (('nullable', 'server_default'))
              CALL_KW                  4

446           CALL                     2
              POP_TOP

455           LOAD_GLOBAL              0 (op)
              LOAD_ATTR               32 (add_column)
              PUSH_NULL

456           LOAD_CONST             126 ('user_settings')

457           LOAD_GLOBAL              4 (sa)
              LOAD_ATTR                6 (Column)
              PUSH_NULL

458           LOAD_CONST             130 ('handoff_offer_timeout_seconds')

459           LOAD_GLOBAL              4 (sa)
              LOAD_ATTR               14 (Integer)
              PUSH_NULL
              CALL                     0

460           LOAD_CONST              10 (False)

461           LOAD_GLOBAL              4 (sa)
              LOAD_ATTR               22 (text)
              PUSH_NULL
              LOAD_CONST             131 ('20')
              CALL                     1

457           LOAD_CONST              23 (('nullable', 'server_default'))
              CALL_KW                  4

455           CALL                     2
              POP_TOP

464           LOAD_GLOBAL              0 (op)
              LOAD_ATTR               32 (add_column)
              PUSH_NULL

465           LOAD_CONST             126 ('user_settings')

466           LOAD_GLOBAL              4 (sa)
              LOAD_ATTR                6 (Column)
              PUSH_NULL

467           LOAD_CONST             132 ('business_hours_enabled')

468           LOAD_GLOBAL              4 (sa)
              LOAD_ATTR               34 (Boolean)
              PUSH_NULL
              CALL                     0

469           LOAD_CONST              10 (False)

470           LOAD_GLOBAL              4 (sa)
              LOAD_ATTR               22 (text)
              PUSH_NULL
              LOAD_CONST             112 ('false')
              CALL                     1

466           LOAD_CONST              23 (('nullable', 'server_default'))
              CALL_KW                  4

464           CALL                     2
              POP_TOP

473           LOAD_GLOBAL              0 (op)
              LOAD_ATTR               32 (add_column)
              PUSH_NULL

474           LOAD_CONST             126 ('user_settings')

475           LOAD_GLOBAL              4 (sa)
              LOAD_ATTR                6 (Column)
              PUSH_NULL
              LOAD_CONST             133 ('business_hours_start')
              LOAD_GLOBAL              4 (sa)
              LOAD_ATTR               38 (Time)
              PUSH_NULL
              CALL                     0
              LOAD_CONST               3 (True)
              LOAD_CONST              11 (('nullable',))
              CALL_KW                  3

473           CALL                     2
              POP_TOP

477           LOAD_GLOBAL              0 (op)
              LOAD_ATTR               32 (add_column)
              PUSH_NULL

478           LOAD_CONST             126 ('user_settings')

479           LOAD_GLOBAL              4 (sa)
              LOAD_ATTR                6 (Column)
              PUSH_NULL
              LOAD_CONST             134 ('business_hours_end')
              LOAD_GLOBAL              4 (sa)
              LOAD_ATTR               38 (Time)
              PUSH_NULL
              CALL                     0
              LOAD_CONST               3 (True)
              LOAD_CONST              11 (('nullable',))
              CALL_KW                  3

477           CALL                     2
              POP_TOP

481           LOAD_GLOBAL              0 (op)
              LOAD_ATTR               32 (add_column)
              PUSH_NULL

482           LOAD_CONST             126 ('user_settings')

483           LOAD_GLOBAL              4 (sa)
              LOAD_ATTR                6 (Column)
              PUSH_NULL

484           LOAD_CONST             135 ('business_hours_days')

485           LOAD_GLOBAL             31 (JSONB + NULL)
              CALL                     0

486           LOAD_CONST              10 (False)

487           LOAD_GLOBAL              4 (sa)
              LOAD_ATTR               22 (text)
              PUSH_NULL
              LOAD_CONST             136 ("'[]'::jsonb")
              CALL                     1

483           LOAD_CONST              23 (('nullable', 'server_default'))
              CALL_KW                  4

481           CALL                     2
              POP_TOP

490           LOAD_GLOBAL              0 (op)
              LOAD_ATTR               32 (add_column)
              PUSH_NULL

491           LOAD_CONST             126 ('user_settings')

492           LOAD_GLOBAL              4 (sa)
              LOAD_ATTR                6 (Column)
              PUSH_NULL

493           LOAD_CONST             137 ('after_hours_behavior')

494           LOAD_GLOBAL              4 (sa)
              LOAD_ATTR               16 (String)
              PUSH_NULL
              LOAD_CONST             138 (40)
              CALL                     1

495           LOAD_CONST              10 (False)

496           LOAD_GLOBAL              4 (sa)
              LOAD_ATTR               22 (text)
              PUSH_NULL
              LOAD_CONST             139 ("'screen_normally'")
              CALL                     1

492           LOAD_CONST              23 (('nullable', 'server_default'))
              CALL_KW                  4

490           CALL                     2
              POP_TOP

499           LOAD_GLOBAL              0 (op)
              LOAD_ATTR               32 (add_column)
              PUSH_NULL

500           LOAD_CONST             126 ('user_settings')

501           LOAD_GLOBAL              4 (sa)
              LOAD_ATTR                6 (Column)
              PUSH_NULL

502           LOAD_CONST             140 ('temperament_preset')

503           LOAD_GLOBAL              4 (sa)
              LOAD_ATTR               16 (String)
              PUSH_NULL
              LOAD_CONST             138 (40)
              CALL                     1

504           LOAD_CONST              10 (False)

505           LOAD_GLOBAL              4 (sa)
              LOAD_ATTR               22 (text)
              PUSH_NULL
              LOAD_CONST             141 ("'professional_polite'")
              CALL                     1

501           LOAD_CONST              23 (('nullable', 'server_default'))
              CALL_KW                  4

499           CALL                     2
              POP_TOP

508           LOAD_GLOBAL              0 (op)
              LOAD_ATTR               32 (add_column)
              PUSH_NULL

509           LOAD_CONST             126 ('user_settings')

510           LOAD_GLOBAL              4 (sa)
              LOAD_ATTR                6 (Column)
              PUSH_NULL

511           LOAD_CONST             142 ('swearing_rule')

512           LOAD_GLOBAL              4 (sa)
              LOAD_ATTR               16 (String)
              PUSH_NULL
              LOAD_CONST              41 (20)
              CALL                     1

513           LOAD_CONST              10 (False)

514           LOAD_GLOBAL              4 (sa)
              LOAD_ATTR               22 (text)
              PUSH_NULL
              LOAD_CONST             143 ("'no_swearing'")
              CALL                     1

510           LOAD_CONST              23 (('nullable', 'server_default'))
              CALL_KW                  4

508           CALL                     2
              POP_TOP

517           LOAD_GLOBAL              0 (op)
              LOAD_ATTR               32 (add_column)
              PUSH_NULL

518           LOAD_CONST             126 ('user_settings')

519           LOAD_GLOBAL              4 (sa)
              LOAD_ATTR                6 (Column)
              PUSH_NULL

520           LOAD_CONST             144 ('language_primary')

521           LOAD_GLOBAL              4 (sa)
              LOAD_ATTR               16 (String)
              PUSH_NULL
              LOAD_CONST             145 (10)
              CALL                     1

522           LOAD_CONST              10 (False)

523           LOAD_GLOBAL              4 (sa)
              LOAD_ATTR               22 (text)
              PUSH_NULL
              LOAD_CONST             146 ("'en'")
              CALL                     1

519           LOAD_CONST              23 (('nullable', 'server_default'))
              CALL_KW                  4

517           CALL                     2
              POP_TOP

526           LOAD_GLOBAL              0 (op)
              LOAD_ATTR               32 (add_column)
              PUSH_NULL

527           LOAD_CONST             126 ('user_settings')

528           LOAD_GLOBAL              4 (sa)
              LOAD_ATTR                6 (Column)
              PUSH_NULL
              LOAD_CONST             147 ('language_secondary')
              LOAD_GLOBAL              4 (sa)
              LOAD_ATTR               16 (String)
              PUSH_NULL
              LOAD_CONST             145 (10)
              CALL                     1
              LOAD_CONST               3 (True)
              LOAD_CONST              11 (('nullable',))
              CALL_KW                  3

526           CALL                     2
              POP_TOP

530           LOAD_GLOBAL              0 (op)
              LOAD_ATTR               32 (add_column)
              PUSH_NULL

531           LOAD_CONST             126 ('user_settings')

532           LOAD_GLOBAL              4 (sa)
              LOAD_ATTR                6 (Column)
              PUSH_NULL

533           LOAD_CONST             148 ('vip_calls_mark_important')

534           LOAD_GLOBAL              4 (sa)
              LOAD_ATTR               34 (Boolean)
              PUSH_NULL
              CALL                     0

535           LOAD_CONST              10 (False)

536           LOAD_GLOBAL              4 (sa)
              LOAD_ATTR               22 (text)
              PUSH_NULL
              LOAD_CONST             149 ('true')
              CALL                     1

532           LOAD_CONST              23 (('nullable', 'server_default'))
              CALL_KW                  4

530           CALL                     2
              POP_TOP

539           LOAD_GLOBAL              0 (op)
              LOAD_ATTR               32 (add_column)
              PUSH_NULL

540           LOAD_CONST             126 ('user_settings')

541           LOAD_GLOBAL              4 (sa)
              LOAD_ATTR                6 (Column)
              PUSH_NULL

542           LOAD_CONST             150 ('vip_notification_intensity')

543           LOAD_GLOBAL              4 (sa)
              LOAD_ATTR               16 (String)
              PUSH_NULL
              LOAD_CONST             145 (10)
              CALL                     1

544           LOAD_CONST              10 (False)

545           LOAD_GLOBAL              4 (sa)
              LOAD_ATTR               22 (text)
              PUSH_NULL
              LOAD_CONST              52 ("'normal'")
              CALL                     1

541           LOAD_CONST              23 (('nullable', 'server_default'))
              CALL_KW                  4

539           CALL                     2
              POP_TOP

548           LOAD_GLOBAL              0 (op)
              LOAD_ATTR               32 (add_column)
              PUSH_NULL

549           LOAD_CONST             126 ('user_settings')

550           LOAD_GLOBAL              4 (sa)
              LOAD_ATTR                6 (Column)
              PUSH_NULL

551           LOAD_CONST             151 ('blocked_caller_behavior')

552           LOAD_GLOBAL              4 (sa)
              LOAD_ATTR               16 (String)
              PUSH_NULL
              LOAD_CONST             152 (30)
              CALL                     1

553           LOAD_CONST              10 (False)

554           LOAD_GLOBAL              4 (sa)
              LOAD_ATTR               22 (text)
              PUSH_NULL
              LOAD_CONST             153 ("'end_immediately'")
              CALL                     1

550           LOAD_CONST              23 (('nullable', 'server_default'))
              CALL_KW                  4

548           CALL                     2
              POP_TOP

557           LOAD_GLOBAL              0 (op)
              LOAD_ATTR               32 (add_column)
              PUSH_NULL

558           LOAD_CONST             126 ('user_settings')

559           LOAD_GLOBAL              4 (sa)
              LOAD_ATTR                6 (Column)
              PUSH_NULL

560           LOAD_CONST             154 ('log_blocked_attempts')

561           LOAD_GLOBAL              4 (sa)
              LOAD_ATTR               34 (Boolean)
              PUSH_NULL
              CALL                     0

562           LOAD_CONST              10 (False)

563           LOAD_GLOBAL              4 (sa)
              LOAD_ATTR               22 (text)
              PUSH_NULL
              LOAD_CONST             112 ('false')
              CALL                     1

559           LOAD_CONST              23 (('nullable', 'server_default'))
              CALL_KW                  4

557           CALL                     2
              POP_TOP

566           LOAD_GLOBAL              0 (op)
              LOAD_ATTR               32 (add_column)
              PUSH_NULL

567           LOAD_CONST             126 ('user_settings')

568           LOAD_GLOBAL              4 (sa)
              LOAD_ATTR                6 (Column)
              PUSH_NULL

569           LOAD_CONST             155 ('notify_on_blocked')

570           LOAD_GLOBAL              4 (sa)
              LOAD_ATTR               34 (Boolean)
              PUSH_NULL
              CALL                     0

571           LOAD_CONST              10 (False)

572           LOAD_GLOBAL              4 (sa)
              LOAD_ATTR               22 (text)
              PUSH_NULL
              LOAD_CONST             112 ('false')
              CALL                     1

568           LOAD_CONST              23 (('nullable', 'server_default'))
              CALL_KW                  4

566           CALL                     2
              POP_TOP

575           LOAD_GLOBAL              0 (op)
              LOAD_ATTR               32 (add_column)
              PUSH_NULL

576           LOAD_CONST             126 ('user_settings')

577           LOAD_GLOBAL              4 (sa)
              LOAD_ATTR                6 (Column)
              PUSH_NULL

578           LOAD_CONST             156 ('spam_labeling_enabled')

579           LOAD_GLOBAL              4 (sa)
              LOAD_ATTR               34 (Boolean)
              PUSH_NULL
              CALL                     0

580           LOAD_CONST              10 (False)

581           LOAD_GLOBAL              4 (sa)
              LOAD_ATTR               22 (text)
              PUSH_NULL
              LOAD_CONST             149 ('true')
              CALL                     1

577           LOAD_CONST              23 (('nullable', 'server_default'))
              CALL_KW                  4

575           CALL                     2
              POP_TOP

584           LOAD_GLOBAL              0 (op)
              LOAD_ATTR               32 (add_column)
              PUSH_NULL

585           LOAD_CONST             126 ('user_settings')

586           LOAD_GLOBAL              4 (sa)
              LOAD_ATTR                6 (Column)
              PUSH_NULL

587           LOAD_CONST             157 ('block_suggestions_enabled')

588           LOAD_GLOBAL              4 (sa)
              LOAD_ATTR               34 (Boolean)
              PUSH_NULL
              CALL                     0

589           LOAD_CONST              10 (False)

590           LOAD_GLOBAL              4 (sa)
              LOAD_ATTR               22 (text)
              PUSH_NULL
              LOAD_CONST             149 ('true')
              CALL                     1

586           LOAD_CONST              23 (('nullable', 'server_default'))
              CALL_KW                  4

584           CALL                     2
              POP_TOP

593           LOAD_GLOBAL              0 (op)
              LOAD_ATTR               32 (add_column)
              PUSH_NULL

594           LOAD_CONST             126 ('user_settings')

595           LOAD_GLOBAL              4 (sa)
              LOAD_ATTR                6 (Column)
              PUSH_NULL

596           LOAD_CONST             158 ('repeat_caller_threshold')

597           LOAD_GLOBAL              4 (sa)
              LOAD_ATTR               14 (Integer)
              PUSH_NULL
              CALL                     0

598           LOAD_CONST              10 (False)

599           LOAD_GLOBAL              4 (sa)
              LOAD_ATTR               22 (text)
              PUSH_NULL
              LOAD_CONST             159 ('3')
              CALL                     1

595           LOAD_CONST              23 (('nullable', 'server_default'))
              CALL_KW                  4

593           CALL                     2
              POP_TOP

602           LOAD_GLOBAL              0 (op)
              LOAD_ATTR               32 (add_column)
              PUSH_NULL

603           LOAD_CONST             126 ('user_settings')

604           LOAD_GLOBAL              4 (sa)
              LOAD_ATTR                6 (Column)
              PUSH_NULL

605           LOAD_CONST             160 ('text_approval_mode')

606           LOAD_GLOBAL              4 (sa)
              LOAD_ATTR               16 (String)
              PUSH_NULL
              LOAD_CONST              41 (20)
              CALL                     1

607           LOAD_CONST              10 (False)

608           LOAD_GLOBAL              4 (sa)
              LOAD_ATTR               22 (text)
              PUSH_NULL
              LOAD_CONST             161 ("'always_approve'")
              CALL                     1

604           LOAD_CONST              23 (('nullable', 'server_default'))
              CALL_KW                  4

602           CALL                     2
              POP_TOP

611           LOAD_GLOBAL              0 (op)
              LOAD_ATTR               32 (add_column)
              PUSH_NULL

612           LOAD_CONST             126 ('user_settings')

613           LOAD_GLOBAL              4 (sa)
              LOAD_ATTR                6 (Column)
              PUSH_NULL

614           LOAD_CONST             162 ('assistant_name')

615           LOAD_GLOBAL              4 (sa)
              LOAD_ATTR               16 (String)
              PUSH_NULL
              LOAD_CONST             163 (60)
              CALL                     1

616           LOAD_CONST              10 (False)

617           LOAD_GLOBAL              4 (sa)
              LOAD_ATTR               22 (text)
              PUSH_NULL
              LOAD_CONST             164 ("'Alex'")
              CALL                     1

613           LOAD_CONST              23 (('nullable', 'server_default'))
              CALL_KW                  4

611           CALL                     2
              POP_TOP

620           LOAD_GLOBAL              0 (op)
              LOAD_ATTR               32 (add_column)
              PUSH_NULL

621           LOAD_CONST             126 ('user_settings')

622           LOAD_GLOBAL              4 (sa)
              LOAD_ATTR                6 (Column)
              PUSH_NULL

623           LOAD_CONST             165 ('greeting_template')

624           LOAD_GLOBAL              4 (sa)
              LOAD_ATTR               16 (String)
              PUSH_NULL
              LOAD_CONST             138 (40)
              CALL                     1

625           LOAD_CONST              10 (False)

626           LOAD_GLOBAL              4 (sa)
              LOAD_ATTR               22 (text)
              PUSH_NULL
              LOAD_CONST             166 ("'standard'")
              CALL                     1

622           LOAD_CONST              23 (('nullable', 'server_default'))
              CALL_KW                  4

620           CALL                     2
              POP_TOP

629           LOAD_GLOBAL              0 (op)
              LOAD_ATTR               32 (add_column)
              PUSH_NULL

630           LOAD_CONST             126 ('user_settings')

631           LOAD_GLOBAL              4 (sa)
              LOAD_ATTR                6 (Column)
              PUSH_NULL

632           LOAD_CONST             167 ('transcript_disclosure_mode')

633           LOAD_GLOBAL              4 (sa)
              LOAD_ATTR               16 (String)
              PUSH_NULL
              LOAD_CONST              41 (20)
              CALL                     1

634           LOAD_CONST              10 (False)

635           LOAD_GLOBAL              4 (sa)
              LOAD_ATTR               22 (text)
              PUSH_NULL
              LOAD_CONST             168 ("'ai_says_it'")
              CALL                     1

631           LOAD_CONST              23 (('nullable', 'server_default'))
              CALL_KW                  4

629           CALL                     2
              POP_TOP

638           LOAD_GLOBAL              0 (op)
              LOAD_ATTR               32 (add_column)
              PUSH_NULL

639           LOAD_CONST             126 ('user_settings')

640           LOAD_GLOBAL              4 (sa)
              LOAD_ATTR                6 (Column)
              PUSH_NULL

641           LOAD_CONST             169 ('recording_announcement_required')

642           LOAD_GLOBAL              4 (sa)
              LOAD_ATTR               34 (Boolean)
              PUSH_NULL
              CALL                     0

643           LOAD_CONST              10 (False)

644           LOAD_GLOBAL              4 (sa)
              LOAD_ATTR               22 (text)
              PUSH_NULL
              LOAD_CONST             149 ('true')
              CALL                     1

640           LOAD_CONST              23 (('nullable', 'server_default'))
              CALL_KW                  4

638           CALL                     2
              POP_TOP

647           LOAD_GLOBAL              0 (op)
              LOAD_ATTR               32 (add_column)
              PUSH_NULL

648           LOAD_CONST             126 ('user_settings')

649           LOAD_GLOBAL              4 (sa)
              LOAD_ATTR                6 (Column)
              PUSH_NULL

650           LOAD_CONST             170 ('important_rule')

651           LOAD_GLOBAL              4 (sa)
              LOAD_ATTR               16 (String)
              PUSH_NULL
              LOAD_CONST              41 (20)
              CALL                     1

652           LOAD_CONST              10 (False)

653           LOAD_GLOBAL              4 (sa)
              LOAD_ATTR               22 (text)
              PUSH_NULL
              LOAD_CONST             171 ("'vip_and_urgent'")
              CALL                     1

649           LOAD_CONST              23 (('nullable', 'server_default'))
              CALL_KW                  4

647           CALL                     2
              POP_TOP

656           LOAD_GLOBAL              0 (op)
              LOAD_ATTR               32 (add_column)
              PUSH_NULL

657           LOAD_CONST             126 ('user_settings')

658           LOAD_GLOBAL              4 (sa)
              LOAD_ATTR                6 (Column)
              PUSH_NULL

659           LOAD_CONST             172 ('biometric_policy')

660           LOAD_GLOBAL              4 (sa)
              LOAD_ATTR               16 (String)
              PUSH_NULL
              LOAD_CONST             152 (30)
              CALL                     1

661           LOAD_CONST              10 (False)

662           LOAD_GLOBAL              4 (sa)
              LOAD_ATTR               22 (text)
              PUSH_NULL
              LOAD_CONST             173 ("'gate_call_details'")
              CALL                     1

658           LOAD_CONST              23 (('nullable', 'server_default'))
              CALL_KW                  4

656           CALL                     2
              POP_TOP

667           LOAD_GLOBAL              0 (op)
              LOAD_ATTR               36 (create_check_constraint)
              PUSH_NULL

668           LOAD_CONST             174 ('ck_user_settings_handoff_trigger')

669           LOAD_CONST             126 ('user_settings')

670           LOAD_CONST             175 ("handoff_trigger IN ('vip_only', 'always', 'never')")

667           CALL                     3
              POP_TOP

672           LOAD_GLOBAL              0 (op)
              LOAD_ATTR               36 (create_check_constraint)
              PUSH_NULL

673           LOAD_CONST             176 ('ck_user_settings_handoff_timeout')

674           LOAD_CONST             126 ('user_settings')

675           LOAD_CONST             177 ('handoff_offer_timeout_seconds BETWEEN 10 AND 60')

672           CALL                     3
              POP_TOP

677           LOAD_GLOBAL              0 (op)
              LOAD_ATTR               36 (create_check_constraint)
              PUSH_NULL

678           LOAD_CONST             178 ('ck_user_settings_after_hours')

679           LOAD_CONST             126 ('user_settings')

680           LOAD_CONST             179 ("after_hours_behavior IN ('screen_normally', 'voicemail_only', 'reject')")

677           CALL                     3
              POP_TOP

682           LOAD_GLOBAL              0 (op)
              LOAD_ATTR               36 (create_check_constraint)
              PUSH_NULL

683           LOAD_CONST             180 ('ck_user_settings_temperament')

684           LOAD_CONST             126 ('user_settings')

685           LOAD_CONST             181 ("temperament_preset IN ('professional_polite', 'casual_friendly', 'formal', 'custom')")

682           CALL                     3
              POP_TOP

687           LOAD_GLOBAL              0 (op)
              LOAD_ATTR               36 (create_check_constraint)
              PUSH_NULL

688           LOAD_CONST             182 ('ck_user_settings_swearing')

689           LOAD_CONST             126 ('user_settings')

690           LOAD_CONST             183 ("swearing_rule IN ('no_swearing', 'mirror_caller', 'allow')")

687           CALL                     3
              POP_TOP

692           LOAD_GLOBAL              0 (op)
              LOAD_ATTR               36 (create_check_constraint)
              PUSH_NULL

693           LOAD_CONST             184 ('ck_user_settings_vip_notif')

694           LOAD_CONST             126 ('user_settings')

695           LOAD_CONST             185 ("vip_notification_intensity IN ('normal', 'high', 'urgent')")

692           CALL                     3
              POP_TOP

697           LOAD_GLOBAL              0 (op)
              LOAD_ATTR               36 (create_check_constraint)
              PUSH_NULL

698           LOAD_CONST             186 ('ck_user_settings_blocked_behavior')

699           LOAD_CONST             126 ('user_settings')

700           LOAD_CONST             187 ("blocked_caller_behavior IN ('end_immediately', 'play_message', 'silent_drop')")

697           CALL                     3
              POP_TOP

702           LOAD_GLOBAL              0 (op)
              LOAD_ATTR               36 (create_check_constraint)
              PUSH_NULL

703           LOAD_CONST             188 ('ck_user_settings_repeat_threshold')

704           LOAD_CONST             126 ('user_settings')

705           LOAD_CONST             189 ('repeat_caller_threshold BETWEEN 1 AND 10')

702           CALL                     3
              POP_TOP

707           LOAD_GLOBAL              0 (op)
              LOAD_ATTR               36 (create_check_constraint)
              PUSH_NULL

708           LOAD_CONST             190 ('ck_user_settings_text_approval')

709           LOAD_CONST             126 ('user_settings')

710           LOAD_CONST             191 ("text_approval_mode IN ('always_approve', 'auto_send', 'never')")

707           CALL                     3
              POP_TOP

712           LOAD_GLOBAL              0 (op)
              LOAD_ATTR               36 (create_check_constraint)
              PUSH_NULL

713           LOAD_CONST             192 ('ck_user_settings_greeting')

714           LOAD_CONST             126 ('user_settings')

715           LOAD_CONST             193 ("greeting_template IN ('standard', 'brief', 'formal', 'custom')")

712           CALL                     3
              POP_TOP

717           LOAD_GLOBAL              0 (op)
              LOAD_ATTR               36 (create_check_constraint)
              PUSH_NULL

718           LOAD_CONST             194 ('ck_user_settings_disclosure')

719           LOAD_CONST             126 ('user_settings')

720           LOAD_CONST             195 ("transcript_disclosure_mode IN ('ai_says_it', 'silent', 'beep')")

717           CALL                     3
              POP_TOP

722           LOAD_GLOBAL              0 (op)
              LOAD_ATTR               36 (create_check_constraint)
              PUSH_NULL

723           LOAD_CONST             196 ('ck_user_settings_important_rule')

724           LOAD_CONST             126 ('user_settings')

725           LOAD_CONST             197 ("important_rule IN ('vip_and_urgent', 'vip_only', 'urgent_only', 'all')")

722           CALL                     3
              POP_TOP

727           LOAD_GLOBAL              0 (op)
              LOAD_ATTR               36 (create_check_constraint)
              PUSH_NULL

728           LOAD_CONST             198 ('ck_user_settings_biometric_policy')

729           LOAD_CONST             126 ('user_settings')

730           LOAD_CONST             199 ("biometric_policy IN ('gate_call_details', 'gate_all', 'off')")

727           CALL                     3
              POP_TOP
              RETURN_CONST             0 (None)

Disassembly of <code object downgrade at 0x00000185C9A4A180, file "D:\fluence\Github\mattbot\backend\alembic\versions\015_phase1_completion.py", line 734>:
734           RESUME                   0

736           LOAD_GLOBAL              0 (op)
              LOAD_ATTR                2 (drop_constraint)
              PUSH_NULL
              LOAD_CONST               1 ('ck_user_settings_biometric_policy')
              LOAD_CONST               2 ('user_settings')
              LOAD_CONST               3 ('check')
              LOAD_CONST               4 (('type_',))
              CALL_KW                  3
              POP_TOP

737           LOAD_GLOBAL              0 (op)
              LOAD_ATTR                2 (drop_constraint)
              PUSH_NULL
              LOAD_CONST               5 ('ck_user_settings_important_rule')
              LOAD_CONST               2 ('user_settings')
              LOAD_CONST               3 ('check')
              LOAD_CONST               4 (('type_',))
              CALL_KW                  3
              POP_TOP

738           LOAD_GLOBAL              0 (op)
              LOAD_ATTR                2 (drop_constraint)
              PUSH_NULL
              LOAD_CONST               6 ('ck_user_settings_disclosure')
              LOAD_CONST               2 ('user_settings')
              LOAD_CONST               3 ('check')
              LOAD_CONST               4 (('type_',))
              CALL_KW                  3
              POP_TOP

739           LOAD_GLOBAL              0 (op)
              LOAD_ATTR                2 (drop_constraint)
              PUSH_NULL
              LOAD_CONST               7 ('ck_user_settings_greeting')
              LOAD_CONST               2 ('user_settings')
              LOAD_CONST               3 ('check')
              LOAD_CONST               4 (('type_',))
              CALL_KW                  3
              POP_TOP

740           LOAD_GLOBAL              0 (op)
              LOAD_ATTR                2 (drop_constraint)
              PUSH_NULL
              LOAD_CONST               8 ('ck_user_settings_text_approval')
              LOAD_CONST               2 ('user_settings')
              LOAD_CONST               3 ('check')
              LOAD_CONST               4 (('type_',))
              CALL_KW                  3
              POP_TOP

741           LOAD_GLOBAL              0 (op)
              LOAD_ATTR                2 (drop_constraint)
              PUSH_NULL
              LOAD_CONST               9 ('ck_user_settings_repeat_threshold')
              LOAD_CONST               2 ('user_settings')
              LOAD_CONST               3 ('check')
              LOAD_CONST               4 (('type_',))
              CALL_KW                  3
              POP_TOP

742           LOAD_GLOBAL              0 (op)
              LOAD_ATTR                2 (drop_constraint)
              PUSH_NULL
              LOAD_CONST              10 ('ck_user_settings_blocked_behavior')
              LOAD_CONST               2 ('user_settings')
              LOAD_CONST               3 ('check')
              LOAD_CONST               4 (('type_',))
              CALL_KW                  3
              POP_TOP

743           LOAD_GLOBAL              0 (op)
              LOAD_ATTR                2 (drop_constraint)
              PUSH_NULL
              LOAD_CONST              11 ('ck_user_settings_vip_notif')
              LOAD_CONST               2 ('user_settings')
              LOAD_CONST               3 ('check')
              LOAD_CONST               4 (('type_',))
              CALL_KW                  3
              POP_TOP

744           LOAD_GLOBAL              0 (op)
              LOAD_ATTR                2 (drop_constraint)
              PUSH_NULL
              LOAD_CONST              12 ('ck_user_settings_swearing')
              LOAD_CONST               2 ('user_settings')
              LOAD_CONST               3 ('check')
              LOAD_CONST               4 (('type_',))
              CALL_KW                  3
              POP_TOP

745           LOAD_GLOBAL              0 (op)
              LOAD_ATTR                2 (drop_constraint)
              PUSH_NULL
              LOAD_CONST              13 ('ck_user_settings_temperament')
              LOAD_CONST               2 ('user_settings')
              LOAD_CONST               3 ('check')
              LOAD_CONST               4 (('type_',))
              CALL_KW                  3
              POP_TOP

746           LOAD_GLOBAL              0 (op)
              LOAD_ATTR                2 (drop_constraint)
              PUSH_NULL
              LOAD_CONST              14 ('ck_user_settings_after_hours')
              LOAD_CONST               2 ('user_settings')
              LOAD_CONST               3 ('check')
              LOAD_CONST               4 (('type_',))
              CALL_KW                  3
              POP_TOP

747           LOAD_GLOBAL              0 (op)
              LOAD_ATTR                2 (drop_constraint)
              PUSH_NULL
              LOAD_CONST              15 ('ck_user_settings_handoff_timeout')
              LOAD_CONST               2 ('user_settings')
              LOAD_CONST               3 ('check')
              LOAD_CONST               4 (('type_',))
              CALL_KW                  3
              POP_TOP

748           LOAD_GLOBAL              0 (op)
              LOAD_ATTR                2 (drop_constraint)
              PUSH_NULL
              LOAD_CONST              16 ('ck_user_settings_handoff_trigger')
              LOAD_CONST               2 ('user_settings')
              LOAD_CONST               3 ('check')
              LOAD_CONST               4 (('type_',))
              CALL_KW                  3
              POP_TOP

751           LOAD_GLOBAL              0 (op)
              LOAD_ATTR                4 (drop_column)
              PUSH_NULL
              LOAD_CONST               2 ('user_settings')
              LOAD_CONST              17 ('biometric_policy')
              CALL                     2
              POP_TOP

752           LOAD_GLOBAL              0 (op)
              LOAD_ATTR                4 (drop_column)
              PUSH_NULL
              LOAD_CONST               2 ('user_settings')
              LOAD_CONST              18 ('important_rule')
              CALL                     2
              POP_TOP

753           LOAD_GLOBAL              0 (op)
              LOAD_ATTR                4 (drop_column)
              PUSH_NULL
              LOAD_CONST               2 ('user_settings')
              LOAD_CONST              19 ('recording_announcement_required')
              CALL                     2
              POP_TOP

754           LOAD_GLOBAL              0 (op)
              LOAD_ATTR                4 (drop_column)
              PUSH_NULL
              LOAD_CONST               2 ('user_settings')
              LOAD_CONST              20 ('transcript_disclosure_mode')
              CALL                     2
              POP_TOP

755           LOAD_GLOBAL              0 (op)
              LOAD_ATTR                4 (drop_column)
              PUSH_NULL
              LOAD_CONST               2 ('user_settings')
              LOAD_CONST              21 ('greeting_template')
              CALL                     2
              POP_TOP

756           LOAD_GLOBAL              0 (op)
              LOAD_ATTR                4 (drop_column)
              PUSH_NULL
              LOAD_CONST               2 ('user_settings')
              LOAD_CONST              22 ('assistant_name')
              CALL                     2
              POP_TOP

757           LOAD_GLOBAL              0 (op)
              LOAD_ATTR                4 (drop_column)
              PUSH_NULL
              LOAD_CONST               2 ('user_settings')
              LOAD_CONST              23 ('text_approval_mode')
              CALL                     2
              POP_TOP

758           LOAD_GLOBAL              0 (op)
              LOAD_ATTR                4 (drop_column)
              PUSH_NULL
              LOAD_CONST               2 ('user_settings')
              LOAD_CONST              24 ('repeat_caller_threshold')
              CALL                     2
              POP_TOP

759           LOAD_GLOBAL              0 (op)
              LOAD_ATTR                4 (drop_column)
              PUSH_NULL
              LOAD_CONST               2 ('user_settings')
              LOAD_CONST              25 ('block_suggestions_enabled')
              CALL                     2
              POP_TOP

760           LOAD_GLOBAL              0 (op)
              LOAD_ATTR                4 (drop_column)
              PUSH_NULL
              LOAD_CONST               2 ('user_settings')
              LOAD_CONST              26 ('spam_labeling_enabled')
              CALL                     2
              POP_TOP

761           LOAD_GLOBAL              0 (op)
              LOAD_ATTR                4 (drop_column)
              PUSH_NULL
              LOAD_CONST               2 ('user_settings')
              LOAD_CONST              27 ('notify_on_blocked')
              CALL                     2
              POP_TOP

762           LOAD_GLOBAL              0 (op)
              LOAD_ATTR                4 (drop_column)
              PUSH_NULL
              LOAD_CONST               2 ('user_settings')
              LOAD_CONST              28 ('log_blocked_attempts')
              CALL                     2
              POP_TOP

763           LOAD_GLOBAL              0 (op)
              LOAD_ATTR                4 (drop_column)
              PUSH_NULL
              LOAD_CONST               2 ('user_settings')
              LOAD_CONST              29 ('blocked_caller_behavior')
              CALL                     2
              POP_TOP

764           LOAD_GLOBAL              0 (op)
              LOAD_ATTR                4 (drop_column)
              PUSH_NULL
              LOAD_CONST               2 ('user_settings')
              LOAD_CONST              30 ('vip_notification_intensity')
              CALL                     2
              POP_TOP

765           LOAD_GLOBAL              0 (op)
              LOAD_ATTR                4 (drop_column)
              PUSH_NULL
              LOAD_CONST               2 ('user_settings')
              LOAD_CONST              31 ('vip_calls_mark_important')
              CALL                     2
              POP_TOP

766           LOAD_GLOBAL              0 (op)
              LOAD_ATTR                4 (drop_column)
              PUSH_NULL
              LOAD_CONST               2 ('user_settings')
              LOAD_CONST              32 ('language_secondary')
              CALL                     2
              POP_TOP

767           LOAD_GLOBAL              0 (op)
              LOAD_ATTR                4 (drop_column)
              PUSH_NULL
              LOAD_CONST               2 ('user_settings')
              LOAD_CONST              33 ('language_primary')
              CALL                     2
              POP_TOP

768           LOAD_GLOBAL              0 (op)
              LOAD_ATTR                4 (drop_column)
              PUSH_NULL
              LOAD_CONST               2 ('user_settings')
              LOAD_CONST              34 ('swearing_rule')
              CALL                     2
              POP_TOP

769           LOAD_GLOBAL              0 (op)
              LOAD_ATTR                4 (drop_column)
              PUSH_NULL
              LOAD_CONST               2 ('user_settings')
              LOAD_CONST              35 ('temperament_preset')
              CALL                     2
              POP_TOP

770           LOAD_GLOBAL              0 (op)
              LOAD_ATTR                4 (drop_column)
              PUSH_NULL
              LOAD_CONST               2 ('user_settings')
              LOAD_CONST              36 ('after_hours_behavior')
              CALL                     2
              POP_TOP

771           LOAD_GLOBAL              0 (op)
              LOAD_ATTR                4 (drop_column)
              PUSH_NULL
              LOAD_CONST               2 ('user_settings')
              LOAD_CONST              37 ('business_hours_days')
              CALL                     2
              POP_TOP

772           LOAD_GLOBAL              0 (op)
              LOAD_ATTR                4 (drop_column)
              PUSH_NULL
              LOAD_CONST               2 ('user_settings')
              LOAD_CONST              38 ('business_hours_end')
              CALL                     2
              POP_TOP

773           LOAD_GLOBAL              0 (op)
              LOAD_ATTR                4 (drop_column)
              PUSH_NULL
              LOAD_CONST               2 ('user_settings')
              LOAD_CONST              39 ('business_hours_start')
              CALL                     2
              POP_TOP

774           LOAD_GLOBAL              0 (op)
              LOAD_ATTR                4 (drop_column)
              PUSH_NULL
              LOAD_CONST               2 ('user_settings')
              LOAD_CONST              40 ('business_hours_enabled')
              CALL                     2
              POP_TOP

775           LOAD_GLOBAL              0 (op)
              LOAD_ATTR                4 (drop_column)
              PUSH_NULL
              LOAD_CONST               2 ('user_settings')
              LOAD_CONST              41 ('handoff_offer_timeout_seconds')
              CALL                     2
              POP_TOP

776           LOAD_GLOBAL              0 (op)
              LOAD_ATTR                4 (drop_column)
              PUSH_NULL
              LOAD_CONST               2 ('user_settings')
              LOAD_CONST              42 ('handoff_trigger')
              CALL                     2
              POP_TOP

777           LOAD_GLOBAL              0 (op)
              LOAD_ATTR                4 (drop_column)
              PUSH_NULL
              LOAD_CONST               2 ('user_settings')
              LOAD_CONST              43 ('handoff_enabled')
              CALL                     2
              POP_TOP

780           LOAD_GLOBAL              0 (op)
              LOAD_ATTR                6 (drop_index)
              PUSH_NULL
              LOAD_CONST              44 ('calls_retention_idx')
              LOAD_CONST              45 ('calls')
              LOAD_CONST              46 (('table_name',))
              CALL_KW                  2
              POP_TOP

781           LOAD_GLOBAL              0 (op)
              LOAD_ATTR                2 (drop_constraint)
              PUSH_NULL
              LOAD_CONST              47 ('ck_calls_handoff_status')
              LOAD_CONST              45 ('calls')
              LOAD_CONST               3 ('check')
              LOAD_CONST               4 (('type_',))
              CALL_KW                  3
              POP_TOP

782           LOAD_GLOBAL              0 (op)
              LOAD_ATTR                4 (drop_column)
              PUSH_NULL
              LOAD_CONST              45 ('calls')
              LOAD_CONST              48 ('handoff_loop_detected')
              CALL                     2
              POP_TOP

783           LOAD_GLOBAL              0 (op)
              LOAD_ATTR                4 (drop_column)
              PUSH_NULL
              LOAD_CONST              45 ('calls')
              LOAD_CONST              49 ('handoff_failure_reason')
              CALL                     2
              POP_TOP

784           LOAD_GLOBAL              0 (op)
              LOAD_ATTR                4 (drop_column)
              PUSH_NULL
              LOAD_CONST              45 ('calls')
              LOAD_CONST              50 ('handoff_attempt_count')
              CALL                     2
              POP_TOP

785           LOAD_GLOBAL              0 (op)
              LOAD_ATTR                4 (drop_column)
              PUSH_NULL
              LOAD_CONST              45 ('calls')
              LOAD_CONST              51 ('handoff_selected_device_id')
              CALL                     2
              POP_TOP

786           LOAD_GLOBAL              0 (op)
              LOAD_ATTR                4 (drop_column)
              PUSH_NULL
              LOAD_CONST              45 ('calls')
              LOAD_CONST              52 ('handoff_accepted_at')
              CALL                     2
              POP_TOP

787           LOAD_GLOBAL              0 (op)
              LOAD_ATTR                4 (drop_column)
              PUSH_NULL
              LOAD_CONST              45 ('calls')
              LOAD_CONST              53 ('handoff_offer_expires_at')
              CALL                     2
              POP_TOP

788           LOAD_GLOBAL              0 (op)
              LOAD_ATTR                4 (drop_column)
              PUSH_NULL
              LOAD_CONST              45 ('calls')
              LOAD_CONST              54 ('handoff_offered_at')
              CALL                     2
              POP_TOP

789           LOAD_GLOBAL              0 (op)
              LOAD_ATTR                4 (drop_column)
              PUSH_NULL
              LOAD_CONST              45 ('calls')
              LOAD_CONST              55 ('handoff_status')
              CALL                     2
              POP_TOP

790           LOAD_GLOBAL              0 (op)
              LOAD_ATTR                4 (drop_column)
              PUSH_NULL
              LOAD_CONST              45 ('calls')
              LOAD_CONST              56 ('handoff_eligible')
              CALL                     2
              POP_TOP

793           LOAD_GLOBAL              0 (op)
              LOAD_ATTR                8 (drop_table)
              PUSH_NULL
              LOAD_CONST              57 ('handoff_suppressions')
              CALL                     1
              POP_TOP

794           LOAD_GLOBAL              0 (op)
              LOAD_ATTR                8 (drop_table)
              PUSH_NULL
              LOAD_CONST              58 ('handoff_offers')
              CALL                     1
              POP_TOP

795           LOAD_GLOBAL              0 (op)
              LOAD_ATTR                8 (drop_table)
              PUSH_NULL
              LOAD_CONST              59 ('notification_deliveries')
              CALL                     1
              POP_TOP

796           LOAD_GLOBAL              0 (op)
              LOAD_ATTR                8 (drop_table)
              PUSH_NULL
              LOAD_CONST              60 ('notifications')
              CALL                     1
              POP_TOP

797           LOAD_GLOBAL              0 (op)
              LOAD_ATTR                8 (drop_table)
              PUSH_NULL
              LOAD_CONST              61 ('reminders')
              CALL                     1
              POP_TOP

798           LOAD_GLOBAL              0 (op)
              LOAD_ATTR                8 (drop_table)
              PUSH_NULL
              LOAD_CONST              62 ('block_entries')
              CALL                     1
              POP_TOP

799           LOAD_GLOBAL              0 (op)
              LOAD_ATTR                8 (drop_table)
              PUSH_NULL
              LOAD_CONST              63 ('vip_entries')
              CALL                     1
              POP_TOP
              RETURN_CONST             0 (None)
