# Bytecode dump of: 028_contact_profiles_and_category_defaults.pyc
# co_filename: D:\fluence\Github\mattbot\backend\alembic\versions\028_contact_profiles_and_category_defaults.py
# co_names: ('__doc__', 'typing', 'Sequence', 'Union', 'alembic', 'op', 'sqlalchemy', 'sa', 'sqlalchemy.dialects.postgresql', 'UUID', 'revision', 'str', '__annotations__', 'down_revision', 'branch_labels', 'depends_on', 'upgrade', 'downgrade')
# co_consts (strings): ['028 – contact_profiles table and category defaults column.\n\nRevision ID: 028\nRevises: 196ccde938db\nCreate Date: 2026-03-08\n', '028', 'revision', '196ccde938db', 'down_revision', 'branch_labels', 'depends_on']

# --- Nested code object: upgrade ---
    # co_names: ('op', 'create_table', 'sa', 'Column', 'UUID', 'ForeignKey', 'LargeBinary', 'Integer', 'String', 'Text', 'text', 'Boolean', 'DateTime', 'UniqueConstraint', 'CheckConstraint', 'create_index', 'add_column', 'JSON', 'execute')
    # co_varnames: ()
    # co_consts (strings): ['contact_profiles', 'id', 'owner_user_id', 'users.id', 'CASCADE', 'phone_ciphertext', 'phone_nonce', 'phone_key_version', 'phone_hash', 'phone_last4', 'display_name', 'company', 'relationship', 'email', 'notes', 'category', "'other'", 'is_vip', 'false', 'is_blocked', 'block_reason', 'ai_temperament_preset', 'ai_greeting_template', 'ai_greeting_instructions_ciphertext', 'ai_greeting_instructions_nonce', 'ai_greeting_instructions_key_version', 'ai_swearing_rule', 'ai_max_call_length_seconds', 'ai_custom_instructions_ciphertext', 'ai_custom_instructions_nonce', 'ai_custom_instructions_key_version', 'created_at', 'now()', 'updated_at', 'deleted_at', 'uq_contact_profiles_user_phone', "category IN ('business', 'friends', 'family', 'other')", 'ck_contact_profiles_category', "ai_temperament_preset IS NULL OR ai_temperament_preset IN ('professional_polite', 'casual_friendly', 'short_and_direct', 'warm_and_supportive', 'formal', 'custom')", 'ck_contact_profiles_temperament', "ai_swearing_rule IS NULL OR ai_swearing_rule IN ('no_swearing', 'mirror_caller', 'allow')", 'ck_contact_profiles_swearing', "ai_greeting_template IS NULL OR ai_greeting_template IN ('standard', 'brief', 'formal', 'custom')", 'ck_contact_profiles_greeting_template', 'contact_profiles_user_idx', 'contact_profiles_user_category_idx', 'user_settings', 'contact_category_defaults', "'{}'::jsonb", "\n        INSERT INTO contact_profiles (\n            id, owner_user_id,\n            phone_ciphertext, phone_nonce, phone_key_version,\n            phone_hash, phone_last4,\n            display_name, company, relationship, email, notes,\n            category, is_vip, is_blocked,\n            created_at, updated_at\n        )\n        SELECT\n            gen_random_uuid(), v.owner_user_id,\n            v.phone_ciphertext, v.phone_nonce, v.phone_key_version,\n            v.phone_hash, v.phone_last4,\n            v.display_name, v.company, v.relationship, v.email, v.notes,\n            'other', true, false,\n            v.created_at, v.updated_at\n        FROM vip_entries v\n        ON CONFLICT (owner_user_id, phone_hash) DO UPDATE\n            SET is_vip = true\n    ", "\n        INSERT INTO contact_profiles (\n            id, owner_user_id,\n            phone_ciphertext, phone_nonce, phone_key_version,\n            phone_hash, phone_last4,\n            display_name, company, relationship, email, notes,\n            category, is_vip, is_blocked, block_reason,\n            created_at, updated_at\n        )\n        SELECT\n            gen_random_uuid(), b.owner_user_id,\n            b.phone_ciphertext, b.phone_nonce, b.phone_key_version,\n            b.phone_hash, b.phone_last4,\n            b.display_name, b.company, b.relationship, b.email, b.notes,\n            'other', false, true, b.reason,\n            b.created_at, b.updated_at\n        FROM block_entries b\n        ON CONFLICT (owner_user_id, phone_hash) DO UPDATE\n            SET is_blocked = true,\n                block_reason = EXCLUDED.block_reason\n    "]
 19           RESUME                   0

 21           LOAD_GLOBAL              0 (op)
              LOAD_ATTR                2 (create_table)
              PUSH_NULL
              BUILD_LIST               0

 22           LOAD_CONST               1 ('contact_profiles')

 21           LIST_APPEND              1

 23           LOAD_GLOBAL              4 (sa)
              LOAD_ATTR                6 (Column)
              PUSH_NULL
              LOAD_CONST               2 ('id')
              LOAD_GLOBAL              9 (UUID + NULL)
              LOAD_CONST               3 (True)
              LOAD_CONST               4 (('as_uuid',))
              CALL_KW                  1
              LOAD_CONST               3 (True)
              LOAD_CONST               5 (('primary_key',))
              CALL_KW                  3

 21           LIST_APPEND              1

 24           LOAD_GLOBAL              4 (sa)
              LOAD_ATTR                6 (Column)
              PUSH_NULL

 25           LOAD_CONST               6 ('owner_user_id')
              LOAD_GLOBAL              9 (UUID + NULL)
              LOAD_CONST               3 (True)
              LOAD_CONST               4 (('as_uuid',))
              CALL_KW                  1

 26           LOAD_GLOBAL              4 (sa)
              LOAD_ATTR               10 (ForeignKey)
              PUSH_NULL
              LOAD_CONST               7 ('users.id')
              LOAD_CONST               8 ('CASCADE')
              LOAD_CONST               9 (('ondelete',))
              CALL_KW                  2
              LOAD_CONST              10 (False)

 24           LOAD_CONST              11 (('nullable',))
              CALL_KW                  4

 21           LIST_APPEND              1

 28           LOAD_GLOBAL              4 (sa)
              LOAD_ATTR                6 (Column)
              PUSH_NULL
              LOAD_CONST              12 ('phone_ciphertext')
              LOAD_GLOBAL              4 (sa)
              LOAD_ATTR               12 (LargeBinary)
              LOAD_CONST              10 (False)
              LOAD_CONST              11 (('nullable',))
              CALL_KW                  3

 21           LIST_APPEND              1

 29           LOAD_GLOBAL              4 (sa)
              LOAD_ATTR                6 (Column)
              PUSH_NULL
              LOAD_CONST              13 ('phone_nonce')
              LOAD_GLOBAL              4 (sa)
              LOAD_ATTR               12 (LargeBinary)
              LOAD_CONST              10 (False)
              LOAD_CONST              11 (('nullable',))
              CALL_KW                  3

 21           LIST_APPEND              1

 30           LOAD_GLOBAL              4 (sa)
              LOAD_ATTR                6 (Column)
              PUSH_NULL
              LOAD_CONST              14 ('phone_key_version')
              LOAD_GLOBAL              4 (sa)
              LOAD_ATTR               14 (Integer)
              LOAD_CONST              10 (False)
              LOAD_CONST              11 (('nullable',))
              CALL_KW                  3

 21           LIST_APPEND              1

 31           LOAD_GLOBAL              4 (sa)
              LOAD_ATTR                6 (Column)
              PUSH_NULL
              LOAD_CONST              15 ('phone_hash')
              LOAD_GLOBAL              4 (sa)
              LOAD_ATTR               16 (String)
              PUSH_NULL
              LOAD_CONST              16 (64)
              CALL                     1
              LOAD_CONST              10 (False)
              LOAD_CONST              11 (('nullable',))
              CALL_KW                  3

 21           LIST_APPEND              1

 32           LOAD_GLOBAL              4 (sa)
              LOAD_ATTR                6 (Column)
              PUSH_NULL
              LOAD_CONST              17 ('phone_last4')
              LOAD_GLOBAL              4 (sa)
              LOAD_ATTR               16 (String)
              PUSH_NULL
              LOAD_CONST              18 (4)
              CALL                     1
              LOAD_CONST              10 (False)
              LOAD_CONST              11 (('nullable',))
              CALL_KW                  3

 21           LIST_APPEND              1

 33           LOAD_GLOBAL              4 (sa)
              LOAD_ATTR                6 (Column)
              PUSH_NULL
              LOAD_CONST              19 ('display_name')
              LOAD_GLOBAL              4 (sa)
              LOAD_ATTR               18 (Text)
              LOAD_CONST               3 (True)
              LOAD_CONST              11 (('nullable',))
              CALL_KW                  3

 21           LIST_APPEND              1

 34           LOAD_GLOBAL              4 (sa)
              LOAD_ATTR                6 (Column)
              PUSH_NULL
              LOAD_CONST              20 ('company')
              LOAD_GLOBAL              4 (sa)
              LOAD_ATTR               16 (String)
              PUSH_NULL
              LOAD_CONST              21 (200)
              CALL                     1
              LOAD_CONST               3 (True)
              LOAD_CONST              11 (('nullable',))
              CALL_KW                  3

 21           LIST_APPEND              1

 35           LOAD_GLOBAL              4 (sa)
              LOAD_ATTR                6 (Column)
              PUSH_NULL
              LOAD_CONST              22 ('relationship')
              LOAD_GLOBAL              4 (sa)
              LOAD_ATTR               16 (String)
              PUSH_NULL
              LOAD_CONST              23 (100)
              CALL                     1
              LOAD_CONST               3 (True)
              LOAD_CONST              11 (('nullable',))
              CALL_KW                  3

 21           LIST_APPEND              1

 36           LOAD_GLOBAL              4 (sa)
              LOAD_ATTR                6 (Column)
              PUSH_NULL
              LOAD_CONST              24 ('email')
              LOAD_GLOBAL              4 (sa)
              LOAD_ATTR               16 (String)
              PUSH_NULL
              LOAD_CONST              25 (254)
              CALL                     1
              LOAD_CONST               3 (True)
              LOAD_CONST              11 (('nullable',))
              CALL_KW                  3

 21           LIST_APPEND              1

 37           LOAD_GLOBAL              4 (sa)
              LOAD_ATTR                6 (Column)
              PUSH_NULL
              LOAD_CONST              26 ('notes')
              LOAD_GLOBAL              4 (sa)
              LOAD_ATTR               18 (Text)
              LOAD_CONST               3 (True)
              LOAD_CONST              11 (('nullable',))
              CALL_KW                  3

 21           LIST_APPEND              1

 38           LOAD_GLOBAL              4 (sa)
              LOAD_ATTR                6 (Column)
              PUSH_NULL

 39           LOAD_CONST              27 ('category')
              LOAD_GLOBAL              4 (sa)
              LOAD_ATTR               16 (String)
              PUSH_NULL
              LOAD_CONST              28 (20)
              CALL                     1
              LOAD_CONST              10 (False)

 40           LOAD_GLOBAL              4 (sa)
              LOAD_ATTR               20 (text)
              PUSH_NULL
              LOAD_CONST              29 ("'other'")
              CALL                     1

 38           LOAD_CONST              30 (('nullable', 'server_default'))
              CALL_KW                  4

 21           LIST_APPEND              1

 42           LOAD_GLOBAL              4 (sa)
              LOAD_ATTR                6 (Column)
              PUSH_NULL

 43           LOAD_CONST              31 ('is_vip')
              LOAD_GLOBAL              4 (sa)
              LOAD_ATTR               22 (Boolean)
              LOAD_CONST              10 (False)

 44           LOAD_GLOBAL              4 (sa)
              LOAD_ATTR               20 (text)
              PUSH_NULL
              LOAD_CONST              32 ('false')
              CALL                     1

 42           LOAD_CONST              30 (('nullable', 'server_default'))
              CALL_KW                  4

 21           LIST_APPEND              1

 46           LOAD_GLOBAL              4 (sa)
              LOAD_ATTR                6 (Column)
              PUSH_NULL

 47           LOAD_CONST              33 ('is_blocked')
              LOAD_GLOBAL              4 (sa)
              LOAD_ATTR               22 (Boolean)
              LOAD_CONST              10 (False)

 48           LOAD_GLOBAL              4 (sa)
              LOAD_ATTR               20 (text)
              PUSH_NULL
              LOAD_CONST              32 ('false')
              CALL                     1

 46           LOAD_CONST              30 (('nullable', 'server_default'))
              CALL_KW                  4

 21           LIST_APPEND              1

 50           LOAD_GLOBAL              4 (sa)
              LOAD_ATTR                6 (Column)
              PUSH_NULL
              LOAD_CONST              34 ('block_reason')
              LOAD_GLOBAL              4 (sa)
              LOAD_ATTR               18 (Text)
              LOAD_CONST               3 (True)
              LOAD_CONST              11 (('nullable',))
              CALL_KW                  3

 21           LIST_APPEND              1

 52           LOAD_GLOBAL              4 (sa)
              LOAD_ATTR                6 (Column)
              PUSH_NULL
              LOAD_CONST              35 ('ai_temperament_preset')
              LOAD_GLOBAL              4 (sa)
              LOAD_ATTR               16 (String)
              PUSH_NULL
              LOAD_CONST              36 (40)
              CALL                     1
              LOAD_CONST               3 (True)
              LOAD_CONST              11 (('nullable',))
              CALL_KW                  3

 21           LIST_APPEND              1

 53           LOAD_GLOBAL              4 (sa)
              LOAD_ATTR                6 (Column)
              PUSH_NULL
              LOAD_CONST              37 ('ai_greeting_template')
              LOAD_GLOBAL              4 (sa)
              LOAD_ATTR               16 (String)
              PUSH_NULL
              LOAD_CONST              36 (40)
              CALL                     1
              LOAD_CONST               3 (True)
              LOAD_CONST              11 (('nullable',))
              CALL_KW                  3

 21           LIST_APPEND              1

 54           LOAD_GLOBAL              4 (sa)
              LOAD_ATTR                6 (Column)
              PUSH_NULL
              LOAD_CONST              38 ('ai_greeting_instructions_ciphertext')
              LOAD_GLOBAL              4 (sa)
              LOAD_ATTR               12 (LargeBinary)
              LOAD_CONST               3 (True)
              LOAD_CONST              11 (('nullable',))
              CALL_KW                  3

 21           LIST_APPEND              1

 55           LOAD_GLOBAL              4 (sa)
              LOAD_ATTR                6 (Column)
              PUSH_NULL
              LOAD_CONST              39 ('ai_greeting_instructions_nonce')
              LOAD_GLOBAL              4 (sa)
              LOAD_ATTR               12 (LargeBinary)
              LOAD_CONST               3 (True)
              LOAD_CONST              11 (('nullable',))
              CALL_KW                  3

 21           LIST_APPEND              1

 56           LOAD_GLOBAL              4 (sa)
              LOAD_ATTR                6 (Column)
              PUSH_NULL
              LOAD_CONST              40 ('ai_greeting_instructions_key_version')
              LOAD_GLOBAL              4 (sa)
              LOAD_ATTR               14 (Integer)
              LOAD_CONST               3 (True)
              LOAD_CONST              11 (('nullable',))
              CALL_KW                  3

 21           LIST_APPEND              1

 57           LOAD_GLOBAL              4 (sa)
              LOAD_ATTR                6 (Column)
              PUSH_NULL
              LOAD_CONST              41 ('ai_swearing_rule')
              LOAD_GLOBAL              4 (sa)
              LOAD_ATTR               16 (String)
              PUSH_NULL
              LOAD_CONST              28 (20)
              CALL                     1
              LOAD_CONST               3 (True)
              LOAD_CONST              11 (('nullable',))
              CALL_KW                  3

 21           LIST_APPEND              1

 58           LOAD_GLOBAL              4 (sa)
              LOAD_ATTR                6 (Column)
              PUSH_NULL
              LOAD_CONST              42 ('ai_max_call_length_seconds')
              LOAD_GLOBAL              4 (sa)
              LOAD_ATTR               14 (Integer)
              LOAD_CONST               3 (True)
              LOAD_CONST              11 (('nullable',))
              CALL_KW                  3

 21           LIST_APPEND              1

 59           LOAD_GLOBAL              4 (sa)
              LOAD_ATTR                6 (Column)
              PUSH_NULL
              LOAD_CONST              43 ('ai_custom_instructions_ciphertext')
              LOAD_GLOBAL              4 (sa)
              LOAD_ATTR               12 (LargeBinary)
              LOAD_CONST               3 (True)
              LOAD_CONST              11 (('nullable',))
              CALL_KW                  3

 21           LIST_APPEND              1

 60           LOAD_GLOBAL              4 (sa)
              LOAD_ATTR                6 (Column)
              PUSH_NULL
              LOAD_CONST              44 ('ai_custom_instructions_nonce')
              LOAD_GLOBAL              4 (sa)
              LOAD_ATTR               12 (LargeBinary)
              LOAD_CONST               3 (True)
              LOAD_CONST              11 (('nullable',))
              CALL_KW                  3

 21           LIST_APPEND              1

 61           LOAD_GLOBAL              4 (sa)
              LOAD_ATTR                6 (Column)
              PUSH_NULL
              LOAD_CONST              45 ('ai_custom_instructions_key_version')
              LOAD_GLOBAL              4 (sa)
              LOAD_ATTR               14 (Integer)
              LOAD_CONST               3 (True)
              LOAD_CONST              11 (('nullable',))
              CALL_KW                  3

 21           LIST_APPEND              1

 63           LOAD_GLOBAL              4 (sa)
              LOAD_ATTR                6 (Column)
              PUSH_NULL

 64           LOAD_CONST              46 ('created_at')
              LOAD_GLOBAL              4 (sa)
              LOAD_ATTR               24 (DateTime)
              PUSH_NULL
              LOAD_CONST               3 (True)
              LOAD_CONST              47 (('timezone',))
              CALL_KW                  1
              LOAD_CONST              10 (False)

 65           LOAD_GLOBAL              4 (sa)
              LOAD_ATTR               20 (text)
              PUSH_NULL
              LOAD_CONST              48 ('now()')
              CALL                     1

 63           LOAD_CONST              30 (('nullable', 'server_default'))
              CALL_KW                  4

 21           LIST_APPEND              1

 67           LOAD_GLOBAL              4 (sa)
              LOAD_ATTR                6 (Column)
              PUSH_NULL

 68           LOAD_CONST              49 ('updated_at')
              LOAD_GLOBAL              4 (sa)
              LOAD_ATTR               24 (DateTime)
              PUSH_NULL
              LOAD_CONST               3 (True)
              LOAD_CONST              47 (('timezone',))
              CALL_KW                  1
              LOAD_CONST              10 (False)

 69           LOAD_GLOBAL              4 (sa)
              LOAD_ATTR               20 (text)
              PUSH_NULL
              LOAD_CONST              48 ('now()')
              CALL                     1

 67           LOAD_CONST              30 (('nullable', 'server_default'))
              CALL_KW                  4

 21           LIST_APPEND              1

 71           LOAD_GLOBAL              4 (sa)
              LOAD_ATTR                6 (Column)
              PUSH_NULL
              LOAD_CONST              50 ('deleted_at')
              LOAD_GLOBAL              4 (sa)
              LOAD_ATTR               24 (DateTime)
              PUSH_NULL
              LOAD_CONST               3 (True)
              LOAD_CONST              47 (('timezone',))
              CALL_KW                  1
              LOAD_CONST               3 (True)
              LOAD_CONST              11 (('nullable',))
              CALL_KW                  3

 21           LIST_APPEND              1

 73           LOAD_GLOBAL              4 (sa)
              LOAD_ATTR               26 (UniqueConstraint)
              PUSH_NULL

 74           LOAD_CONST               6 ('owner_user_id')
              LOAD_CONST              15 ('phone_hash')

 75           LOAD_CONST              51 ('uq_contact_profiles_user_phone')

 73           LOAD_CONST              52 (('name',))
              CALL_KW                  3

 21           LIST_APPEND              1

 77           LOAD_GLOBAL              4 (sa)
              LOAD_ATTR               28 (CheckConstraint)
              PUSH_NULL

 78           LOAD_CONST              53 ("category IN ('business', 'friends', 'family', 'other')")

 79           LOAD_CONST              54 ('ck_contact_profiles_category')

 77           LOAD_CONST              52 (('name',))
              CALL_KW                  2

 21           LIST_APPEND              1

 81           LOAD_GLOBAL              4 (sa)
              LOAD_ATTR               28 (CheckConstraint)
              PUSH_NULL

 82           LOAD_CONST              55 ("ai_temperament_preset IS NULL OR ai_temperament_preset IN ('professional_polite', 'casual_friendly', 'short_and_direct', 'warm_and_supportive', 'formal', 'custom')")

 85           LOAD_CONST              56 ('ck_contact_profiles_temperament')

 81           LOAD_CONST              52 (('name',))
              CALL_KW                  2

 21           LIST_APPEND              1

 87           LOAD_GLOBAL              4 (sa)
              LOAD_ATTR               28 (CheckConstraint)
              PUSH_NULL

 88           LOAD_CONST              57 ("ai_swearing_rule IS NULL OR ai_swearing_rule IN ('no_swearing', 'mirror_caller', 'allow')")

 90           LOAD_CONST              58 ('ck_contact_profiles_swearing')

 87           LOAD_CONST              52 (('name',))
              CALL_KW                  2

 21           LIST_APPEND              1

 92           LOAD_GLOBAL              4 (sa)
              LOAD_ATTR               28 (CheckConstraint)
              PUSH_NULL

 93           LOAD_CONST              59 ("ai_greeting_template IS NULL OR ai_greeting_template IN ('standard', 'brief', 'formal', 'custom')")

 95           LOAD_CONST              60 ('ck_contact_profiles_greeting_template')

 92           LOAD_CONST              52 (('name',))
              CALL_KW                  2

 21           LIST_APPEND              1
              CALL_INTRINSIC_1         6 (INTRINSIC_LIST_TO_TUPLE)
              CALL_FUNCTION_EX         0
              POP_TOP

 98           LOAD_GLOBAL              0 (op)
              LOAD_ATTR               30 (create_index)
              PUSH_NULL

 99           LOAD_CONST              61 ('contact_profiles_user_idx')
              LOAD_CONST               1 ('contact_profiles')
              LOAD_CONST               6 ('owner_user_id')
              BUILD_LIST               1

 98           CALL                     3
              POP_TOP

101           LOAD_GLOBAL              0 (op)
              LOAD_ATTR               30 (create_index)
              PUSH_NULL

102           LOAD_CONST              62 ('contact_profiles_user_category_idx')
              LOAD_CONST               1 ('contact_profiles')

103           LOAD_CONST               6 ('owner_user_id')
              LOAD_CONST              27 ('category')
              BUILD_LIST               2

101           CALL                     3
              POP_TOP

107           LOAD_GLOBAL              0 (op)
              LOAD_ATTR               32 (add_column)
              PUSH_NULL

108           LOAD_CONST              63 ('user_settings')

109           LOAD_GLOBAL              4 (sa)
              LOAD_ATTR                6 (Column)
              PUSH_NULL

110           LOAD_CONST              64 ('contact_category_defaults')

111           LOAD_GLOBAL              4 (sa)
              LOAD_ATTR               34 (JSON)
              LOAD_CONST              10 (False)
              LOAD_GLOBAL              4 (sa)
              LOAD_ATTR               20 (text)
              PUSH_NULL
              LOAD_CONST              65 ("'{}'::jsonb")
              CALL                     1

109           LOAD_CONST              30 (('nullable', 'server_default'))
              CALL_KW                  4

107           CALL                     2
              POP_TOP

116           LOAD_GLOBAL              0 (op)
              LOAD_ATTR               36 (execute)
              PUSH_NULL
              LOAD_CONST              66 ("\n        INSERT INTO contact_profiles (\n            id, owner_user_id,\n            phone_ciphertext, phone_nonce, phone_key_version,\n            phone_hash, phone_last4,\n            display_name, company, relationship, email, notes,\n            category, is_vip, is_blocked,\n            created_at, updated_at\n        )\n        SELECT\n            gen_random_uuid(), v.owner_user_id,\n            v.phone_ciphertext, v.phone_nonce, v.phone_key_version,\n            v.phone_hash, v.phone_last4,\n            v.display_name, v.company, v.relationship, v.email, v.notes,\n            'other', true, false,\n            v.created_at, v.updated_at\n        FROM vip_entries v\n        ON CONFLICT (owner_user_id, phone_hash) DO UPDATE\n            SET is_vip = true\n    ")
              CALL                     1
              POP_TOP

138           LOAD_GLOBAL              0 (op)
              LOAD_ATTR               36 (execute)
              PUSH_NULL
              LOAD_CONST              67 ("\n        INSERT INTO contact_profiles (\n            id, owner_user_id,\n            phone_ciphertext, phone_nonce, phone_key_version,\n            phone_hash, phone_last4,\n            display_name, company, relationship, email, notes,\n            category, is_vip, is_blocked, block_reason,\n            created_at, updated_at\n        )\n        SELECT\n            gen_random_uuid(), b.owner_user_id,\n            b.phone_ciphertext, b.phone_nonce, b.phone_key_version,\n            b.phone_hash, b.phone_last4,\n            b.display_name, b.company, b.relationship, b.email, b.notes,\n            'other', false, true, b.reason,\n            b.created_at, b.updated_at\n        FROM block_entries b\n        ON CONFLICT (owner_user_id, phone_hash) DO UPDATE\n            SET is_blocked = true,\n                block_reason = EXCLUDED.block_reason\n    ")
              CALL                     1
              POP_TOP
              RETURN_CONST             0 (None)

# --- Nested code object: downgrade ---
    # co_names: ('op', 'drop_column', 'drop_index', 'drop_table')
    # co_varnames: ()
    # co_consts (strings): ['user_settings', 'contact_category_defaults', 'contact_profiles_user_category_idx', 'contact_profiles', 'contact_profiles_user_idx']
161           RESUME                   0

162           LOAD_GLOBAL              0 (op)
              LOAD_ATTR                2 (drop_column)
              PUSH_NULL
              LOAD_CONST               1 ('user_settings')
              LOAD_CONST               2 ('contact_category_defaults')
              CALL                     2
              POP_TOP

163           LOAD_GLOBAL              0 (op)
              LOAD_ATTR                4 (drop_index)
              PUSH_NULL
              LOAD_CONST               3 ('contact_profiles_user_category_idx')
              LOAD_CONST               4 ('contact_profiles')
              LOAD_CONST               5 (('table_name',))
              CALL_KW                  2
              POP_TOP

164           LOAD_GLOBAL              0 (op)
              LOAD_ATTR                4 (drop_index)
              PUSH_NULL
              LOAD_CONST               6 ('contact_profiles_user_idx')
              LOAD_CONST               4 ('contact_profiles')
              LOAD_CONST               5 (('table_name',))
              CALL_KW                  2
              POP_TOP

165           LOAD_GLOBAL              0 (op)
              LOAD_ATTR                6 (drop_table)
              PUSH_NULL
              LOAD_CONST               4 ('contact_profiles')
              CALL                     1
              POP_TOP
              RETURN_CONST             0 (None)

# --- Module-level bytecode ---
  0           RESUME                   0

  1           SETUP_ANNOTATIONS
              LOAD_CONST               0 ('028 – contact_profiles table and category defaults column.\n\nRevision ID: 028\nRevises: 196ccde938db\nCreate Date: 2026-03-08\n')
              STORE_NAME               0 (__doc__)

  7           LOAD_CONST               1 (0)
              LOAD_CONST               2 (('Sequence', 'Union'))
              IMPORT_NAME              1 (typing)
              IMPORT_FROM              2 (Sequence)
              STORE_NAME               2 (Sequence)
              IMPORT_FROM              3 (Union)
              STORE_NAME               3 (Union)
              POP_TOP

  9           LOAD_CONST               1 (0)
              LOAD_CONST               3 (('op',))
              IMPORT_NAME              4 (alembic)
              IMPORT_FROM              5 (op)
              STORE_NAME               5 (op)
              POP_TOP

 10           LOAD_CONST               1 (0)
              LOAD_CONST               4 (None)
              IMPORT_NAME              6 (sqlalchemy)
              STORE_NAME               7 (sa)

 11           LOAD_CONST               1 (0)
              LOAD_CONST               5 (('UUID',))
              IMPORT_NAME              8 (sqlalchemy.dialects.postgresql)
              IMPORT_FROM              9 (UUID)
              STORE_NAME               9 (UUID)
              POP_TOP

 13           LOAD_CONST               6 ('028')
              STORE_NAME              10 (revision)
              LOAD_NAME               11 (str)
              LOAD_NAME               12 (__annotations__)
              LOAD_CONST               7 ('revision')
              STORE_SUBSCR

 14           LOAD_CONST               8 ('196ccde938db')
              STORE_NAME              13 (down_revision)
              LOAD_NAME                3 (Union)
              LOAD_NAME               11 (str)
              LOAD_CONST               4 (None)
              BUILD_TUPLE              2
              BINARY_SUBSCR
              LOAD_NAME               12 (__annotations__)
              LOAD_CONST               9 ('down_revision')
              STORE_SUBSCR

 15           LOAD_CONST               4 (None)
              STORE_NAME              14 (branch_labels)
              LOAD_NAME                3 (Union)
              LOAD_NAME               11 (str)
              LOAD_NAME                2 (Sequence)
              LOAD_NAME               11 (str)
              BINARY_SUBSCR
              LOAD_CONST               4 (None)
              BUILD_TUPLE              3
              BINARY_SUBSCR
              LOAD_NAME               12 (__annotations__)
              LOAD_CONST              10 ('branch_labels')
              STORE_SUBSCR

 16           LOAD_CONST               4 (None)
              STORE_NAME              15 (depends_on)
              LOAD_NAME                3 (Union)
              LOAD_NAME               11 (str)
              LOAD_NAME                2 (Sequence)
              LOAD_NAME               11 (str)
              BINARY_SUBSCR
              LOAD_CONST               4 (None)
              BUILD_TUPLE              3
              BINARY_SUBSCR
              LOAD_NAME               12 (__annotations__)
              LOAD_CONST              11 ('depends_on')
              STORE_SUBSCR

 19           LOAD_CONST              14 (('return', None))
              LOAD_CONST              12 (<code object upgrade at 0x00000185C9ADACB0, file "D:\fluence\Github\mattbot\backend\alembic\versions\028_contact_profiles_and_category_defaults.py", line 19>)
              MAKE_FUNCTION
              SET_FUNCTION_ATTRIBUTE   4 (annotations)
              STORE_NAME              16 (upgrade)

161           LOAD_CONST              14 (('return', None))
              LOAD_CONST              13 (<code object downgrade at 0x00000185CB7D5E30, file "D:\fluence\Github\mattbot\backend\alembic\versions\028_contact_profiles_and_category_defaults.py", line 161>)
              MAKE_FUNCTION
              SET_FUNCTION_ATTRIBUTE   4 (annotations)
              STORE_NAME              17 (downgrade)
              RETURN_CONST             4 (None)

Disassembly of <code object upgrade at 0x00000185C9ADACB0, file "D:\fluence\Github\mattbot\backend\alembic\versions\028_contact_profiles_and_category_defaults.py", line 19>:
 19           RESUME                   0

 21           LOAD_GLOBAL              0 (op)
              LOAD_ATTR                2 (create_table)
              PUSH_NULL
              BUILD_LIST               0

 22           LOAD_CONST               1 ('contact_profiles')

 21           LIST_APPEND              1

 23           LOAD_GLOBAL              4 (sa)
              LOAD_ATTR                6 (Column)
              PUSH_NULL
              LOAD_CONST               2 ('id')
              LOAD_GLOBAL              9 (UUID + NULL)
              LOAD_CONST               3 (True)
              LOAD_CONST               4 (('as_uuid',))
              CALL_KW                  1
              LOAD_CONST               3 (True)
              LOAD_CONST               5 (('primary_key',))
              CALL_KW                  3

 21           LIST_APPEND              1

 24           LOAD_GLOBAL              4 (sa)
              LOAD_ATTR                6 (Column)
              PUSH_NULL

 25           LOAD_CONST               6 ('owner_user_id')
              LOAD_GLOBAL              9 (UUID + NULL)
              LOAD_CONST               3 (True)
              LOAD_CONST               4 (('as_uuid',))
              CALL_KW                  1

 26           LOAD_GLOBAL              4 (sa)
              LOAD_ATTR               10 (ForeignKey)
              PUSH_NULL
              LOAD_CONST               7 ('users.id')
              LOAD_CONST               8 ('CASCADE')
              LOAD_CONST               9 (('ondelete',))
              CALL_KW                  2
              LOAD_CONST              10 (False)

 24           LOAD_CONST              11 (('nullable',))
              CALL_KW                  4

 21           LIST_APPEND              1

 28           LOAD_GLOBAL              4 (sa)
              LOAD_ATTR                6 (Column)
              PUSH_NULL
              LOAD_CONST              12 ('phone_ciphertext')
              LOAD_GLOBAL              4 (sa)
              LOAD_ATTR               12 (LargeBinary)
              LOAD_CONST              10 (False)
              LOAD_CONST              11 (('nullable',))
              CALL_KW                  3

 21           LIST_APPEND              1

 29           LOAD_GLOBAL              4 (sa)
              LOAD_ATTR                6 (Column)
              PUSH_NULL
              LOAD_CONST              13 ('phone_nonce')
              LOAD_GLOBAL              4 (sa)
              LOAD_ATTR               12 (LargeBinary)
              LOAD_CONST              10 (False)
              LOAD_CONST              11 (('nullable',))
              CALL_KW                  3

 21           LIST_APPEND              1

 30           LOAD_GLOBAL              4 (sa)
              LOAD_ATTR                6 (Column)
              PUSH_NULL
              LOAD_CONST              14 ('phone_key_version')
              LOAD_GLOBAL              4 (sa)
              LOAD_ATTR               14 (Integer)
              LOAD_CONST              10 (False)
              LOAD_CONST              11 (('nullable',))
              CALL_KW                  3

 21           LIST_APPEND              1

 31           LOAD_GLOBAL              4 (sa)
              LOAD_ATTR                6 (Column)
              PUSH_NULL
              LOAD_CONST              15 ('phone_hash')
              LOAD_GLOBAL              4 (sa)
              LOAD_ATTR               16 (String)
              PUSH_NULL
              LOAD_CONST              16 (64)
              CALL                     1
              LOAD_CONST              10 (False)
              LOAD_CONST              11 (('nullable',))
              CALL_KW                  3

 21           LIST_APPEND              1

 32           LOAD_GLOBAL              4 (sa)
              LOAD_ATTR                6 (Column)
              PUSH_NULL
              LOAD_CONST              17 ('phone_last4')
              LOAD_GLOBAL              4 (sa)
              LOAD_ATTR               16 (String)
              PUSH_NULL
              LOAD_CONST              18 (4)
              CALL                     1
              LOAD_CONST              10 (False)
              LOAD_CONST              11 (('nullable',))
              CALL_KW                  3

 21           LIST_APPEND              1

 33           LOAD_GLOBAL              4 (sa)
              LOAD_ATTR                6 (Column)
              PUSH_NULL
              LOAD_CONST              19 ('display_name')
              LOAD_GLOBAL              4 (sa)
              LOAD_ATTR               18 (Text)
              LOAD_CONST               3 (True)
              LOAD_CONST              11 (('nullable',))
              CALL_KW                  3

 21           LIST_APPEND              1

 34           LOAD_GLOBAL              4 (sa)
              LOAD_ATTR                6 (Column)
              PUSH_NULL
              LOAD_CONST              20 ('company')
              LOAD_GLOBAL              4 (sa)
              LOAD_ATTR               16 (String)
              PUSH_NULL
              LOAD_CONST              21 (200)
              CALL                     1
              LOAD_CONST               3 (True)
              LOAD_CONST              11 (('nullable',))
              CALL_KW                  3

 21           LIST_APPEND              1

 35           LOAD_GLOBAL              4 (sa)
              LOAD_ATTR                6 (Column)
              PUSH_NULL
              LOAD_CONST              22 ('relationship')
              LOAD_GLOBAL              4 (sa)
              LOAD_ATTR               16 (String)
              PUSH_NULL
              LOAD_CONST              23 (100)
              CALL                     1
              LOAD_CONST               3 (True)
              LOAD_CONST              11 (('nullable',))
              CALL_KW                  3

 21           LIST_APPEND              1

 36           LOAD_GLOBAL              4 (sa)
              LOAD_ATTR                6 (Column)
              PUSH_NULL
              LOAD_CONST              24 ('email')
              LOAD_GLOBAL              4 (sa)
              LOAD_ATTR               16 (String)
              PUSH_NULL
              LOAD_CONST              25 (254)
              CALL                     1
              LOAD_CONST               3 (True)
              LOAD_CONST              11 (('nullable',))
              CALL_KW                  3

 21           LIST_APPEND              1

 37           LOAD_GLOBAL              4 (sa)
              LOAD_ATTR                6 (Column)
              PUSH_NULL
              LOAD_CONST              26 ('notes')
              LOAD_GLOBAL              4 (sa)
              LOAD_ATTR               18 (Text)
              LOAD_CONST               3 (True)
              LOAD_CONST              11 (('nullable',))
              CALL_KW                  3

 21           LIST_APPEND              1

 38           LOAD_GLOBAL              4 (sa)
              LOAD_ATTR                6 (Column)
              PUSH_NULL

 39           LOAD_CONST              27 ('category')
              LOAD_GLOBAL              4 (sa)
              LOAD_ATTR               16 (String)
              PUSH_NULL
              LOAD_CONST              28 (20)
              CALL                     1
              LOAD_CONST              10 (False)

 40           LOAD_GLOBAL              4 (sa)
              LOAD_ATTR               20 (text)
              PUSH_NULL
              LOAD_CONST              29 ("'other'")
              CALL                     1

 38           LOAD_CONST              30 (('nullable', 'server_default'))
              CALL_KW                  4

 21           LIST_APPEND              1

 42           LOAD_GLOBAL              4 (sa)
              LOAD_ATTR                6 (Column)
              PUSH_NULL

 43           LOAD_CONST              31 ('is_vip')
              LOAD_GLOBAL              4 (sa)
              LOAD_ATTR               22 (Boolean)
              LOAD_CONST              10 (False)

 44           LOAD_GLOBAL              4 (sa)
              LOAD_ATTR               20 (text)
              PUSH_NULL
              LOAD_CONST              32 ('false')
              CALL                     1

 42           LOAD_CONST              30 (('nullable', 'server_default'))
              CALL_KW                  4

 21           LIST_APPEND              1

 46           LOAD_GLOBAL              4 (sa)
              LOAD_ATTR                6 (Column)
              PUSH_NULL

 47           LOAD_CONST              33 ('is_blocked')
              LOAD_GLOBAL              4 (sa)
              LOAD_ATTR               22 (Boolean)
              LOAD_CONST              10 (False)

 48           LOAD_GLOBAL              4 (sa)
              LOAD_ATTR               20 (text)
              PUSH_NULL
              LOAD_CONST              32 ('false')
              CALL                     1

 46           LOAD_CONST              30 (('nullable', 'server_default'))
              CALL_KW                  4

 21           LIST_APPEND              1

 50           LOAD_GLOBAL              4 (sa)
              LOAD_ATTR                6 (Column)
              PUSH_NULL
              LOAD_CONST              34 ('block_reason')
              LOAD_GLOBAL              4 (sa)
              LOAD_ATTR               18 (Text)
              LOAD_CONST               3 (True)
              LOAD_CONST              11 (('nullable',))
              CALL_KW                  3

 21           LIST_APPEND              1

 52           LOAD_GLOBAL              4 (sa)
              LOAD_ATTR                6 (Column)
              PUSH_NULL
              LOAD_CONST              35 ('ai_temperament_preset')
              LOAD_GLOBAL              4 (sa)
              LOAD_ATTR               16 (String)
              PUSH_NULL
              LOAD_CONST              36 (40)
              CALL                     1
              LOAD_CONST               3 (True)
              LOAD_CONST              11 (('nullable',))
              CALL_KW                  3

 21           LIST_APPEND              1

 53           LOAD_GLOBAL              4 (sa)
              LOAD_ATTR                6 (Column)
              PUSH_NULL
              LOAD_CONST              37 ('ai_greeting_template')
              LOAD_GLOBAL              4 (sa)
              LOAD_ATTR               16 (String)
              PUSH_NULL
              LOAD_CONST              36 (40)
              CALL                     1
              LOAD_CONST               3 (True)
              LOAD_CONST              11 (('nullable',))
              CALL_KW                  3

 21           LIST_APPEND              1

 54           LOAD_GLOBAL              4 (sa)
              LOAD_ATTR                6 (Column)
              PUSH_NULL
              LOAD_CONST              38 ('ai_greeting_instructions_ciphertext')
              LOAD_GLOBAL              4 (sa)
              LOAD_ATTR               12 (LargeBinary)
              LOAD_CONST               3 (True)
              LOAD_CONST              11 (('nullable',))
              CALL_KW                  3

 21           LIST_APPEND              1

 55           LOAD_GLOBAL              4 (sa)
              LOAD_ATTR                6 (Column)
              PUSH_NULL
              LOAD_CONST              39 ('ai_greeting_instructions_nonce')
              LOAD_GLOBAL              4 (sa)
              LOAD_ATTR               12 (LargeBinary)
              LOAD_CONST               3 (True)
              LOAD_CONST              11 (('nullable',))
              CALL_KW                  3

 21           LIST_APPEND              1

 56           LOAD_GLOBAL              4 (sa)
              LOAD_ATTR                6 (Column)
              PUSH_NULL
              LOAD_CONST              40 ('ai_greeting_instructions_key_version')
              LOAD_GLOBAL              4 (sa)
              LOAD_ATTR               14 (Integer)
              LOAD_CONST               3 (True)
              LOAD_CONST              11 (('nullable',))
              CALL_KW                  3

 21           LIST_APPEND              1

 57           LOAD_GLOBAL              4 (sa)
              LOAD_ATTR                6 (Column)
              PUSH_NULL
              LOAD_CONST              41 ('ai_swearing_rule')
              LOAD_GLOBAL              4 (sa)
              LOAD_ATTR               16 (String)
              PUSH_NULL
              LOAD_CONST              28 (20)
              CALL                     1
              LOAD_CONST               3 (True)
              LOAD_CONST              11 (('nullable',))
              CALL_KW                  3

 21           LIST_APPEND              1

 58           LOAD_GLOBAL              4 (sa)
              LOAD_ATTR                6 (Column)
              PUSH_NULL
              LOAD_CONST              42 ('ai_max_call_length_seconds')
              LOAD_GLOBAL              4 (sa)
              LOAD_ATTR               14 (Integer)
              LOAD_CONST               3 (True)
              LOAD_CONST              11 (('nullable',))
              CALL_KW                  3

 21           LIST_APPEND              1

 59           LOAD_GLOBAL              4 (sa)
              LOAD_ATTR                6 (Column)
              PUSH_NULL
              LOAD_CONST              43 ('ai_custom_instructions_ciphertext')
              LOAD_GLOBAL              4 (sa)
              LOAD_ATTR               12 (LargeBinary)
              LOAD_CONST               3 (True)
              LOAD_CONST              11 (('nullable',))
              CALL_KW                  3

 21           LIST_APPEND              1

 60           LOAD_GLOBAL              4 (sa)
              LOAD_ATTR                6 (Column)
              PUSH_NULL
              LOAD_CONST              44 ('ai_custom_instructions_nonce')
              LOAD_GLOBAL              4 (sa)
              LOAD_ATTR               12 (LargeBinary)
              LOAD_CONST               3 (True)
              LOAD_CONST              11 (('nullable',))
              CALL_KW                  3

 21           LIST_APPEND              1

 61           LOAD_GLOBAL              4 (sa)
              LOAD_ATTR                6 (Column)
              PUSH_NULL
              LOAD_CONST              45 ('ai_custom_instructions_key_version')
              LOAD_GLOBAL              4 (sa)
              LOAD_ATTR               14 (Integer)
              LOAD_CONST               3 (True)
              LOAD_CONST              11 (('nullable',))
              CALL_KW                  3

 21           LIST_APPEND              1

 63           LOAD_GLOBAL              4 (sa)
              LOAD_ATTR                6 (Column)
              PUSH_NULL

 64           LOAD_CONST              46 ('created_at')
              LOAD_GLOBAL              4 (sa)
              LOAD_ATTR               24 (DateTime)
              PUSH_NULL
              LOAD_CONST               3 (True)
              LOAD_CONST              47 (('timezone',))
              CALL_KW                  1
              LOAD_CONST              10 (False)

 65           LOAD_GLOBAL              4 (sa)
              LOAD_ATTR               20 (text)
              PUSH_NULL
              LOAD_CONST              48 ('now()')
              CALL                     1

 63           LOAD_CONST              30 (('nullable', 'server_default'))
              CALL_KW                  4

 21           LIST_APPEND              1

 67           LOAD_GLOBAL              4 (sa)
              LOAD_ATTR                6 (Column)
              PUSH_NULL

 68           LOAD_CONST              49 ('updated_at')
              LOAD_GLOBAL              4 (sa)
              LOAD_ATTR               24 (DateTime)
              PUSH_NULL
              LOAD_CONST               3 (True)
              LOAD_CONST              47 (('timezone',))
              CALL_KW                  1
              LOAD_CONST              10 (False)

 69           LOAD_GLOBAL              4 (sa)
              LOAD_ATTR               20 (text)
              PUSH_NULL
              LOAD_CONST              48 ('now()')
              CALL                     1

 67           LOAD_CONST              30 (('nullable', 'server_default'))
              CALL_KW                  4

 21           LIST_APPEND              1

 71           LOAD_GLOBAL              4 (sa)
              LOAD_ATTR                6 (Column)
              PUSH_NULL
              LOAD_CONST              50 ('deleted_at')
              LOAD_GLOBAL              4 (sa)
              LOAD_ATTR               24 (DateTime)
              PUSH_NULL
              LOAD_CONST               3 (True)
              LOAD_CONST              47 (('timezone',))
              CALL_KW                  1
              LOAD_CONST               3 (True)
              LOAD_CONST              11 (('nullable',))
              CALL_KW                  3

 21           LIST_APPEND              1

 73           LOAD_GLOBAL              4 (sa)
              LOAD_ATTR               26 (UniqueConstraint)
              PUSH_NULL

 74           LOAD_CONST               6 ('owner_user_id')
              LOAD_CONST              15 ('phone_hash')

 75           LOAD_CONST              51 ('uq_contact_profiles_user_phone')

 73           LOAD_CONST              52 (('name',))
              CALL_KW                  3

 21           LIST_APPEND              1

 77           LOAD_GLOBAL              4 (sa)
              LOAD_ATTR               28 (CheckConstraint)
              PUSH_NULL

 78           LOAD_CONST              53 ("category IN ('business', 'friends', 'family', 'other')")

 79           LOAD_CONST              54 ('ck_contact_profiles_category')

 77           LOAD_CONST              52 (('name',))
              CALL_KW                  2

 21           LIST_APPEND              1

 81           LOAD_GLOBAL              4 (sa)
              LOAD_ATTR               28 (CheckConstraint)
              PUSH_NULL

 82           LOAD_CONST              55 ("ai_temperament_preset IS NULL OR ai_temperament_preset IN ('professional_polite', 'casual_friendly', 'short_and_direct', 'warm_and_supportive', 'formal', 'custom')")

 85           LOAD_CONST              56 ('ck_contact_profiles_temperament')

 81           LOAD_CONST              52 (('name',))
              CALL_KW                  2

 21           LIST_APPEND              1

 87           LOAD_GLOBAL              4 (sa)
              LOAD_ATTR               28 (CheckConstraint)
              PUSH_NULL

 88           LOAD_CONST              57 ("ai_swearing_rule IS NULL OR ai_swearing_rule IN ('no_swearing', 'mirror_caller', 'allow')")

 90           LOAD_CONST              58 ('ck_contact_profiles_swearing')

 87           LOAD_CONST              52 (('name',))
              CALL_KW                  2

 21           LIST_APPEND              1

 92           LOAD_GLOBAL              4 (sa)
              LOAD_ATTR               28 (CheckConstraint)
              PUSH_NULL

 93           LOAD_CONST              59 ("ai_greeting_template IS NULL OR ai_greeting_template IN ('standard', 'brief', 'formal', 'custom')")

 95           LOAD_CONST              60 ('ck_contact_profiles_greeting_template')

 92           LOAD_CONST              52 (('name',))
              CALL_KW                  2

 21           LIST_APPEND              1
              CALL_INTRINSIC_1         6 (INTRINSIC_LIST_TO_TUPLE)
              CALL_FUNCTION_EX         0
              POP_TOP

 98           LOAD_GLOBAL              0 (op)
              LOAD_ATTR               30 (create_index)
              PUSH_NULL

 99           LOAD_CONST              61 ('contact_profiles_user_idx')
              LOAD_CONST               1 ('contact_profiles')
              LOAD_CONST               6 ('owner_user_id')
              BUILD_LIST               1

 98           CALL                     3
              POP_TOP

101           LOAD_GLOBAL              0 (op)
              LOAD_ATTR               30 (create_index)
              PUSH_NULL

102           LOAD_CONST              62 ('contact_profiles_user_category_idx')
              LOAD_CONST               1 ('contact_profiles')

103           LOAD_CONST               6 ('owner_user_id')
              LOAD_CONST              27 ('category')
              BUILD_LIST               2

101           CALL                     3
              POP_TOP

107           LOAD_GLOBAL              0 (op)
              LOAD_ATTR               32 (add_column)
              PUSH_NULL

108           LOAD_CONST              63 ('user_settings')

109           LOAD_GLOBAL              4 (sa)
              LOAD_ATTR                6 (Column)
              PUSH_NULL

110           LOAD_CONST              64 ('contact_category_defaults')

111           LOAD_GLOBAL              4 (sa)
              LOAD_ATTR               34 (JSON)
              LOAD_CONST              10 (False)
              LOAD_GLOBAL              4 (sa)
              LOAD_ATTR               20 (text)
              PUSH_NULL
              LOAD_CONST              65 ("'{}'::jsonb")
              CALL                     1

109           LOAD_CONST              30 (('nullable', 'server_default'))
              CALL_KW                  4

107           CALL                     2
              POP_TOP

116           LOAD_GLOBAL              0 (op)
              LOAD_ATTR               36 (execute)
              PUSH_NULL
              LOAD_CONST              66 ("\n        INSERT INTO contact_profiles (\n            id, owner_user_id,\n            phone_ciphertext, phone_nonce, phone_key_version,\n            phone_hash, phone_last4,\n            display_name, company, relationship, email, notes,\n            category, is_vip, is_blocked,\n            created_at, updated_at\n        )\n        SELECT\n            gen_random_uuid(), v.owner_user_id,\n            v.phone_ciphertext, v.phone_nonce, v.phone_key_version,\n            v.phone_hash, v.phone_last4,\n            v.display_name, v.company, v.relationship, v.email, v.notes,\n            'other', true, false,\n            v.created_at, v.updated_at\n        FROM vip_entries v\n        ON CONFLICT (owner_user_id, phone_hash) DO UPDATE\n            SET is_vip = true\n    ")
              CALL                     1
              POP_TOP

138           LOAD_GLOBAL              0 (op)
              LOAD_ATTR               36 (execute)
              PUSH_NULL
              LOAD_CONST              67 ("\n        INSERT INTO contact_profiles (\n            id, owner_user_id,\n            phone_ciphertext, phone_nonce, phone_key_version,\n            phone_hash, phone_last4,\n            display_name, company, relationship, email, notes,\n            category, is_vip, is_blocked, block_reason,\n            created_at, updated_at\n        )\n        SELECT\n            gen_random_uuid(), b.owner_user_id,\n            b.phone_ciphertext, b.phone_nonce, b.phone_key_version,\n            b.phone_hash, b.phone_last4,\n            b.display_name, b.company, b.relationship, b.email, b.notes,\n            'other', false, true, b.reason,\n            b.created_at, b.updated_at\n        FROM block_entries b\n        ON CONFLICT (owner_user_id, phone_hash) DO UPDATE\n            SET is_blocked = true,\n                block_reason = EXCLUDED.block_reason\n    ")
              CALL                     1
              POP_TOP
              RETURN_CONST             0 (None)

Disassembly of <code object downgrade at 0x00000185CB7D5E30, file "D:\fluence\Github\mattbot\backend\alembic\versions\028_contact_profiles_and_category_defaults.py", line 161>:
161           RESUME                   0

162           LOAD_GLOBAL              0 (op)
              LOAD_ATTR                2 (drop_column)
              PUSH_NULL
              LOAD_CONST               1 ('user_settings')
              LOAD_CONST               2 ('contact_category_defaults')
              CALL                     2
              POP_TOP

163           LOAD_GLOBAL              0 (op)
              LOAD_ATTR                4 (drop_index)
              PUSH_NULL
              LOAD_CONST               3 ('contact_profiles_user_category_idx')
              LOAD_CONST               4 ('contact_profiles')
              LOAD_CONST               5 (('table_name',))
              CALL_KW                  2
              POP_TOP

164           LOAD_GLOBAL              0 (op)
              LOAD_ATTR                4 (drop_index)
              PUSH_NULL
              LOAD_CONST               6 ('contact_profiles_user_idx')
              LOAD_CONST               4 ('contact_profiles')
              LOAD_CONST               5 (('table_name',))
              CALL_KW                  2
              POP_TOP

165           LOAD_GLOBAL              0 (op)
              LOAD_ATTR                6 (drop_table)
              PUSH_NULL
              LOAD_CONST               4 ('contact_profiles')
              CALL                     1
              POP_TOP
              RETURN_CONST             0 (None)
