# Bytecode dump of: agent.cpython-313.pyc
# co_filename: D:\fluence\Github\mattbot\backend\app\models\agent.py
# co_names: ('__doc__', 'uuid', 'datetime', 'UTC', 'sqlalchemy', 'Boolean', 'CheckConstraint', 'ForeignKey', 'Index', 'String', 'Text', 'text', 'sqlalchemy.dialects.postgresql', 'UUID', 'sqlalchemy.orm', 'Mapped', 'mapped_column', 'relationship', 'app.database', 'Base', 'app.models._types', 'tz_datetime', 'Agent')
# co_consts (strings): ['Agent model. Each user has one default agent in Phase 1, multi-agent ready.', 'Agent']

# DOCSTRING: """Agent model. Each user has one default agent in Phase 1, multi-agent ready."""
# --- Nested code object: Agent ---
    # DOCSTRING: """Agent"""
    # --- Nested code object: Agent.<lambda> ---
        # co_names: ('datetime', 'now', 'UTC')
        # co_varnames: ()
         56           RESUME                   0
                      LOAD_GLOBAL              0 (datetime)
                      LOAD_ATTR                2 (now)
                      PUSH_NULL
                      LOAD_GLOBAL              4 (UTC)
                      CALL                     1
                      RETURN_VALUE
        
    # co_names: ('__name__', '__module__', '__qualname__', '__firstlineno__', '__tablename__', 'mapped_column', 'UUID', 'uuid', 'uuid4', 'id', 'Mapped', '__annotations__', 'ForeignKey', 'owner_user_id', 'Text', 'text', 'display_name', 'str', 'String', 'function_type', 'Boolean', 'is_default', 'bool', 'status', 'elevenlabs_agent_id', 'tz_datetime', 'created_at', 'datetime', 'updated_at', 'relationship', 'user', 'config', 'CheckConstraint', 'Index', '__table_args__', '__static_attributes__')
    # co_varnames: ()
     22           RESUME                   0
                  LOAD_NAME                0 (__name__)
                  STORE_NAME               1 (__module__)
                  LOAD_CONST               0 ('Agent')
                  STORE_NAME               2 (__qualname__)
                  LOAD_CONST               1 (22)
                  STORE_NAME               3 (__firstlineno__)
                  SETUP_ANNOTATIONS
    
     23           LOAD_CONST               2 ('agents')
                  STORE_NAME               4 (__tablename__)
    
     25           LOAD_NAME                5 (mapped_column)
                  PUSH_NULL
    
     26           LOAD_NAME                6 (UUID)
                  PUSH_NULL
                  LOAD_CONST               3 (True)
                  LOAD_CONST               4 (('as_uuid',))
                  CALL_KW                  1
                  LOAD_CONST               3 (True)
                  LOAD_NAME                7 (uuid)
                  LOAD_ATTR               16 (uuid4)
    
     25           LOAD_CONST               5 (('primary_key', 'default'))
                  CALL_KW                  3
                  STORE_NAME               9 (id)
                  LOAD_NAME               10 (Mapped)
                  LOAD_NAME                7 (uuid)
                  LOAD_ATTR               12 (UUID)
                  BINARY_SUBSCR
                  LOAD_NAME               11 (__annotations__)
                  LOAD_CONST               6 ('id')
                  STORE_SUBSCR
    
     28           LOAD_NAME                5 (mapped_column)
                  PUSH_NULL
    
     29           LOAD_NAME                6 (UUID)
                  PUSH_NULL
                  LOAD_CONST               3 (True)
                  LOAD_CONST               4 (('as_uuid',))
                  CALL_KW                  1
    
     30           LOAD_NAME               12 (ForeignKey)
                  PUSH_NULL
                  LOAD_CONST               7 ('users.id')
                  LOAD_CONST               8 ('CASCADE')
                  LOAD_CONST               9 (('ondelete',))
                  CALL_KW                  2
    
     31           LOAD_CONST              10 (False)
    
     28           LOAD_CONST              11 (('nullable',))
                  CALL_KW                  3
                  STORE_NAME              13 (owner_user_id)
                  LOAD_NAME               10 (Mapped)
                  LOAD_NAME                7 (uuid)
                  LOAD_ATTR               12 (UUID)
                  BINARY_SUBSCR
                  LOAD_NAME               11 (__annotations__)
                  LOAD_CONST              12 ('owner_user_id')
                  STORE_SUBSCR
    
     33           LOAD_NAME                5 (mapped_column)
                  PUSH_NULL
    
     34           LOAD_NAME               14 (Text)
                  LOAD_CONST              10 (False)
                  LOAD_NAME               15 (text)
                  PUSH_NULL
                  LOAD_CONST              13 ("'Call Screener'")
                  CALL                     1
    
     33           LOAD_CONST              14 (('nullable', 'server_default'))
                  CALL_KW                  3
                  STORE_NAME              16 (display_name)
                  LOAD_NAME               10 (Mapped)
                  LOAD_NAME               17 (str)
                  BINARY_SUBSCR
                  LOAD_NAME               11 (__annotations__)
                  LOAD_CONST              15 ('display_name')
                  STORE_SUBSCR
    
     36           LOAD_NAME                5 (mapped_column)
                  PUSH_NULL
    
     37           LOAD_NAME               18 (String)
                  PUSH_NULL
                  LOAD_CONST              16 (40)
                  CALL                     1
                  LOAD_CONST              10 (False)
                  LOAD_NAME               15 (text)
                  PUSH_NULL
                  LOAD_CONST              17 ("'call_screener'")
                  CALL                     1
    
     36           LOAD_CONST              14 (('nullable', 'server_default'))
                  CALL_KW                  3
                  STORE_NAME              19 (function_type)
                  LOAD_NAME               10 (Mapped)
                  LOAD_NAME               17 (str)
                  BINARY_SUBSCR
                  LOAD_NAME               11 (__annotations__)
                  LOAD_CONST              18 ('function_type')
                  STORE_SUBSCR
    
     39           LOAD_NAME                5 (mapped_column)
                  PUSH_NULL
    
     40           LOAD_NAME               20 (Boolean)
                  LOAD_CONST              10 (False)
                  LOAD_NAME               15 (text)
                  PUSH_NULL
                  LOAD_CONST              19 ('true')
                  CALL                     1
    
     39           LOAD_CONST              14 (('nullable', 'server_default'))
                  CALL_KW                  3
                  STORE_NAME              21 (is_default)
                  LOAD_NAME               10 (Mapped)
                  LOAD_NAME               22 (bool)
                  BINARY_SUBSCR
                  LOAD_NAME               11 (__annotations__)
                  LOAD_CONST              20 ('is_default')
                  STORE_SUBSCR
    
     42           LOAD_NAME                5 (mapped_column)
                  PUSH_NULL
    
     43           LOAD_NAME               18 (String)
                  PUSH_NULL
                  LOAD_CONST              21 (20)
                  CALL                     1
                  LOAD_CONST              10 (False)
                  LOAD_NAME               15 (text)
                  PUSH_NULL
                  LOAD_CONST              22 ("'active'")
                  CALL                     1
    
     42           LOAD_CONST              14 (('nullable', 'server_default'))
                  CALL_KW                  3
                  STORE_NAME              23 (status)
                  LOAD_NAME               10 (Mapped)
                  LOAD_NAME               17 (str)
                  BINARY_SUBSCR
                  LOAD_NAME               11 (__annotations__)
                  LOAD_CONST              23 ('status')
                  STORE_SUBSCR
    
     45           LOAD_NAME                5 (mapped_column)
                  PUSH_NULL
    
     46           LOAD_NAME               18 (String)
                  PUSH_NULL
                  LOAD_CONST              24 (50)
                  CALL                     1
                  LOAD_CONST               3 (True)
    
     45           LOAD_CONST              11 (('nullable',))
                  CALL_KW                  2
                  STORE_NAME              24 (elevenlabs_agent_id)
                  LOAD_NAME               10 (Mapped)
                  LOAD_NAME               17 (str)
                  LOAD_CONST              25 (None)
                  BINARY_OP                7 (|)
                  BINARY_SUBSCR
                  LOAD_NAME               11 (__annotations__)
                  LOAD_CONST              26 ('elevenlabs_agent_id')
                  STORE_SUBSCR
    
     49           LOAD_NAME                5 (mapped_column)
                  PUSH_NULL
    
     50           LOAD_NAME               25 (tz_datetime)
                  PUSH_NULL
                  CALL                     0
                  LOAD_CONST              10 (False)
                  LOAD_NAME               15 (text)
                  PUSH_NULL
                  LOAD_CONST              27 ('now()')
                  CALL                     1
    
     49           LOAD_CONST              14 (('nullable', 'server_default'))
                  CALL_KW                  3
                  STORE_NAME              26 (created_at)
                  LOAD_NAME               10 (Mapped)
                  LOAD_NAME               27 (datetime)
                  BINARY_SUBSCR
                  LOAD_NAME               11 (__annotations__)
                  LOAD_CONST              28 ('created_at')
                  STORE_SUBSCR
    
     52           LOAD_NAME                5 (mapped_column)
                  PUSH_NULL
    
     53           LOAD_NAME               25 (tz_datetime)
                  PUSH_NULL
                  CALL                     0
    
     54           LOAD_CONST              10 (False)
    
     55           LOAD_NAME               15 (text)
                  PUSH_NULL
                  LOAD_CONST              27 ('now()')
                  CALL                     1
    
     56           LOAD_CONST              29 (<code object <lambda> at 0x0000024C11423930, file "D:\fluence\Github\mattbot\backend\app\models\agent.py", line 56>)
                  MAKE_FUNCTION
    
     52           LOAD_CONST              30 (('nullable', 'server_default', 'onupdate'))
                  CALL_KW                  4
                  STORE_NAME              28 (updated_at)
                  LOAD_NAME               10 (Mapped)
                  LOAD_NAME               27 (datetime)
                  BINARY_SUBSCR
                  LOAD_NAME               11 (__annotations__)
                  LOAD_CONST              31 ('updated_at')
                  STORE_SUBSCR
    
     59           LOAD_NAME               29 (relationship)
                  PUSH_NULL
                  LOAD_CONST               2 ('agents')
                  LOAD_CONST              32 (('back_populates',))
                  CALL_KW                  1
                  STORE_NAME              30 (user)
                  LOAD_NAME               10 (Mapped)
                  LOAD_CONST              33 ('User')
                  BINARY_SUBSCR
                  LOAD_NAME               11 (__annotations__)
                  LOAD_CONST              34 ('user')
                  STORE_SUBSCR
    
     61           LOAD_NAME               29 (relationship)
                  PUSH_NULL
    
     62           LOAD_CONST              35 ('agent')
    
     63           LOAD_CONST              36 ('all, delete-orphan')
    
     64           LOAD_CONST              10 (False)
    
     61           LOAD_CONST              37 (('back_populates', 'cascade', 'uselist'))
                  CALL_KW                  3
                  STORE_NAME              31 (config)
                  LOAD_NAME               10 (Mapped)
                  LOAD_CONST              38 ('AgentConfig | None')
                  BINARY_SUBSCR
                  LOAD_NAME               11 (__annotations__)
                  LOAD_CONST              39 ('config')
                  STORE_SUBSCR
    
     68           LOAD_NAME               32 (CheckConstraint)
                  PUSH_NULL
    
     69           LOAD_CONST              40 ("status IN ('active', 'archived')")
    
     70           LOAD_CONST              41 ('ck_agents_status')
    
     68           LOAD_CONST              42 (('name',))
                  CALL_KW                  2
    
     72           LOAD_NAME               33 (Index)
                  PUSH_NULL
    
     73           LOAD_CONST              43 ('uq_agents_user_default')
    
     74           LOAD_CONST              12 ('owner_user_id')
    
     75           LOAD_CONST               3 (True)
    
     76           LOAD_NAME               15 (text)
                  PUSH_NULL
                  LOAD_CONST              44 ('is_default = true')
                  CALL                     1
    
     72           LOAD_CONST              45 (('unique', 'postgresql_where'))
                  CALL_KW                  4
    
     78           LOAD_NAME               33 (Index)
                  PUSH_NULL
                  LOAD_CONST              46 ('agents_owner_user_id_idx')
                  LOAD_CONST              12 ('owner_user_id')
                  CALL                     2
    
     67           BUILD_TUPLE              3
                  STORE_NAME              34 (__table_args__)
                  LOAD_CONST              47 (())
                  STORE_NAME              35 (__static_attributes__)
                  RETURN_CONST            25 (None)
    
    Disassembly of <code object <lambda> at 0x0000024C11423930, file "D:\fluence\Github\mattbot\backend\app\models\agent.py", line 56>:
     56           RESUME                   0
                  LOAD_GLOBAL              0 (datetime)
                  LOAD_ATTR                2 (now)
                  PUSH_NULL
                  LOAD_GLOBAL              4 (UTC)
                  CALL                     1
                  RETURN_VALUE
    
# co_names: ('__doc__', 'uuid', 'datetime', 'UTC', 'sqlalchemy', 'Boolean', 'CheckConstraint', 'ForeignKey', 'Index', 'String', 'Text', 'text', 'sqlalchemy.dialects.postgresql', 'UUID', 'sqlalchemy.orm', 'Mapped', 'mapped_column', 'relationship', 'app.database', 'Base', 'app.models._types', 'tz_datetime', 'Agent')
# co_varnames: ()
  0           RESUME                   0

  1           LOAD_CONST               0 ('Agent model. Each user has one default agent in Phase 1, multi-agent ready.')
              STORE_NAME               0 (__doc__)

  3           LOAD_CONST               1 (0)
              LOAD_CONST               2 (None)
              IMPORT_NAME              1 (uuid)
              STORE_NAME               1 (uuid)

  4           LOAD_CONST               1 (0)
              LOAD_CONST               3 (('UTC', 'datetime'))
              IMPORT_NAME              2 (datetime)
              IMPORT_FROM              3 (UTC)
              STORE_NAME               3 (UTC)
              IMPORT_FROM              2 (datetime)
              STORE_NAME               2 (datetime)
              POP_TOP

  6           LOAD_CONST               1 (0)
              LOAD_CONST               4 (('Boolean', 'CheckConstraint', 'ForeignKey', 'Index', 'String', 'Text', 'text'))
              IMPORT_NAME              4 (sqlalchemy)
              IMPORT_FROM              5 (Boolean)
              STORE_NAME               5 (Boolean)
              IMPORT_FROM              6 (CheckConstraint)
              STORE_NAME               6 (CheckConstraint)
              IMPORT_FROM              7 (ForeignKey)
              STORE_NAME               7 (ForeignKey)
              IMPORT_FROM              8 (Index)
              STORE_NAME               8 (Index)
              IMPORT_FROM              9 (String)
              STORE_NAME               9 (String)
              IMPORT_FROM             10 (Text)
              STORE_NAME              10 (Text)
              IMPORT_FROM             11 (text)
              STORE_NAME              11 (text)
              POP_TOP

 15           LOAD_CONST               1 (0)
              LOAD_CONST               5 (('UUID',))
              IMPORT_NAME             12 (sqlalchemy.dialects.postgresql)
              IMPORT_FROM             13 (UUID)
              STORE_NAME              13 (UUID)
              POP_TOP

 16           LOAD_CONST               1 (0)
              LOAD_CONST               6 (('Mapped', 'mapped_column', 'relationship'))
              IMPORT_NAME             14 (sqlalchemy.orm)
              IMPORT_FROM             15 (Mapped)
              STORE_NAME              15 (Mapped)
              IMPORT_FROM             16 (mapped_column)
              STORE_NAME              16 (mapped_column)
              IMPORT_FROM             17 (relationship)
              STORE_NAME              17 (relationship)
              POP_TOP

 18           LOAD_CONST               1 (0)
              LOAD_CONST               7 (('Base',))
              IMPORT_NAME             18 (app.database)
              IMPORT_FROM             19 (Base)
              STORE_NAME              19 (Base)
              POP_TOP

 19           LOAD_CONST               1 (0)
              LOAD_CONST               8 (('tz_datetime',))
              IMPORT_NAME             20 (app.models._types)
              IMPORT_FROM             21 (tz_datetime)
              STORE_NAME              21 (tz_datetime)
              POP_TOP

 22           LOAD_BUILD_CLASS
              PUSH_NULL
              LOAD_CONST               9 (<code object Agent at 0x0000024C0FCA3570, file "D:\fluence\Github\mattbot\backend\app\models\agent.py", line 22>)
              MAKE_FUNCTION
              LOAD_CONST              10 ('Agent')
              LOAD_NAME               19 (Base)
              CALL                     3
              STORE_NAME              22 (Agent)
              RETURN_CONST             2 (None)

Disassembly of <code object Agent at 0x0000024C0FCA3570, file "D:\fluence\Github\mattbot\backend\app\models\agent.py", line 22>:
 22           RESUME                   0
              LOAD_NAME                0 (__name__)
              STORE_NAME               1 (__module__)
              LOAD_CONST               0 ('Agent')
              STORE_NAME               2 (__qualname__)
              LOAD_CONST               1 (22)
              STORE_NAME               3 (__firstlineno__)
              SETUP_ANNOTATIONS

 23           LOAD_CONST               2 ('agents')
              STORE_NAME               4 (__tablename__)

 25           LOAD_NAME                5 (mapped_column)
              PUSH_NULL

 26           LOAD_NAME                6 (UUID)
              PUSH_NULL
              LOAD_CONST               3 (True)
              LOAD_CONST               4 (('as_uuid',))
              CALL_KW                  1
              LOAD_CONST               3 (True)
              LOAD_NAME                7 (uuid)
              LOAD_ATTR               16 (uuid4)

 25           LOAD_CONST               5 (('primary_key', 'default'))
              CALL_KW                  3
              STORE_NAME               9 (id)
              LOAD_NAME               10 (Mapped)
              LOAD_NAME                7 (uuid)
              LOAD_ATTR               12 (UUID)
              BINARY_SUBSCR
              LOAD_NAME               11 (__annotations__)
              LOAD_CONST               6 ('id')
              STORE_SUBSCR

 28           LOAD_NAME                5 (mapped_column)
              PUSH_NULL

 29           LOAD_NAME                6 (UUID)
              PUSH_NULL
              LOAD_CONST               3 (True)
              LOAD_CONST               4 (('as_uuid',))
              CALL_KW                  1

 30           LOAD_NAME               12 (ForeignKey)
              PUSH_NULL
              LOAD_CONST               7 ('users.id')
              LOAD_CONST               8 ('CASCADE')
              LOAD_CONST               9 (('ondelete',))
              CALL_KW                  2

 31           LOAD_CONST              10 (False)

 28           LOAD_CONST              11 (('nullable',))
              CALL_KW                  3
              STORE_NAME              13 (owner_user_id)
              LOAD_NAME               10 (Mapped)
              LOAD_NAME                7 (uuid)
              LOAD_ATTR               12 (UUID)
              BINARY_SUBSCR
              LOAD_NAME               11 (__annotations__)
              LOAD_CONST              12 ('owner_user_id')
              STORE_SUBSCR

 33           LOAD_NAME                5 (mapped_column)
              PUSH_NULL

 34           LOAD_NAME               14 (Text)
              LOAD_CONST              10 (False)
              LOAD_NAME               15 (text)
              PUSH_NULL
              LOAD_CONST              13 ("'Call Screener'")
              CALL                     1

 33           LOAD_CONST              14 (('nullable', 'server_default'))
              CALL_KW                  3
              STORE_NAME              16 (display_name)
              LOAD_NAME               10 (Mapped)
              LOAD_NAME               17 (str)
              BINARY_SUBSCR
              LOAD_NAME               11 (__annotations__)
              LOAD_CONST              15 ('display_name')
              STORE_SUBSCR

 36           LOAD_NAME                5 (mapped_column)
              PUSH_NULL

 37           LOAD_NAME               18 (String)
              PUSH_NULL
              LOAD_CONST              16 (40)
              CALL                     1
              LOAD_CONST              10 (False)
              LOAD_NAME               15 (text)
              PUSH_NULL
              LOAD_CONST              17 ("'call_screener'")
              CALL                     1

 36           LOAD_CONST              14 (('nullable', 'server_default'))
              CALL_KW                  3
              STORE_NAME              19 (function_type)
              LOAD_NAME               10 (Mapped)
              LOAD_NAME               17 (str)
              BINARY_SUBSCR
              LOAD_NAME               11 (__annotations__)
              LOAD_CONST              18 ('function_type')
              STORE_SUBSCR

 39           LOAD_NAME                5 (mapped_column)
              PUSH_NULL

 40           LOAD_NAME               20 (Boolean)
              LOAD_CONST              10 (False)
              LOAD_NAME               15 (text)
              PUSH_NULL
              LOAD_CONST              19 ('true')
              CALL                     1

 39           LOAD_CONST              14 (('nullable', 'server_default'))
              CALL_KW                  3
              STORE_NAME              21 (is_default)
              LOAD_NAME               10 (Mapped)
              LOAD_NAME               22 (bool)
              BINARY_SUBSCR
              LOAD_NAME               11 (__annotations__)
              LOAD_CONST              20 ('is_default')
              STORE_SUBSCR

 42           LOAD_NAME                5 (mapped_column)
              PUSH_NULL

 43           LOAD_NAME               18 (String)
              PUSH_NULL
              LOAD_CONST              21 (20)
              CALL                     1
              LOAD_CONST              10 (False)
              LOAD_NAME               15 (text)
              PUSH_NULL
              LOAD_CONST              22 ("'active'")
              CALL                     1

 42           LOAD_CONST              14 (('nullable', 'server_default'))
              CALL_KW                  3
              STORE_NAME              23 (status)
              LOAD_NAME               10 (Mapped)
              LOAD_NAME               17 (str)
              BINARY_SUBSCR
              LOAD_NAME               11 (__annotations__)
              LOAD_CONST              23 ('status')
              STORE_SUBSCR

 45           LOAD_NAME                5 (mapped_column)
              PUSH_NULL

 46           LOAD_NAME               18 (String)
              PUSH_NULL
              LOAD_CONST              24 (50)
              CALL                     1
              LOAD_CONST               3 (True)

 45           LOAD_CONST              11 (('nullable',))
              CALL_KW                  2
              STORE_NAME              24 (elevenlabs_agent_id)
              LOAD_NAME               10 (Mapped)
              LOAD_NAME               17 (str)
              LOAD_CONST              25 (None)
              BINARY_OP                7 (|)
              BINARY_SUBSCR
              LOAD_NAME               11 (__annotations__)
              LOAD_CONST              26 ('elevenlabs_agent_id')
              STORE_SUBSCR

 49           LOAD_NAME                5 (mapped_column)
              PUSH_NULL

 50           LOAD_NAME               25 (tz_datetime)
              PUSH_NULL
              CALL                     0
              LOAD_CONST              10 (False)
              LOAD_NAME               15 (text)
              PUSH_NULL
              LOAD_CONST              27 ('now()')
              CALL                     1

 49           LOAD_CONST              14 (('nullable', 'server_default'))
              CALL_KW                  3
              STORE_NAME              26 (created_at)
              LOAD_NAME               10 (Mapped)
              LOAD_NAME               27 (datetime)
              BINARY_SUBSCR
              LOAD_NAME               11 (__annotations__)
              LOAD_CONST              28 ('created_at')
              STORE_SUBSCR

 52           LOAD_NAME                5 (mapped_column)
              PUSH_NULL

 53           LOAD_NAME               25 (tz_datetime)
              PUSH_NULL
              CALL                     0

 54           LOAD_CONST              10 (False)

 55           LOAD_NAME               15 (text)
              PUSH_NULL
              LOAD_CONST              27 ('now()')
              CALL                     1

 56           LOAD_CONST              29 (<code object <lambda> at 0x0000024C11423930, file "D:\fluence\Github\mattbot\backend\app\models\agent.py", line 56>)
              MAKE_FUNCTION

 52           LOAD_CONST              30 (('nullable', 'server_default', 'onupdate'))
              CALL_KW                  4
              STORE_NAME              28 (updated_at)
              LOAD_NAME               10 (Mapped)
              LOAD_NAME               27 (datetime)
              BINARY_SUBSCR
              LOAD_NAME               11 (__annotations__)
              LOAD_CONST              31 ('updated_at')
              STORE_SUBSCR

 59           LOAD_NAME               29 (relationship)
              PUSH_NULL
              LOAD_CONST               2 ('agents')
              LOAD_CONST              32 (('back_populates',))
              CALL_KW                  1
              STORE_NAME              30 (user)
              LOAD_NAME               10 (Mapped)
              LOAD_CONST              33 ('User')
              BINARY_SUBSCR
              LOAD_NAME               11 (__annotations__)
              LOAD_CONST              34 ('user')
              STORE_SUBSCR

 61           LOAD_NAME               29 (relationship)
              PUSH_NULL

 62           LOAD_CONST              35 ('agent')

 63           LOAD_CONST              36 ('all, delete-orphan')

 64           LOAD_CONST              10 (False)

 61           LOAD_CONST              37 (('back_populates', 'cascade', 'uselist'))
              CALL_KW                  3
              STORE_NAME              31 (config)
              LOAD_NAME               10 (Mapped)
              LOAD_CONST              38 ('AgentConfig | None')
              BINARY_SUBSCR
              LOAD_NAME               11 (__annotations__)
              LOAD_CONST              39 ('config')
              STORE_SUBSCR

 68           LOAD_NAME               32 (CheckConstraint)
              PUSH_NULL

 69           LOAD_CONST              40 ("status IN ('active', 'archived')")

 70           LOAD_CONST              41 ('ck_agents_status')

 68           LOAD_CONST              42 (('name',))
              CALL_KW                  2

 72           LOAD_NAME               33 (Index)
              PUSH_NULL

 73           LOAD_CONST              43 ('uq_agents_user_default')

 74           LOAD_CONST              12 ('owner_user_id')

 75           LOAD_CONST               3 (True)

 76           LOAD_NAME               15 (text)
              PUSH_NULL
              LOAD_CONST              44 ('is_default = true')
              CALL                     1

 72           LOAD_CONST              45 (('unique', 'postgresql_where'))
              CALL_KW                  4

 78           LOAD_NAME               33 (Index)
              PUSH_NULL
              LOAD_CONST              46 ('agents_owner_user_id_idx')
              LOAD_CONST              12 ('owner_user_id')
              CALL                     2

 67           BUILD_TUPLE              3
              STORE_NAME              34 (__table_args__)
              LOAD_CONST              47 (())
              STORE_NAME              35 (__static_attributes__)
              RETURN_CONST            25 (None)

Disassembly of <code object <lambda> at 0x0000024C11423930, file "D:\fluence\Github\mattbot\backend\app\models\agent.py", line 56>:
 56           RESUME                   0
              LOAD_GLOBAL              0 (datetime)
              LOAD_ATTR                2 (now)
              PUSH_NULL
              LOAD_GLOBAL              4 (UTC)
              CALL                     1
              RETURN_VALUE
