# Bytecode dump of: contact_profile.cpython-313.pyc
# co_filename: D:\fluence\Github\mattbot\backend\app\models\contact_profile.py
# co_names: ('__doc__', 'uuid', 'datetime', 'UTC', 'sqlalchemy', 'Boolean', 'CheckConstraint', 'ForeignKey', 'Index', 'Integer', 'LargeBinary', 'String', 'Text', 'UniqueConstraint', 'text', 'sqlalchemy.dialects.postgresql', 'UUID', 'sqlalchemy.orm', 'Mapped', 'mapped_column', 'app.database', 'Base', 'app.models._types', 'tz_datetime', '_TEMPERAMENT_CHECK', '_SWEARING_CHECK', '_GREETING_TEMPLATE_CHECK', 'ContactProfile')
# co_consts (strings): ['Unified contact profile: replaces separate VIP / block entries.\n\nEach row represents a known caller whose AI interactions the owner has\ncustomised (category, temperament, greeting, blocking, VIP status, etc.).\n', "ai_temperament_preset IS NULL OR ai_temperament_preset IN ('professional_polite', 'casual_friendly', 'short_and_direct', 'warm_and_supportive', 'formal', 'custom')", "ai_swearing_rule IS NULL OR ai_swearing_rule IN ('no_swearing', 'mirror_caller', 'allow')", "ai_greeting_template IS NULL OR ai_greeting_template IN ('standard', 'brief', 'formal', 'custom')", 'ContactProfile']

# DOCSTRING: """Unified contact profile: replaces separate VIP / block entries.

Each row represents a known caller whose AI interactions the owner has
customised (category, temperament, greeting, blocking, VIP status, etc.).
"""
# --- Nested code object: ContactProfile ---
    # DOCSTRING: """ContactProfile"""
    # --- Nested code object: ContactProfile.<lambda> ---
        # co_names: ('datetime', 'now', 'UTC')
        # co_varnames: ()
        123           RESUME                   0
                      LOAD_GLOBAL              0 (datetime)
                      LOAD_ATTR                2 (now)
                      PUSH_NULL
                      LOAD_GLOBAL              4 (UTC)
                      CALL                     1
                      RETURN_VALUE
        
    # co_names: ('__name__', '__module__', '__qualname__', '__firstlineno__', '__tablename__', 'mapped_column', 'UUID', 'uuid', 'uuid4', 'id', 'Mapped', '__annotations__', 'ForeignKey', 'owner_user_id', 'LargeBinary', 'phone_ciphertext', 'bytes', 'phone_nonce', 'Integer', 'phone_key_version', 'int', 'String', 'phone_hash', 'str', 'phone_last4', 'Text', 'display_name', 'company', 'relationship', 'email', 'notes', 'text', 'category', 'Boolean', 'is_vip', 'bool', 'is_blocked', 'block_reason', 'ai_temperament_preset', 'ai_greeting_template', 'ai_greeting_instructions_ciphertext', 'ai_greeting_instructions_nonce', 'ai_greeting_instructions_key_version', 'ai_swearing_rule', 'ai_max_call_length_seconds', 'ai_custom_instructions_ciphertext', 'ai_custom_instructions_nonce', 'ai_custom_instructions_key_version', 'tz_datetime', 'created_at', 'datetime', 'updated_at', 'deleted_at', 'UniqueConstraint', 'Index', 'CheckConstraint', '_TEMPERAMENT_CHECK', '_SWEARING_CHECK', '_GREETING_TEMPLATE_CHECK', '__table_args__', '__static_attributes__')
    # co_varnames: ()
     45           RESUME                   0
                  LOAD_NAME                0 (__name__)
                  STORE_NAME               1 (__module__)
                  LOAD_CONST               0 ('ContactProfile')
                  STORE_NAME               2 (__qualname__)
                  LOAD_CONST               1 (45)
                  STORE_NAME               3 (__firstlineno__)
                  SETUP_ANNOTATIONS
    
     46           LOAD_CONST               2 ('contact_profiles')
                  STORE_NAME               4 (__tablename__)
    
     48           LOAD_NAME                5 (mapped_column)
                  PUSH_NULL
    
     49           LOAD_NAME                6 (UUID)
                  PUSH_NULL
                  LOAD_CONST               3 (True)
                  LOAD_CONST               4 (('as_uuid',))
                  CALL_KW                  1
                  LOAD_CONST               3 (True)
                  LOAD_NAME                7 (uuid)
                  LOAD_ATTR               16 (uuid4)
    
     48           LOAD_CONST               5 (('primary_key', 'default'))
                  CALL_KW                  3
                  STORE_NAME               9 (id)
                  LOAD_NAME               10 (Mapped)
                  LOAD_NAME                7 (uuid)
                  LOAD_ATTR               12 (UUID)
                  BINARY_SUBSCR
                  LOAD_NAME               11 (__annotations__)
                  LOAD_CONST               6 ('id')
                  STORE_SUBSCR
    
     51           LOAD_NAME                5 (mapped_column)
                  PUSH_NULL
    
     52           LOAD_NAME                6 (UUID)
                  PUSH_NULL
                  LOAD_CONST               3 (True)
                  LOAD_CONST               4 (('as_uuid',))
                  CALL_KW                  1
    
     53           LOAD_NAME               12 (ForeignKey)
                  PUSH_NULL
                  LOAD_CONST               7 ('users.id')
                  LOAD_CONST               8 ('CASCADE')
                  LOAD_CONST               9 (('ondelete',))
                  CALL_KW                  2
    
     54           LOAD_CONST              10 (False)
    
     51           LOAD_CONST              11 (('nullable',))
                  CALL_KW                  3
                  STORE_NAME              13 (owner_user_id)
                  LOAD_NAME               10 (Mapped)
                  LOAD_NAME                7 (uuid)
                  LOAD_ATTR               12 (UUID)
                  BINARY_SUBSCR
                  LOAD_NAME               11 (__annotations__)
                  LOAD_CONST              12 ('owner_user_id')
                  STORE_SUBSCR
    
     58           LOAD_NAME                5 (mapped_column)
                  PUSH_NULL
                  LOAD_NAME               14 (LargeBinary)
                  LOAD_CONST              10 (False)
                  LOAD_CONST              11 (('nullable',))
                  CALL_KW                  2
                  STORE_NAME              15 (phone_ciphertext)
                  LOAD_NAME               10 (Mapped)
                  LOAD_NAME               16 (bytes)
                  BINARY_SUBSCR
                  LOAD_NAME               11 (__annotations__)
                  LOAD_CONST              13 ('phone_ciphertext')
                  STORE_SUBSCR
    
     59           LOAD_NAME                5 (mapped_column)
                  PUSH_NULL
                  LOAD_NAME               14 (LargeBinary)
                  LOAD_CONST              10 (False)
                  LOAD_CONST              11 (('nullable',))
                  CALL_KW                  2
                  STORE_NAME              17 (phone_nonce)
                  LOAD_NAME               10 (Mapped)
                  LOAD_NAME               16 (bytes)
                  BINARY_SUBSCR
                  LOAD_NAME               11 (__annotations__)
                  LOAD_CONST              14 ('phone_nonce')
                  STORE_SUBSCR
    
     60           LOAD_NAME                5 (mapped_column)
                  PUSH_NULL
                  LOAD_NAME               18 (Integer)
                  LOAD_CONST              10 (False)
                  LOAD_CONST              11 (('nullable',))
                  CALL_KW                  2
                  STORE_NAME              19 (phone_key_version)
                  LOAD_NAME               10 (Mapped)
                  LOAD_NAME               20 (int)
                  BINARY_SUBSCR
                  LOAD_NAME               11 (__annotations__)
                  LOAD_CONST              15 ('phone_key_version')
                  STORE_SUBSCR
    
     61           LOAD_NAME                5 (mapped_column)
                  PUSH_NULL
                  LOAD_NAME               21 (String)
                  PUSH_NULL
                  LOAD_CONST              16 (64)
                  CALL                     1
                  LOAD_CONST              10 (False)
                  LOAD_CONST              11 (('nullable',))
                  CALL_KW                  2
                  STORE_NAME              22 (phone_hash)
                  LOAD_NAME               10 (Mapped)
                  LOAD_NAME               23 (str)
                  BINARY_SUBSCR
                  LOAD_NAME               11 (__annotations__)
                  LOAD_CONST              17 ('phone_hash')
                  STORE_SUBSCR
    
     62           LOAD_NAME                5 (mapped_column)
                  PUSH_NULL
                  LOAD_NAME               21 (String)
                  PUSH_NULL
                  LOAD_CONST              18 (4)
                  CALL                     1
                  LOAD_CONST              10 (False)
                  LOAD_CONST              11 (('nullable',))
                  CALL_KW                  2
                  STORE_NAME              24 (phone_last4)
                  LOAD_NAME               10 (Mapped)
                  LOAD_NAME               23 (str)
                  BINARY_SUBSCR
                  LOAD_NAME               11 (__annotations__)
                  LOAD_CONST              19 ('phone_last4')
                  STORE_SUBSCR
    
     65           LOAD_NAME                5 (mapped_column)
                  PUSH_NULL
                  LOAD_NAME               25 (Text)
                  LOAD_CONST               3 (True)
                  LOAD_CONST              11 (('nullable',))
                  CALL_KW                  2
                  STORE_NAME              26 (display_name)
                  LOAD_NAME               10 (Mapped)
                  LOAD_NAME               23 (str)
                  LOAD_CONST              20 (None)
                  BINARY_OP                7 (|)
                  BINARY_SUBSCR
                  LOAD_NAME               11 (__annotations__)
                  LOAD_CONST              21 ('display_name')
                  STORE_SUBSCR
    
     66           LOAD_NAME                5 (mapped_column)
                  PUSH_NULL
                  LOAD_NAME               21 (String)
                  PUSH_NULL
                  LOAD_CONST              22 (200)
                  CALL                     1
                  LOAD_CONST               3 (True)
                  LOAD_CONST              11 (('nullable',))
                  CALL_KW                  2
                  STORE_NAME              27 (company)
                  LOAD_NAME               10 (Mapped)
                  LOAD_NAME               23 (str)
                  LOAD_CONST              20 (None)
                  BINARY_OP                7 (|)
                  BINARY_SUBSCR
                  LOAD_NAME               11 (__annotations__)
                  LOAD_CONST              23 ('company')
                  STORE_SUBSCR
    
     67           LOAD_NAME                5 (mapped_column)
                  PUSH_NULL
                  LOAD_NAME               21 (String)
                  PUSH_NULL
                  LOAD_CONST              24 (100)
                  CALL                     1
                  LOAD_CONST               3 (True)
                  LOAD_CONST              11 (('nullable',))
                  CALL_KW                  2
                  STORE_NAME              28 (relationship)
                  LOAD_NAME               10 (Mapped)
                  LOAD_NAME               23 (str)
                  LOAD_CONST              20 (None)
                  BINARY_OP                7 (|)
                  BINARY_SUBSCR
                  LOAD_NAME               11 (__annotations__)
                  LOAD_CONST              25 ('relationship')
                  STORE_SUBSCR
    
     68           LOAD_NAME                5 (mapped_column)
                  PUSH_NULL
                  LOAD_NAME               21 (String)
                  PUSH_NULL
                  LOAD_CONST              26 (254)
                  CALL                     1
                  LOAD_CONST               3 (True)
                  LOAD_CONST              11 (('nullable',))
                  CALL_KW                  2
                  STORE_NAME              29 (email)
                  LOAD_NAME               10 (Mapped)
                  LOAD_NAME               23 (str)
                  LOAD_CONST              20 (None)
                  BINARY_OP                7 (|)
                  BINARY_SUBSCR
                  LOAD_NAME               11 (__annotations__)
                  LOAD_CONST              27 ('email')
                  STORE_SUBSCR
    
     69           LOAD_NAME                5 (mapped_column)
                  PUSH_NULL
                  LOAD_NAME               25 (Text)
                  LOAD_CONST               3 (True)
                  LOAD_CONST              11 (('nullable',))
                  CALL_KW                  2
                  STORE_NAME              30 (notes)
                  LOAD_NAME               10 (Mapped)
                  LOAD_NAME               23 (str)
                  LOAD_CONST              20 (None)
                  BINARY_OP                7 (|)
                  BINARY_SUBSCR
                  LOAD_NAME               11 (__annotations__)
                  LOAD_CONST              28 ('notes')
                  STORE_SUBSCR
    
     72           LOAD_NAME                5 (mapped_column)
                  PUSH_NULL
    
     73           LOAD_NAME               21 (String)
                  PUSH_NULL
                  LOAD_CONST              29 (50)
                  CALL                     1
                  LOAD_CONST              10 (False)
                  LOAD_NAME               31 (text)
                  PUSH_NULL
                  LOAD_CONST              30 ("'other'")
                  CALL                     1
    
     72           LOAD_CONST              31 (('nullable', 'server_default'))
                  CALL_KW                  3
                  STORE_NAME              32 (category)
                  LOAD_NAME               10 (Mapped)
                  LOAD_NAME               23 (str)
                  BINARY_SUBSCR
                  LOAD_NAME               11 (__annotations__)
                  LOAD_CONST              32 ('category')
                  STORE_SUBSCR
    
     75           LOAD_NAME                5 (mapped_column)
                  PUSH_NULL
    
     76           LOAD_NAME               33 (Boolean)
                  LOAD_CONST              10 (False)
                  LOAD_NAME               31 (text)
                  PUSH_NULL
                  LOAD_CONST              33 ('false')
                  CALL                     1
    
     75           LOAD_CONST              31 (('nullable', 'server_default'))
                  CALL_KW                  3
                  STORE_NAME              34 (is_vip)
                  LOAD_NAME               10 (Mapped)
                  LOAD_NAME               35 (bool)
                  BINARY_SUBSCR
                  LOAD_NAME               11 (__annotations__)
                  LOAD_CONST              34 ('is_vip')
                  STORE_SUBSCR
    
     78           LOAD_NAME                5 (mapped_column)
                  PUSH_NULL
    
     79           LOAD_NAME               33 (Boolean)
                  LOAD_CONST              10 (False)
                  LOAD_NAME               31 (text)
                  PUSH_NULL
                  LOAD_CONST              33 ('false')
                  CALL                     1
    
     78           LOAD_CONST              31 (('nullable', 'server_default'))
                  CALL_KW                  3
                  STORE_NAME              36 (is_blocked)
                  LOAD_NAME               10 (Mapped)
                  LOAD_NAME               35 (bool)
                  BINARY_SUBSCR
                  LOAD_NAME               11 (__annotations__)
                  LOAD_CONST              35 ('is_blocked')
                  STORE_SUBSCR
    
     81           LOAD_NAME                5 (mapped_column)
                  PUSH_NULL
                  LOAD_NAME               25 (Text)
                  LOAD_CONST               3 (True)
                  LOAD_CONST              11 (('nullable',))
                  CALL_KW                  2
                  STORE_NAME              37 (block_reason)
                  LOAD_NAME               10 (Mapped)
                  LOAD_NAME               23 (str)
                  LOAD_CONST              20 (None)
                  BINARY_OP                7 (|)
                  BINARY_SUBSCR
                  LOAD_NAME               11 (__annotations__)
                  LOAD_CONST              36 ('block_reason')
                  STORE_SUBSCR
    
     84           LOAD_NAME                5 (mapped_column)
                  PUSH_NULL
    
     85           LOAD_NAME               21 (String)
                  PUSH_NULL
                  LOAD_CONST              37 (40)
                  CALL                     1
                  LOAD_CONST               3 (True)
    
     84           LOAD_CONST              11 (('nullable',))
                  CALL_KW                  2
                  STORE_NAME              38 (ai_temperament_preset)
                  LOAD_NAME               10 (Mapped)
                  LOAD_NAME               23 (str)
                  LOAD_CONST              20 (None)
                  BINARY_OP                7 (|)
                  BINARY_SUBSCR
                  LOAD_NAME               11 (__annotations__)
                  LOAD_CONST              38 ('ai_temperament_preset')
                  STORE_SUBSCR
    
     87           LOAD_NAME                5 (mapped_column)
                  PUSH_NULL
    
     88           LOAD_NAME               21 (String)
                  PUSH_NULL
                  LOAD_CONST              37 (40)
                  CALL                     1
                  LOAD_CONST               3 (True)
    
     87           LOAD_CONST              11 (('nullable',))
                  CALL_KW                  2
                  STORE_NAME              39 (ai_greeting_template)
                  LOAD_NAME               10 (Mapped)
                  LOAD_NAME               23 (str)
                  LOAD_CONST              20 (None)
                  BINARY_OP                7 (|)
                  BINARY_SUBSCR
                  LOAD_NAME               11 (__annotations__)
                  LOAD_CONST              39 ('ai_greeting_template')
                  STORE_SUBSCR
    
     90           LOAD_NAME                5 (mapped_column)
                  PUSH_NULL
    
     91           LOAD_NAME               14 (LargeBinary)
                  LOAD_CONST               3 (True)
    
     90           LOAD_CONST              11 (('nullable',))
                  CALL_KW                  2
                  STORE_NAME              40 (ai_greeting_instructions_ciphertext)
                  LOAD_NAME               10 (Mapped)
                  LOAD_NAME               16 (bytes)
                  LOAD_CONST              20 (None)
                  BINARY_OP                7 (|)
                  BINARY_SUBSCR
                  LOAD_NAME               11 (__annotations__)
                  LOAD_CONST              40 ('ai_greeting_instructions_ciphertext')
                  STORE_SUBSCR
    
     93           LOAD_NAME                5 (mapped_column)
                  PUSH_NULL
    
     94           LOAD_NAME               14 (LargeBinary)
                  LOAD_CONST               3 (True)
    
     93           LOAD_CONST              11 (('nullable',))
                  CALL_KW                  2
                  STORE_NAME              41 (ai_greeting_instructions_nonce)
                  LOAD_NAME               10 (Mapped)
                  LOAD_NAME               16 (bytes)
                  LOAD_CONST              20 (None)
                  BINARY_OP                7 (|)
                  BINARY_SUBSCR
                  LOAD_NAME               11 (__annotations__)
                  LOAD_CONST              41 ('ai_greeting_instructions_nonce')
                  STORE_SUBSCR
    
     96           LOAD_NAME                5 (mapped_column)
                  PUSH_NULL
    
     97           LOAD_NAME               18 (Integer)
                  LOAD_CONST               3 (True)
    
     96           LOAD_CONST              11 (('nullable',))
                  CALL_KW                  2
                  STORE_NAME              42 (ai_greeting_instructions_key_version)
                  LOAD_NAME               10 (Mapped)
                  LOAD_NAME               20 (int)
                  LOAD_CONST              20 (None)
                  BINARY_OP                7 (|)
                  BINARY_SUBSCR
                  LOAD_NAME               11 (__annotations__)
                  LOAD_CONST              42 ('ai_greeting_instructions_key_version')
                  STORE_SUBSCR
    
     99           LOAD_NAME                5 (mapped_column)
                  PUSH_NULL
    
    100           LOAD_NAME               21 (String)
                  PUSH_NULL
                  LOAD_CONST              43 (20)
                  CALL                     1
                  LOAD_CONST               3 (True)
    
     99           LOAD_CONST              11 (('nullable',))
                  CALL_KW                  2
                  STORE_NAME              43 (ai_swearing_rule)
                  LOAD_NAME               10 (Mapped)
                  LOAD_NAME               23 (str)
                  LOAD_CONST              20 (None)
                  BINARY_OP                7 (|)
                  BINARY_SUBSCR
                  LOAD_NAME               11 (__annotations__)
                  LOAD_CONST              44 ('ai_swearing_rule')
                  STORE_SUBSCR
    
    102           LOAD_NAME                5 (mapped_column)
                  PUSH_NULL
    
    103           LOAD_NAME               18 (Integer)
                  LOAD_CONST               3 (True)
    
    102           LOAD_CONST              11 (('nullable',))
                  CALL_KW                  2
                  STORE_NAME              44 (ai_max_call_length_seconds)
                  LOAD_NAME               10 (Mapped)
                  LOAD_NAME               20 (int)
                  LOAD_CONST              20 (None)
                  BINARY_OP                7 (|)
                  BINARY_SUBSCR
                  LOAD_NAME               11 (__annotations__)
                  LOAD_CONST              45 ('ai_max_call_length_seconds')
                  STORE_SUBSCR
    
    105           LOAD_NAME                5 (mapped_column)
                  PUSH_NULL
    
    106           LOAD_NAME               14 (LargeBinary)
                  LOAD_CONST               3 (True)
    
    105           LOAD_CONST              11 (('nullable',))
                  CALL_KW                  2
                  STORE_NAME              45 (ai_custom_instructions_ciphertext)
                  LOAD_NAME               10 (Mapped)
                  LOAD_NAME               16 (bytes)
                  LOAD_CONST              20 (None)
                  BINARY_OP                7 (|)
                  BINARY_SUBSCR
                  LOAD_NAME               11 (__annotations__)
                  LOAD_CONST              46 ('ai_custom_instructions_ciphertext')
                  STORE_SUBSCR
    
    108           LOAD_NAME                5 (mapped_column)
                  PUSH_NULL
    
    109           LOAD_NAME               14 (LargeBinary)
                  LOAD_CONST               3 (True)
    
    108           LOAD_CONST              11 (('nullable',))
                  CALL_KW                  2
                  STORE_NAME              46 (ai_custom_instructions_nonce)
                  LOAD_NAME               10 (Mapped)
                  LOAD_NAME               16 (bytes)
                  LOAD_CONST              20 (None)
                  BINARY_OP                7 (|)
                  BINARY_SUBSCR
                  LOAD_NAME               11 (__annotations__)
                  LOAD_CONST              47 ('ai_custom_instructions_nonce')
                  STORE_SUBSCR
    
    111           LOAD_NAME                5 (mapped_column)
                  PUSH_NULL
    
    112           LOAD_NAME               18 (Integer)
                  LOAD_CONST               3 (True)
    
    111           LOAD_CONST              11 (('nullable',))
                  CALL_KW                  2
                  STORE_NAME              47 (ai_custom_instructions_key_version)
                  LOAD_NAME               10 (Mapped)
                  LOAD_NAME               20 (int)
                  LOAD_CONST              20 (None)
                  BINARY_OP                7 (|)
                  BINARY_SUBSCR
                  LOAD_NAME               11 (__annotations__)
                  LOAD_CONST              48 ('ai_custom_instructions_key_version')
                  STORE_SUBSCR
    
    116           LOAD_NAME                5 (mapped_column)
                  PUSH_NULL
    
    117           LOAD_NAME               48 (tz_datetime)
                  PUSH_NULL
                  CALL                     0
                  LOAD_CONST              10 (False)
                  LOAD_NAME               31 (text)
                  PUSH_NULL
                  LOAD_CONST              49 ('now()')
                  CALL                     1
    
    116           LOAD_CONST              31 (('nullable', 'server_default'))
                  CALL_KW                  3
                  STORE_NAME              49 (created_at)
                  LOAD_NAME               10 (Mapped)
                  LOAD_NAME               50 (datetime)
                  BINARY_SUBSCR
                  LOAD_NAME               11 (__annotations__)
                  LOAD_CONST              50 ('created_at')
                  STORE_SUBSCR
    
    119           LOAD_NAME                5 (mapped_column)
                  PUSH_NULL
    
    120           LOAD_NAME               48 (tz_datetime)
                  PUSH_NULL
                  CALL                     0
    
    121           LOAD_CONST              10 (False)
    
    122           LOAD_NAME               31 (text)
                  PUSH_NULL
                  LOAD_CONST              49 ('now()')
                  CALL                     1
    
    123           LOAD_CONST              51 (<code object <lambda> at 0x0000024C11422F30, file "D:\fluence\Github\mattbot\backend\app\models\contact_profile.py", line 123>)
                  MAKE_FUNCTION
    
    119           LOAD_CONST              52 (('nullable', 'server_default', 'onupdate'))
                  CALL_KW                  4
                  STORE_NAME              51 (updated_at)
                  LOAD_NAME               10 (Mapped)
                  LOAD_NAME               50 (datetime)
                  BINARY_SUBSCR
                  LOAD_NAME               11 (__annotations__)
                  LOAD_CONST              53 ('updated_at')
                  STORE_SUBSCR
    
    125           LOAD_NAME                5 (mapped_column)
                  PUSH_NULL
    
    126           LOAD_NAME               48 (tz_datetime)
                  PUSH_NULL
                  CALL                     0
                  LOAD_CONST               3 (True)
    
    125           LOAD_CONST              11 (('nullable',))
                  CALL_KW                  2
                  STORE_NAME              52 (deleted_at)
                  LOAD_NAME               10 (Mapped)
                  LOAD_NAME               50 (datetime)
                  LOAD_CONST              20 (None)
                  BINARY_OP                7 (|)
                  BINARY_SUBSCR
                  LOAD_NAME               11 (__annotations__)
                  LOAD_CONST              54 ('deleted_at')
                  STORE_SUBSCR
    
    130           LOAD_NAME               53 (UniqueConstraint)
                  PUSH_NULL
    
    131           LOAD_CONST              12 ('owner_user_id')
                  LOAD_CONST              17 ('phone_hash')
    
    132           LOAD_CONST              55 ('uq_contact_profiles_user_phone')
    
    130           LOAD_CONST              56 (('name',))
                  CALL_KW                  3
    
    134           LOAD_NAME               54 (Index)
                  PUSH_NULL
                  LOAD_CONST              57 ('contact_profiles_user_idx')
                  LOAD_CONST              12 ('owner_user_id')
                  CALL                     2
    
    135           LOAD_NAME               54 (Index)
                  PUSH_NULL
    
    136           LOAD_CONST              58 ('contact_profiles_user_category_idx')
    
    137           LOAD_CONST              12 ('owner_user_id')
                  LOAD_CONST              32 ('category')
    
    135           CALL                     3
    
    139           LOAD_NAME               55 (CheckConstraint)
                  PUSH_NULL
                  LOAD_NAME               56 (_TEMPERAMENT_CHECK)
                  LOAD_CONST              59 ('ck_contact_profiles_temperament')
                  LOAD_CONST              56 (('name',))
                  CALL_KW                  2
    
    140           LOAD_NAME               55 (CheckConstraint)
                  PUSH_NULL
                  LOAD_NAME               57 (_SWEARING_CHECK)
                  LOAD_CONST              60 ('ck_contact_profiles_swearing')
                  LOAD_CONST              56 (('name',))
                  CALL_KW                  2
    
    141           LOAD_NAME               55 (CheckConstraint)
                  PUSH_NULL
    
    142           LOAD_NAME               58 (_GREETING_TEMPLATE_CHECK)
    
    143           LOAD_CONST              61 ('ck_contact_profiles_greeting_template')
    
    141           LOAD_CONST              56 (('name',))
                  CALL_KW                  2
    
    129           BUILD_TUPLE              6
                  STORE_NAME              59 (__table_args__)
                  LOAD_CONST              62 (())
                  STORE_NAME              60 (__static_attributes__)
                  RETURN_CONST            20 (None)
    
    Disassembly of <code object <lambda> at 0x0000024C11422F30, file "D:\fluence\Github\mattbot\backend\app\models\contact_profile.py", line 123>:
    123           RESUME                   0
                  LOAD_GLOBAL              0 (datetime)
                  LOAD_ATTR                2 (now)
                  PUSH_NULL
                  LOAD_GLOBAL              4 (UTC)
                  CALL                     1
                  RETURN_VALUE
    
# co_names: ('__doc__', 'uuid', 'datetime', 'UTC', 'sqlalchemy', 'Boolean', 'CheckConstraint', 'ForeignKey', 'Index', 'Integer', 'LargeBinary', 'String', 'Text', 'UniqueConstraint', 'text', 'sqlalchemy.dialects.postgresql', 'UUID', 'sqlalchemy.orm', 'Mapped', 'mapped_column', 'app.database', 'Base', 'app.models._types', 'tz_datetime', '_TEMPERAMENT_CHECK', '_SWEARING_CHECK', '_GREETING_TEMPLATE_CHECK', 'ContactProfile')
# co_varnames: ()
  0           RESUME                   0

  1           LOAD_CONST               0 ('Unified contact profile: replaces separate VIP / block entries.\n\nEach row represents a known caller whose AI interactions the owner has\ncustomised (category, temperament, greeting, blocking, VIP status, etc.).\n')
              STORE_NAME               0 (__doc__)

  7           LOAD_CONST               1 (0)
              LOAD_CONST               2 (None)
              IMPORT_NAME              1 (uuid)
              STORE_NAME               1 (uuid)

  8           LOAD_CONST               1 (0)
              LOAD_CONST               3 (('UTC', 'datetime'))
              IMPORT_NAME              2 (datetime)
              IMPORT_FROM              3 (UTC)
              STORE_NAME               3 (UTC)
              IMPORT_FROM              2 (datetime)
              STORE_NAME               2 (datetime)
              POP_TOP

 10           LOAD_CONST               1 (0)
              LOAD_CONST               4 (('Boolean', 'CheckConstraint', 'ForeignKey', 'Index', 'Integer', 'LargeBinary', 'String', 'Text', 'UniqueConstraint', 'text'))
              IMPORT_NAME              4 (sqlalchemy)
              IMPORT_FROM              5 (Boolean)
              STORE_NAME               5 (Boolean)
              IMPORT_FROM              6 (CheckConstraint)
              STORE_NAME               6 (CheckConstraint)
              IMPORT_FROM              7 (ForeignKey)
              STORE_NAME               7 (ForeignKey)
              IMPORT_FROM              8 (Index)
              STORE_NAME               8 (Index)
              IMPORT_FROM              9 (Integer)
              STORE_NAME               9 (Integer)
              IMPORT_FROM             10 (LargeBinary)
              STORE_NAME              10 (LargeBinary)
              IMPORT_FROM             11 (String)
              STORE_NAME              11 (String)
              IMPORT_FROM             12 (Text)
              STORE_NAME              12 (Text)
              IMPORT_FROM             13 (UniqueConstraint)
              STORE_NAME              13 (UniqueConstraint)
              IMPORT_FROM             14 (text)
              STORE_NAME              14 (text)
              POP_TOP

 22           LOAD_CONST               1 (0)
              LOAD_CONST               5 (('UUID',))
              IMPORT_NAME             15 (sqlalchemy.dialects.postgresql)
              IMPORT_FROM             16 (UUID)
              STORE_NAME              16 (UUID)
              POP_TOP

 23           LOAD_CONST               1 (0)
              LOAD_CONST               6 (('Mapped', 'mapped_column'))
              IMPORT_NAME             17 (sqlalchemy.orm)
              IMPORT_FROM             18 (Mapped)
              STORE_NAME              18 (Mapped)
              IMPORT_FROM             19 (mapped_column)
              STORE_NAME              19 (mapped_column)
              POP_TOP

 25           LOAD_CONST               1 (0)
              LOAD_CONST               7 (('Base',))
              IMPORT_NAME             20 (app.database)
              IMPORT_FROM             21 (Base)
              STORE_NAME              21 (Base)
              POP_TOP

 26           LOAD_CONST               1 (0)
              LOAD_CONST               8 (('tz_datetime',))
              IMPORT_NAME             22 (app.models._types)
              IMPORT_FROM             23 (tz_datetime)
              STORE_NAME              23 (tz_datetime)
              POP_TOP

 29           LOAD_CONST               9 ("ai_temperament_preset IS NULL OR ai_temperament_preset IN ('professional_polite', 'casual_friendly', 'short_and_direct', 'warm_and_supportive', 'formal', 'custom')")

 28           STORE_NAME              24 (_TEMPERAMENT_CHECK)

 35           LOAD_CONST              10 ("ai_swearing_rule IS NULL OR ai_swearing_rule IN ('no_swearing', 'mirror_caller', 'allow')")

 34           STORE_NAME              25 (_SWEARING_CHECK)

 40           LOAD_CONST              11 ("ai_greeting_template IS NULL OR ai_greeting_template IN ('standard', 'brief', 'formal', 'custom')")

 39           STORE_NAME              26 (_GREETING_TEMPLATE_CHECK)

 45           LOAD_BUILD_CLASS
              PUSH_NULL
              LOAD_CONST              12 (<code object ContactProfile at 0x0000024C0FBAACD0, file "D:\fluence\Github\mattbot\backend\app\models\contact_profile.py", line 45>)
              MAKE_FUNCTION
              LOAD_CONST              13 ('ContactProfile')
              LOAD_NAME               21 (Base)
              CALL                     3
              STORE_NAME              27 (ContactProfile)
              RETURN_CONST             2 (None)

Disassembly of <code object ContactProfile at 0x0000024C0FBAACD0, file "D:\fluence\Github\mattbot\backend\app\models\contact_profile.py", line 45>:
 45           RESUME                   0
              LOAD_NAME                0 (__name__)
              STORE_NAME               1 (__module__)
              LOAD_CONST               0 ('ContactProfile')
              STORE_NAME               2 (__qualname__)
              LOAD_CONST               1 (45)
              STORE_NAME               3 (__firstlineno__)
              SETUP_ANNOTATIONS

 46           LOAD_CONST               2 ('contact_profiles')
              STORE_NAME               4 (__tablename__)

 48           LOAD_NAME                5 (mapped_column)
              PUSH_NULL

 49           LOAD_NAME                6 (UUID)
              PUSH_NULL
              LOAD_CONST               3 (True)
              LOAD_CONST               4 (('as_uuid',))
              CALL_KW                  1
              LOAD_CONST               3 (True)
              LOAD_NAME                7 (uuid)
              LOAD_ATTR               16 (uuid4)

 48           LOAD_CONST               5 (('primary_key', 'default'))
              CALL_KW                  3
              STORE_NAME               9 (id)
              LOAD_NAME               10 (Mapped)
              LOAD_NAME                7 (uuid)
              LOAD_ATTR               12 (UUID)
              BINARY_SUBSCR
              LOAD_NAME               11 (__annotations__)
              LOAD_CONST               6 ('id')
              STORE_SUBSCR

 51           LOAD_NAME                5 (mapped_column)
              PUSH_NULL

 52           LOAD_NAME                6 (UUID)
              PUSH_NULL
              LOAD_CONST               3 (True)
              LOAD_CONST               4 (('as_uuid',))
              CALL_KW                  1

 53           LOAD_NAME               12 (ForeignKey)
              PUSH_NULL
              LOAD_CONST               7 ('users.id')
              LOAD_CONST               8 ('CASCADE')
              LOAD_CONST               9 (('ondelete',))
              CALL_KW                  2

 54           LOAD_CONST              10 (False)

 51           LOAD_CONST              11 (('nullable',))
              CALL_KW                  3
              STORE_NAME              13 (owner_user_id)
              LOAD_NAME               10 (Mapped)
              LOAD_NAME                7 (uuid)
              LOAD_ATTR               12 (UUID)
              BINARY_SUBSCR
              LOAD_NAME               11 (__annotations__)
              LOAD_CONST              12 ('owner_user_id')
              STORE_SUBSCR

 58           LOAD_NAME                5 (mapped_column)
              PUSH_NULL
              LOAD_NAME               14 (LargeBinary)
              LOAD_CONST              10 (False)
              LOAD_CONST              11 (('nullable',))
              CALL_KW                  2
              STORE_NAME              15 (phone_ciphertext)
              LOAD_NAME               10 (Mapped)
              LOAD_NAME               16 (bytes)
              BINARY_SUBSCR
              LOAD_NAME               11 (__annotations__)
              LOAD_CONST              13 ('phone_ciphertext')
              STORE_SUBSCR

 59           LOAD_NAME                5 (mapped_column)
              PUSH_NULL
              LOAD_NAME               14 (LargeBinary)
              LOAD_CONST              10 (False)
              LOAD_CONST              11 (('nullable',))
              CALL_KW                  2
              STORE_NAME              17 (phone_nonce)
              LOAD_NAME               10 (Mapped)
              LOAD_NAME               16 (bytes)
              BINARY_SUBSCR
              LOAD_NAME               11 (__annotations__)
              LOAD_CONST              14 ('phone_nonce')
              STORE_SUBSCR

 60           LOAD_NAME                5 (mapped_column)
              PUSH_NULL
              LOAD_NAME               18 (Integer)
              LOAD_CONST              10 (False)
              LOAD_CONST              11 (('nullable',))
              CALL_KW                  2
              STORE_NAME              19 (phone_key_version)
              LOAD_NAME               10 (Mapped)
              LOAD_NAME               20 (int)
              BINARY_SUBSCR
              LOAD_NAME               11 (__annotations__)
              LOAD_CONST              15 ('phone_key_version')
              STORE_SUBSCR

 61           LOAD_NAME                5 (mapped_column)
              PUSH_NULL
              LOAD_NAME               21 (String)
              PUSH_NULL
              LOAD_CONST              16 (64)
              CALL                     1
              LOAD_CONST              10 (False)
              LOAD_CONST              11 (('nullable',))
              CALL_KW                  2
              STORE_NAME              22 (phone_hash)
              LOAD_NAME               10 (Mapped)
              LOAD_NAME               23 (str)
              BINARY_SUBSCR
              LOAD_NAME               11 (__annotations__)
              LOAD_CONST              17 ('phone_hash')
              STORE_SUBSCR

 62           LOAD_NAME                5 (mapped_column)
              PUSH_NULL
              LOAD_NAME               21 (String)
              PUSH_NULL
              LOAD_CONST              18 (4)
              CALL                     1
              LOAD_CONST              10 (False)
              LOAD_CONST              11 (('nullable',))
              CALL_KW                  2
              STORE_NAME              24 (phone_last4)
              LOAD_NAME               10 (Mapped)
              LOAD_NAME               23 (str)
              BINARY_SUBSCR
              LOAD_NAME               11 (__annotations__)
              LOAD_CONST              19 ('phone_last4')
              STORE_SUBSCR

 65           LOAD_NAME                5 (mapped_column)
              PUSH_NULL
              LOAD_NAME               25 (Text)
              LOAD_CONST               3 (True)
              LOAD_CONST              11 (('nullable',))
              CALL_KW                  2
              STORE_NAME              26 (display_name)
              LOAD_NAME               10 (Mapped)
              LOAD_NAME               23 (str)
              LOAD_CONST              20 (None)
              BINARY_OP                7 (|)
              BINARY_SUBSCR
              LOAD_NAME               11 (__annotations__)
              LOAD_CONST              21 ('display_name')
              STORE_SUBSCR

 66           LOAD_NAME                5 (mapped_column)
              PUSH_NULL
              LOAD_NAME               21 (String)
              PUSH_NULL
              LOAD_CONST              22 (200)
              CALL                     1
              LOAD_CONST               3 (True)
              LOAD_CONST              11 (('nullable',))
              CALL_KW                  2
              STORE_NAME              27 (company)
              LOAD_NAME               10 (Mapped)
              LOAD_NAME               23 (str)
              LOAD_CONST              20 (None)
              BINARY_OP                7 (|)
              BINARY_SUBSCR
              LOAD_NAME               11 (__annotations__)
              LOAD_CONST              23 ('company')
              STORE_SUBSCR

 67           LOAD_NAME                5 (mapped_column)
              PUSH_NULL
              LOAD_NAME               21 (String)
              PUSH_NULL
              LOAD_CONST              24 (100)
              CALL                     1
              LOAD_CONST               3 (True)
              LOAD_CONST              11 (('nullable',))
              CALL_KW                  2
              STORE_NAME              28 (relationship)
              LOAD_NAME               10 (Mapped)
              LOAD_NAME               23 (str)
              LOAD_CONST              20 (None)
              BINARY_OP                7 (|)
              BINARY_SUBSCR
              LOAD_NAME               11 (__annotations__)
              LOAD_CONST              25 ('relationship')
              STORE_SUBSCR

 68           LOAD_NAME                5 (mapped_column)
              PUSH_NULL
              LOAD_NAME               21 (String)
              PUSH_NULL
              LOAD_CONST              26 (254)
              CALL                     1
              LOAD_CONST               3 (True)
              LOAD_CONST              11 (('nullable',))
              CALL_KW                  2
              STORE_NAME              29 (email)
              LOAD_NAME               10 (Mapped)
              LOAD_NAME               23 (str)
              LOAD_CONST              20 (None)
              BINARY_OP                7 (|)
              BINARY_SUBSCR
              LOAD_NAME               11 (__annotations__)
              LOAD_CONST              27 ('email')
              STORE_SUBSCR

 69           LOAD_NAME                5 (mapped_column)
              PUSH_NULL
              LOAD_NAME               25 (Text)
              LOAD_CONST               3 (True)
              LOAD_CONST              11 (('nullable',))
              CALL_KW                  2
              STORE_NAME              30 (notes)
              LOAD_NAME               10 (Mapped)
              LOAD_NAME               23 (str)
              LOAD_CONST              20 (None)
              BINARY_OP                7 (|)
              BINARY_SUBSCR
              LOAD_NAME               11 (__annotations__)
              LOAD_CONST              28 ('notes')
              STORE_SUBSCR

 72           LOAD_NAME                5 (mapped_column)
              PUSH_NULL

 73           LOAD_NAME               21 (String)
              PUSH_NULL
              LOAD_CONST              29 (50)
              CALL                     1
              LOAD_CONST              10 (False)
              LOAD_NAME               31 (text)
              PUSH_NULL
              LOAD_CONST              30 ("'other'")
              CALL                     1

 72           LOAD_CONST              31 (('nullable', 'server_default'))
              CALL_KW                  3
              STORE_NAME              32 (category)
              LOAD_NAME               10 (Mapped)
              LOAD_NAME               23 (str)
              BINARY_SUBSCR
              LOAD_NAME               11 (__annotations__)
              LOAD_CONST              32 ('category')
              STORE_SUBSCR

 75           LOAD_NAME                5 (mapped_column)
              PUSH_NULL

 76           LOAD_NAME               33 (Boolean)
              LOAD_CONST              10 (False)
              LOAD_NAME               31 (text)
              PUSH_NULL
              LOAD_CONST              33 ('false')
              CALL                     1

 75           LOAD_CONST              31 (('nullable', 'server_default'))
              CALL_KW                  3
              STORE_NAME              34 (is_vip)
              LOAD_NAME               10 (Mapped)
              LOAD_NAME               35 (bool)
              BINARY_SUBSCR
              LOAD_NAME               11 (__annotations__)
              LOAD_CONST              34 ('is_vip')
              STORE_SUBSCR

 78           LOAD_NAME                5 (mapped_column)
              PUSH_NULL

 79           LOAD_NAME               33 (Boolean)
              LOAD_CONST              10 (False)
              LOAD_NAME               31 (text)
              PUSH_NULL
              LOAD_CONST              33 ('false')
              CALL                     1

 78           LOAD_CONST              31 (('nullable', 'server_default'))
              CALL_KW                  3
              STORE_NAME              36 (is_blocked)
              LOAD_NAME               10 (Mapped)
              LOAD_NAME               35 (bool)
              BINARY_SUBSCR
              LOAD_NAME               11 (__annotations__)
              LOAD_CONST              35 ('is_blocked')
              STORE_SUBSCR

 81           LOAD_NAME                5 (mapped_column)
              PUSH_NULL
              LOAD_NAME               25 (Text)
              LOAD_CONST               3 (True)
              LOAD_CONST              11 (('nullable',))
              CALL_KW                  2
              STORE_NAME              37 (block_reason)
              LOAD_NAME               10 (Mapped)
              LOAD_NAME               23 (str)
              LOAD_CONST              20 (None)
              BINARY_OP                7 (|)
              BINARY_SUBSCR
              LOAD_NAME               11 (__annotations__)
              LOAD_CONST              36 ('block_reason')
              STORE_SUBSCR

 84           LOAD_NAME                5 (mapped_column)
              PUSH_NULL

 85           LOAD_NAME               21 (String)
              PUSH_NULL
              LOAD_CONST              37 (40)
              CALL                     1
              LOAD_CONST               3 (True)

 84           LOAD_CONST              11 (('nullable',))
              CALL_KW                  2
              STORE_NAME              38 (ai_temperament_preset)
              LOAD_NAME               10 (Mapped)
              LOAD_NAME               23 (str)
              LOAD_CONST              20 (None)
              BINARY_OP                7 (|)
              BINARY_SUBSCR
              LOAD_NAME               11 (__annotations__)
              LOAD_CONST              38 ('ai_temperament_preset')
              STORE_SUBSCR

 87           LOAD_NAME                5 (mapped_column)
              PUSH_NULL

 88           LOAD_NAME               21 (String)
              PUSH_NULL
              LOAD_CONST              37 (40)
              CALL                     1
              LOAD_CONST               3 (True)

 87           LOAD_CONST              11 (('nullable',))
              CALL_KW                  2
              STORE_NAME              39 (ai_greeting_template)
              LOAD_NAME               10 (Mapped)
              LOAD_NAME               23 (str)
              LOAD_CONST              20 (None)
              BINARY_OP                7 (|)
              BINARY_SUBSCR
              LOAD_NAME               11 (__annotations__)
              LOAD_CONST              39 ('ai_greeting_template')
              STORE_SUBSCR

 90           LOAD_NAME                5 (mapped_column)
              PUSH_NULL

 91           LOAD_NAME               14 (LargeBinary)
              LOAD_CONST               3 (True)

 90           LOAD_CONST              11 (('nullable',))
              CALL_KW                  2
              STORE_NAME              40 (ai_greeting_instructions_ciphertext)
              LOAD_NAME               10 (Mapped)
              LOAD_NAME               16 (bytes)
              LOAD_CONST              20 (None)
              BINARY_OP                7 (|)
              BINARY_SUBSCR
              LOAD_NAME               11 (__annotations__)
              LOAD_CONST              40 ('ai_greeting_instructions_ciphertext')
              STORE_SUBSCR

 93           LOAD_NAME                5 (mapped_column)
              PUSH_NULL

 94           LOAD_NAME               14 (LargeBinary)
              LOAD_CONST               3 (True)

 93           LOAD_CONST              11 (('nullable',))
              CALL_KW                  2
              STORE_NAME              41 (ai_greeting_instructions_nonce)
              LOAD_NAME               10 (Mapped)
              LOAD_NAME               16 (bytes)
              LOAD_CONST              20 (None)
              BINARY_OP                7 (|)
              BINARY_SUBSCR
              LOAD_NAME               11 (__annotations__)
              LOAD_CONST              41 ('ai_greeting_instructions_nonce')
              STORE_SUBSCR

 96           LOAD_NAME                5 (mapped_column)
              PUSH_NULL

 97           LOAD_NAME               18 (Integer)
              LOAD_CONST               3 (True)

 96           LOAD_CONST              11 (('nullable',))
              CALL_KW                  2
              STORE_NAME              42 (ai_greeting_instructions_key_version)
              LOAD_NAME               10 (Mapped)
              LOAD_NAME               20 (int)
              LOAD_CONST              20 (None)
              BINARY_OP                7 (|)
              BINARY_SUBSCR
              LOAD_NAME               11 (__annotations__)
              LOAD_CONST              42 ('ai_greeting_instructions_key_version')
              STORE_SUBSCR

 99           LOAD_NAME                5 (mapped_column)
              PUSH_NULL

100           LOAD_NAME               21 (String)
              PUSH_NULL
              LOAD_CONST              43 (20)
              CALL                     1
              LOAD_CONST               3 (True)

 99           LOAD_CONST              11 (('nullable',))
              CALL_KW                  2
              STORE_NAME              43 (ai_swearing_rule)
              LOAD_NAME               10 (Mapped)
              LOAD_NAME               23 (str)
              LOAD_CONST              20 (None)
              BINARY_OP                7 (|)
              BINARY_SUBSCR
              LOAD_NAME               11 (__annotations__)
              LOAD_CONST              44 ('ai_swearing_rule')
              STORE_SUBSCR

102           LOAD_NAME                5 (mapped_column)
              PUSH_NULL

103           LOAD_NAME               18 (Integer)
              LOAD_CONST               3 (True)

102           LOAD_CONST              11 (('nullable',))
              CALL_KW                  2
              STORE_NAME              44 (ai_max_call_length_seconds)
              LOAD_NAME               10 (Mapped)
              LOAD_NAME               20 (int)
              LOAD_CONST              20 (None)
              BINARY_OP                7 (|)
              BINARY_SUBSCR
              LOAD_NAME               11 (__annotations__)
              LOAD_CONST              45 ('ai_max_call_length_seconds')
              STORE_SUBSCR

105           LOAD_NAME                5 (mapped_column)
              PUSH_NULL

106           LOAD_NAME               14 (LargeBinary)
              LOAD_CONST               3 (True)

105           LOAD_CONST              11 (('nullable',))
              CALL_KW                  2
              STORE_NAME              45 (ai_custom_instructions_ciphertext)
              LOAD_NAME               10 (Mapped)
              LOAD_NAME               16 (bytes)
              LOAD_CONST              20 (None)
              BINARY_OP                7 (|)
              BINARY_SUBSCR
              LOAD_NAME               11 (__annotations__)
              LOAD_CONST              46 ('ai_custom_instructions_ciphertext')
              STORE_SUBSCR

108           LOAD_NAME                5 (mapped_column)
              PUSH_NULL

109           LOAD_NAME               14 (LargeBinary)
              LOAD_CONST               3 (True)

108           LOAD_CONST              11 (('nullable',))
              CALL_KW                  2
              STORE_NAME              46 (ai_custom_instructions_nonce)
              LOAD_NAME               10 (Mapped)
              LOAD_NAME               16 (bytes)
              LOAD_CONST              20 (None)
              BINARY_OP                7 (|)
              BINARY_SUBSCR
              LOAD_NAME               11 (__annotations__)
              LOAD_CONST              47 ('ai_custom_instructions_nonce')
              STORE_SUBSCR

111           LOAD_NAME                5 (mapped_column)
              PUSH_NULL

112           LOAD_NAME               18 (Integer)
              LOAD_CONST               3 (True)

111           LOAD_CONST              11 (('nullable',))
              CALL_KW                  2
              STORE_NAME              47 (ai_custom_instructions_key_version)
              LOAD_NAME               10 (Mapped)
              LOAD_NAME               20 (int)
              LOAD_CONST              20 (None)
              BINARY_OP                7 (|)
              BINARY_SUBSCR
              LOAD_NAME               11 (__annotations__)
              LOAD_CONST              48 ('ai_custom_instructions_key_version')
              STORE_SUBSCR

116           LOAD_NAME                5 (mapped_column)
              PUSH_NULL

117           LOAD_NAME               48 (tz_datetime)
              PUSH_NULL
              CALL                     0
              LOAD_CONST              10 (False)
              LOAD_NAME               31 (text)
              PUSH_NULL
              LOAD_CONST              49 ('now()')
              CALL                     1

116           LOAD_CONST              31 (('nullable', 'server_default'))
              CALL_KW                  3
              STORE_NAME              49 (created_at)
              LOAD_NAME               10 (Mapped)
              LOAD_NAME               50 (datetime)
              BINARY_SUBSCR
              LOAD_NAME               11 (__annotations__)
              LOAD_CONST              50 ('created_at')
              STORE_SUBSCR

119           LOAD_NAME                5 (mapped_column)
              PUSH_NULL

120           LOAD_NAME               48 (tz_datetime)
              PUSH_NULL
              CALL                     0

121           LOAD_CONST              10 (False)

122           LOAD_NAME               31 (text)
              PUSH_NULL
              LOAD_CONST              49 ('now()')
              CALL                     1

123           LOAD_CONST              51 (<code object <lambda> at 0x0000024C11422F30, file "D:\fluence\Github\mattbot\backend\app\models\contact_profile.py", line 123>)
              MAKE_FUNCTION

119           LOAD_CONST              52 (('nullable', 'server_default', 'onupdate'))
              CALL_KW                  4
              STORE_NAME              51 (updated_at)
              LOAD_NAME               10 (Mapped)
              LOAD_NAME               50 (datetime)
              BINARY_SUBSCR
              LOAD_NAME               11 (__annotations__)
              LOAD_CONST              53 ('updated_at')
              STORE_SUBSCR

125           LOAD_NAME                5 (mapped_column)
              PUSH_NULL

126           LOAD_NAME               48 (tz_datetime)
              PUSH_NULL
              CALL                     0
              LOAD_CONST               3 (True)

125           LOAD_CONST              11 (('nullable',))
              CALL_KW                  2
              STORE_NAME              52 (deleted_at)
              LOAD_NAME               10 (Mapped)
              LOAD_NAME               50 (datetime)
              LOAD_CONST              20 (None)
              BINARY_OP                7 (|)
              BINARY_SUBSCR
              LOAD_NAME               11 (__annotations__)
              LOAD_CONST              54 ('deleted_at')
              STORE_SUBSCR

130           LOAD_NAME               53 (UniqueConstraint)
              PUSH_NULL

131           LOAD_CONST              12 ('owner_user_id')
              LOAD_CONST              17 ('phone_hash')

132           LOAD_CONST              55 ('uq_contact_profiles_user_phone')

130           LOAD_CONST              56 (('name',))
              CALL_KW                  3

134           LOAD_NAME               54 (Index)
              PUSH_NULL
              LOAD_CONST              57 ('contact_profiles_user_idx')
              LOAD_CONST              12 ('owner_user_id')
              CALL                     2

135           LOAD_NAME               54 (Index)
              PUSH_NULL

136           LOAD_CONST              58 ('contact_profiles_user_category_idx')

137           LOAD_CONST              12 ('owner_user_id')
              LOAD_CONST              32 ('category')

135           CALL                     3

139           LOAD_NAME               55 (CheckConstraint)
              PUSH_NULL
              LOAD_NAME               56 (_TEMPERAMENT_CHECK)
              LOAD_CONST              59 ('ck_contact_profiles_temperament')
              LOAD_CONST              56 (('name',))
              CALL_KW                  2

140           LOAD_NAME               55 (CheckConstraint)
              PUSH_NULL
              LOAD_NAME               57 (_SWEARING_CHECK)
              LOAD_CONST              60 ('ck_contact_profiles_swearing')
              LOAD_CONST              56 (('name',))
              CALL_KW                  2

141           LOAD_NAME               55 (CheckConstraint)
              PUSH_NULL

142           LOAD_NAME               58 (_GREETING_TEMPLATE_CHECK)

143           LOAD_CONST              61 ('ck_contact_profiles_greeting_template')

141           LOAD_CONST              56 (('name',))
              CALL_KW                  2

129           BUILD_TUPLE              6
              STORE_NAME              59 (__table_args__)
              LOAD_CONST              62 (())
              STORE_NAME              60 (__static_attributes__)
              RETURN_CONST            20 (None)

Disassembly of <code object <lambda> at 0x0000024C11422F30, file "D:\fluence\Github\mattbot\backend\app\models\contact_profile.py", line 123>:
123           RESUME                   0
              LOAD_GLOBAL              0 (datetime)
              LOAD_ATTR                2 (now)
              PUSH_NULL
              LOAD_GLOBAL              4 (UTC)
              CALL                     1
              RETURN_VALUE
