# Bytecode dump of: calendar_service.cpython-313.pyc
# co_filename: D:\fluence\Github\mattbot\backend\app\services\calendar_service.py
# co_names: ('__doc__', '__future__', 'annotations', 'logging', 'uuid', 'datetime', 'UTC', 'timedelta', 'time', 'dt_time', 'typing', 'Any', 'urllib.parse', 'urlencode', 'httpx', 'app.config', 'settings', 'app_settings', 'app.core.encryption', 'decrypt_field', 'encrypt_field', 'getLogger', '__name__', 'logger', '_GOOGLE_AUTH_URL', '_GOOGLE_TOKEN_URL', '_GOOGLE_REVOKE_URL', '_GOOGLE_USERINFO_URL', '_GOOGLE_CALENDAR_API', '_TIMEOUT', 'generate_auth_url', 'exchange_code_for_tokens', '_refresh_access_token', 'fetch_google_email', 'store_tokens', 'get_valid_access_token', 'get_calendar_status', '_parse_caller_from_description', 'list_events', 'create_event', 'get_free_busy', 'find_available_slots', 'disconnect_calendar')
# co_consts (strings): ['Google Calendar integration: OAuth token management and Calendar API calls.', 'https://accounts.google.com/o/oauth2/v2/auth', 'https://oauth2.googleapis.com/token', 'https://oauth2.googleapis.com/revoke', 'https://www.googleapis.com/oauth2/v2/userinfo', 'https://www.googleapis.com/calendar/v3']

# DOCSTRING: """Google Calendar integration: OAuth token management and Calendar API calls."""
# --- Nested code object: generate_auth_url ---
    # DOCSTRING: """Build Google OAuth2 authorization URL for calendar scope."""
    # co_names: ('app_settings', 'GOOGLE_CALENDAR_CLIENT_ID', 'GOOGLE_CALENDAR_REDIRECT_URI', 'GOOGLE_CALENDAR_SCOPES', '_GOOGLE_AUTH_URL', 'urlencode')
    # co_varnames: ('state', 'params')
     32           RESUME                   0
    
     35           LOAD_GLOBAL              0 (app_settings)
                  LOAD_ATTR                2 (GOOGLE_CALENDAR_CLIENT_ID)
    
     36           LOAD_GLOBAL              0 (app_settings)
                  LOAD_ATTR                4 (GOOGLE_CALENDAR_REDIRECT_URI)
    
     37           LOAD_CONST               1 ('code')
    
     38           LOAD_GLOBAL              0 (app_settings)
                  LOAD_ATTR                6 (GOOGLE_CALENDAR_SCOPES)
    
     39           LOAD_CONST               2 ('offline')
    
     40           LOAD_CONST               3 ('consent')
    
     41           LOAD_FAST                0 (state)
    
     34           LOAD_CONST               4 (('client_id', 'redirect_uri', 'response_type', 'scope', 'access_type', 'prompt', 'state'))
                  BUILD_CONST_KEY_MAP      7
                  STORE_FAST               1 (params)
    
     43           LOAD_GLOBAL              8 (_GOOGLE_AUTH_URL)
                  FORMAT_SIMPLE
                  LOAD_CONST               5 ('?')
                  LOAD_GLOBAL             11 (urlencode + NULL)
                  LOAD_FAST                1 (params)
                  CALL                     1
                  FORMAT_SIMPLE
                  BUILD_STRING             3
                  RETURN_VALUE
    
# --- Nested code object: exchange_code_for_tokens ---
    # DOCSTRING: """Exchange authorization code for access/refresh tokens."""
    # co_names: ('app_settings', 'GOOGLE_CALENDAR_CLIENT_ID', 'GOOGLE_CALENDAR_CLIENT_SECRET', 'GOOGLE_CALENDAR_REDIRECT_URI', 'httpx', 'AsyncClient', '_TIMEOUT', 'post', '_GOOGLE_TOKEN_URL', 'status_code', 'logger', 'error', 'text', 'raise_for_status', 'json')
    # co_varnames: ('code', 'payload', 'client', 'resp')
      46            RETURN_GENERATOR
                    POP_TOP
            L1:     RESUME                   0
    
      49            LOAD_FAST                0 (code)
    
      50            LOAD_GLOBAL              0 (app_settings)
                    LOAD_ATTR                2 (GOOGLE_CALENDAR_CLIENT_ID)
    
      51            LOAD_GLOBAL              0 (app_settings)
                    LOAD_ATTR                4 (GOOGLE_CALENDAR_CLIENT_SECRET)
    
      52            LOAD_GLOBAL              0 (app_settings)
                    LOAD_ATTR                6 (GOOGLE_CALENDAR_REDIRECT_URI)
    
      53            LOAD_CONST               1 ('authorization_code')
    
      48            LOAD_CONST               2 (('code', 'client_id', 'client_secret', 'redirect_uri', 'grant_type'))
                    BUILD_CONST_KEY_MAP      5
                    STORE_FAST               1 (payload)
    
      55            LOAD_GLOBAL              8 (httpx)
                    LOAD_ATTR               10 (AsyncClient)
                    PUSH_NULL
                    LOAD_GLOBAL             12 (_TIMEOUT)
                    LOAD_CONST               3 (('timeout',))
                    CALL_KW                  1
                    BEFORE_ASYNC_WITH
                    GET_AWAITABLE            1
                    LOAD_CONST               4 (None)
            L2:     SEND                     3 (to L5)
            L3:     YIELD_VALUE              1
            L4:     RESUME                   3
                    JUMP_BACKWARD_NO_INTERRUPT 5 (to L2)
            L5:     END_SEND
            L6:     STORE_FAST               2 (client)
    
      56            LOAD_FAST                2 (client)
                    LOAD_ATTR               15 (post + NULL|self)
                    LOAD_GLOBAL             16 (_GOOGLE_TOKEN_URL)
                    LOAD_FAST                1 (payload)
                    LOAD_CONST               5 (('data',))
                    CALL_KW                  2
                    GET_AWAITABLE            0
                    LOAD_CONST               4 (None)
            L7:     SEND                     3 (to L10)
            L8:     YIELD_VALUE              1
            L9:     RESUME                   3
                    JUMP_BACKWARD_NO_INTERRUPT 5 (to L7)
           L10:     END_SEND
                    STORE_FAST               3 (resp)
    
      57            LOAD_FAST                3 (resp)
                    LOAD_ATTR               18 (status_code)
                    LOAD_CONST               6 (200)
                    COMPARE_OP             119 (bool(!=))
                    POP_JUMP_IF_FALSE       62 (to L11)
    
      58            LOAD_GLOBAL             20 (logger)
                    LOAD_ATTR               23 (error + NULL|self)
                    LOAD_CONST               7 ('Google token exchange failed: %d %s')
                    LOAD_FAST                3 (resp)
                    LOAD_ATTR               18 (status_code)
                    LOAD_FAST                3 (resp)
                    LOAD_ATTR               24 (text)
                    LOAD_CONST               4 (None)
                    LOAD_CONST               8 (300)
                    BINARY_SLICE
                    CALL                     3
                    POP_TOP
    
      59            LOAD_FAST                3 (resp)
                    LOAD_ATTR               27 (raise_for_status + NULL|self)
                    CALL                     0
                    POP_TOP
    
      60   L11:     LOAD_FAST                3 (resp)
                    LOAD_ATTR               29 (json + NULL|self)
                    CALL                     0
    
      55   L12:     SWAP                     2
                    LOAD_CONST               4 (None)
                    LOAD_CONST               4 (None)
                    LOAD_CONST               4 (None)
                    CALL                     2
                    GET_AWAITABLE            2
                    LOAD_CONST               4 (None)
           L13:     SEND                     3 (to L16)
           L14:     YIELD_VALUE              1
           L15:     RESUME                   3
                    JUMP_BACKWARD_NO_INTERRUPT 5 (to L13)
           L16:     END_SEND
                    POP_TOP
                    RETURN_VALUE
           L17:     CLEANUP_THROW
           L18:     JUMP_BACKWARD_NO_INTERRUPT 143 (to L5)
    
      56   L19:     CLEANUP_THROW
           L20:     JUMP_BACKWARD_NO_INTERRUPT 117 (to L10)
    
      55   L21:     CLEANUP_THROW
           L22:     JUMP_BACKWARD_NO_INTERRUPT 9 (to L16)
           L23:     PUSH_EXC_INFO
                    WITH_EXCEPT_START
                    GET_AWAITABLE            2
                    LOAD_CONST               4 (None)
           L24:     SEND                     4 (to L28)
           L25:     YIELD_VALUE              1
           L26:     RESUME                   3
                    JUMP_BACKWARD_NO_INTERRUPT 5 (to L24)
           L27:     CLEANUP_THROW
           L28:     END_SEND
                    TO_BOOL
                    POP_JUMP_IF_TRUE         1 (to L29)
                    RERAISE                  2
           L29:     POP_TOP
           L30:     POP_EXCEPT
                    POP_TOP
                    POP_TOP
                    RETURN_CONST             4 (None)
    
      --   L31:     COPY                     3
                    POP_EXCEPT
                    RERAISE                  1
           L32:     CALL_INTRINSIC_1         3 (INTRINSIC_STOPITERATION_ERROR)
                    RERAISE                  1
    ExceptionTable:
      L1 to L3 -> L32 [0] lasti
      L3 to L4 -> L17 [3]
      L4 to L6 -> L32 [0] lasti
      L6 to L8 -> L23 [1] lasti
      L8 to L9 -> L19 [3]
      L9 to L12 -> L23 [1] lasti
      L12 to L14 -> L32 [0] lasti
      L14 to L15 -> L21 [3]
      L15 to L18 -> L32 [0] lasti
      L19 to L20 -> L23 [1] lasti
      L21 to L22 -> L32 [0] lasti
      L23 to L25 -> L31 [3] lasti
      L25 to L26 -> L27 [6]
      L26 to L30 -> L31 [3] lasti
      L30 to L32 -> L32 [0] lasti
    
# --- Nested code object: _refresh_access_token ---
    # DOCSTRING: """Use refresh token to obtain a new access token."""
    # co_names: ('app_settings', 'GOOGLE_CALENDAR_CLIENT_ID', 'GOOGLE_CALENDAR_CLIENT_SECRET', 'httpx', 'AsyncClient', '_TIMEOUT', 'post', '_GOOGLE_TOKEN_URL', 'status_code', 'logger', 'error', 'text', 'raise_for_status', 'json')
    # co_varnames: ('refresh_token', 'payload', 'client', 'resp')
      63            RETURN_GENERATOR
                    POP_TOP
            L1:     RESUME                   0
    
      66            LOAD_GLOBAL              0 (app_settings)
                    LOAD_ATTR                2 (GOOGLE_CALENDAR_CLIENT_ID)
    
      67            LOAD_GLOBAL              0 (app_settings)
                    LOAD_ATTR                4 (GOOGLE_CALENDAR_CLIENT_SECRET)
    
      68            LOAD_FAST                0 (refresh_token)
    
      69            LOAD_CONST               1 ('refresh_token')
    
      65            LOAD_CONST               2 (('client_id', 'client_secret', 'refresh_token', 'grant_type'))
                    BUILD_CONST_KEY_MAP      4
                    STORE_FAST               1 (payload)
    
      71            LOAD_GLOBAL              6 (httpx)
                    LOAD_ATTR                8 (AsyncClient)
                    PUSH_NULL
                    LOAD_GLOBAL             10 (_TIMEOUT)
                    LOAD_CONST               3 (('timeout',))
                    CALL_KW                  1
                    BEFORE_ASYNC_WITH
                    GET_AWAITABLE            1
                    LOAD_CONST               4 (None)
            L2:     SEND                     3 (to L5)
            L3:     YIELD_VALUE              1
            L4:     RESUME                   3
                    JUMP_BACKWARD_NO_INTERRUPT 5 (to L2)
            L5:     END_SEND
            L6:     STORE_FAST               2 (client)
    
      72            LOAD_FAST                2 (client)
                    LOAD_ATTR               13 (post + NULL|self)
                    LOAD_GLOBAL             14 (_GOOGLE_TOKEN_URL)
                    LOAD_FAST                1 (payload)
                    LOAD_CONST               5 (('data',))
                    CALL_KW                  2
                    GET_AWAITABLE            0
                    LOAD_CONST               4 (None)
            L7:     SEND                     3 (to L10)
            L8:     YIELD_VALUE              1
            L9:     RESUME                   3
                    JUMP_BACKWARD_NO_INTERRUPT 5 (to L7)
           L10:     END_SEND
                    STORE_FAST               3 (resp)
    
      73            LOAD_FAST                3 (resp)
                    LOAD_ATTR               16 (status_code)
                    LOAD_CONST               6 (200)
                    COMPARE_OP             119 (bool(!=))
                    POP_JUMP_IF_FALSE       62 (to L11)
    
      74            LOAD_GLOBAL             18 (logger)
                    LOAD_ATTR               21 (error + NULL|self)
                    LOAD_CONST               7 ('Google token refresh failed: %d %s')
                    LOAD_FAST                3 (resp)
                    LOAD_ATTR               16 (status_code)
                    LOAD_FAST                3 (resp)
                    LOAD_ATTR               22 (text)
                    LOAD_CONST               4 (None)
                    LOAD_CONST               8 (300)
                    BINARY_SLICE
                    CALL                     3
                    POP_TOP
    
      75            LOAD_FAST                3 (resp)
                    LOAD_ATTR               25 (raise_for_status + NULL|self)
                    CALL                     0
                    POP_TOP
    
      76   L11:     LOAD_FAST                3 (resp)
                    LOAD_ATTR               27 (json + NULL|self)
                    CALL                     0
    
      71   L12:     SWAP                     2
                    LOAD_CONST               4 (None)
                    LOAD_CONST               4 (None)
                    LOAD_CONST               4 (None)
                    CALL                     2
                    GET_AWAITABLE            2
                    LOAD_CONST               4 (None)
           L13:     SEND                     3 (to L16)
           L14:     YIELD_VALUE              1
           L15:     RESUME                   3
                    JUMP_BACKWARD_NO_INTERRUPT 5 (to L13)
           L16:     END_SEND
                    POP_TOP
                    RETURN_VALUE
           L17:     CLEANUP_THROW
           L18:     JUMP_BACKWARD_NO_INTERRUPT 143 (to L5)
    
      72   L19:     CLEANUP_THROW
           L20:     JUMP_BACKWARD_NO_INTERRUPT 117 (to L10)
    
      71   L21:     CLEANUP_THROW
           L22:     JUMP_BACKWARD_NO_INTERRUPT 9 (to L16)
           L23:     PUSH_EXC_INFO
                    WITH_EXCEPT_START
                    GET_AWAITABLE            2
                    LOAD_CONST               4 (None)
           L24:     SEND                     4 (to L28)
           L25:     YIELD_VALUE              1
           L26:     RESUME                   3
                    JUMP_BACKWARD_NO_INTERRUPT 5 (to L24)
           L27:     CLEANUP_THROW
           L28:     END_SEND
                    TO_BOOL
                    POP_JUMP_IF_TRUE         1 (to L29)
                    RERAISE                  2
           L29:     POP_TOP
           L30:     POP_EXCEPT
                    POP_TOP
                    POP_TOP
                    RETURN_CONST             4 (None)
    
      --   L31:     COPY                     3
                    POP_EXCEPT
                    RERAISE                  1
           L32:     CALL_INTRINSIC_1         3 (INTRINSIC_STOPITERATION_ERROR)
                    RERAISE                  1
    ExceptionTable:
      L1 to L3 -> L32 [0] lasti
      L3 to L4 -> L17 [3]
      L4 to L6 -> L32 [0] lasti
      L6 to L8 -> L23 [1] lasti
      L8 to L9 -> L19 [3]
      L9 to L12 -> L23 [1] lasti
      L12 to L14 -> L32 [0] lasti
      L14 to L15 -> L21 [3]
      L15 to L18 -> L32 [0] lasti
      L19 to L20 -> L23 [1] lasti
      L21 to L22 -> L32 [0] lasti
      L23 to L25 -> L31 [3] lasti
      L25 to L26 -> L27 [6]
      L26 to L30 -> L31 [3] lasti
      L30 to L32 -> L32 [0] lasti
    
# --- Nested code object: fetch_google_email ---
    # DOCSTRING: """Fetch the authenticated user's email from Google userinfo."""
    # co_names: ('httpx', 'AsyncClient', '_TIMEOUT', 'get', '_GOOGLE_USERINFO_URL', 'raise_for_status', 'json')
    # co_varnames: ('access_token', 'client', 'resp', 'email')
      79            RETURN_GENERATOR
                    POP_TOP
            L1:     RESUME                   0
    
      81            LOAD_GLOBAL              0 (httpx)
                    LOAD_ATTR                2 (AsyncClient)
                    PUSH_NULL
                    LOAD_GLOBAL              4 (_TIMEOUT)
                    LOAD_CONST               1 (('timeout',))
                    CALL_KW                  1
                    BEFORE_ASYNC_WITH
                    GET_AWAITABLE            1
                    LOAD_CONST               2 (None)
            L2:     SEND                     3 (to L5)
            L3:     YIELD_VALUE              1
            L4:     RESUME                   3
                    JUMP_BACKWARD_NO_INTERRUPT 5 (to L2)
            L5:     END_SEND
            L6:     STORE_FAST               1 (client)
    
      82            LOAD_FAST                1 (client)
                    LOAD_ATTR                7 (get + NULL|self)
    
      83            LOAD_GLOBAL              8 (_GOOGLE_USERINFO_URL)
    
      84            LOAD_CONST               3 ('Authorization')
                    LOAD_CONST               4 ('Bearer ')
                    LOAD_FAST                0 (access_token)
                    FORMAT_SIMPLE
                    BUILD_STRING             2
                    BUILD_MAP                1
    
      82            LOAD_CONST               5 (('headers',))
                    CALL_KW                  2
                    GET_AWAITABLE            0
                    LOAD_CONST               2 (None)
            L7:     SEND                     3 (to L10)
            L8:     YIELD_VALUE              1
            L9:     RESUME                   3
                    JUMP_BACKWARD_NO_INTERRUPT 5 (to L7)
           L10:     END_SEND
                    STORE_FAST               2 (resp)
    
      86            LOAD_FAST                2 (resp)
                    LOAD_ATTR               11 (raise_for_status + NULL|self)
                    CALL                     0
                    POP_TOP
    
      87            LOAD_FAST                2 (resp)
                    LOAD_ATTR               13 (json + NULL|self)
                    CALL                     0
                    LOAD_ATTR                7 (get + NULL|self)
                    LOAD_CONST               6 ('email')
                    LOAD_CONST               7 ('')
                    CALL                     2
                    STORE_FAST               3 (email)
    
      88            LOAD_FAST                3 (email)
    
      81   L11:     SWAP                     2
                    LOAD_CONST               2 (None)
                    LOAD_CONST               2 (None)
                    LOAD_CONST               2 (None)
                    CALL                     2
                    GET_AWAITABLE            2
                    LOAD_CONST               2 (None)
           L12:     SEND                     3 (to L15)
           L13:     YIELD_VALUE              1
           L14:     RESUME                   3
                    JUMP_BACKWARD_NO_INTERRUPT 5 (to L12)
           L15:     END_SEND
                    POP_TOP
                    RETURN_VALUE
           L16:     CLEANUP_THROW
           L17:     JUMP_BACKWARD_NO_INTERRUPT 104 (to L5)
    
      82   L18:     CLEANUP_THROW
           L19:     JUMP_BACKWARD_NO_INTERRUPT 73 (to L10)
    
      81   L20:     CLEANUP_THROW
           L21:     JUMP_BACKWARD_NO_INTERRUPT 9 (to L15)
           L22:     PUSH_EXC_INFO
                    WITH_EXCEPT_START
                    GET_AWAITABLE            2
                    LOAD_CONST               2 (None)
           L23:     SEND                     4 (to L27)
           L24:     YIELD_VALUE              1
           L25:     RESUME                   3
                    JUMP_BACKWARD_NO_INTERRUPT 5 (to L23)
           L26:     CLEANUP_THROW
           L27:     END_SEND
                    TO_BOOL
                    POP_JUMP_IF_TRUE         1 (to L28)
                    RERAISE                  2
           L28:     POP_TOP
           L29:     POP_EXCEPT
                    POP_TOP
                    POP_TOP
                    RETURN_CONST             2 (None)
    
      --   L30:     COPY                     3
                    POP_EXCEPT
                    RERAISE                  1
           L31:     CALL_INTRINSIC_1         3 (INTRINSIC_STOPITERATION_ERROR)
                    RERAISE                  1
    ExceptionTable:
      L1 to L3 -> L31 [0] lasti
      L3 to L4 -> L16 [3]
      L4 to L6 -> L31 [0] lasti
      L6 to L8 -> L22 [1] lasti
      L8 to L9 -> L18 [3]
      L9 to L11 -> L22 [1] lasti
      L11 to L13 -> L31 [0] lasti
      L13 to L14 -> L20 [3]
      L14 to L17 -> L31 [0] lasti
      L18 to L19 -> L22 [1] lasti
      L20 to L21 -> L31 [0] lasti
      L22 to L24 -> L30 [3] lasti
      L24 to L25 -> L26 [6]
      L25 to L29 -> L30 [3] lasti
      L29 to L31 -> L31 [0] lasti
    
# --- Nested code object: store_tokens ---
    # DOCSTRING: """Encrypt and store (or update) Google Calendar tokens."""
    # co_names: ('sqlalchemy.ext.asyncio', 'AsyncSession', 'app.models.google_calendar_token', 'GoogleCalendarToken', 'encrypt_field', 'encode', 'datetime', 'now', 'UTC', 'timedelta', 'int', 'get', 'refresh_token_ciphertext', 'refresh_token_nonce', 'ValueError', 'access_token_ciphertext', 'access_token_nonce', 'key_version', 'token_expiry', 'google_email', 'updated_at', 'add', 'flush')
    # co_varnames: ('db', 'user_id', 'tokens', 'google_email', 'AsyncSession', 'GoogleCalendarToken', 'session', 'access_ct', 'access_nonce', 'kv', 'expiry', 'existing', 'refresh_token_str', 'refresh_ct', 'refresh_nonce', '_', 'entry')
      96            RETURN_GENERATOR
                    POP_TOP
            L1:     RESUME                   0
    
     103            LOAD_CONST               1 (0)
                    LOAD_CONST               2 (('AsyncSession',))
                    IMPORT_NAME              0 (sqlalchemy.ext.asyncio)
                    IMPORT_FROM              1 (AsyncSession)
                    STORE_FAST               4 (AsyncSession)
                    POP_TOP
    
     105            LOAD_CONST               1 (0)
                    LOAD_CONST               3 (('GoogleCalendarToken',))
                    IMPORT_NAME              2 (app.models.google_calendar_token)
                    IMPORT_FROM              3 (GoogleCalendarToken)
                    STORE_FAST               5 (GoogleCalendarToken)
                    POP_TOP
    
     107            LOAD_FAST                0 (db)
                    STORE_FAST               6 (session)
    
     109            LOAD_GLOBAL              9 (encrypt_field + NULL)
                    LOAD_FAST                2 (tokens)
                    LOAD_CONST               4 ('access_token')
                    BINARY_SUBSCR
                    LOAD_ATTR               11 (encode + NULL|self)
                    CALL                     0
                    CALL                     1
                    UNPACK_SEQUENCE          3
                    STORE_FAST_STORE_FAST  120 (access_ct, access_nonce)
                    STORE_FAST               9 (kv)
    
     111            LOAD_CONST               5 (None)
                    STORE_FAST              10 (expiry)
    
     112            LOAD_CONST               6 ('expires_in')
                    LOAD_FAST                2 (tokens)
                    CONTAINS_OP              0
                    POP_JUMP_IF_FALSE       48 (to L2)
    
     113            LOAD_GLOBAL             12 (datetime)
                    LOAD_ATTR               14 (now)
                    PUSH_NULL
                    LOAD_GLOBAL             16 (UTC)
                    CALL                     1
                    LOAD_GLOBAL             19 (timedelta + NULL)
                    LOAD_GLOBAL             21 (int + NULL)
                    LOAD_FAST                2 (tokens)
                    LOAD_CONST               6 ('expires_in')
                    BINARY_SUBSCR
                    CALL                     1
                    LOAD_CONST               7 (('seconds',))
                    CALL_KW                  1
                    BINARY_OP                0 (+)
                    STORE_FAST              10 (expiry)
    
     115    L2:     LOAD_FAST                6 (session)
                    LOAD_ATTR               23 (get + NULL|self)
                    LOAD_FAST_LOAD_FAST     81 (GoogleCalendarToken, user_id)
                    CALL                     2
                    GET_AWAITABLE            0
                    LOAD_CONST               5 (None)
            L3:     SEND                     3 (to L6)
            L4:     YIELD_VALUE              1
            L5:     RESUME                   3
                    JUMP_BACKWARD_NO_INTERRUPT 5 (to L3)
            L6:     END_SEND
                    STORE_FAST              11 (existing)
    
     117            LOAD_FAST                2 (tokens)
                    LOAD_ATTR               23 (get + NULL|self)
                    LOAD_CONST               8 ('refresh_token')
                    CALL                     1
                    STORE_FAST              12 (refresh_token_str)
    
     118            LOAD_FAST               12 (refresh_token_str)
                    TO_BOOL
                    POP_JUMP_IF_FALSE       29 (to L7)
    
     119            LOAD_GLOBAL              9 (encrypt_field + NULL)
                    LOAD_FAST               12 (refresh_token_str)
                    LOAD_ATTR               11 (encode + NULL|self)
                    CALL                     0
                    CALL                     1
                    UNPACK_SEQUENCE          3
                    STORE_FAST_STORE_FAST  222 (refresh_ct, refresh_nonce)
                    STORE_FAST              15 (_)
                    JUMP_FORWARD            43 (to L9)
    
     120    L7:     LOAD_FAST               11 (existing)
                    TO_BOOL
                    POP_JUMP_IF_FALSE       25 (to L8)
    
     121            LOAD_FAST               11 (existing)
                    LOAD_ATTR               24 (refresh_token_ciphertext)
                    STORE_FAST              13 (refresh_ct)
    
     122            LOAD_FAST               11 (existing)
                    LOAD_ATTR               26 (refresh_token_nonce)
                    STORE_FAST              14 (refresh_nonce)
                    JUMP_FORWARD            11 (to L9)
    
     124    L8:     LOAD_GLOBAL             29 (ValueError + NULL)
                    LOAD_CONST               9 ('No refresh token received and no existing token on file')
                    CALL                     1
                    RAISE_VARARGS            1
    
     126    L9:     LOAD_FAST               11 (existing)
                    TO_BOOL
                    POP_JUMP_IF_FALSE       74 (to L10)
    
     127            LOAD_FAST_LOAD_FAST    123 (access_ct, existing)
                    STORE_ATTR              15 (access_token_ciphertext)
    
     128            LOAD_FAST_LOAD_FAST    139 (access_nonce, existing)
                    STORE_ATTR              16 (access_token_nonce)
    
     129            LOAD_FAST_LOAD_FAST    219 (refresh_ct, existing)
                    STORE_ATTR              12 (refresh_token_ciphertext)
    
     130            LOAD_FAST_LOAD_FAST    235 (refresh_nonce, existing)
                    STORE_ATTR              13 (refresh_token_nonce)
    
     131            LOAD_FAST_LOAD_FAST    155 (kv, existing)
                    STORE_ATTR              17 (key_version)
    
     132            LOAD_FAST_LOAD_FAST    171 (expiry, existing)
                    STORE_ATTR              18 (token_expiry)
    
     133            LOAD_FAST_LOAD_FAST     59 (google_email, existing)
                    STORE_ATTR              19 (google_email)
    
     134            LOAD_GLOBAL             12 (datetime)
                    LOAD_ATTR               14 (now)
                    PUSH_NULL
                    LOAD_GLOBAL             16 (UTC)
                    CALL                     1
                    LOAD_FAST               11 (existing)
                    STORE_ATTR              20 (updated_at)
                    JUMP_FORWARD            30 (to L11)
    
     136   L10:     LOAD_FAST                5 (GoogleCalendarToken)
                    PUSH_NULL
    
     137            LOAD_FAST                1 (user_id)
    
     138            LOAD_FAST                7 (access_ct)
    
     139            LOAD_FAST                8 (access_nonce)
    
     140            LOAD_FAST               13 (refresh_ct)
    
     141            LOAD_FAST               14 (refresh_nonce)
    
     142            LOAD_FAST                9 (kv)
    
     143            LOAD_FAST               10 (expiry)
    
     144            LOAD_FAST                3 (google_email)
    
     136            LOAD_CONST              10 (('owner_user_id', 'access_token_ciphertext', 'access_token_nonce', 'refresh_token_ciphertext', 'refresh_token_nonce', 'key_version', 'token_expiry', 'google_email'))
                    CALL_KW                  8
                    STORE_FAST              16 (entry)
    
     146            LOAD_FAST                6 (session)
                    LOAD_ATTR               43 (add + NULL|self)
                    LOAD_FAST               16 (entry)
                    CALL                     1
                    POP_TOP
    
     148   L11:     LOAD_FAST                6 (session)
                    LOAD_ATTR               45 (flush + NULL|self)
                    CALL                     0
                    GET_AWAITABLE            0
                    LOAD_CONST               5 (None)
           L12:     SEND                     3 (to L15)
           L13:     YIELD_VALUE              1
           L14:     RESUME                   3
                    JUMP_BACKWARD_NO_INTERRUPT 5 (to L12)
           L15:     END_SEND
                    POP_TOP
                    RETURN_CONST             5 (None)
    
     115   L16:     CLEANUP_THROW
           L17:     JUMP_BACKWARD_NO_INTERRUPT 236 (to L6)
    
     148   L18:     CLEANUP_THROW
           L19:     JUMP_BACKWARD_NO_INTERRUPT 7 (to L15)
    
      --   L20:     CALL_INTRINSIC_1         3 (INTRINSIC_STOPITERATION_ERROR)
                    RERAISE                  1
    ExceptionTable:
      L1 to L4 -> L20 [0] lasti
      L4 to L5 -> L16 [2]
      L5 to L13 -> L20 [0] lasti
      L13 to L14 -> L18 [2]
      L14 to L17 -> L20 [0] lasti
      L18 to L19 -> L20 [0] lasti
    
# --- Nested code object: get_valid_access_token ---
    # DOCSTRING: """Decrypt tokens, refresh if expired, return a valid access token."""
    # co_names: ('sqlalchemy.ext.asyncio', 'AsyncSession', 'app.models.google_calendar_token', 'GoogleCalendarToken', 'get', 'decrypt_field', 'access_token_ciphertext', 'access_token_nonce', 'key_version', 'decode', 'token_expiry', 'datetime', 'now', 'UTC', 'timedelta', 'refresh_token_ciphertext', 'refresh_token_nonce', '_refresh_access_token', 'httpx', 'HTTPStatusError', 'logger', 'warning', 'str', 'encrypt_field', 'encode', 'int', 'updated_at', 'flush')
    # co_varnames: ('db', 'user_id', 'AsyncSession', 'GoogleCalendarToken', 'session', 'row', 'access_token', 'refresh_token', 'new_tokens', 'ct', 'nonce', 'kv', 'rct', 'rnonce', '_')
     151            RETURN_GENERATOR
                    POP_TOP
            L1:     RESUME                   0
    
     153            LOAD_CONST               1 (0)
                    LOAD_CONST               2 (('AsyncSession',))
                    IMPORT_NAME              0 (sqlalchemy.ext.asyncio)
                    IMPORT_FROM              1 (AsyncSession)
                    STORE_FAST               2 (AsyncSession)
                    POP_TOP
    
     155            LOAD_CONST               1 (0)
                    LOAD_CONST               3 (('GoogleCalendarToken',))
                    IMPORT_NAME              2 (app.models.google_calendar_token)
                    IMPORT_FROM              3 (GoogleCalendarToken)
                    STORE_FAST               3 (GoogleCalendarToken)
                    POP_TOP
    
     157            LOAD_FAST                0 (db)
                    STORE_FAST               4 (session)
    
     158            LOAD_FAST                4 (session)
                    LOAD_ATTR                9 (get + NULL|self)
                    LOAD_FAST_LOAD_FAST     49 (GoogleCalendarToken, user_id)
                    CALL                     2
                    GET_AWAITABLE            0
                    LOAD_CONST               4 (None)
            L2:     SEND                     3 (to L5)
            L3:     YIELD_VALUE              1
            L4:     RESUME                   3
                    JUMP_BACKWARD_NO_INTERRUPT 5 (to L2)
            L5:     END_SEND
                    STORE_FAST               5 (row)
    
     159            LOAD_FAST                5 (row)
                    POP_JUMP_IF_NOT_NONE     1 (to L6)
    
     160            RETURN_CONST             4 (None)
    
     162    L6:     LOAD_GLOBAL             11 (decrypt_field + NULL)
    
     163            LOAD_FAST                5 (row)
                    LOAD_ATTR               12 (access_token_ciphertext)
                    LOAD_FAST                5 (row)
                    LOAD_ATTR               14 (access_token_nonce)
                    LOAD_FAST                5 (row)
                    LOAD_ATTR               16 (key_version)
    
     162            CALL                     3
    
     164            LOAD_ATTR               19 (decode + NULL|self)
                    CALL                     0
    
     162            STORE_FAST               6 (access_token)
    
     166            LOAD_FAST                5 (row)
                    LOAD_ATTR               20 (token_expiry)
                    TO_BOOL
                    EXTENDED_ARG             1
                    POP_JUMP_IF_FALSE      342 (to L20)
                    LOAD_FAST                5 (row)
                    LOAD_ATTR               20 (token_expiry)
                    LOAD_GLOBAL             22 (datetime)
                    LOAD_ATTR               24 (now)
                    PUSH_NULL
                    LOAD_GLOBAL             26 (UTC)
                    CALL                     1
                    LOAD_GLOBAL             29 (timedelta + NULL)
                    LOAD_CONST               5 (2)
                    LOAD_CONST               6 (('minutes',))
                    CALL_KW                  1
                    BINARY_OP                0 (+)
                    COMPARE_OP              18 (bool(<))
                    EXTENDED_ARG             1
                    POP_JUMP_IF_FALSE      291 (to L20)
    
     167            LOAD_GLOBAL             11 (decrypt_field + NULL)
    
     168            LOAD_FAST                5 (row)
                    LOAD_ATTR               30 (refresh_token_ciphertext)
                    LOAD_FAST                5 (row)
                    LOAD_ATTR               32 (refresh_token_nonce)
                    LOAD_FAST                5 (row)
                    LOAD_ATTR               16 (key_version)
    
     167            CALL                     3
    
     169            LOAD_ATTR               19 (decode + NULL|self)
                    CALL                     0
    
     167            STORE_FAST               7 (refresh_token)
    
     170    L7:     NOP
    
     171    L8:     LOAD_GLOBAL             35 (_refresh_access_token + NULL)
                    LOAD_FAST                7 (refresh_token)
                    CALL                     1
                    GET_AWAITABLE            0
                    LOAD_CONST               4 (None)
            L9:     SEND                     3 (to L12)
           L10:     YIELD_VALUE              1
           L11:     RESUME                   3
                    JUMP_BACKWARD_NO_INTERRUPT 5 (to L9)
           L12:     END_SEND
                    STORE_FAST               8 (new_tokens)
    
     176   L13:     LOAD_FAST                8 (new_tokens)
                    LOAD_CONST               9 ('access_token')
                    BINARY_SUBSCR
                    STORE_FAST               6 (access_token)
    
     177            LOAD_GLOBAL             47 (encrypt_field + NULL)
                    LOAD_FAST                6 (access_token)
                    LOAD_ATTR               49 (encode + NULL|self)
                    CALL                     0
                    CALL                     1
                    UNPACK_SEQUENCE          3
                    STORE_FAST_STORE_FAST  154 (ct, nonce)
                    STORE_FAST              11 (kv)
    
     178            LOAD_FAST_LOAD_FAST    149 (ct, row)
                    STORE_ATTR               6 (access_token_ciphertext)
    
     179            LOAD_FAST_LOAD_FAST    165 (nonce, row)
                    STORE_ATTR               7 (access_token_nonce)
    
     180            LOAD_FAST_LOAD_FAST    181 (kv, row)
                    STORE_ATTR               8 (key_version)
    
     181            LOAD_CONST              10 ('expires_in')
                    LOAD_FAST                8 (new_tokens)
                    CONTAINS_OP              0
                    POP_JUMP_IF_FALSE       53 (to L14)
    
     182            LOAD_GLOBAL             22 (datetime)
                    LOAD_ATTR               24 (now)
                    PUSH_NULL
                    LOAD_GLOBAL             26 (UTC)
                    CALL                     1
                    LOAD_GLOBAL             29 (timedelta + NULL)
                    LOAD_GLOBAL             51 (int + NULL)
                    LOAD_FAST                8 (new_tokens)
                    LOAD_CONST              10 ('expires_in')
                    BINARY_SUBSCR
                    CALL                     1
                    LOAD_CONST              11 (('seconds',))
                    CALL_KW                  1
                    BINARY_OP                0 (+)
                    LOAD_FAST                5 (row)
                    STORE_ATTR              10 (token_expiry)
    
     184   L14:     LOAD_CONST              12 ('refresh_token')
                    LOAD_FAST                8 (new_tokens)
                    CONTAINS_OP              0
                    POP_JUMP_IF_FALSE       43 (to L15)
    
     185            LOAD_GLOBAL             47 (encrypt_field + NULL)
                    LOAD_FAST                8 (new_tokens)
                    LOAD_CONST              12 ('refresh_token')
                    BINARY_SUBSCR
                    LOAD_ATTR               49 (encode + NULL|self)
                    CALL                     0
                    CALL                     1
                    UNPACK_SEQUENCE          3
                    STORE_FAST_STORE_FAST  205 (rct, rnonce)
                    STORE_FAST              14 (_)
    
     186            LOAD_FAST_LOAD_FAST    197 (rct, row)
                    STORE_ATTR              15 (refresh_token_ciphertext)
    
     187            LOAD_FAST_LOAD_FAST    213 (rnonce, row)
                    STORE_ATTR              16 (refresh_token_nonce)
    
     189   L15:     LOAD_GLOBAL             22 (datetime)
                    LOAD_ATTR               24 (now)
                    PUSH_NULL
                    LOAD_GLOBAL             26 (UTC)
                    CALL                     1
                    LOAD_FAST                5 (row)
                    STORE_ATTR              26 (updated_at)
    
     190            LOAD_FAST                4 (session)
                    LOAD_ATTR               55 (flush + NULL|self)
                    CALL                     0
                    GET_AWAITABLE            0
                    LOAD_CONST               4 (None)
           L16:     SEND                     3 (to L19)
           L17:     YIELD_VALUE              1
           L18:     RESUME                   3
                    JUMP_BACKWARD_NO_INTERRUPT 5 (to L16)
           L19:     END_SEND
                    POP_TOP
    
     192   L20:     LOAD_FAST                6 (access_token)
                    RETURN_VALUE
    
     158   L21:     CLEANUP_THROW
           L22:     EXTENDED_ARG             1
                    JUMP_BACKWARD_NO_INTERRUPT 428 (to L5)
    
     171   L23:     CLEANUP_THROW
           L24:     JUMP_BACKWARD_NO_INTERRUPT 223 (to L12)
    
      --   L25:     PUSH_EXC_INFO
    
     172            LOAD_GLOBAL             36 (httpx)
                    LOAD_ATTR               38 (HTTPStatusError)
                    CHECK_EXC_MATCH
                    POP_JUMP_IF_FALSE       37 (to L27)
                    POP_TOP
    
     173            LOAD_GLOBAL             40 (logger)
                    LOAD_ATTR               43 (warning + NULL|self)
                    LOAD_CONST               7 ('Failed to refresh Google token for user %s')
                    LOAD_GLOBAL             45 (str + NULL)
                    LOAD_FAST                1 (user_id)
                    CALL                     1
                    LOAD_CONST               4 (None)
                    LOAD_CONST               8 (8)
                    BINARY_SLICE
                    CALL                     2
                    POP_TOP
    
     174   L26:     POP_EXCEPT
                    RETURN_CONST             4 (None)
    
     172   L27:     RERAISE                  0
    
      --   L28:     COPY                     3
                    POP_EXCEPT
                    RERAISE                  1
    
     190   L29:     CLEANUP_THROW
           L30:     JUMP_BACKWARD_NO_INTERRUPT 71 (to L19)
    
      --   L31:     CALL_INTRINSIC_1         3 (INTRINSIC_STOPITERATION_ERROR)
                    RERAISE                  1
    ExceptionTable:
      L1 to L3 -> L31 [0] lasti
      L3 to L4 -> L21 [2]
      L4 to L7 -> L31 [0] lasti
      L8 to L10 -> L25 [0]
      L10 to L11 -> L23 [2]
      L11 to L13 -> L25 [0]
      L13 to L17 -> L31 [0] lasti
      L17 to L18 -> L29 [2]
      L18 to L22 -> L31 [0] lasti
      L23 to L24 -> L25 [0]
      L25 to L26 -> L28 [1] lasti
      L26 to L27 -> L31 [0] lasti
      L27 to L28 -> L28 [1] lasti
      L28 to L30 -> L31 [0] lasti
    
# --- Nested code object: get_calendar_status ---
    # DOCSTRING: """Return connection status for the user's Google Calendar."""
    # co_names: ('sqlalchemy.ext.asyncio', 'AsyncSession', 'app.models.google_calendar_token', 'GoogleCalendarToken', 'get', 'google_email', 'calendar_id')
    # co_varnames: ('db', 'user_id', 'AsyncSession', 'GoogleCalendarToken', 'session', 'row')
     195           RETURN_GENERATOR
                   POP_TOP
           L1:     RESUME                   0
    
     197           LOAD_CONST               1 (0)
                   LOAD_CONST               2 (('AsyncSession',))
                   IMPORT_NAME              0 (sqlalchemy.ext.asyncio)
                   IMPORT_FROM              1 (AsyncSession)
                   STORE_FAST               2 (AsyncSession)
                   POP_TOP
    
     199           LOAD_CONST               1 (0)
                   LOAD_CONST               3 (('GoogleCalendarToken',))
                   IMPORT_NAME              2 (app.models.google_calendar_token)
                   IMPORT_FROM              3 (GoogleCalendarToken)
                   STORE_FAST               3 (GoogleCalendarToken)
                   POP_TOP
    
     201           LOAD_FAST                0 (db)
                   STORE_FAST               4 (session)
    
     202           LOAD_FAST                4 (session)
                   LOAD_ATTR                9 (get + NULL|self)
                   LOAD_FAST_LOAD_FAST     49 (GoogleCalendarToken, user_id)
                   CALL                     2
                   GET_AWAITABLE            0
                   LOAD_CONST               4 (None)
           L2:     SEND                     3 (to L5)
           L3:     YIELD_VALUE              1
           L4:     RESUME                   3
                   JUMP_BACKWARD_NO_INTERRUPT 5 (to L2)
           L5:     END_SEND
                   STORE_FAST               5 (row)
    
     203           LOAD_FAST                5 (row)
                   POP_JUMP_IF_NOT_NONE     6 (to L6)
    
     204           LOAD_CONST               5 (False)
                   LOAD_CONST               4 (None)
                   LOAD_CONST               4 (None)
                   LOAD_CONST               6 (('connected', 'email', 'calendar_id'))
                   BUILD_CONST_KEY_MAP      3
                   RETURN_VALUE
    
     206   L6:     LOAD_CONST               7 (True)
    
     207           LOAD_FAST                5 (row)
                   LOAD_ATTR               10 (google_email)
    
     208           LOAD_FAST                5 (row)
                   LOAD_ATTR               12 (calendar_id)
    
     205           LOAD_CONST               6 (('connected', 'email', 'calendar_id'))
                   BUILD_CONST_KEY_MAP      3
                   RETURN_VALUE
    
     202   L7:     CLEANUP_THROW
           L8:     JUMP_BACKWARD_NO_INTERRUPT 39 (to L5)
    
      --   L9:     CALL_INTRINSIC_1         3 (INTRINSIC_STOPITERATION_ERROR)
                   RERAISE                  1
    ExceptionTable:
      L1 to L3 -> L9 [0] lasti
      L3 to L4 -> L7 [2]
      L4 to L8 -> L9 [0] lasti
    
# --- Nested code object: _parse_caller_from_description ---
    # DOCSTRING: """Extract 'Caller: ...' or 'Phone: ...' from a MattBot event description."""
    # co_names: ('splitlines', 'strip', 'startswith', 'len')
    # co_varnames: ('description', 'field', 'prefix', 'line', 'stripped')
    217           RESUME                   0
    
    219           LOAD_FAST                1 (field)
                  LOAD_CONST               1 ('name')
                  COMPARE_OP              88 (bool(==))
                  POP_JUMP_IF_FALSE        2 (to L1)
                  LOAD_CONST               2 ('Caller: ')
                  JUMP_FORWARD             1 (to L2)
          L1:     LOAD_CONST               3 ('Phone: ')
          L2:     STORE_FAST               2 (prefix)
    
    220           LOAD_FAST                0 (description)
                  LOAD_ATTR                1 (splitlines + NULL|self)
                  CALL                     0
                  GET_ITER
          L3:     FOR_ITER                71 (to L5)
                  STORE_FAST               3 (line)
    
    221           LOAD_FAST                3 (line)
                  LOAD_ATTR                3 (strip + NULL|self)
                  CALL                     0
                  STORE_FAST               4 (stripped)
    
    222           LOAD_FAST                4 (stripped)
                  LOAD_ATTR                5 (startswith + NULL|self)
                  LOAD_FAST                2 (prefix)
                  CALL                     1
                  TO_BOOL
                  POP_JUMP_IF_TRUE         2 (to L4)
                  JUMP_BACKWARD           43 (to L3)
    
    223   L4:     LOAD_FAST                4 (stripped)
                  LOAD_GLOBAL              7 (len + NULL)
                  LOAD_FAST                2 (prefix)
                  CALL                     1
                  LOAD_CONST               4 (None)
                  BINARY_SLICE
                  LOAD_ATTR                3 (strip + NULL|self)
                  CALL                     0
                  SWAP                     2
                  POP_TOP
                  RETURN_VALUE
    
    220   L5:     END_FOR
                  POP_TOP
    
    224           RETURN_CONST             4 (None)
    
# --- Nested code object: list_events ---
    # DOCSTRING: """List events from the user's primary Google Calendar.

All returned ``start`` / ``end`` ISO strings are normalised to the
caller-supplied *timezone* so the mobile app can display them
without knowing the user's timezone itself.
"""
    # co_names: ('get_valid_access_token', 'httpx', 'AsyncClient', '_TIMEOUT', 'get', '_GOOGLE_CALENDAR_API', 'status_code', 'logger', 'error', 'json', 'append', 'len', 'bool', '_parse_caller_from_description')
    # co_varnames: ('db', 'user_id', 'time_min', 'time_max', 'timezone', 'token', 'params', 'client', 'resp', 'data', 'items', 'results', 'ev', 'ext_private', 'mattbot_call_id', 'desc')
     227            RETURN_GENERATOR
                    POP_TOP
            L1:     RESUME                   0
    
     240            LOAD_GLOBAL              1 (get_valid_access_token + NULL)
                    LOAD_FAST_LOAD_FAST      1 (db, user_id)
                    CALL                     2
                    GET_AWAITABLE            0
                    LOAD_CONST               1 (None)
            L2:     SEND                     3 (to L5)
            L3:     YIELD_VALUE              1
            L4:     RESUME                   3
                    JUMP_BACKWARD_NO_INTERRUPT 5 (to L2)
            L5:     END_SEND
                    STORE_FAST               5 (token)
    
     241            LOAD_FAST                5 (token)
                    TO_BOOL
                    POP_JUMP_IF_TRUE         2 (to L6)
    
     242            BUILD_LIST               0
                    RETURN_VALUE
    
     245    L6:     LOAD_FAST                2 (time_min)
    
     246            LOAD_FAST                3 (time_max)
    
     247            LOAD_CONST               2 ('true')
    
     248            LOAD_CONST               3 ('startTime')
    
     249            LOAD_CONST               4 ('250')
    
     250            LOAD_FAST                4 (timezone)
    
     244            LOAD_CONST               5 (('timeMin', 'timeMax', 'singleEvents', 'orderBy', 'maxResults', 'timeZone'))
                    BUILD_CONST_KEY_MAP      6
                    STORE_FAST               6 (params)
    
     252            LOAD_GLOBAL              2 (httpx)
                    LOAD_ATTR                4 (AsyncClient)
                    PUSH_NULL
                    LOAD_GLOBAL              6 (_TIMEOUT)
                    LOAD_CONST               6 (('timeout',))
                    CALL_KW                  1
                    BEFORE_ASYNC_WITH
                    GET_AWAITABLE            1
                    LOAD_CONST               1 (None)
            L7:     SEND                     3 (to L10)
            L8:     YIELD_VALUE              1
            L9:     RESUME                   3
                    JUMP_BACKWARD_NO_INTERRUPT 5 (to L7)
           L10:     END_SEND
           L11:     STORE_FAST               7 (client)
    
     253            LOAD_FAST                7 (client)
                    LOAD_ATTR                9 (get + NULL|self)
    
     254            LOAD_GLOBAL             10 (_GOOGLE_CALENDAR_API)
                    FORMAT_SIMPLE
                    LOAD_CONST               7 ('/calendars/primary/events')
                    BUILD_STRING             2
    
     255            LOAD_CONST               8 ('Authorization')
                    LOAD_CONST               9 ('Bearer ')
                    LOAD_FAST                5 (token)
                    FORMAT_SIMPLE
                    BUILD_STRING             2
                    BUILD_MAP                1
    
     256            LOAD_FAST                6 (params)
    
     253            LOAD_CONST              10 (('headers', 'params'))
                    CALL_KW                  3
                    GET_AWAITABLE            0
                    LOAD_CONST               1 (None)
           L12:     SEND                     3 (to L15)
           L13:     YIELD_VALUE              1
           L14:     RESUME                   3
                    JUMP_BACKWARD_NO_INTERRUPT 5 (to L12)
           L15:     END_SEND
                    STORE_FAST               8 (resp)
    
     258            LOAD_FAST                8 (resp)
                    LOAD_ATTR               12 (status_code)
                    LOAD_CONST              11 (200)
                    COMPARE_OP             119 (bool(!=))
                    POP_JUMP_IF_FALSE       51 (to L21)
    
     259            LOAD_GLOBAL             14 (logger)
                    LOAD_ATTR               17 (error + NULL|self)
                    LOAD_CONST              12 ('Google Calendar list_events failed: %d')
                    LOAD_FAST                8 (resp)
                    LOAD_ATTR               12 (status_code)
                    CALL                     2
                    POP_TOP
    
     260            BUILD_LIST               0
    
     252   L16:     SWAP                     2
                    LOAD_CONST               1 (None)
                    LOAD_CONST               1 (None)
                    LOAD_CONST               1 (None)
                    CALL                     2
                    GET_AWAITABLE            2
                    LOAD_CONST               1 (None)
           L17:     SEND                     3 (to L20)
           L18:     YIELD_VALUE              1
           L19:     RESUME                   3
                    JUMP_BACKWARD_NO_INTERRUPT 5 (to L17)
           L20:     END_SEND
                    POP_TOP
                    RETURN_VALUE
    
     261   L21:     LOAD_FAST                8 (resp)
                    LOAD_ATTR               19 (json + NULL|self)
                    CALL                     0
                    STORE_FAST               9 (data)
    
     262            LOAD_FAST                9 (data)
                    LOAD_ATTR                9 (get + NULL|self)
                    LOAD_CONST              13 ('items')
                    BUILD_LIST               0
                    CALL                     2
                    STORE_FAST              10 (items)
    
     263            BUILD_LIST               0
                    STORE_FAST              11 (results)
    
     264            LOAD_FAST               10 (items)
                    GET_ITER
           L22:     EXTENDED_ARG             1
                    FOR_ITER               398 (to L25)
                    STORE_FAST              12 (ev)
    
     265            LOAD_FAST               12 (ev)
                    LOAD_ATTR                9 (get + NULL|self)
                    LOAD_CONST              14 ('extendedProperties')
                    BUILD_MAP                0
                    CALL                     2
                    LOAD_ATTR                9 (get + NULL|self)
                    LOAD_CONST              15 ('private')
                    BUILD_MAP                0
                    CALL                     2
                    STORE_FAST              13 (ext_private)
    
     266            LOAD_FAST               13 (ext_private)
                    LOAD_ATTR                9 (get + NULL|self)
                    LOAD_CONST              16 ('mattbot_call_id')
                    CALL                     1
                    STORE_FAST              14 (mattbot_call_id)
    
     267            LOAD_FAST               12 (ev)
                    LOAD_ATTR                9 (get + NULL|self)
                    LOAD_CONST              17 ('description')
                    LOAD_CONST              18 ('')
                    CALL                     2
                    STORE_FAST              15 (desc)
    
     268            LOAD_FAST               11 (results)
                    LOAD_ATTR               21 (append + NULL|self)
    
     269            LOAD_FAST               12 (ev)
                    LOAD_ATTR                9 (get + NULL|self)
                    LOAD_CONST              19 ('id')
                    LOAD_CONST              18 ('')
                    CALL                     2
    
     270            LOAD_FAST               12 (ev)
                    LOAD_ATTR                9 (get + NULL|self)
                    LOAD_CONST              20 ('summary')
                    LOAD_CONST              21 ('(No title)')
                    CALL                     2
    
     272            LOAD_FAST               12 (ev)
                    LOAD_ATTR                9 (get + NULL|self)
                    LOAD_CONST              22 ('start')
                    BUILD_MAP                0
                    CALL                     2
                    LOAD_ATTR                9 (get + NULL|self)
                    LOAD_CONST              23 ('dateTime')
                    CALL                     1
                    COPY                     1
                    TO_BOOL
                    POP_JUMP_IF_TRUE        34 (to L23)
                    POP_TOP
    
     273            LOAD_FAST               12 (ev)
                    LOAD_ATTR                9 (get + NULL|self)
                    LOAD_CONST              22 ('start')
                    BUILD_MAP                0
                    CALL                     2
                    LOAD_ATTR                9 (get + NULL|self)
                    LOAD_CONST              24 ('date')
                    LOAD_CONST              18 ('')
                    CALL                     2
    
     276   L23:     LOAD_FAST               12 (ev)
                    LOAD_ATTR                9 (get + NULL|self)
                    LOAD_CONST              25 ('end')
                    BUILD_MAP                0
                    CALL                     2
                    LOAD_ATTR                9 (get + NULL|self)
                    LOAD_CONST              23 ('dateTime')
                    CALL                     1
                    COPY                     1
                    TO_BOOL
                    POP_JUMP_IF_TRUE        34 (to L24)
                    POP_TOP
    
     277            LOAD_FAST               12 (ev)
                    LOAD_ATTR                9 (get + NULL|self)
                    LOAD_CONST              25 ('end')
                    BUILD_MAP                0
                    CALL                     2
                    LOAD_ATTR                9 (get + NULL|self)
                    LOAD_CONST              24 ('date')
                    LOAD_CONST              18 ('')
                    CALL                     2
    
     279   L24:     LOAD_FAST               15 (desc)
    
     280            LOAD_FAST               12 (ev)
                    LOAD_ATTR                9 (get + NULL|self)
                    LOAD_CONST              26 ('location')
                    LOAD_CONST              18 ('')
                    CALL                     2
    
     281            LOAD_FAST               12 (ev)
                    LOAD_ATTR                9 (get + NULL|self)
                    LOAD_CONST              27 ('status')
                    LOAD_CONST              28 ('confirmed')
                    CALL                     2
    
     282            LOAD_FAST               12 (ev)
                    LOAD_ATTR                9 (get + NULL|self)
                    LOAD_CONST              29 ('organizer')
                    BUILD_MAP                0
                    CALL                     2
                    LOAD_ATTR                9 (get + NULL|self)
                    LOAD_CONST              30 ('email')
                    LOAD_CONST              18 ('')
                    CALL                     2
    
     283            LOAD_GLOBAL             23 (len + NULL)
                    LOAD_FAST               12 (ev)
                    LOAD_ATTR                9 (get + NULL|self)
                    LOAD_CONST              31 ('attendees')
                    BUILD_LIST               0
                    CALL                     2
                    CALL                     1
    
     284            LOAD_FAST               14 (mattbot_call_id)
    
     285            LOAD_GLOBAL             25 (bool + NULL)
                    LOAD_FAST               14 (mattbot_call_id)
                    CALL                     1
    
     286            LOAD_GLOBAL             27 (_parse_caller_from_description + NULL)
                    LOAD_FAST               15 (desc)
                    LOAD_CONST              32 ('name')
                    CALL                     2
    
     287            LOAD_GLOBAL             27 (_parse_caller_from_description + NULL)
                    LOAD_FAST               15 (desc)
                    LOAD_CONST              33 ('phone')
                    CALL                     2
    
     268            LOAD_CONST              34 (('id', 'summary', 'start', 'end', 'description', 'location', 'status', 'organizer_email', 'attendees_count', 'call_id', 'is_mattbot_booked', 'caller_name', 'caller_phone'))
                    BUILD_CONST_KEY_MAP     13
                    CALL                     1
                    POP_TOP
                    EXTENDED_ARG             1
                    JUMP_BACKWARD          401 (to L22)
    
     264   L25:     END_FOR
                    POP_TOP
    
     289            LOAD_FAST               11 (results)
    
     252   L26:     SWAP                     2
                    LOAD_CONST               1 (None)
                    LOAD_CONST               1 (None)
                    LOAD_CONST               1 (None)
                    CALL                     2
                    GET_AWAITABLE            2
                    LOAD_CONST               1 (None)
           L27:     SEND                     3 (to L30)
           L28:     YIELD_VALUE              1
           L29:     RESUME                   3
                    JUMP_BACKWARD_NO_INTERRUPT 5 (to L27)
           L30:     END_SEND
                    POP_TOP
                    RETURN_VALUE
    
     240   L31:     CLEANUP_THROW
           L32:     EXTENDED_ARG             2
                    JUMP_BACKWARD_NO_INTERRUPT 620 (to L5)
    
     252   L33:     CLEANUP_THROW
           L34:     EXTENDED_ARG             2
                    JUMP_BACKWARD_NO_INTERRUPT 572 (to L10)
    
     253   L35:     CLEANUP_THROW
           L36:     EXTENDED_ARG             2
                    JUMP_BACKWARD_NO_INTERRUPT 538 (to L15)
    
     252   L37:     CLEANUP_THROW
           L38:     EXTENDED_ARG             1
                    JUMP_BACKWARD_NO_INTERRUPT 475 (to L20)
           L39:     CLEANUP_THROW
           L40:     JUMP_BACKWARD_NO_INTERRUPT 17 (to L30)
           L41:     PUSH_EXC_INFO
                    WITH_EXCEPT_START
                    GET_AWAITABLE            2
                    LOAD_CONST               1 (None)
           L42:     SEND                     4 (to L46)
           L43:     YIELD_VALUE              1
           L44:     RESUME                   3
                    JUMP_BACKWARD_NO_INTERRUPT 5 (to L42)
           L45:     CLEANUP_THROW
           L46:     END_SEND
                    TO_BOOL
                    POP_JUMP_IF_TRUE         1 (to L47)
                    RERAISE                  2
           L47:     POP_TOP
           L48:     POP_EXCEPT
                    POP_TOP
                    POP_TOP
                    RETURN_CONST             1 (None)
    
      --   L49:     COPY                     3
                    POP_EXCEPT
                    RERAISE                  1
           L50:     CALL_INTRINSIC_1         3 (INTRINSIC_STOPITERATION_ERROR)
                    RERAISE                  1
    ExceptionTable:
      L1 to L3 -> L50 [0] lasti
      L3 to L4 -> L31 [2]
      L4 to L8 -> L50 [0] lasti
      L8 to L9 -> L33 [3]
      L9 to L11 -> L50 [0] lasti
      L11 to L13 -> L41 [1] lasti
      L13 to L14 -> L35 [3]
      L14 to L16 -> L41 [1] lasti
      L16 to L18 -> L50 [0] lasti
      L18 to L19 -> L37 [3]
      L19 to L21 -> L50 [0] lasti
      L21 to L26 -> L41 [1] lasti
      L26 to L28 -> L50 [0] lasti
      L28 to L29 -> L39 [3]
      L29 to L32 -> L50 [0] lasti
      L33 to L34 -> L50 [0] lasti
      L35 to L36 -> L41 [1] lasti
      L37 to L38 -> L50 [0] lasti
      L39 to L40 -> L50 [0] lasti
      L41 to L43 -> L49 [3] lasti
      L43 to L44 -> L45 [6]
      L44 to L48 -> L49 [3] lasti
      L48 to L50 -> L50 [0] lasti
    
# --- Nested code object: create_event ---
    # DOCSTRING: """Create an event on the user's primary Google Calendar."""
    # co_names: ('get_valid_access_token', 'str', 'httpx', 'AsyncClient', '_TIMEOUT', 'post', '_GOOGLE_CALENDAR_API', 'status_code', 'logger', 'error', 'text', 'json', 'get')
    # co_varnames: ('db', 'user_id', 'summary', 'start_datetime', 'end_datetime', 'description', 'attendee_email', 'timezone', 'call_id', 'token', 'event_body', 'client', 'resp', 'data')
     292            RETURN_GENERATOR
                    POP_TOP
            L1:     RESUME                   0
    
     304            LOAD_GLOBAL              1 (get_valid_access_token + NULL)
                    LOAD_FAST_LOAD_FAST      1 (db, user_id)
                    CALL                     2
                    GET_AWAITABLE            0
                    LOAD_CONST               1 (None)
            L2:     SEND                     3 (to L5)
            L3:     YIELD_VALUE              1
            L4:     RESUME                   3
                    JUMP_BACKWARD_NO_INTERRUPT 5 (to L2)
            L5:     END_SEND
                    STORE_FAST               9 (token)
    
     305            LOAD_FAST                9 (token)
                    TO_BOOL
                    POP_JUMP_IF_TRUE         1 (to L6)
    
     306            RETURN_CONST             1 (None)
    
     309    L6:     LOAD_FAST                2 (summary)
    
     310            LOAD_FAST                5 (description)
    
     311            LOAD_FAST_LOAD_FAST     55 (start_datetime, timezone)
                    LOAD_CONST               2 (('dateTime', 'timeZone'))
                    BUILD_CONST_KEY_MAP      2
    
     312            LOAD_FAST_LOAD_FAST     71 (end_datetime, timezone)
                    LOAD_CONST               2 (('dateTime', 'timeZone'))
                    BUILD_CONST_KEY_MAP      2
    
     308            LOAD_CONST               3 (('summary', 'description', 'start', 'end'))
                    BUILD_CONST_KEY_MAP      4
                    STORE_FAST              10 (event_body)
    
     314            LOAD_FAST                6 (attendee_email)
                    TO_BOOL
                    POP_JUMP_IF_FALSE        8 (to L7)
    
     315            LOAD_CONST               4 ('email')
                    LOAD_FAST                6 (attendee_email)
                    BUILD_MAP                1
                    BUILD_LIST               1
                    LOAD_FAST               10 (event_body)
                    LOAD_CONST               5 ('attendees')
                    STORE_SUBSCR
    
     316    L7:     LOAD_FAST                8 (call_id)
                    TO_BOOL
                    POP_JUMP_IF_FALSE       18 (to L8)
    
     318            LOAD_CONST               6 ('private')
                    LOAD_CONST               7 ('mattbot_call_id')
                    LOAD_GLOBAL              3 (str + NULL)
                    LOAD_FAST                8 (call_id)
                    CALL                     1
                    BUILD_MAP                1
    
     317            BUILD_MAP                1
                    LOAD_FAST               10 (event_body)
                    LOAD_CONST               8 ('extendedProperties')
                    STORE_SUBSCR
    
     321    L8:     LOAD_GLOBAL              4 (httpx)
                    LOAD_ATTR                6 (AsyncClient)
                    PUSH_NULL
                    LOAD_GLOBAL              8 (_TIMEOUT)
                    LOAD_CONST               9 (('timeout',))
                    CALL_KW                  1
                    BEFORE_ASYNC_WITH
                    GET_AWAITABLE            1
                    LOAD_CONST               1 (None)
            L9:     SEND                     3 (to L12)
           L10:     YIELD_VALUE              1
           L11:     RESUME                   3
                    JUMP_BACKWARD_NO_INTERRUPT 5 (to L9)
           L12:     END_SEND
           L13:     STORE_FAST              11 (client)
    
     322            LOAD_FAST               11 (client)
                    LOAD_ATTR               11 (post + NULL|self)
    
     323            LOAD_GLOBAL             12 (_GOOGLE_CALENDAR_API)
                    FORMAT_SIMPLE
                    LOAD_CONST              10 ('/calendars/primary/events')
                    BUILD_STRING             2
    
     325            LOAD_CONST              11 ('Bearer ')
                    LOAD_FAST                9 (token)
                    FORMAT_SIMPLE
                    BUILD_STRING             2
    
     326            LOAD_CONST              12 ('application/json')
    
     324            LOAD_CONST              13 (('Authorization', 'Content-Type'))
                    BUILD_CONST_KEY_MAP      2
    
     328            LOAD_FAST               10 (event_body)
    
     322            LOAD_CONST              14 (('headers', 'json'))
                    CALL_KW                  3
                    GET_AWAITABLE            0
                    LOAD_CONST               1 (None)
           L14:     SEND                     3 (to L17)
           L15:     YIELD_VALUE              1
           L16:     RESUME                   3
                    JUMP_BACKWARD_NO_INTERRUPT 5 (to L14)
           L17:     END_SEND
                    STORE_FAST              12 (resp)
    
     330            LOAD_FAST               12 (resp)
                    LOAD_ATTR               14 (status_code)
                    LOAD_CONST              15 ((200, 201))
                    CONTAINS_OP              1
                    POP_JUMP_IF_FALSE       64 (to L23)
    
     331            LOAD_GLOBAL             16 (logger)
                    LOAD_ATTR               19 (error + NULL|self)
    
     332            LOAD_CONST              16 ('Google Calendar create_event failed: %d %s')
    
     333            LOAD_FAST               12 (resp)
                    LOAD_ATTR               14 (status_code)
    
     334            LOAD_FAST               12 (resp)
                    LOAD_ATTR               20 (text)
                    LOAD_CONST               1 (None)
                    LOAD_CONST              17 (300)
                    BINARY_SLICE
    
     331            CALL                     3
                    POP_TOP
    
     336            NOP
    
     321   L18:     LOAD_CONST               1 (None)
                    LOAD_CONST               1 (None)
                    LOAD_CONST               1 (None)
                    CALL                     2
                    GET_AWAITABLE            2
                    LOAD_CONST               1 (None)
           L19:     SEND                     3 (to L22)
           L20:     YIELD_VALUE              1
           L21:     RESUME                   3
                    JUMP_BACKWARD_NO_INTERRUPT 5 (to L19)
           L22:     END_SEND
                    POP_TOP
                    RETURN_CONST             1 (None)
    
     337   L23:     LOAD_FAST               12 (resp)
                    LOAD_ATTR               23 (json + NULL|self)
                    CALL                     0
                    STORE_FAST              13 (data)
    
     339            LOAD_FAST               13 (data)
                    LOAD_ATTR               25 (get + NULL|self)
                    LOAD_CONST              18 ('id')
                    LOAD_CONST              19 ('')
                    CALL                     2
    
     340            LOAD_FAST               13 (data)
                    LOAD_ATTR               25 (get + NULL|self)
                    LOAD_CONST              20 ('summary')
                    LOAD_CONST              19 ('')
                    CALL                     2
    
     341            LOAD_FAST               13 (data)
                    LOAD_ATTR               25 (get + NULL|self)
                    LOAD_CONST              21 ('start')
                    BUILD_MAP                0
                    CALL                     2
                    LOAD_ATTR               25 (get + NULL|self)
                    LOAD_CONST              22 ('dateTime')
                    LOAD_CONST              19 ('')
                    CALL                     2
    
     342            LOAD_FAST               13 (data)
                    LOAD_ATTR               25 (get + NULL|self)
                    LOAD_CONST              23 ('end')
                    BUILD_MAP                0
                    CALL                     2
                    LOAD_ATTR               25 (get + NULL|self)
                    LOAD_CONST              22 ('dateTime')
                    LOAD_CONST              19 ('')
                    CALL                     2
    
     343            LOAD_FAST               13 (data)
                    LOAD_ATTR               25 (get + NULL|self)
                    LOAD_CONST              24 ('htmlLink')
                    LOAD_CONST              19 ('')
                    CALL                     2
    
     338            LOAD_CONST              25 (('id', 'summary', 'start', 'end', 'html_link'))
                    BUILD_CONST_KEY_MAP      5
    
     321   L24:     SWAP                     2
                    LOAD_CONST               1 (None)
                    LOAD_CONST               1 (None)
                    LOAD_CONST               1 (None)
                    CALL                     2
                    GET_AWAITABLE            2
                    LOAD_CONST               1 (None)
           L25:     SEND                     3 (to L28)
           L26:     YIELD_VALUE              1
           L27:     RESUME                   3
                    JUMP_BACKWARD_NO_INTERRUPT 5 (to L25)
           L28:     END_SEND
                    POP_TOP
                    RETURN_VALUE
    
     304   L29:     CLEANUP_THROW
           L30:     EXTENDED_ARG             1
                    JUMP_BACKWARD_NO_INTERRUPT 368 (to L5)
    
     321   L31:     CLEANUP_THROW
           L32:     EXTENDED_ARG             1
                    JUMP_BACKWARD_NO_INTERRUPT 279 (to L12)
    
     322   L33:     CLEANUP_THROW
           L34:     JUMP_BACKWARD_NO_INTERRUPT 243 (to L17)
    
     321   L35:     CLEANUP_THROW
           L36:     JUMP_BACKWARD_NO_INTERRUPT 166 (to L22)
           L37:     CLEANUP_THROW
           L38:     JUMP_BACKWARD_NO_INTERRUPT 15 (to L28)
           L39:     PUSH_EXC_INFO
                    WITH_EXCEPT_START
                    GET_AWAITABLE            2
                    LOAD_CONST               1 (None)
           L40:     SEND                     4 (to L44)
           L41:     YIELD_VALUE              1
           L42:     RESUME                   3
                    JUMP_BACKWARD_NO_INTERRUPT 5 (to L40)
           L43:     CLEANUP_THROW
           L44:     END_SEND
                    TO_BOOL
                    POP_JUMP_IF_TRUE         1 (to L45)
                    RERAISE                  2
           L45:     POP_TOP
           L46:     POP_EXCEPT
                    POP_TOP
                    POP_TOP
                    RETURN_CONST             1 (None)
    
      --   L47:     COPY                     3
                    POP_EXCEPT
                    RERAISE                  1
           L48:     CALL_INTRINSIC_1         3 (INTRINSIC_STOPITERATION_ERROR)
                    RERAISE                  1
    ExceptionTable:
      L1 to L3 -> L48 [0] lasti
      L3 to L4 -> L29 [2]
      L4 to L10 -> L48 [0] lasti
      L10 to L11 -> L31 [3]
      L11 to L13 -> L48 [0] lasti
      L13 to L15 -> L39 [1] lasti
      L15 to L16 -> L33 [3]
      L16 to L18 -> L39 [1] lasti
      L18 to L20 -> L48 [0] lasti
      L20 to L21 -> L35 [2]
      L21 to L23 -> L48 [0] lasti
      L23 to L24 -> L39 [1] lasti
      L24 to L26 -> L48 [0] lasti
      L26 to L27 -> L37 [3]
      L27 to L30 -> L48 [0] lasti
      L31 to L32 -> L48 [0] lasti
      L33 to L34 -> L39 [1] lasti
      L35 to L36 -> L48 [0] lasti
      L37 to L38 -> L48 [0] lasti
      L39 to L41 -> L47 [3] lasti
      L41 to L42 -> L43 [6]
      L42 to L46 -> L47 [3] lasti
      L46 to L48 -> L48 [0] lasti
    
# --- Nested code object: get_free_busy ---
    # DOCSTRING: """Query Google Calendar freebusy API to get busy intervals."""
    # co_names: ('get_valid_access_token', 'httpx', 'AsyncClient', '_TIMEOUT', 'post', '_GOOGLE_CALENDAR_API', 'status_code', 'logger', 'error', 'json', 'get')
    # co_varnames: ('db', 'user_id', 'time_min', 'time_max', 'token', 'body', 'client', 'resp', 'data')
     347            RETURN_GENERATOR
                    POP_TOP
            L1:     RESUME                   0
    
     354            LOAD_GLOBAL              1 (get_valid_access_token + NULL)
                    LOAD_FAST_LOAD_FAST      1 (db, user_id)
                    CALL                     2
                    GET_AWAITABLE            0
                    LOAD_CONST               1 (None)
            L2:     SEND                     3 (to L5)
            L3:     YIELD_VALUE              1
            L4:     RESUME                   3
                    JUMP_BACKWARD_NO_INTERRUPT 5 (to L2)
            L5:     END_SEND
                    STORE_FAST               4 (token)
    
     355            LOAD_FAST                4 (token)
                    TO_BOOL
                    POP_JUMP_IF_TRUE         2 (to L6)
    
     356            BUILD_LIST               0
                    RETURN_VALUE
    
     359    L6:     LOAD_FAST                2 (time_min)
    
     360            LOAD_FAST                3 (time_max)
    
     361            LOAD_CONST               2 ('id')
                    LOAD_CONST               3 ('primary')
                    BUILD_MAP                1
                    BUILD_LIST               1
    
     358            LOAD_CONST               4 (('timeMin', 'timeMax', 'items'))
                    BUILD_CONST_KEY_MAP      3
                    STORE_FAST               5 (body)
    
     363            LOAD_GLOBAL              2 (httpx)
                    LOAD_ATTR                4 (AsyncClient)
                    PUSH_NULL
                    LOAD_GLOBAL              6 (_TIMEOUT)
                    LOAD_CONST               5 (('timeout',))
                    CALL_KW                  1
                    BEFORE_ASYNC_WITH
                    GET_AWAITABLE            1
                    LOAD_CONST               1 (None)
            L7:     SEND                     3 (to L10)
            L8:     YIELD_VALUE              1
            L9:     RESUME                   3
                    JUMP_BACKWARD_NO_INTERRUPT 5 (to L7)
           L10:     END_SEND
           L11:     STORE_FAST               6 (client)
    
     364            LOAD_FAST                6 (client)
                    LOAD_ATTR                9 (post + NULL|self)
    
     365            LOAD_GLOBAL             10 (_GOOGLE_CALENDAR_API)
                    FORMAT_SIMPLE
                    LOAD_CONST               6 ('/freeBusy')
                    BUILD_STRING             2
    
     367            LOAD_CONST               7 ('Bearer ')
                    LOAD_FAST                4 (token)
                    FORMAT_SIMPLE
                    BUILD_STRING             2
    
     368            LOAD_CONST               8 ('application/json')
    
     366            LOAD_CONST               9 (('Authorization', 'Content-Type'))
                    BUILD_CONST_KEY_MAP      2
    
     370            LOAD_FAST                5 (body)
    
     364            LOAD_CONST              10 (('headers', 'json'))
                    CALL_KW                  3
                    GET_AWAITABLE            0
                    LOAD_CONST               1 (None)
           L12:     SEND                     3 (to L15)
           L13:     YIELD_VALUE              1
           L14:     RESUME                   3
                    JUMP_BACKWARD_NO_INTERRUPT 5 (to L12)
           L15:     END_SEND
                    STORE_FAST               7 (resp)
    
     372            LOAD_FAST                7 (resp)
                    LOAD_ATTR               12 (status_code)
                    LOAD_CONST              11 (200)
                    COMPARE_OP             119 (bool(!=))
                    POP_JUMP_IF_FALSE       51 (to L21)
    
     373            LOAD_GLOBAL             14 (logger)
                    LOAD_ATTR               17 (error + NULL|self)
                    LOAD_CONST              12 ('Google Calendar freeBusy failed: %d')
                    LOAD_FAST                7 (resp)
                    LOAD_ATTR               12 (status_code)
                    CALL                     2
                    POP_TOP
    
     374            BUILD_LIST               0
    
     363   L16:     SWAP                     2
                    LOAD_CONST               1 (None)
                    LOAD_CONST               1 (None)
                    LOAD_CONST               1 (None)
                    CALL                     2
                    GET_AWAITABLE            2
                    LOAD_CONST               1 (None)
           L17:     SEND                     3 (to L20)
           L18:     YIELD_VALUE              1
           L19:     RESUME                   3
                    JUMP_BACKWARD_NO_INTERRUPT 5 (to L17)
           L20:     END_SEND
                    POP_TOP
                    RETURN_VALUE
    
     375   L21:     LOAD_FAST                7 (resp)
                    LOAD_ATTR               19 (json + NULL|self)
                    CALL                     0
                    STORE_FAST               8 (data)
    
     376            LOAD_FAST                8 (data)
                    LOAD_ATTR               21 (get + NULL|self)
                    LOAD_CONST              13 ('calendars')
                    BUILD_MAP                0
                    CALL                     2
                    LOAD_ATTR               21 (get + NULL|self)
                    LOAD_CONST               3 ('primary')
                    BUILD_MAP                0
                    CALL                     2
                    LOAD_ATTR               21 (get + NULL|self)
                    LOAD_CONST              14 ('busy')
                    BUILD_LIST               0
                    CALL                     2
    
     363   L22:     SWAP                     2
                    LOAD_CONST               1 (None)
                    LOAD_CONST               1 (None)
                    LOAD_CONST               1 (None)
                    CALL                     2
                    GET_AWAITABLE            2
                    LOAD_CONST               1 (None)
           L23:     SEND                     3 (to L26)
           L24:     YIELD_VALUE              1
           L25:     RESUME                   3
                    JUMP_BACKWARD_NO_INTERRUPT 5 (to L23)
           L26:     END_SEND
                    POP_TOP
                    RETURN_VALUE
    
     354   L27:     CLEANUP_THROW
           L28:     JUMP_BACKWARD_NO_INTERRUPT 243 (to L5)
    
     363   L29:     CLEANUP_THROW
           L30:     JUMP_BACKWARD_NO_INTERRUPT 194 (to L10)
    
     364   L31:     CLEANUP_THROW
           L32:     JUMP_BACKWARD_NO_INTERRUPT 158 (to L15)
    
     363   L33:     CLEANUP_THROW
           L34:     JUMP_BACKWARD_NO_INTERRUPT 94 (to L20)
           L35:     CLEANUP_THROW
           L36:     JUMP_BACKWARD_NO_INTERRUPT 13 (to L26)
           L37:     PUSH_EXC_INFO
                    WITH_EXCEPT_START
                    GET_AWAITABLE            2
                    LOAD_CONST               1 (None)
           L38:     SEND                     4 (to L42)
           L39:     YIELD_VALUE              1
           L40:     RESUME                   3
                    JUMP_BACKWARD_NO_INTERRUPT 5 (to L38)
           L41:     CLEANUP_THROW
           L42:     END_SEND
                    TO_BOOL
                    POP_JUMP_IF_TRUE         1 (to L43)
                    RERAISE                  2
           L43:     POP_TOP
           L44:     POP_EXCEPT
                    POP_TOP
                    POP_TOP
                    RETURN_CONST             1 (None)
    
      --   L45:     COPY                     3
                    POP_EXCEPT
                    RERAISE                  1
           L46:     CALL_INTRINSIC_1         3 (INTRINSIC_STOPITERATION_ERROR)
                    RERAISE                  1
    ExceptionTable:
      L1 to L3 -> L46 [0] lasti
      L3 to L4 -> L27 [2]
      L4 to L8 -> L46 [0] lasti
      L8 to L9 -> L29 [3]
      L9 to L11 -> L46 [0] lasti
      L11 to L13 -> L37 [1] lasti
      L13 to L14 -> L31 [3]
      L14 to L16 -> L37 [1] lasti
      L16 to L18 -> L46 [0] lasti
      L18 to L19 -> L33 [3]
      L19 to L21 -> L46 [0] lasti
      L21 to L22 -> L37 [1] lasti
      L22 to L24 -> L46 [0] lasti
      L24 to L25 -> L35 [3]
      L25 to L28 -> L46 [0] lasti
      L29 to L30 -> L46 [0] lasti
      L31 to L32 -> L37 [1] lasti
      L33 to L34 -> L46 [0] lasti
      L35 to L36 -> L46 [0] lasti
      L37 to L39 -> L45 [3] lasti
      L39 to L40 -> L41 [6]
      L40 to L44 -> L45 [3] lasti
      L44 to L46 -> L46 [0] lasti
    
# --- Nested code object: find_available_slots ---
    # DOCSTRING: """Find available time slots on a given date.

Checks freebusy data and returns open slots within business hours.
"""
    # --- Nested code object: find_available_slots.<locals>.<lambda> ---
        # co_names: ()
        # co_varnames: ('x',)
        412           RESUME                   0
                      LOAD_FAST                0 (x)
                      LOAD_CONST               1 (0)
                      BINARY_SUBSCR
                      RETURN_VALUE
        
    # co_names: ('zoneinfo', 'ZoneInfo', 'datetime', 'strptime', 'date', 'dt_time', 'combine', 'isoformat', 'get_free_busy', 'fromisoformat', 'append', 'sort', 'timedelta', 'astimezone')
    # co_varnames: ('db', 'user_id', 'date_str', 'duration_minutes', 'business_start', 'business_end', 'timezone', 'ZoneInfo', 'tz', 'day', 'start_hour', 'end_hour', 'day_start', 'day_end', 'time_min', 'time_max', 'busy', 'busy_intervals', 'b', 'bs', 'be', 'slots', 'slot_duration', 'cursor', 'busy_start', 'busy_end')
     379            RETURN_GENERATOR
                    POP_TOP
            L1:     RESUME                   0
    
     392            LOAD_CONST               1 (0)
                    LOAD_CONST               2 (('ZoneInfo',))
                    IMPORT_NAME              0 (zoneinfo)
                    IMPORT_FROM              1 (ZoneInfo)
                    STORE_FAST               7 (ZoneInfo)
                    POP_TOP
    
     394            LOAD_FAST                7 (ZoneInfo)
                    PUSH_NULL
                    LOAD_FAST                6 (timezone)
                    CALL                     1
                    STORE_FAST               8 (tz)
    
     395            LOAD_GLOBAL              4 (datetime)
                    LOAD_ATTR                6 (strptime)
                    PUSH_NULL
                    LOAD_FAST                2 (date_str)
                    LOAD_CONST               3 ('%Y-%m-%d')
                    CALL                     2
                    LOAD_ATTR                9 (date + NULL|self)
                    CALL                     0
                    STORE_FAST               9 (day)
    
     396            LOAD_FAST                4 (business_start)
                    COPY                     1
                    TO_BOOL
                    POP_JUMP_IF_TRUE        12 (to L2)
                    POP_TOP
                    LOAD_GLOBAL             11 (dt_time + NULL)
                    LOAD_CONST               4 (9)
                    LOAD_CONST               1 (0)
                    CALL                     2
            L2:     STORE_FAST              10 (start_hour)
    
     397            LOAD_FAST                5 (business_end)
                    COPY                     1
                    TO_BOOL
                    POP_JUMP_IF_TRUE        12 (to L3)
                    POP_TOP
                    LOAD_GLOBAL             11 (dt_time + NULL)
                    LOAD_CONST               5 (17)
                    LOAD_CONST               1 (0)
                    CALL                     2
            L3:     STORE_FAST              11 (end_hour)
    
     399            LOAD_GLOBAL              4 (datetime)
                    LOAD_ATTR               12 (combine)
                    PUSH_NULL
                    LOAD_FAST_LOAD_FAST    154 (day, start_hour)
                    LOAD_FAST                8 (tz)
                    LOAD_CONST               6 (('tzinfo',))
                    CALL_KW                  3
                    STORE_FAST              12 (day_start)
    
     400            LOAD_GLOBAL              4 (datetime)
                    LOAD_ATTR               12 (combine)
                    PUSH_NULL
                    LOAD_FAST_LOAD_FAST    155 (day, end_hour)
                    LOAD_FAST                8 (tz)
                    LOAD_CONST               6 (('tzinfo',))
                    CALL_KW                  3
                    STORE_FAST              13 (day_end)
    
     402            LOAD_FAST               12 (day_start)
                    LOAD_ATTR               15 (isoformat + NULL|self)
                    CALL                     0
                    STORE_FAST              14 (time_min)
    
     403            LOAD_FAST               13 (day_end)
                    LOAD_ATTR               15 (isoformat + NULL|self)
                    CALL                     0
                    STORE_FAST              15 (time_max)
    
     405            LOAD_GLOBAL             17 (get_free_busy + NULL)
                    LOAD_FAST_LOAD_FAST      1 (db, user_id)
                    LOAD_FAST_LOAD_FAST    239 (time_min, time_max)
                    CALL                     4
                    GET_AWAITABLE            0
                    LOAD_CONST               7 (None)
            L4:     SEND                     3 (to L7)
            L5:     YIELD_VALUE              1
            L6:     RESUME                   3
                    JUMP_BACKWARD_NO_INTERRUPT 5 (to L4)
            L7:     END_SEND
                    STORE_FAST              16 (busy)
    
     407            BUILD_LIST               0
                    STORE_FAST              17 (busy_intervals)
    
     408            LOAD_FAST               16 (busy)
                    GET_ITER
            L8:     FOR_ITER                72 (to L9)
                    STORE_FAST              18 (b)
    
     409            LOAD_GLOBAL              4 (datetime)
                    LOAD_ATTR               18 (fromisoformat)
                    PUSH_NULL
                    LOAD_FAST               18 (b)
                    LOAD_CONST               8 ('start')
                    BINARY_SUBSCR
                    CALL                     1
                    STORE_FAST              19 (bs)
    
     410            LOAD_GLOBAL              4 (datetime)
                    LOAD_ATTR               18 (fromisoformat)
                    PUSH_NULL
                    LOAD_FAST               18 (b)
                    LOAD_CONST               9 ('end')
                    BINARY_SUBSCR
                    CALL                     1
                    STORE_FAST              20 (be)
    
     411            LOAD_FAST               17 (busy_intervals)
                    LOAD_ATTR               21 (append + NULL|self)
                    LOAD_FAST               19 (bs)
                    LOAD_FAST               20 (be)
                    BUILD_TUPLE              2
                    CALL                     1
                    POP_TOP
                    JUMP_BACKWARD           74 (to L8)
    
     408    L9:     END_FOR
                    POP_TOP
    
     412            LOAD_FAST               17 (busy_intervals)
                    LOAD_ATTR               23 (sort + NULL|self)
                    LOAD_CONST              10 (<code object <lambda> at 0x0000024C0EF0F750, file "D:\fluence\Github\mattbot\backend\app\services\calendar_service.py", line 412>)
                    MAKE_FUNCTION
                    LOAD_CONST              11 (('key',))
                    CALL_KW                  1
                    POP_TOP
    
     414            BUILD_LIST               0
                    STORE_FAST              21 (slots)
    
     415            LOAD_GLOBAL             25 (timedelta + NULL)
                    LOAD_FAST                3 (duration_minutes)
                    LOAD_CONST              12 (('minutes',))
                    CALL_KW                  1
                    STORE_FAST              22 (slot_duration)
    
     416            LOAD_FAST               12 (day_start)
                    STORE_FAST              23 (cursor)
    
     418            LOAD_FAST               17 (busy_intervals)
                    GET_ITER
           L10:     FOR_ITER               107 (to L16)
                    UNPACK_SEQUENCE          2
                    STORE_FAST              24 (busy_start)
                    STORE_FAST              25 (busy_end)
    
     419            LOAD_FAST               23 (cursor)
                    LOAD_FAST               22 (slot_duration)
                    BINARY_OP                0 (+)
                    LOAD_FAST               24 (busy_start)
                    COMPARE_OP              58 (bool(<=))
                    POP_JUMP_IF_FALSE       67 (to L13)
    
     420   L11:     LOAD_FAST               21 (slots)
                    LOAD_ATTR               21 (append + NULL|self)
    
     421            LOAD_FAST               23 (cursor)
                    LOAD_ATTR               15 (isoformat + NULL|self)
                    CALL                     0
    
     422            LOAD_FAST               23 (cursor)
                    LOAD_FAST               22 (slot_duration)
                    BINARY_OP                0 (+)
                    LOAD_ATTR               15 (isoformat + NULL|self)
                    CALL                     0
    
     420            LOAD_CONST              13 (('start', 'end'))
                    BUILD_CONST_KEY_MAP      2
                    CALL                     1
                    POP_TOP
    
     424            LOAD_FAST               23 (cursor)
                    LOAD_FAST               22 (slot_duration)
                    BINARY_OP               13 (+=)
                    STORE_FAST              23 (cursor)
    
     419            LOAD_FAST               23 (cursor)
                    LOAD_FAST               22 (slot_duration)
                    BINARY_OP                0 (+)
                    LOAD_FAST               24 (busy_start)
                    COMPARE_OP              58 (bool(<=))
                    POP_JUMP_IF_FALSE        2 (to L13)
           L12:     JUMP_BACKWARD           67 (to L11)
    
     425   L13:     LOAD_FAST               23 (cursor)
                    LOAD_FAST               25 (busy_end)
                    COMPARE_OP              18 (bool(<))
           L14:     POP_JUMP_IF_TRUE         2 (to L15)
                    JUMP_BACKWARD           90 (to L10)
    
     426   L15:     LOAD_FAST               25 (busy_end)
                    LOAD_ATTR               27 (astimezone + NULL|self)
                    LOAD_FAST                8 (tz)
                    CALL                     1
                    STORE_FAST              23 (cursor)
                    JUMP_BACKWARD          109 (to L10)
    
     418   L16:     END_FOR
                    POP_TOP
    
     428            LOAD_FAST               23 (cursor)
                    LOAD_FAST               22 (slot_duration)
                    BINARY_OP                0 (+)
                    LOAD_FAST               13 (day_end)
                    COMPARE_OP              58 (bool(<=))
                    POP_JUMP_IF_FALSE       67 (to L19)
    
     429   L17:     LOAD_FAST               21 (slots)
                    LOAD_ATTR               21 (append + NULL|self)
    
     430            LOAD_FAST               23 (cursor)
                    LOAD_ATTR               15 (isoformat + NULL|self)
                    CALL                     0
    
     431            LOAD_FAST               23 (cursor)
                    LOAD_FAST               22 (slot_duration)
                    BINARY_OP                0 (+)
                    LOAD_ATTR               15 (isoformat + NULL|self)
                    CALL                     0
    
     429            LOAD_CONST              13 (('start', 'end'))
                    BUILD_CONST_KEY_MAP      2
                    CALL                     1
                    POP_TOP
    
     433            LOAD_FAST               23 (cursor)
                    LOAD_FAST               22 (slot_duration)
                    BINARY_OP               13 (+=)
                    STORE_FAST              23 (cursor)
    
     428            LOAD_FAST               23 (cursor)
                    LOAD_FAST               22 (slot_duration)
                    BINARY_OP                0 (+)
                    LOAD_FAST               13 (day_end)
                    COMPARE_OP              58 (bool(<=))
                    POP_JUMP_IF_FALSE        2 (to L19)
           L18:     JUMP_BACKWARD           67 (to L17)
    
     435   L19:     LOAD_FAST               21 (slots)
                    RETURN_VALUE
    
     405   L20:     CLEANUP_THROW
           L21:     EXTENDED_ARG             1
                    JUMP_BACKWARD_NO_INTERRUPT 305 (to L7)
    
      --   L22:     CALL_INTRINSIC_1         3 (INTRINSIC_STOPITERATION_ERROR)
                    RERAISE                  1
    ExceptionTable:
      L1 to L5 -> L22 [0] lasti
      L5 to L6 -> L20 [2]
      L6 to L12 -> L22 [0] lasti
      L13 to L14 -> L22 [0] lasti
      L15 to L18 -> L22 [0] lasti
      L19 to L21 -> L22 [0] lasti
    
    Disassembly of <code object <lambda> at 0x0000024C0EF0F750, file "D:\fluence\Github\mattbot\backend\app\services\calendar_service.py", line 412>:
    412           RESUME                   0
                  LOAD_FAST                0 (x)
                  LOAD_CONST               1 (0)
                  BINARY_SUBSCR
                  RETURN_VALUE
    
# --- Nested code object: disconnect_calendar ---
    # DOCSTRING: """Revoke Google tokens and remove from DB."""
    # co_names: ('sqlalchemy.ext.asyncio', 'AsyncSession', 'app.models.google_calendar_token', 'GoogleCalendarToken', 'get', 'decrypt_field', 'access_token_ciphertext', 'access_token_nonce', 'key_version', 'decode', 'httpx', 'AsyncClient', '_TIMEOUT', 'post', '_GOOGLE_REVOKE_URL', 'Exception', 'logger', 'warning', 'str', 'delete', 'flush')
    # co_varnames: ('db', 'user_id', 'AsyncSession', 'GoogleCalendarToken', 'session', 'row', 'access_token', 'client')
     443            RETURN_GENERATOR
                    POP_TOP
            L1:     RESUME                   0
    
     445            LOAD_CONST               1 (0)
                    LOAD_CONST               2 (('AsyncSession',))
                    IMPORT_NAME              0 (sqlalchemy.ext.asyncio)
                    IMPORT_FROM              1 (AsyncSession)
                    STORE_FAST               2 (AsyncSession)
                    POP_TOP
    
     447            LOAD_CONST               1 (0)
                    LOAD_CONST               3 (('GoogleCalendarToken',))
                    IMPORT_NAME              2 (app.models.google_calendar_token)
                    IMPORT_FROM              3 (GoogleCalendarToken)
                    STORE_FAST               3 (GoogleCalendarToken)
                    POP_TOP
    
     449            LOAD_FAST                0 (db)
                    STORE_FAST               4 (session)
    
     450            LOAD_FAST                4 (session)
                    LOAD_ATTR                9 (get + NULL|self)
                    LOAD_FAST_LOAD_FAST     49 (GoogleCalendarToken, user_id)
                    CALL                     2
                    GET_AWAITABLE            0
                    LOAD_CONST               4 (None)
            L2:     SEND                     3 (to L5)
            L3:     YIELD_VALUE              1
            L4:     RESUME                   3
                    JUMP_BACKWARD_NO_INTERRUPT 5 (to L2)
            L5:     END_SEND
                    STORE_FAST               5 (row)
    
     451            LOAD_FAST                5 (row)
                    POP_JUMP_IF_NOT_NONE     1 (to L6)
    
     452            RETURN_CONST             5 (False)
    
     454    L6:     NOP
    
     455    L7:     LOAD_GLOBAL             11 (decrypt_field + NULL)
    
     456            LOAD_FAST                5 (row)
                    LOAD_ATTR               12 (access_token_ciphertext)
                    LOAD_FAST                5 (row)
                    LOAD_ATTR               14 (access_token_nonce)
                    LOAD_FAST                5 (row)
                    LOAD_ATTR               16 (key_version)
    
     455            CALL                     3
    
     457            LOAD_ATTR               19 (decode + NULL|self)
                    CALL                     0
    
     455            STORE_FAST               6 (access_token)
    
     458            LOAD_GLOBAL             20 (httpx)
                    LOAD_ATTR               22 (AsyncClient)
                    PUSH_NULL
                    LOAD_GLOBAL             24 (_TIMEOUT)
                    LOAD_CONST               6 (('timeout',))
                    CALL_KW                  1
                    BEFORE_ASYNC_WITH
                    GET_AWAITABLE            1
                    LOAD_CONST               4 (None)
            L8:     SEND                     3 (to L11)
            L9:     YIELD_VALUE              1
           L10:     RESUME                   3
                    JUMP_BACKWARD_NO_INTERRUPT 5 (to L8)
           L11:     END_SEND
           L12:     STORE_FAST               7 (client)
    
     459            LOAD_FAST                7 (client)
                    LOAD_ATTR               27 (post + NULL|self)
                    LOAD_GLOBAL             28 (_GOOGLE_REVOKE_URL)
                    LOAD_CONST               7 ('token')
                    LOAD_FAST                6 (access_token)
                    BUILD_MAP                1
                    LOAD_CONST               8 (('params',))
                    CALL_KW                  2
                    GET_AWAITABLE            0
                    LOAD_CONST               4 (None)
           L13:     SEND                     3 (to L16)
           L14:     YIELD_VALUE              1
           L15:     RESUME                   3
                    JUMP_BACKWARD_NO_INTERRUPT 5 (to L13)
           L16:     END_SEND
                    POP_TOP
    
     458   L17:     LOAD_CONST               4 (None)
                    LOAD_CONST               4 (None)
                    LOAD_CONST               4 (None)
                    CALL                     2
                    GET_AWAITABLE            2
                    LOAD_CONST               4 (None)
           L18:     SEND                     3 (to L21)
           L19:     YIELD_VALUE              1
           L20:     RESUME                   3
                    JUMP_BACKWARD_NO_INTERRUPT 5 (to L18)
           L21:     END_SEND
                    POP_TOP
    
     463   L22:     LOAD_FAST                4 (session)
                    LOAD_ATTR               39 (delete + NULL|self)
                    LOAD_FAST                5 (row)
                    CALL                     1
                    GET_AWAITABLE            0
                    LOAD_CONST               4 (None)
           L23:     SEND                     3 (to L26)
           L24:     YIELD_VALUE              1
           L25:     RESUME                   3
                    JUMP_BACKWARD_NO_INTERRUPT 5 (to L23)
           L26:     END_SEND
                    POP_TOP
    
     464            LOAD_FAST                4 (session)
                    LOAD_ATTR               41 (flush + NULL|self)
                    CALL                     0
                    GET_AWAITABLE            0
                    LOAD_CONST               4 (None)
           L27:     SEND                     3 (to L30)
           L28:     YIELD_VALUE              1
           L29:     RESUME                   3
                    JUMP_BACKWARD_NO_INTERRUPT 5 (to L27)
           L30:     END_SEND
                    POP_TOP
    
     465            RETURN_CONST            11 (True)
    
     450   L31:     CLEANUP_THROW
           L32:     JUMP_BACKWARD_NO_INTERRUPT 195 (to L5)
    
     458   L33:     CLEANUP_THROW
           L34:     JUMP_BACKWARD_NO_INTERRUPT 102 (to L11)
    
     459   L35:     CLEANUP_THROW
           L36:     JUMP_BACKWARD_NO_INTERRUPT 74 (to L16)
    
     458   L37:     CLEANUP_THROW
           L38:     JUMP_BACKWARD_NO_INTERRUPT 60 (to L21)
           L39:     PUSH_EXC_INFO
                    WITH_EXCEPT_START
                    GET_AWAITABLE            2
                    LOAD_CONST               4 (None)
           L40:     SEND                     4 (to L44)
           L41:     YIELD_VALUE              1
           L42:     RESUME                   3
                    JUMP_BACKWARD_NO_INTERRUPT 5 (to L40)
           L43:     CLEANUP_THROW
           L44:     END_SEND
                    TO_BOOL
                    POP_JUMP_IF_TRUE         1 (to L45)
                    RERAISE                  2
           L45:     POP_TOP
           L46:     POP_EXCEPT
                    POP_TOP
                    POP_TOP
           L47:     JUMP_BACKWARD_NO_INTERRUPT 81 (to L22)
    
      --   L48:     COPY                     3
                    POP_EXCEPT
                    RERAISE                  1
           L49:     PUSH_EXC_INFO
    
     460            LOAD_GLOBAL             30 (Exception)
                    CHECK_EXC_MATCH
                    POP_JUMP_IF_FALSE       37 (to L51)
                    POP_TOP
    
     461            LOAD_GLOBAL             32 (logger)
                    LOAD_ATTR               35 (warning + NULL|self)
                    LOAD_CONST               9 ('Failed to revoke Google token for user %s')
                    LOAD_GLOBAL             37 (str + NULL)
                    LOAD_FAST                1 (user_id)
                    CALL                     1
                    LOAD_CONST               4 (None)
                    LOAD_CONST              10 (8)
                    BINARY_SLICE
                    CALL                     2
                    POP_TOP
           L50:     POP_EXCEPT
                    JUMP_BACKWARD_NO_INTERRUPT 130 (to L22)
    
     460   L51:     RERAISE                  0
    
      --   L52:     COPY                     3
                    POP_EXCEPT
                    RERAISE                  1
    
     463   L53:     CLEANUP_THROW
           L54:     JUMP_BACKWARD_NO_INTERRUPT 113 (to L26)
    
     464   L55:     CLEANUP_THROW
           L56:     JUMP_BACKWARD_NO_INTERRUPT 91 (to L30)
    
      --   L57:     CALL_INTRINSIC_1         3 (INTRINSIC_STOPITERATION_ERROR)
                    RERAISE                  1
    ExceptionTable:
      L1 to L3 -> L57 [0] lasti
      L3 to L4 -> L31 [2]
      L4 to L6 -> L57 [0] lasti
      L7 to L9 -> L49 [0]
      L9 to L10 -> L33 [3]
      L10 to L12 -> L49 [0]
      L12 to L14 -> L39 [1] lasti
      L14 to L15 -> L35 [3]
      L15 to L17 -> L39 [1] lasti
      L17 to L19 -> L49 [0]
      L19 to L20 -> L37 [2]
      L20 to L22 -> L49 [0]
      L22 to L24 -> L57 [0] lasti
      L24 to L25 -> L53 [2]
      L25 to L28 -> L57 [0] lasti
      L28 to L29 -> L55 [2]
      L29 to L32 -> L57 [0] lasti
      L33 to L34 -> L49 [0]
      L35 to L36 -> L39 [1] lasti
      L37 to L38 -> L49 [0]
      L39 to L41 -> L48 [3] lasti
      L41 to L42 -> L43 [6]
      L42 to L46 -> L48 [3] lasti
      L46 to L47 -> L49 [0]
      L47 to L48 -> L57 [0] lasti
      L48 to L49 -> L49 [0]
      L49 to L50 -> L52 [1] lasti
      L50 to L51 -> L57 [0] lasti
      L51 to L52 -> L52 [1] lasti
      L52 to L54 -> L57 [0] lasti
      L55 to L56 -> L57 [0] lasti
    
# co_names: ('__doc__', '__future__', 'annotations', 'logging', 'uuid', 'datetime', 'UTC', 'timedelta', 'time', 'dt_time', 'typing', 'Any', 'urllib.parse', 'urlencode', 'httpx', 'app.config', 'settings', 'app_settings', 'app.core.encryption', 'decrypt_field', 'encrypt_field', 'getLogger', '__name__', 'logger', '_GOOGLE_AUTH_URL', '_GOOGLE_TOKEN_URL', '_GOOGLE_REVOKE_URL', '_GOOGLE_USERINFO_URL', '_GOOGLE_CALENDAR_API', '_TIMEOUT', 'generate_auth_url', 'exchange_code_for_tokens', '_refresh_access_token', 'fetch_google_email', 'store_tokens', 'get_valid_access_token', 'get_calendar_status', '_parse_caller_from_description', 'list_events', 'create_event', 'get_free_busy', 'find_available_slots', 'disconnect_calendar')
# co_varnames: ()
  0           RESUME                   0

  1           LOAD_CONST               0 ('Google Calendar integration: OAuth token management and Calendar API calls.')
              STORE_NAME               0 (__doc__)

  3           LOAD_CONST               1 (0)
              LOAD_CONST               2 (('annotations',))
              IMPORT_NAME              1 (__future__)
              IMPORT_FROM              2 (annotations)
              STORE_NAME               2 (annotations)
              POP_TOP

  5           LOAD_CONST               1 (0)
              LOAD_CONST               3 (None)
              IMPORT_NAME              3 (logging)
              STORE_NAME               3 (logging)

  6           LOAD_CONST               1 (0)
              LOAD_CONST               3 (None)
              IMPORT_NAME              4 (uuid)
              STORE_NAME               4 (uuid)

  7           LOAD_CONST               1 (0)
              LOAD_CONST               4 (('UTC', 'datetime', 'timedelta'))
              IMPORT_NAME              5 (datetime)
              IMPORT_FROM              6 (UTC)
              STORE_NAME               6 (UTC)
              IMPORT_FROM              5 (datetime)
              STORE_NAME               5 (datetime)
              IMPORT_FROM              7 (timedelta)
              STORE_NAME               7 (timedelta)
              POP_TOP

  8           LOAD_CONST               1 (0)
              LOAD_CONST               5 (('time',))
              IMPORT_NAME              5 (datetime)
              IMPORT_FROM              8 (time)
              STORE_NAME               9 (dt_time)
              POP_TOP

  9           LOAD_CONST               1 (0)
              LOAD_CONST               6 (('Any',))
              IMPORT_NAME             10 (typing)
              IMPORT_FROM             11 (Any)
              STORE_NAME              11 (Any)
              POP_TOP

 10           LOAD_CONST               1 (0)
              LOAD_CONST               7 (('urlencode',))
              IMPORT_NAME             12 (urllib.parse)
              IMPORT_FROM             13 (urlencode)
              STORE_NAME              13 (urlencode)
              POP_TOP

 12           LOAD_CONST               1 (0)
              LOAD_CONST               3 (None)
              IMPORT_NAME             14 (httpx)
              STORE_NAME              14 (httpx)

 14           LOAD_CONST               1 (0)
              LOAD_CONST               8 (('settings',))
              IMPORT_NAME             15 (app.config)
              IMPORT_FROM             16 (settings)
              STORE_NAME              17 (app_settings)
              POP_TOP

 15           LOAD_CONST               1 (0)
              LOAD_CONST               9 (('decrypt_field', 'encrypt_field'))
              IMPORT_NAME             18 (app.core.encryption)
              IMPORT_FROM             19 (decrypt_field)
              STORE_NAME              19 (decrypt_field)
              IMPORT_FROM             20 (encrypt_field)
              STORE_NAME              20 (encrypt_field)
              POP_TOP

 17           LOAD_NAME                3 (logging)
              LOAD_ATTR               42 (getLogger)
              PUSH_NULL
              LOAD_NAME               22 (__name__)
              CALL                     1
              STORE_NAME              23 (logger)

 19           LOAD_CONST              10 ('https://accounts.google.com/o/oauth2/v2/auth')
              STORE_NAME              24 (_GOOGLE_AUTH_URL)

 20           LOAD_CONST              11 ('https://oauth2.googleapis.com/token')
              STORE_NAME              25 (_GOOGLE_TOKEN_URL)

 21           LOAD_CONST              12 ('https://oauth2.googleapis.com/revoke')
              STORE_NAME              26 (_GOOGLE_REVOKE_URL)

 22           LOAD_CONST              13 ('https://www.googleapis.com/oauth2/v2/userinfo')
              STORE_NAME              27 (_GOOGLE_USERINFO_URL)

 23           LOAD_CONST              14 ('https://www.googleapis.com/calendar/v3')
              STORE_NAME              28 (_GOOGLE_CALENDAR_API)

 24           LOAD_CONST              15 (15.0)
              STORE_NAME              29 (_TIMEOUT)

 32           LOAD_CONST              29 (('state', 'str', 'return', 'str'))
              LOAD_CONST              16 (<code object generate_auth_url at 0x0000024C0EEFB1B0, file "D:\fluence\Github\mattbot\backend\app\services\calendar_service.py", line 32>)
              MAKE_FUNCTION
              SET_FUNCTION_ATTRIBUTE   4 (annotations)
              STORE_NAME              30 (generate_auth_url)

 46           LOAD_CONST              30 (('code', 'str', 'return', 'dict[str, Any]'))
              LOAD_CONST              17 (<code object exchange_code_for_tokens at 0x0000024C0FBEEC70, file "D:\fluence\Github\mattbot\backend\app\services\calendar_service.py", line 46>)
              MAKE_FUNCTION
              SET_FUNCTION_ATTRIBUTE   4 (annotations)
              STORE_NAME              31 (exchange_code_for_tokens)

 63           LOAD_CONST              31 (('refresh_token', 'str', 'return', 'dict[str, Any]'))
              LOAD_CONST              18 (<code object _refresh_access_token at 0x0000024C0FC75320, file "D:\fluence\Github\mattbot\backend\app\services\calendar_service.py", line 63>)
              MAKE_FUNCTION
              SET_FUNCTION_ATTRIBUTE   4 (annotations)
              STORE_NAME              32 (_refresh_access_token)

 79           LOAD_CONST              32 (('access_token', 'str', 'return', 'str'))
              LOAD_CONST              19 (<code object fetch_google_email at 0x0000024C0FBEC150, file "D:\fluence\Github\mattbot\backend\app\services\calendar_service.py", line 79>)
              MAKE_FUNCTION
              SET_FUNCTION_ATTRIBUTE   4 (annotations)
              STORE_NAME              33 (fetch_google_email)

 96           NOP

 97           NOP

 96           NOP

 98           NOP

 96           NOP

 99           NOP

 96           NOP

100           NOP

 96           NOP

101           NOP

 96           LOAD_CONST              33 (('db', 'object', 'user_id', 'uuid.UUID', 'tokens', 'dict', 'google_email', 'str', 'return', 'None'))
              LOAD_CONST              20 (<code object store_tokens at 0x0000024C0FE612C0, file "D:\fluence\Github\mattbot\backend\app\services\calendar_service.py", line 96>)
              MAKE_FUNCTION
              SET_FUNCTION_ATTRIBUTE   4 (annotations)
              STORE_NAME              34 (store_tokens)

151           LOAD_CONST              34 (('db', 'object', 'user_id', 'uuid.UUID', 'return', 'str | None'))
              LOAD_CONST              21 (<code object get_valid_access_token at 0x0000024C0FC72D50, file "D:\fluence\Github\mattbot\backend\app\services\calendar_service.py", line 151>)
              MAKE_FUNCTION
              SET_FUNCTION_ATTRIBUTE   4 (annotations)
              STORE_NAME              35 (get_valid_access_token)

195           LOAD_CONST              35 (('db', 'object', 'user_id', 'uuid.UUID', 'return', 'dict'))
              LOAD_CONST              22 (<code object get_calendar_status at 0x0000024C114358A0, file "D:\fluence\Github\mattbot\backend\app\services\calendar_service.py", line 195>)
              MAKE_FUNCTION
              SET_FUNCTION_ATTRIBUTE   4 (annotations)
              STORE_NAME              36 (get_calendar_status)

217           LOAD_CONST              36 (('description', 'str', 'field', 'str', 'return', 'str | None'))
              LOAD_CONST              23 (<code object _parse_caller_from_description at 0x0000024C0EBFFC50, file "D:\fluence\Github\mattbot\backend\app\services\calendar_service.py", line 217>)
              MAKE_FUNCTION
              SET_FUNCTION_ATTRIBUTE   4 (annotations)
              STORE_NAME              37 (_parse_caller_from_description)

232           NOP

227           LOAD_CONST              37 (('UTC',))

228           NOP

227           NOP

229           NOP

227           NOP

230           NOP

227           NOP

231           NOP

227           NOP

232           NOP

227           NOP

233           NOP

227           LOAD_CONST              38 (('db', 'object', 'user_id', 'uuid.UUID', 'time_min', 'str', 'time_max', 'str', 'timezone', 'str', 'return', 'list[dict]'))
              LOAD_CONST              24 (<code object list_events at 0x0000024C0FCFF890, file "D:\fluence\Github\mattbot\backend\app\services\calendar_service.py", line 227>)
              MAKE_FUNCTION
              SET_FUNCTION_ATTRIBUTE   4 (annotations)
              SET_FUNCTION_ATTRIBUTE   1 (defaults)
              STORE_NAME              38 (list_events)

298           NOP

299           NOP

300           NOP

301           NOP

292           LOAD_CONST              39 (('', None, 'UTC', None))

293           NOP

292           NOP

294           NOP

292           NOP

295           NOP

292           NOP

296           NOP

292           NOP

297           NOP

292           NOP

298           NOP

292           NOP

299           NOP

292           NOP

300           NOP

292           NOP

301           NOP

292           NOP

302           NOP

292           LOAD_CONST              40 (('db', 'object', 'user_id', 'uuid.UUID', 'summary', 'str', 'start_datetime', 'str', 'end_datetime', 'str', 'description', 'str', 'attendee_email', 'str | None', 'timezone', 'str', 'call_id', 'str | None', 'return', 'dict | None'))
              LOAD_CONST              25 (<code object create_event at 0x0000024C0FB6B350, file "D:\fluence\Github\mattbot\backend\app\services\calendar_service.py", line 292>)
              MAKE_FUNCTION
              SET_FUNCTION_ATTRIBUTE   4 (annotations)
              SET_FUNCTION_ATTRIBUTE   1 (defaults)
              STORE_NAME              39 (create_event)

347           NOP

348           NOP

347           NOP

349           NOP

347           NOP

350           NOP

347           NOP

351           NOP

347           NOP

352           NOP

347           LOAD_CONST              41 (('db', 'object', 'user_id', 'uuid.UUID', 'time_min', 'str', 'time_max', 'str', 'return', 'list[dict]'))
              LOAD_CONST              26 (<code object get_free_busy at 0x0000024C0FED9050, file "D:\fluence\Github\mattbot\backend\app\services\calendar_service.py", line 347>)
              MAKE_FUNCTION
              SET_FUNCTION_ATTRIBUTE   4 (annotations)
              STORE_NAME              40 (get_free_busy)

383           NOP

384           NOP

385           NOP

386           NOP

379           LOAD_CONST              42 ((30, None, None, 'UTC'))

380           NOP

379           NOP

381           NOP

379           NOP

382           NOP

379           NOP

383           NOP

379           NOP

384           NOP

379           NOP

385           NOP

379           NOP

386           NOP

379           NOP

387           NOP

379           LOAD_CONST              43 (('db', 'object', 'user_id', 'uuid.UUID', 'date_str', 'str', 'duration_minutes', 'int', 'business_start', 'dt_time | None', 'business_end', 'dt_time | None', 'timezone', 'str', 'return', 'list[dict]'))
              LOAD_CONST              27 (<code object find_available_slots at 0x0000024C0FB59FD0, file "D:\fluence\Github\mattbot\backend\app\services\calendar_service.py", line 379>)
              MAKE_FUNCTION
              SET_FUNCTION_ATTRIBUTE   4 (annotations)
              SET_FUNCTION_ATTRIBUTE   1 (defaults)
              STORE_NAME              41 (find_available_slots)

443           LOAD_CONST              44 (('db', 'object', 'user_id', 'uuid.UUID', 'return', 'bool'))
              LOAD_CONST              28 (<code object disconnect_calendar at 0x0000024C0FBE4020, file "D:\fluence\Github\mattbot\backend\app\services\calendar_service.py", line 443>)
              MAKE_FUNCTION
              SET_FUNCTION_ATTRIBUTE   4 (annotations)
              STORE_NAME              42 (disconnect_calendar)
              RETURN_CONST             3 (None)

Disassembly of <code object generate_auth_url at 0x0000024C0EEFB1B0, file "D:\fluence\Github\mattbot\backend\app\services\calendar_service.py", line 32>:
 32           RESUME                   0

 35           LOAD_GLOBAL              0 (app_settings)
              LOAD_ATTR                2 (GOOGLE_CALENDAR_CLIENT_ID)

 36           LOAD_GLOBAL              0 (app_settings)
              LOAD_ATTR                4 (GOOGLE_CALENDAR_REDIRECT_URI)

 37           LOAD_CONST               1 ('code')

 38           LOAD_GLOBAL              0 (app_settings)
              LOAD_ATTR                6 (GOOGLE_CALENDAR_SCOPES)

 39           LOAD_CONST               2 ('offline')

 40           LOAD_CONST               3 ('consent')

 41           LOAD_FAST                0 (state)

 34           LOAD_CONST               4 (('client_id', 'redirect_uri', 'response_type', 'scope', 'access_type', 'prompt', 'state'))
              BUILD_CONST_KEY_MAP      7
              STORE_FAST               1 (params)

 43           LOAD_GLOBAL              8 (_GOOGLE_AUTH_URL)
              FORMAT_SIMPLE
              LOAD_CONST               5 ('?')
              LOAD_GLOBAL             11 (urlencode + NULL)
              LOAD_FAST                1 (params)
              CALL                     1
              FORMAT_SIMPLE
              BUILD_STRING             3
              RETURN_VALUE

Disassembly of <code object exchange_code_for_tokens at 0x0000024C0FBEEC70, file "D:\fluence\Github\mattbot\backend\app\services\calendar_service.py", line 46>:
  46            RETURN_GENERATOR
                POP_TOP
        L1:     RESUME                   0

  49            LOAD_FAST                0 (code)

  50            LOAD_GLOBAL              0 (app_settings)
                LOAD_ATTR                2 (GOOGLE_CALENDAR_CLIENT_ID)

  51            LOAD_GLOBAL              0 (app_settings)
                LOAD_ATTR                4 (GOOGLE_CALENDAR_CLIENT_SECRET)

  52            LOAD_GLOBAL              0 (app_settings)
                LOAD_ATTR                6 (GOOGLE_CALENDAR_REDIRECT_URI)

  53            LOAD_CONST               1 ('authorization_code')

  48            LOAD_CONST               2 (('code', 'client_id', 'client_secret', 'redirect_uri', 'grant_type'))
                BUILD_CONST_KEY_MAP      5
                STORE_FAST               1 (payload)

  55            LOAD_GLOBAL              8 (httpx)
                LOAD_ATTR               10 (AsyncClient)
                PUSH_NULL
                LOAD_GLOBAL             12 (_TIMEOUT)
                LOAD_CONST               3 (('timeout',))
                CALL_KW                  1
                BEFORE_ASYNC_WITH
                GET_AWAITABLE            1
                LOAD_CONST               4 (None)
        L2:     SEND                     3 (to L5)
        L3:     YIELD_VALUE              1
        L4:     RESUME                   3
                JUMP_BACKWARD_NO_INTERRUPT 5 (to L2)
        L5:     END_SEND
        L6:     STORE_FAST               2 (client)

  56            LOAD_FAST                2 (client)
                LOAD_ATTR               15 (post + NULL|self)
                LOAD_GLOBAL             16 (_GOOGLE_TOKEN_URL)
                LOAD_FAST                1 (payload)
                LOAD_CONST               5 (('data',))
                CALL_KW                  2
                GET_AWAITABLE            0
                LOAD_CONST               4 (None)
        L7:     SEND                     3 (to L10)
        L8:     YIELD_VALUE              1
        L9:     RESUME                   3
                JUMP_BACKWARD_NO_INTERRUPT 5 (to L7)
       L10:     END_SEND
                STORE_FAST               3 (resp)

  57            LOAD_FAST                3 (resp)
                LOAD_ATTR               18 (status_code)
                LOAD_CONST               6 (200)
                COMPARE_OP             119 (bool(!=))
                POP_JUMP_IF_FALSE       62 (to L11)

  58            LOAD_GLOBAL             20 (logger)
                LOAD_ATTR               23 (error + NULL|self)
                LOAD_CONST               7 ('Google token exchange failed: %d %s')
                LOAD_FAST                3 (resp)
                LOAD_ATTR               18 (status_code)
                LOAD_FAST                3 (resp)
                LOAD_ATTR               24 (text)
                LOAD_CONST               4 (None)
                LOAD_CONST               8 (300)
                BINARY_SLICE
                CALL                     3
                POP_TOP

  59            LOAD_FAST                3 (resp)
                LOAD_ATTR               27 (raise_for_status + NULL|self)
                CALL                     0
                POP_TOP

  60   L11:     LOAD_FAST                3 (resp)
                LOAD_ATTR               29 (json + NULL|self)
                CALL                     0

  55   L12:     SWAP                     2
                LOAD_CONST               4 (None)
                LOAD_CONST               4 (None)
                LOAD_CONST               4 (None)
                CALL                     2
                GET_AWAITABLE            2
                LOAD_CONST               4 (None)
       L13:     SEND                     3 (to L16)
       L14:     YIELD_VALUE              1
       L15:     RESUME                   3
                JUMP_BACKWARD_NO_INTERRUPT 5 (to L13)
       L16:     END_SEND
                POP_TOP
                RETURN_VALUE
       L17:     CLEANUP_THROW
       L18:     JUMP_BACKWARD_NO_INTERRUPT 143 (to L5)

  56   L19:     CLEANUP_THROW
       L20:     JUMP_BACKWARD_NO_INTERRUPT 117 (to L10)

  55   L21:     CLEANUP_THROW
       L22:     JUMP_BACKWARD_NO_INTERRUPT 9 (to L16)
       L23:     PUSH_EXC_INFO
                WITH_EXCEPT_START
                GET_AWAITABLE            2
                LOAD_CONST               4 (None)
       L24:     SEND                     4 (to L28)
       L25:     YIELD_VALUE              1
       L26:     RESUME                   3
                JUMP_BACKWARD_NO_INTERRUPT 5 (to L24)
       L27:     CLEANUP_THROW
       L28:     END_SEND
                TO_BOOL
                POP_JUMP_IF_TRUE         1 (to L29)
                RERAISE                  2
       L29:     POP_TOP
       L30:     POP_EXCEPT
                POP_TOP
                POP_TOP
                RETURN_CONST             4 (None)

  --   L31:     COPY                     3
                POP_EXCEPT
                RERAISE                  1
       L32:     CALL_INTRINSIC_1         3 (INTRINSIC_STOPITERATION_ERROR)
                RERAISE                  1
ExceptionTable:
  L1 to L3 -> L32 [0] lasti
  L3 to L4 -> L17 [3]
  L4 to L6 -> L32 [0] lasti
  L6 to L8 -> L23 [1] lasti
  L8 to L9 -> L19 [3]
  L9 to L12 -> L23 [1] lasti
  L12 to L14 -> L32 [0] lasti
  L14 to L15 -> L21 [3]
  L15 to L18 -> L32 [0] lasti
  L19 to L20 -> L23 [1] lasti
  L21 to L22 -> L32 [0] lasti
  L23 to L25 -> L31 [3] lasti
  L25 to L26 -> L27 [6]
  L26 to L30 -> L31 [3] lasti
  L30 to L32 -> L32 [0] lasti

Disassembly of <code object _refresh_access_token at 0x0000024C0FC75320, file "D:\fluence\Github\mattbot\backend\app\services\calendar_service.py", line 63>:
  63            RETURN_GENERATOR
                POP_TOP
        L1:     RESUME                   0

  66            LOAD_GLOBAL              0 (app_settings)
                LOAD_ATTR                2 (GOOGLE_CALENDAR_CLIENT_ID)

  67            LOAD_GLOBAL              0 (app_settings)
                LOAD_ATTR                4 (GOOGLE_CALENDAR_CLIENT_SECRET)

  68            LOAD_FAST                0 (refresh_token)

  69            LOAD_CONST               1 ('refresh_token')

  65            LOAD_CONST               2 (('client_id', 'client_secret', 'refresh_token', 'grant_type'))
                BUILD_CONST_KEY_MAP      4
                STORE_FAST               1 (payload)

  71            LOAD_GLOBAL              6 (httpx)
                LOAD_ATTR                8 (AsyncClient)
                PUSH_NULL
                LOAD_GLOBAL             10 (_TIMEOUT)
                LOAD_CONST               3 (('timeout',))
                CALL_KW                  1
                BEFORE_ASYNC_WITH
                GET_AWAITABLE            1
                LOAD_CONST               4 (None)
        L2:     SEND                     3 (to L5)
        L3:     YIELD_VALUE              1
        L4:     RESUME                   3
                JUMP_BACKWARD_NO_INTERRUPT 5 (to L2)
        L5:     END_SEND
        L6:     STORE_FAST               2 (client)

  72            LOAD_FAST                2 (client)
                LOAD_ATTR               13 (post + NULL|self)
                LOAD_GLOBAL             14 (_GOOGLE_TOKEN_URL)
                LOAD_FAST                1 (payload)
                LOAD_CONST               5 (('data',))
                CALL_KW                  2
                GET_AWAITABLE            0
                LOAD_CONST               4 (None)
        L7:     SEND                     3 (to L10)
        L8:     YIELD_VALUE              1
        L9:     RESUME                   3
                JUMP_BACKWARD_NO_INTERRUPT 5 (to L7)
       L10:     END_SEND
                STORE_FAST               3 (resp)

  73            LOAD_FAST                3 (resp)
                LOAD_ATTR               16 (status_code)
                LOAD_CONST               6 (200)
                COMPARE_OP             119 (bool(!=))
                POP_JUMP_IF_FALSE       62 (to L11)

  74            LOAD_GLOBAL             18 (logger)
                LOAD_ATTR               21 (error + NULL|self)
                LOAD_CONST               7 ('Google token refresh failed: %d %s')
                LOAD_FAST                3 (resp)
                LOAD_ATTR               16 (status_code)
                LOAD_FAST                3 (resp)
                LOAD_ATTR               22 (text)
                LOAD_CONST               4 (None)
                LOAD_CONST               8 (300)
                BINARY_SLICE
                CALL                     3
                POP_TOP

  75            LOAD_FAST                3 (resp)
                LOAD_ATTR               25 (raise_for_status + NULL|self)
                CALL                     0
                POP_TOP

  76   L11:     LOAD_FAST                3 (resp)
                LOAD_ATTR               27 (json + NULL|self)
                CALL                     0

  71   L12:     SWAP                     2
                LOAD_CONST               4 (None)
                LOAD_CONST               4 (None)
                LOAD_CONST               4 (None)
                CALL                     2
                GET_AWAITABLE            2
                LOAD_CONST               4 (None)
       L13:     SEND                     3 (to L16)
       L14:     YIELD_VALUE              1
       L15:     RESUME                   3
                JUMP_BACKWARD_NO_INTERRUPT 5 (to L13)
       L16:     END_SEND
                POP_TOP
                RETURN_VALUE
       L17:     CLEANUP_THROW
       L18:     JUMP_BACKWARD_NO_INTERRUPT 143 (to L5)

  72   L19:     CLEANUP_THROW
       L20:     JUMP_BACKWARD_NO_INTERRUPT 117 (to L10)

  71   L21:     CLEANUP_THROW
       L22:     JUMP_BACKWARD_NO_INTERRUPT 9 (to L16)
       L23:     PUSH_EXC_INFO
                WITH_EXCEPT_START
                GET_AWAITABLE            2
                LOAD_CONST               4 (None)
       L24:     SEND                     4 (to L28)
       L25:     YIELD_VALUE              1
       L26:     RESUME                   3
                JUMP_BACKWARD_NO_INTERRUPT 5 (to L24)
       L27:     CLEANUP_THROW
       L28:     END_SEND
                TO_BOOL
                POP_JUMP_IF_TRUE         1 (to L29)
                RERAISE                  2
       L29:     POP_TOP
       L30:     POP_EXCEPT
                POP_TOP
                POP_TOP
                RETURN_CONST             4 (None)

  --   L31:     COPY                     3
                POP_EXCEPT
                RERAISE                  1
       L32:     CALL_INTRINSIC_1         3 (INTRINSIC_STOPITERATION_ERROR)
                RERAISE                  1
ExceptionTable:
  L1 to L3 -> L32 [0] lasti
  L3 to L4 -> L17 [3]
  L4 to L6 -> L32 [0] lasti
  L6 to L8 -> L23 [1] lasti
  L8 to L9 -> L19 [3]
  L9 to L12 -> L23 [1] lasti
  L12 to L14 -> L32 [0] lasti
  L14 to L15 -> L21 [3]
  L15 to L18 -> L32 [0] lasti
  L19 to L20 -> L23 [1] lasti
  L21 to L22 -> L32 [0] lasti
  L23 to L25 -> L31 [3] lasti
  L25 to L26 -> L27 [6]
  L26 to L30 -> L31 [3] lasti
  L30 to L32 -> L32 [0] lasti

Disassembly of <code object fetch_google_email at 0x0000024C0FBEC150, file "D:\fluence\Github\mattbot\backend\app\services\calendar_service.py", line 79>:
  79            RETURN_GENERATOR
                POP_TOP
        L1:     RESUME                   0

  81            LOAD_GLOBAL              0 (httpx)
                LOAD_ATTR                2 (AsyncClient)
                PUSH_NULL
                LOAD_GLOBAL              4 (_TIMEOUT)
                LOAD_CONST               1 (('timeout',))
                CALL_KW                  1
                BEFORE_ASYNC_WITH
                GET_AWAITABLE            1
                LOAD_CONST               2 (None)
        L2:     SEND                     3 (to L5)
        L3:     YIELD_VALUE              1
        L4:     RESUME                   3
                JUMP_BACKWARD_NO_INTERRUPT 5 (to L2)
        L5:     END_SEND
        L6:     STORE_FAST               1 (client)

  82            LOAD_FAST                1 (client)
                LOAD_ATTR                7 (get + NULL|self)

  83            LOAD_GLOBAL              8 (_GOOGLE_USERINFO_URL)

  84            LOAD_CONST               3 ('Authorization')
                LOAD_CONST               4 ('Bearer ')
                LOAD_FAST                0 (access_token)
                FORMAT_SIMPLE
                BUILD_STRING             2
                BUILD_MAP                1

  82            LOAD_CONST               5 (('headers',))
                CALL_KW                  2
                GET_AWAITABLE            0
                LOAD_CONST               2 (None)
        L7:     SEND                     3 (to L10)
        L8:     YIELD_VALUE              1
        L9:     RESUME                   3
                JUMP_BACKWARD_NO_INTERRUPT 5 (to L7)
       L10:     END_SEND
                STORE_FAST               2 (resp)

  86            LOAD_FAST                2 (resp)
                LOAD_ATTR               11 (raise_for_status + NULL|self)
                CALL                     0
                POP_TOP

  87            LOAD_FAST                2 (resp)
                LOAD_ATTR               13 (json + NULL|self)
                CALL                     0
                LOAD_ATTR                7 (get + NULL|self)
                LOAD_CONST               6 ('email')
                LOAD_CONST               7 ('')
                CALL                     2
                STORE_FAST               3 (email)

  88            LOAD_FAST                3 (email)

  81   L11:     SWAP                     2
                LOAD_CONST               2 (None)
                LOAD_CONST               2 (None)
                LOAD_CONST               2 (None)
                CALL                     2
                GET_AWAITABLE            2
                LOAD_CONST               2 (None)
       L12:     SEND                     3 (to L15)
       L13:     YIELD_VALUE              1
       L14:     RESUME                   3
                JUMP_BACKWARD_NO_INTERRUPT 5 (to L12)
       L15:     END_SEND
                POP_TOP
                RETURN_VALUE
       L16:     CLEANUP_THROW
       L17:     JUMP_BACKWARD_NO_INTERRUPT 104 (to L5)

  82   L18:     CLEANUP_THROW
       L19:     JUMP_BACKWARD_NO_INTERRUPT 73 (to L10)

  81   L20:     CLEANUP_THROW
       L21:     JUMP_BACKWARD_NO_INTERRUPT 9 (to L15)
       L22:     PUSH_EXC_INFO
                WITH_EXCEPT_START
                GET_AWAITABLE            2
                LOAD_CONST               2 (None)
       L23:     SEND                     4 (to L27)
       L24:     YIELD_VALUE              1
       L25:     RESUME                   3
                JUMP_BACKWARD_NO_INTERRUPT 5 (to L23)
       L26:     CLEANUP_THROW
       L27:     END_SEND
                TO_BOOL
                POP_JUMP_IF_TRUE         1 (to L28)
                RERAISE                  2
       L28:     POP_TOP
       L29:     POP_EXCEPT
                POP_TOP
                POP_TOP
                RETURN_CONST             2 (None)

  --   L30:     COPY                     3
                POP_EXCEPT
                RERAISE                  1
       L31:     CALL_INTRINSIC_1         3 (INTRINSIC_STOPITERATION_ERROR)
                RERAISE                  1
ExceptionTable:
  L1 to L3 -> L31 [0] lasti
  L3 to L4 -> L16 [3]
  L4 to L6 -> L31 [0] lasti
  L6 to L8 -> L22 [1] lasti
  L8 to L9 -> L18 [3]
  L9 to L11 -> L22 [1] lasti
  L11 to L13 -> L31 [0] lasti
  L13 to L14 -> L20 [3]
  L14 to L17 -> L31 [0] lasti
  L18 to L19 -> L22 [1] lasti
  L20 to L21 -> L31 [0] lasti
  L22 to L24 -> L30 [3] lasti
  L24 to L25 -> L26 [6]
  L25 to L29 -> L30 [3] lasti
  L29 to L31 -> L31 [0] lasti

Disassembly of <code object store_tokens at 0x0000024C0FE612C0, file "D:\fluence\Github\mattbot\backend\app\services\calendar_service.py", line 96>:
  96            RETURN_GENERATOR
                POP_TOP
        L1:     RESUME                   0

 103            LOAD_CONST               1 (0)
                LOAD_CONST               2 (('AsyncSession',))
                IMPORT_NAME              0 (sqlalchemy.ext.asyncio)
                IMPORT_FROM              1 (AsyncSession)
                STORE_FAST               4 (AsyncSession)
                POP_TOP

 105            LOAD_CONST               1 (0)
                LOAD_CONST               3 (('GoogleCalendarToken',))
                IMPORT_NAME              2 (app.models.google_calendar_token)
                IMPORT_FROM              3 (GoogleCalendarToken)
                STORE_FAST               5 (GoogleCalendarToken)
                POP_TOP

 107            LOAD_FAST                0 (db)
                STORE_FAST               6 (session)

 109            LOAD_GLOBAL              9 (encrypt_field + NULL)
                LOAD_FAST                2 (tokens)
                LOAD_CONST               4 ('access_token')
                BINARY_SUBSCR
                LOAD_ATTR               11 (encode + NULL|self)
                CALL                     0
                CALL                     1
                UNPACK_SEQUENCE          3
                STORE_FAST_STORE_FAST  120 (access_ct, access_nonce)
                STORE_FAST               9 (kv)

 111            LOAD_CONST               5 (None)
                STORE_FAST              10 (expiry)

 112            LOAD_CONST               6 ('expires_in')
                LOAD_FAST                2 (tokens)
                CONTAINS_OP              0
                POP_JUMP_IF_FALSE       48 (to L2)

 113            LOAD_GLOBAL             12 (datetime)
                LOAD_ATTR               14 (now)
                PUSH_NULL
                LOAD_GLOBAL             16 (UTC)
                CALL                     1
                LOAD_GLOBAL             19 (timedelta + NULL)
                LOAD_GLOBAL             21 (int + NULL)
                LOAD_FAST                2 (tokens)
                LOAD_CONST               6 ('expires_in')
                BINARY_SUBSCR
                CALL                     1
                LOAD_CONST               7 (('seconds',))
                CALL_KW                  1
                BINARY_OP                0 (+)
                STORE_FAST              10 (expiry)

 115    L2:     LOAD_FAST                6 (session)
                LOAD_ATTR               23 (get + NULL|self)
                LOAD_FAST_LOAD_FAST     81 (GoogleCalendarToken, user_id)
                CALL                     2
                GET_AWAITABLE            0
                LOAD_CONST               5 (None)
        L3:     SEND                     3 (to L6)
        L4:     YIELD_VALUE              1
        L5:     RESUME                   3
                JUMP_BACKWARD_NO_INTERRUPT 5 (to L3)
        L6:     END_SEND
                STORE_FAST              11 (existing)

 117            LOAD_FAST                2 (tokens)
                LOAD_ATTR               23 (get + NULL|self)
                LOAD_CONST               8 ('refresh_token')
                CALL                     1
                STORE_FAST              12 (refresh_token_str)

 118            LOAD_FAST               12 (refresh_token_str)
                TO_BOOL
                POP_JUMP_IF_FALSE       29 (to L7)

 119            LOAD_GLOBAL              9 (encrypt_field + NULL)
                LOAD_FAST               12 (refresh_token_str)
                LOAD_ATTR               11 (encode + NULL|self)
                CALL                     0
                CALL                     1
                UNPACK_SEQUENCE          3
                STORE_FAST_STORE_FAST  222 (refresh_ct, refresh_nonce)
                STORE_FAST              15 (_)
                JUMP_FORWARD            43 (to L9)

 120    L7:     LOAD_FAST               11 (existing)
                TO_BOOL
                POP_JUMP_IF_FALSE       25 (to L8)

 121            LOAD_FAST               11 (existing)
                LOAD_ATTR               24 (refresh_token_ciphertext)
                STORE_FAST              13 (refresh_ct)

 122            LOAD_FAST               11 (existing)
                LOAD_ATTR               26 (refresh_token_nonce)
                STORE_FAST              14 (refresh_nonce)
                JUMP_FORWARD            11 (to L9)

 124    L8:     LOAD_GLOBAL             29 (ValueError + NULL)
                LOAD_CONST               9 ('No refresh token received and no existing token on file')
                CALL                     1
                RAISE_VARARGS            1

 126    L9:     LOAD_FAST               11 (existing)
                TO_BOOL
                POP_JUMP_IF_FALSE       74 (to L10)

 127            LOAD_FAST_LOAD_FAST    123 (access_ct, existing)
                STORE_ATTR              15 (access_token_ciphertext)

 128            LOAD_FAST_LOAD_FAST    139 (access_nonce, existing)
                STORE_ATTR              16 (access_token_nonce)

 129            LOAD_FAST_LOAD_FAST    219 (refresh_ct, existing)
                STORE_ATTR              12 (refresh_token_ciphertext)

 130            LOAD_FAST_LOAD_FAST    235 (refresh_nonce, existing)
                STORE_ATTR              13 (refresh_token_nonce)

 131            LOAD_FAST_LOAD_FAST    155 (kv, existing)
                STORE_ATTR              17 (key_version)

 132            LOAD_FAST_LOAD_FAST    171 (expiry, existing)
                STORE_ATTR              18 (token_expiry)

 133            LOAD_FAST_LOAD_FAST     59 (google_email, existing)
                STORE_ATTR              19 (google_email)

 134            LOAD_GLOBAL             12 (datetime)
                LOAD_ATTR               14 (now)
                PUSH_NULL
                LOAD_GLOBAL             16 (UTC)
                CALL                     1
                LOAD_FAST               11 (existing)
                STORE_ATTR              20 (updated_at)
                JUMP_FORWARD            30 (to L11)

 136   L10:     LOAD_FAST                5 (GoogleCalendarToken)
                PUSH_NULL

 137            LOAD_FAST                1 (user_id)

 138            LOAD_FAST                7 (access_ct)

 139            LOAD_FAST                8 (access_nonce)

 140            LOAD_FAST               13 (refresh_ct)

 141            LOAD_FAST               14 (refresh_nonce)

 142            LOAD_FAST                9 (kv)

 143            LOAD_FAST               10 (expiry)

 144            LOAD_FAST                3 (google_email)

 136            LOAD_CONST              10 (('owner_user_id', 'access_token_ciphertext', 'access_token_nonce', 'refresh_token_ciphertext', 'refresh_token_nonce', 'key_version', 'token_expiry', 'google_email'))
                CALL_KW                  8
                STORE_FAST              16 (entry)

 146            LOAD_FAST                6 (session)
                LOAD_ATTR               43 (add + NULL|self)
                LOAD_FAST               16 (entry)
                CALL                     1
                POP_TOP

 148   L11:     LOAD_FAST                6 (session)
                LOAD_ATTR               45 (flush + NULL|self)
                CALL                     0
                GET_AWAITABLE            0
                LOAD_CONST               5 (None)
       L12:     SEND                     3 (to L15)
       L13:     YIELD_VALUE              1
       L14:     RESUME                   3
                JUMP_BACKWARD_NO_INTERRUPT 5 (to L12)
       L15:     END_SEND
                POP_TOP
                RETURN_CONST             5 (None)

 115   L16:     CLEANUP_THROW
       L17:     JUMP_BACKWARD_NO_INTERRUPT 236 (to L6)

 148   L18:     CLEANUP_THROW
       L19:     JUMP_BACKWARD_NO_INTERRUPT 7 (to L15)

  --   L20:     CALL_INTRINSIC_1         3 (INTRINSIC_STOPITERATION_ERROR)
                RERAISE                  1
ExceptionTable:
  L1 to L4 -> L20 [0] lasti
  L4 to L5 -> L16 [2]
  L5 to L13 -> L20 [0] lasti
  L13 to L14 -> L18 [2]
  L14 to L17 -> L20 [0] lasti
  L18 to L19 -> L20 [0] lasti

Disassembly of <code object get_valid_access_token at 0x0000024C0FC72D50, file "D:\fluence\Github\mattbot\backend\app\services\calendar_service.py", line 151>:
 151            RETURN_GENERATOR
                POP_TOP
        L1:     RESUME                   0

 153            LOAD_CONST               1 (0)
                LOAD_CONST               2 (('AsyncSession',))
                IMPORT_NAME              0 (sqlalchemy.ext.asyncio)
                IMPORT_FROM              1 (AsyncSession)
                STORE_FAST               2 (AsyncSession)
                POP_TOP

 155            LOAD_CONST               1 (0)
                LOAD_CONST               3 (('GoogleCalendarToken',))
                IMPORT_NAME              2 (app.models.google_calendar_token)
                IMPORT_FROM              3 (GoogleCalendarToken)
                STORE_FAST               3 (GoogleCalendarToken)
                POP_TOP

 157            LOAD_FAST                0 (db)
                STORE_FAST               4 (session)

 158            LOAD_FAST                4 (session)
                LOAD_ATTR                9 (get + NULL|self)
                LOAD_FAST_LOAD_FAST     49 (GoogleCalendarToken, user_id)
                CALL                     2
                GET_AWAITABLE            0
                LOAD_CONST               4 (None)
        L2:     SEND                     3 (to L5)
        L3:     YIELD_VALUE              1
        L4:     RESUME                   3
                JUMP_BACKWARD_NO_INTERRUPT 5 (to L2)
        L5:     END_SEND
                STORE_FAST               5 (row)

 159            LOAD_FAST                5 (row)
                POP_JUMP_IF_NOT_NONE     1 (to L6)

 160            RETURN_CONST             4 (None)

 162    L6:     LOAD_GLOBAL             11 (decrypt_field + NULL)

 163            LOAD_FAST                5 (row)
                LOAD_ATTR               12 (access_token_ciphertext)
                LOAD_FAST                5 (row)
                LOAD_ATTR               14 (access_token_nonce)
                LOAD_FAST                5 (row)
                LOAD_ATTR               16 (key_version)

 162            CALL                     3

 164            LOAD_ATTR               19 (decode + NULL|self)
                CALL                     0

 162            STORE_FAST               6 (access_token)

 166            LOAD_FAST                5 (row)
                LOAD_ATTR               20 (token_expiry)
                TO_BOOL
                EXTENDED_ARG             1
                POP_JUMP_IF_FALSE      342 (to L20)
                LOAD_FAST                5 (row)
                LOAD_ATTR               20 (token_expiry)
                LOAD_GLOBAL             22 (datetime)
                LOAD_ATTR               24 (now)
                PUSH_NULL
                LOAD_GLOBAL             26 (UTC)
                CALL                     1
                LOAD_GLOBAL             29 (timedelta + NULL)
                LOAD_CONST               5 (2)
                LOAD_CONST               6 (('minutes',))
                CALL_KW                  1
                BINARY_OP                0 (+)
                COMPARE_OP              18 (bool(<))
                EXTENDED_ARG             1
                POP_JUMP_IF_FALSE      291 (to L20)

 167            LOAD_GLOBAL             11 (decrypt_field + NULL)

 168            LOAD_FAST                5 (row)
                LOAD_ATTR               30 (refresh_token_ciphertext)
                LOAD_FAST                5 (row)
                LOAD_ATTR               32 (refresh_token_nonce)
                LOAD_FAST                5 (row)
                LOAD_ATTR               16 (key_version)

 167            CALL                     3

 169            LOAD_ATTR               19 (decode + NULL|self)
                CALL                     0

 167            STORE_FAST               7 (refresh_token)

 170    L7:     NOP

 171    L8:     LOAD_GLOBAL             35 (_refresh_access_token + NULL)
                LOAD_FAST                7 (refresh_token)
                CALL                     1
                GET_AWAITABLE            0
                LOAD_CONST               4 (None)
        L9:     SEND                     3 (to L12)
       L10:     YIELD_VALUE              1
       L11:     RESUME                   3
                JUMP_BACKWARD_NO_INTERRUPT 5 (to L9)
       L12:     END_SEND
                STORE_FAST               8 (new_tokens)

 176   L13:     LOAD_FAST                8 (new_tokens)
                LOAD_CONST               9 ('access_token')
                BINARY_SUBSCR
                STORE_FAST               6 (access_token)

 177            LOAD_GLOBAL             47 (encrypt_field + NULL)
                LOAD_FAST                6 (access_token)
                LOAD_ATTR               49 (encode + NULL|self)
                CALL                     0
                CALL                     1
                UNPACK_SEQUENCE          3
                STORE_FAST_STORE_FAST  154 (ct, nonce)
                STORE_FAST              11 (kv)

 178            LOAD_FAST_LOAD_FAST    149 (ct, row)
                STORE_ATTR               6 (access_token_ciphertext)

 179            LOAD_FAST_LOAD_FAST    165 (nonce, row)
                STORE_ATTR               7 (access_token_nonce)

 180            LOAD_FAST_LOAD_FAST    181 (kv, row)
                STORE_ATTR               8 (key_version)

 181            LOAD_CONST              10 ('expires_in')
                LOAD_FAST                8 (new_tokens)
                CONTAINS_OP              0
                POP_JUMP_IF_FALSE       53 (to L14)

 182            LOAD_GLOBAL             22 (datetime)
                LOAD_ATTR               24 (now)
                PUSH_NULL
                LOAD_GLOBAL             26 (UTC)
                CALL                     1
                LOAD_GLOBAL             29 (timedelta + NULL)
                LOAD_GLOBAL             51 (int + NULL)
                LOAD_FAST                8 (new_tokens)
                LOAD_CONST              10 ('expires_in')
                BINARY_SUBSCR
                CALL                     1
                LOAD_CONST              11 (('seconds',))
                CALL_KW                  1
                BINARY_OP                0 (+)
                LOAD_FAST                5 (row)
                STORE_ATTR              10 (token_expiry)

 184   L14:     LOAD_CONST              12 ('refresh_token')
                LOAD_FAST                8 (new_tokens)
                CONTAINS_OP              0
                POP_JUMP_IF_FALSE       43 (to L15)

 185            LOAD_GLOBAL             47 (encrypt_field + NULL)
                LOAD_FAST                8 (new_tokens)
                LOAD_CONST              12 ('refresh_token')
                BINARY_SUBSCR
                LOAD_ATTR               49 (encode + NULL|self)
                CALL                     0
                CALL                     1
                UNPACK_SEQUENCE          3
                STORE_FAST_STORE_FAST  205 (rct, rnonce)
                STORE_FAST              14 (_)

 186            LOAD_FAST_LOAD_FAST    197 (rct, row)
                STORE_ATTR              15 (refresh_token_ciphertext)

 187            LOAD_FAST_LOAD_FAST    213 (rnonce, row)
                STORE_ATTR              16 (refresh_token_nonce)

 189   L15:     LOAD_GLOBAL             22 (datetime)
                LOAD_ATTR               24 (now)
                PUSH_NULL
                LOAD_GLOBAL             26 (UTC)
                CALL                     1
                LOAD_FAST                5 (row)
                STORE_ATTR              26 (updated_at)

 190            LOAD_FAST                4 (session)
                LOAD_ATTR               55 (flush + NULL|self)
                CALL                     0
                GET_AWAITABLE            0
                LOAD_CONST               4 (None)
       L16:     SEND                     3 (to L19)
       L17:     YIELD_VALUE              1
       L18:     RESUME                   3
                JUMP_BACKWARD_NO_INTERRUPT 5 (to L16)
       L19:     END_SEND
                POP_TOP

 192   L20:     LOAD_FAST                6 (access_token)
                RETURN_VALUE

 158   L21:     CLEANUP_THROW
       L22:     EXTENDED_ARG             1
                JUMP_BACKWARD_NO_INTERRUPT 428 (to L5)

 171   L23:     CLEANUP_THROW
       L24:     JUMP_BACKWARD_NO_INTERRUPT 223 (to L12)

  --   L25:     PUSH_EXC_INFO

 172            LOAD_GLOBAL             36 (httpx)
                LOAD_ATTR               38 (HTTPStatusError)
                CHECK_EXC_MATCH
                POP_JUMP_IF_FALSE       37 (to L27)
                POP_TOP

 173            LOAD_GLOBAL             40 (logger)
                LOAD_ATTR               43 (warning + NULL|self)
                LOAD_CONST               7 ('Failed to refresh Google token for user %s')
                LOAD_GLOBAL             45 (str + NULL)
                LOAD_FAST                1 (user_id)
                CALL                     1
                LOAD_CONST               4 (None)
                LOAD_CONST               8 (8)
                BINARY_SLICE
                CALL                     2
                POP_TOP

 174   L26:     POP_EXCEPT
                RETURN_CONST             4 (None)

 172   L27:     RERAISE                  0

  --   L28:     COPY                     3
                POP_EXCEPT
                RERAISE                  1

 190   L29:     CLEANUP_THROW
       L30:     JUMP_BACKWARD_NO_INTERRUPT 71 (to L19)

  --   L31:     CALL_INTRINSIC_1         3 (INTRINSIC_STOPITERATION_ERROR)
                RERAISE                  1
ExceptionTable:
  L1 to L3 -> L31 [0] lasti
  L3 to L4 -> L21 [2]
  L4 to L7 -> L31 [0] lasti
  L8 to L10 -> L25 [0]
  L10 to L11 -> L23 [2]
  L11 to L13 -> L25 [0]
  L13 to L17 -> L31 [0] lasti
  L17 to L18 -> L29 [2]
  L18 to L22 -> L31 [0] lasti
  L23 to L24 -> L25 [0]
  L25 to L26 -> L28 [1] lasti
  L26 to L27 -> L31 [0] lasti
  L27 to L28 -> L28 [1] lasti
  L28 to L30 -> L31 [0] lasti

Disassembly of <code object get_calendar_status at 0x0000024C114358A0, file "D:\fluence\Github\mattbot\backend\app\services\calendar_service.py", line 195>:
 195           RETURN_GENERATOR
               POP_TOP
       L1:     RESUME                   0

 197           LOAD_CONST               1 (0)
               LOAD_CONST               2 (('AsyncSession',))
               IMPORT_NAME              0 (sqlalchemy.ext.asyncio)
               IMPORT_FROM              1 (AsyncSession)
               STORE_FAST               2 (AsyncSession)
               POP_TOP

 199           LOAD_CONST               1 (0)
               LOAD_CONST               3 (('GoogleCalendarToken',))
               IMPORT_NAME              2 (app.models.google_calendar_token)
               IMPORT_FROM              3 (GoogleCalendarToken)
               STORE_FAST               3 (GoogleCalendarToken)
               POP_TOP

 201           LOAD_FAST                0 (db)
               STORE_FAST               4 (session)

 202           LOAD_FAST                4 (session)
               LOAD_ATTR                9 (get + NULL|self)
               LOAD_FAST_LOAD_FAST     49 (GoogleCalendarToken, user_id)
               CALL                     2
               GET_AWAITABLE            0
               LOAD_CONST               4 (None)
       L2:     SEND                     3 (to L5)
       L3:     YIELD_VALUE              1
       L4:     RESUME                   3
               JUMP_BACKWARD_NO_INTERRUPT 5 (to L2)
       L5:     END_SEND
               STORE_FAST               5 (row)

 203           LOAD_FAST                5 (row)
               POP_JUMP_IF_NOT_NONE     6 (to L6)

 204           LOAD_CONST               5 (False)
               LOAD_CONST               4 (None)
               LOAD_CONST               4 (None)
               LOAD_CONST               6 (('connected', 'email', 'calendar_id'))
               BUILD_CONST_KEY_MAP      3
               RETURN_VALUE

 206   L6:     LOAD_CONST               7 (True)

 207           LOAD_FAST                5 (row)
               LOAD_ATTR               10 (google_email)

 208           LOAD_FAST                5 (row)
               LOAD_ATTR               12 (calendar_id)

 205           LOAD_CONST               6 (('connected', 'email', 'calendar_id'))
               BUILD_CONST_KEY_MAP      3
               RETURN_VALUE

 202   L7:     CLEANUP_THROW
       L8:     JUMP_BACKWARD_NO_INTERRUPT 39 (to L5)

  --   L9:     CALL_INTRINSIC_1         3 (INTRINSIC_STOPITERATION_ERROR)
               RERAISE                  1
ExceptionTable:
  L1 to L3 -> L9 [0] lasti
  L3 to L4 -> L7 [2]
  L4 to L8 -> L9 [0] lasti

Disassembly of <code object _parse_caller_from_description at 0x0000024C0EBFFC50, file "D:\fluence\Github\mattbot\backend\app\services\calendar_service.py", line 217>:
217           RESUME                   0

219           LOAD_FAST                1 (field)
              LOAD_CONST               1 ('name')
              COMPARE_OP              88 (bool(==))
              POP_JUMP_IF_FALSE        2 (to L1)
              LOAD_CONST               2 ('Caller: ')
              JUMP_FORWARD             1 (to L2)
      L1:     LOAD_CONST               3 ('Phone: ')
      L2:     STORE_FAST               2 (prefix)

220           LOAD_FAST                0 (description)
              LOAD_ATTR                1 (splitlines + NULL|self)
              CALL                     0
              GET_ITER
      L3:     FOR_ITER                71 (to L5)
              STORE_FAST               3 (line)

221           LOAD_FAST                3 (line)
              LOAD_ATTR                3 (strip + NULL|self)
              CALL                     0
              STORE_FAST               4 (stripped)

222           LOAD_FAST                4 (stripped)
              LOAD_ATTR                5 (startswith + NULL|self)
              LOAD_FAST                2 (prefix)
              CALL                     1
              TO_BOOL
              POP_JUMP_IF_TRUE         2 (to L4)
              JUMP_BACKWARD           43 (to L3)

223   L4:     LOAD_FAST                4 (stripped)
              LOAD_GLOBAL              7 (len + NULL)
              LOAD_FAST                2 (prefix)
              CALL                     1
              LOAD_CONST               4 (None)
              BINARY_SLICE
              LOAD_ATTR                3 (strip + NULL|self)
              CALL                     0
              SWAP                     2
              POP_TOP
              RETURN_VALUE

220   L5:     END_FOR
              POP_TOP

224           RETURN_CONST             4 (None)

Disassembly of <code object list_events at 0x0000024C0FCFF890, file "D:\fluence\Github\mattbot\backend\app\services\calendar_service.py", line 227>:
 227            RETURN_GENERATOR
                POP_TOP
        L1:     RESUME                   0

 240            LOAD_GLOBAL              1 (get_valid_access_token + NULL)
                LOAD_FAST_LOAD_FAST      1 (db, user_id)
                CALL                     2
                GET_AWAITABLE            0
                LOAD_CONST               1 (None)
        L2:     SEND                     3 (to L5)
        L3:     YIELD_VALUE              1
        L4:     RESUME                   3
                JUMP_BACKWARD_NO_INTERRUPT 5 (to L2)
        L5:     END_SEND
                STORE_FAST               5 (token)

 241            LOAD_FAST                5 (token)
                TO_BOOL
                POP_JUMP_IF_TRUE         2 (to L6)

 242            BUILD_LIST               0
                RETURN_VALUE

 245    L6:     LOAD_FAST                2 (time_min)

 246            LOAD_FAST                3 (time_max)

 247            LOAD_CONST               2 ('true')

 248            LOAD_CONST               3 ('startTime')

 249            LOAD_CONST               4 ('250')

 250            LOAD_FAST                4 (timezone)

 244            LOAD_CONST               5 (('timeMin', 'timeMax', 'singleEvents', 'orderBy', 'maxResults', 'timeZone'))
                BUILD_CONST_KEY_MAP      6
                STORE_FAST               6 (params)

 252            LOAD_GLOBAL              2 (httpx)
                LOAD_ATTR                4 (AsyncClient)
                PUSH_NULL
                LOAD_GLOBAL              6 (_TIMEOUT)
                LOAD_CONST               6 (('timeout',))
                CALL_KW                  1
                BEFORE_ASYNC_WITH
                GET_AWAITABLE            1
                LOAD_CONST               1 (None)
        L7:     SEND                     3 (to L10)
        L8:     YIELD_VALUE              1
        L9:     RESUME                   3
                JUMP_BACKWARD_NO_INTERRUPT 5 (to L7)
       L10:     END_SEND
       L11:     STORE_FAST               7 (client)

 253            LOAD_FAST                7 (client)
                LOAD_ATTR                9 (get + NULL|self)

 254            LOAD_GLOBAL             10 (_GOOGLE_CALENDAR_API)
                FORMAT_SIMPLE
                LOAD_CONST               7 ('/calendars/primary/events')
                BUILD_STRING             2

 255            LOAD_CONST               8 ('Authorization')
                LOAD_CONST               9 ('Bearer ')
                LOAD_FAST                5 (token)
                FORMAT_SIMPLE
                BUILD_STRING             2
                BUILD_MAP                1

 256            LOAD_FAST                6 (params)

 253            LOAD_CONST              10 (('headers', 'params'))
                CALL_KW                  3
                GET_AWAITABLE            0
                LOAD_CONST               1 (None)
       L12:     SEND                     3 (to L15)
       L13:     YIELD_VALUE              1
       L14:     RESUME                   3
                JUMP_BACKWARD_NO_INTERRUPT 5 (to L12)
       L15:     END_SEND
                STORE_FAST               8 (resp)

 258            LOAD_FAST                8 (resp)
                LOAD_ATTR               12 (status_code)
                LOAD_CONST              11 (200)
                COMPARE_OP             119 (bool(!=))
                POP_JUMP_IF_FALSE       51 (to L21)

 259            LOAD_GLOBAL             14 (logger)
                LOAD_ATTR               17 (error + NULL|self)
                LOAD_CONST              12 ('Google Calendar list_events failed: %d')
                LOAD_FAST                8 (resp)
                LOAD_ATTR               12 (status_code)
                CALL                     2
                POP_TOP

 260            BUILD_LIST               0

 252   L16:     SWAP                     2
                LOAD_CONST               1 (None)
                LOAD_CONST               1 (None)
                LOAD_CONST               1 (None)
                CALL                     2
                GET_AWAITABLE            2
                LOAD_CONST               1 (None)
       L17:     SEND                     3 (to L20)
       L18:     YIELD_VALUE              1
       L19:     RESUME                   3
                JUMP_BACKWARD_NO_INTERRUPT 5 (to L17)
       L20:     END_SEND
                POP_TOP
                RETURN_VALUE

 261   L21:     LOAD_FAST                8 (resp)
                LOAD_ATTR               19 (json + NULL|self)
                CALL                     0
                STORE_FAST               9 (data)

 262            LOAD_FAST                9 (data)
                LOAD_ATTR                9 (get + NULL|self)
                LOAD_CONST              13 ('items')
                BUILD_LIST               0
                CALL                     2
                STORE_FAST              10 (items)

 263            BUILD_LIST               0
                STORE_FAST              11 (results)

 264            LOAD_FAST               10 (items)
                GET_ITER
       L22:     EXTENDED_ARG             1
                FOR_ITER               398 (to L25)
                STORE_FAST              12 (ev)

 265            LOAD_FAST               12 (ev)
                LOAD_ATTR                9 (get + NULL|self)
                LOAD_CONST              14 ('extendedProperties')
                BUILD_MAP                0
                CALL                     2
                LOAD_ATTR                9 (get + NULL|self)
                LOAD_CONST              15 ('private')
                BUILD_MAP                0
                CALL                     2
                STORE_FAST              13 (ext_private)

 266            LOAD_FAST               13 (ext_private)
                LOAD_ATTR                9 (get + NULL|self)
                LOAD_CONST              16 ('mattbot_call_id')
                CALL                     1
                STORE_FAST              14 (mattbot_call_id)

 267            LOAD_FAST               12 (ev)
                LOAD_ATTR                9 (get + NULL|self)
                LOAD_CONST              17 ('description')
                LOAD_CONST              18 ('')
                CALL                     2
                STORE_FAST              15 (desc)

 268            LOAD_FAST               11 (results)
                LOAD_ATTR               21 (append + NULL|self)

 269            LOAD_FAST               12 (ev)
                LOAD_ATTR                9 (get + NULL|self)
                LOAD_CONST              19 ('id')
                LOAD_CONST              18 ('')
                CALL                     2

 270            LOAD_FAST               12 (ev)
                LOAD_ATTR                9 (get + NULL|self)
                LOAD_CONST              20 ('summary')
                LOAD_CONST              21 ('(No title)')
                CALL                     2

 272            LOAD_FAST               12 (ev)
                LOAD_ATTR                9 (get + NULL|self)
                LOAD_CONST              22 ('start')
                BUILD_MAP                0
                CALL                     2
                LOAD_ATTR                9 (get + NULL|self)
                LOAD_CONST              23 ('dateTime')
                CALL                     1
                COPY                     1
                TO_BOOL
                POP_JUMP_IF_TRUE        34 (to L23)
                POP_TOP

 273            LOAD_FAST               12 (ev)
                LOAD_ATTR                9 (get + NULL|self)
                LOAD_CONST              22 ('start')
                BUILD_MAP                0
                CALL                     2
                LOAD_ATTR                9 (get + NULL|self)
                LOAD_CONST              24 ('date')
                LOAD_CONST              18 ('')
                CALL                     2

 276   L23:     LOAD_FAST               12 (ev)
                LOAD_ATTR                9 (get + NULL|self)
                LOAD_CONST              25 ('end')
                BUILD_MAP                0
                CALL                     2
                LOAD_ATTR                9 (get + NULL|self)
                LOAD_CONST              23 ('dateTime')
                CALL                     1
                COPY                     1
                TO_BOOL
                POP_JUMP_IF_TRUE        34 (to L24)
                POP_TOP

 277            LOAD_FAST               12 (ev)
                LOAD_ATTR                9 (get + NULL|self)
                LOAD_CONST              25 ('end')
                BUILD_MAP                0
                CALL                     2
                LOAD_ATTR                9 (get + NULL|self)
                LOAD_CONST              24 ('date')
                LOAD_CONST              18 ('')
                CALL                     2

 279   L24:     LOAD_FAST               15 (desc)

 280            LOAD_FAST               12 (ev)
                LOAD_ATTR                9 (get + NULL|self)
                LOAD_CONST              26 ('location')
                LOAD_CONST              18 ('')
                CALL                     2

 281            LOAD_FAST               12 (ev)
                LOAD_ATTR                9 (get + NULL|self)
                LOAD_CONST              27 ('status')
                LOAD_CONST              28 ('confirmed')
                CALL                     2

 282            LOAD_FAST               12 (ev)
                LOAD_ATTR                9 (get + NULL|self)
                LOAD_CONST              29 ('organizer')
                BUILD_MAP                0
                CALL                     2
                LOAD_ATTR                9 (get + NULL|self)
                LOAD_CONST              30 ('email')
                LOAD_CONST              18 ('')
                CALL                     2

 283            LOAD_GLOBAL             23 (len + NULL)
                LOAD_FAST               12 (ev)
                LOAD_ATTR                9 (get + NULL|self)
                LOAD_CONST              31 ('attendees')
                BUILD_LIST               0
                CALL                     2
                CALL                     1

 284            LOAD_FAST               14 (mattbot_call_id)

 285            LOAD_GLOBAL             25 (bool + NULL)
                LOAD_FAST               14 (mattbot_call_id)
                CALL                     1

 286            LOAD_GLOBAL             27 (_parse_caller_from_description + NULL)
                LOAD_FAST               15 (desc)
                LOAD_CONST              32 ('name')
                CALL                     2

 287            LOAD_GLOBAL             27 (_parse_caller_from_description + NULL)
                LOAD_FAST               15 (desc)
                LOAD_CONST              33 ('phone')
                CALL                     2

 268            LOAD_CONST              34 (('id', 'summary', 'start', 'end', 'description', 'location', 'status', 'organizer_email', 'attendees_count', 'call_id', 'is_mattbot_booked', 'caller_name', 'caller_phone'))
                BUILD_CONST_KEY_MAP     13
                CALL                     1
                POP_TOP
                EXTENDED_ARG             1
                JUMP_BACKWARD          401 (to L22)

 264   L25:     END_FOR
                POP_TOP

 289            LOAD_FAST               11 (results)

 252   L26:     SWAP                     2
                LOAD_CONST               1 (None)
                LOAD_CONST               1 (None)
                LOAD_CONST               1 (None)
                CALL                     2
                GET_AWAITABLE            2
                LOAD_CONST               1 (None)
       L27:     SEND                     3 (to L30)
       L28:     YIELD_VALUE              1
       L29:     RESUME                   3
                JUMP_BACKWARD_NO_INTERRUPT 5 (to L27)
       L30:     END_SEND
                POP_TOP
                RETURN_VALUE

 240   L31:     CLEANUP_THROW
       L32:     EXTENDED_ARG             2
                JUMP_BACKWARD_NO_INTERRUPT 620 (to L5)

 252   L33:     CLEANUP_THROW
       L34:     EXTENDED_ARG             2
                JUMP_BACKWARD_NO_INTERRUPT 572 (to L10)

 253   L35:     CLEANUP_THROW
       L36:     EXTENDED_ARG             2
                JUMP_BACKWARD_NO_INTERRUPT 538 (to L15)

 252   L37:     CLEANUP_THROW
       L38:     EXTENDED_ARG             1
                JUMP_BACKWARD_NO_INTERRUPT 475 (to L20)
       L39:     CLEANUP_THROW
       L40:     JUMP_BACKWARD_NO_INTERRUPT 17 (to L30)
       L41:     PUSH_EXC_INFO
                WITH_EXCEPT_START
                GET_AWAITABLE            2
                LOAD_CONST               1 (None)
       L42:     SEND                     4 (to L46)
       L43:     YIELD_VALUE              1
       L44:     RESUME                   3
                JUMP_BACKWARD_NO_INTERRUPT 5 (to L42)
       L45:     CLEANUP_THROW
       L46:     END_SEND
                TO_BOOL
                POP_JUMP_IF_TRUE         1 (to L47)
                RERAISE                  2
       L47:     POP_TOP
       L48:     POP_EXCEPT
                POP_TOP
                POP_TOP
                RETURN_CONST             1 (None)

  --   L49:     COPY                     3
                POP_EXCEPT
                RERAISE                  1
       L50:     CALL_INTRINSIC_1         3 (INTRINSIC_STOPITERATION_ERROR)
                RERAISE                  1
ExceptionTable:
  L1 to L3 -> L50 [0] lasti
  L3 to L4 -> L31 [2]
  L4 to L8 -> L50 [0] lasti
  L8 to L9 -> L33 [3]
  L9 to L11 -> L50 [0] lasti
  L11 to L13 -> L41 [1] lasti
  L13 to L14 -> L35 [3]
  L14 to L16 -> L41 [1] lasti
  L16 to L18 -> L50 [0] lasti
  L18 to L19 -> L37 [3]
  L19 to L21 -> L50 [0] lasti
  L21 to L26 -> L41 [1] lasti
  L26 to L28 -> L50 [0] lasti
  L28 to L29 -> L39 [3]
  L29 to L32 -> L50 [0] lasti
  L33 to L34 -> L50 [0] lasti
  L35 to L36 -> L41 [1] lasti
  L37 to L38 -> L50 [0] lasti
  L39 to L40 -> L50 [0] lasti
  L41 to L43 -> L49 [3] lasti
  L43 to L44 -> L45 [6]
  L44 to L48 -> L49 [3] lasti
  L48 to L50 -> L50 [0] lasti

Disassembly of <code object create_event at 0x0000024C0FB6B350, file "D:\fluence\Github\mattbot\backend\app\services\calendar_service.py", line 292>:
 292            RETURN_GENERATOR
                POP_TOP
        L1:     RESUME                   0

 304            LOAD_GLOBAL              1 (get_valid_access_token + NULL)
                LOAD_FAST_LOAD_FAST      1 (db, user_id)
                CALL                     2
                GET_AWAITABLE            0
                LOAD_CONST               1 (None)
        L2:     SEND                     3 (to L5)
        L3:     YIELD_VALUE              1
        L4:     RESUME                   3
                JUMP_BACKWARD_NO_INTERRUPT 5 (to L2)
        L5:     END_SEND
                STORE_FAST               9 (token)

 305            LOAD_FAST                9 (token)
                TO_BOOL
                POP_JUMP_IF_TRUE         1 (to L6)

 306            RETURN_CONST             1 (None)

 309    L6:     LOAD_FAST                2 (summary)

 310            LOAD_FAST                5 (description)

 311            LOAD_FAST_LOAD_FAST     55 (start_datetime, timezone)
                LOAD_CONST               2 (('dateTime', 'timeZone'))
                BUILD_CONST_KEY_MAP      2

 312            LOAD_FAST_LOAD_FAST     71 (end_datetime, timezone)
                LOAD_CONST               2 (('dateTime', 'timeZone'))
                BUILD_CONST_KEY_MAP      2

 308            LOAD_CONST               3 (('summary', 'description', 'start', 'end'))
                BUILD_CONST_KEY_MAP      4
                STORE_FAST              10 (event_body)

 314            LOAD_FAST                6 (attendee_email)
                TO_BOOL
                POP_JUMP_IF_FALSE        8 (to L7)

 315            LOAD_CONST               4 ('email')
                LOAD_FAST                6 (attendee_email)
                BUILD_MAP                1
                BUILD_LIST               1
                LOAD_FAST               10 (event_body)
                LOAD_CONST               5 ('attendees')
                STORE_SUBSCR

 316    L7:     LOAD_FAST                8 (call_id)
                TO_BOOL
                POP_JUMP_IF_FALSE       18 (to L8)

 318            LOAD_CONST               6 ('private')
                LOAD_CONST               7 ('mattbot_call_id')
                LOAD_GLOBAL              3 (str + NULL)
                LOAD_FAST                8 (call_id)
                CALL                     1
                BUILD_MAP                1

 317            BUILD_MAP                1
                LOAD_FAST               10 (event_body)
                LOAD_CONST               8 ('extendedProperties')
                STORE_SUBSCR

 321    L8:     LOAD_GLOBAL              4 (httpx)
                LOAD_ATTR                6 (AsyncClient)
                PUSH_NULL
                LOAD_GLOBAL              8 (_TIMEOUT)
                LOAD_CONST               9 (('timeout',))
                CALL_KW                  1
                BEFORE_ASYNC_WITH
                GET_AWAITABLE            1
                LOAD_CONST               1 (None)
        L9:     SEND                     3 (to L12)
       L10:     YIELD_VALUE              1
       L11:     RESUME                   3
                JUMP_BACKWARD_NO_INTERRUPT 5 (to L9)
       L12:     END_SEND
       L13:     STORE_FAST              11 (client)

 322            LOAD_FAST               11 (client)
                LOAD_ATTR               11 (post + NULL|self)

 323            LOAD_GLOBAL             12 (_GOOGLE_CALENDAR_API)
                FORMAT_SIMPLE
                LOAD_CONST              10 ('/calendars/primary/events')
                BUILD_STRING             2

 325            LOAD_CONST              11 ('Bearer ')
                LOAD_FAST                9 (token)
                FORMAT_SIMPLE
                BUILD_STRING             2

 326            LOAD_CONST              12 ('application/json')

 324            LOAD_CONST              13 (('Authorization', 'Content-Type'))
                BUILD_CONST_KEY_MAP      2

 328            LOAD_FAST               10 (event_body)

 322            LOAD_CONST              14 (('headers', 'json'))
                CALL_KW                  3
                GET_AWAITABLE            0
                LOAD_CONST               1 (None)
       L14:     SEND                     3 (to L17)
       L15:     YIELD_VALUE              1
       L16:     RESUME                   3
                JUMP_BACKWARD_NO_INTERRUPT 5 (to L14)
       L17:     END_SEND
                STORE_FAST              12 (resp)

 330            LOAD_FAST               12 (resp)
                LOAD_ATTR               14 (status_code)
                LOAD_CONST              15 ((200, 201))
                CONTAINS_OP              1
                POP_JUMP_IF_FALSE       64 (to L23)

 331            LOAD_GLOBAL             16 (logger)
                LOAD_ATTR               19 (error + NULL|self)

 332            LOAD_CONST              16 ('Google Calendar create_event failed: %d %s')

 333            LOAD_FAST               12 (resp)
                LOAD_ATTR               14 (status_code)

 334            LOAD_FAST               12 (resp)
                LOAD_ATTR               20 (text)
                LOAD_CONST               1 (None)
                LOAD_CONST              17 (300)
                BINARY_SLICE

 331            CALL                     3
                POP_TOP

 336            NOP

 321   L18:     LOAD_CONST               1 (None)
                LOAD_CONST               1 (None)
                LOAD_CONST               1 (None)
                CALL                     2
                GET_AWAITABLE            2
                LOAD_CONST               1 (None)
       L19:     SEND                     3 (to L22)
       L20:     YIELD_VALUE              1
       L21:     RESUME                   3
                JUMP_BACKWARD_NO_INTERRUPT 5 (to L19)
       L22:     END_SEND
                POP_TOP
                RETURN_CONST             1 (None)

 337   L23:     LOAD_FAST               12 (resp)
                LOAD_ATTR               23 (json + NULL|self)
                CALL                     0
                STORE_FAST              13 (data)

 339            LOAD_FAST               13 (data)
                LOAD_ATTR               25 (get + NULL|self)
                LOAD_CONST              18 ('id')
                LOAD_CONST              19 ('')
                CALL                     2

 340            LOAD_FAST               13 (data)
                LOAD_ATTR               25 (get + NULL|self)
                LOAD_CONST              20 ('summary')
                LOAD_CONST              19 ('')
                CALL                     2

 341            LOAD_FAST               13 (data)
                LOAD_ATTR               25 (get + NULL|self)
                LOAD_CONST              21 ('start')
                BUILD_MAP                0
                CALL                     2
                LOAD_ATTR               25 (get + NULL|self)
                LOAD_CONST              22 ('dateTime')
                LOAD_CONST              19 ('')
                CALL                     2

 342            LOAD_FAST               13 (data)
                LOAD_ATTR               25 (get + NULL|self)
                LOAD_CONST              23 ('end')
                BUILD_MAP                0
                CALL                     2
                LOAD_ATTR               25 (get + NULL|self)
                LOAD_CONST              22 ('dateTime')
                LOAD_CONST              19 ('')
                CALL                     2

 343            LOAD_FAST               13 (data)
                LOAD_ATTR               25 (get + NULL|self)
                LOAD_CONST              24 ('htmlLink')
                LOAD_CONST              19 ('')
                CALL                     2

 338            LOAD_CONST              25 (('id', 'summary', 'start', 'end', 'html_link'))
                BUILD_CONST_KEY_MAP      5

 321   L24:     SWAP                     2
                LOAD_CONST               1 (None)
                LOAD_CONST               1 (None)
                LOAD_CONST               1 (None)
                CALL                     2
                GET_AWAITABLE            2
                LOAD_CONST               1 (None)
       L25:     SEND                     3 (to L28)
       L26:     YIELD_VALUE              1
       L27:     RESUME                   3
                JUMP_BACKWARD_NO_INTERRUPT 5 (to L25)
       L28:     END_SEND
                POP_TOP
                RETURN_VALUE

 304   L29:     CLEANUP_THROW
       L30:     EXTENDED_ARG             1
                JUMP_BACKWARD_NO_INTERRUPT 368 (to L5)

 321   L31:     CLEANUP_THROW
       L32:     EXTENDED_ARG             1
                JUMP_BACKWARD_NO_INTERRUPT 279 (to L12)

 322   L33:     CLEANUP_THROW
       L34:     JUMP_BACKWARD_NO_INTERRUPT 243 (to L17)

 321   L35:     CLEANUP_THROW
       L36:     JUMP_BACKWARD_NO_INTERRUPT 166 (to L22)
       L37:     CLEANUP_THROW
       L38:     JUMP_BACKWARD_NO_INTERRUPT 15 (to L28)
       L39:     PUSH_EXC_INFO
                WITH_EXCEPT_START
                GET_AWAITABLE            2
                LOAD_CONST               1 (None)
       L40:     SEND                     4 (to L44)
       L41:     YIELD_VALUE              1
       L42:     RESUME                   3
                JUMP_BACKWARD_NO_INTERRUPT 5 (to L40)
       L43:     CLEANUP_THROW
       L44:     END_SEND
                TO_BOOL
                POP_JUMP_IF_TRUE         1 (to L45)
                RERAISE                  2
       L45:     POP_TOP
       L46:     POP_EXCEPT
                POP_TOP
                POP_TOP
                RETURN_CONST             1 (None)

  --   L47:     COPY                     3
                POP_EXCEPT
                RERAISE                  1
       L48:     CALL_INTRINSIC_1         3 (INTRINSIC_STOPITERATION_ERROR)
                RERAISE                  1
ExceptionTable:
  L1 to L3 -> L48 [0] lasti
  L3 to L4 -> L29 [2]
  L4 to L10 -> L48 [0] lasti
  L10 to L11 -> L31 [3]
  L11 to L13 -> L48 [0] lasti
  L13 to L15 -> L39 [1] lasti
  L15 to L16 -> L33 [3]
  L16 to L18 -> L39 [1] lasti
  L18 to L20 -> L48 [0] lasti
  L20 to L21 -> L35 [2]
  L21 to L23 -> L48 [0] lasti
  L23 to L24 -> L39 [1] lasti
  L24 to L26 -> L48 [0] lasti
  L26 to L27 -> L37 [3]
  L27 to L30 -> L48 [0] lasti
  L31 to L32 -> L48 [0] lasti
  L33 to L34 -> L39 [1] lasti
  L35 to L36 -> L48 [0] lasti
  L37 to L38 -> L48 [0] lasti
  L39 to L41 -> L47 [3] lasti
  L41 to L42 -> L43 [6]
  L42 to L46 -> L47 [3] lasti
  L46 to L48 -> L48 [0] lasti

Disassembly of <code object get_free_busy at 0x0000024C0FED9050, file "D:\fluence\Github\mattbot\backend\app\services\calendar_service.py", line 347>:
 347            RETURN_GENERATOR
                POP_TOP
        L1:     RESUME                   0

 354            LOAD_GLOBAL              1 (get_valid_access_token + NULL)
                LOAD_FAST_LOAD_FAST      1 (db, user_id)
                CALL                     2
                GET_AWAITABLE            0
                LOAD_CONST               1 (None)
        L2:     SEND                     3 (to L5)
        L3:     YIELD_VALUE              1
        L4:     RESUME                   3
                JUMP_BACKWARD_NO_INTERRUPT 5 (to L2)
        L5:     END_SEND
                STORE_FAST               4 (token)

 355            LOAD_FAST                4 (token)
                TO_BOOL
                POP_JUMP_IF_TRUE         2 (to L6)

 356            BUILD_LIST               0
                RETURN_VALUE

 359    L6:     LOAD_FAST                2 (time_min)

 360            LOAD_FAST                3 (time_max)

 361            LOAD_CONST               2 ('id')
                LOAD_CONST               3 ('primary')
                BUILD_MAP                1
                BUILD_LIST               1

 358            LOAD_CONST               4 (('timeMin', 'timeMax', 'items'))
                BUILD_CONST_KEY_MAP      3
                STORE_FAST               5 (body)

 363            LOAD_GLOBAL              2 (httpx)
                LOAD_ATTR                4 (AsyncClient)
                PUSH_NULL
                LOAD_GLOBAL              6 (_TIMEOUT)
                LOAD_CONST               5 (('timeout',))
                CALL_KW                  1
                BEFORE_ASYNC_WITH
                GET_AWAITABLE            1
                LOAD_CONST               1 (None)
        L7:     SEND                     3 (to L10)
        L8:     YIELD_VALUE              1
        L9:     RESUME                   3
                JUMP_BACKWARD_NO_INTERRUPT 5 (to L7)
       L10:     END_SEND
       L11:     STORE_FAST               6 (client)

 364            LOAD_FAST                6 (client)
                LOAD_ATTR                9 (post + NULL|self)

 365            LOAD_GLOBAL             10 (_GOOGLE_CALENDAR_API)
                FORMAT_SIMPLE
                LOAD_CONST               6 ('/freeBusy')
                BUILD_STRING             2

 367            LOAD_CONST               7 ('Bearer ')
                LOAD_FAST                4 (token)
                FORMAT_SIMPLE
                BUILD_STRING             2

 368            LOAD_CONST               8 ('application/json')

 366            LOAD_CONST               9 (('Authorization', 'Content-Type'))
                BUILD_CONST_KEY_MAP      2

 370            LOAD_FAST                5 (body)

 364            LOAD_CONST              10 (('headers', 'json'))
                CALL_KW                  3
                GET_AWAITABLE            0
                LOAD_CONST               1 (None)
       L12:     SEND                     3 (to L15)
       L13:     YIELD_VALUE              1
       L14:     RESUME                   3
                JUMP_BACKWARD_NO_INTERRUPT 5 (to L12)
       L15:     END_SEND
                STORE_FAST               7 (resp)

 372            LOAD_FAST                7 (resp)
                LOAD_ATTR               12 (status_code)
                LOAD_CONST              11 (200)
                COMPARE_OP             119 (bool(!=))
                POP_JUMP_IF_FALSE       51 (to L21)

 373            LOAD_GLOBAL             14 (logger)
                LOAD_ATTR               17 (error + NULL|self)
                LOAD_CONST              12 ('Google Calendar freeBusy failed: %d')
                LOAD_FAST                7 (resp)
                LOAD_ATTR               12 (status_code)
                CALL                     2
                POP_TOP

 374            BUILD_LIST               0

 363   L16:     SWAP                     2
                LOAD_CONST               1 (None)
                LOAD_CONST               1 (None)
                LOAD_CONST               1 (None)
                CALL                     2
                GET_AWAITABLE            2
                LOAD_CONST               1 (None)
       L17:     SEND                     3 (to L20)
       L18:     YIELD_VALUE              1
       L19:     RESUME                   3
                JUMP_BACKWARD_NO_INTERRUPT 5 (to L17)
       L20:     END_SEND
                POP_TOP
                RETURN_VALUE

 375   L21:     LOAD_FAST                7 (resp)
                LOAD_ATTR               19 (json + NULL|self)
                CALL                     0
                STORE_FAST               8 (data)

 376            LOAD_FAST                8 (data)
                LOAD_ATTR               21 (get + NULL|self)
                LOAD_CONST              13 ('calendars')
                BUILD_MAP                0
                CALL                     2
                LOAD_ATTR               21 (get + NULL|self)
                LOAD_CONST               3 ('primary')
                BUILD_MAP                0
                CALL                     2
                LOAD_ATTR               21 (get + NULL|self)
                LOAD_CONST              14 ('busy')
                BUILD_LIST               0
                CALL                     2

 363   L22:     SWAP                     2
                LOAD_CONST               1 (None)
                LOAD_CONST               1 (None)
                LOAD_CONST               1 (None)
                CALL                     2
                GET_AWAITABLE            2
                LOAD_CONST               1 (None)
       L23:     SEND                     3 (to L26)
       L24:     YIELD_VALUE              1
       L25:     RESUME                   3
                JUMP_BACKWARD_NO_INTERRUPT 5 (to L23)
       L26:     END_SEND
                POP_TOP
                RETURN_VALUE

 354   L27:     CLEANUP_THROW
       L28:     JUMP_BACKWARD_NO_INTERRUPT 243 (to L5)

 363   L29:     CLEANUP_THROW
       L30:     JUMP_BACKWARD_NO_INTERRUPT 194 (to L10)

 364   L31:     CLEANUP_THROW
       L32:     JUMP_BACKWARD_NO_INTERRUPT 158 (to L15)

 363   L33:     CLEANUP_THROW
       L34:     JUMP_BACKWARD_NO_INTERRUPT 94 (to L20)
       L35:     CLEANUP_THROW
       L36:     JUMP_BACKWARD_NO_INTERRUPT 13 (to L26)
       L37:     PUSH_EXC_INFO
                WITH_EXCEPT_START
                GET_AWAITABLE            2
                LOAD_CONST               1 (None)
       L38:     SEND                     4 (to L42)
       L39:     YIELD_VALUE              1
       L40:     RESUME                   3
                JUMP_BACKWARD_NO_INTERRUPT 5 (to L38)
       L41:     CLEANUP_THROW
       L42:     END_SEND
                TO_BOOL
                POP_JUMP_IF_TRUE         1 (to L43)
                RERAISE                  2
       L43:     POP_TOP
       L44:     POP_EXCEPT
                POP_TOP
                POP_TOP
                RETURN_CONST             1 (None)

  --   L45:     COPY                     3
                POP_EXCEPT
                RERAISE                  1
       L46:     CALL_INTRINSIC_1         3 (INTRINSIC_STOPITERATION_ERROR)
                RERAISE                  1
ExceptionTable:
  L1 to L3 -> L46 [0] lasti
  L3 to L4 -> L27 [2]
  L4 to L8 -> L46 [0] lasti
  L8 to L9 -> L29 [3]
  L9 to L11 -> L46 [0] lasti
  L11 to L13 -> L37 [1] lasti
  L13 to L14 -> L31 [3]
  L14 to L16 -> L37 [1] lasti
  L16 to L18 -> L46 [0] lasti
  L18 to L19 -> L33 [3]
  L19 to L21 -> L46 [0] lasti
  L21 to L22 -> L37 [1] lasti
  L22 to L24 -> L46 [0] lasti
  L24 to L25 -> L35 [3]
  L25 to L28 -> L46 [0] lasti
  L29 to L30 -> L46 [0] lasti
  L31 to L32 -> L37 [1] lasti
  L33 to L34 -> L46 [0] lasti
  L35 to L36 -> L46 [0] lasti
  L37 to L39 -> L45 [3] lasti
  L39 to L40 -> L41 [6]
  L40 to L44 -> L45 [3] lasti
  L44 to L46 -> L46 [0] lasti

Disassembly of <code object find_available_slots at 0x0000024C0FB59FD0, file "D:\fluence\Github\mattbot\backend\app\services\calendar_service.py", line 379>:
 379            RETURN_GENERATOR
                POP_TOP
        L1:     RESUME                   0

 392            LOAD_CONST               1 (0)
                LOAD_CONST               2 (('ZoneInfo',))
                IMPORT_NAME              0 (zoneinfo)
                IMPORT_FROM              1 (ZoneInfo)
                STORE_FAST               7 (ZoneInfo)
                POP_TOP

 394            LOAD_FAST                7 (ZoneInfo)
                PUSH_NULL
                LOAD_FAST                6 (timezone)
                CALL                     1
                STORE_FAST               8 (tz)

 395            LOAD_GLOBAL              4 (datetime)
                LOAD_ATTR                6 (strptime)
                PUSH_NULL
                LOAD_FAST                2 (date_str)
                LOAD_CONST               3 ('%Y-%m-%d')
                CALL                     2
                LOAD_ATTR                9 (date + NULL|self)
                CALL                     0
                STORE_FAST               9 (day)

 396            LOAD_FAST                4 (business_start)
                COPY                     1
                TO_BOOL
                POP_JUMP_IF_TRUE        12 (to L2)
                POP_TOP
                LOAD_GLOBAL             11 (dt_time + NULL)
                LOAD_CONST               4 (9)
                LOAD_CONST               1 (0)
                CALL                     2
        L2:     STORE_FAST              10 (start_hour)

 397            LOAD_FAST                5 (business_end)
                COPY                     1
                TO_BOOL
                POP_JUMP_IF_TRUE        12 (to L3)
                POP_TOP
                LOAD_GLOBAL             11 (dt_time + NULL)
                LOAD_CONST               5 (17)
                LOAD_CONST               1 (0)
                CALL                     2
        L3:     STORE_FAST              11 (end_hour)

 399            LOAD_GLOBAL              4 (datetime)
                LOAD_ATTR               12 (combine)
                PUSH_NULL
                LOAD_FAST_LOAD_FAST    154 (day, start_hour)
                LOAD_FAST                8 (tz)
                LOAD_CONST               6 (('tzinfo',))
                CALL_KW                  3
                STORE_FAST              12 (day_start)

 400            LOAD_GLOBAL              4 (datetime)
                LOAD_ATTR               12 (combine)
                PUSH_NULL
                LOAD_FAST_LOAD_FAST    155 (day, end_hour)
                LOAD_FAST                8 (tz)
                LOAD_CONST               6 (('tzinfo',))
                CALL_KW                  3
                STORE_FAST              13 (day_end)

 402            LOAD_FAST               12 (day_start)
                LOAD_ATTR               15 (isoformat + NULL|self)
                CALL                     0
                STORE_FAST              14 (time_min)

 403            LOAD_FAST               13 (day_end)
                LOAD_ATTR               15 (isoformat + NULL|self)
                CALL                     0
                STORE_FAST              15 (time_max)

 405            LOAD_GLOBAL             17 (get_free_busy + NULL)
                LOAD_FAST_LOAD_FAST      1 (db, user_id)
                LOAD_FAST_LOAD_FAST    239 (time_min, time_max)
                CALL                     4
                GET_AWAITABLE            0
                LOAD_CONST               7 (None)
        L4:     SEND                     3 (to L7)
        L5:     YIELD_VALUE              1
        L6:     RESUME                   3
                JUMP_BACKWARD_NO_INTERRUPT 5 (to L4)
        L7:     END_SEND
                STORE_FAST              16 (busy)

 407            BUILD_LIST               0
                STORE_FAST              17 (busy_intervals)

 408            LOAD_FAST               16 (busy)
                GET_ITER
        L8:     FOR_ITER                72 (to L9)
                STORE_FAST              18 (b)

 409            LOAD_GLOBAL              4 (datetime)
                LOAD_ATTR               18 (fromisoformat)
                PUSH_NULL
                LOAD_FAST               18 (b)
                LOAD_CONST               8 ('start')
                BINARY_SUBSCR
                CALL                     1
                STORE_FAST              19 (bs)

 410            LOAD_GLOBAL              4 (datetime)
                LOAD_ATTR               18 (fromisoformat)
                PUSH_NULL
                LOAD_FAST               18 (b)
                LOAD_CONST               9 ('end')
                BINARY_SUBSCR
                CALL                     1
                STORE_FAST              20 (be)

 411            LOAD_FAST               17 (busy_intervals)
                LOAD_ATTR               21 (append + NULL|self)
                LOAD_FAST               19 (bs)
                LOAD_FAST               20 (be)
                BUILD_TUPLE              2
                CALL                     1
                POP_TOP
                JUMP_BACKWARD           74 (to L8)

 408    L9:     END_FOR
                POP_TOP

 412            LOAD_FAST               17 (busy_intervals)
                LOAD_ATTR               23 (sort + NULL|self)
                LOAD_CONST              10 (<code object <lambda> at 0x0000024C0EF0F750, file "D:\fluence\Github\mattbot\backend\app\services\calendar_service.py", line 412>)
                MAKE_FUNCTION
                LOAD_CONST              11 (('key',))
                CALL_KW                  1
                POP_TOP

 414            BUILD_LIST               0
                STORE_FAST              21 (slots)

 415            LOAD_GLOBAL             25 (timedelta + NULL)
                LOAD_FAST                3 (duration_minutes)
                LOAD_CONST              12 (('minutes',))
                CALL_KW                  1
                STORE_FAST              22 (slot_duration)

 416            LOAD_FAST               12 (day_start)
                STORE_FAST              23 (cursor)

 418            LOAD_FAST               17 (busy_intervals)
                GET_ITER
       L10:     FOR_ITER               107 (to L16)
                UNPACK_SEQUENCE          2
                STORE_FAST              24 (busy_start)
                STORE_FAST              25 (busy_end)

 419            LOAD_FAST               23 (cursor)
                LOAD_FAST               22 (slot_duration)
                BINARY_OP                0 (+)
                LOAD_FAST               24 (busy_start)
                COMPARE_OP              58 (bool(<=))
                POP_JUMP_IF_FALSE       67 (to L13)

 420   L11:     LOAD_FAST               21 (slots)
                LOAD_ATTR               21 (append + NULL|self)

 421            LOAD_FAST               23 (cursor)
                LOAD_ATTR               15 (isoformat + NULL|self)
                CALL                     0

 422            LOAD_FAST               23 (cursor)
                LOAD_FAST               22 (slot_duration)
                BINARY_OP                0 (+)
                LOAD_ATTR               15 (isoformat + NULL|self)
                CALL                     0

 420            LOAD_CONST              13 (('start', 'end'))
                BUILD_CONST_KEY_MAP      2
                CALL                     1
                POP_TOP

 424            LOAD_FAST               23 (cursor)
                LOAD_FAST               22 (slot_duration)
                BINARY_OP               13 (+=)
                STORE_FAST              23 (cursor)

 419            LOAD_FAST               23 (cursor)
                LOAD_FAST               22 (slot_duration)
                BINARY_OP                0 (+)
                LOAD_FAST               24 (busy_start)
                COMPARE_OP              58 (bool(<=))
                POP_JUMP_IF_FALSE        2 (to L13)
       L12:     JUMP_BACKWARD           67 (to L11)

 425   L13:     LOAD_FAST               23 (cursor)
                LOAD_FAST               25 (busy_end)
                COMPARE_OP              18 (bool(<))
       L14:     POP_JUMP_IF_TRUE         2 (to L15)
                JUMP_BACKWARD           90 (to L10)

 426   L15:     LOAD_FAST               25 (busy_end)
                LOAD_ATTR               27 (astimezone + NULL|self)
                LOAD_FAST                8 (tz)
                CALL                     1
                STORE_FAST              23 (cursor)
                JUMP_BACKWARD          109 (to L10)

 418   L16:     END_FOR
                POP_TOP

 428            LOAD_FAST               23 (cursor)
                LOAD_FAST               22 (slot_duration)
                BINARY_OP                0 (+)
                LOAD_FAST               13 (day_end)
                COMPARE_OP              58 (bool(<=))
                POP_JUMP_IF_FALSE       67 (to L19)

 429   L17:     LOAD_FAST               21 (slots)
                LOAD_ATTR               21 (append + NULL|self)

 430            LOAD_FAST               23 (cursor)
                LOAD_ATTR               15 (isoformat + NULL|self)
                CALL                     0

 431            LOAD_FAST               23 (cursor)
                LOAD_FAST               22 (slot_duration)
                BINARY_OP                0 (+)
                LOAD_ATTR               15 (isoformat + NULL|self)
                CALL                     0

 429            LOAD_CONST              13 (('start', 'end'))
                BUILD_CONST_KEY_MAP      2
                CALL                     1
                POP_TOP

 433            LOAD_FAST               23 (cursor)
                LOAD_FAST               22 (slot_duration)
                BINARY_OP               13 (+=)
                STORE_FAST              23 (cursor)

 428            LOAD_FAST               23 (cursor)
                LOAD_FAST               22 (slot_duration)
                BINARY_OP                0 (+)
                LOAD_FAST               13 (day_end)
                COMPARE_OP              58 (bool(<=))
                POP_JUMP_IF_FALSE        2 (to L19)
       L18:     JUMP_BACKWARD           67 (to L17)

 435   L19:     LOAD_FAST               21 (slots)
                RETURN_VALUE

 405   L20:     CLEANUP_THROW
       L21:     EXTENDED_ARG             1
                JUMP_BACKWARD_NO_INTERRUPT 305 (to L7)

  --   L22:     CALL_INTRINSIC_1         3 (INTRINSIC_STOPITERATION_ERROR)
                RERAISE                  1
ExceptionTable:
  L1 to L5 -> L22 [0] lasti
  L5 to L6 -> L20 [2]
  L6 to L12 -> L22 [0] lasti
  L13 to L14 -> L22 [0] lasti
  L15 to L18 -> L22 [0] lasti
  L19 to L21 -> L22 [0] lasti

Disassembly of <code object <lambda> at 0x0000024C0EF0F750, file "D:\fluence\Github\mattbot\backend\app\services\calendar_service.py", line 412>:
412           RESUME                   0
              LOAD_FAST                0 (x)
              LOAD_CONST               1 (0)
              BINARY_SUBSCR
              RETURN_VALUE

Disassembly of <code object disconnect_calendar at 0x0000024C0FBE4020, file "D:\fluence\Github\mattbot\backend\app\services\calendar_service.py", line 443>:
 443            RETURN_GENERATOR
                POP_TOP
        L1:     RESUME                   0

 445            LOAD_CONST               1 (0)
                LOAD_CONST               2 (('AsyncSession',))
                IMPORT_NAME              0 (sqlalchemy.ext.asyncio)
                IMPORT_FROM              1 (AsyncSession)
                STORE_FAST               2 (AsyncSession)
                POP_TOP

 447            LOAD_CONST               1 (0)
                LOAD_CONST               3 (('GoogleCalendarToken',))
                IMPORT_NAME              2 (app.models.google_calendar_token)
                IMPORT_FROM              3 (GoogleCalendarToken)
                STORE_FAST               3 (GoogleCalendarToken)
                POP_TOP

 449            LOAD_FAST                0 (db)
                STORE_FAST               4 (session)

 450            LOAD_FAST                4 (session)
                LOAD_ATTR                9 (get + NULL|self)
                LOAD_FAST_LOAD_FAST     49 (GoogleCalendarToken, user_id)
                CALL                     2
                GET_AWAITABLE            0
                LOAD_CONST               4 (None)
        L2:     SEND                     3 (to L5)
        L3:     YIELD_VALUE              1
        L4:     RESUME                   3
                JUMP_BACKWARD_NO_INTERRUPT 5 (to L2)
        L5:     END_SEND
                STORE_FAST               5 (row)

 451            LOAD_FAST                5 (row)
                POP_JUMP_IF_NOT_NONE     1 (to L6)

 452            RETURN_CONST             5 (False)

 454    L6:     NOP

 455    L7:     LOAD_GLOBAL             11 (decrypt_field + NULL)

 456            LOAD_FAST                5 (row)
                LOAD_ATTR               12 (access_token_ciphertext)
                LOAD_FAST                5 (row)
                LOAD_ATTR               14 (access_token_nonce)
                LOAD_FAST                5 (row)
                LOAD_ATTR               16 (key_version)

 455            CALL                     3

 457            LOAD_ATTR               19 (decode + NULL|self)
                CALL                     0

 455            STORE_FAST               6 (access_token)

 458            LOAD_GLOBAL             20 (httpx)
                LOAD_ATTR               22 (AsyncClient)
                PUSH_NULL
                LOAD_GLOBAL             24 (_TIMEOUT)
                LOAD_CONST               6 (('timeout',))
                CALL_KW                  1
                BEFORE_ASYNC_WITH
                GET_AWAITABLE            1
                LOAD_CONST               4 (None)
        L8:     SEND                     3 (to L11)
        L9:     YIELD_VALUE              1
       L10:     RESUME                   3
                JUMP_BACKWARD_NO_INTERRUPT 5 (to L8)
       L11:     END_SEND
       L12:     STORE_FAST               7 (client)

 459            LOAD_FAST                7 (client)
                LOAD_ATTR               27 (post + NULL|self)
                LOAD_GLOBAL             28 (_GOOGLE_REVOKE_URL)
                LOAD_CONST               7 ('token')
                LOAD_FAST                6 (access_token)
                BUILD_MAP                1
                LOAD_CONST               8 (('params',))
                CALL_KW                  2
                GET_AWAITABLE            0
                LOAD_CONST               4 (None)
       L13:     SEND                     3 (to L16)
       L14:     YIELD_VALUE              1
       L15:     RESUME                   3
                JUMP_BACKWARD_NO_INTERRUPT 5 (to L13)
       L16:     END_SEND
                POP_TOP

 458   L17:     LOAD_CONST               4 (None)
                LOAD_CONST               4 (None)
                LOAD_CONST               4 (None)
                CALL                     2
                GET_AWAITABLE            2
                LOAD_CONST               4 (None)
       L18:     SEND                     3 (to L21)
       L19:     YIELD_VALUE              1
       L20:     RESUME                   3
                JUMP_BACKWARD_NO_INTERRUPT 5 (to L18)
       L21:     END_SEND
                POP_TOP

 463   L22:     LOAD_FAST                4 (session)
                LOAD_ATTR               39 (delete + NULL|self)
                LOAD_FAST                5 (row)
                CALL                     1
                GET_AWAITABLE            0
                LOAD_CONST               4 (None)
       L23:     SEND                     3 (to L26)
       L24:     YIELD_VALUE              1
       L25:     RESUME                   3
                JUMP_BACKWARD_NO_INTERRUPT 5 (to L23)
       L26:     END_SEND
                POP_TOP

 464            LOAD_FAST                4 (session)
                LOAD_ATTR               41 (flush + NULL|self)
                CALL                     0
                GET_AWAITABLE            0
                LOAD_CONST               4 (None)
       L27:     SEND                     3 (to L30)
       L28:     YIELD_VALUE              1
       L29:     RESUME                   3
                JUMP_BACKWARD_NO_INTERRUPT 5 (to L27)
       L30:     END_SEND
                POP_TOP

 465            RETURN_CONST            11 (True)

 450   L31:     CLEANUP_THROW
       L32:     JUMP_BACKWARD_NO_INTERRUPT 195 (to L5)

 458   L33:     CLEANUP_THROW
       L34:     JUMP_BACKWARD_NO_INTERRUPT 102 (to L11)

 459   L35:     CLEANUP_THROW
       L36:     JUMP_BACKWARD_NO_INTERRUPT 74 (to L16)

 458   L37:     CLEANUP_THROW
       L38:     JUMP_BACKWARD_NO_INTERRUPT 60 (to L21)
       L39:     PUSH_EXC_INFO
                WITH_EXCEPT_START
                GET_AWAITABLE            2
                LOAD_CONST               4 (None)
       L40:     SEND                     4 (to L44)
       L41:     YIELD_VALUE              1
       L42:     RESUME                   3
                JUMP_BACKWARD_NO_INTERRUPT 5 (to L40)
       L43:     CLEANUP_THROW
       L44:     END_SEND
                TO_BOOL
                POP_JUMP_IF_TRUE         1 (to L45)
                RERAISE                  2
       L45:     POP_TOP
       L46:     POP_EXCEPT
                POP_TOP
                POP_TOP
       L47:     JUMP_BACKWARD_NO_INTERRUPT 81 (to L22)

  --   L48:     COPY                     3
                POP_EXCEPT
                RERAISE                  1
       L49:     PUSH_EXC_INFO

 460            LOAD_GLOBAL             30 (Exception)
                CHECK_EXC_MATCH
                POP_JUMP_IF_FALSE       37 (to L51)
                POP_TOP

 461            LOAD_GLOBAL             32 (logger)
                LOAD_ATTR               35 (warning + NULL|self)
                LOAD_CONST               9 ('Failed to revoke Google token for user %s')
                LOAD_GLOBAL             37 (str + NULL)
                LOAD_FAST                1 (user_id)
                CALL                     1
                LOAD_CONST               4 (None)
                LOAD_CONST              10 (8)
                BINARY_SLICE
                CALL                     2
                POP_TOP
       L50:     POP_EXCEPT
                JUMP_BACKWARD_NO_INTERRUPT 130 (to L22)

 460   L51:     RERAISE                  0

  --   L52:     COPY                     3
                POP_EXCEPT
                RERAISE                  1

 463   L53:     CLEANUP_THROW
       L54:     JUMP_BACKWARD_NO_INTERRUPT 113 (to L26)

 464   L55:     CLEANUP_THROW
       L56:     JUMP_BACKWARD_NO_INTERRUPT 91 (to L30)

  --   L57:     CALL_INTRINSIC_1         3 (INTRINSIC_STOPITERATION_ERROR)
                RERAISE                  1
ExceptionTable:
  L1 to L3 -> L57 [0] lasti
  L3 to L4 -> L31 [2]
  L4 to L6 -> L57 [0] lasti
  L7 to L9 -> L49 [0]
  L9 to L10 -> L33 [3]
  L10 to L12 -> L49 [0]
  L12 to L14 -> L39 [1] lasti
  L14 to L15 -> L35 [3]
  L15 to L17 -> L39 [1] lasti
  L17 to L19 -> L49 [0]
  L19 to L20 -> L37 [2]
  L20 to L22 -> L49 [0]
  L22 to L24 -> L57 [0] lasti
  L24 to L25 -> L53 [2]
  L25 to L28 -> L57 [0] lasti
  L28 to L29 -> L55 [2]
  L29 to L32 -> L57 [0] lasti
  L33 to L34 -> L49 [0]
  L35 to L36 -> L39 [1] lasti
  L37 to L38 -> L49 [0]
  L39 to L41 -> L48 [3] lasti
  L41 to L42 -> L43 [6]
  L42 to L46 -> L48 [3] lasti
  L46 to L47 -> L49 [0]
  L47 to L48 -> L57 [0] lasti
  L48 to L49 -> L49 [0]
  L49 to L50 -> L52 [1] lasti
  L50 to L51 -> L57 [0] lasti
  L51 to L52 -> L52 [1] lasti
  L52 to L54 -> L57 [0] lasti
  L55 to L56 -> L57 [0] lasti
