# Bytecode dump of: call_service.cpython-313.pyc
# co_filename: D:\fluence\Github\mattbot\backend\app\services\call_service.py
# co_names: ('__doc__', '__future__', 'annotations', 'logging', 'uuid', 'datetime', 'UTC', 'timedelta', 'sqlalchemy', 'select', 'sqlalchemy.ext.asyncio', 'AsyncSession', 'app.config', 'settings', 'app.core.encryption', 'encrypt_field', 'app.core.twilio_utils', 'compute_payload_hash', 'extract_last4', 'hash_phone', 'mask_phone', 'redact_twilio_params', 'app.models.call', 'Call', 'app.models.call_event', 'CallEvent', 'app.models.provider_event', 'ProviderEvent', 'app.models.user_number', 'UserNumber', 'getLogger', '__name__', 'logger', 'STATE_ORDER', '__annotations__', 'TERMINAL_STATES', 'TWILIO_STATUS_MAP', 'Exception', 'InvalidTransitionError', 'is_valid_transition', 'map_twilio_status', 'find_user_by_called_number', 'DEFAULT_CALL_RETENTION_DAYS', 'create_or_get_call', 'transition_call_status', 'record_provider_event', 'get_call_for_user', 'list_calls_for_user', 'get_call_events', 'get_call_by_sid', 'soft_delete_call', 'soft_delete_all_calls')
# co_consts (strings): ['Call service: state machine, idempotent record creation, provider events.', 'dict[str, int]', 'STATE_ORDER', 'created', 'inbound_received', 'in_progress', 'completed', 'failed', 'canceled', 'dict[str, str]', 'TWILIO_STATUS_MAP', 'InvalidTransitionError', 'dedicated_number', 'provider_status_update']

# DOCSTRING: """Call service: state machine, idempotent record creation, provider events."""
# --- Nested code object: InvalidTransitionError ---
    # DOCSTRING: """InvalidTransitionError"""
    # co_names: ('__name__', '__module__', '__qualname__', '__firstlineno__', '__static_attributes__')
    # co_varnames: ()
     57           RESUME                   0
                  LOAD_NAME                0 (__name__)
                  STORE_NAME               1 (__module__)
                  LOAD_CONST               0 ('InvalidTransitionError')
                  STORE_NAME               2 (__qualname__)
                  LOAD_CONST               1 (57)
                  STORE_NAME               3 (__firstlineno__)
    
     58           LOAD_CONST               2 (())
                  STORE_NAME               4 (__static_attributes__)
                  RETURN_CONST             3 (None)
    
# --- Nested code object: is_valid_transition ---
    # co_names: ('STATE_ORDER', 'get', 'TERMINAL_STATES')
    # co_varnames: ('current', 'new', 'current_order', 'new_order')
     61           RESUME                   0
    
     62           LOAD_GLOBAL              0 (STATE_ORDER)
                  LOAD_ATTR                3 (get + NULL|self)
                  LOAD_FAST                0 (current)
                  LOAD_CONST               1 (0)
                  CALL                     2
                  STORE_FAST               2 (current_order)
    
     63           LOAD_GLOBAL              0 (STATE_ORDER)
                  LOAD_ATTR                3 (get + NULL|self)
                  LOAD_FAST                1 (new)
                  LOAD_CONST               1 (0)
                  CALL                     2
                  STORE_FAST               3 (new_order)
    
     64           LOAD_FAST                0 (current)
                  LOAD_GLOBAL              4 (TERMINAL_STATES)
                  CONTAINS_OP              0
                  POP_JUMP_IF_FALSE       11 (to L1)
                  LOAD_FAST                1 (new)
                  LOAD_GLOBAL              4 (TERMINAL_STATES)
                  CONTAINS_OP              1
                  POP_JUMP_IF_FALSE        1 (to L1)
    
     65           RETURN_CONST             2 (False)
    
     66   L1:     LOAD_FAST_LOAD_FAST     50 (new_order, current_order)
                  COMPARE_OP             172 (>=)
                  RETURN_VALUE
    
# --- Nested code object: map_twilio_status ---
    # co_names: ('TWILIO_STATUS_MAP', 'get')
    # co_varnames: ('twilio_status',)
     69           RESUME                   0
    
     70           LOAD_GLOBAL              0 (TWILIO_STATUS_MAP)
                  LOAD_ATTR                3 (get + NULL|self)
                  LOAD_FAST                0 (twilio_status)
                  CALL                     1
                  RETURN_VALUE
    
# --- Nested code object: find_user_by_called_number ---
    # co_names: ('select', 'UserNumber', 'where', 'e164', 'status', 'execute', 'scalar_one_or_none')
    # co_varnames: ('db', 'called_e164', 'stmt', 'result')
      77           RETURN_GENERATOR
                   POP_TOP
           L1:     RESUME                   0
    
      80           LOAD_GLOBAL              1 (select + NULL)
                   LOAD_GLOBAL              2 (UserNumber)
                   CALL                     1
                   LOAD_ATTR                5 (where + NULL|self)
    
      81           LOAD_GLOBAL              2 (UserNumber)
                   LOAD_ATTR                6 (e164)
                   LOAD_FAST                1 (called_e164)
                   COMPARE_OP              72 (==)
    
      82           LOAD_GLOBAL              2 (UserNumber)
                   LOAD_ATTR                8 (status)
                   LOAD_CONST               1 ('active')
                   COMPARE_OP              72 (==)
    
      80           CALL                     2
                   STORE_FAST               2 (stmt)
    
      84           LOAD_FAST                0 (db)
                   LOAD_ATTR               11 (execute + NULL|self)
                   LOAD_FAST                2 (stmt)
                   CALL                     1
                   GET_AWAITABLE            0
                   LOAD_CONST               0 (None)
           L2:     SEND                     3 (to L5)
           L3:     YIELD_VALUE              1
           L4:     RESUME                   3
                   JUMP_BACKWARD_NO_INTERRUPT 5 (to L2)
           L5:     END_SEND
                   STORE_FAST               3 (result)
    
      85           LOAD_FAST                3 (result)
                   LOAD_ATTR               13 (scalar_one_or_none + NULL|self)
                   CALL                     0
                   RETURN_VALUE
    
      84   L6:     CLEANUP_THROW
           L7:     JUMP_BACKWARD_NO_INTERRUPT 20 (to L5)
    
      --   L8:     CALL_INTRINSIC_1         3 (INTRINSIC_STOPITERATION_ERROR)
                   RERAISE                  1
    ExceptionTable:
      L1 to L3 -> L8 [0] lasti
      L3 to L4 -> L6 [2]
      L4 to L7 -> L8 [0] lasti
    
# --- Nested code object: create_or_get_call ---
    # DOCSTRING: """Create or return existing call record. Returns (call, created)."""
    # co_names: ('select', 'Call', 'where', 'provider_call_sid', 'execute', 'scalar_one_or_none', 'encrypt_field', 'encode', 'hash_phone', 'extract_last4', 'mask_phone', 'datetime', 'now', 'UTC', 'timedelta', 'add', 'flush')
    # co_varnames: ('db', 'user_id', 'call_sid', 'caller_e164', 'called_e164', 'source_type', 'forwarding_detected', 'forwarding_hint', 'parent_call_sid', 'retention_days', 'agent_id', 'voice_id', 'stmt', 'result', 'existing', 'caller_for_encrypt', 'ciphertext', 'nonce', 'key_version', 'call')
      92            RETURN_GENERATOR
                    POP_TOP
            L1:     RESUME                   0
    
     108            LOAD_GLOBAL              1 (select + NULL)
                    LOAD_GLOBAL              2 (Call)
                    CALL                     1
                    LOAD_ATTR                5 (where + NULL|self)
                    LOAD_GLOBAL              2 (Call)
                    LOAD_ATTR                6 (provider_call_sid)
                    LOAD_FAST                2 (call_sid)
                    COMPARE_OP              72 (==)
                    CALL                     1
                    STORE_FAST              12 (stmt)
    
     109            LOAD_FAST                0 (db)
                    LOAD_ATTR                9 (execute + NULL|self)
                    LOAD_FAST               12 (stmt)
                    CALL                     1
                    GET_AWAITABLE            0
                    LOAD_CONST               1 (None)
            L2:     SEND                     3 (to L5)
            L3:     YIELD_VALUE              1
            L4:     RESUME                   3
                    JUMP_BACKWARD_NO_INTERRUPT 5 (to L2)
            L5:     END_SEND
                    STORE_FAST              13 (result)
    
     110            LOAD_FAST               13 (result)
                    LOAD_ATTR               11 (scalar_one_or_none + NULL|self)
                    CALL                     0
                    STORE_FAST              14 (existing)
    
     111            LOAD_FAST               14 (existing)
                    POP_JUMP_IF_NONE         4 (to L6)
    
     112            LOAD_FAST               14 (existing)
                    LOAD_CONST               2 (False)
                    BUILD_TUPLE              2
                    RETURN_VALUE
    
     114    L6:     LOAD_FAST                3 (caller_e164)
                    COPY                     1
                    TO_BOOL
                    POP_JUMP_IF_TRUE         2 (to L7)
                    POP_TOP
                    LOAD_CONST               3 ('anonymous')
            L7:     STORE_FAST              15 (caller_for_encrypt)
    
     115            LOAD_GLOBAL             13 (encrypt_field + NULL)
                    LOAD_FAST               15 (caller_for_encrypt)
                    LOAD_ATTR               15 (encode + NULL|self)
                    LOAD_CONST               4 ('utf-8')
                    CALL                     1
                    CALL                     1
                    UNPACK_SEQUENCE          3
                    STORE_FAST              16 (ciphertext)
                    STORE_FAST              17 (nonce)
                    STORE_FAST              18 (key_version)
    
     117            LOAD_GLOBAL              3 (Call + NULL)
                    LOAD_CONST              34 (())
                    BUILD_MAP                0
                    LOAD_CONST               5 ('owner_user_id')
    
     118            LOAD_FAST                1 (user_id)
                    MAP_ADD                  1
    
     117            LOAD_CONST               6 ('source_type')
    
     119            LOAD_FAST                5 (source_type)
                    MAP_ADD                  1
    
     117            LOAD_CONST               7 ('direction')
    
     120            LOAD_CONST               8 ('inbound')
                    MAP_ADD                  1
    
     117            LOAD_CONST               9 ('status')
    
     121            LOAD_CONST              10 ('inbound_received')
                    MAP_ADD                  1
    
     117            LOAD_CONST              11 ('caller_phone_ciphertext')
    
     122            LOAD_FAST               16 (ciphertext)
                    MAP_ADD                  1
    
     117            LOAD_CONST              12 ('caller_phone_nonce')
    
     123            LOAD_FAST               17 (nonce)
                    MAP_ADD                  1
    
     117            LOAD_CONST              13 ('caller_phone_key_version')
    
     124            LOAD_FAST               18 (key_version)
                    MAP_ADD                  1
    
     117            LOAD_CONST              14 ('caller_phone_hash')
    
     125            LOAD_GLOBAL             17 (hash_phone + NULL)
                    LOAD_FAST               15 (caller_for_encrypt)
                    CALL                     1
                    MAP_ADD                  1
    
     117            LOAD_CONST              15 ('caller_phone_last4')
    
     126            LOAD_GLOBAL             19 (extract_last4 + NULL)
                    LOAD_FAST               15 (caller_for_encrypt)
                    CALL                     1
                    MAP_ADD                  1
    
     117            LOAD_CONST              16 ('caller_display')
    
     127            LOAD_CONST               1 (None)
                    MAP_ADD                  1
    
     117            LOAD_CONST              17 ('provider')
    
     128            LOAD_CONST              18 ('twilio')
                    MAP_ADD                  1
    
     117            LOAD_CONST              19 ('provider_call_sid')
    
     129            LOAD_FAST                2 (call_sid)
                    MAP_ADD                  1
    
     117            LOAD_CONST              20 ('provider_parent_call_sid')
    
     130            LOAD_FAST                8 (parent_call_sid)
                    MAP_ADD                  1
    
     117            LOAD_CONST              21 ('forwarding_detected')
    
     131            LOAD_FAST                6 (forwarding_detected)
                    MAP_ADD                  1
    
     117            LOAD_CONST              22 ('forwarding_verification_hint')
    
     132            LOAD_FAST                7 (forwarding_hint)
                    MAP_ADD                  1
    
     117            LOAD_CONST              23 ('missing_summary')
    
     133            LOAD_CONST              24 (True)
                    MAP_ADD                  1
    
     117            LOAD_CONST              25 ('missing_transcript')
    
     134            LOAD_CONST              24 (True)
                    MAP_ADD                  1
    
     117            LOAD_CONST              26 ('missing_labels')
    
     135            LOAD_CONST              24 (True)
                    MAP_ADD                  1
    
     117            LOAD_CONST              27 ('from_masked')
    
     136            LOAD_FAST                3 (caller_e164)
                    TO_BOOL
                    POP_JUMP_IF_FALSE       11 (to L8)
                    LOAD_GLOBAL             21 (mask_phone + NULL)
                    LOAD_FAST                3 (caller_e164)
                    CALL                     1
                    JUMP_FORWARD             1 (to L9)
            L8:     LOAD_CONST              28 ('Unknown')
    
      --    L9:     MAP_ADD                  1
    
     117            LOAD_CONST              29 ('to_masked')
    
     137            LOAD_FAST                4 (called_e164)
                    TO_BOOL
                    POP_JUMP_IF_FALSE       11 (to L10)
                    LOAD_GLOBAL             21 (mask_phone + NULL)
                    LOAD_FAST                4 (called_e164)
                    CALL                     1
                    JUMP_FORWARD             1 (to L11)
           L10:     LOAD_CONST              28 ('Unknown')
    
      --   L11:     MAP_ADD                  1
    
     117            LOAD_CONST              30 ('retention_expires_at')
    
     138            LOAD_GLOBAL             22 (datetime)
                    LOAD_ATTR               24 (now)
                    PUSH_NULL
                    LOAD_GLOBAL             26 (UTC)
                    CALL                     1
                    LOAD_GLOBAL             29 (timedelta + NULL)
                    LOAD_FAST                9 (retention_days)
                    LOAD_CONST              31 (('days',))
                    CALL_KW                  1
                    BINARY_OP                0 (+)
                    MAP_ADD                  1
    
     117            LOAD_CONST              32 ('agent_id')
    
     139            LOAD_FAST               10 (agent_id)
                    MAP_ADD                  1
    
     117            LOAD_CONST              33 ('voice_id')
    
     140            LOAD_FAST               11 (voice_id)
                    MAP_ADD                  1
    
     117            CALL_FUNCTION_EX         1
                    STORE_FAST              19 (call)
    
     142            LOAD_FAST                0 (db)
                    LOAD_ATTR               31 (add + NULL|self)
                    LOAD_FAST               19 (call)
                    CALL                     1
                    POP_TOP
    
     143            LOAD_FAST                0 (db)
                    LOAD_ATTR               33 (flush + NULL|self)
                    CALL                     0
                    GET_AWAITABLE            0
                    LOAD_CONST               1 (None)
           L12:     SEND                     3 (to L15)
           L13:     YIELD_VALUE              1
           L14:     RESUME                   3
                    JUMP_BACKWARD_NO_INTERRUPT 5 (to L12)
           L15:     END_SEND
                    POP_TOP
    
     144            LOAD_FAST               19 (call)
                    LOAD_CONST              24 (True)
                    BUILD_TUPLE              2
                    RETURN_VALUE
    
     109   L16:     CLEANUP_THROW
           L17:     EXTENDED_ARG             1
                    JUMP_BACKWARD_NO_INTERRUPT 280 (to L5)
    
     143   L18:     CLEANUP_THROW
           L19:     JUMP_BACKWARD_NO_INTERRUPT 11 (to L15)
    
      --   L20:     CALL_INTRINSIC_1         3 (INTRINSIC_STOPITERATION_ERROR)
                    RERAISE                  1
    ExceptionTable:
      L1 to L3 -> L20 [0] lasti
      L3 to L4 -> L16 [2]
      L4 to L13 -> L20 [0] lasti
      L13 to L14 -> L18 [2]
      L14 to L17 -> L20 [0] lasti
      L18 to L19 -> L20 [0] lasti
    
# --- Nested code object: transition_call_status ---
    # DOCSTRING: """Transition call status and insert a call_event. Returns None if duplicate."""
    # co_names: ('is_valid_transition', 'status', 'logger', 'info', 'id', 'execute', 'select', 'CallEvent', 'where', 'call_id', 'event_type', 'provider_status', 'scalar_one_or_none', 'debug', 'ended_at', 'duration_seconds', 'owner_user_id', 'add', 'flush')
    # co_varnames: ('db', 'call', 'new_status', 'provider_status', 'event_type', 'event_details', 'ended_at', 'duration_seconds', 'existing', 'event')
     151            RETURN_GENERATOR
                    POP_TOP
            L1:     RESUME                   0
    
     163            LOAD_GLOBAL              1 (is_valid_transition + NULL)
                    LOAD_FAST                1 (call)
                    LOAD_ATTR                2 (status)
                    LOAD_FAST                2 (new_status)
                    CALL                     2
                    TO_BOOL
                    POP_JUMP_IF_TRUE        44 (to L2)
    
     164            LOAD_GLOBAL              4 (logger)
                    LOAD_ATTR                7 (info + NULL|self)
    
     165            LOAD_CONST               1 ('Ignoring invalid transition %s -> %s for call %s')
    
     166            LOAD_FAST                1 (call)
                    LOAD_ATTR                2 (status)
                    LOAD_FAST_LOAD_FAST     33 (new_status, call)
                    LOAD_ATTR                8 (id)
    
     164            CALL                     4
                    POP_TOP
    
     168            RETURN_CONST             2 (None)
    
     171    L2:     LOAD_FAST                0 (db)
                    LOAD_ATTR               11 (execute + NULL|self)
    
     172            LOAD_GLOBAL             13 (select + NULL)
                    LOAD_GLOBAL             14 (CallEvent)
                    CALL                     1
                    LOAD_ATTR               17 (where + NULL|self)
    
     173            LOAD_GLOBAL             14 (CallEvent)
                    LOAD_ATTR               18 (call_id)
                    LOAD_FAST                1 (call)
                    LOAD_ATTR                8 (id)
                    COMPARE_OP              72 (==)
    
     174            LOAD_GLOBAL             14 (CallEvent)
                    LOAD_ATTR               20 (event_type)
                    LOAD_FAST                4 (event_type)
                    COMPARE_OP              72 (==)
    
     175            LOAD_GLOBAL             14 (CallEvent)
                    LOAD_ATTR               22 (provider_status)
                    LOAD_FAST                3 (provider_status)
                    COMPARE_OP              72 (==)
    
     172            CALL                     3
    
     171            CALL                     1
                    GET_AWAITABLE            0
                    LOAD_CONST               2 (None)
            L3:     SEND                     3 (to L6)
            L4:     YIELD_VALUE              1
            L5:     RESUME                   3
                    JUMP_BACKWARD_NO_INTERRUPT 5 (to L3)
            L6:     END_SEND
    
     178            LOAD_ATTR               25 (scalar_one_or_none + NULL|self)
                    CALL                     0
    
     170            STORE_FAST               8 (existing)
    
     179            LOAD_FAST                8 (existing)
                    POP_JUMP_IF_NONE        33 (to L7)
    
     180            LOAD_GLOBAL              4 (logger)
                    LOAD_ATTR               27 (debug + NULL|self)
                    LOAD_CONST               3 ('Duplicate call event ignored for call %s')
                    LOAD_FAST                1 (call)
                    LOAD_ATTR                8 (id)
                    CALL                     2
                    POP_TOP
    
     181            RETURN_CONST             2 (None)
    
     183    L7:     LOAD_FAST_LOAD_FAST     33 (new_status, call)
                    STORE_ATTR               1 (status)
    
     184            LOAD_FAST                6 (ended_at)
                    POP_JUMP_IF_NONE         6 (to L8)
    
     185            LOAD_FAST_LOAD_FAST     97 (ended_at, call)
                    STORE_ATTR              14 (ended_at)
    
     186    L8:     LOAD_FAST                7 (duration_seconds)
                    POP_JUMP_IF_NONE         6 (to L9)
    
     187            LOAD_FAST_LOAD_FAST    113 (duration_seconds, call)
                    STORE_ATTR              15 (duration_seconds)
    
     189    L9:     LOAD_GLOBAL             15 (CallEvent + NULL)
    
     190            LOAD_FAST                1 (call)
                    LOAD_ATTR                8 (id)
    
     191            LOAD_FAST                1 (call)
                    LOAD_ATTR               32 (owner_user_id)
    
     192            LOAD_FAST                4 (event_type)
    
     193            LOAD_FAST                3 (provider_status)
    
     194            LOAD_FAST                5 (event_details)
    
     189            LOAD_CONST               4 (('call_id', 'owner_user_id', 'event_type', 'provider_status', 'details_redacted'))
                    CALL_KW                  5
                    STORE_FAST               9 (event)
    
     196            LOAD_FAST                0 (db)
                    LOAD_ATTR               35 (add + NULL|self)
                    LOAD_FAST                9 (event)
                    CALL                     1
                    POP_TOP
    
     197            LOAD_FAST                0 (db)
                    LOAD_ATTR               37 (flush + NULL|self)
                    CALL                     0
                    GET_AWAITABLE            0
                    LOAD_CONST               2 (None)
           L10:     SEND                     3 (to L13)
           L11:     YIELD_VALUE              1
           L12:     RESUME                   3
                    JUMP_BACKWARD_NO_INTERRUPT 5 (to L10)
           L13:     END_SEND
                    POP_TOP
    
     199            LOAD_FAST                9 (event)
                    RETURN_VALUE
    
     171   L14:     CLEANUP_THROW
           L15:     JUMP_BACKWARD_NO_INTERRUPT 154 (to L6)
    
     197   L16:     CLEANUP_THROW
           L17:     JUMP_BACKWARD_NO_INTERRUPT 8 (to L13)
    
      --   L18:     CALL_INTRINSIC_1         3 (INTRINSIC_STOPITERATION_ERROR)
                    RERAISE                  1
    ExceptionTable:
      L1 to L4 -> L18 [0] lasti
      L4 to L5 -> L14 [2]
      L5 to L11 -> L18 [0] lasti
      L11 to L12 -> L16 [2]
      L12 to L15 -> L18 [0] lasti
      L16 to L17 -> L18 [0] lasti
    
# --- Nested code object: record_provider_event ---
    # co_names: ('compute_payload_hash', 'redact_twilio_params', 'ProviderEvent', 'add', 'flush')
    # co_varnames: ('db', 'provider', 'event_type', 'call_sid', 'raw_params', 'signature_valid', 'call_id', 'owner_user_id', 'payload_hash', 'redacted', 'pe')
     206           RETURN_GENERATOR
                   POP_TOP
           L1:     RESUME                   0
    
     217           LOAD_GLOBAL              1 (compute_payload_hash + NULL)
                   LOAD_FAST                4 (raw_params)
                   CALL                     1
                   STORE_FAST               8 (payload_hash)
    
     218           LOAD_GLOBAL              3 (redact_twilio_params + NULL)
                   LOAD_FAST                4 (raw_params)
                   CALL                     1
                   STORE_FAST               9 (redacted)
    
     220           LOAD_GLOBAL              5 (ProviderEvent + NULL)
    
     221           LOAD_FAST                1 (provider)
    
     222           LOAD_FAST                3 (call_sid)
    
     223           LOAD_FAST                2 (event_type)
    
     224           LOAD_FAST                8 (payload_hash)
    
     225           LOAD_FAST                9 (redacted)
    
     226           LOAD_FAST                5 (signature_valid)
    
     227           LOAD_FAST                6 (call_id)
    
     228           LOAD_FAST                7 (owner_user_id)
    
     229           LOAD_CONST               1 ('received')
    
     220           LOAD_CONST               2 (('provider', 'provider_call_sid', 'event_type', 'payload_hash', 'payload_redacted', 'signature_valid', 'call_id', 'owner_user_id', 'process_status'))
                   CALL_KW                  9
                   STORE_FAST              10 (pe)
    
     231           LOAD_FAST                0 (db)
                   LOAD_ATTR                7 (add + NULL|self)
                   LOAD_FAST               10 (pe)
                   CALL                     1
                   POP_TOP
    
     232           LOAD_FAST                0 (db)
                   LOAD_ATTR                9 (flush + NULL|self)
                   CALL                     0
                   GET_AWAITABLE            0
                   LOAD_CONST               0 (None)
           L2:     SEND                     3 (to L5)
           L3:     YIELD_VALUE              1
           L4:     RESUME                   3
                   JUMP_BACKWARD_NO_INTERRUPT 5 (to L2)
           L5:     END_SEND
                   POP_TOP
    
     233           LOAD_FAST               10 (pe)
                   RETURN_VALUE
    
     232   L6:     CLEANUP_THROW
           L7:     JUMP_BACKWARD_NO_INTERRUPT 6 (to L5)
    
      --   L8:     CALL_INTRINSIC_1         3 (INTRINSIC_STOPITERATION_ERROR)
                   RERAISE                  1
    ExceptionTable:
      L1 to L3 -> L8 [0] lasti
      L3 to L4 -> L6 [2]
      L4 to L7 -> L8 [0] lasti
    
# --- Nested code object: get_call_for_user ---
    # co_names: ('select', 'Call', 'where', 'id', 'owner_user_id', 'deleted_at', 'is_', 'execute', 'scalar_one_or_none')
    # co_varnames: ('db', 'user_id', 'call_id', 'stmt', 'result')
     240           RETURN_GENERATOR
                   POP_TOP
           L1:     RESUME                   0
    
     243           LOAD_GLOBAL              1 (select + NULL)
                   LOAD_GLOBAL              2 (Call)
                   CALL                     1
                   LOAD_ATTR                5 (where + NULL|self)
    
     244           LOAD_GLOBAL              2 (Call)
                   LOAD_ATTR                6 (id)
                   LOAD_FAST                2 (call_id)
                   COMPARE_OP              72 (==)
    
     245           LOAD_GLOBAL              2 (Call)
                   LOAD_ATTR                8 (owner_user_id)
                   LOAD_FAST                1 (user_id)
                   COMPARE_OP              72 (==)
    
     246           LOAD_GLOBAL              2 (Call)
                   LOAD_ATTR               10 (deleted_at)
                   LOAD_ATTR               13 (is_ + NULL|self)
                   LOAD_CONST               0 (None)
                   CALL                     1
    
     243           CALL                     3
                   STORE_FAST               3 (stmt)
    
     248           LOAD_FAST                0 (db)
                   LOAD_ATTR               15 (execute + NULL|self)
                   LOAD_FAST                3 (stmt)
                   CALL                     1
                   GET_AWAITABLE            0
                   LOAD_CONST               0 (None)
           L2:     SEND                     3 (to L5)
           L3:     YIELD_VALUE              1
           L4:     RESUME                   3
                   JUMP_BACKWARD_NO_INTERRUPT 5 (to L2)
           L5:     END_SEND
                   STORE_FAST               4 (result)
    
     249           LOAD_FAST                4 (result)
                   LOAD_ATTR               17 (scalar_one_or_none + NULL|self)
                   CALL                     0
                   RETURN_VALUE
    
     248   L6:     CLEANUP_THROW
           L7:     JUMP_BACKWARD_NO_INTERRUPT 20 (to L5)
    
      --   L8:     CALL_INTRINSIC_1         3 (INTRINSIC_STOPITERATION_ERROR)
                   RERAISE                  1
    ExceptionTable:
      L1 to L3 -> L8 [0] lasti
      L3 to L4 -> L6 [2]
      L4 to L7 -> L8 [0] lasti
    
# --- Nested code object: list_calls_for_user ---
    # DOCSTRING: """Return (calls, next_cursor, has_more). Cursor is the last item's id."""
    # co_names: ('app.models.call_artifact', 'CallArtifact', 'select', 'Call', 'where', 'owner_user_id', 'deleted_at', 'is_', 'provider_parent_call_sid', 'status', 'source_type', 'started_at', 'duration_seconds', 'from_masked', 'startswith', 'ilike', 'join', 'call_id', 'id', 'transcript_provider_ref', 'isnot', 'transcript_status', 'in_', 'sqlalchemy', 'cast', 'type_coerce', 'sqlalchemy.dialects.postgresql', 'JSONB', 'labels_json', 'labels_status', 'op', 'created_at', 'order_by', 'asc', 'desc', 'limit', 'uuid', 'UUID', 'correlate', 'scalar_subquery', 'ValueError', 'TypeError', 'execute', 'list', 'scalars', 'all', 'len', 'str')
    # co_varnames: ('db', 'user_id', 'cursor', 'limit', 'status', 'source_type', 'date_from', 'date_to', 'duration_min', 'duration_max', 'country_prefix', 'has_recording', 'search', 'label', 'sort_by', 'sort_dir', 'CallArtifact', 'stmt', 'need_artifact_join', 'cast', 'type_coerce', 'JSONB', 'target', 'order_col', 'cursor_id', 'ref_ts', 'result', 'rows', 'has_more', 'next_cursor')
     252            RETURN_GENERATOR
                    POP_TOP
            L1:     RESUME                   0
    
     272            LOAD_CONST               1 (0)
                    LOAD_CONST               2 (('CallArtifact',))
                    IMPORT_NAME              0 (app.models.call_artifact)
                    IMPORT_FROM              1 (CallArtifact)
                    STORE_FAST              16 (CallArtifact)
                    POP_TOP
    
     275            LOAD_GLOBAL              5 (select + NULL)
                    LOAD_GLOBAL              6 (Call)
                    CALL                     1
    
     276            LOAD_ATTR                9 (where + NULL|self)
    
     277            LOAD_GLOBAL              6 (Call)
                    LOAD_ATTR               10 (owner_user_id)
                    LOAD_FAST                1 (user_id)
                    COMPARE_OP              72 (==)
    
     278            LOAD_GLOBAL              6 (Call)
                    LOAD_ATTR               12 (deleted_at)
                    LOAD_ATTR               15 (is_ + NULL|self)
                    LOAD_CONST               3 (None)
                    CALL                     1
    
     279            LOAD_GLOBAL              6 (Call)
                    LOAD_ATTR               16 (provider_parent_call_sid)
                    LOAD_ATTR               15 (is_ + NULL|self)
                    LOAD_CONST               3 (None)
                    CALL                     1
    
     276            CALL                     3
    
     274            STORE_FAST              17 (stmt)
    
     283            LOAD_FAST                4 (status)
                    TO_BOOL
                    POP_JUMP_IF_FALSE       34 (to L2)
    
     284            LOAD_FAST               17 (stmt)
                    LOAD_ATTR                9 (where + NULL|self)
                    LOAD_GLOBAL              6 (Call)
                    LOAD_ATTR               18 (status)
                    LOAD_FAST                4 (status)
                    COMPARE_OP              72 (==)
                    CALL                     1
                    STORE_FAST              17 (stmt)
    
     285    L2:     LOAD_FAST                5 (source_type)
                    TO_BOOL
                    POP_JUMP_IF_FALSE       34 (to L3)
    
     286            LOAD_FAST               17 (stmt)
                    LOAD_ATTR                9 (where + NULL|self)
                    LOAD_GLOBAL              6 (Call)
                    LOAD_ATTR               20 (source_type)
                    LOAD_FAST                5 (source_type)
                    COMPARE_OP              72 (==)
                    CALL                     1
                    STORE_FAST              17 (stmt)
    
     287    L3:     LOAD_FAST                6 (date_from)
                    TO_BOOL
                    POP_JUMP_IF_FALSE       34 (to L4)
    
     288            LOAD_FAST               17 (stmt)
                    LOAD_ATTR                9 (where + NULL|self)
                    LOAD_GLOBAL              6 (Call)
                    LOAD_ATTR               22 (started_at)
                    LOAD_FAST                6 (date_from)
                    COMPARE_OP             172 (>=)
                    CALL                     1
                    STORE_FAST              17 (stmt)
    
     289    L4:     LOAD_FAST                7 (date_to)
                    TO_BOOL
                    POP_JUMP_IF_FALSE       34 (to L5)
    
     290            LOAD_FAST               17 (stmt)
                    LOAD_ATTR                9 (where + NULL|self)
                    LOAD_GLOBAL              6 (Call)
                    LOAD_ATTR               22 (started_at)
                    LOAD_FAST                7 (date_to)
                    COMPARE_OP              42 (<=)
                    CALL                     1
                    STORE_FAST              17 (stmt)
    
     291    L5:     LOAD_FAST                8 (duration_min)
                    POP_JUMP_IF_NONE        34 (to L6)
    
     292            LOAD_FAST               17 (stmt)
                    LOAD_ATTR                9 (where + NULL|self)
                    LOAD_GLOBAL              6 (Call)
                    LOAD_ATTR               24 (duration_seconds)
                    LOAD_FAST                8 (duration_min)
                    COMPARE_OP             172 (>=)
                    CALL                     1
                    STORE_FAST              17 (stmt)
    
     293    L6:     LOAD_FAST                9 (duration_max)
                    POP_JUMP_IF_NONE        34 (to L7)
    
     294            LOAD_FAST               17 (stmt)
                    LOAD_ATTR                9 (where + NULL|self)
                    LOAD_GLOBAL              6 (Call)
                    LOAD_ATTR               24 (duration_seconds)
                    LOAD_FAST                9 (duration_max)
                    COMPARE_OP              42 (<=)
                    CALL                     1
                    STORE_FAST              17 (stmt)
    
     295    L7:     LOAD_FAST               10 (country_prefix)
                    TO_BOOL
                    POP_JUMP_IF_FALSE       46 (to L8)
    
     296            LOAD_FAST               17 (stmt)
                    LOAD_ATTR                9 (where + NULL|self)
                    LOAD_GLOBAL              6 (Call)
                    LOAD_ATTR               26 (from_masked)
                    LOAD_ATTR               29 (startswith + NULL|self)
                    LOAD_FAST               10 (country_prefix)
                    CALL                     1
                    CALL                     1
                    STORE_FAST              17 (stmt)
    
     297    L8:     LOAD_FAST               12 (search)
                    TO_BOOL
                    POP_JUMP_IF_FALSE       50 (to L9)
    
     298            LOAD_FAST               17 (stmt)
                    LOAD_ATTR                9 (where + NULL|self)
                    LOAD_GLOBAL              6 (Call)
                    LOAD_ATTR               26 (from_masked)
                    LOAD_ATTR               31 (ilike + NULL|self)
                    LOAD_CONST               4 ('%')
                    LOAD_FAST               12 (search)
                    FORMAT_SIMPLE
                    LOAD_CONST               4 ('%')
                    BUILD_STRING             3
                    CALL                     1
                    CALL                     1
                    STORE_FAST              17 (stmt)
    
     300    L9:     LOAD_FAST               11 (has_recording)
                    LOAD_CONST               5 (True)
                    IS_OP                    0
                    COPY                     1
                    TO_BOOL
                    POP_JUMP_IF_TRUE         2 (to L10)
                    POP_TOP
                    LOAD_FAST               13 (label)
           L10:     STORE_FAST              18 (need_artifact_join)
    
     301            LOAD_FAST               18 (need_artifact_join)
                    TO_BOOL
                    POP_JUMP_IF_FALSE       45 (to L11)
    
     302            LOAD_FAST               17 (stmt)
                    LOAD_ATTR               33 (join + NULL|self)
                    LOAD_FAST               16 (CallArtifact)
                    LOAD_FAST               16 (CallArtifact)
                    LOAD_ATTR               34 (call_id)
                    LOAD_GLOBAL              6 (Call)
                    LOAD_ATTR               36 (id)
                    COMPARE_OP              72 (==)
                    CALL                     2
                    STORE_FAST              17 (stmt)
    
     304   L11:     LOAD_FAST               11 (has_recording)
                    LOAD_CONST               5 (True)
                    IS_OP                    0
                    POP_JUMP_IF_FALSE       70 (to L12)
    
     305            LOAD_FAST               17 (stmt)
                    LOAD_ATTR                9 (where + NULL|self)
    
     306            LOAD_FAST               16 (CallArtifact)
                    LOAD_ATTR               38 (transcript_provider_ref)
                    LOAD_ATTR               41 (isnot + NULL|self)
                    LOAD_CONST               3 (None)
                    CALL                     1
    
     307            LOAD_FAST               16 (CallArtifact)
                    LOAD_ATTR               42 (transcript_status)
                    LOAD_ATTR               45 (in_ + NULL|self)
                    LOAD_CONST               6 ('ready')
                    LOAD_CONST               7 ('partial')
                    BUILD_LIST               2
                    CALL                     1
    
     305            CALL                     2
                    STORE_FAST              17 (stmt)
    
     310   L12:     LOAD_FAST               13 (label)
                    TO_BOOL
                    POP_JUMP_IF_FALSE      121 (to L13)
    
     311            LOAD_CONST               1 (0)
                    LOAD_CONST               8 (('cast', 'type_coerce'))
                    IMPORT_NAME             23 (sqlalchemy)
                    IMPORT_FROM             24 (cast)
                    STORE_FAST              19 (cast)
                    IMPORT_FROM             25 (type_coerce)
                    STORE_FAST              20 (type_coerce)
                    POP_TOP
    
     312            LOAD_CONST               1 (0)
                    LOAD_CONST               9 (('JSONB',))
                    IMPORT_NAME             26 (sqlalchemy.dialects.postgresql)
                    IMPORT_FROM             27 (JSONB)
                    STORE_FAST              21 (JSONB)
                    POP_TOP
    
     314            LOAD_CONST              10 ('label_name')
                    LOAD_FAST               13 (label)
                    BUILD_MAP                1
                    BUILD_LIST               1
                    STORE_FAST              22 (target)
    
     315            LOAD_FAST               17 (stmt)
                    LOAD_ATTR                9 (where + NULL|self)
    
     316            LOAD_FAST               16 (CallArtifact)
                    LOAD_ATTR               56 (labels_json)
                    LOAD_ATTR               41 (isnot + NULL|self)
                    LOAD_CONST               3 (None)
                    CALL                     1
    
     317            LOAD_FAST               16 (CallArtifact)
                    LOAD_ATTR               58 (labels_status)
                    LOAD_CONST               6 ('ready')
                    COMPARE_OP              72 (==)
    
     318            LOAD_FAST               19 (cast)
                    PUSH_NULL
                    LOAD_FAST               16 (CallArtifact)
                    LOAD_ATTR               56 (labels_json)
                    LOAD_FAST               21 (JSONB)
                    CALL                     2
                    LOAD_ATTR               61 (op + NULL|self)
                    LOAD_CONST              11 ('@>')
                    CALL                     1
                    PUSH_NULL
    
     319            LOAD_FAST               20 (type_coerce)
                    PUSH_NULL
                    LOAD_FAST               22 (target)
                    LOAD_FAST               21 (JSONB)
                    CALL                     2
    
     318            CALL                     1
    
     315            CALL                     3
                    STORE_FAST              17 (stmt)
    
     323   L13:     LOAD_FAST               14 (sort_by)
                    LOAD_CONST              12 ('started_at')
                    COMPARE_OP              88 (bool(==))
                    POP_JUMP_IF_FALSE       16 (to L14)
                    LOAD_GLOBAL              6 (Call)
                    LOAD_ATTR               22 (started_at)
                    JUMP_FORWARD            15 (to L15)
           L14:     LOAD_GLOBAL              6 (Call)
                    LOAD_ATTR               62 (created_at)
           L15:     STORE_FAST              23 (order_col)
    
     326            LOAD_FAST               15 (sort_dir)
                    LOAD_CONST              13 ('asc')
                    COMPARE_OP              88 (bool(==))
                    POP_JUMP_IF_FALSE       31 (to L16)
    
     325            LOAD_FAST               17 (stmt)
                    LOAD_ATTR               65 (order_by + NULL|self)
                    LOAD_FAST               23 (order_col)
                    LOAD_ATTR               67 (asc + NULL|self)
                    CALL                     0
                    CALL                     1
                    JUMP_FORWARD            30 (to L17)
    
     327   L16:     LOAD_FAST               17 (stmt)
                    LOAD_ATTR               65 (order_by + NULL|self)
                    LOAD_FAST               23 (order_col)
                    LOAD_ATTR               69 (desc + NULL|self)
                    CALL                     0
                    CALL                     1
    
     324   L17:     STORE_FAST              17 (stmt)
    
     330            LOAD_FAST               17 (stmt)
                    LOAD_ATTR               71 (limit + NULL|self)
                    LOAD_FAST                3 (limit)
                    LOAD_CONST              14 (1)
                    BINARY_OP                0 (+)
                    CALL                     1
                    STORE_FAST              17 (stmt)
    
     332            LOAD_FAST                2 (cursor)
                    TO_BOOL
                    POP_JUMP_IF_FALSE      143 (to L20)
    
     333   L18:     NOP
    
     334   L19:     LOAD_GLOBAL             72 (uuid)
                    LOAD_ATTR               74 (UUID)
                    PUSH_NULL
                    LOAD_FAST                2 (cursor)
                    CALL                     1
                    STORE_FAST              24 (cursor_id)
    
     336            LOAD_GLOBAL              5 (select + NULL)
                    LOAD_GLOBAL              6 (Call)
                    LOAD_ATTR               62 (created_at)
                    CALL                     1
    
     337            LOAD_ATTR                9 (where + NULL|self)
                    LOAD_GLOBAL              6 (Call)
                    LOAD_ATTR               36 (id)
                    LOAD_FAST               24 (cursor_id)
                    COMPARE_OP              72 (==)
                    CALL                     1
    
     338            LOAD_ATTR               77 (correlate + NULL|self)
                    LOAD_CONST               3 (None)
                    CALL                     1
    
     339            LOAD_ATTR               79 (scalar_subquery + NULL|self)
                    CALL                     0
    
     335            STORE_FAST              25 (ref_ts)
    
     341            LOAD_FAST               17 (stmt)
                    LOAD_ATTR                9 (where + NULL|self)
                    LOAD_GLOBAL              6 (Call)
                    LOAD_ATTR               62 (created_at)
                    LOAD_FAST               25 (ref_ts)
                    COMPARE_OP               2 (<)
                    CALL                     1
                    STORE_FAST              17 (stmt)
    
     345   L20:     LOAD_FAST                0 (db)
                    LOAD_ATTR               85 (execute + NULL|self)
                    LOAD_FAST               17 (stmt)
                    CALL                     1
                    GET_AWAITABLE            0
                    LOAD_CONST               3 (None)
           L21:     SEND                     3 (to L24)
           L22:     YIELD_VALUE              1
           L23:     RESUME                   3
                    JUMP_BACKWARD_NO_INTERRUPT 5 (to L21)
           L24:     END_SEND
                    STORE_FAST              26 (result)
    
     346            LOAD_GLOBAL             87 (list + NULL)
                    LOAD_FAST               26 (result)
                    LOAD_ATTR               89 (scalars + NULL|self)
                    CALL                     0
                    LOAD_ATTR               91 (all + NULL|self)
                    CALL                     0
                    CALL                     1
                    STORE_FAST              27 (rows)
    
     348            LOAD_GLOBAL             93 (len + NULL)
                    LOAD_FAST               27 (rows)
                    CALL                     1
                    LOAD_FAST                3 (limit)
                    COMPARE_OP             132 (>)
                    STORE_FAST              28 (has_more)
    
     349            LOAD_FAST               28 (has_more)
                    TO_BOOL
                    POP_JUMP_IF_FALSE        5 (to L25)
    
     350            LOAD_FAST               27 (rows)
                    LOAD_CONST               3 (None)
                    LOAD_FAST                3 (limit)
                    BINARY_SLICE
                    STORE_FAST              27 (rows)
    
     352   L25:     LOAD_FAST               27 (rows)
                    TO_BOOL
                    POP_JUMP_IF_FALSE       31 (to L26)
                    LOAD_FAST               28 (has_more)
                    TO_BOOL
                    POP_JUMP_IF_FALSE       24 (to L26)
                    LOAD_GLOBAL             95 (str + NULL)
                    LOAD_FAST               27 (rows)
                    LOAD_CONST              15 (-1)
                    BINARY_SUBSCR
                    LOAD_ATTR               36 (id)
                    CALL                     1
                    JUMP_FORWARD             1 (to L27)
           L26:     LOAD_CONST               3 (None)
           L27:     STORE_FAST              29 (next_cursor)
    
     353            LOAD_FAST               27 (rows)
                    LOAD_FAST               29 (next_cursor)
                    LOAD_FAST               28 (has_more)
                    BUILD_TUPLE              3
                    RETURN_VALUE
    
      --   L28:     PUSH_EXC_INFO
    
     342            LOAD_GLOBAL             80 (ValueError)
                    LOAD_GLOBAL             82 (TypeError)
                    BUILD_TUPLE              2
                    CHECK_EXC_MATCH
                    POP_JUMP_IF_FALSE        3 (to L30)
                    POP_TOP
    
     343   L29:     POP_EXCEPT
                    JUMP_BACKWARD_NO_INTERRUPT 153 (to L20)
    
     342   L30:     RERAISE                  0
    
      --   L31:     COPY                     3
                    POP_EXCEPT
                    RERAISE                  1
    
     345   L32:     CLEANUP_THROW
           L33:     JUMP_BACKWARD_NO_INTERRUPT 136 (to L24)
    
      --   L34:     CALL_INTRINSIC_1         3 (INTRINSIC_STOPITERATION_ERROR)
                    RERAISE                  1
    ExceptionTable:
      L1 to L18 -> L34 [0] lasti
      L19 to L20 -> L28 [0]
      L20 to L22 -> L34 [0] lasti
      L22 to L23 -> L32 [2]
      L23 to L28 -> L34 [0] lasti
      L28 to L29 -> L31 [1] lasti
      L29 to L30 -> L34 [0] lasti
      L30 to L31 -> L31 [1] lasti
      L31 to L33 -> L34 [0] lasti
    
# --- Nested code object: get_call_events ---
    # co_names: ('select', 'CallEvent', 'where', 'call_id', 'owner_user_id', 'order_by', 'event_at', 'asc', 'execute', 'list', 'scalars', 'all')
    # co_varnames: ('db', 'call_id', 'user_id', 'stmt', 'result')
     356           RETURN_GENERATOR
                   POP_TOP
           L1:     RESUME                   0
    
     360           LOAD_GLOBAL              1 (select + NULL)
                   LOAD_GLOBAL              2 (CallEvent)
                   CALL                     1
    
     361           LOAD_ATTR                5 (where + NULL|self)
    
     362           LOAD_GLOBAL              2 (CallEvent)
                   LOAD_ATTR                6 (call_id)
                   LOAD_FAST                1 (call_id)
                   COMPARE_OP              72 (==)
    
     363           LOAD_GLOBAL              2 (CallEvent)
                   LOAD_ATTR                8 (owner_user_id)
                   LOAD_FAST                2 (user_id)
                   COMPARE_OP              72 (==)
    
     361           CALL                     2
    
     365           LOAD_ATTR               11 (order_by + NULL|self)
                   LOAD_GLOBAL              2 (CallEvent)
                   LOAD_ATTR               12 (event_at)
                   LOAD_ATTR               15 (asc + NULL|self)
                   CALL                     0
                   CALL                     1
    
     359           STORE_FAST               3 (stmt)
    
     367           LOAD_FAST                0 (db)
                   LOAD_ATTR               17 (execute + NULL|self)
                   LOAD_FAST                3 (stmt)
                   CALL                     1
                   GET_AWAITABLE            0
                   LOAD_CONST               0 (None)
           L2:     SEND                     3 (to L5)
           L3:     YIELD_VALUE              1
           L4:     RESUME                   3
                   JUMP_BACKWARD_NO_INTERRUPT 5 (to L2)
           L5:     END_SEND
                   STORE_FAST               4 (result)
    
     368           LOAD_GLOBAL             19 (list + NULL)
                   LOAD_FAST                4 (result)
                   LOAD_ATTR               21 (scalars + NULL|self)
                   CALL                     0
                   LOAD_ATTR               23 (all + NULL|self)
                   CALL                     0
                   CALL                     1
                   RETURN_VALUE
    
     367   L6:     CLEANUP_THROW
           L7:     JUMP_BACKWARD_NO_INTERRUPT 43 (to L5)
    
      --   L8:     CALL_INTRINSIC_1         3 (INTRINSIC_STOPITERATION_ERROR)
                   RERAISE                  1
    ExceptionTable:
      L1 to L3 -> L8 [0] lasti
      L3 to L4 -> L6 [2]
      L4 to L7 -> L8 [0] lasti
    
# --- Nested code object: get_call_by_sid ---
    # co_names: ('select', 'Call', 'where', 'provider_call_sid', 'execute', 'scalar_one_or_none')
    # co_varnames: ('db', 'call_sid', 'stmt', 'result')
     371           RETURN_GENERATOR
                   POP_TOP
           L1:     RESUME                   0
    
     372           LOAD_GLOBAL              1 (select + NULL)
                   LOAD_GLOBAL              2 (Call)
                   CALL                     1
                   LOAD_ATTR                5 (where + NULL|self)
                   LOAD_GLOBAL              2 (Call)
                   LOAD_ATTR                6 (provider_call_sid)
                   LOAD_FAST                1 (call_sid)
                   COMPARE_OP              72 (==)
                   CALL                     1
                   STORE_FAST               2 (stmt)
    
     373           LOAD_FAST                0 (db)
                   LOAD_ATTR                9 (execute + NULL|self)
                   LOAD_FAST                2 (stmt)
                   CALL                     1
                   GET_AWAITABLE            0
                   LOAD_CONST               0 (None)
           L2:     SEND                     3 (to L5)
           L3:     YIELD_VALUE              1
           L4:     RESUME                   3
                   JUMP_BACKWARD_NO_INTERRUPT 5 (to L2)
           L5:     END_SEND
                   STORE_FAST               3 (result)
    
     374           LOAD_FAST                3 (result)
                   LOAD_ATTR               11 (scalar_one_or_none + NULL|self)
                   CALL                     0
                   RETURN_VALUE
    
     373   L6:     CLEANUP_THROW
           L7:     JUMP_BACKWARD_NO_INTERRUPT 20 (to L5)
    
      --   L8:     CALL_INTRINSIC_1         3 (INTRINSIC_STOPITERATION_ERROR)
                   RERAISE                  1
    ExceptionTable:
      L1 to L3 -> L8 [0] lasti
      L3 to L4 -> L6 [2]
      L4 to L7 -> L8 [0] lasti
    
# --- Nested code object: soft_delete_call ---
    # DOCSTRING: """Soft-delete a call. Returns True if deleted.

Dependent rows (artifacts, AI sessions) reference calls with ON DELETE
CASCADE and will be purged during the hard-delete phase.  Memory items
confirmed by the user keep their data but lose the call link.
"""
    # co_names: ('get_call_for_user', 'datetime', 'now', 'UTC', 'deleted_at', 'app.models.call_memory_item', 'CallMemoryItem', 'select', 'where', 'source_call_id', 'owner_user_id', 'execute', 'scalars', 'all', 'user_confirmed', 'flush')
    # co_varnames: ('db', 'user_id', 'call_id', 'call', 'now', 'CallMemoryItem', 'memory_stmt', 'memory_items', 'item')
     381            RETURN_GENERATOR
                    POP_TOP
            L1:     RESUME                   0
    
     390            LOAD_GLOBAL              1 (get_call_for_user + NULL)
                    LOAD_FAST_LOAD_FAST      1 (db, user_id)
                    LOAD_FAST                2 (call_id)
                    CALL                     3
                    GET_AWAITABLE            0
                    LOAD_CONST               1 (None)
            L2:     SEND                     3 (to L5)
            L3:     YIELD_VALUE              1
            L4:     RESUME                   3
                    JUMP_BACKWARD_NO_INTERRUPT 5 (to L2)
            L5:     END_SEND
                    STORE_FAST               3 (call)
    
     391            LOAD_FAST                3 (call)
                    POP_JUMP_IF_NOT_NONE     1 (to L6)
    
     392            RETURN_CONST             2 (False)
    
     394    L6:     LOAD_GLOBAL              2 (datetime)
                    LOAD_ATTR                4 (now)
                    PUSH_NULL
                    LOAD_GLOBAL              6 (UTC)
                    CALL                     1
                    STORE_FAST               4 (now)
    
     395            LOAD_FAST_LOAD_FAST     67 (now, call)
                    STORE_ATTR               4 (deleted_at)
    
     397            LOAD_CONST               3 (0)
                    LOAD_CONST               4 (('CallMemoryItem',))
                    IMPORT_NAME              5 (app.models.call_memory_item)
                    IMPORT_FROM              6 (CallMemoryItem)
                    STORE_FAST               5 (CallMemoryItem)
                    POP_TOP
    
     399            LOAD_GLOBAL             15 (select + NULL)
                    LOAD_FAST                5 (CallMemoryItem)
                    CALL                     1
                    LOAD_ATTR               17 (where + NULL|self)
    
     400            LOAD_FAST                5 (CallMemoryItem)
                    LOAD_ATTR               18 (source_call_id)
                    LOAD_FAST                2 (call_id)
                    COMPARE_OP              72 (==)
    
     401            LOAD_FAST                5 (CallMemoryItem)
                    LOAD_ATTR               20 (owner_user_id)
                    LOAD_FAST                1 (user_id)
                    COMPARE_OP              72 (==)
    
     399            CALL                     2
                    STORE_FAST               6 (memory_stmt)
    
     403            LOAD_FAST                0 (db)
                    LOAD_ATTR               23 (execute + NULL|self)
                    LOAD_FAST                6 (memory_stmt)
                    CALL                     1
                    GET_AWAITABLE            0
                    LOAD_CONST               1 (None)
            L7:     SEND                     3 (to L10)
            L8:     YIELD_VALUE              1
            L9:     RESUME                   3
                    JUMP_BACKWARD_NO_INTERRUPT 5 (to L7)
           L10:     END_SEND
                    LOAD_ATTR               25 (scalars + NULL|self)
                    CALL                     0
                    LOAD_ATTR               27 (all + NULL|self)
                    CALL                     0
                    STORE_FAST               7 (memory_items)
    
     404            LOAD_FAST                7 (memory_items)
                    GET_ITER
           L11:     FOR_ITER                35 (to L13)
                    STORE_FAST               8 (item)
    
     405            LOAD_FAST                8 (item)
                    LOAD_ATTR               28 (user_confirmed)
                    TO_BOOL
                    POP_JUMP_IF_FALSE        9 (to L12)
    
     406            LOAD_CONST               1 (None)
                    LOAD_FAST                8 (item)
                    STORE_ATTR               9 (source_call_id)
                    JUMP_BACKWARD           29 (to L11)
    
     408   L12:     LOAD_FAST_LOAD_FAST     72 (now, item)
                    STORE_ATTR               4 (deleted_at)
                    JUMP_BACKWARD           37 (to L11)
    
     404   L13:     END_FOR
                    POP_TOP
    
     410            LOAD_FAST                0 (db)
                    LOAD_ATTR               31 (flush + NULL|self)
                    CALL                     0
                    GET_AWAITABLE            0
                    LOAD_CONST               1 (None)
           L14:     SEND                     3 (to L17)
           L15:     YIELD_VALUE              1
           L16:     RESUME                   3
                    JUMP_BACKWARD_NO_INTERRUPT 5 (to L14)
           L17:     END_SEND
                    POP_TOP
    
     411            RETURN_CONST             5 (True)
    
     390   L18:     CLEANUP_THROW
           L19:     JUMP_BACKWARD_NO_INTERRUPT 218 (to L5)
    
     403   L20:     CLEANUP_THROW
           L21:     JUMP_BACKWARD_NO_INTERRUPT 100 (to L10)
    
     410   L22:     CLEANUP_THROW
           L23:     JUMP_BACKWARD_NO_INTERRUPT 9 (to L17)
    
      --   L24:     CALL_INTRINSIC_1         3 (INTRINSIC_STOPITERATION_ERROR)
                    RERAISE                  1
    ExceptionTable:
      L1 to L3 -> L24 [0] lasti
      L3 to L4 -> L18 [2]
      L4 to L8 -> L24 [0] lasti
      L8 to L9 -> L20 [2]
      L9 to L15 -> L24 [0] lasti
      L15 to L16 -> L22 [2]
      L16 to L19 -> L24 [0] lasti
      L20 to L21 -> L24 [0] lasti
      L22 to L23 -> L24 [0] lasti
    
# --- Nested code object: soft_delete_all_calls ---
    # DOCSTRING: """Soft-delete all calls for a user. Returns count of deleted calls."""
    # co_names: ('sqlalchemy', 'func', 'update', 'app.models.call_memory_item', 'CallMemoryItem', 'datetime', 'now', 'UTC', 'select', 'count', 'select_from', 'Call', 'where', 'owner_user_id', 'deleted_at', 'is_', 'execute', 'scalar', 'values', 'user_confirmed', 'flush')
    # co_varnames: ('db', 'user_id', 'sa_func', 'sa_update', 'CallMemoryItem', 'now', 'count_stmt', 'count')
     414            RETURN_GENERATOR
                    POP_TOP
            L1:     RESUME                   0
    
     418            LOAD_CONST               1 (0)
                    LOAD_CONST               2 (('func',))
                    IMPORT_NAME              0 (sqlalchemy)
                    IMPORT_FROM              1 (func)
                    STORE_FAST               2 (sa_func)
                    POP_TOP
    
     419            LOAD_CONST               1 (0)
                    LOAD_CONST               3 (('update',))
                    IMPORT_NAME              0 (sqlalchemy)
                    IMPORT_FROM              2 (update)
                    STORE_FAST               3 (sa_update)
                    POP_TOP
    
     421            LOAD_CONST               1 (0)
                    LOAD_CONST               4 (('CallMemoryItem',))
                    IMPORT_NAME              3 (app.models.call_memory_item)
                    IMPORT_FROM              4 (CallMemoryItem)
                    STORE_FAST               4 (CallMemoryItem)
                    POP_TOP
    
     423            LOAD_GLOBAL             10 (datetime)
                    LOAD_ATTR               12 (now)
                    PUSH_NULL
                    LOAD_GLOBAL             14 (UTC)
                    CALL                     1
                    STORE_FAST               5 (now)
    
     426            LOAD_GLOBAL             17 (select + NULL)
                    LOAD_FAST                2 (sa_func)
                    LOAD_ATTR               19 (count + NULL|self)
                    CALL                     0
                    CALL                     1
    
     427            LOAD_ATTR               21 (select_from + NULL|self)
                    LOAD_GLOBAL             22 (Call)
                    CALL                     1
    
     428            LOAD_ATTR               25 (where + NULL|self)
                    LOAD_GLOBAL             22 (Call)
                    LOAD_ATTR               26 (owner_user_id)
                    LOAD_FAST                1 (user_id)
                    COMPARE_OP              72 (==)
                    LOAD_GLOBAL             22 (Call)
                    LOAD_ATTR               28 (deleted_at)
                    LOAD_ATTR               31 (is_ + NULL|self)
                    LOAD_CONST               5 (None)
                    CALL                     1
                    CALL                     2
    
     425            STORE_FAST               6 (count_stmt)
    
     430            LOAD_FAST                0 (db)
                    LOAD_ATTR               33 (execute + NULL|self)
                    LOAD_FAST                6 (count_stmt)
                    CALL                     1
                    GET_AWAITABLE            0
                    LOAD_CONST               5 (None)
            L2:     SEND                     3 (to L5)
            L3:     YIELD_VALUE              1
            L4:     RESUME                   3
                    JUMP_BACKWARD_NO_INTERRUPT 5 (to L2)
            L5:     END_SEND
                    LOAD_ATTR               35 (scalar + NULL|self)
                    CALL                     0
                    COPY                     1
                    TO_BOOL
                    POP_JUMP_IF_TRUE         2 (to L6)
                    POP_TOP
                    LOAD_CONST               1 (0)
            L6:     STORE_FAST               7 (count)
    
     432            LOAD_FAST                0 (db)
                    LOAD_ATTR               33 (execute + NULL|self)
    
     433            LOAD_FAST                3 (sa_update)
                    PUSH_NULL
                    LOAD_GLOBAL             22 (Call)
                    CALL                     1
    
     434            LOAD_ATTR               25 (where + NULL|self)
                    LOAD_GLOBAL             22 (Call)
                    LOAD_ATTR               26 (owner_user_id)
                    LOAD_FAST                1 (user_id)
                    COMPARE_OP              72 (==)
                    LOAD_GLOBAL             22 (Call)
                    LOAD_ATTR               28 (deleted_at)
                    LOAD_ATTR               31 (is_ + NULL|self)
                    LOAD_CONST               5 (None)
                    CALL                     1
                    CALL                     2
    
     435            LOAD_ATTR               37 (values + NULL|self)
                    LOAD_FAST                5 (now)
                    LOAD_CONST               6 (('deleted_at',))
                    CALL_KW                  1
    
     432            CALL                     1
                    GET_AWAITABLE            0
                    LOAD_CONST               5 (None)
            L7:     SEND                     3 (to L10)
            L8:     YIELD_VALUE              1
            L9:     RESUME                   3
                    JUMP_BACKWARD_NO_INTERRUPT 5 (to L7)
           L10:     END_SEND
                    POP_TOP
    
     438            LOAD_FAST                7 (count)
                    TO_BOOL
                    POP_JUMP_IF_FALSE      222 (to L19)
    
     439            LOAD_FAST                0 (db)
                    LOAD_ATTR               33 (execute + NULL|self)
    
     440            LOAD_FAST                3 (sa_update)
                    PUSH_NULL
                    LOAD_FAST                4 (CallMemoryItem)
                    CALL                     1
    
     441            LOAD_ATTR               25 (where + NULL|self)
    
     442            LOAD_FAST                4 (CallMemoryItem)
                    LOAD_ATTR               26 (owner_user_id)
                    LOAD_FAST                1 (user_id)
                    COMPARE_OP              72 (==)
    
     443            LOAD_FAST                4 (CallMemoryItem)
                    LOAD_ATTR               38 (user_confirmed)
                    LOAD_ATTR               31 (is_ + NULL|self)
                    LOAD_CONST               7 (False)
                    CALL                     1
    
     444            LOAD_FAST                4 (CallMemoryItem)
                    LOAD_ATTR               28 (deleted_at)
                    LOAD_ATTR               31 (is_ + NULL|self)
                    LOAD_CONST               5 (None)
                    CALL                     1
    
     441            CALL                     3
    
     446            LOAD_ATTR               37 (values + NULL|self)
                    LOAD_FAST                5 (now)
                    LOAD_CONST               6 (('deleted_at',))
                    CALL_KW                  1
    
     439            CALL                     1
                    GET_AWAITABLE            0
                    LOAD_CONST               5 (None)
           L11:     SEND                     3 (to L14)
           L12:     YIELD_VALUE              1
           L13:     RESUME                   3
                    JUMP_BACKWARD_NO_INTERRUPT 5 (to L11)
           L14:     END_SEND
                    POP_TOP
    
     448            LOAD_FAST                0 (db)
                    LOAD_ATTR               33 (execute + NULL|self)
    
     449            LOAD_FAST                3 (sa_update)
                    PUSH_NULL
                    LOAD_FAST                4 (CallMemoryItem)
                    CALL                     1
    
     450            LOAD_ATTR               25 (where + NULL|self)
    
     451            LOAD_FAST                4 (CallMemoryItem)
                    LOAD_ATTR               26 (owner_user_id)
                    LOAD_FAST                1 (user_id)
                    COMPARE_OP              72 (==)
    
     452            LOAD_FAST                4 (CallMemoryItem)
                    LOAD_ATTR               38 (user_confirmed)
                    LOAD_ATTR               31 (is_ + NULL|self)
                    LOAD_CONST               8 (True)
                    CALL                     1
    
     450            CALL                     2
    
     454            LOAD_ATTR               37 (values + NULL|self)
                    LOAD_CONST               5 (None)
                    LOAD_CONST               9 (('source_call_id',))
                    CALL_KW                  1
    
     448            CALL                     1
                    GET_AWAITABLE            0
                    LOAD_CONST               5 (None)
           L15:     SEND                     3 (to L18)
           L16:     YIELD_VALUE              1
           L17:     RESUME                   3
                    JUMP_BACKWARD_NO_INTERRUPT 5 (to L15)
           L18:     END_SEND
                    POP_TOP
    
     457   L19:     LOAD_FAST                0 (db)
                    LOAD_ATTR               41 (flush + NULL|self)
                    CALL                     0
                    GET_AWAITABLE            0
                    LOAD_CONST               5 (None)
           L20:     SEND                     3 (to L23)
           L21:     YIELD_VALUE              1
           L22:     RESUME                   3
                    JUMP_BACKWARD_NO_INTERRUPT 5 (to L20)
           L23:     END_SEND
                    POP_TOP
    
     458            LOAD_FAST                7 (count)
                    RETURN_VALUE
    
     430   L24:     CLEANUP_THROW
           L25:     EXTENDED_ARG             1
                    JUMP_BACKWARD_NO_INTERRUPT 393 (to L5)
    
     432   L26:     CLEANUP_THROW
           L27:     EXTENDED_ARG             1
                    JUMP_BACKWARD_NO_INTERRUPT 263 (to L10)
    
     439   L28:     CLEANUP_THROW
           L29:     JUMP_BACKWARD_NO_INTERRUPT 134 (to L14)
    
     448   L30:     CLEANUP_THROW
           L31:     JUMP_BACKWARD_NO_INTERRUPT 38 (to L18)
    
     457   L32:     CLEANUP_THROW
           L33:     JUMP_BACKWARD_NO_INTERRUPT 16 (to L23)
    
      --   L34:     CALL_INTRINSIC_1         3 (INTRINSIC_STOPITERATION_ERROR)
                    RERAISE                  1
    ExceptionTable:
      L1 to L3 -> L34 [0] lasti
      L3 to L4 -> L24 [2]
      L4 to L8 -> L34 [0] lasti
      L8 to L9 -> L26 [2]
      L9 to L12 -> L34 [0] lasti
      L12 to L13 -> L28 [2]
      L13 to L16 -> L34 [0] lasti
      L16 to L17 -> L30 [2]
      L17 to L21 -> L34 [0] lasti
      L21 to L22 -> L32 [2]
      L22 to L25 -> L34 [0] lasti
      L26 to L27 -> L34 [0] lasti
      L28 to L29 -> L34 [0] lasti
      L30 to L31 -> L34 [0] lasti
      L32 to L33 -> L34 [0] lasti
    
# co_names: ('__doc__', '__future__', 'annotations', 'logging', 'uuid', 'datetime', 'UTC', 'timedelta', 'sqlalchemy', 'select', 'sqlalchemy.ext.asyncio', 'AsyncSession', 'app.config', 'settings', 'app.core.encryption', 'encrypt_field', 'app.core.twilio_utils', 'compute_payload_hash', 'extract_last4', 'hash_phone', 'mask_phone', 'redact_twilio_params', 'app.models.call', 'Call', 'app.models.call_event', 'CallEvent', 'app.models.provider_event', 'ProviderEvent', 'app.models.user_number', 'UserNumber', 'getLogger', '__name__', 'logger', 'STATE_ORDER', '__annotations__', 'TERMINAL_STATES', 'TWILIO_STATUS_MAP', 'Exception', 'InvalidTransitionError', 'is_valid_transition', 'map_twilio_status', 'find_user_by_called_number', 'DEFAULT_CALL_RETENTION_DAYS', 'create_or_get_call', 'transition_call_status', 'record_provider_event', 'get_call_for_user', 'list_calls_for_user', 'get_call_events', 'get_call_by_sid', 'soft_delete_call', 'soft_delete_all_calls')
# co_varnames: ()
  0           RESUME                   0

  1           SETUP_ANNOTATIONS
              LOAD_CONST               0 ('Call service: state machine, idempotent record creation, provider events.')
              STORE_NAME               0 (__doc__)

  3           LOAD_CONST               1 (0)
              LOAD_CONST               2 (('annotations',))
              IMPORT_NAME              1 (__future__)
              IMPORT_FROM              2 (annotations)
              STORE_NAME               2 (annotations)
              POP_TOP

  5           LOAD_CONST               1 (0)
              LOAD_CONST               3 (None)
              IMPORT_NAME              3 (logging)
              STORE_NAME               3 (logging)

  6           LOAD_CONST               1 (0)
              LOAD_CONST               3 (None)
              IMPORT_NAME              4 (uuid)
              STORE_NAME               4 (uuid)

  7           LOAD_CONST               1 (0)
              LOAD_CONST               4 (('UTC', 'datetime', 'timedelta'))
              IMPORT_NAME              5 (datetime)
              IMPORT_FROM              6 (UTC)
              STORE_NAME               6 (UTC)
              IMPORT_FROM              5 (datetime)
              STORE_NAME               5 (datetime)
              IMPORT_FROM              7 (timedelta)
              STORE_NAME               7 (timedelta)
              POP_TOP

  9           LOAD_CONST               1 (0)
              LOAD_CONST               5 (('select',))
              IMPORT_NAME              8 (sqlalchemy)
              IMPORT_FROM              9 (select)
              STORE_NAME               9 (select)
              POP_TOP

 10           LOAD_CONST               1 (0)
              LOAD_CONST               6 (('AsyncSession',))
              IMPORT_NAME             10 (sqlalchemy.ext.asyncio)
              IMPORT_FROM             11 (AsyncSession)
              STORE_NAME              11 (AsyncSession)
              POP_TOP

 12           LOAD_CONST               1 (0)
              LOAD_CONST               7 (('settings',))
              IMPORT_NAME             12 (app.config)
              IMPORT_FROM             13 (settings)
              STORE_NAME              13 (settings)
              POP_TOP

 13           LOAD_CONST               1 (0)
              LOAD_CONST               8 (('encrypt_field',))
              IMPORT_NAME             14 (app.core.encryption)
              IMPORT_FROM             15 (encrypt_field)
              STORE_NAME              15 (encrypt_field)
              POP_TOP

 14           LOAD_CONST               1 (0)
              LOAD_CONST               9 (('compute_payload_hash', 'extract_last4', 'hash_phone', 'mask_phone', 'redact_twilio_params'))
              IMPORT_NAME             16 (app.core.twilio_utils)
              IMPORT_FROM             17 (compute_payload_hash)
              STORE_NAME              17 (compute_payload_hash)
              IMPORT_FROM             18 (extract_last4)
              STORE_NAME              18 (extract_last4)
              IMPORT_FROM             19 (hash_phone)
              STORE_NAME              19 (hash_phone)
              IMPORT_FROM             20 (mask_phone)
              STORE_NAME              20 (mask_phone)
              IMPORT_FROM             21 (redact_twilio_params)
              STORE_NAME              21 (redact_twilio_params)
              POP_TOP

 21           LOAD_CONST               1 (0)
              LOAD_CONST              10 (('Call',))
              IMPORT_NAME             22 (app.models.call)
              IMPORT_FROM             23 (Call)
              STORE_NAME              23 (Call)
              POP_TOP

 22           LOAD_CONST               1 (0)
              LOAD_CONST              11 (('CallEvent',))
              IMPORT_NAME             24 (app.models.call_event)
              IMPORT_FROM             25 (CallEvent)
              STORE_NAME              25 (CallEvent)
              POP_TOP

 23           LOAD_CONST               1 (0)
              LOAD_CONST              12 (('ProviderEvent',))
              IMPORT_NAME             26 (app.models.provider_event)
              IMPORT_FROM             27 (ProviderEvent)
              STORE_NAME              27 (ProviderEvent)
              POP_TOP

 24           LOAD_CONST               1 (0)
              LOAD_CONST              13 (('UserNumber',))
              IMPORT_NAME             28 (app.models.user_number)
              IMPORT_FROM             29 (UserNumber)
              STORE_NAME              29 (UserNumber)
              POP_TOP

 26           LOAD_NAME                3 (logging)
              LOAD_ATTR               60 (getLogger)
              PUSH_NULL
              LOAD_NAME               31 (__name__)
              CALL                     1
              STORE_NAME              32 (logger)

 33           LOAD_CONST               1 (0)

 34           LOAD_CONST              14 (1)

 35           LOAD_CONST              15 (2)

 36           LOAD_CONST              16 (3)

 37           LOAD_CONST              17 (10)

 38           LOAD_CONST              17 (10)

 39           LOAD_CONST              17 (10)

 40           LOAD_CONST              17 (10)

 32           LOAD_CONST              18 (('created', 'inbound_received', 'twiml_responded', 'in_progress', 'completed', 'partial', 'failed', 'canceled'))
              BUILD_CONST_KEY_MAP      8
              STORE_NAME              33 (STATE_ORDER)
              LOAD_CONST              19 ('dict[str, int]')
              LOAD_NAME               34 (__annotations__)
              LOAD_CONST              20 ('STATE_ORDER')
              STORE_SUBSCR

 43           BUILD_SET                0
              LOAD_CONST              21 (frozenset({'completed', 'partial', 'failed', 'canceled'}))
              SET_UPDATE               1
              STORE_NAME              35 (TERMINAL_STATES)

 46           LOAD_CONST              22 ('created')

 47           LOAD_CONST              23 ('inbound_received')

 48           LOAD_CONST              24 ('in_progress')

 49           LOAD_CONST              25 ('completed')

 50           LOAD_CONST              26 ('failed')

 51           LOAD_CONST              26 ('failed')

 52           LOAD_CONST              26 ('failed')

 53           LOAD_CONST              27 ('canceled')

 45           LOAD_CONST              28 (('queued', 'ringing', 'in-progress', 'completed', 'busy', 'failed', 'no-answer', 'canceled'))
              BUILD_CONST_KEY_MAP      8
              STORE_NAME              36 (TWILIO_STATUS_MAP)
              LOAD_CONST              29 ('dict[str, str]')
              LOAD_NAME               34 (__annotations__)
              LOAD_CONST              30 ('TWILIO_STATUS_MAP')
              STORE_SUBSCR

 57           LOAD_BUILD_CLASS
              PUSH_NULL
              LOAD_CONST              31 (<code object InvalidTransitionError at 0x0000024C0EF0FC90, file "D:\fluence\Github\mattbot\backend\app\services\call_service.py", line 57>)
              MAKE_FUNCTION
              LOAD_CONST              32 ('InvalidTransitionError')
              LOAD_NAME               37 (Exception)
              CALL                     3
              STORE_NAME              38 (InvalidTransitionError)

 61           LOAD_CONST              53 (('current', 'str', 'new', 'str', 'return', 'bool'))
              LOAD_CONST              33 (<code object is_valid_transition at 0x0000024C0EEFB1B0, file "D:\fluence\Github\mattbot\backend\app\services\call_service.py", line 61>)
              MAKE_FUNCTION
              SET_FUNCTION_ATTRIBUTE   4 (annotations)
              STORE_NAME              39 (is_valid_transition)

 69           LOAD_CONST              54 (('twilio_status', 'str', 'return', 'str | None'))
              LOAD_CONST              34 (<code object map_twilio_status at 0x0000024C11423E30, file "D:\fluence\Github\mattbot\backend\app\services\call_service.py", line 69>)
              MAKE_FUNCTION
              SET_FUNCTION_ATTRIBUTE   4 (annotations)
              STORE_NAME              40 (map_twilio_status)

 77           NOP

 78           NOP

 77           NOP

 78           NOP

 77           NOP

 79           NOP

 77           LOAD_CONST              55 (('db', 'AsyncSession', 'called_e164', 'str', 'return', 'UserNumber | None'))
              LOAD_CONST              35 (<code object find_user_by_called_number at 0x0000024C0EC73CF0, file "D:\fluence\Github\mattbot\backend\app\services\call_service.py", line 77>)
              MAKE_FUNCTION
              SET_FUNCTION_ATTRIBUTE   4 (annotations)
              STORE_NAME              41 (find_user_by_called_number)

 99           LOAD_CONST              36 ('dedicated_number')

100           LOAD_CONST              37 (False)

101           LOAD_CONST               3 (None)

102           LOAD_CONST               3 (None)

103           LOAD_NAME               13 (settings)
              LOAD_ATTR               84 (DEFAULT_CALL_RETENTION_DAYS)

104           LOAD_CONST               3 (None)

105           LOAD_CONST               3 (None)

 92           LOAD_CONST              38 (('source_type', 'forwarding_detected', 'forwarding_hint', 'parent_call_sid', 'retention_days', 'agent_id', 'voice_id'))
              BUILD_CONST_KEY_MAP      7

 93           NOP

 92           NOP

 95           NOP

 92           NOP

 96           NOP

 92           NOP

 97           NOP

 92           NOP

 98           NOP

 92           NOP

 99           NOP

 92           NOP

100           NOP

 92           NOP

101           NOP

 92           NOP

102           NOP

 92           NOP

103           NOP

 92           NOP

104           NOP

 92           NOP

105           NOP

 92           NOP

106           NOP

 92           LOAD_CONST              56 (('db', 'AsyncSession', 'user_id', 'uuid.UUID', 'call_sid', 'str', 'caller_e164', 'str', 'called_e164', 'str', 'source_type', 'str', 'forwarding_detected', 'bool', 'forwarding_hint', 'str | None', 'parent_call_sid', 'str | None', 'retention_days', 'int', 'agent_id', 'uuid.UUID | None', 'voice_id', 'uuid.UUID | None', 'return', 'tuple[Call, bool]'))
              LOAD_CONST              39 (<code object create_or_get_call at 0x0000024C0FA659B0, file "D:\fluence\Github\mattbot\backend\app\services\call_service.py", line 92>)
              MAKE_FUNCTION
              SET_FUNCTION_ATTRIBUTE   4 (annotations)
              SET_FUNCTION_ATTRIBUTE   2 (kwdefaults)
              STORE_NAME              43 (create_or_get_call)

156           LOAD_CONST               3 (None)

157           LOAD_CONST              40 ('provider_status_update')

158           LOAD_CONST               3 (None)

159           LOAD_CONST               3 (None)

160           LOAD_CONST               3 (None)

151           LOAD_CONST              41 (('provider_status', 'event_type', 'event_details', 'ended_at', 'duration_seconds'))
              BUILD_CONST_KEY_MAP      5

152           NOP

151           NOP

153           NOP

151           NOP

154           NOP

151           NOP

156           NOP

151           NOP

157           NOP

151           NOP

158           NOP

151           NOP

159           NOP

151           NOP

160           NOP

151           NOP

161           NOP

151           LOAD_CONST              57 (('db', 'AsyncSession', 'call', 'Call', 'new_status', 'str', 'provider_status', 'str | None', 'event_type', 'str', 'event_details', 'dict | None', 'ended_at', 'datetime | None', 'duration_seconds', 'int | None', 'return', 'CallEvent | None'))
              LOAD_CONST              42 (<code object transition_call_status at 0x0000024C0FB5F3D0, file "D:\fluence\Github\mattbot\backend\app\services\call_service.py", line 151>)
              MAKE_FUNCTION
              SET_FUNCTION_ATTRIBUTE   4 (annotations)
              SET_FUNCTION_ATTRIBUTE   2 (kwdefaults)
              STORE_NAME              44 (transition_call_status)

214           LOAD_CONST               3 (None)

215           LOAD_CONST               3 (None)

206           LOAD_CONST              43 (('call_id', 'owner_user_id'))
              BUILD_CONST_KEY_MAP      2

207           NOP

206           NOP

209           NOP

206           NOP

210           NOP

206           NOP

211           NOP

206           NOP

212           NOP

206           NOP

213           NOP

206           NOP

214           NOP

206           NOP

215           NOP

206           NOP

216           NOP

206           LOAD_CONST              58 (('db', 'AsyncSession', 'provider', 'str', 'event_type', 'str', 'call_sid', 'str | None', 'raw_params', 'dict[str, str]', 'signature_valid', 'bool', 'call_id', 'uuid.UUID | None', 'owner_user_id', 'uuid.UUID | None', 'return', 'ProviderEvent'))
              LOAD_CONST              44 (<code object record_provider_event at 0x0000024C0EC47330, file "D:\fluence\Github\mattbot\backend\app\services\call_service.py", line 206>)
              MAKE_FUNCTION
              SET_FUNCTION_ATTRIBUTE   4 (annotations)
              SET_FUNCTION_ATTRIBUTE   2 (kwdefaults)
              STORE_NAME              45 (record_provider_event)

240           NOP

241           NOP

240           NOP

241           NOP

240           NOP

241           NOP

240           NOP

242           NOP

240           LOAD_CONST              59 (('db', 'AsyncSession', 'user_id', 'uuid.UUID', 'call_id', 'uuid.UUID', 'return', 'Call | None'))
              LOAD_CONST              45 (<code object get_call_for_user at 0x0000024C0EC33C40, file "D:\fluence\Github\mattbot\backend\app\services\call_service.py", line 240>)
              MAKE_FUNCTION
              SET_FUNCTION_ATTRIBUTE   4 (annotations)
              STORE_NAME              46 (get_call_for_user)

256           LOAD_CONST               3 (None)

257           LOAD_CONST              46 (20)

258           LOAD_CONST               3 (None)

259           LOAD_CONST               3 (None)

260           LOAD_CONST               3 (None)

261           LOAD_CONST               3 (None)

262           LOAD_CONST               3 (None)

263           LOAD_CONST               3 (None)

264           LOAD_CONST               3 (None)

265           LOAD_CONST               3 (None)

266           LOAD_CONST               3 (None)

267           LOAD_CONST               3 (None)

268           LOAD_CONST               3 (None)

269           LOAD_CONST               3 (None)

252           LOAD_CONST              47 (('cursor', 'limit', 'status', 'source_type', 'date_from', 'date_to', 'duration_min', 'duration_max', 'country_prefix', 'has_recording', 'search', 'label', 'sort_by', 'sort_dir'))
              BUILD_CONST_KEY_MAP     14

253           NOP

252           NOP

254           NOP

252           NOP

256           NOP

252           NOP

257           NOP

252           NOP

258           NOP

252           NOP

259           NOP

252           NOP

260           NOP

252           NOP

261           NOP

252           NOP

262           NOP

252           NOP

263           NOP

252           NOP

264           NOP

252           NOP

265           NOP

252           NOP

266           NOP

252           NOP

267           NOP

252           NOP

268           NOP

252           NOP

269           NOP

252           NOP

270           NOP

252           LOAD_CONST              60 (('db', 'AsyncSession', 'user_id', 'uuid.UUID', 'cursor', 'str | None', 'limit', 'int', 'status', 'str | None', 'source_type', 'str | None', 'date_from', 'datetime | None', 'date_to', 'datetime | None', 'duration_min', 'int | None', 'duration_max', 'int | None', 'country_prefix', 'str | None', 'has_recording', 'bool | None', 'search', 'str | None', 'label', 'str | None', 'sort_by', 'str | None', 'sort_dir', 'str | None', 'return', 'tuple[list[Call], str | None, bool]'))
              LOAD_CONST              48 (<code object list_calls_for_user at 0x0000024C0FCE8050, file "D:\fluence\Github\mattbot\backend\app\services\call_service.py", line 252>)
              MAKE_FUNCTION
              SET_FUNCTION_ATTRIBUTE   4 (annotations)
              SET_FUNCTION_ATTRIBUTE   2 (kwdefaults)
              STORE_NAME              47 (list_calls_for_user)

356           NOP

357           NOP

356           NOP

357           NOP

356           NOP

357           NOP

356           NOP

358           NOP

356           LOAD_CONST              61 (('db', 'AsyncSession', 'call_id', 'uuid.UUID', 'user_id', 'uuid.UUID', 'return', 'list[CallEvent]'))
              LOAD_CONST              49 (<code object get_call_events at 0x0000024C0FEDCCC0, file "D:\fluence\Github\mattbot\backend\app\services\call_service.py", line 356>)
              MAKE_FUNCTION
              SET_FUNCTION_ATTRIBUTE   4 (annotations)
              STORE_NAME              48 (get_call_events)

371           LOAD_CONST              62 (('db', 'AsyncSession', 'call_sid', 'str', 'return', 'Call | None'))
              LOAD_CONST              50 (<code object get_call_by_sid at 0x0000024C11467B90, file "D:\fluence\Github\mattbot\backend\app\services\call_service.py", line 371>)
              MAKE_FUNCTION
              SET_FUNCTION_ATTRIBUTE   4 (annotations)
              STORE_NAME              49 (get_call_by_sid)

381           NOP

382           NOP

381           NOP

382           NOP

381           NOP

382           NOP

381           NOP

383           NOP

381           LOAD_CONST              63 (('db', 'AsyncSession', 'user_id', 'uuid.UUID', 'call_id', 'uuid.UUID', 'return', 'bool'))
              LOAD_CONST              51 (<code object soft_delete_call at 0x0000024C0FBAA650, file "D:\fluence\Github\mattbot\backend\app\services\call_service.py", line 381>)
              MAKE_FUNCTION
              SET_FUNCTION_ATTRIBUTE   4 (annotations)
              STORE_NAME              50 (soft_delete_call)

414           NOP

415           NOP

414           NOP

415           NOP

414           NOP

416           NOP

414           LOAD_CONST              64 (('db', 'AsyncSession', 'user_id', 'uuid.UUID', 'return', 'int'))
              LOAD_CONST              52 (<code object soft_delete_all_calls at 0x0000024C0FB5D150, file "D:\fluence\Github\mattbot\backend\app\services\call_service.py", line 414>)
              MAKE_FUNCTION
              SET_FUNCTION_ATTRIBUTE   4 (annotations)
              STORE_NAME              51 (soft_delete_all_calls)
              RETURN_CONST             3 (None)

Disassembly of <code object InvalidTransitionError at 0x0000024C0EF0FC90, file "D:\fluence\Github\mattbot\backend\app\services\call_service.py", line 57>:
 57           RESUME                   0
              LOAD_NAME                0 (__name__)
              STORE_NAME               1 (__module__)
              LOAD_CONST               0 ('InvalidTransitionError')
              STORE_NAME               2 (__qualname__)
              LOAD_CONST               1 (57)
              STORE_NAME               3 (__firstlineno__)

 58           LOAD_CONST               2 (())
              STORE_NAME               4 (__static_attributes__)
              RETURN_CONST             3 (None)

Disassembly of <code object is_valid_transition at 0x0000024C0EEFB1B0, file "D:\fluence\Github\mattbot\backend\app\services\call_service.py", line 61>:
 61           RESUME                   0

 62           LOAD_GLOBAL              0 (STATE_ORDER)
              LOAD_ATTR                3 (get + NULL|self)
              LOAD_FAST                0 (current)
              LOAD_CONST               1 (0)
              CALL                     2
              STORE_FAST               2 (current_order)

 63           LOAD_GLOBAL              0 (STATE_ORDER)
              LOAD_ATTR                3 (get + NULL|self)
              LOAD_FAST                1 (new)
              LOAD_CONST               1 (0)
              CALL                     2
              STORE_FAST               3 (new_order)

 64           LOAD_FAST                0 (current)
              LOAD_GLOBAL              4 (TERMINAL_STATES)
              CONTAINS_OP              0
              POP_JUMP_IF_FALSE       11 (to L1)
              LOAD_FAST                1 (new)
              LOAD_GLOBAL              4 (TERMINAL_STATES)
              CONTAINS_OP              1
              POP_JUMP_IF_FALSE        1 (to L1)

 65           RETURN_CONST             2 (False)

 66   L1:     LOAD_FAST_LOAD_FAST     50 (new_order, current_order)
              COMPARE_OP             172 (>=)
              RETURN_VALUE

Disassembly of <code object map_twilio_status at 0x0000024C11423E30, file "D:\fluence\Github\mattbot\backend\app\services\call_service.py", line 69>:
 69           RESUME                   0

 70           LOAD_GLOBAL              0 (TWILIO_STATUS_MAP)
              LOAD_ATTR                3 (get + NULL|self)
              LOAD_FAST                0 (twilio_status)
              CALL                     1
              RETURN_VALUE

Disassembly of <code object find_user_by_called_number at 0x0000024C0EC73CF0, file "D:\fluence\Github\mattbot\backend\app\services\call_service.py", line 77>:
  77           RETURN_GENERATOR
               POP_TOP
       L1:     RESUME                   0

  80           LOAD_GLOBAL              1 (select + NULL)
               LOAD_GLOBAL              2 (UserNumber)
               CALL                     1
               LOAD_ATTR                5 (where + NULL|self)

  81           LOAD_GLOBAL              2 (UserNumber)
               LOAD_ATTR                6 (e164)
               LOAD_FAST                1 (called_e164)
               COMPARE_OP              72 (==)

  82           LOAD_GLOBAL              2 (UserNumber)
               LOAD_ATTR                8 (status)
               LOAD_CONST               1 ('active')
               COMPARE_OP              72 (==)

  80           CALL                     2
               STORE_FAST               2 (stmt)

  84           LOAD_FAST                0 (db)
               LOAD_ATTR               11 (execute + NULL|self)
               LOAD_FAST                2 (stmt)
               CALL                     1
               GET_AWAITABLE            0
               LOAD_CONST               0 (None)
       L2:     SEND                     3 (to L5)
       L3:     YIELD_VALUE              1
       L4:     RESUME                   3
               JUMP_BACKWARD_NO_INTERRUPT 5 (to L2)
       L5:     END_SEND
               STORE_FAST               3 (result)

  85           LOAD_FAST                3 (result)
               LOAD_ATTR               13 (scalar_one_or_none + NULL|self)
               CALL                     0
               RETURN_VALUE

  84   L6:     CLEANUP_THROW
       L7:     JUMP_BACKWARD_NO_INTERRUPT 20 (to L5)

  --   L8:     CALL_INTRINSIC_1         3 (INTRINSIC_STOPITERATION_ERROR)
               RERAISE                  1
ExceptionTable:
  L1 to L3 -> L8 [0] lasti
  L3 to L4 -> L6 [2]
  L4 to L7 -> L8 [0] lasti

Disassembly of <code object create_or_get_call at 0x0000024C0FA659B0, file "D:\fluence\Github\mattbot\backend\app\services\call_service.py", line 92>:
  92            RETURN_GENERATOR
                POP_TOP
        L1:     RESUME                   0

 108            LOAD_GLOBAL              1 (select + NULL)
                LOAD_GLOBAL              2 (Call)
                CALL                     1
                LOAD_ATTR                5 (where + NULL|self)
                LOAD_GLOBAL              2 (Call)
                LOAD_ATTR                6 (provider_call_sid)
                LOAD_FAST                2 (call_sid)
                COMPARE_OP              72 (==)
                CALL                     1
                STORE_FAST              12 (stmt)

 109            LOAD_FAST                0 (db)
                LOAD_ATTR                9 (execute + NULL|self)
                LOAD_FAST               12 (stmt)
                CALL                     1
                GET_AWAITABLE            0
                LOAD_CONST               1 (None)
        L2:     SEND                     3 (to L5)
        L3:     YIELD_VALUE              1
        L4:     RESUME                   3
                JUMP_BACKWARD_NO_INTERRUPT 5 (to L2)
        L5:     END_SEND
                STORE_FAST              13 (result)

 110            LOAD_FAST               13 (result)
                LOAD_ATTR               11 (scalar_one_or_none + NULL|self)
                CALL                     0
                STORE_FAST              14 (existing)

 111            LOAD_FAST               14 (existing)
                POP_JUMP_IF_NONE         4 (to L6)

 112            LOAD_FAST               14 (existing)
                LOAD_CONST               2 (False)
                BUILD_TUPLE              2
                RETURN_VALUE

 114    L6:     LOAD_FAST                3 (caller_e164)
                COPY                     1
                TO_BOOL
                POP_JUMP_IF_TRUE         2 (to L7)
                POP_TOP
                LOAD_CONST               3 ('anonymous')
        L7:     STORE_FAST              15 (caller_for_encrypt)

 115            LOAD_GLOBAL             13 (encrypt_field + NULL)
                LOAD_FAST               15 (caller_for_encrypt)
                LOAD_ATTR               15 (encode + NULL|self)
                LOAD_CONST               4 ('utf-8')
                CALL                     1
                CALL                     1
                UNPACK_SEQUENCE          3
                STORE_FAST              16 (ciphertext)
                STORE_FAST              17 (nonce)
                STORE_FAST              18 (key_version)

 117            LOAD_GLOBAL              3 (Call + NULL)
                LOAD_CONST              34 (())
                BUILD_MAP                0
                LOAD_CONST               5 ('owner_user_id')

 118            LOAD_FAST                1 (user_id)
                MAP_ADD                  1

 117            LOAD_CONST               6 ('source_type')

 119            LOAD_FAST                5 (source_type)
                MAP_ADD                  1

 117            LOAD_CONST               7 ('direction')

 120            LOAD_CONST               8 ('inbound')
                MAP_ADD                  1

 117            LOAD_CONST               9 ('status')

 121            LOAD_CONST              10 ('inbound_received')
                MAP_ADD                  1

 117            LOAD_CONST              11 ('caller_phone_ciphertext')

 122            LOAD_FAST               16 (ciphertext)
                MAP_ADD                  1

 117            LOAD_CONST              12 ('caller_phone_nonce')

 123            LOAD_FAST               17 (nonce)
                MAP_ADD                  1

 117            LOAD_CONST              13 ('caller_phone_key_version')

 124            LOAD_FAST               18 (key_version)
                MAP_ADD                  1

 117            LOAD_CONST              14 ('caller_phone_hash')

 125            LOAD_GLOBAL             17 (hash_phone + NULL)
                LOAD_FAST               15 (caller_for_encrypt)
                CALL                     1
                MAP_ADD                  1

 117            LOAD_CONST              15 ('caller_phone_last4')

 126            LOAD_GLOBAL             19 (extract_last4 + NULL)
                LOAD_FAST               15 (caller_for_encrypt)
                CALL                     1
                MAP_ADD                  1

 117            LOAD_CONST              16 ('caller_display')

 127            LOAD_CONST               1 (None)
                MAP_ADD                  1

 117            LOAD_CONST              17 ('provider')

 128            LOAD_CONST              18 ('twilio')
                MAP_ADD                  1

 117            LOAD_CONST              19 ('provider_call_sid')

 129            LOAD_FAST                2 (call_sid)
                MAP_ADD                  1

 117            LOAD_CONST              20 ('provider_parent_call_sid')

 130            LOAD_FAST                8 (parent_call_sid)
                MAP_ADD                  1

 117            LOAD_CONST              21 ('forwarding_detected')

 131            LOAD_FAST                6 (forwarding_detected)
                MAP_ADD                  1

 117            LOAD_CONST              22 ('forwarding_verification_hint')

 132            LOAD_FAST                7 (forwarding_hint)
                MAP_ADD                  1

 117            LOAD_CONST              23 ('missing_summary')

 133            LOAD_CONST              24 (True)
                MAP_ADD                  1

 117            LOAD_CONST              25 ('missing_transcript')

 134            LOAD_CONST              24 (True)
                MAP_ADD                  1

 117            LOAD_CONST              26 ('missing_labels')

 135            LOAD_CONST              24 (True)
                MAP_ADD                  1

 117            LOAD_CONST              27 ('from_masked')

 136            LOAD_FAST                3 (caller_e164)
                TO_BOOL
                POP_JUMP_IF_FALSE       11 (to L8)
                LOAD_GLOBAL             21 (mask_phone + NULL)
                LOAD_FAST                3 (caller_e164)
                CALL                     1
                JUMP_FORWARD             1 (to L9)
        L8:     LOAD_CONST              28 ('Unknown')

  --    L9:     MAP_ADD                  1

 117            LOAD_CONST              29 ('to_masked')

 137            LOAD_FAST                4 (called_e164)
                TO_BOOL
                POP_JUMP_IF_FALSE       11 (to L10)
                LOAD_GLOBAL             21 (mask_phone + NULL)
                LOAD_FAST                4 (called_e164)
                CALL                     1
                JUMP_FORWARD             1 (to L11)
       L10:     LOAD_CONST              28 ('Unknown')

  --   L11:     MAP_ADD                  1

 117            LOAD_CONST              30 ('retention_expires_at')

 138            LOAD_GLOBAL             22 (datetime)
                LOAD_ATTR               24 (now)
                PUSH_NULL
                LOAD_GLOBAL             26 (UTC)
                CALL                     1
                LOAD_GLOBAL             29 (timedelta + NULL)
                LOAD_FAST                9 (retention_days)
                LOAD_CONST              31 (('days',))
                CALL_KW                  1
                BINARY_OP                0 (+)
                MAP_ADD                  1

 117            LOAD_CONST              32 ('agent_id')

 139            LOAD_FAST               10 (agent_id)
                MAP_ADD                  1

 117            LOAD_CONST              33 ('voice_id')

 140            LOAD_FAST               11 (voice_id)
                MAP_ADD                  1

 117            CALL_FUNCTION_EX         1
                STORE_FAST              19 (call)

 142            LOAD_FAST                0 (db)
                LOAD_ATTR               31 (add + NULL|self)
                LOAD_FAST               19 (call)
                CALL                     1
                POP_TOP

 143            LOAD_FAST                0 (db)
                LOAD_ATTR               33 (flush + NULL|self)
                CALL                     0
                GET_AWAITABLE            0
                LOAD_CONST               1 (None)
       L12:     SEND                     3 (to L15)
       L13:     YIELD_VALUE              1
       L14:     RESUME                   3
                JUMP_BACKWARD_NO_INTERRUPT 5 (to L12)
       L15:     END_SEND
                POP_TOP

 144            LOAD_FAST               19 (call)
                LOAD_CONST              24 (True)
                BUILD_TUPLE              2
                RETURN_VALUE

 109   L16:     CLEANUP_THROW
       L17:     EXTENDED_ARG             1
                JUMP_BACKWARD_NO_INTERRUPT 280 (to L5)

 143   L18:     CLEANUP_THROW
       L19:     JUMP_BACKWARD_NO_INTERRUPT 11 (to L15)

  --   L20:     CALL_INTRINSIC_1         3 (INTRINSIC_STOPITERATION_ERROR)
                RERAISE                  1
ExceptionTable:
  L1 to L3 -> L20 [0] lasti
  L3 to L4 -> L16 [2]
  L4 to L13 -> L20 [0] lasti
  L13 to L14 -> L18 [2]
  L14 to L17 -> L20 [0] lasti
  L18 to L19 -> L20 [0] lasti

Disassembly of <code object transition_call_status at 0x0000024C0FB5F3D0, file "D:\fluence\Github\mattbot\backend\app\services\call_service.py", line 151>:
 151            RETURN_GENERATOR
                POP_TOP
        L1:     RESUME                   0

 163            LOAD_GLOBAL              1 (is_valid_transition + NULL)
                LOAD_FAST                1 (call)
                LOAD_ATTR                2 (status)
                LOAD_FAST                2 (new_status)
                CALL                     2
                TO_BOOL
                POP_JUMP_IF_TRUE        44 (to L2)

 164            LOAD_GLOBAL              4 (logger)
                LOAD_ATTR                7 (info + NULL|self)

 165            LOAD_CONST               1 ('Ignoring invalid transition %s -> %s for call %s')

 166            LOAD_FAST                1 (call)
                LOAD_ATTR                2 (status)
                LOAD_FAST_LOAD_FAST     33 (new_status, call)
                LOAD_ATTR                8 (id)

 164            CALL                     4
                POP_TOP

 168            RETURN_CONST             2 (None)

 171    L2:     LOAD_FAST                0 (db)
                LOAD_ATTR               11 (execute + NULL|self)

 172            LOAD_GLOBAL             13 (select + NULL)
                LOAD_GLOBAL             14 (CallEvent)
                CALL                     1
                LOAD_ATTR               17 (where + NULL|self)

 173            LOAD_GLOBAL             14 (CallEvent)
                LOAD_ATTR               18 (call_id)
                LOAD_FAST                1 (call)
                LOAD_ATTR                8 (id)
                COMPARE_OP              72 (==)

 174            LOAD_GLOBAL             14 (CallEvent)
                LOAD_ATTR               20 (event_type)
                LOAD_FAST                4 (event_type)
                COMPARE_OP              72 (==)

 175            LOAD_GLOBAL             14 (CallEvent)
                LOAD_ATTR               22 (provider_status)
                LOAD_FAST                3 (provider_status)
                COMPARE_OP              72 (==)

 172            CALL                     3

 171            CALL                     1
                GET_AWAITABLE            0
                LOAD_CONST               2 (None)
        L3:     SEND                     3 (to L6)
        L4:     YIELD_VALUE              1
        L5:     RESUME                   3
                JUMP_BACKWARD_NO_INTERRUPT 5 (to L3)
        L6:     END_SEND

 178            LOAD_ATTR               25 (scalar_one_or_none + NULL|self)
                CALL                     0

 170            STORE_FAST               8 (existing)

 179            LOAD_FAST                8 (existing)
                POP_JUMP_IF_NONE        33 (to L7)

 180            LOAD_GLOBAL              4 (logger)
                LOAD_ATTR               27 (debug + NULL|self)
                LOAD_CONST               3 ('Duplicate call event ignored for call %s')
                LOAD_FAST                1 (call)
                LOAD_ATTR                8 (id)
                CALL                     2
                POP_TOP

 181            RETURN_CONST             2 (None)

 183    L7:     LOAD_FAST_LOAD_FAST     33 (new_status, call)
                STORE_ATTR               1 (status)

 184            LOAD_FAST                6 (ended_at)
                POP_JUMP_IF_NONE         6 (to L8)

 185            LOAD_FAST_LOAD_FAST     97 (ended_at, call)
                STORE_ATTR              14 (ended_at)

 186    L8:     LOAD_FAST                7 (duration_seconds)
                POP_JUMP_IF_NONE         6 (to L9)

 187            LOAD_FAST_LOAD_FAST    113 (duration_seconds, call)
                STORE_ATTR              15 (duration_seconds)

 189    L9:     LOAD_GLOBAL             15 (CallEvent + NULL)

 190            LOAD_FAST                1 (call)
                LOAD_ATTR                8 (id)

 191            LOAD_FAST                1 (call)
                LOAD_ATTR               32 (owner_user_id)

 192            LOAD_FAST                4 (event_type)

 193            LOAD_FAST                3 (provider_status)

 194            LOAD_FAST                5 (event_details)

 189            LOAD_CONST               4 (('call_id', 'owner_user_id', 'event_type', 'provider_status', 'details_redacted'))
                CALL_KW                  5
                STORE_FAST               9 (event)

 196            LOAD_FAST                0 (db)
                LOAD_ATTR               35 (add + NULL|self)
                LOAD_FAST                9 (event)
                CALL                     1
                POP_TOP

 197            LOAD_FAST                0 (db)
                LOAD_ATTR               37 (flush + NULL|self)
                CALL                     0
                GET_AWAITABLE            0
                LOAD_CONST               2 (None)
       L10:     SEND                     3 (to L13)
       L11:     YIELD_VALUE              1
       L12:     RESUME                   3
                JUMP_BACKWARD_NO_INTERRUPT 5 (to L10)
       L13:     END_SEND
                POP_TOP

 199            LOAD_FAST                9 (event)
                RETURN_VALUE

 171   L14:     CLEANUP_THROW
       L15:     JUMP_BACKWARD_NO_INTERRUPT 154 (to L6)

 197   L16:     CLEANUP_THROW
       L17:     JUMP_BACKWARD_NO_INTERRUPT 8 (to L13)

  --   L18:     CALL_INTRINSIC_1         3 (INTRINSIC_STOPITERATION_ERROR)
                RERAISE                  1
ExceptionTable:
  L1 to L4 -> L18 [0] lasti
  L4 to L5 -> L14 [2]
  L5 to L11 -> L18 [0] lasti
  L11 to L12 -> L16 [2]
  L12 to L15 -> L18 [0] lasti
  L16 to L17 -> L18 [0] lasti

Disassembly of <code object record_provider_event at 0x0000024C0EC47330, file "D:\fluence\Github\mattbot\backend\app\services\call_service.py", line 206>:
 206           RETURN_GENERATOR
               POP_TOP
       L1:     RESUME                   0

 217           LOAD_GLOBAL              1 (compute_payload_hash + NULL)
               LOAD_FAST                4 (raw_params)
               CALL                     1
               STORE_FAST               8 (payload_hash)

 218           LOAD_GLOBAL              3 (redact_twilio_params + NULL)
               LOAD_FAST                4 (raw_params)
               CALL                     1
               STORE_FAST               9 (redacted)

 220           LOAD_GLOBAL              5 (ProviderEvent + NULL)

 221           LOAD_FAST                1 (provider)

 222           LOAD_FAST                3 (call_sid)

 223           LOAD_FAST                2 (event_type)

 224           LOAD_FAST                8 (payload_hash)

 225           LOAD_FAST                9 (redacted)

 226           LOAD_FAST                5 (signature_valid)

 227           LOAD_FAST                6 (call_id)

 228           LOAD_FAST                7 (owner_user_id)

 229           LOAD_CONST               1 ('received')

 220           LOAD_CONST               2 (('provider', 'provider_call_sid', 'event_type', 'payload_hash', 'payload_redacted', 'signature_valid', 'call_id', 'owner_user_id', 'process_status'))
               CALL_KW                  9
               STORE_FAST              10 (pe)

 231           LOAD_FAST                0 (db)
               LOAD_ATTR                7 (add + NULL|self)
               LOAD_FAST               10 (pe)
               CALL                     1
               POP_TOP

 232           LOAD_FAST                0 (db)
               LOAD_ATTR                9 (flush + NULL|self)
               CALL                     0
               GET_AWAITABLE            0
               LOAD_CONST               0 (None)
       L2:     SEND                     3 (to L5)
       L3:     YIELD_VALUE              1
       L4:     RESUME                   3
               JUMP_BACKWARD_NO_INTERRUPT 5 (to L2)
       L5:     END_SEND
               POP_TOP

 233           LOAD_FAST               10 (pe)
               RETURN_VALUE

 232   L6:     CLEANUP_THROW
       L7:     JUMP_BACKWARD_NO_INTERRUPT 6 (to L5)

  --   L8:     CALL_INTRINSIC_1         3 (INTRINSIC_STOPITERATION_ERROR)
               RERAISE                  1
ExceptionTable:
  L1 to L3 -> L8 [0] lasti
  L3 to L4 -> L6 [2]
  L4 to L7 -> L8 [0] lasti

Disassembly of <code object get_call_for_user at 0x0000024C0EC33C40, file "D:\fluence\Github\mattbot\backend\app\services\call_service.py", line 240>:
 240           RETURN_GENERATOR
               POP_TOP
       L1:     RESUME                   0

 243           LOAD_GLOBAL              1 (select + NULL)
               LOAD_GLOBAL              2 (Call)
               CALL                     1
               LOAD_ATTR                5 (where + NULL|self)

 244           LOAD_GLOBAL              2 (Call)
               LOAD_ATTR                6 (id)
               LOAD_FAST                2 (call_id)
               COMPARE_OP              72 (==)

 245           LOAD_GLOBAL              2 (Call)
               LOAD_ATTR                8 (owner_user_id)
               LOAD_FAST                1 (user_id)
               COMPARE_OP              72 (==)

 246           LOAD_GLOBAL              2 (Call)
               LOAD_ATTR               10 (deleted_at)
               LOAD_ATTR               13 (is_ + NULL|self)
               LOAD_CONST               0 (None)
               CALL                     1

 243           CALL                     3
               STORE_FAST               3 (stmt)

 248           LOAD_FAST                0 (db)
               LOAD_ATTR               15 (execute + NULL|self)
               LOAD_FAST                3 (stmt)
               CALL                     1
               GET_AWAITABLE            0
               LOAD_CONST               0 (None)
       L2:     SEND                     3 (to L5)
       L3:     YIELD_VALUE              1
       L4:     RESUME                   3
               JUMP_BACKWARD_NO_INTERRUPT 5 (to L2)
       L5:     END_SEND
               STORE_FAST               4 (result)

 249           LOAD_FAST                4 (result)
               LOAD_ATTR               17 (scalar_one_or_none + NULL|self)
               CALL                     0
               RETURN_VALUE

 248   L6:     CLEANUP_THROW
       L7:     JUMP_BACKWARD_NO_INTERRUPT 20 (to L5)

  --   L8:     CALL_INTRINSIC_1         3 (INTRINSIC_STOPITERATION_ERROR)
               RERAISE                  1
ExceptionTable:
  L1 to L3 -> L8 [0] lasti
  L3 to L4 -> L6 [2]
  L4 to L7 -> L8 [0] lasti

Disassembly of <code object list_calls_for_user at 0x0000024C0FCE8050, file "D:\fluence\Github\mattbot\backend\app\services\call_service.py", line 252>:
 252            RETURN_GENERATOR
                POP_TOP
        L1:     RESUME                   0

 272            LOAD_CONST               1 (0)
                LOAD_CONST               2 (('CallArtifact',))
                IMPORT_NAME              0 (app.models.call_artifact)
                IMPORT_FROM              1 (CallArtifact)
                STORE_FAST              16 (CallArtifact)
                POP_TOP

 275            LOAD_GLOBAL              5 (select + NULL)
                LOAD_GLOBAL              6 (Call)
                CALL                     1

 276            LOAD_ATTR                9 (where + NULL|self)

 277            LOAD_GLOBAL              6 (Call)
                LOAD_ATTR               10 (owner_user_id)
                LOAD_FAST                1 (user_id)
                COMPARE_OP              72 (==)

 278            LOAD_GLOBAL              6 (Call)
                LOAD_ATTR               12 (deleted_at)
                LOAD_ATTR               15 (is_ + NULL|self)
                LOAD_CONST               3 (None)
                CALL                     1

 279            LOAD_GLOBAL              6 (Call)
                LOAD_ATTR               16 (provider_parent_call_sid)
                LOAD_ATTR               15 (is_ + NULL|self)
                LOAD_CONST               3 (None)
                CALL                     1

 276            CALL                     3

 274            STORE_FAST              17 (stmt)

 283            LOAD_FAST                4 (status)
                TO_BOOL
                POP_JUMP_IF_FALSE       34 (to L2)

 284            LOAD_FAST               17 (stmt)
                LOAD_ATTR                9 (where + NULL|self)
                LOAD_GLOBAL              6 (Call)
                LOAD_ATTR               18 (status)
                LOAD_FAST                4 (status)
                COMPARE_OP              72 (==)
                CALL                     1
                STORE_FAST              17 (stmt)

 285    L2:     LOAD_FAST                5 (source_type)
                TO_BOOL
                POP_JUMP_IF_FALSE       34 (to L3)

 286            LOAD_FAST               17 (stmt)
                LOAD_ATTR                9 (where + NULL|self)
                LOAD_GLOBAL              6 (Call)
                LOAD_ATTR               20 (source_type)
                LOAD_FAST                5 (source_type)
                COMPARE_OP              72 (==)
                CALL                     1
                STORE_FAST              17 (stmt)

 287    L3:     LOAD_FAST                6 (date_from)
                TO_BOOL
                POP_JUMP_IF_FALSE       34 (to L4)

 288            LOAD_FAST               17 (stmt)
                LOAD_ATTR                9 (where + NULL|self)
                LOAD_GLOBAL              6 (Call)
                LOAD_ATTR               22 (started_at)
                LOAD_FAST                6 (date_from)
                COMPARE_OP             172 (>=)
                CALL                     1
                STORE_FAST              17 (stmt)

 289    L4:     LOAD_FAST                7 (date_to)
                TO_BOOL
                POP_JUMP_IF_FALSE       34 (to L5)

 290            LOAD_FAST               17 (stmt)
                LOAD_ATTR                9 (where + NULL|self)
                LOAD_GLOBAL              6 (Call)
                LOAD_ATTR               22 (started_at)
                LOAD_FAST                7 (date_to)
                COMPARE_OP              42 (<=)
                CALL                     1
                STORE_FAST              17 (stmt)

 291    L5:     LOAD_FAST                8 (duration_min)
                POP_JUMP_IF_NONE        34 (to L6)

 292            LOAD_FAST               17 (stmt)
                LOAD_ATTR                9 (where + NULL|self)
                LOAD_GLOBAL              6 (Call)
                LOAD_ATTR               24 (duration_seconds)
                LOAD_FAST                8 (duration_min)
                COMPARE_OP             172 (>=)
                CALL                     1
                STORE_FAST              17 (stmt)

 293    L6:     LOAD_FAST                9 (duration_max)
                POP_JUMP_IF_NONE        34 (to L7)

 294            LOAD_FAST               17 (stmt)
                LOAD_ATTR                9 (where + NULL|self)
                LOAD_GLOBAL              6 (Call)
                LOAD_ATTR               24 (duration_seconds)
                LOAD_FAST                9 (duration_max)
                COMPARE_OP              42 (<=)
                CALL                     1
                STORE_FAST              17 (stmt)

 295    L7:     LOAD_FAST               10 (country_prefix)
                TO_BOOL
                POP_JUMP_IF_FALSE       46 (to L8)

 296            LOAD_FAST               17 (stmt)
                LOAD_ATTR                9 (where + NULL|self)
                LOAD_GLOBAL              6 (Call)
                LOAD_ATTR               26 (from_masked)
                LOAD_ATTR               29 (startswith + NULL|self)
                LOAD_FAST               10 (country_prefix)
                CALL                     1
                CALL                     1
                STORE_FAST              17 (stmt)

 297    L8:     LOAD_FAST               12 (search)
                TO_BOOL
                POP_JUMP_IF_FALSE       50 (to L9)

 298            LOAD_FAST               17 (stmt)
                LOAD_ATTR                9 (where + NULL|self)
                LOAD_GLOBAL              6 (Call)
                LOAD_ATTR               26 (from_masked)
                LOAD_ATTR               31 (ilike + NULL|self)
                LOAD_CONST               4 ('%')
                LOAD_FAST               12 (search)
                FORMAT_SIMPLE
                LOAD_CONST               4 ('%')
                BUILD_STRING             3
                CALL                     1
                CALL                     1
                STORE_FAST              17 (stmt)

 300    L9:     LOAD_FAST               11 (has_recording)
                LOAD_CONST               5 (True)
                IS_OP                    0
                COPY                     1
                TO_BOOL
                POP_JUMP_IF_TRUE         2 (to L10)
                POP_TOP
                LOAD_FAST               13 (label)
       L10:     STORE_FAST              18 (need_artifact_join)

 301            LOAD_FAST               18 (need_artifact_join)
                TO_BOOL
                POP_JUMP_IF_FALSE       45 (to L11)

 302            LOAD_FAST               17 (stmt)
                LOAD_ATTR               33 (join + NULL|self)
                LOAD_FAST               16 (CallArtifact)
                LOAD_FAST               16 (CallArtifact)
                LOAD_ATTR               34 (call_id)
                LOAD_GLOBAL              6 (Call)
                LOAD_ATTR               36 (id)
                COMPARE_OP              72 (==)
                CALL                     2
                STORE_FAST              17 (stmt)

 304   L11:     LOAD_FAST               11 (has_recording)
                LOAD_CONST               5 (True)
                IS_OP                    0
                POP_JUMP_IF_FALSE       70 (to L12)

 305            LOAD_FAST               17 (stmt)
                LOAD_ATTR                9 (where + NULL|self)

 306            LOAD_FAST               16 (CallArtifact)
                LOAD_ATTR               38 (transcript_provider_ref)
                LOAD_ATTR               41 (isnot + NULL|self)
                LOAD_CONST               3 (None)
                CALL                     1

 307            LOAD_FAST               16 (CallArtifact)
                LOAD_ATTR               42 (transcript_status)
                LOAD_ATTR               45 (in_ + NULL|self)
                LOAD_CONST               6 ('ready')
                LOAD_CONST               7 ('partial')
                BUILD_LIST               2
                CALL                     1

 305            CALL                     2
                STORE_FAST              17 (stmt)

 310   L12:     LOAD_FAST               13 (label)
                TO_BOOL
                POP_JUMP_IF_FALSE      121 (to L13)

 311            LOAD_CONST               1 (0)
                LOAD_CONST               8 (('cast', 'type_coerce'))
                IMPORT_NAME             23 (sqlalchemy)
                IMPORT_FROM             24 (cast)
                STORE_FAST              19 (cast)
                IMPORT_FROM             25 (type_coerce)
                STORE_FAST              20 (type_coerce)
                POP_TOP

 312            LOAD_CONST               1 (0)
                LOAD_CONST               9 (('JSONB',))
                IMPORT_NAME             26 (sqlalchemy.dialects.postgresql)
                IMPORT_FROM             27 (JSONB)
                STORE_FAST              21 (JSONB)
                POP_TOP

 314            LOAD_CONST              10 ('label_name')
                LOAD_FAST               13 (label)
                BUILD_MAP                1
                BUILD_LIST               1
                STORE_FAST              22 (target)

 315            LOAD_FAST               17 (stmt)
                LOAD_ATTR                9 (where + NULL|self)

 316            LOAD_FAST               16 (CallArtifact)
                LOAD_ATTR               56 (labels_json)
                LOAD_ATTR               41 (isnot + NULL|self)
                LOAD_CONST               3 (None)
                CALL                     1

 317            LOAD_FAST               16 (CallArtifact)
                LOAD_ATTR               58 (labels_status)
                LOAD_CONST               6 ('ready')
                COMPARE_OP              72 (==)

 318            LOAD_FAST               19 (cast)
                PUSH_NULL
                LOAD_FAST               16 (CallArtifact)
                LOAD_ATTR               56 (labels_json)
                LOAD_FAST               21 (JSONB)
                CALL                     2
                LOAD_ATTR               61 (op + NULL|self)
                LOAD_CONST              11 ('@>')
                CALL                     1
                PUSH_NULL

 319            LOAD_FAST               20 (type_coerce)
                PUSH_NULL
                LOAD_FAST               22 (target)
                LOAD_FAST               21 (JSONB)
                CALL                     2

 318            CALL                     1

 315            CALL                     3
                STORE_FAST              17 (stmt)

 323   L13:     LOAD_FAST               14 (sort_by)
                LOAD_CONST              12 ('started_at')
                COMPARE_OP              88 (bool(==))
                POP_JUMP_IF_FALSE       16 (to L14)
                LOAD_GLOBAL              6 (Call)
                LOAD_ATTR               22 (started_at)
                JUMP_FORWARD            15 (to L15)
       L14:     LOAD_GLOBAL              6 (Call)
                LOAD_ATTR               62 (created_at)
       L15:     STORE_FAST              23 (order_col)

 326            LOAD_FAST               15 (sort_dir)
                LOAD_CONST              13 ('asc')
                COMPARE_OP              88 (bool(==))
                POP_JUMP_IF_FALSE       31 (to L16)

 325            LOAD_FAST               17 (stmt)
                LOAD_ATTR               65 (order_by + NULL|self)
                LOAD_FAST               23 (order_col)
                LOAD_ATTR               67 (asc + NULL|self)
                CALL                     0
                CALL                     1
                JUMP_FORWARD            30 (to L17)

 327   L16:     LOAD_FAST               17 (stmt)
                LOAD_ATTR               65 (order_by + NULL|self)
                LOAD_FAST               23 (order_col)
                LOAD_ATTR               69 (desc + NULL|self)
                CALL                     0
                CALL                     1

 324   L17:     STORE_FAST              17 (stmt)

 330            LOAD_FAST               17 (stmt)
                LOAD_ATTR               71 (limit + NULL|self)
                LOAD_FAST                3 (limit)
                LOAD_CONST              14 (1)
                BINARY_OP                0 (+)
                CALL                     1
                STORE_FAST              17 (stmt)

 332            LOAD_FAST                2 (cursor)
                TO_BOOL
                POP_JUMP_IF_FALSE      143 (to L20)

 333   L18:     NOP

 334   L19:     LOAD_GLOBAL             72 (uuid)
                LOAD_ATTR               74 (UUID)
                PUSH_NULL
                LOAD_FAST                2 (cursor)
                CALL                     1
                STORE_FAST              24 (cursor_id)

 336            LOAD_GLOBAL              5 (select + NULL)
                LOAD_GLOBAL              6 (Call)
                LOAD_ATTR               62 (created_at)
                CALL                     1

 337            LOAD_ATTR                9 (where + NULL|self)
                LOAD_GLOBAL              6 (Call)
                LOAD_ATTR               36 (id)
                LOAD_FAST               24 (cursor_id)
                COMPARE_OP              72 (==)
                CALL                     1

 338            LOAD_ATTR               77 (correlate + NULL|self)
                LOAD_CONST               3 (None)
                CALL                     1

 339            LOAD_ATTR               79 (scalar_subquery + NULL|self)
                CALL                     0

 335            STORE_FAST              25 (ref_ts)

 341            LOAD_FAST               17 (stmt)
                LOAD_ATTR                9 (where + NULL|self)
                LOAD_GLOBAL              6 (Call)
                LOAD_ATTR               62 (created_at)
                LOAD_FAST               25 (ref_ts)
                COMPARE_OP               2 (<)
                CALL                     1
                STORE_FAST              17 (stmt)

 345   L20:     LOAD_FAST                0 (db)
                LOAD_ATTR               85 (execute + NULL|self)
                LOAD_FAST               17 (stmt)
                CALL                     1
                GET_AWAITABLE            0
                LOAD_CONST               3 (None)
       L21:     SEND                     3 (to L24)
       L22:     YIELD_VALUE              1
       L23:     RESUME                   3
                JUMP_BACKWARD_NO_INTERRUPT 5 (to L21)
       L24:     END_SEND
                STORE_FAST              26 (result)

 346            LOAD_GLOBAL             87 (list + NULL)
                LOAD_FAST               26 (result)
                LOAD_ATTR               89 (scalars + NULL|self)
                CALL                     0
                LOAD_ATTR               91 (all + NULL|self)
                CALL                     0
                CALL                     1
                STORE_FAST              27 (rows)

 348            LOAD_GLOBAL             93 (len + NULL)
                LOAD_FAST               27 (rows)
                CALL                     1
                LOAD_FAST                3 (limit)
                COMPARE_OP             132 (>)
                STORE_FAST              28 (has_more)

 349            LOAD_FAST               28 (has_more)
                TO_BOOL
                POP_JUMP_IF_FALSE        5 (to L25)

 350            LOAD_FAST               27 (rows)
                LOAD_CONST               3 (None)
                LOAD_FAST                3 (limit)
                BINARY_SLICE
                STORE_FAST              27 (rows)

 352   L25:     LOAD_FAST               27 (rows)
                TO_BOOL
                POP_JUMP_IF_FALSE       31 (to L26)
                LOAD_FAST               28 (has_more)
                TO_BOOL
                POP_JUMP_IF_FALSE       24 (to L26)
                LOAD_GLOBAL             95 (str + NULL)
                LOAD_FAST               27 (rows)
                LOAD_CONST              15 (-1)
                BINARY_SUBSCR
                LOAD_ATTR               36 (id)
                CALL                     1
                JUMP_FORWARD             1 (to L27)
       L26:     LOAD_CONST               3 (None)
       L27:     STORE_FAST              29 (next_cursor)

 353            LOAD_FAST               27 (rows)
                LOAD_FAST               29 (next_cursor)
                LOAD_FAST               28 (has_more)
                BUILD_TUPLE              3
                RETURN_VALUE

  --   L28:     PUSH_EXC_INFO

 342            LOAD_GLOBAL             80 (ValueError)
                LOAD_GLOBAL             82 (TypeError)
                BUILD_TUPLE              2
                CHECK_EXC_MATCH
                POP_JUMP_IF_FALSE        3 (to L30)
                POP_TOP

 343   L29:     POP_EXCEPT
                JUMP_BACKWARD_NO_INTERRUPT 153 (to L20)

 342   L30:     RERAISE                  0

  --   L31:     COPY                     3
                POP_EXCEPT
                RERAISE                  1

 345   L32:     CLEANUP_THROW
       L33:     JUMP_BACKWARD_NO_INTERRUPT 136 (to L24)

  --   L34:     CALL_INTRINSIC_1         3 (INTRINSIC_STOPITERATION_ERROR)
                RERAISE                  1
ExceptionTable:
  L1 to L18 -> L34 [0] lasti
  L19 to L20 -> L28 [0]
  L20 to L22 -> L34 [0] lasti
  L22 to L23 -> L32 [2]
  L23 to L28 -> L34 [0] lasti
  L28 to L29 -> L31 [1] lasti
  L29 to L30 -> L34 [0] lasti
  L30 to L31 -> L31 [1] lasti
  L31 to L33 -> L34 [0] lasti

Disassembly of <code object get_call_events at 0x0000024C0FEDCCC0, file "D:\fluence\Github\mattbot\backend\app\services\call_service.py", line 356>:
 356           RETURN_GENERATOR
               POP_TOP
       L1:     RESUME                   0

 360           LOAD_GLOBAL              1 (select + NULL)
               LOAD_GLOBAL              2 (CallEvent)
               CALL                     1

 361           LOAD_ATTR                5 (where + NULL|self)

 362           LOAD_GLOBAL              2 (CallEvent)
               LOAD_ATTR                6 (call_id)
               LOAD_FAST                1 (call_id)
               COMPARE_OP              72 (==)

 363           LOAD_GLOBAL              2 (CallEvent)
               LOAD_ATTR                8 (owner_user_id)
               LOAD_FAST                2 (user_id)
               COMPARE_OP              72 (==)

 361           CALL                     2

 365           LOAD_ATTR               11 (order_by + NULL|self)
               LOAD_GLOBAL              2 (CallEvent)
               LOAD_ATTR               12 (event_at)
               LOAD_ATTR               15 (asc + NULL|self)
               CALL                     0
               CALL                     1

 359           STORE_FAST               3 (stmt)

 367           LOAD_FAST                0 (db)
               LOAD_ATTR               17 (execute + NULL|self)
               LOAD_FAST                3 (stmt)
               CALL                     1
               GET_AWAITABLE            0
               LOAD_CONST               0 (None)
       L2:     SEND                     3 (to L5)
       L3:     YIELD_VALUE              1
       L4:     RESUME                   3
               JUMP_BACKWARD_NO_INTERRUPT 5 (to L2)
       L5:     END_SEND
               STORE_FAST               4 (result)

 368           LOAD_GLOBAL             19 (list + NULL)
               LOAD_FAST                4 (result)
               LOAD_ATTR               21 (scalars + NULL|self)
               CALL                     0
               LOAD_ATTR               23 (all + NULL|self)
               CALL                     0
               CALL                     1
               RETURN_VALUE

 367   L6:     CLEANUP_THROW
       L7:     JUMP_BACKWARD_NO_INTERRUPT 43 (to L5)

  --   L8:     CALL_INTRINSIC_1         3 (INTRINSIC_STOPITERATION_ERROR)
               RERAISE                  1
ExceptionTable:
  L1 to L3 -> L8 [0] lasti
  L3 to L4 -> L6 [2]
  L4 to L7 -> L8 [0] lasti

Disassembly of <code object get_call_by_sid at 0x0000024C11467B90, file "D:\fluence\Github\mattbot\backend\app\services\call_service.py", line 371>:
 371           RETURN_GENERATOR
               POP_TOP
       L1:     RESUME                   0

 372           LOAD_GLOBAL              1 (select + NULL)
               LOAD_GLOBAL              2 (Call)
               CALL                     1
               LOAD_ATTR                5 (where + NULL|self)
               LOAD_GLOBAL              2 (Call)
               LOAD_ATTR                6 (provider_call_sid)
               LOAD_FAST                1 (call_sid)
               COMPARE_OP              72 (==)
               CALL                     1
               STORE_FAST               2 (stmt)

 373           LOAD_FAST                0 (db)
               LOAD_ATTR                9 (execute + NULL|self)
               LOAD_FAST                2 (stmt)
               CALL                     1
               GET_AWAITABLE            0
               LOAD_CONST               0 (None)
       L2:     SEND                     3 (to L5)
       L3:     YIELD_VALUE              1
       L4:     RESUME                   3
               JUMP_BACKWARD_NO_INTERRUPT 5 (to L2)
       L5:     END_SEND
               STORE_FAST               3 (result)

 374           LOAD_FAST                3 (result)
               LOAD_ATTR               11 (scalar_one_or_none + NULL|self)
               CALL                     0
               RETURN_VALUE

 373   L6:     CLEANUP_THROW
       L7:     JUMP_BACKWARD_NO_INTERRUPT 20 (to L5)

  --   L8:     CALL_INTRINSIC_1         3 (INTRINSIC_STOPITERATION_ERROR)
               RERAISE                  1
ExceptionTable:
  L1 to L3 -> L8 [0] lasti
  L3 to L4 -> L6 [2]
  L4 to L7 -> L8 [0] lasti

Disassembly of <code object soft_delete_call at 0x0000024C0FBAA650, file "D:\fluence\Github\mattbot\backend\app\services\call_service.py", line 381>:
 381            RETURN_GENERATOR
                POP_TOP
        L1:     RESUME                   0

 390            LOAD_GLOBAL              1 (get_call_for_user + NULL)
                LOAD_FAST_LOAD_FAST      1 (db, user_id)
                LOAD_FAST                2 (call_id)
                CALL                     3
                GET_AWAITABLE            0
                LOAD_CONST               1 (None)
        L2:     SEND                     3 (to L5)
        L3:     YIELD_VALUE              1
        L4:     RESUME                   3
                JUMP_BACKWARD_NO_INTERRUPT 5 (to L2)
        L5:     END_SEND
                STORE_FAST               3 (call)

 391            LOAD_FAST                3 (call)
                POP_JUMP_IF_NOT_NONE     1 (to L6)

 392            RETURN_CONST             2 (False)

 394    L6:     LOAD_GLOBAL              2 (datetime)
                LOAD_ATTR                4 (now)
                PUSH_NULL
                LOAD_GLOBAL              6 (UTC)
                CALL                     1
                STORE_FAST               4 (now)

 395            LOAD_FAST_LOAD_FAST     67 (now, call)
                STORE_ATTR               4 (deleted_at)

 397            LOAD_CONST               3 (0)
                LOAD_CONST               4 (('CallMemoryItem',))
                IMPORT_NAME              5 (app.models.call_memory_item)
                IMPORT_FROM              6 (CallMemoryItem)
                STORE_FAST               5 (CallMemoryItem)
                POP_TOP

 399            LOAD_GLOBAL             15 (select + NULL)
                LOAD_FAST                5 (CallMemoryItem)
                CALL                     1
                LOAD_ATTR               17 (where + NULL|self)

 400            LOAD_FAST                5 (CallMemoryItem)
                LOAD_ATTR               18 (source_call_id)
                LOAD_FAST                2 (call_id)
                COMPARE_OP              72 (==)

 401            LOAD_FAST                5 (CallMemoryItem)
                LOAD_ATTR               20 (owner_user_id)
                LOAD_FAST                1 (user_id)
                COMPARE_OP              72 (==)

 399            CALL                     2
                STORE_FAST               6 (memory_stmt)

 403            LOAD_FAST                0 (db)
                LOAD_ATTR               23 (execute + NULL|self)
                LOAD_FAST                6 (memory_stmt)
                CALL                     1
                GET_AWAITABLE            0
                LOAD_CONST               1 (None)
        L7:     SEND                     3 (to L10)
        L8:     YIELD_VALUE              1
        L9:     RESUME                   3
                JUMP_BACKWARD_NO_INTERRUPT 5 (to L7)
       L10:     END_SEND
                LOAD_ATTR               25 (scalars + NULL|self)
                CALL                     0
                LOAD_ATTR               27 (all + NULL|self)
                CALL                     0
                STORE_FAST               7 (memory_items)

 404            LOAD_FAST                7 (memory_items)
                GET_ITER
       L11:     FOR_ITER                35 (to L13)
                STORE_FAST               8 (item)

 405            LOAD_FAST                8 (item)
                LOAD_ATTR               28 (user_confirmed)
                TO_BOOL
                POP_JUMP_IF_FALSE        9 (to L12)

 406            LOAD_CONST               1 (None)
                LOAD_FAST                8 (item)
                STORE_ATTR               9 (source_call_id)
                JUMP_BACKWARD           29 (to L11)

 408   L12:     LOAD_FAST_LOAD_FAST     72 (now, item)
                STORE_ATTR               4 (deleted_at)
                JUMP_BACKWARD           37 (to L11)

 404   L13:     END_FOR
                POP_TOP

 410            LOAD_FAST                0 (db)
                LOAD_ATTR               31 (flush + NULL|self)
                CALL                     0
                GET_AWAITABLE            0
                LOAD_CONST               1 (None)
       L14:     SEND                     3 (to L17)
       L15:     YIELD_VALUE              1
       L16:     RESUME                   3
                JUMP_BACKWARD_NO_INTERRUPT 5 (to L14)
       L17:     END_SEND
                POP_TOP

 411            RETURN_CONST             5 (True)

 390   L18:     CLEANUP_THROW
       L19:     JUMP_BACKWARD_NO_INTERRUPT 218 (to L5)

 403   L20:     CLEANUP_THROW
       L21:     JUMP_BACKWARD_NO_INTERRUPT 100 (to L10)

 410   L22:     CLEANUP_THROW
       L23:     JUMP_BACKWARD_NO_INTERRUPT 9 (to L17)

  --   L24:     CALL_INTRINSIC_1         3 (INTRINSIC_STOPITERATION_ERROR)
                RERAISE                  1
ExceptionTable:
  L1 to L3 -> L24 [0] lasti
  L3 to L4 -> L18 [2]
  L4 to L8 -> L24 [0] lasti
  L8 to L9 -> L20 [2]
  L9 to L15 -> L24 [0] lasti
  L15 to L16 -> L22 [2]
  L16 to L19 -> L24 [0] lasti
  L20 to L21 -> L24 [0] lasti
  L22 to L23 -> L24 [0] lasti

Disassembly of <code object soft_delete_all_calls at 0x0000024C0FB5D150, file "D:\fluence\Github\mattbot\backend\app\services\call_service.py", line 414>:
 414            RETURN_GENERATOR
                POP_TOP
        L1:     RESUME                   0

 418            LOAD_CONST               1 (0)
                LOAD_CONST               2 (('func',))
                IMPORT_NAME              0 (sqlalchemy)
                IMPORT_FROM              1 (func)
                STORE_FAST               2 (sa_func)
                POP_TOP

 419            LOAD_CONST               1 (0)
                LOAD_CONST               3 (('update',))
                IMPORT_NAME              0 (sqlalchemy)
                IMPORT_FROM              2 (update)
                STORE_FAST               3 (sa_update)
                POP_TOP

 421            LOAD_CONST               1 (0)
                LOAD_CONST               4 (('CallMemoryItem',))
                IMPORT_NAME              3 (app.models.call_memory_item)
                IMPORT_FROM              4 (CallMemoryItem)
                STORE_FAST               4 (CallMemoryItem)
                POP_TOP

 423            LOAD_GLOBAL             10 (datetime)
                LOAD_ATTR               12 (now)
                PUSH_NULL
                LOAD_GLOBAL             14 (UTC)
                CALL                     1
                STORE_FAST               5 (now)

 426            LOAD_GLOBAL             17 (select + NULL)
                LOAD_FAST                2 (sa_func)
                LOAD_ATTR               19 (count + NULL|self)
                CALL                     0
                CALL                     1

 427            LOAD_ATTR               21 (select_from + NULL|self)
                LOAD_GLOBAL             22 (Call)
                CALL                     1

 428            LOAD_ATTR               25 (where + NULL|self)
                LOAD_GLOBAL             22 (Call)
                LOAD_ATTR               26 (owner_user_id)
                LOAD_FAST                1 (user_id)
                COMPARE_OP              72 (==)
                LOAD_GLOBAL             22 (Call)
                LOAD_ATTR               28 (deleted_at)
                LOAD_ATTR               31 (is_ + NULL|self)
                LOAD_CONST               5 (None)
                CALL                     1
                CALL                     2

 425            STORE_FAST               6 (count_stmt)

 430            LOAD_FAST                0 (db)
                LOAD_ATTR               33 (execute + NULL|self)
                LOAD_FAST                6 (count_stmt)
                CALL                     1
                GET_AWAITABLE            0
                LOAD_CONST               5 (None)
        L2:     SEND                     3 (to L5)
        L3:     YIELD_VALUE              1
        L4:     RESUME                   3
                JUMP_BACKWARD_NO_INTERRUPT 5 (to L2)
        L5:     END_SEND
                LOAD_ATTR               35 (scalar + NULL|self)
                CALL                     0
                COPY                     1
                TO_BOOL
                POP_JUMP_IF_TRUE         2 (to L6)
                POP_TOP
                LOAD_CONST               1 (0)
        L6:     STORE_FAST               7 (count)

 432            LOAD_FAST                0 (db)
                LOAD_ATTR               33 (execute + NULL|self)

 433            LOAD_FAST                3 (sa_update)
                PUSH_NULL
                LOAD_GLOBAL             22 (Call)
                CALL                     1

 434            LOAD_ATTR               25 (where + NULL|self)
                LOAD_GLOBAL             22 (Call)
                LOAD_ATTR               26 (owner_user_id)
                LOAD_FAST                1 (user_id)
                COMPARE_OP              72 (==)
                LOAD_GLOBAL             22 (Call)
                LOAD_ATTR               28 (deleted_at)
                LOAD_ATTR               31 (is_ + NULL|self)
                LOAD_CONST               5 (None)
                CALL                     1
                CALL                     2

 435            LOAD_ATTR               37 (values + NULL|self)
                LOAD_FAST                5 (now)
                LOAD_CONST               6 (('deleted_at',))
                CALL_KW                  1

 432            CALL                     1
                GET_AWAITABLE            0
                LOAD_CONST               5 (None)
        L7:     SEND                     3 (to L10)
        L8:     YIELD_VALUE              1
        L9:     RESUME                   3
                JUMP_BACKWARD_NO_INTERRUPT 5 (to L7)
       L10:     END_SEND
                POP_TOP

 438            LOAD_FAST                7 (count)
                TO_BOOL
                POP_JUMP_IF_FALSE      222 (to L19)

 439            LOAD_FAST                0 (db)
                LOAD_ATTR               33 (execute + NULL|self)

 440            LOAD_FAST                3 (sa_update)
                PUSH_NULL
                LOAD_FAST                4 (CallMemoryItem)
                CALL                     1

 441            LOAD_ATTR               25 (where + NULL|self)

 442            LOAD_FAST                4 (CallMemoryItem)
                LOAD_ATTR               26 (owner_user_id)
                LOAD_FAST                1 (user_id)
                COMPARE_OP              72 (==)

 443            LOAD_FAST                4 (CallMemoryItem)
                LOAD_ATTR               38 (user_confirmed)
                LOAD_ATTR               31 (is_ + NULL|self)
                LOAD_CONST               7 (False)
                CALL                     1

 444            LOAD_FAST                4 (CallMemoryItem)
                LOAD_ATTR               28 (deleted_at)
                LOAD_ATTR               31 (is_ + NULL|self)
                LOAD_CONST               5 (None)
                CALL                     1

 441            CALL                     3

 446            LOAD_ATTR               37 (values + NULL|self)
                LOAD_FAST                5 (now)
                LOAD_CONST               6 (('deleted_at',))
                CALL_KW                  1

 439            CALL                     1
                GET_AWAITABLE            0
                LOAD_CONST               5 (None)
       L11:     SEND                     3 (to L14)
       L12:     YIELD_VALUE              1
       L13:     RESUME                   3
                JUMP_BACKWARD_NO_INTERRUPT 5 (to L11)
       L14:     END_SEND
                POP_TOP

 448            LOAD_FAST                0 (db)
                LOAD_ATTR               33 (execute + NULL|self)

 449            LOAD_FAST                3 (sa_update)
                PUSH_NULL
                LOAD_FAST                4 (CallMemoryItem)
                CALL                     1

 450            LOAD_ATTR               25 (where + NULL|self)

 451            LOAD_FAST                4 (CallMemoryItem)
                LOAD_ATTR               26 (owner_user_id)
                LOAD_FAST                1 (user_id)
                COMPARE_OP              72 (==)

 452            LOAD_FAST                4 (CallMemoryItem)
                LOAD_ATTR               38 (user_confirmed)
                LOAD_ATTR               31 (is_ + NULL|self)
                LOAD_CONST               8 (True)
                CALL                     1

 450            CALL                     2

 454            LOAD_ATTR               37 (values + NULL|self)
                LOAD_CONST               5 (None)
                LOAD_CONST               9 (('source_call_id',))
                CALL_KW                  1

 448            CALL                     1
                GET_AWAITABLE            0
                LOAD_CONST               5 (None)
       L15:     SEND                     3 (to L18)
       L16:     YIELD_VALUE              1
       L17:     RESUME                   3
                JUMP_BACKWARD_NO_INTERRUPT 5 (to L15)
       L18:     END_SEND
                POP_TOP

 457   L19:     LOAD_FAST                0 (db)
                LOAD_ATTR               41 (flush + NULL|self)
                CALL                     0
                GET_AWAITABLE            0
                LOAD_CONST               5 (None)
       L20:     SEND                     3 (to L23)
       L21:     YIELD_VALUE              1
       L22:     RESUME                   3
                JUMP_BACKWARD_NO_INTERRUPT 5 (to L20)
       L23:     END_SEND
                POP_TOP

 458            LOAD_FAST                7 (count)
                RETURN_VALUE

 430   L24:     CLEANUP_THROW
       L25:     EXTENDED_ARG             1
                JUMP_BACKWARD_NO_INTERRUPT 393 (to L5)

 432   L26:     CLEANUP_THROW
       L27:     EXTENDED_ARG             1
                JUMP_BACKWARD_NO_INTERRUPT 263 (to L10)

 439   L28:     CLEANUP_THROW
       L29:     JUMP_BACKWARD_NO_INTERRUPT 134 (to L14)

 448   L30:     CLEANUP_THROW
       L31:     JUMP_BACKWARD_NO_INTERRUPT 38 (to L18)

 457   L32:     CLEANUP_THROW
       L33:     JUMP_BACKWARD_NO_INTERRUPT 16 (to L23)

  --   L34:     CALL_INTRINSIC_1         3 (INTRINSIC_STOPITERATION_ERROR)
                RERAISE                  1
ExceptionTable:
  L1 to L3 -> L34 [0] lasti
  L3 to L4 -> L24 [2]
  L4 to L8 -> L34 [0] lasti
  L8 to L9 -> L26 [2]
  L9 to L12 -> L34 [0] lasti
  L12 to L13 -> L28 [2]
  L13 to L16 -> L34 [0] lasti
  L16 to L17 -> L30 [2]
  L17 to L21 -> L34 [0] lasti
  L21 to L22 -> L32 [2]
  L22 to L25 -> L34 [0] lasti
  L26 to L27 -> L34 [0] lasti
  L28 to L29 -> L34 [0] lasti
  L30 to L31 -> L34 [0] lasti
  L32 to L33 -> L34 [0] lasti
