# Bytecode dump of: elevenlabs_agent_service.cpython-313.pyc
# co_filename: D:\fluence\Github\mattbot\backend\app\services\elevenlabs_agent_service.py
# co_names: ('__doc__', '__future__', 'annotations', 'logging', 'httpx', 'app.config', 'settings', 'app_settings', 'getLogger', '__name__', 'logger', '_API_BASE', '_TIMEOUT', '_headers', 'TURN_EAGERNESS_MAP', '__annotations__', '_MATTBOT_TOOL_PREFIX', '_make_property', '_const_property', '_dynamic_var_property', '_booking_tool_body', '_availability_tool_body', '_create_tool', '_list_tools', '_delete_tool', '_update_tool', 'ensure_booking_tools', 'build_booking_tool_config', 'build_availability_tool_config', 'create_agent', 'update_agent', 'delete_agent', 'fetch_voices', 'sync_voice_catalog', 'fetch_conversation_audio')
# co_consts (strings): ['ElevenLabs agent management: create, update, delete per-user agents + voice catalog sync.', 'https://api.elevenlabs.io/v1', 'dict[str, str]', 'normal', 'eager', 'patient', 'TURN_EAGERNESS_MAP', 'mattbot_', 'en', 'professional_polite']

# DOCSTRING: """ElevenLabs agent management: create, update, delete per-user agents + voice catalog sync."""
# --- Nested code object: _headers ---
    # co_names: ('app_settings', 'ELEVENLABS_API_KEY')
    # co_varnames: ()
     17           RESUME                   0
    
     18           LOAD_CONST               1 ('xi-api-key')
                  LOAD_GLOBAL              0 (app_settings)
                  LOAD_ATTR                2 (ELEVENLABS_API_KEY)
                  BUILD_MAP                1
                  RETURN_VALUE
    
# --- Nested code object: _make_property ---
    # DOCSTRING: """Build a user-provided parameter property."""
    # co_names: ()
    # co_varnames: ('prop_type', 'description')
     42           RESUME                   0
    
     44           LOAD_FAST_LOAD_FAST      1 (prop_type, description)
                  LOAD_CONST               1 (('type', 'description'))
                  BUILD_CONST_KEY_MAP      2
                  RETURN_VALUE
    
# --- Nested code object: _const_property ---
    # DOCSTRING: """Build a constant-value parameter (always the same, hidden from LLM)."""
    # co_names: ()
    # co_varnames: ('prop_type', 'value')
     47           RESUME                   0
    
     49           LOAD_FAST_LOAD_FAST      1 (prop_type, value)
                  LOAD_CONST               1 (('type', 'constant_value'))
                  BUILD_CONST_KEY_MAP      2
                  RETURN_VALUE
    
# --- Nested code object: _dynamic_var_property ---
    # DOCSTRING: """Build a parameter populated from a conversation dynamic variable."""
    # co_names: ()
    # co_varnames: ('prop_type', 'var_name')
     52           RESUME                   0
    
     54           LOAD_FAST_LOAD_FAST      1 (prop_type, var_name)
                  LOAD_CONST               1 (('type', 'dynamic_variable'))
                  BUILD_CONST_KEY_MAP      2
                  RETURN_VALUE
    
# --- Nested code object: _booking_tool_body ---
    # DOCSTRING: """POST body for creating the book_appointment tool via /v1/convai/tools."""
    # co_names: ('_MATTBOT_TOOL_PREFIX', '_const_property', '_dynamic_var_property', '_make_property')
    # co_varnames: ('webhook_url', 'tool_secret', 'headers')
     57           RESUME                   0
    
     59           LOAD_FAST                1 (tool_secret)
                  TO_BOOL
                  POP_JUMP_IF_FALSE        4 (to L1)
                  LOAD_CONST               1 ('X-Tool-Secret')
                  LOAD_FAST                1 (tool_secret)
                  BUILD_MAP                1
                  JUMP_FORWARD             1 (to L2)
          L1:     BUILD_MAP                0
          L2:     STORE_FAST               2 (headers)
    
     60           LOAD_CONST               2 ('tool_config')
    
     61           LOAD_GLOBAL              0 (_MATTBOT_TOOL_PREFIX)
                  FORMAT_SIMPLE
                  LOAD_CONST               3 ('book_appointment')
                  BUILD_STRING             2
    
     63           LOAD_CONST               4 ("Book an appointment on the user's calendar for the caller.")
    
     65           LOAD_CONST               5 ('webhook')
    
     67           LOAD_FAST                0 (webhook_url)
    
     68           LOAD_CONST               6 ('POST')
    
     69           LOAD_FAST                2 (headers)
    
     70           BUILD_MAP                0
    
     71           LOAD_CONST               7 (None)
    
     73           LOAD_CONST               8 ('object')
    
     74           LOAD_CONST               9 ('')
    
     75           BUILD_LIST               0
                  LOAD_CONST              10 (('tool_name', 'date', 'time', 'caller_name', 'reason'))
                  LIST_EXTEND              1
    
     79           LOAD_GLOBAL              3 (_const_property + NULL)
    
     80           LOAD_CONST              11 ('string')
                  LOAD_CONST               3 ('book_appointment')
    
     79           CALL                     2
    
     82           LOAD_GLOBAL              5 (_dynamic_var_property + NULL)
                  LOAD_CONST              11 ('string')
                  LOAD_CONST              12 ('el_agent_id')
                  CALL                     2
    
     83           LOAD_GLOBAL              7 (_make_property + NULL)
    
     84           LOAD_CONST              11 ('string')
                  LOAD_CONST              13 ('Date in YYYY-MM-DD format')
    
     83           CALL                     2
    
     86           LOAD_GLOBAL              7 (_make_property + NULL)
    
     87           LOAD_CONST              11 ('string')
                  LOAD_CONST              14 ('Time in HH:MM 24-hour format')
    
     86           CALL                     2
    
     89           LOAD_GLOBAL              7 (_make_property + NULL)
    
     90           LOAD_CONST              15 ('integer')
    
     91           LOAD_CONST              16 ('Duration in minutes (default 30)')
    
     89           CALL                     2
    
     93           LOAD_GLOBAL              7 (_make_property + NULL)
    
     94           LOAD_CONST              11 ('string')
                  LOAD_CONST              17 ('Name of the person booking')
    
     93           CALL                     2
    
     96           LOAD_GLOBAL              7 (_make_property + NULL)
    
     97           LOAD_CONST              11 ('string')
                  LOAD_CONST              18 ('Purpose of the appointment')
    
     96           CALL                     2
    
     99           LOAD_GLOBAL              7 (_make_property + NULL)
    
    100           LOAD_CONST              11 ('string')
                  LOAD_CONST              19 ('Phone number of the caller')
    
     99           CALL                     2
    
     78           LOAD_CONST              20 (('tool_name', 'agent_id', 'date', 'time', 'duration_minutes', 'caller_name', 'reason', 'caller_phone'))
                  BUILD_CONST_KEY_MAP      8
    
     72           LOAD_CONST              21 (('type', 'description', 'required', 'properties'))
                  BUILD_CONST_KEY_MAP      4
    
    104           LOAD_CONST              22 ('application/json')
    
    105           LOAD_CONST               7 (None)
    
     66           LOAD_CONST              23 (('url', 'method', 'request_headers', 'path_params_schema', 'query_params_schema', 'request_body_schema', 'content_type', 'auth_connection'))
                  BUILD_CONST_KEY_MAP      8
    
     60           LOAD_CONST              24 (('name', 'description', 'type', 'api_schema'))
                  BUILD_CONST_KEY_MAP      4
                  BUILD_MAP                1
                  RETURN_VALUE
    
# --- Nested code object: _availability_tool_body ---
    # DOCSTRING: """POST body for creating the get_available_slots tool via /v1/convai/tools."""
    # co_names: ('_MATTBOT_TOOL_PREFIX', '_const_property', '_dynamic_var_property', '_make_property')
    # co_varnames: ('webhook_url', 'tool_secret', 'headers')
    110           RESUME                   0
    
    112           LOAD_FAST                1 (tool_secret)
                  TO_BOOL
                  POP_JUMP_IF_FALSE        4 (to L1)
                  LOAD_CONST               1 ('X-Tool-Secret')
                  LOAD_FAST                1 (tool_secret)
                  BUILD_MAP                1
                  JUMP_FORWARD             1 (to L2)
          L1:     BUILD_MAP                0
          L2:     STORE_FAST               2 (headers)
    
    113           LOAD_CONST               2 ('tool_config')
    
    114           LOAD_GLOBAL              0 (_MATTBOT_TOOL_PREFIX)
                  FORMAT_SIMPLE
                  LOAD_CONST               3 ('get_available_slots')
                  BUILD_STRING             2
    
    116           LOAD_CONST               4 ("Check the calendar owner's availability for a given date and return ALL open appointment slots for that day. Call this BEFORE offering any times to the caller. You must convert the caller's natural language date (e.g. 'next Monday', 'tomorrow', 'March 10th') into YYYY-MM-DD format yourself before calling this tool. IMPORTANT: Only present up to 3 slots at a time to the caller to avoid overwhelming them. If they don't like those, offer the next batch from the remaining slots.")
    
    126           LOAD_CONST               5 ('webhook')
    
    128           LOAD_FAST                0 (webhook_url)
    
    129           LOAD_CONST               6 ('POST')
    
    130           LOAD_FAST                2 (headers)
    
    131           BUILD_MAP                0
    
    132           LOAD_CONST               7 (None)
    
    134           LOAD_CONST               8 ('object')
    
    135           LOAD_CONST               9 ('')
    
    136           LOAD_CONST              10 ('tool_name')
                  LOAD_CONST              11 ('date')
                  BUILD_LIST               2
    
    138           LOAD_GLOBAL              3 (_const_property + NULL)
    
    139           LOAD_CONST              12 ('string')
                  LOAD_CONST               3 ('get_available_slots')
    
    138           CALL                     2
    
    141           LOAD_GLOBAL              5 (_dynamic_var_property + NULL)
                  LOAD_CONST              12 ('string')
                  LOAD_CONST              13 ('el_agent_id')
                  CALL                     2
    
    142           LOAD_GLOBAL              7 (_make_property + NULL)
    
    143           LOAD_CONST              12 ('string')
    
    144           LOAD_CONST              14 ('Date to check in YYYY-MM-DD format')
    
    142           CALL                     2
    
    146           LOAD_GLOBAL              7 (_make_property + NULL)
    
    147           LOAD_CONST              15 ('integer')
    
    148           LOAD_CONST              16 ('Desired appointment duration in minutes (default 30)')
    
    146           CALL                     2
    
    137           LOAD_CONST              17 (('tool_name', 'agent_id', 'date', 'duration_minutes'))
                  BUILD_CONST_KEY_MAP      4
    
    133           LOAD_CONST              18 (('type', 'description', 'required', 'properties'))
                  BUILD_CONST_KEY_MAP      4
    
    152           LOAD_CONST              19 ('application/json')
    
    153           LOAD_CONST               7 (None)
    
    127           LOAD_CONST              20 (('url', 'method', 'request_headers', 'path_params_schema', 'query_params_schema', 'request_body_schema', 'content_type', 'auth_connection'))
                  BUILD_CONST_KEY_MAP      8
    
    113           LOAD_CONST              21 (('name', 'description', 'type', 'api_schema'))
                  BUILD_CONST_KEY_MAP      4
                  BUILD_MAP                1
                  RETURN_VALUE
    
# --- Nested code object: _create_tool ---
    # DOCSTRING: """Create a tool via POST /v1/convai/tools and return its ID."""
    # co_names: ('httpx', 'AsyncClient', '_TIMEOUT', 'post', '_API_BASE', '_headers', 'status_code', 'logger', 'error', 'text', 'raise_for_status', 'json', 'get', 'info')
    # co_varnames: ('body', 'client', 'resp', 'data', 'tool_id')
     158            RETURN_GENERATOR
                    POP_TOP
            L1:     RESUME                   0
    
     160            LOAD_GLOBAL              0 (httpx)
                    LOAD_ATTR                2 (AsyncClient)
                    PUSH_NULL
                    LOAD_GLOBAL              4 (_TIMEOUT)
                    LOAD_CONST               1 (('timeout',))
                    CALL_KW                  1
                    BEFORE_ASYNC_WITH
                    GET_AWAITABLE            1
                    LOAD_CONST               2 (None)
            L2:     SEND                     3 (to L5)
            L3:     YIELD_VALUE              1
            L4:     RESUME                   3
                    JUMP_BACKWARD_NO_INTERRUPT 5 (to L2)
            L5:     END_SEND
            L6:     STORE_FAST               1 (client)
    
     161            LOAD_FAST                1 (client)
                    LOAD_ATTR                7 (post + NULL|self)
    
     162            LOAD_GLOBAL              8 (_API_BASE)
                    FORMAT_SIMPLE
                    LOAD_CONST               3 ('/convai/tools')
                    BUILD_STRING             2
    
     163            LOAD_FAST                0 (body)
    
     164            LOAD_GLOBAL             11 (_headers + NULL)
                    CALL                     0
    
     161            LOAD_CONST               4 (('json', 'headers'))
                    CALL_KW                  3
                    GET_AWAITABLE            0
                    LOAD_CONST               2 (None)
            L7:     SEND                     3 (to L10)
            L8:     YIELD_VALUE              1
            L9:     RESUME                   3
                    JUMP_BACKWARD_NO_INTERRUPT 5 (to L7)
           L10:     END_SEND
                    STORE_FAST               2 (resp)
    
     166            LOAD_FAST                2 (resp)
                    LOAD_ATTR               12 (status_code)
                    LOAD_CONST               5 ((200, 201))
                    CONTAINS_OP              1
                    POP_JUMP_IF_FALSE       62 (to L11)
    
     167            LOAD_GLOBAL             14 (logger)
                    LOAD_ATTR               17 (error + NULL|self)
    
     168            LOAD_CONST               6 ('ElevenLabs create tool failed: %d %s')
    
     169            LOAD_FAST                2 (resp)
                    LOAD_ATTR               12 (status_code)
                    LOAD_FAST                2 (resp)
                    LOAD_ATTR               18 (text)
                    LOAD_CONST               2 (None)
                    LOAD_CONST               7 (500)
                    BINARY_SLICE
    
     167            CALL                     3
                    POP_TOP
    
     171            LOAD_FAST                2 (resp)
                    LOAD_ATTR               21 (raise_for_status + NULL|self)
                    CALL                     0
                    POP_TOP
    
     172   L11:     LOAD_FAST                2 (resp)
                    LOAD_ATTR               23 (json + NULL|self)
                    CALL                     0
                    STORE_FAST               3 (data)
    
     173            LOAD_FAST                3 (data)
                    LOAD_ATTR               25 (get + NULL|self)
                    LOAD_CONST               8 ('id')
                    LOAD_CONST               9 ('')
                    CALL                     2
                    STORE_FAST               4 (tool_id)
    
     174            LOAD_GLOBAL             14 (logger)
                    LOAD_ATTR               27 (info + NULL|self)
    
     175            LOAD_CONST              10 ('ElevenLabs tool created: id=%s name=%s')
    
     176            LOAD_FAST_LOAD_FAST     64 (tool_id, body)
                    LOAD_ATTR               25 (get + NULL|self)
                    LOAD_CONST              11 ('tool_config')
                    BUILD_MAP                0
                    CALL                     2
                    LOAD_ATTR               25 (get + NULL|self)
                    LOAD_CONST              12 ('name')
                    CALL                     1
    
     174            CALL                     3
                    POP_TOP
    
     178            LOAD_FAST                4 (tool_id)
    
     160   L12:     SWAP                     2
                    LOAD_CONST               2 (None)
                    LOAD_CONST               2 (None)
                    LOAD_CONST               2 (None)
                    CALL                     2
                    GET_AWAITABLE            2
                    LOAD_CONST               2 (None)
           L13:     SEND                     3 (to L16)
           L14:     YIELD_VALUE              1
           L15:     RESUME                   3
                    JUMP_BACKWARD_NO_INTERRUPT 5 (to L13)
           L16:     END_SEND
                    POP_TOP
                    RETURN_VALUE
           L17:     CLEANUP_THROW
           L18:     JUMP_BACKWARD_NO_INTERRUPT 228 (to L5)
    
     161   L19:     CLEANUP_THROW
           L20:     JUMP_BACKWARD_NO_INTERRUPT 190 (to L10)
    
     160   L21:     CLEANUP_THROW
           L22:     JUMP_BACKWARD_NO_INTERRUPT 9 (to L16)
           L23:     PUSH_EXC_INFO
                    WITH_EXCEPT_START
                    GET_AWAITABLE            2
                    LOAD_CONST               2 (None)
           L24:     SEND                     4 (to L28)
           L25:     YIELD_VALUE              1
           L26:     RESUME                   3
                    JUMP_BACKWARD_NO_INTERRUPT 5 (to L24)
           L27:     CLEANUP_THROW
           L28:     END_SEND
                    TO_BOOL
                    POP_JUMP_IF_TRUE         1 (to L29)
                    RERAISE                  2
           L29:     POP_TOP
           L30:     POP_EXCEPT
                    POP_TOP
                    POP_TOP
                    RETURN_CONST             2 (None)
    
      --   L31:     COPY                     3
                    POP_EXCEPT
                    RERAISE                  1
           L32:     CALL_INTRINSIC_1         3 (INTRINSIC_STOPITERATION_ERROR)
                    RERAISE                  1
    ExceptionTable:
      L1 to L3 -> L32 [0] lasti
      L3 to L4 -> L17 [3]
      L4 to L6 -> L32 [0] lasti
      L6 to L8 -> L23 [1] lasti
      L8 to L9 -> L19 [3]
      L9 to L12 -> L23 [1] lasti
      L12 to L14 -> L32 [0] lasti
      L14 to L15 -> L21 [3]
      L15 to L18 -> L32 [0] lasti
      L19 to L20 -> L23 [1] lasti
      L21 to L22 -> L32 [0] lasti
      L23 to L25 -> L31 [3] lasti
      L25 to L26 -> L27 [6]
      L26 to L30 -> L31 [3] lasti
      L30 to L32 -> L32 [0] lasti
    
# --- Nested code object: _list_tools ---
    # DOCSTRING: """List all tools in the workspace."""
    # co_names: ('httpx', 'AsyncClient', '_TIMEOUT', 'get', '_API_BASE', '_headers', 'status_code', 'logger', 'error', 'json')
    # co_varnames: ('client', 'resp', 'data')
     181            RETURN_GENERATOR
                    POP_TOP
            L1:     RESUME                   0
    
     183            LOAD_GLOBAL              0 (httpx)
                    LOAD_ATTR                2 (AsyncClient)
                    PUSH_NULL
                    LOAD_GLOBAL              4 (_TIMEOUT)
                    LOAD_CONST               1 (('timeout',))
                    CALL_KW                  1
                    BEFORE_ASYNC_WITH
                    GET_AWAITABLE            1
                    LOAD_CONST               2 (None)
            L2:     SEND                     3 (to L5)
            L3:     YIELD_VALUE              1
            L4:     RESUME                   3
                    JUMP_BACKWARD_NO_INTERRUPT 5 (to L2)
            L5:     END_SEND
            L6:     STORE_FAST               0 (client)
    
     184            LOAD_FAST                0 (client)
                    LOAD_ATTR                7 (get + NULL|self)
    
     185            LOAD_GLOBAL              8 (_API_BASE)
                    FORMAT_SIMPLE
                    LOAD_CONST               3 ('/convai/tools')
                    BUILD_STRING             2
                    LOAD_GLOBAL             11 (_headers + NULL)
                    CALL                     0
    
     184            LOAD_CONST               4 (('headers',))
                    CALL_KW                  2
                    GET_AWAITABLE            0
                    LOAD_CONST               2 (None)
            L7:     SEND                     3 (to L10)
            L8:     YIELD_VALUE              1
            L9:     RESUME                   3
                    JUMP_BACKWARD_NO_INTERRUPT 5 (to L7)
           L10:     END_SEND
                    STORE_FAST               1 (resp)
    
     187            LOAD_FAST                1 (resp)
                    LOAD_ATTR               12 (status_code)
                    LOAD_CONST               5 (200)
                    COMPARE_OP             119 (bool(!=))
                    POP_JUMP_IF_FALSE       51 (to L16)
    
     188            LOAD_GLOBAL             14 (logger)
                    LOAD_ATTR               17 (error + NULL|self)
                    LOAD_CONST               6 ('ElevenLabs list tools failed: %d')
                    LOAD_FAST                1 (resp)
                    LOAD_ATTR               12 (status_code)
                    CALL                     2
                    POP_TOP
    
     189            BUILD_LIST               0
    
     183   L11:     SWAP                     2
                    LOAD_CONST               2 (None)
                    LOAD_CONST               2 (None)
                    LOAD_CONST               2 (None)
                    CALL                     2
                    GET_AWAITABLE            2
                    LOAD_CONST               2 (None)
           L12:     SEND                     3 (to L15)
           L13:     YIELD_VALUE              1
           L14:     RESUME                   3
                    JUMP_BACKWARD_NO_INTERRUPT 5 (to L12)
           L15:     END_SEND
                    POP_TOP
                    RETURN_VALUE
    
     190   L16:     LOAD_FAST                1 (resp)
                    LOAD_ATTR               19 (json + NULL|self)
                    CALL                     0
                    STORE_FAST               2 (data)
    
     191            LOAD_FAST                2 (data)
                    LOAD_ATTR                7 (get + NULL|self)
                    LOAD_CONST               7 ('tools')
                    BUILD_LIST               0
                    CALL                     2
    
     183   L17:     SWAP                     2
                    LOAD_CONST               2 (None)
                    LOAD_CONST               2 (None)
                    LOAD_CONST               2 (None)
                    CALL                     2
                    GET_AWAITABLE            2
                    LOAD_CONST               2 (None)
           L18:     SEND                     3 (to L21)
           L19:     YIELD_VALUE              1
           L20:     RESUME                   3
                    JUMP_BACKWARD_NO_INTERRUPT 5 (to L18)
           L21:     END_SEND
                    POP_TOP
                    RETURN_VALUE
           L22:     CLEANUP_THROW
           L23:     JUMP_BACKWARD_NO_INTERRUPT 161 (to L5)
    
     184   L24:     CLEANUP_THROW
           L25:     JUMP_BACKWARD_NO_INTERRUPT 124 (to L10)
    
     183   L26:     CLEANUP_THROW
           L27:     JUMP_BACKWARD_NO_INTERRUPT 60 (to L15)
           L28:     CLEANUP_THROW
           L29:     JUMP_BACKWARD_NO_INTERRUPT 11 (to L21)
           L30:     PUSH_EXC_INFO
                    WITH_EXCEPT_START
                    GET_AWAITABLE            2
                    LOAD_CONST               2 (None)
           L31:     SEND                     4 (to L35)
           L32:     YIELD_VALUE              1
           L33:     RESUME                   3
                    JUMP_BACKWARD_NO_INTERRUPT 5 (to L31)
           L34:     CLEANUP_THROW
           L35:     END_SEND
                    TO_BOOL
                    POP_JUMP_IF_TRUE         1 (to L36)
                    RERAISE                  2
           L36:     POP_TOP
           L37:     POP_EXCEPT
                    POP_TOP
                    POP_TOP
                    RETURN_CONST             2 (None)
    
      --   L38:     COPY                     3
                    POP_EXCEPT
                    RERAISE                  1
           L39:     CALL_INTRINSIC_1         3 (INTRINSIC_STOPITERATION_ERROR)
                    RERAISE                  1
    ExceptionTable:
      L1 to L3 -> L39 [0] lasti
      L3 to L4 -> L22 [3]
      L4 to L6 -> L39 [0] lasti
      L6 to L8 -> L30 [1] lasti
      L8 to L9 -> L24 [3]
      L9 to L11 -> L30 [1] lasti
      L11 to L13 -> L39 [0] lasti
      L13 to L14 -> L26 [3]
      L14 to L16 -> L39 [0] lasti
      L16 to L17 -> L30 [1] lasti
      L17 to L19 -> L39 [0] lasti
      L19 to L20 -> L28 [3]
      L20 to L23 -> L39 [0] lasti
      L24 to L25 -> L30 [1] lasti
      L26 to L27 -> L39 [0] lasti
      L28 to L29 -> L39 [0] lasti
      L30 to L32 -> L38 [3] lasti
      L32 to L33 -> L34 [6]
      L33 to L37 -> L38 [3] lasti
      L37 to L39 -> L39 [0] lasti
    
# --- Nested code object: _delete_tool ---
    # DOCSTRING: """Delete a tool by ID."""
    # co_names: ('httpx', 'AsyncClient', '_TIMEOUT', 'delete', '_API_BASE', '_headers', 'status_code', 'logger', 'info', 'warning')
    # co_varnames: ('tool_id', 'client', 'resp')
     194            RETURN_GENERATOR
                    POP_TOP
            L1:     RESUME                   0
    
     196            LOAD_GLOBAL              0 (httpx)
                    LOAD_ATTR                2 (AsyncClient)
                    PUSH_NULL
                    LOAD_GLOBAL              4 (_TIMEOUT)
                    LOAD_CONST               1 (('timeout',))
                    CALL_KW                  1
                    BEFORE_ASYNC_WITH
                    GET_AWAITABLE            1
                    LOAD_CONST               2 (None)
            L2:     SEND                     3 (to L5)
            L3:     YIELD_VALUE              1
            L4:     RESUME                   3
                    JUMP_BACKWARD_NO_INTERRUPT 5 (to L2)
            L5:     END_SEND
            L6:     STORE_FAST               1 (client)
    
     197            LOAD_FAST                1 (client)
                    LOAD_ATTR                7 (delete + NULL|self)
    
     198            LOAD_GLOBAL              8 (_API_BASE)
                    FORMAT_SIMPLE
                    LOAD_CONST               3 ('/convai/tools/')
                    LOAD_FAST                0 (tool_id)
                    FORMAT_SIMPLE
                    BUILD_STRING             3
                    LOAD_GLOBAL             11 (_headers + NULL)
                    CALL                     0
    
     197            LOAD_CONST               4 (('headers',))
                    CALL_KW                  2
                    GET_AWAITABLE            0
                    LOAD_CONST               2 (None)
            L7:     SEND                     3 (to L10)
            L8:     YIELD_VALUE              1
            L9:     RESUME                   3
                    JUMP_BACKWARD_NO_INTERRUPT 5 (to L7)
           L10:     END_SEND
                    STORE_FAST               2 (resp)
    
     200            LOAD_FAST                2 (resp)
                    LOAD_ATTR               12 (status_code)
                    LOAD_CONST               5 ((200, 204))
                    CONTAINS_OP              0
                    POP_JUMP_IF_FALSE       23 (to L11)
    
     201            LOAD_GLOBAL             14 (logger)
                    LOAD_ATTR               17 (info + NULL|self)
                    LOAD_CONST               6 ('ElevenLabs tool deleted: %s')
                    LOAD_FAST                0 (tool_id)
                    CALL                     2
                    POP_TOP
                    JUMP_FORWARD            32 (to L12)
    
     203   L11:     LOAD_GLOBAL             14 (logger)
                    LOAD_ATTR               19 (warning + NULL|self)
    
     204            LOAD_CONST               7 ('ElevenLabs delete tool %s: %d')
                    LOAD_FAST_LOAD_FAST      2 (tool_id, resp)
                    LOAD_ATTR               12 (status_code)
    
     203            CALL                     3
                    POP_TOP
    
     196   L12:     LOAD_CONST               2 (None)
                    LOAD_CONST               2 (None)
                    LOAD_CONST               2 (None)
                    CALL                     2
                    GET_AWAITABLE            2
                    LOAD_CONST               2 (None)
           L13:     SEND                     3 (to L16)
           L14:     YIELD_VALUE              1
           L15:     RESUME                   3
                    JUMP_BACKWARD_NO_INTERRUPT 5 (to L13)
           L16:     END_SEND
                    POP_TOP
                    RETURN_CONST             2 (None)
           L17:     CLEANUP_THROW
           L18:     JUMP_BACKWARD_NO_INTERRUPT 133 (to L5)
    
     197   L19:     CLEANUP_THROW
           L20:     JUMP_BACKWARD_NO_INTERRUPT 94 (to L10)
    
     196   L21:     CLEANUP_THROW
           L22:     JUMP_BACKWARD_NO_INTERRUPT 9 (to L16)
           L23:     PUSH_EXC_INFO
                    WITH_EXCEPT_START
                    GET_AWAITABLE            2
                    LOAD_CONST               2 (None)
           L24:     SEND                     4 (to L28)
           L25:     YIELD_VALUE              1
           L26:     RESUME                   3
                    JUMP_BACKWARD_NO_INTERRUPT 5 (to L24)
           L27:     CLEANUP_THROW
           L28:     END_SEND
                    TO_BOOL
                    POP_JUMP_IF_TRUE         1 (to L29)
                    RERAISE                  2
           L29:     POP_TOP
           L30:     POP_EXCEPT
                    POP_TOP
                    POP_TOP
                    RETURN_CONST             2 (None)
    
      --   L31:     COPY                     3
                    POP_EXCEPT
                    RERAISE                  1
           L32:     CALL_INTRINSIC_1         3 (INTRINSIC_STOPITERATION_ERROR)
                    RERAISE                  1
    ExceptionTable:
      L1 to L3 -> L32 [0] lasti
      L3 to L4 -> L17 [3]
      L4 to L6 -> L32 [0] lasti
      L6 to L8 -> L23 [1] lasti
      L8 to L9 -> L19 [3]
      L9 to L12 -> L23 [1] lasti
      L12 to L14 -> L32 [0] lasti
      L14 to L15 -> L21 [2]
      L15 to L18 -> L32 [0] lasti
      L19 to L20 -> L23 [1] lasti
      L21 to L22 -> L32 [0] lasti
      L23 to L25 -> L31 [3] lasti
      L25 to L26 -> L27 [6]
      L26 to L30 -> L31 [3] lasti
      L30 to L32 -> L32 [0] lasti
    
# --- Nested code object: _update_tool ---
    # DOCSTRING: """Update an existing tool via PATCH."""
    # co_names: ('httpx', 'AsyncClient', '_TIMEOUT', 'patch', '_API_BASE', '_headers', 'status_code', 'logger', 'error', 'text', 'info')
    # co_varnames: ('tool_id', 'body', 'client', 'resp')
     208            RETURN_GENERATOR
                    POP_TOP
            L1:     RESUME                   0
    
     210            LOAD_GLOBAL              0 (httpx)
                    LOAD_ATTR                2 (AsyncClient)
                    PUSH_NULL
                    LOAD_GLOBAL              4 (_TIMEOUT)
                    LOAD_CONST               1 (('timeout',))
                    CALL_KW                  1
                    BEFORE_ASYNC_WITH
                    GET_AWAITABLE            1
                    LOAD_CONST               2 (None)
            L2:     SEND                     3 (to L5)
            L3:     YIELD_VALUE              1
            L4:     RESUME                   3
                    JUMP_BACKWARD_NO_INTERRUPT 5 (to L2)
            L5:     END_SEND
            L6:     STORE_FAST               2 (client)
    
     211            LOAD_FAST                2 (client)
                    LOAD_ATTR                7 (patch + NULL|self)
    
     212            LOAD_GLOBAL              8 (_API_BASE)
                    FORMAT_SIMPLE
                    LOAD_CONST               3 ('/convai/tools/')
                    LOAD_FAST                0 (tool_id)
                    FORMAT_SIMPLE
                    BUILD_STRING             3
    
     213            LOAD_FAST                1 (body)
    
     214            LOAD_GLOBAL             11 (_headers + NULL)
                    CALL                     0
    
     211            LOAD_CONST               4 (('json', 'headers'))
                    CALL_KW                  3
                    GET_AWAITABLE            0
                    LOAD_CONST               2 (None)
            L7:     SEND                     3 (to L10)
            L8:     YIELD_VALUE              1
            L9:     RESUME                   3
                    JUMP_BACKWARD_NO_INTERRUPT 5 (to L7)
           L10:     END_SEND
                    STORE_FAST               3 (resp)
    
     216            LOAD_FAST                3 (resp)
                    LOAD_ATTR               12 (status_code)
                    LOAD_CONST               5 ((200, 201))
                    CONTAINS_OP              1
                    POP_JUMP_IF_FALSE       47 (to L11)
    
     217            LOAD_GLOBAL             14 (logger)
                    LOAD_ATTR               17 (error + NULL|self)
    
     218            LOAD_CONST               6 ('ElevenLabs update tool %s failed: %d %s')
    
     219            LOAD_FAST_LOAD_FAST      3 (tool_id, resp)
                    LOAD_ATTR               12 (status_code)
                    LOAD_FAST                3 (resp)
                    LOAD_ATTR               18 (text)
                    LOAD_CONST               2 (None)
                    LOAD_CONST               7 (300)
                    BINARY_SLICE
    
     217            CALL                     4
                    POP_TOP
                    JUMP_FORWARD            22 (to L12)
    
     222   L11:     LOAD_GLOBAL             14 (logger)
                    LOAD_ATTR               21 (info + NULL|self)
                    LOAD_CONST               8 ('ElevenLabs tool updated: %s')
                    LOAD_FAST                0 (tool_id)
                    CALL                     2
                    POP_TOP
    
     210   L12:     LOAD_CONST               2 (None)
                    LOAD_CONST               2 (None)
                    LOAD_CONST               2 (None)
                    CALL                     2
                    GET_AWAITABLE            2
                    LOAD_CONST               2 (None)
           L13:     SEND                     3 (to L16)
           L14:     YIELD_VALUE              1
           L15:     RESUME                   3
                    JUMP_BACKWARD_NO_INTERRUPT 5 (to L13)
           L16:     END_SEND
                    POP_TOP
                    RETURN_CONST             2 (None)
           L17:     CLEANUP_THROW
           L18:     JUMP_BACKWARD_NO_INTERRUPT 148 (to L5)
    
     211   L19:     CLEANUP_THROW
           L20:     JUMP_BACKWARD_NO_INTERRUPT 108 (to L10)
    
     210   L21:     CLEANUP_THROW
           L22:     JUMP_BACKWARD_NO_INTERRUPT 9 (to L16)
           L23:     PUSH_EXC_INFO
                    WITH_EXCEPT_START
                    GET_AWAITABLE            2
                    LOAD_CONST               2 (None)
           L24:     SEND                     4 (to L28)
           L25:     YIELD_VALUE              1
           L26:     RESUME                   3
                    JUMP_BACKWARD_NO_INTERRUPT 5 (to L24)
           L27:     CLEANUP_THROW
           L28:     END_SEND
                    TO_BOOL
                    POP_JUMP_IF_TRUE         1 (to L29)
                    RERAISE                  2
           L29:     POP_TOP
           L30:     POP_EXCEPT
                    POP_TOP
                    POP_TOP
                    RETURN_CONST             2 (None)
    
      --   L31:     COPY                     3
                    POP_EXCEPT
                    RERAISE                  1
           L32:     CALL_INTRINSIC_1         3 (INTRINSIC_STOPITERATION_ERROR)
                    RERAISE                  1
    ExceptionTable:
      L1 to L3 -> L32 [0] lasti
      L3 to L4 -> L17 [3]
      L4 to L6 -> L32 [0] lasti
      L6 to L8 -> L23 [1] lasti
      L8 to L9 -> L19 [3]
      L9 to L12 -> L23 [1] lasti
      L12 to L14 -> L32 [0] lasti
      L14 to L15 -> L21 [2]
      L15 to L18 -> L32 [0] lasti
      L19 to L20 -> L23 [1] lasti
      L21 to L22 -> L32 [0] lasti
      L23 to L25 -> L31 [3] lasti
      L25 to L26 -> L27 [6]
      L26 to L30 -> L31 [3] lasti
      L30 to L32 -> L32 [0] lasti
    
# --- Nested code object: ensure_booking_tools ---
    # DOCSTRING: """Ensure the two MattBot booking tools exist, creating if needed.

Returns the list of tool IDs for [get_available_slots, book_appointment].
"""
    # co_names: ('_list_tools', 'get', 'startswith', '_MATTBOT_TOOL_PREFIX', '_availability_tool_body', '_booking_tool_body', '_update_tool', '_create_tool')
    # co_varnames: ('webhook_url', 'tool_secret', 'existing', 'mattbot_tools', 't', 'tc', 'name', 'avail_name', 'book_name', 'avail_body', 'book_body', 'avail_id', 'book_id')
     225            RETURN_GENERATOR
                    POP_TOP
            L1:     RESUME                   0
    
     232            LOAD_GLOBAL              1 (_list_tools + NULL)
                    CALL                     0
                    GET_AWAITABLE            0
                    LOAD_CONST               1 (None)
            L2:     SEND                     3 (to L5)
            L3:     YIELD_VALUE              1
            L4:     RESUME                   3
                    JUMP_BACKWARD_NO_INTERRUPT 5 (to L2)
            L5:     END_SEND
                    STORE_FAST               2 (existing)
    
     234            BUILD_MAP                0
                    STORE_FAST               3 (mattbot_tools)
    
     235            LOAD_FAST                2 (existing)
                    GET_ITER
            L6:     FOR_ITER                74 (to L9)
                    STORE_FAST               4 (t)
    
     236            LOAD_FAST                4 (t)
                    LOAD_ATTR                3 (get + NULL|self)
                    LOAD_CONST               2 ('tool_config')
                    BUILD_MAP                0
                    CALL                     2
                    STORE_FAST               5 (tc)
    
     237            LOAD_FAST                5 (tc)
                    LOAD_ATTR                3 (get + NULL|self)
                    LOAD_CONST               3 ('name')
                    LOAD_CONST               4 ('')
                    CALL                     2
                    STORE_FAST               6 (name)
    
     238            LOAD_FAST                6 (name)
                    LOAD_ATTR                5 (startswith + NULL|self)
                    LOAD_GLOBAL              6 (_MATTBOT_TOOL_PREFIX)
                    CALL                     1
                    TO_BOOL
            L7:     POP_JUMP_IF_TRUE         2 (to L8)
                    JUMP_BACKWARD           67 (to L6)
    
     239    L8:     LOAD_FAST                4 (t)
                    LOAD_CONST               5 ('id')
                    BINARY_SUBSCR
                    LOAD_FAST_LOAD_FAST     54 (mattbot_tools, name)
                    STORE_SUBSCR
                    JUMP_BACKWARD           76 (to L6)
    
     235    L9:     END_FOR
                    POP_TOP
    
     241            LOAD_GLOBAL              6 (_MATTBOT_TOOL_PREFIX)
                    FORMAT_SIMPLE
                    LOAD_CONST               6 ('get_available_slots')
                    BUILD_STRING             2
                    STORE_FAST               7 (avail_name)
    
     242            LOAD_GLOBAL              6 (_MATTBOT_TOOL_PREFIX)
                    FORMAT_SIMPLE
                    LOAD_CONST               7 ('book_appointment')
                    BUILD_STRING             2
                    STORE_FAST               8 (book_name)
    
     244            LOAD_GLOBAL              9 (_availability_tool_body + NULL)
                    LOAD_FAST_LOAD_FAST      1 (webhook_url, tool_secret)
                    CALL                     2
                    STORE_FAST               9 (avail_body)
    
     245            LOAD_GLOBAL             11 (_booking_tool_body + NULL)
                    LOAD_FAST_LOAD_FAST      1 (webhook_url, tool_secret)
                    CALL                     2
                    STORE_FAST              10 (book_body)
    
     247            LOAD_FAST_LOAD_FAST    115 (avail_name, mattbot_tools)
                    CONTAINS_OP              0
                    POP_JUMP_IF_FALSE       27 (to L14)
    
     248            LOAD_GLOBAL             13 (_update_tool + NULL)
                    LOAD_FAST_LOAD_FAST     55 (mattbot_tools, avail_name)
                    BINARY_SUBSCR
                    LOAD_FAST                9 (avail_body)
                    CALL                     2
                    GET_AWAITABLE            0
                    LOAD_CONST               1 (None)
           L10:     SEND                     3 (to L13)
           L11:     YIELD_VALUE              1
           L12:     RESUME                   3
                    JUMP_BACKWARD_NO_INTERRUPT 5 (to L10)
           L13:     END_SEND
                    POP_TOP
    
     249            LOAD_FAST_LOAD_FAST     55 (mattbot_tools, avail_name)
                    BINARY_SUBSCR
                    STORE_FAST              11 (avail_id)
                    JUMP_FORWARD            19 (to L19)
    
     251   L14:     LOAD_GLOBAL             15 (_create_tool + NULL)
                    LOAD_FAST                9 (avail_body)
                    CALL                     1
                    GET_AWAITABLE            0
                    LOAD_CONST               1 (None)
           L15:     SEND                     3 (to L18)
           L16:     YIELD_VALUE              1
           L17:     RESUME                   3
                    JUMP_BACKWARD_NO_INTERRUPT 5 (to L15)
           L18:     END_SEND
                    STORE_FAST              11 (avail_id)
    
     253   L19:     LOAD_FAST_LOAD_FAST    131 (book_name, mattbot_tools)
                    CONTAINS_OP              0
                    POP_JUMP_IF_FALSE       29 (to L24)
    
     254            LOAD_GLOBAL             13 (_update_tool + NULL)
                    LOAD_FAST_LOAD_FAST     56 (mattbot_tools, book_name)
                    BINARY_SUBSCR
                    LOAD_FAST               10 (book_body)
                    CALL                     2
                    GET_AWAITABLE            0
                    LOAD_CONST               1 (None)
           L20:     SEND                     3 (to L23)
           L21:     YIELD_VALUE              1
           L22:     RESUME                   3
                    JUMP_BACKWARD_NO_INTERRUPT 5 (to L20)
           L23:     END_SEND
                    POP_TOP
    
     255            LOAD_FAST_LOAD_FAST     56 (mattbot_tools, book_name)
                    BINARY_SUBSCR
                    STORE_FAST              12 (book_id)
    
     259            LOAD_FAST_LOAD_FAST    188 (avail_id, book_id)
                    BUILD_LIST               2
                    RETURN_VALUE
    
     257   L24:     LOAD_GLOBAL             15 (_create_tool + NULL)
                    LOAD_FAST               10 (book_body)
                    CALL                     1
                    GET_AWAITABLE            0
                    LOAD_CONST               1 (None)
           L25:     SEND                     3 (to L28)
           L26:     YIELD_VALUE              1
           L27:     RESUME                   3
                    JUMP_BACKWARD_NO_INTERRUPT 5 (to L25)
           L28:     END_SEND
                    STORE_FAST              12 (book_id)
    
     259            LOAD_FAST_LOAD_FAST    188 (avail_id, book_id)
                    BUILD_LIST               2
                    RETURN_VALUE
    
     232   L29:     CLEANUP_THROW
           L30:     JUMP_BACKWARD_NO_INTERRUPT 233 (to L5)
    
     248   L31:     CLEANUP_THROW
           L32:     JUMP_BACKWARD_NO_INTERRUPT 86 (to L13)
    
     251   L33:     CLEANUP_THROW
           L34:     JUMP_BACKWARD_NO_INTERRUPT 64 (to L18)
    
     254   L35:     CLEANUP_THROW
           L36:     JUMP_BACKWARD_NO_INTERRUPT 39 (to L23)
    
     257   L37:     CLEANUP_THROW
           L38:     JUMP_BACKWARD_NO_INTERRUPT 15 (to L28)
    
      --   L39:     CALL_INTRINSIC_1         3 (INTRINSIC_STOPITERATION_ERROR)
                    RERAISE                  1
    ExceptionTable:
      L1 to L3 -> L39 [0] lasti
      L3 to L4 -> L29 [2]
      L4 to L7 -> L39 [0] lasti
      L8 to L11 -> L39 [0] lasti
      L11 to L12 -> L31 [2]
      L12 to L16 -> L39 [0] lasti
      L16 to L17 -> L33 [2]
      L17 to L21 -> L39 [0] lasti
      L21 to L22 -> L35 [2]
      L22 to L26 -> L39 [0] lasti
      L26 to L27 -> L37 [2]
      L27 to L30 -> L39 [0] lasti
      L31 to L32 -> L39 [0] lasti
      L33 to L34 -> L39 [0] lasti
      L35 to L36 -> L39 [0] lasti
      L37 to L38 -> L39 [0] lasti
    
# --- Nested code object: build_booking_tool_config ---
    # DOCSTRING: """Deprecated — use ensure_booking_tools() instead."""
    # co_names: ('_booking_tool_body',)
    # co_varnames: ('webhook_base_url', 'tool_secret')
    263           RESUME                   0
    
    265           LOAD_GLOBAL              1 (_booking_tool_body + NULL)
                  LOAD_FAST                0 (webhook_base_url)
                  FORMAT_SIMPLE
                  LOAD_CONST               1 ('/webhooks/elevenlabs/tool')
                  BUILD_STRING             2
                  CALL                     1
                  RETURN_VALUE
    
# --- Nested code object: build_availability_tool_config ---
    # DOCSTRING: """Deprecated — use ensure_booking_tools() instead."""
    # co_names: ('_availability_tool_body',)
    # co_varnames: ('webhook_base_url', 'tool_secret')
    268           RESUME                   0
    
    272           LOAD_GLOBAL              1 (_availability_tool_body + NULL)
    
    273           LOAD_FAST                0 (webhook_base_url)
                  FORMAT_SIMPLE
                  LOAD_CONST               1 ('/webhooks/elevenlabs/tool')
                  BUILD_STRING             2
    
    272           CALL                     1
                  RETURN_VALUE
    
# --- Nested code object: create_agent ---
    # DOCSTRING: """Create an ElevenLabs conversational agent. Returns the raw API response dict."""
    # co_names: ('TURN_EAGERNESS_MAP', 'get', 'httpx', 'AsyncClient', '_TIMEOUT', 'post', '_API_BASE', '_headers', 'status_code', 'logger', 'error', 'text', 'raise_for_status', 'json', 'info')
    # co_varnames: ('name', 'system_prompt', 'first_message', 'voice_id', 'language', 'max_duration_seconds', 'temperament_preset', 'silence_end_call_timeout', 'custom_tools', 'tool_ids', 'turn_eagerness', 'prompt_cfg', 'payload', 'client', 'resp', 'data')
     282            RETURN_GENERATOR
                    POP_TOP
            L1:     RESUME                   0
    
     296            LOAD_GLOBAL              0 (TURN_EAGERNESS_MAP)
                    LOAD_ATTR                3 (get + NULL|self)
                    LOAD_FAST                6 (temperament_preset)
                    LOAD_CONST               1 ('normal')
                    CALL                     2
                    STORE_FAST              10 (turn_eagerness)
    
     298            LOAD_CONST               2 ('prompt')
                    LOAD_FAST                1 (system_prompt)
                    BUILD_MAP                1
                    STORE_FAST              11 (prompt_cfg)
    
     299            LOAD_FAST                9 (tool_ids)
                    TO_BOOL
                    POP_JUMP_IF_FALSE        4 (to L2)
    
     300            LOAD_FAST_LOAD_FAST    155 (tool_ids, prompt_cfg)
                    LOAD_CONST               3 ('tool_ids')
                    STORE_SUBSCR
    
     303    L2:     LOAD_FAST                0 (name)
    
     306            LOAD_FAST               11 (prompt_cfg)
    
     307            LOAD_FAST                2 (first_message)
    
     308            LOAD_FAST                4 (language)
    
     310            LOAD_CONST               4 ('end_call')
    
     311            LOAD_CONST               5 ('system')
    
     312            LOAD_CONST               4 ('end_call')
    
     313            LOAD_CONST               6 ('system_tool_type')
                    LOAD_CONST               4 ('end_call')
                    BUILD_MAP                1
    
     310            LOAD_CONST               7 (('type', 'name', 'params'))
                    BUILD_CONST_KEY_MAP      3
    
     309            BUILD_MAP                1
    
     305            LOAD_CONST               8 (('prompt', 'first_message', 'language', 'built_in_tools'))
                    BUILD_CONST_KEY_MAP      4
    
     317            BUILD_MAP                0
    
     319            LOAD_CONST               9 ('max_duration_seconds')
                    LOAD_FAST                5 (max_duration_seconds)
    
     318            BUILD_MAP                1
    
     322            LOAD_FAST               10 (turn_eagerness)
    
     323            LOAD_FAST                7 (silence_end_call_timeout)
    
     321            LOAD_CONST              10 (('turn_eagerness', 'silence_end_call_timeout'))
                    BUILD_CONST_KEY_MAP      2
    
     304            LOAD_CONST              11 (('agent', 'tts', 'conversation', 'turn'))
                    BUILD_CONST_KEY_MAP      4
    
     302            LOAD_CONST              12 (('name', 'conversation_config'))
                    BUILD_CONST_KEY_MAP      2
                    STORE_FAST              12 (payload)
    
     328            LOAD_FAST                3 (voice_id)
                    TO_BOOL
                    POP_JUMP_IF_FALSE       10 (to L3)
    
     329            LOAD_FAST_LOAD_FAST     60 (voice_id, payload)
                    LOAD_CONST              13 ('conversation_config')
                    BINARY_SUBSCR
                    LOAD_CONST              14 ('tts')
                    BINARY_SUBSCR
                    LOAD_CONST              15 ('voice_id')
                    STORE_SUBSCR
    
     331    L3:     LOAD_GLOBAL              4 (httpx)
                    LOAD_ATTR                6 (AsyncClient)
                    PUSH_NULL
                    LOAD_GLOBAL              8 (_TIMEOUT)
                    LOAD_CONST              16 (('timeout',))
                    CALL_KW                  1
                    BEFORE_ASYNC_WITH
                    GET_AWAITABLE            1
                    LOAD_CONST              17 (None)
            L4:     SEND                     3 (to L7)
            L5:     YIELD_VALUE              1
            L6:     RESUME                   3
                    JUMP_BACKWARD_NO_INTERRUPT 5 (to L4)
            L7:     END_SEND
            L8:     STORE_FAST              13 (client)
    
     332            LOAD_FAST               13 (client)
                    LOAD_ATTR               11 (post + NULL|self)
    
     333            LOAD_GLOBAL             12 (_API_BASE)
                    FORMAT_SIMPLE
                    LOAD_CONST              18 ('/convai/agents/create')
                    BUILD_STRING             2
    
     334            LOAD_FAST               12 (payload)
    
     335            LOAD_GLOBAL             15 (_headers + NULL)
                    CALL                     0
    
     332            LOAD_CONST              19 (('json', 'headers'))
                    CALL_KW                  3
                    GET_AWAITABLE            0
                    LOAD_CONST              17 (None)
            L9:     SEND                     3 (to L12)
           L10:     YIELD_VALUE              1
           L11:     RESUME                   3
                    JUMP_BACKWARD_NO_INTERRUPT 5 (to L9)
           L12:     END_SEND
                    STORE_FAST              14 (resp)
    
     337            LOAD_FAST               14 (resp)
                    LOAD_ATTR               16 (status_code)
                    LOAD_CONST              20 ((200, 201))
                    CONTAINS_OP              1
                    POP_JUMP_IF_FALSE       62 (to L13)
    
     338            LOAD_GLOBAL             18 (logger)
                    LOAD_ATTR               21 (error + NULL|self)
    
     339            LOAD_CONST              21 ('ElevenLabs create_agent failed: %d %s')
    
     340            LOAD_FAST               14 (resp)
                    LOAD_ATTR               16 (status_code)
    
     341            LOAD_FAST               14 (resp)
                    LOAD_ATTR               22 (text)
                    LOAD_CONST              17 (None)
                    LOAD_CONST              22 (500)
                    BINARY_SLICE
    
     338            CALL                     3
                    POP_TOP
    
     343            LOAD_FAST               14 (resp)
                    LOAD_ATTR               25 (raise_for_status + NULL|self)
                    CALL                     0
                    POP_TOP
    
     345   L13:     LOAD_FAST               14 (resp)
                    LOAD_ATTR               27 (json + NULL|self)
                    CALL                     0
                    STORE_FAST              15 (data)
    
     346            LOAD_GLOBAL             18 (logger)
                    LOAD_ATTR               29 (info + NULL|self)
    
     347            LOAD_CONST              23 ('ElevenLabs agent created: id=%s name=%s')
    
     348            LOAD_FAST               15 (data)
                    LOAD_ATTR                3 (get + NULL|self)
                    LOAD_CONST              24 ('agent_id')
                    LOAD_CONST              25 ('?')
                    CALL                     2
    
     349            LOAD_FAST                0 (name)
    
     346            CALL                     3
                    POP_TOP
    
     351            LOAD_FAST               15 (data)
    
     331   L14:     SWAP                     2
                    LOAD_CONST              17 (None)
                    LOAD_CONST              17 (None)
                    LOAD_CONST              17 (None)
                    CALL                     2
                    GET_AWAITABLE            2
                    LOAD_CONST              17 (None)
           L15:     SEND                     3 (to L18)
           L16:     YIELD_VALUE              1
           L17:     RESUME                   3
                    JUMP_BACKWARD_NO_INTERRUPT 5 (to L15)
           L18:     END_SEND
                    POP_TOP
                    RETURN_VALUE
           L19:     CLEANUP_THROW
           L20:     JUMP_BACKWARD_NO_INTERRUPT 196 (to L7)
    
     332   L21:     CLEANUP_THROW
           L22:     JUMP_BACKWARD_NO_INTERRUPT 158 (to L12)
    
     331   L23:     CLEANUP_THROW
           L24:     JUMP_BACKWARD_NO_INTERRUPT 9 (to L18)
           L25:     PUSH_EXC_INFO
                    WITH_EXCEPT_START
                    GET_AWAITABLE            2
                    LOAD_CONST              17 (None)
           L26:     SEND                     4 (to L30)
           L27:     YIELD_VALUE              1
           L28:     RESUME                   3
                    JUMP_BACKWARD_NO_INTERRUPT 5 (to L26)
           L29:     CLEANUP_THROW
           L30:     END_SEND
                    TO_BOOL
                    POP_JUMP_IF_TRUE         1 (to L31)
                    RERAISE                  2
           L31:     POP_TOP
           L32:     POP_EXCEPT
                    POP_TOP
                    POP_TOP
                    RETURN_CONST            17 (None)
    
      --   L33:     COPY                     3
                    POP_EXCEPT
                    RERAISE                  1
           L34:     CALL_INTRINSIC_1         3 (INTRINSIC_STOPITERATION_ERROR)
                    RERAISE                  1
    ExceptionTable:
      L1 to L5 -> L34 [0] lasti
      L5 to L6 -> L19 [3]
      L6 to L8 -> L34 [0] lasti
      L8 to L10 -> L25 [1] lasti
      L10 to L11 -> L21 [3]
      L11 to L14 -> L25 [1] lasti
      L14 to L16 -> L34 [0] lasti
      L16 to L17 -> L23 [3]
      L17 to L20 -> L34 [0] lasti
      L21 to L22 -> L25 [1] lasti
      L23 to L24 -> L34 [0] lasti
      L25 to L27 -> L33 [3] lasti
      L27 to L28 -> L29 [6]
      L28 to L32 -> L33 [3] lasti
      L32 to L34 -> L34 [0] lasti
    
# --- Nested code object: update_agent ---
    # DOCSTRING: """Patch an existing ElevenLabs agent. Only non-None fields are sent."""
    # co_names: ('TURN_EAGERNESS_MAP', 'get', 'httpx', 'AsyncClient', '_TIMEOUT', 'patch', '_API_BASE', '_headers', 'status_code', 'logger', 'error', 'text', 'raise_for_status', 'json', 'info')
    # co_varnames: ('el_agent_id', 'system_prompt', 'first_message', 'voice_id', 'language', 'max_duration_seconds', 'temperament_preset', 'silence_end_call_timeout', 'enable_end_call_tool', 'custom_tools', 'tool_ids', 'payload', 'agent_cfg', 'tts_cfg', 'conv_cfg', 'turn_cfg', 'prompt_cfg', 'turn_eagerness', 'client', 'resp', 'data')
     354            RETURN_GENERATOR
                    POP_TOP
            L1:     RESUME                   0
    
     369            LOAD_CONST               1 ('conversation_config')
                    BUILD_MAP                0
                    BUILD_MAP                1
                    STORE_FAST              11 (payload)
    
     370            BUILD_MAP                0
                    STORE_FAST              12 (agent_cfg)
    
     371            BUILD_MAP                0
                    STORE_FAST              13 (tts_cfg)
    
     372            BUILD_MAP                0
                    STORE_FAST              14 (conv_cfg)
    
     373            BUILD_MAP                0
                    STORE_FAST              15 (turn_cfg)
    
     375            BUILD_MAP                0
                    STORE_FAST              16 (prompt_cfg)
    
     376            LOAD_FAST                1 (system_prompt)
                    POP_JUMP_IF_NONE         5 (to L2)
    
     377            LOAD_FAST                1 (system_prompt)
                    LOAD_FAST               16 (prompt_cfg)
                    LOAD_CONST               3 ('prompt')
                    STORE_SUBSCR
    
     378    L2:     LOAD_FAST               10 (tool_ids)
                    POP_JUMP_IF_NONE         5 (to L3)
    
     379            LOAD_FAST               10 (tool_ids)
                    LOAD_FAST               16 (prompt_cfg)
                    LOAD_CONST               4 ('tool_ids')
                    STORE_SUBSCR
    
     380    L3:     LOAD_FAST               16 (prompt_cfg)
                    TO_BOOL
                    POP_JUMP_IF_FALSE        5 (to L4)
    
     381            LOAD_FAST               16 (prompt_cfg)
                    LOAD_FAST               12 (agent_cfg)
                    LOAD_CONST               3 ('prompt')
                    STORE_SUBSCR
    
     383    L4:     LOAD_FAST                2 (first_message)
                    POP_JUMP_IF_NONE         4 (to L5)
    
     384            LOAD_FAST_LOAD_FAST     44 (first_message, agent_cfg)
                    LOAD_CONST               5 ('first_message')
                    STORE_SUBSCR
    
     385    L5:     LOAD_FAST                4 (language)
                    POP_JUMP_IF_NONE         4 (to L6)
    
     386            LOAD_FAST_LOAD_FAST     76 (language, agent_cfg)
                    LOAD_CONST               6 ('language')
                    STORE_SUBSCR
    
     387    L6:     LOAD_FAST                8 (enable_end_call_tool)
                    TO_BOOL
                    POP_JUMP_IF_FALSE       13 (to L7)
    
     389            LOAD_CONST               7 ('end_call')
    
     390            LOAD_CONST               8 ('system')
    
     391            LOAD_CONST               7 ('end_call')
    
     392            LOAD_CONST               9 ('system_tool_type')
                    LOAD_CONST               7 ('end_call')
                    BUILD_MAP                1
    
     389            LOAD_CONST              10 (('type', 'name', 'params'))
                    BUILD_CONST_KEY_MAP      3
    
     388            BUILD_MAP                1
                    LOAD_FAST               12 (agent_cfg)
                    LOAD_CONST              11 ('built_in_tools')
                    STORE_SUBSCR
    
     396    L7:     LOAD_FAST                3 (voice_id)
                    POP_JUMP_IF_NONE         4 (to L8)
    
     397            LOAD_FAST_LOAD_FAST     61 (voice_id, tts_cfg)
                    LOAD_CONST              12 ('voice_id')
                    STORE_SUBSCR
    
     399    L8:     LOAD_FAST                5 (max_duration_seconds)
                    POP_JUMP_IF_NONE         4 (to L9)
    
     400            LOAD_FAST_LOAD_FAST     94 (max_duration_seconds, conv_cfg)
                    LOAD_CONST              13 ('max_duration_seconds')
                    STORE_SUBSCR
    
     402    L9:     LOAD_FAST                6 (temperament_preset)
                    POP_JUMP_IF_NONE        27 (to L10)
    
     403            LOAD_GLOBAL              0 (TURN_EAGERNESS_MAP)
                    LOAD_ATTR                3 (get + NULL|self)
                    LOAD_FAST                6 (temperament_preset)
                    LOAD_CONST              14 ('normal')
                    CALL                     2
                    STORE_FAST              17 (turn_eagerness)
    
     404            LOAD_FAST               17 (turn_eagerness)
                    LOAD_FAST               15 (turn_cfg)
                    LOAD_CONST              15 ('turn_eagerness')
                    STORE_SUBSCR
    
     405   L10:     LOAD_FAST                7 (silence_end_call_timeout)
                    POP_JUMP_IF_NONE         4 (to L11)
    
     406            LOAD_FAST_LOAD_FAST    127 (silence_end_call_timeout, turn_cfg)
                    LOAD_CONST              16 ('silence_end_call_timeout')
                    STORE_SUBSCR
    
     408   L11:     LOAD_FAST               12 (agent_cfg)
                    TO_BOOL
                    POP_JUMP_IF_FALSE        7 (to L12)
    
     409            LOAD_FAST_LOAD_FAST    203 (agent_cfg, payload)
                    LOAD_CONST               1 ('conversation_config')
                    BINARY_SUBSCR
                    LOAD_CONST              17 ('agent')
                    STORE_SUBSCR
    
     410   L12:     LOAD_FAST               13 (tts_cfg)
                    TO_BOOL
                    POP_JUMP_IF_FALSE        7 (to L13)
    
     411            LOAD_FAST_LOAD_FAST    219 (tts_cfg, payload)
                    LOAD_CONST               1 ('conversation_config')
                    BINARY_SUBSCR
                    LOAD_CONST              18 ('tts')
                    STORE_SUBSCR
    
     412   L13:     LOAD_FAST               14 (conv_cfg)
                    TO_BOOL
                    POP_JUMP_IF_FALSE        7 (to L14)
    
     413            LOAD_FAST_LOAD_FAST    235 (conv_cfg, payload)
                    LOAD_CONST               1 ('conversation_config')
                    BINARY_SUBSCR
                    LOAD_CONST              19 ('conversation')
                    STORE_SUBSCR
    
     414   L14:     LOAD_FAST               15 (turn_cfg)
                    TO_BOOL
                    POP_JUMP_IF_FALSE        7 (to L15)
    
     415            LOAD_FAST_LOAD_FAST    251 (turn_cfg, payload)
                    LOAD_CONST               1 ('conversation_config')
                    BINARY_SUBSCR
                    LOAD_CONST              20 ('turn')
                    STORE_SUBSCR
    
     417   L15:     LOAD_GLOBAL              4 (httpx)
                    LOAD_ATTR                6 (AsyncClient)
                    PUSH_NULL
                    LOAD_GLOBAL              8 (_TIMEOUT)
                    LOAD_CONST              21 (('timeout',))
                    CALL_KW                  1
                    BEFORE_ASYNC_WITH
                    GET_AWAITABLE            1
                    LOAD_CONST               2 (None)
           L16:     SEND                     3 (to L19)
           L17:     YIELD_VALUE              1
           L18:     RESUME                   3
                    JUMP_BACKWARD_NO_INTERRUPT 5 (to L16)
           L19:     END_SEND
           L20:     STORE_FAST              18 (client)
    
     418            LOAD_FAST               18 (client)
                    LOAD_ATTR               11 (patch + NULL|self)
    
     419            LOAD_GLOBAL             12 (_API_BASE)
                    FORMAT_SIMPLE
                    LOAD_CONST              22 ('/convai/agents/')
                    LOAD_FAST                0 (el_agent_id)
                    FORMAT_SIMPLE
                    BUILD_STRING             3
    
     420            LOAD_FAST               11 (payload)
    
     421            LOAD_GLOBAL             15 (_headers + NULL)
                    CALL                     0
    
     418            LOAD_CONST              23 (('json', 'headers'))
                    CALL_KW                  3
                    GET_AWAITABLE            0
                    LOAD_CONST               2 (None)
           L21:     SEND                     3 (to L24)
           L22:     YIELD_VALUE              1
           L23:     RESUME                   3
                    JUMP_BACKWARD_NO_INTERRUPT 5 (to L21)
           L24:     END_SEND
                    STORE_FAST              19 (resp)
    
     423            LOAD_FAST               19 (resp)
                    LOAD_ATTR               16 (status_code)
                    LOAD_CONST              24 ((200, 201))
                    CONTAINS_OP              1
                    POP_JUMP_IF_FALSE       62 (to L25)
    
     424            LOAD_GLOBAL             18 (logger)
                    LOAD_ATTR               21 (error + NULL|self)
    
     425            LOAD_CONST              25 ('ElevenLabs update_agent failed: %d %s')
    
     426            LOAD_FAST               19 (resp)
                    LOAD_ATTR               16 (status_code)
    
     427            LOAD_FAST               19 (resp)
                    LOAD_ATTR               22 (text)
                    LOAD_CONST               2 (None)
                    LOAD_CONST              26 (500)
                    BINARY_SLICE
    
     424            CALL                     3
                    POP_TOP
    
     429            LOAD_FAST               19 (resp)
                    LOAD_ATTR               25 (raise_for_status + NULL|self)
                    CALL                     0
                    POP_TOP
    
     430   L25:     LOAD_FAST               19 (resp)
                    LOAD_ATTR               27 (json + NULL|self)
                    CALL                     0
                    STORE_FAST              20 (data)
    
     431            LOAD_GLOBAL             18 (logger)
                    LOAD_ATTR               29 (info + NULL|self)
                    LOAD_CONST              27 ('ElevenLabs agent updated: id=%s')
                    LOAD_FAST                0 (el_agent_id)
                    CALL                     2
                    POP_TOP
    
     432            LOAD_FAST               20 (data)
    
     417   L26:     SWAP                     2
                    LOAD_CONST               2 (None)
                    LOAD_CONST               2 (None)
                    LOAD_CONST               2 (None)
                    CALL                     2
                    GET_AWAITABLE            2
                    LOAD_CONST               2 (None)
           L27:     SEND                     3 (to L30)
           L28:     YIELD_VALUE              1
           L29:     RESUME                   3
                    JUMP_BACKWARD_NO_INTERRUPT 5 (to L27)
           L30:     END_SEND
                    POP_TOP
                    RETURN_VALUE
           L31:     CLEANUP_THROW
           L32:     JUMP_BACKWARD_NO_INTERRUPT 181 (to L19)
    
     418   L33:     CLEANUP_THROW
           L34:     JUMP_BACKWARD_NO_INTERRUPT 141 (to L24)
    
     417   L35:     CLEANUP_THROW
           L36:     JUMP_BACKWARD_NO_INTERRUPT 9 (to L30)
           L37:     PUSH_EXC_INFO
                    WITH_EXCEPT_START
                    GET_AWAITABLE            2
                    LOAD_CONST               2 (None)
           L38:     SEND                     4 (to L42)
           L39:     YIELD_VALUE              1
           L40:     RESUME                   3
                    JUMP_BACKWARD_NO_INTERRUPT 5 (to L38)
           L41:     CLEANUP_THROW
           L42:     END_SEND
                    TO_BOOL
                    POP_JUMP_IF_TRUE         1 (to L43)
                    RERAISE                  2
           L43:     POP_TOP
           L44:     POP_EXCEPT
                    POP_TOP
                    POP_TOP
                    RETURN_CONST             2 (None)
    
      --   L45:     COPY                     3
                    POP_EXCEPT
                    RERAISE                  1
           L46:     CALL_INTRINSIC_1         3 (INTRINSIC_STOPITERATION_ERROR)
                    RERAISE                  1
    ExceptionTable:
      L1 to L17 -> L46 [0] lasti
      L17 to L18 -> L31 [3]
      L18 to L20 -> L46 [0] lasti
      L20 to L22 -> L37 [1] lasti
      L22 to L23 -> L33 [3]
      L23 to L26 -> L37 [1] lasti
      L26 to L28 -> L46 [0] lasti
      L28 to L29 -> L35 [3]
      L29 to L32 -> L46 [0] lasti
      L33 to L34 -> L37 [1] lasti
      L35 to L36 -> L46 [0] lasti
      L37 to L39 -> L45 [3] lasti
      L39 to L40 -> L41 [6]
      L40 to L44 -> L45 [3] lasti
      L44 to L46 -> L46 [0] lasti
    
# --- Nested code object: delete_agent ---
    # DOCSTRING: """Delete an ElevenLabs agent. Returns True on success."""
    # co_names: ('httpx', 'AsyncClient', '_TIMEOUT', 'delete', '_API_BASE', '_headers', 'status_code', 'logger', 'info', 'error', 'text')
    # co_varnames: ('el_agent_id', 'client', 'resp')
     435            RETURN_GENERATOR
                    POP_TOP
            L1:     RESUME                   0
    
     437            LOAD_GLOBAL              0 (httpx)
                    LOAD_ATTR                2 (AsyncClient)
                    PUSH_NULL
                    LOAD_GLOBAL              4 (_TIMEOUT)
                    LOAD_CONST               1 (('timeout',))
                    CALL_KW                  1
                    BEFORE_ASYNC_WITH
                    GET_AWAITABLE            1
                    LOAD_CONST               2 (None)
            L2:     SEND                     3 (to L5)
            L3:     YIELD_VALUE              1
            L4:     RESUME                   3
                    JUMP_BACKWARD_NO_INTERRUPT 5 (to L2)
            L5:     END_SEND
            L6:     STORE_FAST               1 (client)
    
     438            LOAD_FAST                1 (client)
                    LOAD_ATTR                7 (delete + NULL|self)
    
     439            LOAD_GLOBAL              8 (_API_BASE)
                    FORMAT_SIMPLE
                    LOAD_CONST               3 ('/convai/agents/')
                    LOAD_FAST                0 (el_agent_id)
                    FORMAT_SIMPLE
                    BUILD_STRING             3
    
     440            LOAD_GLOBAL             11 (_headers + NULL)
                    CALL                     0
    
     438            LOAD_CONST               4 (('headers',))
                    CALL_KW                  2
                    GET_AWAITABLE            0
                    LOAD_CONST               2 (None)
            L7:     SEND                     3 (to L10)
            L8:     YIELD_VALUE              1
            L9:     RESUME                   3
                    JUMP_BACKWARD_NO_INTERRUPT 5 (to L7)
           L10:     END_SEND
                    STORE_FAST               2 (resp)
    
     442            LOAD_FAST                2 (resp)
                    LOAD_ATTR               12 (status_code)
                    LOAD_CONST               5 ((200, 204))
                    CONTAINS_OP              0
                    POP_JUMP_IF_FALSE       40 (to L16)
    
     443            LOAD_GLOBAL             14 (logger)
                    LOAD_ATTR               17 (info + NULL|self)
                    LOAD_CONST               6 ('ElevenLabs agent deleted: id=%s')
                    LOAD_FAST                0 (el_agent_id)
                    CALL                     2
                    POP_TOP
    
     444            NOP
    
     437   L11:     LOAD_CONST               2 (None)
                    LOAD_CONST               2 (None)
                    LOAD_CONST               2 (None)
                    CALL                     2
                    GET_AWAITABLE            2
                    LOAD_CONST               2 (None)
           L12:     SEND                     3 (to L15)
           L13:     YIELD_VALUE              1
           L14:     RESUME                   3
                    JUMP_BACKWARD_NO_INTERRUPT 5 (to L12)
           L15:     END_SEND
                    POP_TOP
                    RETURN_CONST             7 (True)
    
     445   L16:     LOAD_GLOBAL             14 (logger)
                    LOAD_ATTR               19 (error + NULL|self)
    
     446            LOAD_CONST               8 ('ElevenLabs delete_agent failed: %d %s')
    
     447            LOAD_FAST                2 (resp)
                    LOAD_ATTR               12 (status_code)
    
     448            LOAD_FAST                2 (resp)
                    LOAD_ATTR               20 (text)
                    LOAD_CONST               2 (None)
                    LOAD_CONST               9 (500)
                    BINARY_SLICE
    
     445            CALL                     3
                    POP_TOP
    
     450            NOP
    
     437   L17:     LOAD_CONST               2 (None)
                    LOAD_CONST               2 (None)
                    LOAD_CONST               2 (None)
                    CALL                     2
                    GET_AWAITABLE            2
                    LOAD_CONST               2 (None)
           L18:     SEND                     3 (to L21)
           L19:     YIELD_VALUE              1
           L20:     RESUME                   3
                    JUMP_BACKWARD_NO_INTERRUPT 5 (to L18)
           L21:     END_SEND
                    POP_TOP
                    RETURN_CONST            10 (False)
           L22:     CLEANUP_THROW
           L23:     JUMP_BACKWARD_NO_INTERRUPT 165 (to L5)
    
     438   L24:     CLEANUP_THROW
           L25:     JUMP_BACKWARD_NO_INTERRUPT 126 (to L10)
    
     437   L26:     CLEANUP_THROW
           L27:     JUMP_BACKWARD_NO_INTERRUPT 73 (to L15)
           L28:     CLEANUP_THROW
           L29:     JUMP_BACKWARD_NO_INTERRUPT 11 (to L21)
           L30:     PUSH_EXC_INFO
                    WITH_EXCEPT_START
                    GET_AWAITABLE            2
                    LOAD_CONST               2 (None)
           L31:     SEND                     4 (to L35)
           L32:     YIELD_VALUE              1
           L33:     RESUME                   3
                    JUMP_BACKWARD_NO_INTERRUPT 5 (to L31)
           L34:     CLEANUP_THROW
           L35:     END_SEND
                    TO_BOOL
                    POP_JUMP_IF_TRUE         1 (to L36)
                    RERAISE                  2
           L36:     POP_TOP
           L37:     POP_EXCEPT
                    POP_TOP
                    POP_TOP
                    RETURN_CONST             2 (None)
    
      --   L38:     COPY                     3
                    POP_EXCEPT
                    RERAISE                  1
           L39:     CALL_INTRINSIC_1         3 (INTRINSIC_STOPITERATION_ERROR)
                    RERAISE                  1
    ExceptionTable:
      L1 to L3 -> L39 [0] lasti
      L3 to L4 -> L22 [3]
      L4 to L6 -> L39 [0] lasti
      L6 to L8 -> L30 [1] lasti
      L8 to L9 -> L24 [3]
      L9 to L11 -> L30 [1] lasti
      L11 to L13 -> L39 [0] lasti
      L13 to L14 -> L26 [2]
      L14 to L16 -> L39 [0] lasti
      L16 to L17 -> L30 [1] lasti
      L17 to L19 -> L39 [0] lasti
      L19 to L20 -> L28 [2]
      L20 to L23 -> L39 [0] lasti
      L24 to L25 -> L30 [1] lasti
      L26 to L27 -> L39 [0] lasti
      L28 to L29 -> L39 [0] lasti
      L30 to L32 -> L38 [3] lasti
      L32 to L33 -> L34 [6]
      L33 to L37 -> L38 [3] lasti
      L37 to L39 -> L39 [0] lasti
    
# --- Nested code object: fetch_voices ---
    # DOCSTRING: """Fetch all voices from ElevenLabs GET /v1/voices."""
    # co_names: ('httpx', 'AsyncClient', '_TIMEOUT', 'get', '_API_BASE', '_headers', 'status_code', 'logger', 'error', 'json')
    # co_varnames: ('client', 'resp', 'data', 'voices')
     458            RETURN_GENERATOR
                    POP_TOP
            L1:     RESUME                   0
    
     460            LOAD_GLOBAL              0 (httpx)
                    LOAD_ATTR                2 (AsyncClient)
                    PUSH_NULL
                    LOAD_GLOBAL              4 (_TIMEOUT)
                    LOAD_CONST               1 (('timeout',))
                    CALL_KW                  1
                    BEFORE_ASYNC_WITH
                    GET_AWAITABLE            1
                    LOAD_CONST               2 (None)
            L2:     SEND                     3 (to L5)
            L3:     YIELD_VALUE              1
            L4:     RESUME                   3
                    JUMP_BACKWARD_NO_INTERRUPT 5 (to L2)
            L5:     END_SEND
            L6:     STORE_FAST               0 (client)
    
     461            LOAD_FAST                0 (client)
                    LOAD_ATTR                7 (get + NULL|self)
                    LOAD_GLOBAL              8 (_API_BASE)
                    FORMAT_SIMPLE
                    LOAD_CONST               3 ('/voices')
                    BUILD_STRING             2
                    LOAD_GLOBAL             11 (_headers + NULL)
                    CALL                     0
                    LOAD_CONST               4 (('headers',))
                    CALL_KW                  2
                    GET_AWAITABLE            0
                    LOAD_CONST               2 (None)
            L7:     SEND                     3 (to L10)
            L8:     YIELD_VALUE              1
            L9:     RESUME                   3
                    JUMP_BACKWARD_NO_INTERRUPT 5 (to L7)
           L10:     END_SEND
                    STORE_FAST               1 (resp)
    
     462            LOAD_FAST                1 (resp)
                    LOAD_ATTR               12 (status_code)
                    LOAD_CONST               5 (200)
                    COMPARE_OP             119 (bool(!=))
                    POP_JUMP_IF_FALSE       51 (to L16)
    
     463            LOAD_GLOBAL             14 (logger)
                    LOAD_ATTR               17 (error + NULL|self)
                    LOAD_CONST               6 ('ElevenLabs fetch_voices failed: %d')
                    LOAD_FAST                1 (resp)
                    LOAD_ATTR               12 (status_code)
                    CALL                     2
                    POP_TOP
    
     464            BUILD_LIST               0
    
     460   L11:     SWAP                     2
                    LOAD_CONST               2 (None)
                    LOAD_CONST               2 (None)
                    LOAD_CONST               2 (None)
                    CALL                     2
                    GET_AWAITABLE            2
                    LOAD_CONST               2 (None)
           L12:     SEND                     3 (to L15)
           L13:     YIELD_VALUE              1
           L14:     RESUME                   3
                    JUMP_BACKWARD_NO_INTERRUPT 5 (to L12)
           L15:     END_SEND
                    POP_TOP
                    RETURN_VALUE
    
     465   L16:     LOAD_FAST                1 (resp)
                    LOAD_ATTR               19 (json + NULL|self)
                    CALL                     0
                    STORE_FAST               2 (data)
    
     466            LOAD_FAST                2 (data)
                    LOAD_ATTR                7 (get + NULL|self)
                    LOAD_CONST               7 ('voices')
                    BUILD_LIST               0
                    CALL                     2
                    STORE_FAST               3 (voices)
    
     467            LOAD_FAST                3 (voices)
    
     460   L17:     SWAP                     2
                    LOAD_CONST               2 (None)
                    LOAD_CONST               2 (None)
                    LOAD_CONST               2 (None)
                    CALL                     2
                    GET_AWAITABLE            2
                    LOAD_CONST               2 (None)
           L18:     SEND                     3 (to L21)
           L19:     YIELD_VALUE              1
           L20:     RESUME                   3
                    JUMP_BACKWARD_NO_INTERRUPT 5 (to L18)
           L21:     END_SEND
                    POP_TOP
                    RETURN_VALUE
           L22:     CLEANUP_THROW
           L23:     JUMP_BACKWARD_NO_INTERRUPT 163 (to L5)
    
     461   L24:     CLEANUP_THROW
           L25:     JUMP_BACKWARD_NO_INTERRUPT 126 (to L10)
    
     460   L26:     CLEANUP_THROW
           L27:     JUMP_BACKWARD_NO_INTERRUPT 62 (to L15)
           L28:     CLEANUP_THROW
           L29:     JUMP_BACKWARD_NO_INTERRUPT 11 (to L21)
           L30:     PUSH_EXC_INFO
                    WITH_EXCEPT_START
                    GET_AWAITABLE            2
                    LOAD_CONST               2 (None)
           L31:     SEND                     4 (to L35)
           L32:     YIELD_VALUE              1
           L33:     RESUME                   3
                    JUMP_BACKWARD_NO_INTERRUPT 5 (to L31)
           L34:     CLEANUP_THROW
           L35:     END_SEND
                    TO_BOOL
                    POP_JUMP_IF_TRUE         1 (to L36)
                    RERAISE                  2
           L36:     POP_TOP
           L37:     POP_EXCEPT
                    POP_TOP
                    POP_TOP
                    RETURN_CONST             2 (None)
    
      --   L38:     COPY                     3
                    POP_EXCEPT
                    RERAISE                  1
           L39:     CALL_INTRINSIC_1         3 (INTRINSIC_STOPITERATION_ERROR)
                    RERAISE                  1
    ExceptionTable:
      L1 to L3 -> L39 [0] lasti
      L3 to L4 -> L22 [3]
      L4 to L6 -> L39 [0] lasti
      L6 to L8 -> L30 [1] lasti
      L8 to L9 -> L24 [3]
      L9 to L11 -> L30 [1] lasti
      L11 to L13 -> L39 [0] lasti
      L13 to L14 -> L26 [3]
      L14 to L16 -> L39 [0] lasti
      L16 to L17 -> L30 [1] lasti
      L17 to L19 -> L39 [0] lasti
      L19 to L20 -> L28 [3]
      L20 to L23 -> L39 [0] lasti
      L24 to L25 -> L30 [1] lasti
      L26 to L27 -> L39 [0] lasti
      L28 to L29 -> L39 [0] lasti
      L30 to L32 -> L38 [3] lasti
      L32 to L33 -> L34 [6]
      L33 to L37 -> L38 [3] lasti
      L37 to L39 -> L39 [0] lasti
    
# --- Nested code object: sync_voice_catalog ---
    # DOCSTRING: """Sync voices from ElevenLabs into the local voice_catalog table.

Returns the number of voices upserted.
"""
    # co_names: ('sqlalchemy', 'select', 'sqlalchemy.ext.asyncio', 'AsyncSession', 'app.models.voice_catalog', 'VoiceCatalog', 'fetch_voices', 'set', 'get', 'add', 'execute', 'where', 'provider_voice_id', 'scalar_one_or_none', 'display_name', 'gender_tag', 'locale', 'preview_url', 'is_active', 'scalars', 'all', 'flush', 'logger', 'info')
    # co_varnames: ('db_session', 'sa_select', 'AsyncSession', 'VoiceCatalog', 'db', 'remote_voices', 'seen_provider_ids', 'upserted', 'v', 'provider_voice_id', 'existing', 'display_name', 'labels', 'gender_tag', 'locale', 'preview_url', 'entry', 'all_local', 'local_voice')
     470            RETURN_GENERATOR
                    POP_TOP
            L1:     RESUME                   0
    
     475            LOAD_CONST               1 (0)
                    LOAD_CONST               2 (('select',))
                    IMPORT_NAME              0 (sqlalchemy)
                    IMPORT_FROM              1 (select)
                    STORE_FAST               1 (sa_select)
                    POP_TOP
    
     476            LOAD_CONST               1 (0)
                    LOAD_CONST               3 (('AsyncSession',))
                    IMPORT_NAME              2 (sqlalchemy.ext.asyncio)
                    IMPORT_FROM              3 (AsyncSession)
                    STORE_FAST               2 (AsyncSession)
                    POP_TOP
    
     478            LOAD_CONST               1 (0)
                    LOAD_CONST               4 (('VoiceCatalog',))
                    IMPORT_NAME              4 (app.models.voice_catalog)
                    IMPORT_FROM              5 (VoiceCatalog)
                    STORE_FAST               3 (VoiceCatalog)
                    POP_TOP
    
     480            LOAD_FAST                0 (db_session)
                    STORE_FAST               4 (db)
    
     482            LOAD_GLOBAL             13 (fetch_voices + NULL)
                    CALL                     0
                    GET_AWAITABLE            0
                    LOAD_CONST               5 (None)
            L2:     SEND                     3 (to L5)
            L3:     YIELD_VALUE              1
            L4:     RESUME                   3
                    JUMP_BACKWARD_NO_INTERRUPT 5 (to L2)
            L5:     END_SEND
                    STORE_FAST               5 (remote_voices)
    
     483            LOAD_FAST                5 (remote_voices)
                    TO_BOOL
                    POP_JUMP_IF_TRUE         1 (to L6)
    
     484            RETURN_CONST             1 (0)
    
     486    L6:     LOAD_GLOBAL             15 (set + NULL)
                    CALL                     0
                    STORE_FAST               6 (seen_provider_ids)
    
     487            LOAD_CONST               1 (0)
                    STORE_FAST               7 (upserted)
    
     489            LOAD_FAST                5 (remote_voices)
                    GET_ITER
            L7:     EXTENDED_ARG             1
                    FOR_ITER               336 (to L20)
                    STORE_FAST               8 (v)
    
     490            LOAD_FAST                8 (v)
                    LOAD_ATTR               17 (get + NULL|self)
                    LOAD_CONST               6 ('voice_id')
                    LOAD_CONST               7 ('')
                    CALL                     2
                    STORE_FAST               9 (provider_voice_id)
    
     491            LOAD_FAST                9 (provider_voice_id)
                    TO_BOOL
                    POP_JUMP_IF_TRUE         2 (to L8)
    
     492            JUMP_BACKWARD           31 (to L7)
    
     493    L8:     LOAD_FAST                6 (seen_provider_ids)
                    LOAD_ATTR               19 (add + NULL|self)
                    LOAD_FAST                9 (provider_voice_id)
                    CALL                     1
                    POP_TOP
    
     496            LOAD_FAST                4 (db)
                    LOAD_ATTR               21 (execute + NULL|self)
    
     497            LOAD_FAST                1 (sa_select)
                    PUSH_NULL
                    LOAD_FAST                3 (VoiceCatalog)
                    CALL                     1
                    LOAD_ATTR               23 (where + NULL|self)
    
     498            LOAD_FAST                3 (VoiceCatalog)
                    LOAD_ATTR               24 (provider_voice_id)
                    LOAD_FAST                9 (provider_voice_id)
                    COMPARE_OP              72 (==)
    
     497            CALL                     1
    
     496            CALL                     1
                    GET_AWAITABLE            0
                    LOAD_CONST               5 (None)
            L9:     SEND                     3 (to L12)
           L10:     YIELD_VALUE              1
           L11:     RESUME                   3
                    JUMP_BACKWARD_NO_INTERRUPT 5 (to L9)
           L12:     END_SEND
    
     501            LOAD_ATTR               27 (scalar_one_or_none + NULL|self)
                    CALL                     0
    
     495            STORE_FAST              10 (existing)
    
     503            LOAD_FAST                8 (v)
                    LOAD_ATTR               17 (get + NULL|self)
                    LOAD_CONST               8 ('name')
                    LOAD_CONST               9 ('Unknown Voice')
                    CALL                     2
                    LOAD_CONST               5 (None)
                    LOAD_CONST              10 (100)
                    BINARY_SLICE
                    STORE_FAST              11 (display_name)
    
     504            LOAD_FAST                8 (v)
                    LOAD_ATTR               17 (get + NULL|self)
                    LOAD_CONST              11 ('labels')
                    BUILD_MAP                0
                    CALL                     2
                    STORE_FAST              12 (labels)
    
     505            LOAD_FAST               12 (labels)
                    LOAD_ATTR               17 (get + NULL|self)
                    LOAD_CONST              12 ('gender')
                    CALL                     1
                    COPY                     1
                    TO_BOOL
                    POP_JUMP_IF_TRUE         2 (to L13)
                    POP_TOP
                    LOAD_CONST               7 ('')
           L13:     LOAD_CONST               5 (None)
                    LOAD_CONST              13 (20)
                    BINARY_SLICE
                    COPY                     1
                    TO_BOOL
                    POP_JUMP_IF_TRUE         2 (to L14)
                    POP_TOP
                    LOAD_CONST               5 (None)
           L14:     STORE_FAST              13 (gender_tag)
    
     506            LOAD_FAST               12 (labels)
                    LOAD_ATTR               17 (get + NULL|self)
                    LOAD_CONST              14 ('accent')
                    CALL                     1
                    COPY                     1
                    TO_BOOL
                    POP_JUMP_IF_TRUE         2 (to L15)
                    POP_TOP
                    LOAD_CONST              15 ('en')
           L15:     LOAD_CONST               5 (None)
                    LOAD_CONST              16 (50)
                    BINARY_SLICE
                    STORE_FAST              14 (locale)
    
     507            LOAD_FAST                8 (v)
                    LOAD_ATTR               17 (get + NULL|self)
                    LOAD_CONST              17 ('preview_url')
                    LOAD_CONST               7 ('')
                    CALL                     2
                    STORE_FAST              15 (preview_url)
    
     509            LOAD_FAST               10 (existing)
                    TO_BOOL
                    POP_JUMP_IF_FALSE       42 (to L17)
    
     510            LOAD_FAST_LOAD_FAST    186 (display_name, existing)
                    STORE_ATTR              14 (display_name)
    
     511            LOAD_FAST_LOAD_FAST    218 (gender_tag, existing)
                    STORE_ATTR              15 (gender_tag)
    
     512            LOAD_FAST               14 (locale)
                    COPY                     1
                    TO_BOOL
                    POP_JUMP_IF_TRUE         2 (to L16)
                    POP_TOP
                    LOAD_CONST              15 ('en')
           L16:     LOAD_FAST               10 (existing)
                    STORE_ATTR              16 (locale)
    
     513            LOAD_FAST_LOAD_FAST    250 (preview_url, existing)
                    STORE_ATTR              17 (preview_url)
    
     514            LOAD_CONST              18 (True)
                    LOAD_FAST               10 (existing)
                    STORE_ATTR              18 (is_active)
                    JUMP_FORWARD            37 (to L19)
    
     516   L17:     LOAD_FAST                3 (VoiceCatalog)
                    PUSH_NULL
    
     517            LOAD_FAST                9 (provider_voice_id)
    
     518            LOAD_FAST               11 (display_name)
    
     519            LOAD_FAST               13 (gender_tag)
    
     520            LOAD_FAST               14 (locale)
                    COPY                     1
                    TO_BOOL
                    POP_JUMP_IF_TRUE         2 (to L18)
                    POP_TOP
                    LOAD_CONST              15 ('en')
    
     521   L18:     LOAD_FAST               15 (preview_url)
    
     522            LOAD_CONST              18 (True)
    
     516            LOAD_CONST              19 (('provider_voice_id', 'display_name', 'gender_tag', 'locale', 'preview_url', 'is_active'))
                    CALL_KW                  6
                    STORE_FAST              16 (entry)
    
     524            LOAD_FAST                4 (db)
                    LOAD_ATTR               19 (add + NULL|self)
                    LOAD_FAST               16 (entry)
                    CALL                     1
                    POP_TOP
    
     525   L19:     LOAD_FAST                7 (upserted)
                    LOAD_CONST              20 (1)
                    BINARY_OP               13 (+=)
                    STORE_FAST               7 (upserted)
                    EXTENDED_ARG             1
                    JUMP_BACKWARD          339 (to L7)
    
     489   L20:     END_FOR
                    POP_TOP
    
     528            LOAD_FAST                4 (db)
                    LOAD_ATTR               21 (execute + NULL|self)
                    LOAD_FAST                1 (sa_select)
                    PUSH_NULL
                    LOAD_FAST                3 (VoiceCatalog)
                    CALL                     1
                    CALL                     1
                    GET_AWAITABLE            0
                    LOAD_CONST               5 (None)
           L21:     SEND                     3 (to L24)
           L22:     YIELD_VALUE              1
           L23:     RESUME                   3
                    JUMP_BACKWARD_NO_INTERRUPT 5 (to L21)
           L24:     END_SEND
                    LOAD_ATTR               39 (scalars + NULL|self)
                    CALL                     0
                    LOAD_ATTR               41 (all + NULL|self)
                    CALL                     0
                    STORE_FAST              17 (all_local)
    
     529            LOAD_FAST               17 (all_local)
                    GET_ITER
           L25:     FOR_ITER                28 (to L28)
                    STORE_FAST              18 (local_voice)
    
     530            LOAD_FAST               18 (local_voice)
                    LOAD_ATTR               24 (provider_voice_id)
                    LOAD_FAST                6 (seen_provider_ids)
                    CONTAINS_OP              1
           L26:     POP_JUMP_IF_TRUE         2 (to L27)
                    JUMP_BACKWARD           21 (to L25)
    
     531   L27:     LOAD_CONST              21 (False)
                    LOAD_FAST               18 (local_voice)
                    STORE_ATTR              18 (is_active)
                    JUMP_BACKWARD           30 (to L25)
    
     529   L28:     END_FOR
                    POP_TOP
    
     533            LOAD_FAST                4 (db)
                    LOAD_ATTR               43 (flush + NULL|self)
                    CALL                     0
                    GET_AWAITABLE            0
                    LOAD_CONST               5 (None)
           L29:     SEND                     3 (to L32)
           L30:     YIELD_VALUE              1
           L31:     RESUME                   3
                    JUMP_BACKWARD_NO_INTERRUPT 5 (to L29)
           L32:     END_SEND
                    POP_TOP
    
     534            LOAD_GLOBAL             44 (logger)
                    LOAD_ATTR               47 (info + NULL|self)
                    LOAD_CONST              22 ('Voice catalog synced: %d voices upserted')
                    LOAD_FAST                7 (upserted)
                    CALL                     2
                    POP_TOP
    
     535            LOAD_FAST                7 (upserted)
                    RETURN_VALUE
    
     482   L33:     CLEANUP_THROW
           L34:     EXTENDED_ARG             1
                    JUMP_BACKWARD_NO_INTERRUPT 509 (to L5)
    
     496   L35:     CLEANUP_THROW
           L36:     EXTENDED_ARG             1
                    JUMP_BACKWARD_NO_INTERRUPT 383 (to L12)
    
     528   L37:     CLEANUP_THROW
           L38:     JUMP_BACKWARD_NO_INTERRUPT 120 (to L24)
    
     533   L39:     CLEANUP_THROW
           L40:     JUMP_BACKWARD_NO_INTERRUPT 36 (to L32)
    
      --   L41:     CALL_INTRINSIC_1         3 (INTRINSIC_STOPITERATION_ERROR)
                    RERAISE                  1
    ExceptionTable:
      L1 to L3 -> L41 [0] lasti
      L3 to L4 -> L33 [2]
      L4 to L10 -> L41 [0] lasti
      L10 to L11 -> L35 [3]
      L11 to L22 -> L41 [0] lasti
      L22 to L23 -> L37 [2]
      L23 to L26 -> L41 [0] lasti
      L27 to L30 -> L41 [0] lasti
      L30 to L31 -> L39 [2]
      L31 to L34 -> L41 [0] lasti
      L35 to L36 -> L41 [0] lasti
      L37 to L38 -> L41 [0] lasti
      L39 to L40 -> L41 [0] lasti
    
# --- Nested code object: fetch_conversation_audio ---
    # DOCSTRING: """Fetch recording audio from ElevenLabs for a conversation."""
    # co_names: ('httpx', 'AsyncClient', 'get', '_API_BASE', '_headers', 'status_code', 'content', 'logger', 'warning')
    # co_varnames: ('conversation_id', 'client', 'resp')
     543            RETURN_GENERATOR
                    POP_TOP
            L1:     RESUME                   0
    
     545            LOAD_GLOBAL              0 (httpx)
                    LOAD_ATTR                2 (AsyncClient)
                    PUSH_NULL
                    LOAD_CONST               1 (60.0)
                    LOAD_CONST               2 (('timeout',))
                    CALL_KW                  1
                    BEFORE_ASYNC_WITH
                    GET_AWAITABLE            1
                    LOAD_CONST               3 (None)
            L2:     SEND                     3 (to L5)
            L3:     YIELD_VALUE              1
            L4:     RESUME                   3
                    JUMP_BACKWARD_NO_INTERRUPT 5 (to L2)
            L5:     END_SEND
            L6:     STORE_FAST               1 (client)
    
     546            LOAD_FAST                1 (client)
                    LOAD_ATTR                5 (get + NULL|self)
    
     547            LOAD_GLOBAL              6 (_API_BASE)
                    FORMAT_SIMPLE
                    LOAD_CONST               4 ('/convai/conversations/')
                    LOAD_FAST                0 (conversation_id)
                    FORMAT_SIMPLE
                    LOAD_CONST               5 ('/audio')
                    BUILD_STRING             4
    
     548            LOAD_GLOBAL              9 (_headers + NULL)
                    CALL                     0
    
     546            LOAD_CONST               6 (('headers',))
                    CALL_KW                  2
                    GET_AWAITABLE            0
                    LOAD_CONST               3 (None)
            L7:     SEND                     3 (to L10)
            L8:     YIELD_VALUE              1
            L9:     RESUME                   3
                    JUMP_BACKWARD_NO_INTERRUPT 5 (to L7)
           L10:     END_SEND
                    STORE_FAST               2 (resp)
    
     550            LOAD_FAST                2 (resp)
                    LOAD_ATTR               10 (status_code)
                    LOAD_CONST               7 (200)
                    COMPARE_OP              88 (bool(==))
                    POP_JUMP_IF_FALSE       29 (to L16)
    
     551            LOAD_FAST                2 (resp)
                    LOAD_ATTR               12 (content)
    
     545   L11:     SWAP                     2
                    LOAD_CONST               3 (None)
                    LOAD_CONST               3 (None)
                    LOAD_CONST               3 (None)
                    CALL                     2
                    GET_AWAITABLE            2
                    LOAD_CONST               3 (None)
           L12:     SEND                     3 (to L15)
           L13:     YIELD_VALUE              1
           L14:     RESUME                   3
                    JUMP_BACKWARD_NO_INTERRUPT 5 (to L12)
           L15:     END_SEND
                    POP_TOP
                    RETURN_VALUE
    
     552   L16:     LOAD_GLOBAL             14 (logger)
                    LOAD_ATTR               17 (warning + NULL|self)
    
     553            LOAD_CONST               8 ('ElevenLabs audio fetch returned %d for %s')
    
     554            LOAD_FAST                2 (resp)
                    LOAD_ATTR               10 (status_code)
    
     555            LOAD_FAST                0 (conversation_id)
                    LOAD_CONST               3 (None)
                    LOAD_CONST               9 (12)
                    BINARY_SLICE
    
     552            CALL                     3
                    POP_TOP
    
     557            NOP
    
     545   L17:     LOAD_CONST               3 (None)
                    LOAD_CONST               3 (None)
                    LOAD_CONST               3 (None)
                    CALL                     2
                    GET_AWAITABLE            2
                    LOAD_CONST               3 (None)
           L18:     SEND                     3 (to L21)
           L19:     YIELD_VALUE              1
           L20:     RESUME                   3
                    JUMP_BACKWARD_NO_INTERRUPT 5 (to L18)
           L21:     END_SEND
                    POP_TOP
                    RETURN_CONST             3 (None)
           L22:     CLEANUP_THROW
           L23:     JUMP_BACKWARD_NO_INTERRUPT 145 (to L5)
    
     546   L24:     CLEANUP_THROW
           L25:     JUMP_BACKWARD_NO_INTERRUPT 105 (to L10)
    
     545   L26:     CLEANUP_THROW
           L27:     JUMP_BACKWARD_NO_INTERRUPT 63 (to L15)
           L28:     CLEANUP_THROW
           L29:     JUMP_BACKWARD_NO_INTERRUPT 11 (to L21)
           L30:     PUSH_EXC_INFO
                    WITH_EXCEPT_START
                    GET_AWAITABLE            2
                    LOAD_CONST               3 (None)
           L31:     SEND                     4 (to L35)
           L32:     YIELD_VALUE              1
           L33:     RESUME                   3
                    JUMP_BACKWARD_NO_INTERRUPT 5 (to L31)
           L34:     CLEANUP_THROW
           L35:     END_SEND
                    TO_BOOL
                    POP_JUMP_IF_TRUE         1 (to L36)
                    RERAISE                  2
           L36:     POP_TOP
           L37:     POP_EXCEPT
                    POP_TOP
                    POP_TOP
                    RETURN_CONST             3 (None)
    
      --   L38:     COPY                     3
                    POP_EXCEPT
                    RERAISE                  1
           L39:     CALL_INTRINSIC_1         3 (INTRINSIC_STOPITERATION_ERROR)
                    RERAISE                  1
    ExceptionTable:
      L1 to L3 -> L39 [0] lasti
      L3 to L4 -> L22 [3]
      L4 to L6 -> L39 [0] lasti
      L6 to L8 -> L30 [1] lasti
      L8 to L9 -> L24 [3]
      L9 to L11 -> L30 [1] lasti
      L11 to L13 -> L39 [0] lasti
      L13 to L14 -> L26 [3]
      L14 to L16 -> L39 [0] lasti
      L16 to L17 -> L30 [1] lasti
      L17 to L19 -> L39 [0] lasti
      L19 to L20 -> L28 [2]
      L20 to L23 -> L39 [0] lasti
      L24 to L25 -> L30 [1] lasti
      L26 to L27 -> L39 [0] lasti
      L28 to L29 -> L39 [0] lasti
      L30 to L32 -> L38 [3] lasti
      L32 to L33 -> L34 [6]
      L33 to L37 -> L38 [3] lasti
      L37 to L39 -> L39 [0] lasti
    
# co_names: ('__doc__', '__future__', 'annotations', 'logging', 'httpx', 'app.config', 'settings', 'app_settings', 'getLogger', '__name__', 'logger', '_API_BASE', '_TIMEOUT', '_headers', 'TURN_EAGERNESS_MAP', '__annotations__', '_MATTBOT_TOOL_PREFIX', '_make_property', '_const_property', '_dynamic_var_property', '_booking_tool_body', '_availability_tool_body', '_create_tool', '_list_tools', '_delete_tool', '_update_tool', 'ensure_booking_tools', 'build_booking_tool_config', 'build_availability_tool_config', 'create_agent', 'update_agent', 'delete_agent', 'fetch_voices', 'sync_voice_catalog', 'fetch_conversation_audio')
# co_varnames: ()
  0           RESUME                   0

  1           SETUP_ANNOTATIONS
              LOAD_CONST               0 ('ElevenLabs agent management: create, update, delete per-user agents + voice catalog sync.')
              STORE_NAME               0 (__doc__)

  3           LOAD_CONST               1 (0)
              LOAD_CONST               2 (('annotations',))
              IMPORT_NAME              1 (__future__)
              IMPORT_FROM              2 (annotations)
              STORE_NAME               2 (annotations)
              POP_TOP

  5           LOAD_CONST               1 (0)
              LOAD_CONST               3 (None)
              IMPORT_NAME              3 (logging)
              STORE_NAME               3 (logging)

  7           LOAD_CONST               1 (0)
              LOAD_CONST               3 (None)
              IMPORT_NAME              4 (httpx)
              STORE_NAME               4 (httpx)

  9           LOAD_CONST               1 (0)
              LOAD_CONST               4 (('settings',))
              IMPORT_NAME              5 (app.config)
              IMPORT_FROM              6 (settings)
              STORE_NAME               7 (app_settings)
              POP_TOP

 11           LOAD_NAME                3 (logging)
              LOAD_ATTR               16 (getLogger)
              PUSH_NULL
              LOAD_NAME                9 (__name__)
              CALL                     1
              STORE_NAME              10 (logger)

 13           LOAD_CONST               5 ('https://api.elevenlabs.io/v1')
              STORE_NAME              11 (_API_BASE)

 14           LOAD_CONST               6 (30.0)
              STORE_NAME              12 (_TIMEOUT)

 17           LOAD_CONST              39 (('return', 'dict[str, str]'))
              LOAD_CONST               8 (<code object _headers at 0x0000024C0EF2B5A0, file "D:\fluence\Github\mattbot\backend\app\services\elevenlabs_agent_service.py", line 17>)
              MAKE_FUNCTION
              SET_FUNCTION_ATTRIBUTE   4 (annotations)
              STORE_NAME              13 (_headers)

 26           LOAD_CONST               9 ('normal')

 27           LOAD_CONST              10 ('eager')

 28           LOAD_CONST              10 ('eager')

 29           LOAD_CONST              11 ('patient')

 30           LOAD_CONST              11 ('patient')

 31           LOAD_CONST               9 ('normal')

 25           LOAD_CONST              12 (('professional_polite', 'casual_friendly', 'short_and_direct', 'warm_and_supportive', 'formal', 'custom'))
              BUILD_CONST_KEY_MAP      6
              STORE_NAME              14 (TURN_EAGERNESS_MAP)
              LOAD_CONST               7 ('dict[str, str]')
              LOAD_NAME               15 (__annotations__)
              LOAD_CONST              13 ('TURN_EAGERNESS_MAP')
              STORE_SUBSCR

 39           LOAD_CONST              14 ('mattbot_')
              STORE_NAME              16 (_MATTBOT_TOOL_PREFIX)

 42           LOAD_CONST              40 (('prop_type', 'str', 'description', 'str', 'return', 'dict'))
              LOAD_CONST              15 (<code object _make_property at 0x0000024C0EF0FE50, file "D:\fluence\Github\mattbot\backend\app\services\elevenlabs_agent_service.py", line 42>)
              MAKE_FUNCTION
              SET_FUNCTION_ATTRIBUTE   4 (annotations)
              STORE_NAME              17 (_make_property)

 47           LOAD_CONST              41 (('prop_type', 'str', 'value', 'str', 'return', 'dict'))
              LOAD_CONST              16 (<code object _const_property at 0x0000024C0EF0FC90, file "D:\fluence\Github\mattbot\backend\app\services\elevenlabs_agent_service.py", line 47>)
              MAKE_FUNCTION
              SET_FUNCTION_ATTRIBUTE   4 (annotations)
              STORE_NAME              18 (_const_property)

 52           LOAD_CONST              42 (('prop_type', 'str', 'var_name', 'str', 'return', 'dict'))
              LOAD_CONST              17 (<code object _dynamic_var_property at 0x0000024C0EF0F750, file "D:\fluence\Github\mattbot\backend\app\services\elevenlabs_agent_service.py", line 52>)
              MAKE_FUNCTION
              SET_FUNCTION_ATTRIBUTE   4 (annotations)
              STORE_NAME              19 (_dynamic_var_property)

 57           LOAD_CONST              43 (('',))
              LOAD_CONST              44 (('webhook_url', 'str', 'tool_secret', 'str', 'return', 'dict'))
              LOAD_CONST              18 (<code object _booking_tool_body at 0x0000024C0EC4BE10, file "D:\fluence\Github\mattbot\backend\app\services\elevenlabs_agent_service.py", line 57>)
              MAKE_FUNCTION
              SET_FUNCTION_ATTRIBUTE   4 (annotations)
              SET_FUNCTION_ATTRIBUTE   1 (defaults)
              STORE_NAME              20 (_booking_tool_body)

110           LOAD_CONST              43 (('',))
              LOAD_CONST              44 (('webhook_url', 'str', 'tool_secret', 'str', 'return', 'dict'))
              LOAD_CONST              19 (<code object _availability_tool_body at 0x0000024C0EC47330, file "D:\fluence\Github\mattbot\backend\app\services\elevenlabs_agent_service.py", line 110>)
              MAKE_FUNCTION
              SET_FUNCTION_ATTRIBUTE   4 (annotations)
              SET_FUNCTION_ATTRIBUTE   1 (defaults)
              STORE_NAME              21 (_availability_tool_body)

158           LOAD_CONST              45 (('body', 'dict', 'return', 'str'))
              LOAD_CONST              20 (<code object _create_tool at 0x0000024C0FEDAC70, file "D:\fluence\Github\mattbot\backend\app\services\elevenlabs_agent_service.py", line 158>)
              MAKE_FUNCTION
              SET_FUNCTION_ATTRIBUTE   4 (annotations)
              STORE_NAME              22 (_create_tool)

181           LOAD_CONST              46 (('return', 'list[dict]'))
              LOAD_CONST              21 (<code object _list_tools at 0x0000024C0FED87F0, file "D:\fluence\Github\mattbot\backend\app\services\elevenlabs_agent_service.py", line 181>)
              MAKE_FUNCTION
              SET_FUNCTION_ATTRIBUTE   4 (annotations)
              STORE_NAME              23 (_list_tools)

194           LOAD_CONST              47 (('tool_id', 'str', 'return', 'None'))
              LOAD_CONST              22 (<code object _delete_tool at 0x0000024C0FAD9CD0, file "D:\fluence\Github\mattbot\backend\app\services\elevenlabs_agent_service.py", line 194>)
              MAKE_FUNCTION
              SET_FUNCTION_ATTRIBUTE   4 (annotations)
              STORE_NAME              24 (_delete_tool)

208           LOAD_CONST              48 (('tool_id', 'str', 'body', 'dict', 'return', 'None'))
              LOAD_CONST              23 (<code object _update_tool at 0x0000024C0FB23550, file "D:\fluence\Github\mattbot\backend\app\services\elevenlabs_agent_service.py", line 208>)
              MAKE_FUNCTION
              SET_FUNCTION_ATTRIBUTE   4 (annotations)
              STORE_NAME              25 (_update_tool)

226           NOP

225           LOAD_CONST              43 (('',))

226           NOP

225           NOP

226           NOP

225           NOP

227           NOP

225           LOAD_CONST              49 (('webhook_url', 'str', 'tool_secret', 'str', 'return', 'list[str]'))
              LOAD_CONST              24 (<code object ensure_booking_tools at 0x0000024C0FB6C050, file "D:\fluence\Github\mattbot\backend\app\services\elevenlabs_agent_service.py", line 225>)
              MAKE_FUNCTION
              SET_FUNCTION_ATTRIBUTE   4 (annotations)
              SET_FUNCTION_ATTRIBUTE   1 (defaults)
              STORE_NAME              26 (ensure_booking_tools)

263           LOAD_CONST              50 (('webhook_base_url', 'str', 'tool_secret', 'str', 'return', 'dict'))
              LOAD_CONST              25 (<code object build_booking_tool_config at 0x0000024C0EF2B1E0, file "D:\fluence\Github\mattbot\backend\app\services\elevenlabs_agent_service.py", line 263>)
              MAKE_FUNCTION
              SET_FUNCTION_ATTRIBUTE   4 (annotations)
              STORE_NAME              27 (build_booking_tool_config)

268           NOP

269           NOP

268           NOP

269           NOP

268           NOP

270           NOP

268           LOAD_CONST              50 (('webhook_base_url', 'str', 'tool_secret', 'str', 'return', 'dict'))
              LOAD_CONST              26 (<code object build_availability_tool_config at 0x0000024C0EF2B3C0, file "D:\fluence\Github\mattbot\backend\app\services\elevenlabs_agent_service.py", line 268>)
              MAKE_FUNCTION
              SET_FUNCTION_ATTRIBUTE   4 (annotations)
              STORE_NAME              28 (build_availability_tool_config)

287           LOAD_CONST               3 (None)

288           LOAD_CONST              27 ('en')

289           LOAD_CONST              28 (180)

290           LOAD_CONST              29 ('professional_polite')

291           LOAD_CONST               6 (30.0)

292           LOAD_CONST               3 (None)

293           LOAD_CONST               3 (None)

282           LOAD_CONST              30 (('voice_id', 'language', 'max_duration_seconds', 'temperament_preset', 'silence_end_call_timeout', 'custom_tools', 'tool_ids'))
              BUILD_CONST_KEY_MAP      7

284           NOP

282           NOP

285           NOP

282           NOP

286           NOP

282           NOP

287           NOP

282           NOP

288           NOP

282           NOP

289           NOP

282           NOP

290           NOP

282           NOP

291           NOP

282           NOP

292           NOP

282           NOP

293           NOP

282           NOP

294           NOP

282           LOAD_CONST              51 (('name', 'str', 'system_prompt', 'str', 'first_message', 'str', 'voice_id', 'str | None', 'language', 'str', 'max_duration_seconds', 'int', 'temperament_preset', 'str', 'silence_end_call_timeout', 'float', 'custom_tools', 'list[dict] | None', 'tool_ids', 'list[str] | None', 'return', 'dict'))
              LOAD_CONST              31 (<code object create_agent at 0x0000024C0FB5FE50, file "D:\fluence\Github\mattbot\backend\app\services\elevenlabs_agent_service.py", line 282>)
              MAKE_FUNCTION
              SET_FUNCTION_ATTRIBUTE   4 (annotations)
              SET_FUNCTION_ATTRIBUTE   2 (kwdefaults)
              STORE_NAME              29 (create_agent)

357           LOAD_CONST               3 (None)

358           LOAD_CONST               3 (None)

359           LOAD_CONST               3 (None)

360           LOAD_CONST               3 (None)

361           LOAD_CONST               3 (None)

362           LOAD_CONST               3 (None)

363           LOAD_CONST               3 (None)

364           LOAD_CONST              32 (False)

365           LOAD_CONST               3 (None)

366           LOAD_CONST               3 (None)

354           LOAD_CONST              33 (('system_prompt', 'first_message', 'voice_id', 'language', 'max_duration_seconds', 'temperament_preset', 'silence_end_call_timeout', 'enable_end_call_tool', 'custom_tools', 'tool_ids'))
              BUILD_CONST_KEY_MAP     10

355           NOP

354           NOP

357           NOP

354           NOP

358           NOP

354           NOP

359           NOP

354           NOP

360           NOP

354           NOP

361           NOP

354           NOP

362           NOP

354           NOP

363           NOP

354           NOP

364           NOP

354           NOP

365           NOP

354           NOP

366           NOP

354           NOP

367           NOP

354           LOAD_CONST              52 (('el_agent_id', 'str', 'system_prompt', 'str | None', 'first_message', 'str | None', 'voice_id', 'str | None', 'language', 'str | None', 'max_duration_seconds', 'int | None', 'temperament_preset', 'str | None', 'silence_end_call_timeout', 'float | None', 'enable_end_call_tool', 'bool', 'custom_tools', 'list[dict] | None', 'tool_ids', 'list[str] | None', 'return', 'dict'))
              LOAD_CONST              34 (<code object update_agent at 0x0000024C0FB69590, file "D:\fluence\Github\mattbot\backend\app\services\elevenlabs_agent_service.py", line 354>)
              MAKE_FUNCTION
              SET_FUNCTION_ATTRIBUTE   4 (annotations)
              SET_FUNCTION_ATTRIBUTE   2 (kwdefaults)
              STORE_NAME              30 (update_agent)

435           LOAD_CONST              53 (('el_agent_id', 'str', 'return', 'bool'))
              LOAD_CONST              35 (<code object delete_agent at 0x0000024C0FED7590, file "D:\fluence\Github\mattbot\backend\app\services\elevenlabs_agent_service.py", line 435>)
              MAKE_FUNCTION
              SET_FUNCTION_ATTRIBUTE   4 (annotations)
              STORE_NAME              31 (delete_agent)

458           LOAD_CONST              46 (('return', 'list[dict]'))
              LOAD_CONST              36 (<code object fetch_voices at 0x0000024C0FED7830, file "D:\fluence\Github\mattbot\backend\app\services\elevenlabs_agent_service.py", line 458>)
              MAKE_FUNCTION
              SET_FUNCTION_ATTRIBUTE   4 (annotations)
              STORE_NAME              32 (fetch_voices)

470           LOAD_CONST              54 (('db_session', 'object', 'return', 'int'))
              LOAD_CONST              37 (<code object sync_voice_catalog at 0x0000024C0FDB6550, file "D:\fluence\Github\mattbot\backend\app\services\elevenlabs_agent_service.py", line 470>)
              MAKE_FUNCTION
              SET_FUNCTION_ATTRIBUTE   4 (annotations)
              STORE_NAME              33 (sync_voice_catalog)

543           LOAD_CONST              55 (('conversation_id', 'str', 'return', 'bytes | None'))
              LOAD_CONST              38 (<code object fetch_conversation_audio at 0x0000024C0FCD9160, file "D:\fluence\Github\mattbot\backend\app\services\elevenlabs_agent_service.py", line 543>)
              MAKE_FUNCTION
              SET_FUNCTION_ATTRIBUTE   4 (annotations)
              STORE_NAME              34 (fetch_conversation_audio)
              RETURN_CONST             3 (None)

Disassembly of <code object _headers at 0x0000024C0EF2B5A0, file "D:\fluence\Github\mattbot\backend\app\services\elevenlabs_agent_service.py", line 17>:
 17           RESUME                   0

 18           LOAD_CONST               1 ('xi-api-key')
              LOAD_GLOBAL              0 (app_settings)
              LOAD_ATTR                2 (ELEVENLABS_API_KEY)
              BUILD_MAP                1
              RETURN_VALUE

Disassembly of <code object _make_property at 0x0000024C0EF0FE50, file "D:\fluence\Github\mattbot\backend\app\services\elevenlabs_agent_service.py", line 42>:
 42           RESUME                   0

 44           LOAD_FAST_LOAD_FAST      1 (prop_type, description)
              LOAD_CONST               1 (('type', 'description'))
              BUILD_CONST_KEY_MAP      2
              RETURN_VALUE

Disassembly of <code object _const_property at 0x0000024C0EF0FC90, file "D:\fluence\Github\mattbot\backend\app\services\elevenlabs_agent_service.py", line 47>:
 47           RESUME                   0

 49           LOAD_FAST_LOAD_FAST      1 (prop_type, value)
              LOAD_CONST               1 (('type', 'constant_value'))
              BUILD_CONST_KEY_MAP      2
              RETURN_VALUE

Disassembly of <code object _dynamic_var_property at 0x0000024C0EF0F750, file "D:\fluence\Github\mattbot\backend\app\services\elevenlabs_agent_service.py", line 52>:
 52           RESUME                   0

 54           LOAD_FAST_LOAD_FAST      1 (prop_type, var_name)
              LOAD_CONST               1 (('type', 'dynamic_variable'))
              BUILD_CONST_KEY_MAP      2
              RETURN_VALUE

Disassembly of <code object _booking_tool_body at 0x0000024C0EC4BE10, file "D:\fluence\Github\mattbot\backend\app\services\elevenlabs_agent_service.py", line 57>:
 57           RESUME                   0

 59           LOAD_FAST                1 (tool_secret)
              TO_BOOL
              POP_JUMP_IF_FALSE        4 (to L1)
              LOAD_CONST               1 ('X-Tool-Secret')
              LOAD_FAST                1 (tool_secret)
              BUILD_MAP                1
              JUMP_FORWARD             1 (to L2)
      L1:     BUILD_MAP                0
      L2:     STORE_FAST               2 (headers)

 60           LOAD_CONST               2 ('tool_config')

 61           LOAD_GLOBAL              0 (_MATTBOT_TOOL_PREFIX)
              FORMAT_SIMPLE
              LOAD_CONST               3 ('book_appointment')
              BUILD_STRING             2

 63           LOAD_CONST               4 ("Book an appointment on the user's calendar for the caller.")

 65           LOAD_CONST               5 ('webhook')

 67           LOAD_FAST                0 (webhook_url)

 68           LOAD_CONST               6 ('POST')

 69           LOAD_FAST                2 (headers)

 70           BUILD_MAP                0

 71           LOAD_CONST               7 (None)

 73           LOAD_CONST               8 ('object')

 74           LOAD_CONST               9 ('')

 75           BUILD_LIST               0
              LOAD_CONST              10 (('tool_name', 'date', 'time', 'caller_name', 'reason'))
              LIST_EXTEND              1

 79           LOAD_GLOBAL              3 (_const_property + NULL)

 80           LOAD_CONST              11 ('string')
              LOAD_CONST               3 ('book_appointment')

 79           CALL                     2

 82           LOAD_GLOBAL              5 (_dynamic_var_property + NULL)
              LOAD_CONST              11 ('string')
              LOAD_CONST              12 ('el_agent_id')
              CALL                     2

 83           LOAD_GLOBAL              7 (_make_property + NULL)

 84           LOAD_CONST              11 ('string')
              LOAD_CONST              13 ('Date in YYYY-MM-DD format')

 83           CALL                     2

 86           LOAD_GLOBAL              7 (_make_property + NULL)

 87           LOAD_CONST              11 ('string')
              LOAD_CONST              14 ('Time in HH:MM 24-hour format')

 86           CALL                     2

 89           LOAD_GLOBAL              7 (_make_property + NULL)

 90           LOAD_CONST              15 ('integer')

 91           LOAD_CONST              16 ('Duration in minutes (default 30)')

 89           CALL                     2

 93           LOAD_GLOBAL              7 (_make_property + NULL)

 94           LOAD_CONST              11 ('string')
              LOAD_CONST              17 ('Name of the person booking')

 93           CALL                     2

 96           LOAD_GLOBAL              7 (_make_property + NULL)

 97           LOAD_CONST              11 ('string')
              LOAD_CONST              18 ('Purpose of the appointment')

 96           CALL                     2

 99           LOAD_GLOBAL              7 (_make_property + NULL)

100           LOAD_CONST              11 ('string')
              LOAD_CONST              19 ('Phone number of the caller')

 99           CALL                     2

 78           LOAD_CONST              20 (('tool_name', 'agent_id', 'date', 'time', 'duration_minutes', 'caller_name', 'reason', 'caller_phone'))
              BUILD_CONST_KEY_MAP      8

 72           LOAD_CONST              21 (('type', 'description', 'required', 'properties'))
              BUILD_CONST_KEY_MAP      4

104           LOAD_CONST              22 ('application/json')

105           LOAD_CONST               7 (None)

 66           LOAD_CONST              23 (('url', 'method', 'request_headers', 'path_params_schema', 'query_params_schema', 'request_body_schema', 'content_type', 'auth_connection'))
              BUILD_CONST_KEY_MAP      8

 60           LOAD_CONST              24 (('name', 'description', 'type', 'api_schema'))
              BUILD_CONST_KEY_MAP      4
              BUILD_MAP                1
              RETURN_VALUE

Disassembly of <code object _availability_tool_body at 0x0000024C0EC47330, file "D:\fluence\Github\mattbot\backend\app\services\elevenlabs_agent_service.py", line 110>:
110           RESUME                   0

112           LOAD_FAST                1 (tool_secret)
              TO_BOOL
              POP_JUMP_IF_FALSE        4 (to L1)
              LOAD_CONST               1 ('X-Tool-Secret')
              LOAD_FAST                1 (tool_secret)
              BUILD_MAP                1
              JUMP_FORWARD             1 (to L2)
      L1:     BUILD_MAP                0
      L2:     STORE_FAST               2 (headers)

113           LOAD_CONST               2 ('tool_config')

114           LOAD_GLOBAL              0 (_MATTBOT_TOOL_PREFIX)
              FORMAT_SIMPLE
              LOAD_CONST               3 ('get_available_slots')
              BUILD_STRING             2

116           LOAD_CONST               4 ("Check the calendar owner's availability for a given date and return ALL open appointment slots for that day. Call this BEFORE offering any times to the caller. You must convert the caller's natural language date (e.g. 'next Monday', 'tomorrow', 'March 10th') into YYYY-MM-DD format yourself before calling this tool. IMPORTANT: Only present up to 3 slots at a time to the caller to avoid overwhelming them. If they don't like those, offer the next batch from the remaining slots.")

126           LOAD_CONST               5 ('webhook')

128           LOAD_FAST                0 (webhook_url)

129           LOAD_CONST               6 ('POST')

130           LOAD_FAST                2 (headers)

131           BUILD_MAP                0

132           LOAD_CONST               7 (None)

134           LOAD_CONST               8 ('object')

135           LOAD_CONST               9 ('')

136           LOAD_CONST              10 ('tool_name')
              LOAD_CONST              11 ('date')
              BUILD_LIST               2

138           LOAD_GLOBAL              3 (_const_property + NULL)

139           LOAD_CONST              12 ('string')
              LOAD_CONST               3 ('get_available_slots')

138           CALL                     2

141           LOAD_GLOBAL              5 (_dynamic_var_property + NULL)
              LOAD_CONST              12 ('string')
              LOAD_CONST              13 ('el_agent_id')
              CALL                     2

142           LOAD_GLOBAL              7 (_make_property + NULL)

143           LOAD_CONST              12 ('string')

144           LOAD_CONST              14 ('Date to check in YYYY-MM-DD format')

142           CALL                     2

146           LOAD_GLOBAL              7 (_make_property + NULL)

147           LOAD_CONST              15 ('integer')

148           LOAD_CONST              16 ('Desired appointment duration in minutes (default 30)')

146           CALL                     2

137           LOAD_CONST              17 (('tool_name', 'agent_id', 'date', 'duration_minutes'))
              BUILD_CONST_KEY_MAP      4

133           LOAD_CONST              18 (('type', 'description', 'required', 'properties'))
              BUILD_CONST_KEY_MAP      4

152           LOAD_CONST              19 ('application/json')

153           LOAD_CONST               7 (None)

127           LOAD_CONST              20 (('url', 'method', 'request_headers', 'path_params_schema', 'query_params_schema', 'request_body_schema', 'content_type', 'auth_connection'))
              BUILD_CONST_KEY_MAP      8

113           LOAD_CONST              21 (('name', 'description', 'type', 'api_schema'))
              BUILD_CONST_KEY_MAP      4
              BUILD_MAP                1
              RETURN_VALUE

Disassembly of <code object _create_tool at 0x0000024C0FEDAC70, file "D:\fluence\Github\mattbot\backend\app\services\elevenlabs_agent_service.py", line 158>:
 158            RETURN_GENERATOR
                POP_TOP
        L1:     RESUME                   0

 160            LOAD_GLOBAL              0 (httpx)
                LOAD_ATTR                2 (AsyncClient)
                PUSH_NULL
                LOAD_GLOBAL              4 (_TIMEOUT)
                LOAD_CONST               1 (('timeout',))
                CALL_KW                  1
                BEFORE_ASYNC_WITH
                GET_AWAITABLE            1
                LOAD_CONST               2 (None)
        L2:     SEND                     3 (to L5)
        L3:     YIELD_VALUE              1
        L4:     RESUME                   3
                JUMP_BACKWARD_NO_INTERRUPT 5 (to L2)
        L5:     END_SEND
        L6:     STORE_FAST               1 (client)

 161            LOAD_FAST                1 (client)
                LOAD_ATTR                7 (post + NULL|self)

 162            LOAD_GLOBAL              8 (_API_BASE)
                FORMAT_SIMPLE
                LOAD_CONST               3 ('/convai/tools')
                BUILD_STRING             2

 163            LOAD_FAST                0 (body)

 164            LOAD_GLOBAL             11 (_headers + NULL)
                CALL                     0

 161            LOAD_CONST               4 (('json', 'headers'))
                CALL_KW                  3
                GET_AWAITABLE            0
                LOAD_CONST               2 (None)
        L7:     SEND                     3 (to L10)
        L8:     YIELD_VALUE              1
        L9:     RESUME                   3
                JUMP_BACKWARD_NO_INTERRUPT 5 (to L7)
       L10:     END_SEND
                STORE_FAST               2 (resp)

 166            LOAD_FAST                2 (resp)
                LOAD_ATTR               12 (status_code)
                LOAD_CONST               5 ((200, 201))
                CONTAINS_OP              1
                POP_JUMP_IF_FALSE       62 (to L11)

 167            LOAD_GLOBAL             14 (logger)
                LOAD_ATTR               17 (error + NULL|self)

 168            LOAD_CONST               6 ('ElevenLabs create tool failed: %d %s')

 169            LOAD_FAST                2 (resp)
                LOAD_ATTR               12 (status_code)
                LOAD_FAST                2 (resp)
                LOAD_ATTR               18 (text)
                LOAD_CONST               2 (None)
                LOAD_CONST               7 (500)
                BINARY_SLICE

 167            CALL                     3
                POP_TOP

 171            LOAD_FAST                2 (resp)
                LOAD_ATTR               21 (raise_for_status + NULL|self)
                CALL                     0
                POP_TOP

 172   L11:     LOAD_FAST                2 (resp)
                LOAD_ATTR               23 (json + NULL|self)
                CALL                     0
                STORE_FAST               3 (data)

 173            LOAD_FAST                3 (data)
                LOAD_ATTR               25 (get + NULL|self)
                LOAD_CONST               8 ('id')
                LOAD_CONST               9 ('')
                CALL                     2
                STORE_FAST               4 (tool_id)

 174            LOAD_GLOBAL             14 (logger)
                LOAD_ATTR               27 (info + NULL|self)

 175            LOAD_CONST              10 ('ElevenLabs tool created: id=%s name=%s')

 176            LOAD_FAST_LOAD_FAST     64 (tool_id, body)
                LOAD_ATTR               25 (get + NULL|self)
                LOAD_CONST              11 ('tool_config')
                BUILD_MAP                0
                CALL                     2
                LOAD_ATTR               25 (get + NULL|self)
                LOAD_CONST              12 ('name')
                CALL                     1

 174            CALL                     3
                POP_TOP

 178            LOAD_FAST                4 (tool_id)

 160   L12:     SWAP                     2
                LOAD_CONST               2 (None)
                LOAD_CONST               2 (None)
                LOAD_CONST               2 (None)
                CALL                     2
                GET_AWAITABLE            2
                LOAD_CONST               2 (None)
       L13:     SEND                     3 (to L16)
       L14:     YIELD_VALUE              1
       L15:     RESUME                   3
                JUMP_BACKWARD_NO_INTERRUPT 5 (to L13)
       L16:     END_SEND
                POP_TOP
                RETURN_VALUE
       L17:     CLEANUP_THROW
       L18:     JUMP_BACKWARD_NO_INTERRUPT 228 (to L5)

 161   L19:     CLEANUP_THROW
       L20:     JUMP_BACKWARD_NO_INTERRUPT 190 (to L10)

 160   L21:     CLEANUP_THROW
       L22:     JUMP_BACKWARD_NO_INTERRUPT 9 (to L16)
       L23:     PUSH_EXC_INFO
                WITH_EXCEPT_START
                GET_AWAITABLE            2
                LOAD_CONST               2 (None)
       L24:     SEND                     4 (to L28)
       L25:     YIELD_VALUE              1
       L26:     RESUME                   3
                JUMP_BACKWARD_NO_INTERRUPT 5 (to L24)
       L27:     CLEANUP_THROW
       L28:     END_SEND
                TO_BOOL
                POP_JUMP_IF_TRUE         1 (to L29)
                RERAISE                  2
       L29:     POP_TOP
       L30:     POP_EXCEPT
                POP_TOP
                POP_TOP
                RETURN_CONST             2 (None)

  --   L31:     COPY                     3
                POP_EXCEPT
                RERAISE                  1
       L32:     CALL_INTRINSIC_1         3 (INTRINSIC_STOPITERATION_ERROR)
                RERAISE                  1
ExceptionTable:
  L1 to L3 -> L32 [0] lasti
  L3 to L4 -> L17 [3]
  L4 to L6 -> L32 [0] lasti
  L6 to L8 -> L23 [1] lasti
  L8 to L9 -> L19 [3]
  L9 to L12 -> L23 [1] lasti
  L12 to L14 -> L32 [0] lasti
  L14 to L15 -> L21 [3]
  L15 to L18 -> L32 [0] lasti
  L19 to L20 -> L23 [1] lasti
  L21 to L22 -> L32 [0] lasti
  L23 to L25 -> L31 [3] lasti
  L25 to L26 -> L27 [6]
  L26 to L30 -> L31 [3] lasti
  L30 to L32 -> L32 [0] lasti

Disassembly of <code object _list_tools at 0x0000024C0FED87F0, file "D:\fluence\Github\mattbot\backend\app\services\elevenlabs_agent_service.py", line 181>:
 181            RETURN_GENERATOR
                POP_TOP
        L1:     RESUME                   0

 183            LOAD_GLOBAL              0 (httpx)
                LOAD_ATTR                2 (AsyncClient)
                PUSH_NULL
                LOAD_GLOBAL              4 (_TIMEOUT)
                LOAD_CONST               1 (('timeout',))
                CALL_KW                  1
                BEFORE_ASYNC_WITH
                GET_AWAITABLE            1
                LOAD_CONST               2 (None)
        L2:     SEND                     3 (to L5)
        L3:     YIELD_VALUE              1
        L4:     RESUME                   3
                JUMP_BACKWARD_NO_INTERRUPT 5 (to L2)
        L5:     END_SEND
        L6:     STORE_FAST               0 (client)

 184            LOAD_FAST                0 (client)
                LOAD_ATTR                7 (get + NULL|self)

 185            LOAD_GLOBAL              8 (_API_BASE)
                FORMAT_SIMPLE
                LOAD_CONST               3 ('/convai/tools')
                BUILD_STRING             2
                LOAD_GLOBAL             11 (_headers + NULL)
                CALL                     0

 184            LOAD_CONST               4 (('headers',))
                CALL_KW                  2
                GET_AWAITABLE            0
                LOAD_CONST               2 (None)
        L7:     SEND                     3 (to L10)
        L8:     YIELD_VALUE              1
        L9:     RESUME                   3
                JUMP_BACKWARD_NO_INTERRUPT 5 (to L7)
       L10:     END_SEND
                STORE_FAST               1 (resp)

 187            LOAD_FAST                1 (resp)
                LOAD_ATTR               12 (status_code)
                LOAD_CONST               5 (200)
                COMPARE_OP             119 (bool(!=))
                POP_JUMP_IF_FALSE       51 (to L16)

 188            LOAD_GLOBAL             14 (logger)
                LOAD_ATTR               17 (error + NULL|self)
                LOAD_CONST               6 ('ElevenLabs list tools failed: %d')
                LOAD_FAST                1 (resp)
                LOAD_ATTR               12 (status_code)
                CALL                     2
                POP_TOP

 189            BUILD_LIST               0

 183   L11:     SWAP                     2
                LOAD_CONST               2 (None)
                LOAD_CONST               2 (None)
                LOAD_CONST               2 (None)
                CALL                     2
                GET_AWAITABLE            2
                LOAD_CONST               2 (None)
       L12:     SEND                     3 (to L15)
       L13:     YIELD_VALUE              1
       L14:     RESUME                   3
                JUMP_BACKWARD_NO_INTERRUPT 5 (to L12)
       L15:     END_SEND
                POP_TOP
                RETURN_VALUE

 190   L16:     LOAD_FAST                1 (resp)
                LOAD_ATTR               19 (json + NULL|self)
                CALL                     0
                STORE_FAST               2 (data)

 191            LOAD_FAST                2 (data)
                LOAD_ATTR                7 (get + NULL|self)
                LOAD_CONST               7 ('tools')
                BUILD_LIST               0
                CALL                     2

 183   L17:     SWAP                     2
                LOAD_CONST               2 (None)
                LOAD_CONST               2 (None)
                LOAD_CONST               2 (None)
                CALL                     2
                GET_AWAITABLE            2
                LOAD_CONST               2 (None)
       L18:     SEND                     3 (to L21)
       L19:     YIELD_VALUE              1
       L20:     RESUME                   3
                JUMP_BACKWARD_NO_INTERRUPT 5 (to L18)
       L21:     END_SEND
                POP_TOP
                RETURN_VALUE
       L22:     CLEANUP_THROW
       L23:     JUMP_BACKWARD_NO_INTERRUPT 161 (to L5)

 184   L24:     CLEANUP_THROW
       L25:     JUMP_BACKWARD_NO_INTERRUPT 124 (to L10)

 183   L26:     CLEANUP_THROW
       L27:     JUMP_BACKWARD_NO_INTERRUPT 60 (to L15)
       L28:     CLEANUP_THROW
       L29:     JUMP_BACKWARD_NO_INTERRUPT 11 (to L21)
       L30:     PUSH_EXC_INFO
                WITH_EXCEPT_START
                GET_AWAITABLE            2
                LOAD_CONST               2 (None)
       L31:     SEND                     4 (to L35)
       L32:     YIELD_VALUE              1
       L33:     RESUME                   3
                JUMP_BACKWARD_NO_INTERRUPT 5 (to L31)
       L34:     CLEANUP_THROW
       L35:     END_SEND
                TO_BOOL
                POP_JUMP_IF_TRUE         1 (to L36)
                RERAISE                  2
       L36:     POP_TOP
       L37:     POP_EXCEPT
                POP_TOP
                POP_TOP
                RETURN_CONST             2 (None)

  --   L38:     COPY                     3
                POP_EXCEPT
                RERAISE                  1
       L39:     CALL_INTRINSIC_1         3 (INTRINSIC_STOPITERATION_ERROR)
                RERAISE                  1
ExceptionTable:
  L1 to L3 -> L39 [0] lasti
  L3 to L4 -> L22 [3]
  L4 to L6 -> L39 [0] lasti
  L6 to L8 -> L30 [1] lasti
  L8 to L9 -> L24 [3]
  L9 to L11 -> L30 [1] lasti
  L11 to L13 -> L39 [0] lasti
  L13 to L14 -> L26 [3]
  L14 to L16 -> L39 [0] lasti
  L16 to L17 -> L30 [1] lasti
  L17 to L19 -> L39 [0] lasti
  L19 to L20 -> L28 [3]
  L20 to L23 -> L39 [0] lasti
  L24 to L25 -> L30 [1] lasti
  L26 to L27 -> L39 [0] lasti
  L28 to L29 -> L39 [0] lasti
  L30 to L32 -> L38 [3] lasti
  L32 to L33 -> L34 [6]
  L33 to L37 -> L38 [3] lasti
  L37 to L39 -> L39 [0] lasti

Disassembly of <code object _delete_tool at 0x0000024C0FAD9CD0, file "D:\fluence\Github\mattbot\backend\app\services\elevenlabs_agent_service.py", line 194>:
 194            RETURN_GENERATOR
                POP_TOP
        L1:     RESUME                   0

 196            LOAD_GLOBAL              0 (httpx)
                LOAD_ATTR                2 (AsyncClient)
                PUSH_NULL
                LOAD_GLOBAL              4 (_TIMEOUT)
                LOAD_CONST               1 (('timeout',))
                CALL_KW                  1
                BEFORE_ASYNC_WITH
                GET_AWAITABLE            1
                LOAD_CONST               2 (None)
        L2:     SEND                     3 (to L5)
        L3:     YIELD_VALUE              1
        L4:     RESUME                   3
                JUMP_BACKWARD_NO_INTERRUPT 5 (to L2)
        L5:     END_SEND
        L6:     STORE_FAST               1 (client)

 197            LOAD_FAST                1 (client)
                LOAD_ATTR                7 (delete + NULL|self)

 198            LOAD_GLOBAL              8 (_API_BASE)
                FORMAT_SIMPLE
                LOAD_CONST               3 ('/convai/tools/')
                LOAD_FAST                0 (tool_id)
                FORMAT_SIMPLE
                BUILD_STRING             3
                LOAD_GLOBAL             11 (_headers + NULL)
                CALL                     0

 197            LOAD_CONST               4 (('headers',))
                CALL_KW                  2
                GET_AWAITABLE            0
                LOAD_CONST               2 (None)
        L7:     SEND                     3 (to L10)
        L8:     YIELD_VALUE              1
        L9:     RESUME                   3
                JUMP_BACKWARD_NO_INTERRUPT 5 (to L7)
       L10:     END_SEND
                STORE_FAST               2 (resp)

 200            LOAD_FAST                2 (resp)
                LOAD_ATTR               12 (status_code)
                LOAD_CONST               5 ((200, 204))
                CONTAINS_OP              0
                POP_JUMP_IF_FALSE       23 (to L11)

 201            LOAD_GLOBAL             14 (logger)
                LOAD_ATTR               17 (info + NULL|self)
                LOAD_CONST               6 ('ElevenLabs tool deleted: %s')
                LOAD_FAST                0 (tool_id)
                CALL                     2
                POP_TOP
                JUMP_FORWARD            32 (to L12)

 203   L11:     LOAD_GLOBAL             14 (logger)
                LOAD_ATTR               19 (warning + NULL|self)

 204            LOAD_CONST               7 ('ElevenLabs delete tool %s: %d')
                LOAD_FAST_LOAD_FAST      2 (tool_id, resp)
                LOAD_ATTR               12 (status_code)

 203            CALL                     3
                POP_TOP

 196   L12:     LOAD_CONST               2 (None)
                LOAD_CONST               2 (None)
                LOAD_CONST               2 (None)
                CALL                     2
                GET_AWAITABLE            2
                LOAD_CONST               2 (None)
       L13:     SEND                     3 (to L16)
       L14:     YIELD_VALUE              1
       L15:     RESUME                   3
                JUMP_BACKWARD_NO_INTERRUPT 5 (to L13)
       L16:     END_SEND
                POP_TOP
                RETURN_CONST             2 (None)
       L17:     CLEANUP_THROW
       L18:     JUMP_BACKWARD_NO_INTERRUPT 133 (to L5)

 197   L19:     CLEANUP_THROW
       L20:     JUMP_BACKWARD_NO_INTERRUPT 94 (to L10)

 196   L21:     CLEANUP_THROW
       L22:     JUMP_BACKWARD_NO_INTERRUPT 9 (to L16)
       L23:     PUSH_EXC_INFO
                WITH_EXCEPT_START
                GET_AWAITABLE            2
                LOAD_CONST               2 (None)
       L24:     SEND                     4 (to L28)
       L25:     YIELD_VALUE              1
       L26:     RESUME                   3
                JUMP_BACKWARD_NO_INTERRUPT 5 (to L24)
       L27:     CLEANUP_THROW
       L28:     END_SEND
                TO_BOOL
                POP_JUMP_IF_TRUE         1 (to L29)
                RERAISE                  2
       L29:     POP_TOP
       L30:     POP_EXCEPT
                POP_TOP
                POP_TOP
                RETURN_CONST             2 (None)

  --   L31:     COPY                     3
                POP_EXCEPT
                RERAISE                  1
       L32:     CALL_INTRINSIC_1         3 (INTRINSIC_STOPITERATION_ERROR)
                RERAISE                  1
ExceptionTable:
  L1 to L3 -> L32 [0] lasti
  L3 to L4 -> L17 [3]
  L4 to L6 -> L32 [0] lasti
  L6 to L8 -> L23 [1] lasti
  L8 to L9 -> L19 [3]
  L9 to L12 -> L23 [1] lasti
  L12 to L14 -> L32 [0] lasti
  L14 to L15 -> L21 [2]
  L15 to L18 -> L32 [0] lasti
  L19 to L20 -> L23 [1] lasti
  L21 to L22 -> L32 [0] lasti
  L23 to L25 -> L31 [3] lasti
  L25 to L26 -> L27 [6]
  L26 to L30 -> L31 [3] lasti
  L30 to L32 -> L32 [0] lasti

Disassembly of <code object _update_tool at 0x0000024C0FB23550, file "D:\fluence\Github\mattbot\backend\app\services\elevenlabs_agent_service.py", line 208>:
 208            RETURN_GENERATOR
                POP_TOP
        L1:     RESUME                   0

 210            LOAD_GLOBAL              0 (httpx)
                LOAD_ATTR                2 (AsyncClient)
                PUSH_NULL
                LOAD_GLOBAL              4 (_TIMEOUT)
                LOAD_CONST               1 (('timeout',))
                CALL_KW                  1
                BEFORE_ASYNC_WITH
                GET_AWAITABLE            1
                LOAD_CONST               2 (None)
        L2:     SEND                     3 (to L5)
        L3:     YIELD_VALUE              1
        L4:     RESUME                   3
                JUMP_BACKWARD_NO_INTERRUPT 5 (to L2)
        L5:     END_SEND
        L6:     STORE_FAST               2 (client)

 211            LOAD_FAST                2 (client)
                LOAD_ATTR                7 (patch + NULL|self)

 212            LOAD_GLOBAL              8 (_API_BASE)
                FORMAT_SIMPLE
                LOAD_CONST               3 ('/convai/tools/')
                LOAD_FAST                0 (tool_id)
                FORMAT_SIMPLE
                BUILD_STRING             3

 213            LOAD_FAST                1 (body)

 214            LOAD_GLOBAL             11 (_headers + NULL)
                CALL                     0

 211            LOAD_CONST               4 (('json', 'headers'))
                CALL_KW                  3
                GET_AWAITABLE            0
                LOAD_CONST               2 (None)
        L7:     SEND                     3 (to L10)
        L8:     YIELD_VALUE              1
        L9:     RESUME                   3
                JUMP_BACKWARD_NO_INTERRUPT 5 (to L7)
       L10:     END_SEND
                STORE_FAST               3 (resp)

 216            LOAD_FAST                3 (resp)
                LOAD_ATTR               12 (status_code)
                LOAD_CONST               5 ((200, 201))
                CONTAINS_OP              1
                POP_JUMP_IF_FALSE       47 (to L11)

 217            LOAD_GLOBAL             14 (logger)
                LOAD_ATTR               17 (error + NULL|self)

 218            LOAD_CONST               6 ('ElevenLabs update tool %s failed: %d %s')

 219            LOAD_FAST_LOAD_FAST      3 (tool_id, resp)
                LOAD_ATTR               12 (status_code)
                LOAD_FAST                3 (resp)
                LOAD_ATTR               18 (text)
                LOAD_CONST               2 (None)
                LOAD_CONST               7 (300)
                BINARY_SLICE

 217            CALL                     4
                POP_TOP
                JUMP_FORWARD            22 (to L12)

 222   L11:     LOAD_GLOBAL             14 (logger)
                LOAD_ATTR               21 (info + NULL|self)
                LOAD_CONST               8 ('ElevenLabs tool updated: %s')
                LOAD_FAST                0 (tool_id)
                CALL                     2
                POP_TOP

 210   L12:     LOAD_CONST               2 (None)
                LOAD_CONST               2 (None)
                LOAD_CONST               2 (None)
                CALL                     2
                GET_AWAITABLE            2
                LOAD_CONST               2 (None)
       L13:     SEND                     3 (to L16)
       L14:     YIELD_VALUE              1
       L15:     RESUME                   3
                JUMP_BACKWARD_NO_INTERRUPT 5 (to L13)
       L16:     END_SEND
                POP_TOP
                RETURN_CONST             2 (None)
       L17:     CLEANUP_THROW
       L18:     JUMP_BACKWARD_NO_INTERRUPT 148 (to L5)

 211   L19:     CLEANUP_THROW
       L20:     JUMP_BACKWARD_NO_INTERRUPT 108 (to L10)

 210   L21:     CLEANUP_THROW
       L22:     JUMP_BACKWARD_NO_INTERRUPT 9 (to L16)
       L23:     PUSH_EXC_INFO
                WITH_EXCEPT_START
                GET_AWAITABLE            2
                LOAD_CONST               2 (None)
       L24:     SEND                     4 (to L28)
       L25:     YIELD_VALUE              1
       L26:     RESUME                   3
                JUMP_BACKWARD_NO_INTERRUPT 5 (to L24)
       L27:     CLEANUP_THROW
       L28:     END_SEND
                TO_BOOL
                POP_JUMP_IF_TRUE         1 (to L29)
                RERAISE                  2
       L29:     POP_TOP
       L30:     POP_EXCEPT
                POP_TOP
                POP_TOP
                RETURN_CONST             2 (None)

  --   L31:     COPY                     3
                POP_EXCEPT
                RERAISE                  1
       L32:     CALL_INTRINSIC_1         3 (INTRINSIC_STOPITERATION_ERROR)
                RERAISE                  1
ExceptionTable:
  L1 to L3 -> L32 [0] lasti
  L3 to L4 -> L17 [3]
  L4 to L6 -> L32 [0] lasti
  L6 to L8 -> L23 [1] lasti
  L8 to L9 -> L19 [3]
  L9 to L12 -> L23 [1] lasti
  L12 to L14 -> L32 [0] lasti
  L14 to L15 -> L21 [2]
  L15 to L18 -> L32 [0] lasti
  L19 to L20 -> L23 [1] lasti
  L21 to L22 -> L32 [0] lasti
  L23 to L25 -> L31 [3] lasti
  L25 to L26 -> L27 [6]
  L26 to L30 -> L31 [3] lasti
  L30 to L32 -> L32 [0] lasti

Disassembly of <code object ensure_booking_tools at 0x0000024C0FB6C050, file "D:\fluence\Github\mattbot\backend\app\services\elevenlabs_agent_service.py", line 225>:
 225            RETURN_GENERATOR
                POP_TOP
        L1:     RESUME                   0

 232            LOAD_GLOBAL              1 (_list_tools + NULL)
                CALL                     0
                GET_AWAITABLE            0
                LOAD_CONST               1 (None)
        L2:     SEND                     3 (to L5)
        L3:     YIELD_VALUE              1
        L4:     RESUME                   3
                JUMP_BACKWARD_NO_INTERRUPT 5 (to L2)
        L5:     END_SEND
                STORE_FAST               2 (existing)

 234            BUILD_MAP                0
                STORE_FAST               3 (mattbot_tools)

 235            LOAD_FAST                2 (existing)
                GET_ITER
        L6:     FOR_ITER                74 (to L9)
                STORE_FAST               4 (t)

 236            LOAD_FAST                4 (t)
                LOAD_ATTR                3 (get + NULL|self)
                LOAD_CONST               2 ('tool_config')
                BUILD_MAP                0
                CALL                     2
                STORE_FAST               5 (tc)

 237            LOAD_FAST                5 (tc)
                LOAD_ATTR                3 (get + NULL|self)
                LOAD_CONST               3 ('name')
                LOAD_CONST               4 ('')
                CALL                     2
                STORE_FAST               6 (name)

 238            LOAD_FAST                6 (name)
                LOAD_ATTR                5 (startswith + NULL|self)
                LOAD_GLOBAL              6 (_MATTBOT_TOOL_PREFIX)
                CALL                     1
                TO_BOOL
        L7:     POP_JUMP_IF_TRUE         2 (to L8)
                JUMP_BACKWARD           67 (to L6)

 239    L8:     LOAD_FAST                4 (t)
                LOAD_CONST               5 ('id')
                BINARY_SUBSCR
                LOAD_FAST_LOAD_FAST     54 (mattbot_tools, name)
                STORE_SUBSCR
                JUMP_BACKWARD           76 (to L6)

 235    L9:     END_FOR
                POP_TOP

 241            LOAD_GLOBAL              6 (_MATTBOT_TOOL_PREFIX)
                FORMAT_SIMPLE
                LOAD_CONST               6 ('get_available_slots')
                BUILD_STRING             2
                STORE_FAST               7 (avail_name)

 242            LOAD_GLOBAL              6 (_MATTBOT_TOOL_PREFIX)
                FORMAT_SIMPLE
                LOAD_CONST               7 ('book_appointment')
                BUILD_STRING             2
                STORE_FAST               8 (book_name)

 244            LOAD_GLOBAL              9 (_availability_tool_body + NULL)
                LOAD_FAST_LOAD_FAST      1 (webhook_url, tool_secret)
                CALL                     2
                STORE_FAST               9 (avail_body)

 245            LOAD_GLOBAL             11 (_booking_tool_body + NULL)
                LOAD_FAST_LOAD_FAST      1 (webhook_url, tool_secret)
                CALL                     2
                STORE_FAST              10 (book_body)

 247            LOAD_FAST_LOAD_FAST    115 (avail_name, mattbot_tools)
                CONTAINS_OP              0
                POP_JUMP_IF_FALSE       27 (to L14)

 248            LOAD_GLOBAL             13 (_update_tool + NULL)
                LOAD_FAST_LOAD_FAST     55 (mattbot_tools, avail_name)
                BINARY_SUBSCR
                LOAD_FAST                9 (avail_body)
                CALL                     2
                GET_AWAITABLE            0
                LOAD_CONST               1 (None)
       L10:     SEND                     3 (to L13)
       L11:     YIELD_VALUE              1
       L12:     RESUME                   3
                JUMP_BACKWARD_NO_INTERRUPT 5 (to L10)
       L13:     END_SEND
                POP_TOP

 249            LOAD_FAST_LOAD_FAST     55 (mattbot_tools, avail_name)
                BINARY_SUBSCR
                STORE_FAST              11 (avail_id)
                JUMP_FORWARD            19 (to L19)

 251   L14:     LOAD_GLOBAL             15 (_create_tool + NULL)
                LOAD_FAST                9 (avail_body)
                CALL                     1
                GET_AWAITABLE            0
                LOAD_CONST               1 (None)
       L15:     SEND                     3 (to L18)
       L16:     YIELD_VALUE              1
       L17:     RESUME                   3
                JUMP_BACKWARD_NO_INTERRUPT 5 (to L15)
       L18:     END_SEND
                STORE_FAST              11 (avail_id)

 253   L19:     LOAD_FAST_LOAD_FAST    131 (book_name, mattbot_tools)
                CONTAINS_OP              0
                POP_JUMP_IF_FALSE       29 (to L24)

 254            LOAD_GLOBAL             13 (_update_tool + NULL)
                LOAD_FAST_LOAD_FAST     56 (mattbot_tools, book_name)
                BINARY_SUBSCR
                LOAD_FAST               10 (book_body)
                CALL                     2
                GET_AWAITABLE            0
                LOAD_CONST               1 (None)
       L20:     SEND                     3 (to L23)
       L21:     YIELD_VALUE              1
       L22:     RESUME                   3
                JUMP_BACKWARD_NO_INTERRUPT 5 (to L20)
       L23:     END_SEND
                POP_TOP

 255            LOAD_FAST_LOAD_FAST     56 (mattbot_tools, book_name)
                BINARY_SUBSCR
                STORE_FAST              12 (book_id)

 259            LOAD_FAST_LOAD_FAST    188 (avail_id, book_id)
                BUILD_LIST               2
                RETURN_VALUE

 257   L24:     LOAD_GLOBAL             15 (_create_tool + NULL)
                LOAD_FAST               10 (book_body)
                CALL                     1
                GET_AWAITABLE            0
                LOAD_CONST               1 (None)
       L25:     SEND                     3 (to L28)
       L26:     YIELD_VALUE              1
       L27:     RESUME                   3
                JUMP_BACKWARD_NO_INTERRUPT 5 (to L25)
       L28:     END_SEND
                STORE_FAST              12 (book_id)

 259            LOAD_FAST_LOAD_FAST    188 (avail_id, book_id)
                BUILD_LIST               2
                RETURN_VALUE

 232   L29:     CLEANUP_THROW
       L30:     JUMP_BACKWARD_NO_INTERRUPT 233 (to L5)

 248   L31:     CLEANUP_THROW
       L32:     JUMP_BACKWARD_NO_INTERRUPT 86 (to L13)

 251   L33:     CLEANUP_THROW
       L34:     JUMP_BACKWARD_NO_INTERRUPT 64 (to L18)

 254   L35:     CLEANUP_THROW
       L36:     JUMP_BACKWARD_NO_INTERRUPT 39 (to L23)

 257   L37:     CLEANUP_THROW
       L38:     JUMP_BACKWARD_NO_INTERRUPT 15 (to L28)

  --   L39:     CALL_INTRINSIC_1         3 (INTRINSIC_STOPITERATION_ERROR)
                RERAISE                  1
ExceptionTable:
  L1 to L3 -> L39 [0] lasti
  L3 to L4 -> L29 [2]
  L4 to L7 -> L39 [0] lasti
  L8 to L11 -> L39 [0] lasti
  L11 to L12 -> L31 [2]
  L12 to L16 -> L39 [0] lasti
  L16 to L17 -> L33 [2]
  L17 to L21 -> L39 [0] lasti
  L21 to L22 -> L35 [2]
  L22 to L26 -> L39 [0] lasti
  L26 to L27 -> L37 [2]
  L27 to L30 -> L39 [0] lasti
  L31 to L32 -> L39 [0] lasti
  L33 to L34 -> L39 [0] lasti
  L35 to L36 -> L39 [0] lasti
  L37 to L38 -> L39 [0] lasti

Disassembly of <code object build_booking_tool_config at 0x0000024C0EF2B1E0, file "D:\fluence\Github\mattbot\backend\app\services\elevenlabs_agent_service.py", line 263>:
263           RESUME                   0

265           LOAD_GLOBAL              1 (_booking_tool_body + NULL)
              LOAD_FAST                0 (webhook_base_url)
              FORMAT_SIMPLE
              LOAD_CONST               1 ('/webhooks/elevenlabs/tool')
              BUILD_STRING             2
              CALL                     1
              RETURN_VALUE

Disassembly of <code object build_availability_tool_config at 0x0000024C0EF2B3C0, file "D:\fluence\Github\mattbot\backend\app\services\elevenlabs_agent_service.py", line 268>:
268           RESUME                   0

272           LOAD_GLOBAL              1 (_availability_tool_body + NULL)

273           LOAD_FAST                0 (webhook_base_url)
              FORMAT_SIMPLE
              LOAD_CONST               1 ('/webhooks/elevenlabs/tool')
              BUILD_STRING             2

272           CALL                     1
              RETURN_VALUE

Disassembly of <code object create_agent at 0x0000024C0FB5FE50, file "D:\fluence\Github\mattbot\backend\app\services\elevenlabs_agent_service.py", line 282>:
 282            RETURN_GENERATOR
                POP_TOP
        L1:     RESUME                   0

 296            LOAD_GLOBAL              0 (TURN_EAGERNESS_MAP)
                LOAD_ATTR                3 (get + NULL|self)
                LOAD_FAST                6 (temperament_preset)
                LOAD_CONST               1 ('normal')
                CALL                     2
                STORE_FAST              10 (turn_eagerness)

 298            LOAD_CONST               2 ('prompt')
                LOAD_FAST                1 (system_prompt)
                BUILD_MAP                1
                STORE_FAST              11 (prompt_cfg)

 299            LOAD_FAST                9 (tool_ids)
                TO_BOOL
                POP_JUMP_IF_FALSE        4 (to L2)

 300            LOAD_FAST_LOAD_FAST    155 (tool_ids, prompt_cfg)
                LOAD_CONST               3 ('tool_ids')
                STORE_SUBSCR

 303    L2:     LOAD_FAST                0 (name)

 306            LOAD_FAST               11 (prompt_cfg)

 307            LOAD_FAST                2 (first_message)

 308            LOAD_FAST                4 (language)

 310            LOAD_CONST               4 ('end_call')

 311            LOAD_CONST               5 ('system')

 312            LOAD_CONST               4 ('end_call')

 313            LOAD_CONST               6 ('system_tool_type')
                LOAD_CONST               4 ('end_call')
                BUILD_MAP                1

 310            LOAD_CONST               7 (('type', 'name', 'params'))
                BUILD_CONST_KEY_MAP      3

 309            BUILD_MAP                1

 305            LOAD_CONST               8 (('prompt', 'first_message', 'language', 'built_in_tools'))
                BUILD_CONST_KEY_MAP      4

 317            BUILD_MAP                0

 319            LOAD_CONST               9 ('max_duration_seconds')
                LOAD_FAST                5 (max_duration_seconds)

 318            BUILD_MAP                1

 322            LOAD_FAST               10 (turn_eagerness)

 323            LOAD_FAST                7 (silence_end_call_timeout)

 321            LOAD_CONST              10 (('turn_eagerness', 'silence_end_call_timeout'))
                BUILD_CONST_KEY_MAP      2

 304            LOAD_CONST              11 (('agent', 'tts', 'conversation', 'turn'))
                BUILD_CONST_KEY_MAP      4

 302            LOAD_CONST              12 (('name', 'conversation_config'))
                BUILD_CONST_KEY_MAP      2
                STORE_FAST              12 (payload)

 328            LOAD_FAST                3 (voice_id)
                TO_BOOL
                POP_JUMP_IF_FALSE       10 (to L3)

 329            LOAD_FAST_LOAD_FAST     60 (voice_id, payload)
                LOAD_CONST              13 ('conversation_config')
                BINARY_SUBSCR
                LOAD_CONST              14 ('tts')
                BINARY_SUBSCR
                LOAD_CONST              15 ('voice_id')
                STORE_SUBSCR

 331    L3:     LOAD_GLOBAL              4 (httpx)
                LOAD_ATTR                6 (AsyncClient)
                PUSH_NULL
                LOAD_GLOBAL              8 (_TIMEOUT)
                LOAD_CONST              16 (('timeout',))
                CALL_KW                  1
                BEFORE_ASYNC_WITH
                GET_AWAITABLE            1
                LOAD_CONST              17 (None)
        L4:     SEND                     3 (to L7)
        L5:     YIELD_VALUE              1
        L6:     RESUME                   3
                JUMP_BACKWARD_NO_INTERRUPT 5 (to L4)
        L7:     END_SEND
        L8:     STORE_FAST              13 (client)

 332            LOAD_FAST               13 (client)
                LOAD_ATTR               11 (post + NULL|self)

 333            LOAD_GLOBAL             12 (_API_BASE)
                FORMAT_SIMPLE
                LOAD_CONST              18 ('/convai/agents/create')
                BUILD_STRING             2

 334            LOAD_FAST               12 (payload)

 335            LOAD_GLOBAL             15 (_headers + NULL)
                CALL                     0

 332            LOAD_CONST              19 (('json', 'headers'))
                CALL_KW                  3
                GET_AWAITABLE            0
                LOAD_CONST              17 (None)
        L9:     SEND                     3 (to L12)
       L10:     YIELD_VALUE              1
       L11:     RESUME                   3
                JUMP_BACKWARD_NO_INTERRUPT 5 (to L9)
       L12:     END_SEND
                STORE_FAST              14 (resp)

 337            LOAD_FAST               14 (resp)
                LOAD_ATTR               16 (status_code)
                LOAD_CONST              20 ((200, 201))
                CONTAINS_OP              1
                POP_JUMP_IF_FALSE       62 (to L13)

 338            LOAD_GLOBAL             18 (logger)
                LOAD_ATTR               21 (error + NULL|self)

 339            LOAD_CONST              21 ('ElevenLabs create_agent failed: %d %s')

 340            LOAD_FAST               14 (resp)
                LOAD_ATTR               16 (status_code)

 341            LOAD_FAST               14 (resp)
                LOAD_ATTR               22 (text)
                LOAD_CONST              17 (None)
                LOAD_CONST              22 (500)
                BINARY_SLICE

 338            CALL                     3
                POP_TOP

 343            LOAD_FAST               14 (resp)
                LOAD_ATTR               25 (raise_for_status + NULL|self)
                CALL                     0
                POP_TOP

 345   L13:     LOAD_FAST               14 (resp)
                LOAD_ATTR               27 (json + NULL|self)
                CALL                     0
                STORE_FAST              15 (data)

 346            LOAD_GLOBAL             18 (logger)
                LOAD_ATTR               29 (info + NULL|self)

 347            LOAD_CONST              23 ('ElevenLabs agent created: id=%s name=%s')

 348            LOAD_FAST               15 (data)
                LOAD_ATTR                3 (get + NULL|self)
                LOAD_CONST              24 ('agent_id')
                LOAD_CONST              25 ('?')
                CALL                     2

 349            LOAD_FAST                0 (name)

 346            CALL                     3
                POP_TOP

 351            LOAD_FAST               15 (data)

 331   L14:     SWAP                     2
                LOAD_CONST              17 (None)
                LOAD_CONST              17 (None)
                LOAD_CONST              17 (None)
                CALL                     2
                GET_AWAITABLE            2
                LOAD_CONST              17 (None)
       L15:     SEND                     3 (to L18)
       L16:     YIELD_VALUE              1
       L17:     RESUME                   3
                JUMP_BACKWARD_NO_INTERRUPT 5 (to L15)
       L18:     END_SEND
                POP_TOP
                RETURN_VALUE
       L19:     CLEANUP_THROW
       L20:     JUMP_BACKWARD_NO_INTERRUPT 196 (to L7)

 332   L21:     CLEANUP_THROW
       L22:     JUMP_BACKWARD_NO_INTERRUPT 158 (to L12)

 331   L23:     CLEANUP_THROW
       L24:     JUMP_BACKWARD_NO_INTERRUPT 9 (to L18)
       L25:     PUSH_EXC_INFO
                WITH_EXCEPT_START
                GET_AWAITABLE            2
                LOAD_CONST              17 (None)
       L26:     SEND                     4 (to L30)
       L27:     YIELD_VALUE              1
       L28:     RESUME                   3
                JUMP_BACKWARD_NO_INTERRUPT 5 (to L26)
       L29:     CLEANUP_THROW
       L30:     END_SEND
                TO_BOOL
                POP_JUMP_IF_TRUE         1 (to L31)
                RERAISE                  2
       L31:     POP_TOP
       L32:     POP_EXCEPT
                POP_TOP
                POP_TOP
                RETURN_CONST            17 (None)

  --   L33:     COPY                     3
                POP_EXCEPT
                RERAISE                  1
       L34:     CALL_INTRINSIC_1         3 (INTRINSIC_STOPITERATION_ERROR)
                RERAISE                  1
ExceptionTable:
  L1 to L5 -> L34 [0] lasti
  L5 to L6 -> L19 [3]
  L6 to L8 -> L34 [0] lasti
  L8 to L10 -> L25 [1] lasti
  L10 to L11 -> L21 [3]
  L11 to L14 -> L25 [1] lasti
  L14 to L16 -> L34 [0] lasti
  L16 to L17 -> L23 [3]
  L17 to L20 -> L34 [0] lasti
  L21 to L22 -> L25 [1] lasti
  L23 to L24 -> L34 [0] lasti
  L25 to L27 -> L33 [3] lasti
  L27 to L28 -> L29 [6]
  L28 to L32 -> L33 [3] lasti
  L32 to L34 -> L34 [0] lasti

Disassembly of <code object update_agent at 0x0000024C0FB69590, file "D:\fluence\Github\mattbot\backend\app\services\elevenlabs_agent_service.py", line 354>:
 354            RETURN_GENERATOR
                POP_TOP
        L1:     RESUME                   0

 369            LOAD_CONST               1 ('conversation_config')
                BUILD_MAP                0
                BUILD_MAP                1
                STORE_FAST              11 (payload)

 370            BUILD_MAP                0
                STORE_FAST              12 (agent_cfg)

 371            BUILD_MAP                0
                STORE_FAST              13 (tts_cfg)

 372            BUILD_MAP                0
                STORE_FAST              14 (conv_cfg)

 373            BUILD_MAP                0
                STORE_FAST              15 (turn_cfg)

 375            BUILD_MAP                0
                STORE_FAST              16 (prompt_cfg)

 376            LOAD_FAST                1 (system_prompt)
                POP_JUMP_IF_NONE         5 (to L2)

 377            LOAD_FAST                1 (system_prompt)
                LOAD_FAST               16 (prompt_cfg)
                LOAD_CONST               3 ('prompt')
                STORE_SUBSCR

 378    L2:     LOAD_FAST               10 (tool_ids)
                POP_JUMP_IF_NONE         5 (to L3)

 379            LOAD_FAST               10 (tool_ids)
                LOAD_FAST               16 (prompt_cfg)
                LOAD_CONST               4 ('tool_ids')
                STORE_SUBSCR

 380    L3:     LOAD_FAST               16 (prompt_cfg)
                TO_BOOL
                POP_JUMP_IF_FALSE        5 (to L4)

 381            LOAD_FAST               16 (prompt_cfg)
                LOAD_FAST               12 (agent_cfg)
                LOAD_CONST               3 ('prompt')
                STORE_SUBSCR

 383    L4:     LOAD_FAST                2 (first_message)
                POP_JUMP_IF_NONE         4 (to L5)

 384            LOAD_FAST_LOAD_FAST     44 (first_message, agent_cfg)
                LOAD_CONST               5 ('first_message')
                STORE_SUBSCR

 385    L5:     LOAD_FAST                4 (language)
                POP_JUMP_IF_NONE         4 (to L6)

 386            LOAD_FAST_LOAD_FAST     76 (language, agent_cfg)
                LOAD_CONST               6 ('language')
                STORE_SUBSCR

 387    L6:     LOAD_FAST                8 (enable_end_call_tool)
                TO_BOOL
                POP_JUMP_IF_FALSE       13 (to L7)

 389            LOAD_CONST               7 ('end_call')

 390            LOAD_CONST               8 ('system')

 391            LOAD_CONST               7 ('end_call')

 392            LOAD_CONST               9 ('system_tool_type')
                LOAD_CONST               7 ('end_call')
                BUILD_MAP                1

 389            LOAD_CONST              10 (('type', 'name', 'params'))
                BUILD_CONST_KEY_MAP      3

 388            BUILD_MAP                1
                LOAD_FAST               12 (agent_cfg)
                LOAD_CONST              11 ('built_in_tools')
                STORE_SUBSCR

 396    L7:     LOAD_FAST                3 (voice_id)
                POP_JUMP_IF_NONE         4 (to L8)

 397            LOAD_FAST_LOAD_FAST     61 (voice_id, tts_cfg)
                LOAD_CONST              12 ('voice_id')
                STORE_SUBSCR

 399    L8:     LOAD_FAST                5 (max_duration_seconds)
                POP_JUMP_IF_NONE         4 (to L9)

 400            LOAD_FAST_LOAD_FAST     94 (max_duration_seconds, conv_cfg)
                LOAD_CONST              13 ('max_duration_seconds')
                STORE_SUBSCR

 402    L9:     LOAD_FAST                6 (temperament_preset)
                POP_JUMP_IF_NONE        27 (to L10)

 403            LOAD_GLOBAL              0 (TURN_EAGERNESS_MAP)
                LOAD_ATTR                3 (get + NULL|self)
                LOAD_FAST                6 (temperament_preset)
                LOAD_CONST              14 ('normal')
                CALL                     2
                STORE_FAST              17 (turn_eagerness)

 404            LOAD_FAST               17 (turn_eagerness)
                LOAD_FAST               15 (turn_cfg)
                LOAD_CONST              15 ('turn_eagerness')
                STORE_SUBSCR

 405   L10:     LOAD_FAST                7 (silence_end_call_timeout)
                POP_JUMP_IF_NONE         4 (to L11)

 406            LOAD_FAST_LOAD_FAST    127 (silence_end_call_timeout, turn_cfg)
                LOAD_CONST              16 ('silence_end_call_timeout')
                STORE_SUBSCR

 408   L11:     LOAD_FAST               12 (agent_cfg)
                TO_BOOL
                POP_JUMP_IF_FALSE        7 (to L12)

 409            LOAD_FAST_LOAD_FAST    203 (agent_cfg, payload)
                LOAD_CONST               1 ('conversation_config')
                BINARY_SUBSCR
                LOAD_CONST              17 ('agent')
                STORE_SUBSCR

 410   L12:     LOAD_FAST               13 (tts_cfg)
                TO_BOOL
                POP_JUMP_IF_FALSE        7 (to L13)

 411            LOAD_FAST_LOAD_FAST    219 (tts_cfg, payload)
                LOAD_CONST               1 ('conversation_config')
                BINARY_SUBSCR
                LOAD_CONST              18 ('tts')
                STORE_SUBSCR

 412   L13:     LOAD_FAST               14 (conv_cfg)
                TO_BOOL
                POP_JUMP_IF_FALSE        7 (to L14)

 413            LOAD_FAST_LOAD_FAST    235 (conv_cfg, payload)
                LOAD_CONST               1 ('conversation_config')
                BINARY_SUBSCR
                LOAD_CONST              19 ('conversation')
                STORE_SUBSCR

 414   L14:     LOAD_FAST               15 (turn_cfg)
                TO_BOOL
                POP_JUMP_IF_FALSE        7 (to L15)

 415            LOAD_FAST_LOAD_FAST    251 (turn_cfg, payload)
                LOAD_CONST               1 ('conversation_config')
                BINARY_SUBSCR
                LOAD_CONST              20 ('turn')
                STORE_SUBSCR

 417   L15:     LOAD_GLOBAL              4 (httpx)
                LOAD_ATTR                6 (AsyncClient)
                PUSH_NULL
                LOAD_GLOBAL              8 (_TIMEOUT)
                LOAD_CONST              21 (('timeout',))
                CALL_KW                  1
                BEFORE_ASYNC_WITH
                GET_AWAITABLE            1
                LOAD_CONST               2 (None)
       L16:     SEND                     3 (to L19)
       L17:     YIELD_VALUE              1
       L18:     RESUME                   3
                JUMP_BACKWARD_NO_INTERRUPT 5 (to L16)
       L19:     END_SEND
       L20:     STORE_FAST              18 (client)

 418            LOAD_FAST               18 (client)
                LOAD_ATTR               11 (patch + NULL|self)

 419            LOAD_GLOBAL             12 (_API_BASE)
                FORMAT_SIMPLE
                LOAD_CONST              22 ('/convai/agents/')
                LOAD_FAST                0 (el_agent_id)
                FORMAT_SIMPLE
                BUILD_STRING             3

 420            LOAD_FAST               11 (payload)

 421            LOAD_GLOBAL             15 (_headers + NULL)
                CALL                     0

 418            LOAD_CONST              23 (('json', 'headers'))
                CALL_KW                  3
                GET_AWAITABLE            0
                LOAD_CONST               2 (None)
       L21:     SEND                     3 (to L24)
       L22:     YIELD_VALUE              1
       L23:     RESUME                   3
                JUMP_BACKWARD_NO_INTERRUPT 5 (to L21)
       L24:     END_SEND
                STORE_FAST              19 (resp)

 423            LOAD_FAST               19 (resp)
                LOAD_ATTR               16 (status_code)
                LOAD_CONST              24 ((200, 201))
                CONTAINS_OP              1
                POP_JUMP_IF_FALSE       62 (to L25)

 424            LOAD_GLOBAL             18 (logger)
                LOAD_ATTR               21 (error + NULL|self)

 425            LOAD_CONST              25 ('ElevenLabs update_agent failed: %d %s')

 426            LOAD_FAST               19 (resp)
                LOAD_ATTR               16 (status_code)

 427            LOAD_FAST               19 (resp)
                LOAD_ATTR               22 (text)
                LOAD_CONST               2 (None)
                LOAD_CONST              26 (500)
                BINARY_SLICE

 424            CALL                     3
                POP_TOP

 429            LOAD_FAST               19 (resp)
                LOAD_ATTR               25 (raise_for_status + NULL|self)
                CALL                     0
                POP_TOP

 430   L25:     LOAD_FAST               19 (resp)
                LOAD_ATTR               27 (json + NULL|self)
                CALL                     0
                STORE_FAST              20 (data)

 431            LOAD_GLOBAL             18 (logger)
                LOAD_ATTR               29 (info + NULL|self)
                LOAD_CONST              27 ('ElevenLabs agent updated: id=%s')
                LOAD_FAST                0 (el_agent_id)
                CALL                     2
                POP_TOP

 432            LOAD_FAST               20 (data)

 417   L26:     SWAP                     2
                LOAD_CONST               2 (None)
                LOAD_CONST               2 (None)
                LOAD_CONST               2 (None)
                CALL                     2
                GET_AWAITABLE            2
                LOAD_CONST               2 (None)
       L27:     SEND                     3 (to L30)
       L28:     YIELD_VALUE              1
       L29:     RESUME                   3
                JUMP_BACKWARD_NO_INTERRUPT 5 (to L27)
       L30:     END_SEND
                POP_TOP
                RETURN_VALUE
       L31:     CLEANUP_THROW
       L32:     JUMP_BACKWARD_NO_INTERRUPT 181 (to L19)

 418   L33:     CLEANUP_THROW
       L34:     JUMP_BACKWARD_NO_INTERRUPT 141 (to L24)

 417   L35:     CLEANUP_THROW
       L36:     JUMP_BACKWARD_NO_INTERRUPT 9 (to L30)
       L37:     PUSH_EXC_INFO
                WITH_EXCEPT_START
                GET_AWAITABLE            2
                LOAD_CONST               2 (None)
       L38:     SEND                     4 (to L42)
       L39:     YIELD_VALUE              1
       L40:     RESUME                   3
                JUMP_BACKWARD_NO_INTERRUPT 5 (to L38)
       L41:     CLEANUP_THROW
       L42:     END_SEND
                TO_BOOL
                POP_JUMP_IF_TRUE         1 (to L43)
                RERAISE                  2
       L43:     POP_TOP
       L44:     POP_EXCEPT
                POP_TOP
                POP_TOP
                RETURN_CONST             2 (None)

  --   L45:     COPY                     3
                POP_EXCEPT
                RERAISE                  1
       L46:     CALL_INTRINSIC_1         3 (INTRINSIC_STOPITERATION_ERROR)
                RERAISE                  1
ExceptionTable:
  L1 to L17 -> L46 [0] lasti
  L17 to L18 -> L31 [3]
  L18 to L20 -> L46 [0] lasti
  L20 to L22 -> L37 [1] lasti
  L22 to L23 -> L33 [3]
  L23 to L26 -> L37 [1] lasti
  L26 to L28 -> L46 [0] lasti
  L28 to L29 -> L35 [3]
  L29 to L32 -> L46 [0] lasti
  L33 to L34 -> L37 [1] lasti
  L35 to L36 -> L46 [0] lasti
  L37 to L39 -> L45 [3] lasti
  L39 to L40 -> L41 [6]
  L40 to L44 -> L45 [3] lasti
  L44 to L46 -> L46 [0] lasti

Disassembly of <code object delete_agent at 0x0000024C0FED7590, file "D:\fluence\Github\mattbot\backend\app\services\elevenlabs_agent_service.py", line 435>:
 435            RETURN_GENERATOR
                POP_TOP
        L1:     RESUME                   0

 437            LOAD_GLOBAL              0 (httpx)
                LOAD_ATTR                2 (AsyncClient)
                PUSH_NULL
                LOAD_GLOBAL              4 (_TIMEOUT)
                LOAD_CONST               1 (('timeout',))
                CALL_KW                  1
                BEFORE_ASYNC_WITH
                GET_AWAITABLE            1
                LOAD_CONST               2 (None)
        L2:     SEND                     3 (to L5)
        L3:     YIELD_VALUE              1
        L4:     RESUME                   3
                JUMP_BACKWARD_NO_INTERRUPT 5 (to L2)
        L5:     END_SEND
        L6:     STORE_FAST               1 (client)

 438            LOAD_FAST                1 (client)
                LOAD_ATTR                7 (delete + NULL|self)

 439            LOAD_GLOBAL              8 (_API_BASE)
                FORMAT_SIMPLE
                LOAD_CONST               3 ('/convai/agents/')
                LOAD_FAST                0 (el_agent_id)
                FORMAT_SIMPLE
                BUILD_STRING             3

 440            LOAD_GLOBAL             11 (_headers + NULL)
                CALL                     0

 438            LOAD_CONST               4 (('headers',))
                CALL_KW                  2
                GET_AWAITABLE            0
                LOAD_CONST               2 (None)
        L7:     SEND                     3 (to L10)
        L8:     YIELD_VALUE              1
        L9:     RESUME                   3
                JUMP_BACKWARD_NO_INTERRUPT 5 (to L7)
       L10:     END_SEND
                STORE_FAST               2 (resp)

 442            LOAD_FAST                2 (resp)
                LOAD_ATTR               12 (status_code)
                LOAD_CONST               5 ((200, 204))
                CONTAINS_OP              0
                POP_JUMP_IF_FALSE       40 (to L16)

 443            LOAD_GLOBAL             14 (logger)
                LOAD_ATTR               17 (info + NULL|self)
                LOAD_CONST               6 ('ElevenLabs agent deleted: id=%s')
                LOAD_FAST                0 (el_agent_id)
                CALL                     2
                POP_TOP

 444            NOP

 437   L11:     LOAD_CONST               2 (None)
                LOAD_CONST               2 (None)
                LOAD_CONST               2 (None)
                CALL                     2
                GET_AWAITABLE            2
                LOAD_CONST               2 (None)
       L12:     SEND                     3 (to L15)
       L13:     YIELD_VALUE              1
       L14:     RESUME                   3
                JUMP_BACKWARD_NO_INTERRUPT 5 (to L12)
       L15:     END_SEND
                POP_TOP
                RETURN_CONST             7 (True)

 445   L16:     LOAD_GLOBAL             14 (logger)
                LOAD_ATTR               19 (error + NULL|self)

 446            LOAD_CONST               8 ('ElevenLabs delete_agent failed: %d %s')

 447            LOAD_FAST                2 (resp)
                LOAD_ATTR               12 (status_code)

 448            LOAD_FAST                2 (resp)
                LOAD_ATTR               20 (text)
                LOAD_CONST               2 (None)
                LOAD_CONST               9 (500)
                BINARY_SLICE

 445            CALL                     3
                POP_TOP

 450            NOP

 437   L17:     LOAD_CONST               2 (None)
                LOAD_CONST               2 (None)
                LOAD_CONST               2 (None)
                CALL                     2
                GET_AWAITABLE            2
                LOAD_CONST               2 (None)
       L18:     SEND                     3 (to L21)
       L19:     YIELD_VALUE              1
       L20:     RESUME                   3
                JUMP_BACKWARD_NO_INTERRUPT 5 (to L18)
       L21:     END_SEND
                POP_TOP
                RETURN_CONST            10 (False)
       L22:     CLEANUP_THROW
       L23:     JUMP_BACKWARD_NO_INTERRUPT 165 (to L5)

 438   L24:     CLEANUP_THROW
       L25:     JUMP_BACKWARD_NO_INTERRUPT 126 (to L10)

 437   L26:     CLEANUP_THROW
       L27:     JUMP_BACKWARD_NO_INTERRUPT 73 (to L15)
       L28:     CLEANUP_THROW
       L29:     JUMP_BACKWARD_NO_INTERRUPT 11 (to L21)
       L30:     PUSH_EXC_INFO
                WITH_EXCEPT_START
                GET_AWAITABLE            2
                LOAD_CONST               2 (None)
       L31:     SEND                     4 (to L35)
       L32:     YIELD_VALUE              1
       L33:     RESUME                   3
                JUMP_BACKWARD_NO_INTERRUPT 5 (to L31)
       L34:     CLEANUP_THROW
       L35:     END_SEND
                TO_BOOL
                POP_JUMP_IF_TRUE         1 (to L36)
                RERAISE                  2
       L36:     POP_TOP
       L37:     POP_EXCEPT
                POP_TOP
                POP_TOP
                RETURN_CONST             2 (None)

  --   L38:     COPY                     3
                POP_EXCEPT
                RERAISE                  1
       L39:     CALL_INTRINSIC_1         3 (INTRINSIC_STOPITERATION_ERROR)
                RERAISE                  1
ExceptionTable:
  L1 to L3 -> L39 [0] lasti
  L3 to L4 -> L22 [3]
  L4 to L6 -> L39 [0] lasti
  L6 to L8 -> L30 [1] lasti
  L8 to L9 -> L24 [3]
  L9 to L11 -> L30 [1] lasti
  L11 to L13 -> L39 [0] lasti
  L13 to L14 -> L26 [2]
  L14 to L16 -> L39 [0] lasti
  L16 to L17 -> L30 [1] lasti
  L17 to L19 -> L39 [0] lasti
  L19 to L20 -> L28 [2]
  L20 to L23 -> L39 [0] lasti
  L24 to L25 -> L30 [1] lasti
  L26 to L27 -> L39 [0] lasti
  L28 to L29 -> L39 [0] lasti
  L30 to L32 -> L38 [3] lasti
  L32 to L33 -> L34 [6]
  L33 to L37 -> L38 [3] lasti
  L37 to L39 -> L39 [0] lasti

Disassembly of <code object fetch_voices at 0x0000024C0FED7830, file "D:\fluence\Github\mattbot\backend\app\services\elevenlabs_agent_service.py", line 458>:
 458            RETURN_GENERATOR
                POP_TOP
        L1:     RESUME                   0

 460            LOAD_GLOBAL              0 (httpx)
                LOAD_ATTR                2 (AsyncClient)
                PUSH_NULL
                LOAD_GLOBAL              4 (_TIMEOUT)
                LOAD_CONST               1 (('timeout',))
                CALL_KW                  1
                BEFORE_ASYNC_WITH
                GET_AWAITABLE            1
                LOAD_CONST               2 (None)
        L2:     SEND                     3 (to L5)
        L3:     YIELD_VALUE              1
        L4:     RESUME                   3
                JUMP_BACKWARD_NO_INTERRUPT 5 (to L2)
        L5:     END_SEND
        L6:     STORE_FAST               0 (client)

 461            LOAD_FAST                0 (client)
                LOAD_ATTR                7 (get + NULL|self)
                LOAD_GLOBAL              8 (_API_BASE)
                FORMAT_SIMPLE
                LOAD_CONST               3 ('/voices')
                BUILD_STRING             2
                LOAD_GLOBAL             11 (_headers + NULL)
                CALL                     0
                LOAD_CONST               4 (('headers',))
                CALL_KW                  2
                GET_AWAITABLE            0
                LOAD_CONST               2 (None)
        L7:     SEND                     3 (to L10)
        L8:     YIELD_VALUE              1
        L9:     RESUME                   3
                JUMP_BACKWARD_NO_INTERRUPT 5 (to L7)
       L10:     END_SEND
                STORE_FAST               1 (resp)

 462            LOAD_FAST                1 (resp)
                LOAD_ATTR               12 (status_code)
                LOAD_CONST               5 (200)
                COMPARE_OP             119 (bool(!=))
                POP_JUMP_IF_FALSE       51 (to L16)

 463            LOAD_GLOBAL             14 (logger)
                LOAD_ATTR               17 (error + NULL|self)
                LOAD_CONST               6 ('ElevenLabs fetch_voices failed: %d')
                LOAD_FAST                1 (resp)
                LOAD_ATTR               12 (status_code)
                CALL                     2
                POP_TOP

 464            BUILD_LIST               0

 460   L11:     SWAP                     2
                LOAD_CONST               2 (None)
                LOAD_CONST               2 (None)
                LOAD_CONST               2 (None)
                CALL                     2
                GET_AWAITABLE            2
                LOAD_CONST               2 (None)
       L12:     SEND                     3 (to L15)
       L13:     YIELD_VALUE              1
       L14:     RESUME                   3
                JUMP_BACKWARD_NO_INTERRUPT 5 (to L12)
       L15:     END_SEND
                POP_TOP
                RETURN_VALUE

 465   L16:     LOAD_FAST                1 (resp)
                LOAD_ATTR               19 (json + NULL|self)
                CALL                     0
                STORE_FAST               2 (data)

 466            LOAD_FAST                2 (data)
                LOAD_ATTR                7 (get + NULL|self)
                LOAD_CONST               7 ('voices')
                BUILD_LIST               0
                CALL                     2
                STORE_FAST               3 (voices)

 467            LOAD_FAST                3 (voices)

 460   L17:     SWAP                     2
                LOAD_CONST               2 (None)
                LOAD_CONST               2 (None)
                LOAD_CONST               2 (None)
                CALL                     2
                GET_AWAITABLE            2
                LOAD_CONST               2 (None)
       L18:     SEND                     3 (to L21)
       L19:     YIELD_VALUE              1
       L20:     RESUME                   3
                JUMP_BACKWARD_NO_INTERRUPT 5 (to L18)
       L21:     END_SEND
                POP_TOP
                RETURN_VALUE
       L22:     CLEANUP_THROW
       L23:     JUMP_BACKWARD_NO_INTERRUPT 163 (to L5)

 461   L24:     CLEANUP_THROW
       L25:     JUMP_BACKWARD_NO_INTERRUPT 126 (to L10)

 460   L26:     CLEANUP_THROW
       L27:     JUMP_BACKWARD_NO_INTERRUPT 62 (to L15)
       L28:     CLEANUP_THROW
       L29:     JUMP_BACKWARD_NO_INTERRUPT 11 (to L21)
       L30:     PUSH_EXC_INFO
                WITH_EXCEPT_START
                GET_AWAITABLE            2
                LOAD_CONST               2 (None)
       L31:     SEND                     4 (to L35)
       L32:     YIELD_VALUE              1
       L33:     RESUME                   3
                JUMP_BACKWARD_NO_INTERRUPT 5 (to L31)
       L34:     CLEANUP_THROW
       L35:     END_SEND
                TO_BOOL
                POP_JUMP_IF_TRUE         1 (to L36)
                RERAISE                  2
       L36:     POP_TOP
       L37:     POP_EXCEPT
                POP_TOP
                POP_TOP
                RETURN_CONST             2 (None)

  --   L38:     COPY                     3
                POP_EXCEPT
                RERAISE                  1
       L39:     CALL_INTRINSIC_1         3 (INTRINSIC_STOPITERATION_ERROR)
                RERAISE                  1
ExceptionTable:
  L1 to L3 -> L39 [0] lasti
  L3 to L4 -> L22 [3]
  L4 to L6 -> L39 [0] lasti
  L6 to L8 -> L30 [1] lasti
  L8 to L9 -> L24 [3]
  L9 to L11 -> L30 [1] lasti
  L11 to L13 -> L39 [0] lasti
  L13 to L14 -> L26 [3]
  L14 to L16 -> L39 [0] lasti
  L16 to L17 -> L30 [1] lasti
  L17 to L19 -> L39 [0] lasti
  L19 to L20 -> L28 [3]
  L20 to L23 -> L39 [0] lasti
  L24 to L25 -> L30 [1] lasti
  L26 to L27 -> L39 [0] lasti
  L28 to L29 -> L39 [0] lasti
  L30 to L32 -> L38 [3] lasti
  L32 to L33 -> L34 [6]
  L33 to L37 -> L38 [3] lasti
  L37 to L39 -> L39 [0] lasti

Disassembly of <code object sync_voice_catalog at 0x0000024C0FDB6550, file "D:\fluence\Github\mattbot\backend\app\services\elevenlabs_agent_service.py", line 470>:
 470            RETURN_GENERATOR
                POP_TOP
        L1:     RESUME                   0

 475            LOAD_CONST               1 (0)
                LOAD_CONST               2 (('select',))
                IMPORT_NAME              0 (sqlalchemy)
                IMPORT_FROM              1 (select)
                STORE_FAST               1 (sa_select)
                POP_TOP

 476            LOAD_CONST               1 (0)
                LOAD_CONST               3 (('AsyncSession',))
                IMPORT_NAME              2 (sqlalchemy.ext.asyncio)
                IMPORT_FROM              3 (AsyncSession)
                STORE_FAST               2 (AsyncSession)
                POP_TOP

 478            LOAD_CONST               1 (0)
                LOAD_CONST               4 (('VoiceCatalog',))
                IMPORT_NAME              4 (app.models.voice_catalog)
                IMPORT_FROM              5 (VoiceCatalog)
                STORE_FAST               3 (VoiceCatalog)
                POP_TOP

 480            LOAD_FAST                0 (db_session)
                STORE_FAST               4 (db)

 482            LOAD_GLOBAL             13 (fetch_voices + NULL)
                CALL                     0
                GET_AWAITABLE            0
                LOAD_CONST               5 (None)
        L2:     SEND                     3 (to L5)
        L3:     YIELD_VALUE              1
        L4:     RESUME                   3
                JUMP_BACKWARD_NO_INTERRUPT 5 (to L2)
        L5:     END_SEND
                STORE_FAST               5 (remote_voices)

 483            LOAD_FAST                5 (remote_voices)
                TO_BOOL
                POP_JUMP_IF_TRUE         1 (to L6)

 484            RETURN_CONST             1 (0)

 486    L6:     LOAD_GLOBAL             15 (set + NULL)
                CALL                     0
                STORE_FAST               6 (seen_provider_ids)

 487            LOAD_CONST               1 (0)
                STORE_FAST               7 (upserted)

 489            LOAD_FAST                5 (remote_voices)
                GET_ITER
        L7:     EXTENDED_ARG             1
                FOR_ITER               336 (to L20)
                STORE_FAST               8 (v)

 490            LOAD_FAST                8 (v)
                LOAD_ATTR               17 (get + NULL|self)
                LOAD_CONST               6 ('voice_id')
                LOAD_CONST               7 ('')
                CALL                     2
                STORE_FAST               9 (provider_voice_id)

 491            LOAD_FAST                9 (provider_voice_id)
                TO_BOOL
                POP_JUMP_IF_TRUE         2 (to L8)

 492            JUMP_BACKWARD           31 (to L7)

 493    L8:     LOAD_FAST                6 (seen_provider_ids)
                LOAD_ATTR               19 (add + NULL|self)
                LOAD_FAST                9 (provider_voice_id)
                CALL                     1
                POP_TOP

 496            LOAD_FAST                4 (db)
                LOAD_ATTR               21 (execute + NULL|self)

 497            LOAD_FAST                1 (sa_select)
                PUSH_NULL
                LOAD_FAST                3 (VoiceCatalog)
                CALL                     1
                LOAD_ATTR               23 (where + NULL|self)

 498            LOAD_FAST                3 (VoiceCatalog)
                LOAD_ATTR               24 (provider_voice_id)
                LOAD_FAST                9 (provider_voice_id)
                COMPARE_OP              72 (==)

 497            CALL                     1

 496            CALL                     1
                GET_AWAITABLE            0
                LOAD_CONST               5 (None)
        L9:     SEND                     3 (to L12)
       L10:     YIELD_VALUE              1
       L11:     RESUME                   3
                JUMP_BACKWARD_NO_INTERRUPT 5 (to L9)
       L12:     END_SEND

 501            LOAD_ATTR               27 (scalar_one_or_none + NULL|self)
                CALL                     0

 495            STORE_FAST              10 (existing)

 503            LOAD_FAST                8 (v)
                LOAD_ATTR               17 (get + NULL|self)
                LOAD_CONST               8 ('name')
                LOAD_CONST               9 ('Unknown Voice')
                CALL                     2
                LOAD_CONST               5 (None)
                LOAD_CONST              10 (100)
                BINARY_SLICE
                STORE_FAST              11 (display_name)

 504            LOAD_FAST                8 (v)
                LOAD_ATTR               17 (get + NULL|self)
                LOAD_CONST              11 ('labels')
                BUILD_MAP                0
                CALL                     2
                STORE_FAST              12 (labels)

 505            LOAD_FAST               12 (labels)
                LOAD_ATTR               17 (get + NULL|self)
                LOAD_CONST              12 ('gender')
                CALL                     1
                COPY                     1
                TO_BOOL
                POP_JUMP_IF_TRUE         2 (to L13)
                POP_TOP
                LOAD_CONST               7 ('')
       L13:     LOAD_CONST               5 (None)
                LOAD_CONST              13 (20)
                BINARY_SLICE
                COPY                     1
                TO_BOOL
                POP_JUMP_IF_TRUE         2 (to L14)
                POP_TOP
                LOAD_CONST               5 (None)
       L14:     STORE_FAST              13 (gender_tag)

 506            LOAD_FAST               12 (labels)
                LOAD_ATTR               17 (get + NULL|self)
                LOAD_CONST              14 ('accent')
                CALL                     1
                COPY                     1
                TO_BOOL
                POP_JUMP_IF_TRUE         2 (to L15)
                POP_TOP
                LOAD_CONST              15 ('en')
       L15:     LOAD_CONST               5 (None)
                LOAD_CONST              16 (50)
                BINARY_SLICE
                STORE_FAST              14 (locale)

 507            LOAD_FAST                8 (v)
                LOAD_ATTR               17 (get + NULL|self)
                LOAD_CONST              17 ('preview_url')
                LOAD_CONST               7 ('')
                CALL                     2
                STORE_FAST              15 (preview_url)

 509            LOAD_FAST               10 (existing)
                TO_BOOL
                POP_JUMP_IF_FALSE       42 (to L17)

 510            LOAD_FAST_LOAD_FAST    186 (display_name, existing)
                STORE_ATTR              14 (display_name)

 511            LOAD_FAST_LOAD_FAST    218 (gender_tag, existing)
                STORE_ATTR              15 (gender_tag)

 512            LOAD_FAST               14 (locale)
                COPY                     1
                TO_BOOL
                POP_JUMP_IF_TRUE         2 (to L16)
                POP_TOP
                LOAD_CONST              15 ('en')
       L16:     LOAD_FAST               10 (existing)
                STORE_ATTR              16 (locale)

 513            LOAD_FAST_LOAD_FAST    250 (preview_url, existing)
                STORE_ATTR              17 (preview_url)

 514            LOAD_CONST              18 (True)
                LOAD_FAST               10 (existing)
                STORE_ATTR              18 (is_active)
                JUMP_FORWARD            37 (to L19)

 516   L17:     LOAD_FAST                3 (VoiceCatalog)
                PUSH_NULL

 517            LOAD_FAST                9 (provider_voice_id)

 518            LOAD_FAST               11 (display_name)

 519            LOAD_FAST               13 (gender_tag)

 520            LOAD_FAST               14 (locale)
                COPY                     1
                TO_BOOL
                POP_JUMP_IF_TRUE         2 (to L18)
                POP_TOP
                LOAD_CONST              15 ('en')

 521   L18:     LOAD_FAST               15 (preview_url)

 522            LOAD_CONST              18 (True)

 516            LOAD_CONST              19 (('provider_voice_id', 'display_name', 'gender_tag', 'locale', 'preview_url', 'is_active'))
                CALL_KW                  6
                STORE_FAST              16 (entry)

 524            LOAD_FAST                4 (db)
                LOAD_ATTR               19 (add + NULL|self)
                LOAD_FAST               16 (entry)
                CALL                     1
                POP_TOP

 525   L19:     LOAD_FAST                7 (upserted)
                LOAD_CONST              20 (1)
                BINARY_OP               13 (+=)
                STORE_FAST               7 (upserted)
                EXTENDED_ARG             1
                JUMP_BACKWARD          339 (to L7)

 489   L20:     END_FOR
                POP_TOP

 528            LOAD_FAST                4 (db)
                LOAD_ATTR               21 (execute + NULL|self)
                LOAD_FAST                1 (sa_select)
                PUSH_NULL
                LOAD_FAST                3 (VoiceCatalog)
                CALL                     1
                CALL                     1
                GET_AWAITABLE            0
                LOAD_CONST               5 (None)
       L21:     SEND                     3 (to L24)
       L22:     YIELD_VALUE              1
       L23:     RESUME                   3
                JUMP_BACKWARD_NO_INTERRUPT 5 (to L21)
       L24:     END_SEND
                LOAD_ATTR               39 (scalars + NULL|self)
                CALL                     0
                LOAD_ATTR               41 (all + NULL|self)
                CALL                     0
                STORE_FAST              17 (all_local)

 529            LOAD_FAST               17 (all_local)
                GET_ITER
       L25:     FOR_ITER                28 (to L28)
                STORE_FAST              18 (local_voice)

 530            LOAD_FAST               18 (local_voice)
                LOAD_ATTR               24 (provider_voice_id)
                LOAD_FAST                6 (seen_provider_ids)
                CONTAINS_OP              1
       L26:     POP_JUMP_IF_TRUE         2 (to L27)
                JUMP_BACKWARD           21 (to L25)

 531   L27:     LOAD_CONST              21 (False)
                LOAD_FAST               18 (local_voice)
                STORE_ATTR              18 (is_active)
                JUMP_BACKWARD           30 (to L25)

 529   L28:     END_FOR
                POP_TOP

 533            LOAD_FAST                4 (db)
                LOAD_ATTR               43 (flush + NULL|self)
                CALL                     0
                GET_AWAITABLE            0
                LOAD_CONST               5 (None)
       L29:     SEND                     3 (to L32)
       L30:     YIELD_VALUE              1
       L31:     RESUME                   3
                JUMP_BACKWARD_NO_INTERRUPT 5 (to L29)
       L32:     END_SEND
                POP_TOP

 534            LOAD_GLOBAL             44 (logger)
                LOAD_ATTR               47 (info + NULL|self)
                LOAD_CONST              22 ('Voice catalog synced: %d voices upserted')
                LOAD_FAST                7 (upserted)
                CALL                     2
                POP_TOP

 535            LOAD_FAST                7 (upserted)
                RETURN_VALUE

 482   L33:     CLEANUP_THROW
       L34:     EXTENDED_ARG             1
                JUMP_BACKWARD_NO_INTERRUPT 509 (to L5)

 496   L35:     CLEANUP_THROW
       L36:     EXTENDED_ARG             1
                JUMP_BACKWARD_NO_INTERRUPT 383 (to L12)

 528   L37:     CLEANUP_THROW
       L38:     JUMP_BACKWARD_NO_INTERRUPT 120 (to L24)

 533   L39:     CLEANUP_THROW
       L40:     JUMP_BACKWARD_NO_INTERRUPT 36 (to L32)

  --   L41:     CALL_INTRINSIC_1         3 (INTRINSIC_STOPITERATION_ERROR)
                RERAISE                  1
ExceptionTable:
  L1 to L3 -> L41 [0] lasti
  L3 to L4 -> L33 [2]
  L4 to L10 -> L41 [0] lasti
  L10 to L11 -> L35 [3]
  L11 to L22 -> L41 [0] lasti
  L22 to L23 -> L37 [2]
  L23 to L26 -> L41 [0] lasti
  L27 to L30 -> L41 [0] lasti
  L30 to L31 -> L39 [2]
  L31 to L34 -> L41 [0] lasti
  L35 to L36 -> L41 [0] lasti
  L37 to L38 -> L41 [0] lasti
  L39 to L40 -> L41 [0] lasti

Disassembly of <code object fetch_conversation_audio at 0x0000024C0FCD9160, file "D:\fluence\Github\mattbot\backend\app\services\elevenlabs_agent_service.py", line 543>:
 543            RETURN_GENERATOR
                POP_TOP
        L1:     RESUME                   0

 545            LOAD_GLOBAL              0 (httpx)
                LOAD_ATTR                2 (AsyncClient)
                PUSH_NULL
                LOAD_CONST               1 (60.0)
                LOAD_CONST               2 (('timeout',))
                CALL_KW                  1
                BEFORE_ASYNC_WITH
                GET_AWAITABLE            1
                LOAD_CONST               3 (None)
        L2:     SEND                     3 (to L5)
        L3:     YIELD_VALUE              1
        L4:     RESUME                   3
                JUMP_BACKWARD_NO_INTERRUPT 5 (to L2)
        L5:     END_SEND
        L6:     STORE_FAST               1 (client)

 546            LOAD_FAST                1 (client)
                LOAD_ATTR                5 (get + NULL|self)

 547            LOAD_GLOBAL              6 (_API_BASE)
                FORMAT_SIMPLE
                LOAD_CONST               4 ('/convai/conversations/')
                LOAD_FAST                0 (conversation_id)
                FORMAT_SIMPLE
                LOAD_CONST               5 ('/audio')
                BUILD_STRING             4

 548            LOAD_GLOBAL              9 (_headers + NULL)
                CALL                     0

 546            LOAD_CONST               6 (('headers',))
                CALL_KW                  2
                GET_AWAITABLE            0
                LOAD_CONST               3 (None)
        L7:     SEND                     3 (to L10)
        L8:     YIELD_VALUE              1
        L9:     RESUME                   3
                JUMP_BACKWARD_NO_INTERRUPT 5 (to L7)
       L10:     END_SEND
                STORE_FAST               2 (resp)

 550            LOAD_FAST                2 (resp)
                LOAD_ATTR               10 (status_code)
                LOAD_CONST               7 (200)
                COMPARE_OP              88 (bool(==))
                POP_JUMP_IF_FALSE       29 (to L16)

 551            LOAD_FAST                2 (resp)
                LOAD_ATTR               12 (content)

 545   L11:     SWAP                     2
                LOAD_CONST               3 (None)
                LOAD_CONST               3 (None)
                LOAD_CONST               3 (None)
                CALL                     2
                GET_AWAITABLE            2
                LOAD_CONST               3 (None)
       L12:     SEND                     3 (to L15)
       L13:     YIELD_VALUE              1
       L14:     RESUME                   3
                JUMP_BACKWARD_NO_INTERRUPT 5 (to L12)
       L15:     END_SEND
                POP_TOP
                RETURN_VALUE

 552   L16:     LOAD_GLOBAL             14 (logger)
                LOAD_ATTR               17 (warning + NULL|self)

 553            LOAD_CONST               8 ('ElevenLabs audio fetch returned %d for %s')

 554            LOAD_FAST                2 (resp)
                LOAD_ATTR               10 (status_code)

 555            LOAD_FAST                0 (conversation_id)
                LOAD_CONST               3 (None)
                LOAD_CONST               9 (12)
                BINARY_SLICE

 552            CALL                     3
                POP_TOP

 557            NOP

 545   L17:     LOAD_CONST               3 (None)
                LOAD_CONST               3 (None)
                LOAD_CONST               3 (None)
                CALL                     2
                GET_AWAITABLE            2
                LOAD_CONST               3 (None)
       L18:     SEND                     3 (to L21)
       L19:     YIELD_VALUE              1
       L20:     RESUME                   3
                JUMP_BACKWARD_NO_INTERRUPT 5 (to L18)
       L21:     END_SEND
                POP_TOP
                RETURN_CONST             3 (None)
       L22:     CLEANUP_THROW
       L23:     JUMP_BACKWARD_NO_INTERRUPT 145 (to L5)

 546   L24:     CLEANUP_THROW
       L25:     JUMP_BACKWARD_NO_INTERRUPT 105 (to L10)

 545   L26:     CLEANUP_THROW
       L27:     JUMP_BACKWARD_NO_INTERRUPT 63 (to L15)
       L28:     CLEANUP_THROW
       L29:     JUMP_BACKWARD_NO_INTERRUPT 11 (to L21)
       L30:     PUSH_EXC_INFO
                WITH_EXCEPT_START
                GET_AWAITABLE            2
                LOAD_CONST               3 (None)
       L31:     SEND                     4 (to L35)
       L32:     YIELD_VALUE              1
       L33:     RESUME                   3
                JUMP_BACKWARD_NO_INTERRUPT 5 (to L31)
       L34:     CLEANUP_THROW
       L35:     END_SEND
                TO_BOOL
                POP_JUMP_IF_TRUE         1 (to L36)
                RERAISE                  2
       L36:     POP_TOP
       L37:     POP_EXCEPT
                POP_TOP
                POP_TOP
                RETURN_CONST             3 (None)

  --   L38:     COPY                     3
                POP_EXCEPT
                RERAISE                  1
       L39:     CALL_INTRINSIC_1         3 (INTRINSIC_STOPITERATION_ERROR)
                RERAISE                  1
ExceptionTable:
  L1 to L3 -> L39 [0] lasti
  L3 to L4 -> L22 [3]
  L4 to L6 -> L39 [0] lasti
  L6 to L8 -> L30 [1] lasti
  L8 to L9 -> L24 [3]
  L9 to L11 -> L30 [1] lasti
  L11 to L13 -> L39 [0] lasti
  L13 to L14 -> L26 [3]
  L14 to L16 -> L39 [0] lasti
  L16 to L17 -> L30 [1] lasti
  L17 to L19 -> L39 [0] lasti
  L19 to L20 -> L28 [2]
  L20 to L23 -> L39 [0] lasti
  L24 to L25 -> L30 [1] lasti
  L26 to L27 -> L39 [0] lasti
  L28 to L29 -> L39 [0] lasti
  L30 to L32 -> L38 [3] lasti
  L32 to L33 -> L34 [6]
  L33 to L37 -> L38 [3] lasti
  L37 to L39 -> L39 [0] lasti
