# Bytecode dump of: notification_service.cpython-313.pyc
# co_filename: D:\fluence\Github\mattbot\backend\app\services\notification_service.py
# co_names: ('__doc__', '__future__', 'annotations', 'logging', 'uuid', 'datetime', 'UTC', 'time', 'sqlalchemy', 'select', 'sqlalchemy.ext.asyncio', 'AsyncSession', 'app.core.encryption', 'decrypt_field', 'app.models.device', 'Device', 'app.models.notification', 'Notification', 'app.models.notification_delivery', 'NotificationDelivery', 'app.models.push_token', 'PushToken', 'app.models.user_settings', 'UserSettings', 'app.services.event_emitter', 'emit_event', 'getLogger', '__name__', 'logger', 'build_push_payload', '_build_preview_body', '_time_in_range', 'is_quiet_hours', 'should_allow_call', 'notify_call_screened', 'create_and_enqueue_notification', '_decrypt_personal_phone', 'send_urgent_sms', 'send_urgent_email', 'send_urgent_call', 'dispatch_urgent_notifications')
# co_consts (strings): ['Privacy-safe push notification payload builder and quiet hours check.', 'normal']

# DOCSTRING: """Privacy-safe push notification payload builder and quiet hours check."""
# --- Nested code object: build_push_payload ---
    # DOCSTRING: """Build a push notification payload respecting privacy settings.

Never includes: transcripts, full phone numbers, recording links, OTP codes.
"""
    # co_names: ('items', '_build_preview_body')
    # co_varnames: ('notification_type', 'data', 'privacy_mode', 'payload_data', 'base', 'safe_data_keys', 'k', 'v')
     23           RESUME                   0
    
     32           BUILD_MAP                0
                  STORE_FAST               3 (payload_data)
    
     34           LOAD_CONST               1 ('MattBot')
    
     35           LOAD_FAST                3 (payload_data)
    
     33           LOAD_CONST               2 (('title', 'data'))
                  BUILD_CONST_KEY_MAP      2
                  STORE_FAST               4 (base)
    
     38           BUILD_SET                0
                  LOAD_CONST               3 (frozenset({'event_type', 'call_id', 'timestamp'}))
                  SET_UPDATE               1
                  STORE_FAST               5 (safe_data_keys)
    
     39           LOAD_FAST                1 (data)
                  LOAD_ATTR                1 (items + NULL|self)
                  CALL                     0
                  GET_ITER
          L1:     FOR_ITER                16 (to L3)
                  UNPACK_SEQUENCE          2
                  STORE_FAST_STORE_FAST  103 (k, v)
    
     40           LOAD_FAST_LOAD_FAST    101 (k, safe_data_keys)
                  CONTAINS_OP              0
                  POP_JUMP_IF_TRUE         2 (to L2)
                  JUMP_BACKWARD           12 (to L1)
    
     41   L2:     LOAD_FAST_LOAD_FAST    115 (v, payload_data)
                  LOAD_FAST                6 (k)
                  STORE_SUBSCR
                  JUMP_BACKWARD           18 (to L1)
    
     39   L3:     END_FOR
                  POP_TOP
    
     43           LOAD_CONST               4 ('call_id')
                  LOAD_FAST                1 (data)
                  CONTAINS_OP              0
                  POP_JUMP_IF_FALSE       11 (to L4)
    
     44           LOAD_CONST               5 ('mattbot://call/')
                  LOAD_FAST                1 (data)
                  LOAD_CONST               4 ('call_id')
                  BINARY_SUBSCR
                  FORMAT_SIMPLE
                  BUILD_STRING             2
                  LOAD_FAST                3 (payload_data)
                  LOAD_CONST               6 ('deep_link')
                  STORE_SUBSCR
    
     46   L4:     LOAD_FAST                2 (privacy_mode)
                  LOAD_CONST               7 ('preview')
                  COMPARE_OP              88 (bool(==))
                  POP_JUMP_IF_FALSE       16 (to L5)
    
     47           LOAD_GLOBAL              3 (_build_preview_body + NULL)
                  LOAD_FAST_LOAD_FAST      1 (notification_type, data)
                  CALL                     2
                  LOAD_FAST                4 (base)
                  LOAD_CONST               8 ('body')
                  STORE_SUBSCR
    
     51           LOAD_FAST                4 (base)
                  RETURN_VALUE
    
     49   L5:     LOAD_CONST               9 ('New activity')
                  LOAD_FAST                4 (base)
                  LOAD_CONST               8 ('body')
                  STORE_SUBSCR
    
     51           LOAD_FAST                4 (base)
                  RETURN_VALUE
    
# --- Nested code object: _build_preview_body ---
    # co_names: ('get',)
    # co_varnames: ('notification_type', 'data', 'previews')
     54           RESUME                   0
    
     56           LOAD_CONST               1 ('Incoming call')
    
     57           LOAD_CONST               2 ('Missed call')
    
     58           LOAD_CONST               3 ('New voicemail received')
    
     59           LOAD_CONST               4 ('Call summary ready')
    
     60           LOAD_CONST               5 ('Call was screened')
    
     55           LOAD_CONST               6 (('incoming_call', 'missed_call', 'voicemail', 'call_summary', 'call_screened'))
                  BUILD_CONST_KEY_MAP      5
                  STORE_FAST               2 (previews)
    
     62           LOAD_FAST                2 (previews)
                  LOAD_ATTR                1 (get + NULL|self)
                  LOAD_FAST                0 (notification_type)
                  LOAD_CONST               7 ('New activity')
                  CALL                     2
                  RETURN_VALUE
    
# --- Nested code object: _time_in_range ---
    # DOCSTRING: """Check if current_time falls within start-end, handling overnight spans."""
    # co_names: ('bool',)
    # co_varnames: ('start', 'end', 'current_time')
     65           RESUME                   0
    
     69           LOAD_FAST_LOAD_FAST      1 (start, end)
                  COMPARE_OP              58 (bool(<=))
                  POP_JUMP_IF_FALSE       33 (to L2)
    
     70           LOAD_GLOBAL              1 (bool + NULL)
                  LOAD_FAST_LOAD_FAST      2 (start, current_time)
                  SWAP                     2
                  COPY                     2
                  COMPARE_OP              42 (<=)
                  COPY                     1
                  TO_BOOL
                  POP_JUMP_IF_FALSE        9 (to L1)
                  POP_TOP
                  LOAD_FAST                1 (end)
                  COMPARE_OP              42 (<=)
                  CALL                     1
                  RETURN_VALUE
          L1:     SWAP                     2
                  POP_TOP
                  CALL                     1
                  RETURN_VALUE
    
     71   L2:     LOAD_GLOBAL              1 (bool + NULL)
                  LOAD_FAST_LOAD_FAST     32 (current_time, start)
                  COMPARE_OP             172 (>=)
                  COPY                     1
                  TO_BOOL
                  POP_JUMP_IF_TRUE         4 (to L3)
                  POP_TOP
                  LOAD_FAST_LOAD_FAST     33 (current_time, end)
                  COMPARE_OP              42 (<=)
          L3:     CALL                     1
                  RETURN_VALUE
    
# --- Nested code object: is_quiet_hours ---
    # DOCSTRING: """Check if current time falls within any of the user's quiet hours intervals."""
    # co_names: ('quiet_hours_enabled', 'datetime', 'now', 'UTC', 'weekday', 'time', 'quiet_hours_intervals', 'get', 'split', 'int', '_time_in_range', 'KeyError', 'ValueError', 'IndexError', 'quiet_hours_start', 'quiet_hours_end', 'quiet_hours_days')
    # co_varnames: ('settings', 'now', 'current_day', 'iso_to_js_day', 'current_time', 'intervals', 'iv', 'iv_days', 'parts_s', 'parts_e', 'dt_time', 'start', 'end', 'days')
      74            RESUME                   0
    
      76            LOAD_FAST                0 (settings)
                    LOAD_ATTR                0 (quiet_hours_enabled)
                    TO_BOOL
                    POP_JUMP_IF_TRUE         1 (to L1)
    
      77            RETURN_CONST             1 (False)
    
      79    L1:     LOAD_FAST                1 (now)
                    POP_JUMP_IF_NOT_NONE    26 (to L2)
    
      80            LOAD_GLOBAL              2 (datetime)
                    LOAD_ATTR                4 (now)
                    PUSH_NULL
                    LOAD_GLOBAL              6 (UTC)
                    CALL                     1
                    STORE_FAST               1 (now)
    
      82    L2:     LOAD_FAST                1 (now)
                    LOAD_ATTR                9 (weekday + NULL|self)
                    CALL                     0
                    STORE_FAST               2 (current_day)
    
      83            LOAD_FAST                2 (current_day)
                    LOAD_CONST               2 (1)
                    BINARY_OP                0 (+)
                    LOAD_CONST               3 (7)
                    BINARY_OP                6 (%)
                    STORE_FAST               3 (iso_to_js_day)
    
      84            LOAD_FAST                1 (now)
                    LOAD_ATTR               11 (time + NULL|self)
                    CALL                     0
                    STORE_FAST               4 (current_time)
    
      86            LOAD_FAST                0 (settings)
                    LOAD_ATTR               12 (quiet_hours_intervals)
                    COPY                     1
                    TO_BOOL
                    POP_JUMP_IF_TRUE         2 (to L3)
                    POP_TOP
                    BUILD_LIST               0
            L3:     STORE_FAST               5 (intervals)
    
      87            LOAD_FAST                5 (intervals)
                    TO_BOOL
                    POP_JUMP_IF_FALSE      176 (to L10)
    
      88            LOAD_FAST                5 (intervals)
                    GET_ITER
            L4:     FOR_ITER               169 (to L9)
                    STORE_FAST               6 (iv)
    
      89            LOAD_FAST                6 (iv)
                    LOAD_ATTR               15 (get + NULL|self)
                    LOAD_CONST               4 ('days')
                    BUILD_LIST               0
                    LOAD_CONST               5 ((0, 1, 2, 3, 4, 5, 6))
                    LIST_EXTEND              1
                    CALL                     2
                    STORE_FAST               7 (iv_days)
    
      90            LOAD_FAST                7 (iv_days)
                    TO_BOOL
                    POP_JUMP_IF_FALSE        7 (to L5)
                    LOAD_FAST_LOAD_FAST     55 (iso_to_js_day, iv_days)
                    CONTAINS_OP              1
                    POP_JUMP_IF_FALSE        2 (to L5)
    
      91            JUMP_BACKWARD           37 (to L4)
    
      92    L5:     NOP
    
      93    L6:     LOAD_FAST                6 (iv)
                    LOAD_CONST               6 ('start')
                    BINARY_SUBSCR
                    LOAD_ATTR               17 (split + NULL|self)
                    LOAD_CONST               7 (':')
                    CALL                     1
                    STORE_FAST               8 (parts_s)
    
      94            LOAD_FAST                6 (iv)
                    LOAD_CONST               8 ('end')
                    BINARY_SUBSCR
                    LOAD_ATTR               17 (split + NULL|self)
                    LOAD_CONST               7 (':')
                    CALL                     1
                    STORE_FAST               9 (parts_e)
    
      95            LOAD_CONST               9 (0)
                    LOAD_CONST              10 (('time',))
                    IMPORT_NAME              1 (datetime)
                    IMPORT_FROM              5 (time)
                    STORE_FAST              10 (dt_time)
                    POP_TOP
    
      96            LOAD_FAST               10 (dt_time)
                    PUSH_NULL
                    LOAD_GLOBAL             19 (int + NULL)
                    LOAD_FAST                8 (parts_s)
                    LOAD_CONST               9 (0)
                    BINARY_SUBSCR
                    CALL                     1
                    LOAD_GLOBAL             19 (int + NULL)
                    LOAD_FAST                8 (parts_s)
                    LOAD_CONST               2 (1)
                    BINARY_SUBSCR
                    CALL                     1
                    CALL                     2
                    STORE_FAST              11 (start)
    
      97            LOAD_FAST               10 (dt_time)
                    PUSH_NULL
                    LOAD_GLOBAL             19 (int + NULL)
                    LOAD_FAST                9 (parts_e)
                    LOAD_CONST               9 (0)
                    BINARY_SUBSCR
                    CALL                     1
                    LOAD_GLOBAL             19 (int + NULL)
                    LOAD_FAST                9 (parts_e)
                    LOAD_CONST               2 (1)
                    BINARY_SUBSCR
                    CALL                     1
                    CALL                     2
                    STORE_FAST              12 (end)
    
      98            LOAD_GLOBAL             21 (_time_in_range + NULL)
                    LOAD_FAST_LOAD_FAST    188 (start, end)
                    LOAD_FAST                4 (current_time)
                    CALL                     3
                    TO_BOOL
                    POP_JUMP_IF_FALSE        2 (to L8)
    
      99    L7:     POP_TOP
                    RETURN_CONST            11 (True)
    
      98    L8:     JUMP_BACKWARD          171 (to L4)
    
      88    L9:     END_FOR
                    POP_TOP
    
     102            RETURN_CONST             1 (False)
    
     105   L10:     LOAD_FAST                0 (settings)
                    LOAD_ATTR               28 (quiet_hours_start)
                    POP_JUMP_IF_NONE        13 (to L11)
                    LOAD_FAST                0 (settings)
                    LOAD_ATTR               30 (quiet_hours_end)
                    POP_JUMP_IF_NOT_NONE     1 (to L12)
    
     106   L11:     RETURN_CONST             1 (False)
    
     108   L12:     LOAD_FAST                0 (settings)
                    LOAD_ATTR               32 (quiet_hours_days)
                    COPY                     1
                    TO_BOOL
                    POP_JUMP_IF_TRUE         2 (to L13)
                    POP_TOP
                    BUILD_LIST               0
           L13:     STORE_FAST              13 (days)
    
     109            LOAD_FAST               13 (days)
                    TO_BOOL
                    POP_JUMP_IF_FALSE        6 (to L14)
                    LOAD_FAST_LOAD_FAST     61 (iso_to_js_day, days)
                    CONTAINS_OP              1
                    POP_JUMP_IF_FALSE        1 (to L14)
    
     110            RETURN_CONST             1 (False)
    
     112   L14:     LOAD_GLOBAL             21 (_time_in_range + NULL)
                    LOAD_FAST                0 (settings)
                    LOAD_ATTR               28 (quiet_hours_start)
                    LOAD_FAST                0 (settings)
                    LOAD_ATTR               30 (quiet_hours_end)
                    LOAD_FAST                4 (current_time)
                    CALL                     3
                    RETURN_VALUE
    
      --   L15:     PUSH_EXC_INFO
    
     100            LOAD_GLOBAL             22 (KeyError)
                    LOAD_GLOBAL             24 (ValueError)
                    LOAD_GLOBAL             26 (IndexError)
                    BUILD_TUPLE              3
                    CHECK_EXC_MATCH
                    POP_JUMP_IF_FALSE        5 (to L17)
                    POP_TOP
    
     101   L16:     POP_EXCEPT
                    EXTENDED_ARG             1
                    JUMP_BACKWARD          293 (to L4)
    
     100   L17:     RERAISE                  0
    
      --   L18:     COPY                     3
                    POP_EXCEPT
                    RERAISE                  1
    ExceptionTable:
      L6 to L7 -> L15 [1]
      L15 to L16 -> L18 [2] lasti
      L17 to L18 -> L18 [2] lasti
    
# --- Nested code object: should_allow_call ---
    # DOCSTRING: """Return True if a call should ring through despite quiet hours."""
    # co_names: ('is_quiet_hours', 'quiet_hours_allow_vip')
    # co_varnames: ('settings', 'caller_is_vip')
    115           RESUME                   0
    
    117           LOAD_GLOBAL              1 (is_quiet_hours + NULL)
                  LOAD_FAST                0 (settings)
                  CALL                     1
                  TO_BOOL
                  POP_JUMP_IF_TRUE         1 (to L1)
    
    118           RETURN_CONST             1 (True)
    
    119   L1:     LOAD_FAST                1 (caller_is_vip)
                  COPY                     1
                  TO_BOOL
                  POP_JUMP_IF_FALSE       12 (to L2)
                  POP_TOP
                  LOAD_FAST                0 (settings)
                  LOAD_ATTR                2 (quiet_hours_allow_vip)
          L2:     RETURN_VALUE
    
# --- Nested code object: notify_call_screened ---
    # DOCSTRING: """Send a privacy-safe push notification when post-call artifacts are ready.

Respects quiet hours with bypass for urgent/VIP labels.
"""
    # --- Nested code object: notify_call_screened.<locals>.<genexpr> ---
        # DOCSTRING: """label_name"""
        # co_names: ('get',)
        # co_varnames: ('.0', 'lbl')
          --           COPY_FREE_VARS           1
        
         142           RETURN_GENERATOR
                       POP_TOP
               L1:     RESUME                   0
                       LOAD_FAST                0 (.0)
        
         143           GET_ITER
               L2:     FOR_ITER                24 (to L3)
                       STORE_FAST_LOAD_FAST    17 (lbl, lbl)
                       LOAD_ATTR                1 (get + NULL|self)
                       LOAD_CONST               0 ('label_name')
                       CALL                     1
                       LOAD_DEREF               2 (important_labels)
                       CONTAINS_OP              0
                       YIELD_VALUE              0
                       RESUME                   5
                       POP_TOP
                       JUMP_BACKWARD           26 (to L2)
               L3:     END_FOR
                       POP_TOP
                       RETURN_CONST             1 (None)
        
          --   L4:     CALL_INTRINSIC_1         3 (INTRINSIC_STOPITERATION_ERROR)
                       RERAISE                  1
        ExceptionTable:
          L1 to L4 -> L4 [0] lasti
        
    # co_names: ('execute', 'select', 'UserSettings', 'where', 'owner_user_id', 'scalar_one_or_none', 'any', 'is_quiet_hours', 'logger', 'info', 'str', 'notification_privacy_mode', 'build_push_payload', 'datetime', 'now', 'UTC', 'isoformat', 'PushToken', 'join', 'Device', 'device_id', 'id', 'revoked_at', 'is_', 'list', 'scalars', 'all', 'debug', 'hasattr', 'getattr', 'emit_event')
    # co_varnames: ('db', 'call_id', 'user_id', 'labels', 'settings_row', 'is_important', 'privacy_mode', '_payload', 'tokens_result', 'tokens', 'token', 'uid', 'cid')
      --            MAKE_CELL               13 (important_labels)
    
     122            RETURN_GENERATOR
                    POP_TOP
            L1:     RESUME                   0
    
     134            LOAD_FAST                0 (db)
                    LOAD_ATTR                1 (execute + NULL|self)
    
     135            LOAD_GLOBAL              3 (select + NULL)
                    LOAD_GLOBAL              4 (UserSettings)
                    CALL                     1
                    LOAD_ATTR                7 (where + NULL|self)
                    LOAD_GLOBAL              4 (UserSettings)
                    LOAD_ATTR                8 (owner_user_id)
                    LOAD_FAST                2 (user_id)
                    COMPARE_OP              72 (==)
                    CALL                     1
    
     134            CALL                     1
                    GET_AWAITABLE            0
                    LOAD_CONST               1 (None)
            L2:     SEND                     3 (to L5)
            L3:     YIELD_VALUE              1
            L4:     RESUME                   3
                    JUMP_BACKWARD_NO_INTERRUPT 5 (to L2)
            L5:     END_SEND
    
     137            LOAD_ATTR               11 (scalar_one_or_none + NULL|self)
                    CALL                     0
    
     133            STORE_FAST               4 (settings_row)
    
     139            LOAD_CONST               2 (False)
                    STORE_FAST               5 (is_important)
    
     140            LOAD_FAST                3 (labels)
                    TO_BOOL
                    POP_JUMP_IF_FALSE       25 (to L6)
    
     141            LOAD_CONST               3 ('urgent')
                    LOAD_CONST               4 ('vip')
                    BUILD_SET                2
                    STORE_DEREF             13 (important_labels)
    
     142            LOAD_GLOBAL             13 (any + NULL)
                    LOAD_FAST               13 (important_labels)
                    BUILD_TUPLE              1
                    LOAD_CONST               5 (<code object <genexpr> at 0x0000024C11496C10, file "D:\fluence\Github\mattbot\backend\app\services\notification_service.py", line 142>)
                    MAKE_FUNCTION
                    SET_FUNCTION_ATTRIBUTE   8 (closure)
    
     143            LOAD_FAST                3 (labels)
                    GET_ITER
    
     142            CALL                     0
                    CALL                     1
                    STORE_FAST               5 (is_important)
    
     147    L6:     LOAD_FAST                4 (settings_row)
                    TO_BOOL
                    POP_JUMP_IF_FALSE       58 (to L7)
                    LOAD_GLOBAL             15 (is_quiet_hours + NULL)
                    LOAD_FAST                4 (settings_row)
                    CALL                     1
                    TO_BOOL
                    POP_JUMP_IF_FALSE       42 (to L7)
                    LOAD_FAST                5 (is_important)
                    TO_BOOL
                    POP_JUMP_IF_TRUE        35 (to L7)
    
     148            LOAD_GLOBAL             16 (logger)
                    LOAD_ATTR               19 (info + NULL|self)
    
     149            LOAD_CONST               6 ('Suppressing call_screened notification for %s (quiet hours)')
    
     150            LOAD_GLOBAL             21 (str + NULL)
                    LOAD_FAST                1 (call_id)
                    CALL                     1
                    LOAD_CONST               1 (None)
                    LOAD_CONST               7 (8)
                    BINARY_SLICE
    
     148            CALL                     2
                    POP_TOP
    
     152            RETURN_CONST             1 (None)
    
     154    L7:     LOAD_CONST               8 ('private')
                    STORE_FAST               6 (privacy_mode)
    
     155            LOAD_FAST                4 (settings_row)
                    TO_BOOL
                    POP_JUMP_IF_FALSE       21 (to L9)
    
     156            LOAD_FAST                4 (settings_row)
                    LOAD_ATTR               22 (notification_privacy_mode)
                    COPY                     1
                    TO_BOOL
                    POP_JUMP_IF_TRUE         2 (to L8)
                    POP_TOP
                    LOAD_CONST               8 ('private')
            L8:     STORE_FAST               6 (privacy_mode)
    
     158    L9:     LOAD_GLOBAL             25 (build_push_payload + NULL)
    
     159            LOAD_CONST               9 ('call_screened')
    
     161            LOAD_GLOBAL             21 (str + NULL)
                    LOAD_FAST                1 (call_id)
                    CALL                     1
    
     162            LOAD_CONST               9 ('call_screened')
    
     163            LOAD_GLOBAL             26 (datetime)
                    LOAD_ATTR               28 (now)
                    PUSH_NULL
                    LOAD_GLOBAL             30 (UTC)
                    CALL                     1
                    LOAD_ATTR               33 (isoformat + NULL|self)
                    CALL                     0
    
     160            LOAD_CONST              10 (('call_id', 'event_type', 'timestamp'))
                    BUILD_CONST_KEY_MAP      3
    
     165            LOAD_FAST                6 (privacy_mode)
    
     158            LOAD_CONST              11 (('notification_type', 'data', 'privacy_mode'))
                    CALL_KW                  3
                    STORE_FAST               7 (_payload)
    
     169            LOAD_FAST                0 (db)
                    LOAD_ATTR                1 (execute + NULL|self)
    
     170            LOAD_GLOBAL              3 (select + NULL)
                    LOAD_GLOBAL             34 (PushToken)
                    CALL                     1
    
     171            LOAD_ATTR               37 (join + NULL|self)
                    LOAD_GLOBAL             38 (Device)
                    LOAD_GLOBAL             34 (PushToken)
                    LOAD_ATTR               40 (device_id)
                    LOAD_GLOBAL             38 (Device)
                    LOAD_ATTR               42 (id)
                    COMPARE_OP              72 (==)
                    CALL                     2
    
     172            LOAD_ATTR                7 (where + NULL|self)
    
     173            LOAD_GLOBAL             38 (Device)
                    LOAD_ATTR                8 (owner_user_id)
                    LOAD_FAST                2 (user_id)
                    COMPARE_OP              72 (==)
    
     174            LOAD_GLOBAL             38 (Device)
                    LOAD_ATTR               44 (revoked_at)
                    LOAD_ATTR               47 (is_ + NULL|self)
                    LOAD_CONST               1 (None)
                    CALL                     1
    
     175            LOAD_GLOBAL             34 (PushToken)
                    LOAD_ATTR               44 (revoked_at)
                    LOAD_ATTR               47 (is_ + NULL|self)
                    LOAD_CONST               1 (None)
                    CALL                     1
    
     172            CALL                     3
    
     169            CALL                     1
                    GET_AWAITABLE            0
                    LOAD_CONST               1 (None)
           L10:     SEND                     3 (to L13)
           L11:     YIELD_VALUE              1
           L12:     RESUME                   3
                    JUMP_BACKWARD_NO_INTERRUPT 5 (to L10)
           L13:     END_SEND
                    STORE_FAST               8 (tokens_result)
    
     178            LOAD_GLOBAL             49 (list + NULL)
                    LOAD_FAST                8 (tokens_result)
                    LOAD_ATTR               51 (scalars + NULL|self)
                    CALL                     0
                    LOAD_ATTR               53 (all + NULL|self)
                    CALL                     0
                    CALL                     1
                    STORE_FAST               9 (tokens)
    
     180            LOAD_FAST                9 (tokens)
                    TO_BOOL
                    POP_JUMP_IF_TRUE        35 (to L14)
    
     181            LOAD_GLOBAL             16 (logger)
                    LOAD_ATTR               55 (debug + NULL|self)
                    LOAD_CONST              12 ('No push tokens for user %s')
                    LOAD_GLOBAL             21 (str + NULL)
                    LOAD_FAST                2 (user_id)
                    CALL                     1
                    LOAD_CONST               1 (None)
                    LOAD_CONST               7 (8)
                    BINARY_SLICE
                    CALL                     2
                    POP_TOP
    
     182            RETURN_CONST             1 (None)
    
     184   L14:     LOAD_FAST                9 (tokens)
                    GET_ITER
           L15:     FOR_ITER                91 (to L18)
                    STORE_FAST              10 (token)
    
     185            LOAD_GLOBAL             16 (logger)
                    LOAD_ATTR               19 (info + NULL|self)
    
     186            LOAD_CONST              13 ('Would send push to device %s for call %s (provider=%s)')
    
     187            LOAD_GLOBAL             57 (hasattr + NULL)
                    LOAD_FAST               10 (token)
                    LOAD_CONST              14 ('device_id')
                    CALL                     2
                    TO_BOOL
                    POP_JUMP_IF_FALSE       24 (to L16)
                    LOAD_GLOBAL             21 (str + NULL)
                    LOAD_FAST               10 (token)
                    LOAD_ATTR               40 (device_id)
                    CALL                     1
                    LOAD_CONST               1 (None)
                    LOAD_CONST               7 (8)
                    BINARY_SLICE
                    JUMP_FORWARD             1 (to L17)
           L16:     LOAD_CONST              15 ('unknown')
    
     188   L17:     LOAD_GLOBAL             21 (str + NULL)
                    LOAD_FAST                1 (call_id)
                    CALL                     1
                    LOAD_CONST               1 (None)
                    LOAD_CONST               7 (8)
                    BINARY_SLICE
    
     189            LOAD_GLOBAL             59 (getattr + NULL)
                    LOAD_FAST               10 (token)
                    LOAD_CONST              16 ('provider')
                    LOAD_CONST              15 ('unknown')
                    CALL                     3
    
     185            CALL                     4
                    POP_TOP
                    JUMP_BACKWARD           93 (to L15)
    
     184   L18:     END_FOR
                    POP_TOP
    
     195            LOAD_GLOBAL             21 (str + NULL)
                    LOAD_FAST                2 (user_id)
                    CALL                     1
                    STORE_FAST              11 (uid)
    
     196            LOAD_GLOBAL             21 (str + NULL)
                    LOAD_FAST                1 (call_id)
                    CALL                     1
                    STORE_FAST              12 (cid)
    
     197            LOAD_GLOBAL             61 (emit_event + NULL)
    
     198            LOAD_FAST               11 (uid)
    
     199            LOAD_CONST              17 ('CALL_ENDED')
    
     200            LOAD_FAST               12 (cid)
    
     201            LOAD_CONST              18 (1)
    
     202            LOAD_CONST              19 ('labels')
                    LOAD_FAST                3 (labels)
                    COPY                     1
                    TO_BOOL
                    POP_JUMP_IF_TRUE         2 (to L19)
                    POP_TOP
                    BUILD_LIST               0
           L19:     BUILD_MAP                1
    
     197            LOAD_CONST              20 (('user_id', 'event_type', 'call_id', 'seq', 'payload'))
                    CALL_KW                  5
                    GET_AWAITABLE            0
                    LOAD_CONST               1 (None)
           L20:     SEND                     3 (to L23)
           L21:     YIELD_VALUE              1
           L22:     RESUME                   3
                    JUMP_BACKWARD_NO_INTERRUPT 5 (to L20)
           L23:     END_SEND
                    POP_TOP
    
     204            LOAD_GLOBAL             61 (emit_event + NULL)
    
     205            LOAD_FAST               11 (uid)
    
     206            LOAD_CONST              21 ('SUMMARY_READY')
    
     207            LOAD_FAST               12 (cid)
    
     208            LOAD_CONST              22 (2)
    
     209            BUILD_MAP                0
    
     204            LOAD_CONST              20 (('user_id', 'event_type', 'call_id', 'seq', 'payload'))
                    CALL_KW                  5
                    GET_AWAITABLE            0
                    LOAD_CONST               1 (None)
           L24:     SEND                     3 (to L27)
           L25:     YIELD_VALUE              1
           L26:     RESUME                   3
                    JUMP_BACKWARD_NO_INTERRUPT 5 (to L24)
           L27:     END_SEND
                    POP_TOP
    
     211            LOAD_GLOBAL             61 (emit_event + NULL)
    
     212            LOAD_FAST               11 (uid)
    
     213            LOAD_CONST              23 ('TRANSCRIPT_READY')
    
     214            LOAD_FAST               12 (cid)
    
     215            LOAD_CONST              24 (3)
    
     216            BUILD_MAP                0
    
     211            LOAD_CONST              20 (('user_id', 'event_type', 'call_id', 'seq', 'payload'))
                    CALL_KW                  5
                    GET_AWAITABLE            0
                    LOAD_CONST               1 (None)
           L28:     SEND                     3 (to L31)
           L29:     YIELD_VALUE              1
           L30:     RESUME                   3
                    JUMP_BACKWARD_NO_INTERRUPT 5 (to L28)
           L31:     END_SEND
                    POP_TOP
                    RETURN_CONST             1 (None)
    
     134   L32:     CLEANUP_THROW
           L33:     EXTENDED_ARG             2
                    JUMP_BACKWARD_NO_INTERRUPT 666 (to L5)
    
     169   L34:     CLEANUP_THROW
           L35:     EXTENDED_ARG             1
                    JUMP_BACKWARD_NO_INTERRUPT 283 (to L13)
    
     197   L36:     CLEANUP_THROW
           L37:     JUMP_BACKWARD_NO_INTERRUPT 53 (to L23)
    
     204   L38:     CLEANUP_THROW
           L39:     JUMP_BACKWARD_NO_INTERRUPT 34 (to L27)
    
     211   L40:     CLEANUP_THROW
           L41:     JUMP_BACKWARD_NO_INTERRUPT 15 (to L31)
    
      --   L42:     CALL_INTRINSIC_1         3 (INTRINSIC_STOPITERATION_ERROR)
                    RERAISE                  1
    ExceptionTable:
      L1 to L3 -> L42 [0] lasti
      L3 to L4 -> L32 [2]
      L4 to L11 -> L42 [0] lasti
      L11 to L12 -> L34 [2]
      L12 to L21 -> L42 [0] lasti
      L21 to L22 -> L36 [2]
      L22 to L25 -> L42 [0] lasti
      L25 to L26 -> L38 [2]
      L26 to L29 -> L42 [0] lasti
      L29 to L30 -> L40 [2]
      L30 to L33 -> L42 [0] lasti
      L34 to L35 -> L42 [0] lasti
      L36 to L37 -> L42 [0] lasti
      L38 to L39 -> L42 [0] lasti
      L40 to L41 -> L42 [0] lasti
    
    Disassembly of <code object <genexpr> at 0x0000024C11496C10, file "D:\fluence\Github\mattbot\backend\app\services\notification_service.py", line 142>:
      --           COPY_FREE_VARS           1
    
     142           RETURN_GENERATOR
                   POP_TOP
           L1:     RESUME                   0
                   LOAD_FAST                0 (.0)
    
     143           GET_ITER
           L2:     FOR_ITER                24 (to L3)
                   STORE_FAST_LOAD_FAST    17 (lbl, lbl)
                   LOAD_ATTR                1 (get + NULL|self)
                   LOAD_CONST               0 ('label_name')
                   CALL                     1
                   LOAD_DEREF               2 (important_labels)
                   CONTAINS_OP              0
                   YIELD_VALUE              0
                   RESUME                   5
                   POP_TOP
                   JUMP_BACKWARD           26 (to L2)
           L3:     END_FOR
                   POP_TOP
                   RETURN_CONST             1 (None)
    
      --   L4:     CALL_INTRINSIC_1         3 (INTRINSIC_STOPITERATION_ERROR)
                   RERAISE                  1
    ExceptionTable:
      L1 to L4 -> L4 [0] lasti
    
# --- Nested code object: create_and_enqueue_notification ---
    # DOCSTRING: """Persist a notification and create delivery rows for each active device."""
    # co_names: ('execute', 'select', 'UserSettings', 'where', 'owner_user_id', 'scalar_one_or_none', 'notification_privacy_mode', 'is_quiet_hours', 'Notification', 'add', 'flush', 'PushToken', 'join', 'Device', 'device_id', 'id', 'revoked_at', 'is_', 'list', 'scalars', 'all', 'NotificationDelivery', 'provider', 'logger', 'info', 'str', 'len')
    # co_varnames: ('db', 'owner_user_id', 'notification_type', 'priority', 'source_entity_type', 'source_entity_id', 'settings_row', 'privacy_mode', 'quiet_hours_value', 'notification', 'tokens_result', 'tokens', 'token', 'delivery')
     220            RETURN_GENERATOR
                    POP_TOP
            L1:     RESUME                   0
    
     231            LOAD_FAST                0 (db)
                    LOAD_ATTR                1 (execute + NULL|self)
    
     232            LOAD_GLOBAL              3 (select + NULL)
                    LOAD_GLOBAL              4 (UserSettings)
                    CALL                     1
                    LOAD_ATTR                7 (where + NULL|self)
                    LOAD_GLOBAL              4 (UserSettings)
                    LOAD_ATTR                8 (owner_user_id)
                    LOAD_FAST                1 (owner_user_id)
                    COMPARE_OP              72 (==)
                    CALL                     1
    
     231            CALL                     1
                    GET_AWAITABLE            0
                    LOAD_CONST               1 (None)
            L2:     SEND                     3 (to L5)
            L3:     YIELD_VALUE              1
            L4:     RESUME                   3
                    JUMP_BACKWARD_NO_INTERRUPT 5 (to L2)
            L5:     END_SEND
    
     234            LOAD_ATTR               11 (scalar_one_or_none + NULL|self)
                    CALL                     0
    
     230            STORE_FAST               6 (settings_row)
    
     236            LOAD_CONST               2 ('private')
                    STORE_FAST               7 (privacy_mode)
    
     237            LOAD_FAST                6 (settings_row)
                    TO_BOOL
                    POP_JUMP_IF_FALSE       21 (to L7)
    
     238            LOAD_FAST                6 (settings_row)
                    LOAD_ATTR               12 (notification_privacy_mode)
                    COPY                     1
                    TO_BOOL
                    POP_JUMP_IF_TRUE         2 (to L6)
                    POP_TOP
                    LOAD_CONST               2 ('private')
            L6:     STORE_FAST               7 (privacy_mode)
    
     240    L7:     LOAD_CONST               3 ('none')
                    STORE_FAST               8 (quiet_hours_value)
    
     241            LOAD_FAST                6 (settings_row)
                    TO_BOOL
                    POP_JUMP_IF_FALSE       26 (to L10)
                    LOAD_GLOBAL             15 (is_quiet_hours + NULL)
                    LOAD_FAST                6 (settings_row)
                    CALL                     1
                    TO_BOOL
                    POP_JUMP_IF_FALSE       10 (to L10)
    
     242            LOAD_FAST                3 (priority)
                    LOAD_CONST               4 (('low', 'normal'))
                    CONTAINS_OP              0
                    POP_JUMP_IF_FALSE        2 (to L8)
                    LOAD_CONST               5 ('suppressed')
                    JUMP_FORWARD             1 (to L9)
            L8:     LOAD_CONST               6 ('silent')
            L9:     STORE_FAST               8 (quiet_hours_value)
    
     244   L10:     LOAD_GLOBAL             17 (Notification + NULL)
    
     245            LOAD_FAST                1 (owner_user_id)
    
     246            LOAD_FAST                2 (notification_type)
    
     247            LOAD_FAST                3 (priority)
    
     248            LOAD_FAST                4 (source_entity_type)
    
     249            LOAD_FAST                5 (source_entity_id)
    
     250            LOAD_FAST                7 (privacy_mode)
    
     251            LOAD_FAST                8 (quiet_hours_value)
    
     244            LOAD_CONST               7 (('owner_user_id', 'type', 'priority', 'source_entity_type', 'source_entity_id', 'privacy_mode_applied', 'quiet_hours_applied'))
                    CALL_KW                  7
                    STORE_FAST               9 (notification)
    
     253            LOAD_FAST                0 (db)
                    LOAD_ATTR               19 (add + NULL|self)
                    LOAD_FAST                9 (notification)
                    CALL                     1
                    POP_TOP
    
     254            LOAD_FAST                0 (db)
                    LOAD_ATTR               21 (flush + NULL|self)
                    CALL                     0
                    GET_AWAITABLE            0
                    LOAD_CONST               1 (None)
           L11:     SEND                     3 (to L14)
           L12:     YIELD_VALUE              1
           L13:     RESUME                   3
                    JUMP_BACKWARD_NO_INTERRUPT 5 (to L11)
           L14:     END_SEND
                    POP_TOP
    
     256            LOAD_FAST                0 (db)
                    LOAD_ATTR                1 (execute + NULL|self)
    
     257            LOAD_GLOBAL              3 (select + NULL)
                    LOAD_GLOBAL             22 (PushToken)
                    CALL                     1
    
     258            LOAD_ATTR               25 (join + NULL|self)
                    LOAD_GLOBAL             26 (Device)
                    LOAD_GLOBAL             22 (PushToken)
                    LOAD_ATTR               28 (device_id)
                    LOAD_GLOBAL             26 (Device)
                    LOAD_ATTR               30 (id)
                    COMPARE_OP              72 (==)
                    CALL                     2
    
     259            LOAD_ATTR                7 (where + NULL|self)
    
     260            LOAD_GLOBAL             26 (Device)
                    LOAD_ATTR                8 (owner_user_id)
                    LOAD_FAST                1 (owner_user_id)
                    COMPARE_OP              72 (==)
    
     261            LOAD_GLOBAL             26 (Device)
                    LOAD_ATTR               32 (revoked_at)
                    LOAD_ATTR               35 (is_ + NULL|self)
                    LOAD_CONST               1 (None)
                    CALL                     1
    
     262            LOAD_GLOBAL             22 (PushToken)
                    LOAD_ATTR               32 (revoked_at)
                    LOAD_ATTR               35 (is_ + NULL|self)
                    LOAD_CONST               1 (None)
                    CALL                     1
    
     259            CALL                     3
    
     256            CALL                     1
                    GET_AWAITABLE            0
                    LOAD_CONST               1 (None)
           L15:     SEND                     3 (to L18)
           L16:     YIELD_VALUE              1
           L17:     RESUME                   3
                    JUMP_BACKWARD_NO_INTERRUPT 5 (to L15)
           L18:     END_SEND
                    STORE_FAST              10 (tokens_result)
    
     265            LOAD_GLOBAL             37 (list + NULL)
                    LOAD_FAST               10 (tokens_result)
                    LOAD_ATTR               39 (scalars + NULL|self)
                    CALL                     0
                    LOAD_ATTR               41 (all + NULL|self)
                    CALL                     0
                    CALL                     1
                    STORE_FAST              11 (tokens)
    
     267            LOAD_FAST               11 (tokens)
                    GET_ITER
           L19:     FOR_ITER                61 (to L20)
                    STORE_FAST              12 (token)
    
     268            LOAD_GLOBAL             43 (NotificationDelivery + NULL)
    
     269            LOAD_FAST                9 (notification)
                    LOAD_ATTR               30 (id)
    
     270            LOAD_FAST               12 (token)
                    LOAD_ATTR               28 (device_id)
    
     271            LOAD_FAST               12 (token)
                    LOAD_ATTR               44 (provider)
    
     268            LOAD_CONST               8 (('notification_id', 'device_id', 'provider'))
                    CALL_KW                  3
                    STORE_FAST              13 (delivery)
    
     273            LOAD_FAST                0 (db)
                    LOAD_ATTR               19 (add + NULL|self)
                    LOAD_FAST               13 (delivery)
                    CALL                     1
                    POP_TOP
                    JUMP_BACKWARD           63 (to L19)
    
     267   L20:     END_FOR
                    POP_TOP
    
     275            LOAD_FAST                0 (db)
                    LOAD_ATTR               21 (flush + NULL|self)
                    CALL                     0
                    GET_AWAITABLE            0
                    LOAD_CONST               1 (None)
           L21:     SEND                     3 (to L24)
           L22:     YIELD_VALUE              1
           L23:     RESUME                   3
                    JUMP_BACKWARD_NO_INTERRUPT 5 (to L21)
           L24:     END_SEND
                    POP_TOP
    
     277            LOAD_GLOBAL             46 (logger)
                    LOAD_ATTR               49 (info + NULL|self)
    
     278            LOAD_CONST               9 ('Created notification %s (%s) for user %s with %d delivery(ies)')
    
     279            LOAD_GLOBAL             51 (str + NULL)
                    LOAD_FAST                9 (notification)
                    LOAD_ATTR               30 (id)
                    CALL                     1
                    LOAD_CONST               1 (None)
                    LOAD_CONST              10 (8)
                    BINARY_SLICE
    
     280            LOAD_FAST                2 (notification_type)
    
     281            LOAD_GLOBAL             51 (str + NULL)
                    LOAD_FAST                1 (owner_user_id)
                    CALL                     1
                    LOAD_CONST               1 (None)
                    LOAD_CONST              10 (8)
                    BINARY_SLICE
    
     282            LOAD_GLOBAL             53 (len + NULL)
                    LOAD_FAST               11 (tokens)
                    CALL                     1
    
     277            CALL                     5
                    POP_TOP
    
     285            LOAD_FAST                9 (notification)
                    RETURN_VALUE
    
     231   L25:     CLEANUP_THROW
           L26:     EXTENDED_ARG             2
                    JUMP_BACKWARD_NO_INTERRUPT 521 (to L5)
    
     254   L27:     CLEANUP_THROW
           L28:     EXTENDED_ARG             1
                    JUMP_BACKWARD_NO_INTERRUPT 389 (to L14)
    
     256   L29:     CLEANUP_THROW
           L30:     JUMP_BACKWARD_NO_INTERRUPT 210 (to L18)
    
     275   L31:     CLEANUP_THROW
           L32:     JUMP_BACKWARD_NO_INTERRUPT 82 (to L24)
    
      --   L33:     CALL_INTRINSIC_1         3 (INTRINSIC_STOPITERATION_ERROR)
                    RERAISE                  1
    ExceptionTable:
      L1 to L3 -> L33 [0] lasti
      L3 to L4 -> L25 [2]
      L4 to L12 -> L33 [0] lasti
      L12 to L13 -> L27 [2]
      L13 to L16 -> L33 [0] lasti
      L16 to L17 -> L29 [2]
      L17 to L22 -> L33 [0] lasti
      L22 to L23 -> L31 [2]
      L23 to L26 -> L33 [0] lasti
      L27 to L28 -> L33 [0] lasti
      L29 to L30 -> L33 [0] lasti
      L31 to L32 -> L33 [0] lasti
    
# --- Nested code object: _decrypt_personal_phone ---
    # DOCSTRING: """Decrypt the user's personal phone. Falls back to legacy urgent_notify_phone."""
    # co_names: ('personal_phone_ciphertext', 'personal_phone_nonce', 'personal_phone_key_version', 'decrypt_field', 'decode', 'Exception', 'logger', 'exception', 'urgent_notify_phone_ciphertext', 'urgent_notify_phone_nonce', 'urgent_notify_phone_key_version')
    # co_varnames: ('settings_row', 'ct', 'nonce', 'kv')
     288            RESUME                   0
    
     291            LOAD_FAST                0 (settings_row)
                    LOAD_ATTR                0 (personal_phone_ciphertext)
                    STORE_FAST               1 (ct)
    
     292            LOAD_FAST                0 (settings_row)
                    LOAD_ATTR                2 (personal_phone_nonce)
                    STORE_FAST               2 (nonce)
    
     293            LOAD_FAST                0 (settings_row)
                    LOAD_ATTR                4 (personal_phone_key_version)
                    STORE_FAST               3 (kv)
    
     294            LOAD_FAST                1 (ct)
                    TO_BOOL
                    POP_JUMP_IF_FALSE       38 (to L3)
                    LOAD_FAST                2 (nonce)
                    TO_BOOL
                    POP_JUMP_IF_FALSE       31 (to L3)
                    LOAD_FAST                3 (kv)
                    POP_JUMP_IF_NONE        28 (to L3)
    
     295            NOP
    
     296    L1:     LOAD_GLOBAL              7 (decrypt_field + NULL)
                    LOAD_FAST_LOAD_FAST     18 (ct, nonce)
                    LOAD_FAST                3 (kv)
                    CALL                     3
                    LOAD_ATTR                9 (decode + NULL|self)
                    LOAD_CONST               2 ('utf-8')
                    CALL                     1
            L2:     RETURN_VALUE
    
     301    L3:     LOAD_FAST                0 (settings_row)
                    LOAD_ATTR               16 (urgent_notify_phone_ciphertext)
                    STORE_FAST               1 (ct)
    
     302            LOAD_FAST                0 (settings_row)
                    LOAD_ATTR               18 (urgent_notify_phone_nonce)
                    STORE_FAST               2 (nonce)
    
     303            LOAD_FAST                0 (settings_row)
                    LOAD_ATTR               20 (urgent_notify_phone_key_version)
                    STORE_FAST               3 (kv)
    
     304            LOAD_FAST                1 (ct)
                    TO_BOOL
                    POP_JUMP_IF_FALSE       38 (to L6)
                    LOAD_FAST                2 (nonce)
                    TO_BOOL
                    POP_JUMP_IF_FALSE       31 (to L6)
                    LOAD_FAST                3 (kv)
                    POP_JUMP_IF_NONE        28 (to L6)
    
     305            NOP
    
     306    L4:     LOAD_GLOBAL              7 (decrypt_field + NULL)
                    LOAD_FAST_LOAD_FAST     18 (ct, nonce)
                    LOAD_FAST                3 (kv)
                    CALL                     3
                    LOAD_ATTR                9 (decode + NULL|self)
                    LOAD_CONST               2 ('utf-8')
                    CALL                     1
            L5:     RETURN_VALUE
    
     310    L6:     RETURN_CONST             1 (None)
    
      --    L7:     PUSH_EXC_INFO
    
     297            LOAD_GLOBAL             10 (Exception)
                    CHECK_EXC_MATCH
                    POP_JUMP_IF_FALSE       24 (to L9)
                    POP_TOP
    
     298            LOAD_GLOBAL             12 (logger)
                    LOAD_ATTR               15 (exception + NULL|self)
                    LOAD_CONST               3 ('Failed to decrypt personal phone')
                    CALL                     1
                    POP_TOP
            L8:     POP_EXCEPT
                    JUMP_BACKWARD_NO_INTERRUPT 115 (to L3)
    
     297    L9:     RERAISE                  0
    
      --   L10:     COPY                     3
                    POP_EXCEPT
                    RERAISE                  1
           L11:     PUSH_EXC_INFO
    
     307            LOAD_GLOBAL             10 (Exception)
                    CHECK_EXC_MATCH
                    POP_JUMP_IF_FALSE       24 (to L13)
                    POP_TOP
    
     308            LOAD_GLOBAL             12 (logger)
                    LOAD_ATTR               15 (exception + NULL|self)
                    LOAD_CONST               4 ('Failed to decrypt urgent notify phone')
                    CALL                     1
                    POP_TOP
           L12:     POP_EXCEPT
    
     310            RETURN_CONST             1 (None)
    
     307   L13:     RERAISE                  0
    
      --   L14:     COPY                     3
                    POP_EXCEPT
                    RERAISE                  1
    ExceptionTable:
      L1 to L2 -> L7 [0]
      L4 to L5 -> L11 [0]
      L7 to L8 -> L10 [1] lasti
      L9 to L10 -> L10 [1] lasti
      L11 to L12 -> L14 [1] lasti
      L13 to L14 -> L14 [1] lasti
    
# --- Nested code object: send_urgent_sms ---
    # DOCSTRING: """Send SMS alert to user's urgent notification phone via Twilio."""
    # co_names: ('_decrypt_personal_phone', 'logger', 'warning', 'app.services.telephony_service', '_get_twilio_client', 'messages', 'create', 'info', 'str', 'Exception', 'exception')
    # co_varnames: ('settings_row', 'caller_info', 'summary_snippet', 'call_id', 'from_number', 'phone', '_get_twilio_client', 'client', 'body')
     313            RETURN_GENERATOR
                    POP_TOP
            L1:     RESUME                   0
    
     321            LOAD_GLOBAL              1 (_decrypt_personal_phone + NULL)
                    LOAD_FAST                0 (settings_row)
                    CALL                     1
                    STORE_FAST               5 (phone)
    
     322            LOAD_FAST                5 (phone)
                    TO_BOOL
                    POP_JUMP_IF_TRUE        22 (to L2)
    
     323            LOAD_GLOBAL              2 (logger)
                    LOAD_ATTR                5 (warning + NULL|self)
                    LOAD_CONST               1 ('Cannot send urgent SMS: no phone configured')
                    CALL                     1
                    POP_TOP
    
     324            RETURN_CONST             2 (False)
    
     325    L2:     LOAD_FAST                4 (from_number)
                    TO_BOOL
                    POP_JUMP_IF_TRUE        22 (to L3)
    
     326            LOAD_GLOBAL              2 (logger)
                    LOAD_ATTR                5 (warning + NULL|self)
                    LOAD_CONST               3 ('Cannot send urgent SMS: no from_number available')
                    CALL                     1
                    POP_TOP
    
     327            RETURN_CONST             2 (False)
    
     329    L3:     NOP
    
     330    L4:     LOAD_CONST               4 (0)
                    LOAD_CONST               5 (('_get_twilio_client',))
                    IMPORT_NAME              3 (app.services.telephony_service)
                    IMPORT_FROM              4 (_get_twilio_client)
                    STORE_FAST               6 (_get_twilio_client)
                    POP_TOP
    
     332            LOAD_FAST                6 (_get_twilio_client)
                    PUSH_NULL
                    CALL                     0
                    STORE_FAST               7 (client)
    
     334            LOAD_CONST               6 ('URGENT CALL from ')
                    LOAD_FAST                1 (caller_info)
                    FORMAT_SIMPLE
                    LOAD_CONST               7 (': ')
                    LOAD_FAST                2 (summary_snippet)
                    LOAD_CONST               8 (None)
                    LOAD_CONST               9 (120)
                    BINARY_SLICE
                    FORMAT_SIMPLE
                    LOAD_CONST              10 ('. Open MattBot for details.')
                    BUILD_STRING             5
    
     333            STORE_FAST               8 (body)
    
     337            LOAD_FAST                7 (client)
                    LOAD_ATTR               10 (messages)
                    LOAD_ATTR               13 (create + NULL|self)
    
     338            LOAD_FAST                8 (body)
    
     339            LOAD_FAST                4 (from_number)
    
     340            LOAD_FAST                5 (phone)
    
     337            LOAD_CONST              11 (('body', 'from_', 'to'))
                    CALL_KW                  3
                    POP_TOP
    
     342            LOAD_GLOBAL              2 (logger)
                    LOAD_ATTR               15 (info + NULL|self)
                    LOAD_CONST              12 ('Urgent SMS sent to ***%s for call %s')
                    LOAD_FAST                5 (phone)
                    LOAD_CONST              13 (-4)
                    LOAD_CONST               8 (None)
                    BINARY_SLICE
                    LOAD_GLOBAL             17 (str + NULL)
                    LOAD_FAST                3 (call_id)
                    CALL                     1
                    LOAD_CONST               8 (None)
                    LOAD_CONST              14 (8)
                    BINARY_SLICE
                    CALL                     3
                    POP_TOP
    
     343    L5:     RETURN_CONST            15 (True)
    
      --    L6:     PUSH_EXC_INFO
    
     344            LOAD_GLOBAL             18 (Exception)
                    CHECK_EXC_MATCH
                    POP_JUMP_IF_FALSE       37 (to L8)
                    POP_TOP
    
     345            LOAD_GLOBAL              2 (logger)
                    LOAD_ATTR               21 (exception + NULL|self)
                    LOAD_CONST              16 ('Failed to send urgent SMS for call %s')
                    LOAD_GLOBAL             17 (str + NULL)
                    LOAD_FAST                3 (call_id)
                    CALL                     1
                    LOAD_CONST               8 (None)
                    LOAD_CONST              14 (8)
                    BINARY_SLICE
                    CALL                     2
                    POP_TOP
    
     346    L7:     POP_EXCEPT
                    RETURN_CONST             2 (False)
    
     344    L8:     RERAISE                  0
    
      --    L9:     COPY                     3
                    POP_EXCEPT
                    RERAISE                  1
           L10:     CALL_INTRINSIC_1         3 (INTRINSIC_STOPITERATION_ERROR)
                    RERAISE                  1
    ExceptionTable:
      L1 to L3 -> L10 [0] lasti
      L4 to L5 -> L6 [0]
      L5 to L6 -> L10 [0] lasti
      L6 to L7 -> L9 [1] lasti
      L7 to L8 -> L10 [0] lasti
      L8 to L9 -> L9 [1] lasti
      L9 to L10 -> L10 [0] lasti
    
# --- Nested code object: send_urgent_email ---
    # DOCSTRING: """Send email alert for an urgent call."""
    # co_names: ('urgent_notify_email_address', 'logger', 'warning', 'app.services.email_service', 'send_email', 'info', 'str', 'Exception', 'exception')
    # co_varnames: ('settings_row', 'user_email', 'caller_info', 'summary_snippet', 'call_id', 'to_address', 'send_email', 'subject', 'body')
     349            RETURN_GENERATOR
                    POP_TOP
            L1:     RESUME                   0
    
     357            LOAD_FAST                0 (settings_row)
                    LOAD_ATTR                0 (urgent_notify_email_address)
                    COPY                     1
                    TO_BOOL
                    POP_JUMP_IF_TRUE         2 (to L2)
                    POP_TOP
                    LOAD_FAST                1 (user_email)
            L2:     STORE_FAST               5 (to_address)
    
     358            LOAD_FAST                5 (to_address)
                    TO_BOOL
                    POP_JUMP_IF_TRUE        22 (to L3)
    
     359            LOAD_GLOBAL              2 (logger)
                    LOAD_ATTR                5 (warning + NULL|self)
                    LOAD_CONST               1 ('Cannot send urgent email: no email address available')
                    CALL                     1
                    POP_TOP
    
     360            RETURN_CONST             2 (False)
    
     362    L3:     NOP
    
     363    L4:     LOAD_CONST               3 (0)
                    LOAD_CONST               4 (('send_email',))
                    IMPORT_NAME              3 (app.services.email_service)
                    IMPORT_FROM              4 (send_email)
                    STORE_FAST               6 (send_email)
                    POP_TOP
    
     365            LOAD_CONST               5 ('Urgent Call from ')
                    LOAD_FAST                2 (caller_info)
                    FORMAT_SIMPLE
                    BUILD_STRING             2
                    STORE_FAST               7 (subject)
    
     367            LOAD_CONST               6 ('You have an urgent call in MattBot.\n\nCaller: ')
    
     368            LOAD_FAST                2 (caller_info)
                    FORMAT_SIMPLE
                    LOAD_CONST               7 ('\nSummary: ')
    
     369            LOAD_FAST                3 (summary_snippet)
                    FORMAT_SIMPLE
                    LOAD_CONST               8 ('\n\nOpen the app for full details: mattbot://call/')
    
     370            LOAD_FAST                4 (call_id)
                    FORMAT_SIMPLE
    
     367            BUILD_STRING             6
    
     366            STORE_FAST               8 (body)
    
     372            LOAD_FAST                6 (send_email)
                    PUSH_NULL
                    LOAD_FAST_LOAD_FAST     87 (to_address, subject)
                    LOAD_FAST                8 (body)
                    LOAD_CONST               9 (('to', 'subject', 'body'))
                    CALL_KW                  3
                    GET_AWAITABLE            0
                    LOAD_CONST              10 (None)
            L5:     SEND                     3 (to L8)
            L6:     YIELD_VALUE              1
            L7:     RESUME                   3
                    JUMP_BACKWARD_NO_INTERRUPT 5 (to L5)
            L8:     END_SEND
                    POP_TOP
    
     373            LOAD_GLOBAL              2 (logger)
                    LOAD_ATTR               11 (info + NULL|self)
                    LOAD_CONST              11 ('Urgent email sent to %s for call %s')
                    LOAD_FAST                5 (to_address)
                    LOAD_CONST              10 (None)
                    LOAD_CONST              12 (3)
                    BINARY_SLICE
                    LOAD_CONST              13 ('***')
                    BINARY_OP                0 (+)
                    LOAD_GLOBAL             13 (str + NULL)
                    LOAD_FAST                4 (call_id)
                    CALL                     1
                    LOAD_CONST              10 (None)
                    LOAD_CONST              14 (8)
                    BINARY_SLICE
                    CALL                     3
                    POP_TOP
    
     374    L9:     RETURN_CONST            15 (True)
    
     372   L10:     CLEANUP_THROW
           L11:     JUMP_BACKWARD_NO_INTERRUPT 46 (to L8)
    
      --   L12:     PUSH_EXC_INFO
    
     375            LOAD_GLOBAL             14 (Exception)
                    CHECK_EXC_MATCH
                    POP_JUMP_IF_FALSE       37 (to L14)
                    POP_TOP
    
     376            LOAD_GLOBAL              2 (logger)
                    LOAD_ATTR               17 (exception + NULL|self)
                    LOAD_CONST              16 ('Failed to send urgent email for call %s')
                    LOAD_GLOBAL             13 (str + NULL)
                    LOAD_FAST                4 (call_id)
                    CALL                     1
                    LOAD_CONST              10 (None)
                    LOAD_CONST              14 (8)
                    BINARY_SLICE
                    CALL                     2
                    POP_TOP
    
     377   L13:     POP_EXCEPT
                    RETURN_CONST             2 (False)
    
     375   L14:     RERAISE                  0
    
      --   L15:     COPY                     3
                    POP_EXCEPT
                    RERAISE                  1
           L16:     CALL_INTRINSIC_1         3 (INTRINSIC_STOPITERATION_ERROR)
                    RERAISE                  1
    ExceptionTable:
      L1 to L3 -> L16 [0] lasti
      L4 to L6 -> L12 [0]
      L6 to L7 -> L10 [2]
      L7 to L9 -> L12 [0]
      L9 to L10 -> L16 [0] lasti
      L10 to L11 -> L12 [0]
      L12 to L13 -> L15 [1] lasti
      L13 to L14 -> L16 [0] lasti
      L14 to L15 -> L15 [1] lasti
      L15 to L16 -> L16 [0] lasti
    
# --- Nested code object: send_urgent_call ---
    # DOCSTRING: """Place an outbound TwiML voice call to alert the user about an urgent call.

Note: this call consumes the user's call minutes allocation.
"""
    # co_names: ('_decrypt_personal_phone', 'logger', 'warning', 'xml.sax.saxutils', 'escape', 'app.services.telephony_service', '_get_twilio_client', 'calls', 'create', 'info', 'str', 'sid', 'Exception', 'exception')
    # co_varnames: ('settings_row', 'caller_info', 'summary_snippet', 'call_id', 'from_number', 'phone', 'xml_escape', '_get_twilio_client', 'safe_caller', 'safe_summary', 'twiml', 'client', 'call')
     380            RETURN_GENERATOR
                    POP_TOP
            L1:     RESUME                   0
    
     391            LOAD_GLOBAL              1 (_decrypt_personal_phone + NULL)
                    LOAD_FAST                0 (settings_row)
                    CALL                     1
                    STORE_FAST               5 (phone)
    
     392            LOAD_FAST                5 (phone)
                    TO_BOOL
                    POP_JUMP_IF_TRUE        22 (to L2)
    
     393            LOAD_GLOBAL              2 (logger)
                    LOAD_ATTR                5 (warning + NULL|self)
                    LOAD_CONST               1 ('Cannot send urgent call: no phone configured')
                    CALL                     1
                    POP_TOP
    
     394            RETURN_CONST             2 (False)
    
     395    L2:     LOAD_FAST                4 (from_number)
                    TO_BOOL
                    POP_JUMP_IF_TRUE        22 (to L3)
    
     396            LOAD_GLOBAL              2 (logger)
                    LOAD_ATTR                5 (warning + NULL|self)
                    LOAD_CONST               3 ('Cannot send urgent call: no from_number available')
                    CALL                     1
                    POP_TOP
    
     397            RETURN_CONST             2 (False)
    
     399    L3:     NOP
    
     400    L4:     LOAD_CONST               4 (0)
                    LOAD_CONST               5 (('escape',))
                    IMPORT_NAME              3 (xml.sax.saxutils)
                    IMPORT_FROM              4 (escape)
                    STORE_FAST               6 (xml_escape)
                    POP_TOP
    
     402            LOAD_CONST               4 (0)
                    LOAD_CONST               6 (('_get_twilio_client',))
                    IMPORT_NAME              5 (app.services.telephony_service)
                    IMPORT_FROM              6 (_get_twilio_client)
                    STORE_FAST               7 (_get_twilio_client)
                    POP_TOP
    
     404            LOAD_FAST                6 (xml_escape)
                    PUSH_NULL
                    LOAD_FAST                1 (caller_info)
                    LOAD_CONST               7 (None)
                    LOAD_CONST               8 (80)
                    BINARY_SLICE
                    CALL                     1
                    STORE_FAST               8 (safe_caller)
    
     405            LOAD_FAST                6 (xml_escape)
                    PUSH_NULL
                    LOAD_FAST                2 (summary_snippet)
                    LOAD_CONST               7 (None)
                    LOAD_CONST               9 (200)
                    BINARY_SLICE
                    CALL                     1
                    STORE_FAST               9 (safe_summary)
    
     407            LOAD_CONST              10 ('<?xml version="1.0" encoding="UTF-8"?><Response><Say voice="Polly.Joanna">You have an urgent call in Matt Bot from ')
    
     410            LOAD_FAST                8 (safe_caller)
                    FORMAT_SIMPLE
                    LOAD_CONST              11 ('. The caller said: ')
    
     411            LOAD_FAST                9 (safe_summary)
                    FORMAT_SIMPLE
                    LOAD_CONST              12 ('. Please check the app for full details.</Say><Pause length="1"/><Hangup/></Response>')
    
     407            BUILD_STRING             5
    
     406            STORE_FAST              10 (twiml)
    
     419            LOAD_FAST                7 (_get_twilio_client)
                    PUSH_NULL
                    CALL                     0
                    STORE_FAST              11 (client)
    
     420            LOAD_FAST               11 (client)
                    LOAD_ATTR               14 (calls)
                    LOAD_ATTR               17 (create + NULL|self)
    
     421            LOAD_FAST               10 (twiml)
    
     422            LOAD_FAST                4 (from_number)
    
     423            LOAD_FAST                5 (phone)
    
     420            LOAD_CONST              13 (('twiml', 'from_', 'to'))
                    CALL_KW                  3
                    STORE_FAST              12 (call)
    
     425            LOAD_GLOBAL              2 (logger)
                    LOAD_ATTR               19 (info + NULL|self)
    
     426            LOAD_CONST              14 ('Urgent alert call placed to ***%s for call %s (sid=%s)')
    
     427            LOAD_FAST                5 (phone)
                    LOAD_CONST              15 (-4)
                    LOAD_CONST               7 (None)
                    BINARY_SLICE
                    LOAD_GLOBAL             21 (str + NULL)
                    LOAD_FAST                3 (call_id)
                    CALL                     1
                    LOAD_CONST               7 (None)
                    LOAD_CONST              16 (8)
                    BINARY_SLICE
                    LOAD_FAST               12 (call)
                    LOAD_ATTR               22 (sid)
    
     425            CALL                     4
                    POP_TOP
    
     429    L5:     RETURN_CONST            17 (True)
    
      --    L6:     PUSH_EXC_INFO
    
     430            LOAD_GLOBAL             24 (Exception)
                    CHECK_EXC_MATCH
                    POP_JUMP_IF_FALSE       37 (to L8)
                    POP_TOP
    
     431            LOAD_GLOBAL              2 (logger)
                    LOAD_ATTR               27 (exception + NULL|self)
                    LOAD_CONST              18 ('Failed to place urgent alert call for call %s')
                    LOAD_GLOBAL             21 (str + NULL)
                    LOAD_FAST                3 (call_id)
                    CALL                     1
                    LOAD_CONST               7 (None)
                    LOAD_CONST              16 (8)
                    BINARY_SLICE
                    CALL                     2
                    POP_TOP
    
     432    L7:     POP_EXCEPT
                    RETURN_CONST             2 (False)
    
     430    L8:     RERAISE                  0
    
      --    L9:     COPY                     3
                    POP_EXCEPT
                    RERAISE                  1
           L10:     CALL_INTRINSIC_1         3 (INTRINSIC_STOPITERATION_ERROR)
                    RERAISE                  1
    ExceptionTable:
      L1 to L3 -> L10 [0] lasti
      L4 to L5 -> L6 [0]
      L5 to L6 -> L10 [0] lasti
      L6 to L7 -> L9 [1] lasti
      L7 to L8 -> L10 [0] lasti
      L8 to L9 -> L9 [1] lasti
      L9 to L10 -> L10 [0] lasti
    
# --- Nested code object: dispatch_urgent_notifications ---
    # DOCSTRING: """Check user preferences and dispatch enabled urgent notification channels.

Returns a dict of {channel: success} for each enabled channel.
"""
    # co_names: ('urgent_notify_sms', 'urgent_notify_call', 'app.models.user_number', 'UserNumber', 'execute', 'select', 'where', 'owner_user_id', 'status', 'limit', 'scalar_one_or_none', 'e164', 'send_urgent_sms', 'urgent_notify_email', 'send_urgent_email', 'send_urgent_call', 'app.services', 'audit_service', 'log_event', 'str')
    # co_varnames: ('db', 'settings_row', 'user_email', 'caller_info', 'summary_snippet', 'call_id', 'results', 'from_number', 'UserNumber', 'num_row', 'audit_service')
     435            RETURN_GENERATOR
                    POP_TOP
            L1:     RESUME                   0
    
     448            BUILD_MAP                0
                    STORE_FAST               6 (results)
    
     450            LOAD_CONST               1 (None)
                    STORE_FAST               7 (from_number)
    
     451            LOAD_FAST                1 (settings_row)
                    LOAD_ATTR                0 (urgent_notify_sms)
                    TO_BOOL
                    POP_JUMP_IF_TRUE        17 (to L2)
                    LOAD_FAST                1 (settings_row)
                    LOAD_ATTR                2 (urgent_notify_call)
                    TO_BOOL
                    POP_JUMP_IF_FALSE      140 (to L7)
    
     452    L2:     LOAD_CONST               2 (0)
                    LOAD_CONST               3 (('UserNumber',))
                    IMPORT_NAME              2 (app.models.user_number)
                    IMPORT_FROM              3 (UserNumber)
                    STORE_FAST               8 (UserNumber)
                    POP_TOP
    
     454            LOAD_FAST                0 (db)
                    LOAD_ATTR                9 (execute + NULL|self)
    
     455            LOAD_GLOBAL             11 (select + NULL)
                    LOAD_FAST                8 (UserNumber)
                    CALL                     1
                    LOAD_ATTR               13 (where + NULL|self)
    
     456            LOAD_FAST                8 (UserNumber)
                    LOAD_ATTR               14 (owner_user_id)
                    LOAD_FAST                1 (settings_row)
                    LOAD_ATTR               14 (owner_user_id)
                    COMPARE_OP              72 (==)
    
     457            LOAD_FAST                8 (UserNumber)
                    LOAD_ATTR               16 (status)
                    LOAD_CONST               4 ('active')
                    COMPARE_OP              72 (==)
    
     455            CALL                     2
    
     458            LOAD_ATTR               19 (limit + NULL|self)
                    LOAD_CONST               5 (1)
                    CALL                     1
    
     454            CALL                     1
                    GET_AWAITABLE            0
                    LOAD_CONST               1 (None)
            L3:     SEND                     3 (to L6)
            L4:     YIELD_VALUE              1
            L5:     RESUME                   3
                    JUMP_BACKWARD_NO_INTERRUPT 5 (to L3)
            L6:     END_SEND
    
     460            LOAD_ATTR               21 (scalar_one_or_none + NULL|self)
                    CALL                     0
    
     453            STORE_FAST               9 (num_row)
    
     461            LOAD_FAST                9 (num_row)
                    TO_BOOL
                    POP_JUMP_IF_FALSE       12 (to L7)
    
     462            LOAD_FAST                9 (num_row)
                    LOAD_ATTR               22 (e164)
                    STORE_FAST               7 (from_number)
    
     464    L7:     LOAD_FAST                1 (settings_row)
                    LOAD_ATTR                0 (urgent_notify_sms)
                    TO_BOOL
                    POP_JUMP_IF_FALSE       24 (to L12)
    
     465            LOAD_GLOBAL             25 (send_urgent_sms + NULL)
    
     466            LOAD_FAST_LOAD_FAST     19 (settings_row, caller_info)
                    LOAD_FAST_LOAD_FAST     69 (summary_snippet, call_id)
                    LOAD_FAST                7 (from_number)
    
     465            CALL                     5
                    GET_AWAITABLE            0
                    LOAD_CONST               1 (None)
            L8:     SEND                     3 (to L11)
            L9:     YIELD_VALUE              1
           L10:     RESUME                   3
                    JUMP_BACKWARD_NO_INTERRUPT 5 (to L8)
           L11:     END_SEND
                    LOAD_FAST                6 (results)
                    LOAD_CONST               6 ('sms')
                    STORE_SUBSCR
    
     469   L12:     LOAD_FAST                1 (settings_row)
                    LOAD_ATTR               26 (urgent_notify_email)
                    TO_BOOL
                    POP_JUMP_IF_FALSE       24 (to L17)
    
     470            LOAD_GLOBAL             29 (send_urgent_email + NULL)
    
     471            LOAD_FAST_LOAD_FAST     18 (settings_row, user_email)
                    LOAD_FAST_LOAD_FAST     52 (caller_info, summary_snippet)
                    LOAD_FAST                5 (call_id)
    
     470            CALL                     5
                    GET_AWAITABLE            0
                    LOAD_CONST               1 (None)
           L13:     SEND                     3 (to L16)
           L14:     YIELD_VALUE              1
           L15:     RESUME                   3
                    JUMP_BACKWARD_NO_INTERRUPT 5 (to L13)
           L16:     END_SEND
                    LOAD_FAST                6 (results)
                    LOAD_CONST               7 ('email')
                    STORE_SUBSCR
    
     474   L17:     LOAD_FAST                1 (settings_row)
                    LOAD_ATTR                2 (urgent_notify_call)
                    TO_BOOL
                    POP_JUMP_IF_FALSE       24 (to L22)
    
     475            LOAD_GLOBAL             31 (send_urgent_call + NULL)
    
     476            LOAD_FAST_LOAD_FAST     19 (settings_row, caller_info)
                    LOAD_FAST_LOAD_FAST     69 (summary_snippet, call_id)
                    LOAD_FAST                7 (from_number)
    
     475            CALL                     5
                    GET_AWAITABLE            0
                    LOAD_CONST               1 (None)
           L18:     SEND                     3 (to L21)
           L19:     YIELD_VALUE              1
           L20:     RESUME                   3
                    JUMP_BACKWARD_NO_INTERRUPT 5 (to L18)
           L21:     END_SEND
                    LOAD_FAST                6 (results)
                    LOAD_CONST               8 ('call')
                    STORE_SUBSCR
    
     479   L22:     LOAD_FAST                6 (results)
                    TO_BOOL
                    POP_JUMP_IF_FALSE       54 (to L27)
    
     480            LOAD_CONST               2 (0)
                    LOAD_CONST               9 (('audit_service',))
                    IMPORT_NAME             16 (app.services)
                    IMPORT_FROM             17 (audit_service)
                    STORE_FAST              10 (audit_service)
                    POP_TOP
    
     481            LOAD_FAST               10 (audit_service)
                    LOAD_ATTR               37 (log_event + NULL|self)
    
     482            LOAD_FAST                0 (db)
    
     483            LOAD_FAST                1 (settings_row)
                    LOAD_ATTR               14 (owner_user_id)
    
     484            LOAD_CONST              10 ('urgent_notification.dispatched')
    
     486            LOAD_GLOBAL             39 (str + NULL)
                    LOAD_FAST                5 (call_id)
                    CALL                     1
    
     487            LOAD_FAST                6 (results)
    
     485            LOAD_CONST              11 (('call_id', 'channels'))
                    BUILD_CONST_KEY_MAP      2
    
     481            LOAD_CONST              12 (('owner_user_id', 'event_type', 'details'))
                    CALL_KW                  4
                    GET_AWAITABLE            0
                    LOAD_CONST               1 (None)
           L23:     SEND                     3 (to L26)
           L24:     YIELD_VALUE              1
           L25:     RESUME                   3
                    JUMP_BACKWARD_NO_INTERRUPT 5 (to L23)
           L26:     END_SEND
                    POP_TOP
    
     491   L27:     LOAD_FAST                6 (results)
                    RETURN_VALUE
    
     454   L28:     CLEANUP_THROW
           L29:     JUMP_BACKWARD_NO_INTERRUPT 223 (to L6)
    
     465   L30:     CLEANUP_THROW
           L31:     JUMP_BACKWARD_NO_INTERRUPT 154 (to L11)
    
     470   L32:     CLEANUP_THROW
           L33:     JUMP_BACKWARD_NO_INTERRUPT 115 (to L16)
    
     475   L34:     CLEANUP_THROW
           L35:     JUMP_BACKWARD_NO_INTERRUPT 76 (to L21)
    
     481   L36:     CLEANUP_THROW
           L37:     JUMP_BACKWARD_NO_INTERRUPT 14 (to L26)
    
      --   L38:     CALL_INTRINSIC_1         3 (INTRINSIC_STOPITERATION_ERROR)
                    RERAISE                  1
    ExceptionTable:
      L1 to L4 -> L38 [0] lasti
      L4 to L5 -> L28 [2]
      L5 to L9 -> L38 [0] lasti
      L9 to L10 -> L30 [2]
      L10 to L14 -> L38 [0] lasti
      L14 to L15 -> L32 [2]
      L15 to L19 -> L38 [0] lasti
      L19 to L20 -> L34 [2]
      L20 to L24 -> L38 [0] lasti
      L24 to L25 -> L36 [2]
      L25 to L29 -> L38 [0] lasti
      L30 to L31 -> L38 [0] lasti
      L32 to L33 -> L38 [0] lasti
      L34 to L35 -> L38 [0] lasti
      L36 to L37 -> L38 [0] lasti
    
# co_names: ('__doc__', '__future__', 'annotations', 'logging', 'uuid', 'datetime', 'UTC', 'time', 'sqlalchemy', 'select', 'sqlalchemy.ext.asyncio', 'AsyncSession', 'app.core.encryption', 'decrypt_field', 'app.models.device', 'Device', 'app.models.notification', 'Notification', 'app.models.notification_delivery', 'NotificationDelivery', 'app.models.push_token', 'PushToken', 'app.models.user_settings', 'UserSettings', 'app.services.event_emitter', 'emit_event', 'getLogger', '__name__', 'logger', 'build_push_payload', '_build_preview_body', '_time_in_range', 'is_quiet_hours', 'should_allow_call', 'notify_call_screened', 'create_and_enqueue_notification', '_decrypt_personal_phone', 'send_urgent_sms', 'send_urgent_email', 'send_urgent_call', 'dispatch_urgent_notifications')
# co_varnames: ()
  0           RESUME                   0

  1           LOAD_CONST               0 ('Privacy-safe push notification payload builder and quiet hours check.')
              STORE_NAME               0 (__doc__)

  3           LOAD_CONST               1 (0)
              LOAD_CONST               2 (('annotations',))
              IMPORT_NAME              1 (__future__)
              IMPORT_FROM              2 (annotations)
              STORE_NAME               2 (annotations)
              POP_TOP

  5           LOAD_CONST               1 (0)
              LOAD_CONST               3 (None)
              IMPORT_NAME              3 (logging)
              STORE_NAME               3 (logging)

  6           LOAD_CONST               1 (0)
              LOAD_CONST               3 (None)
              IMPORT_NAME              4 (uuid)
              STORE_NAME               4 (uuid)

  7           LOAD_CONST               1 (0)
              LOAD_CONST               4 (('UTC', 'datetime', 'time'))
              IMPORT_NAME              5 (datetime)
              IMPORT_FROM              6 (UTC)
              STORE_NAME               6 (UTC)
              IMPORT_FROM              5 (datetime)
              STORE_NAME               5 (datetime)
              IMPORT_FROM              7 (time)
              STORE_NAME               7 (time)
              POP_TOP

  9           LOAD_CONST               1 (0)
              LOAD_CONST               5 (('select',))
              IMPORT_NAME              8 (sqlalchemy)
              IMPORT_FROM              9 (select)
              STORE_NAME               9 (select)
              POP_TOP

 10           LOAD_CONST               1 (0)
              LOAD_CONST               6 (('AsyncSession',))
              IMPORT_NAME             10 (sqlalchemy.ext.asyncio)
              IMPORT_FROM             11 (AsyncSession)
              STORE_NAME              11 (AsyncSession)
              POP_TOP

 12           LOAD_CONST               1 (0)
              LOAD_CONST               7 (('decrypt_field',))
              IMPORT_NAME             12 (app.core.encryption)
              IMPORT_FROM             13 (decrypt_field)
              STORE_NAME              13 (decrypt_field)
              POP_TOP

 13           LOAD_CONST               1 (0)
              LOAD_CONST               8 (('Device',))
              IMPORT_NAME             14 (app.models.device)
              IMPORT_FROM             15 (Device)
              STORE_NAME              15 (Device)
              POP_TOP

 14           LOAD_CONST               1 (0)
              LOAD_CONST               9 (('Notification',))
              IMPORT_NAME             16 (app.models.notification)
              IMPORT_FROM             17 (Notification)
              STORE_NAME              17 (Notification)
              POP_TOP

 15           LOAD_CONST               1 (0)
              LOAD_CONST              10 (('NotificationDelivery',))
              IMPORT_NAME             18 (app.models.notification_delivery)
              IMPORT_FROM             19 (NotificationDelivery)
              STORE_NAME              19 (NotificationDelivery)
              POP_TOP

 16           LOAD_CONST               1 (0)
              LOAD_CONST              11 (('PushToken',))
              IMPORT_NAME             20 (app.models.push_token)
              IMPORT_FROM             21 (PushToken)
              STORE_NAME              21 (PushToken)
              POP_TOP

 17           LOAD_CONST               1 (0)
              LOAD_CONST              12 (('UserSettings',))
              IMPORT_NAME             22 (app.models.user_settings)
              IMPORT_FROM             23 (UserSettings)
              STORE_NAME              23 (UserSettings)
              POP_TOP

 18           LOAD_CONST               1 (0)
              LOAD_CONST              13 (('emit_event',))
              IMPORT_NAME             24 (app.services.event_emitter)
              IMPORT_FROM             25 (emit_event)
              STORE_NAME              25 (emit_event)
              POP_TOP

 20           LOAD_NAME                3 (logging)
              LOAD_ATTR               52 (getLogger)
              PUSH_NULL
              LOAD_NAME               27 (__name__)
              CALL                     1
              STORE_NAME              28 (logger)

 26           NOP

 23           LOAD_CONST              29 (('private',))

 24           NOP

 23           NOP

 25           NOP

 23           NOP

 26           NOP

 23           NOP

 27           NOP

 23           LOAD_CONST              30 (('notification_type', 'str', 'data', 'dict[str, str]', 'privacy_mode', 'str', 'return', 'dict[str, object]'))
              LOAD_CONST              14 (<code object build_push_payload at 0x0000024C0EEBE420, file "D:\fluence\Github\mattbot\backend\app\services\notification_service.py", line 23>)
              MAKE_FUNCTION
              SET_FUNCTION_ATTRIBUTE   4 (annotations)
              SET_FUNCTION_ATTRIBUTE   1 (defaults)
              STORE_NAME              29 (build_push_payload)

 54           LOAD_CONST              31 (('notification_type', 'str', 'data', 'dict', 'return', 'str'))
              LOAD_CONST              15 (<code object _build_preview_body at 0x0000024C11423D30, file "D:\fluence\Github\mattbot\backend\app\services\notification_service.py", line 54>)
              MAKE_FUNCTION
              SET_FUNCTION_ATTRIBUTE   4 (annotations)
              STORE_NAME              30 (_build_preview_body)

 65           NOP

 66           NOP

 65           NOP

 66           NOP

 65           NOP

 66           NOP

 65           NOP

 67           NOP

 65           LOAD_CONST              32 (('start', 'time', 'end', 'time', 'current_time', 'time', 'return', 'bool'))
              LOAD_CONST              16 (<code object _time_in_range at 0x0000024C0EEE3DE0, file "D:\fluence\Github\mattbot\backend\app\services\notification_service.py", line 65>)
              MAKE_FUNCTION
              SET_FUNCTION_ATTRIBUTE   4 (annotations)
              STORE_NAME              31 (_time_in_range)

 74           LOAD_CONST              33 ((None,))
              LOAD_CONST              34 (('settings', 'UserSettings', 'now', 'datetime | None', 'return', 'bool'))
              LOAD_CONST              17 (<code object is_quiet_hours at 0x0000024C0FB699D0, file "D:\fluence\Github\mattbot\backend\app\services\notification_service.py", line 74>)
              MAKE_FUNCTION
              SET_FUNCTION_ATTRIBUTE   4 (annotations)
              SET_FUNCTION_ATTRIBUTE   1 (defaults)
              STORE_NAME              32 (is_quiet_hours)

115           LOAD_CONST              35 ((False,))
              LOAD_CONST              36 (('settings', 'UserSettings', 'caller_is_vip', 'bool', 'return', 'bool'))
              LOAD_CONST              18 (<code object should_allow_call at 0x0000024C11495A10, file "D:\fluence\Github\mattbot\backend\app\services\notification_service.py", line 115>)
              MAKE_FUNCTION
              SET_FUNCTION_ATTRIBUTE   4 (annotations)
              SET_FUNCTION_ATTRIBUTE   1 (defaults)
              STORE_NAME              33 (should_allow_call)

127           LOAD_CONST               3 (None)

122           LOAD_CONST              19 (('labels',))
              BUILD_CONST_KEY_MAP      1

123           NOP

122           NOP

125           NOP

122           NOP

126           NOP

122           NOP

127           NOP

122           NOP

128           NOP

122           LOAD_CONST              37 (('db', 'AsyncSession', 'call_id', 'uuid.UUID', 'user_id', 'uuid.UUID', 'labels', 'list[dict] | None', 'return', 'None'))
              LOAD_CONST              20 (<code object notify_call_screened at 0x0000024C0FBAFF90, file "D:\fluence\Github\mattbot\backend\app\services\notification_service.py", line 122>)
              MAKE_FUNCTION
              SET_FUNCTION_ATTRIBUTE   4 (annotations)
              SET_FUNCTION_ATTRIBUTE   2 (kwdefaults)
              STORE_NAME              34 (notify_call_screened)

225           LOAD_CONST              21 ('normal')

226           LOAD_CONST               3 (None)

227           LOAD_CONST               3 (None)

220           LOAD_CONST              22 (('priority', 'source_entity_type', 'source_entity_id'))
              BUILD_CONST_KEY_MAP      3

221           NOP

220           NOP

223           NOP

220           NOP

224           NOP

220           NOP

225           NOP

220           NOP

226           NOP

220           NOP

227           NOP

220           NOP

228           NOP

220           LOAD_CONST              38 (('db', 'AsyncSession', 'owner_user_id', 'uuid.UUID', 'notification_type', 'str', 'priority', 'str', 'source_entity_type', 'str | None', 'source_entity_id', 'uuid.UUID | None', 'return', 'Notification'))
              LOAD_CONST              23 (<code object create_and_enqueue_notification at 0x0000024C0FB5C0D0, file "D:\fluence\Github\mattbot\backend\app\services\notification_service.py", line 220>)
              MAKE_FUNCTION
              SET_FUNCTION_ATTRIBUTE   4 (annotations)
              SET_FUNCTION_ATTRIBUTE   2 (kwdefaults)
              STORE_NAME              35 (create_and_enqueue_notification)

288           LOAD_CONST              39 (('settings_row', 'UserSettings', 'return', 'str | None'))
              LOAD_CONST              24 (<code object _decrypt_personal_phone at 0x0000024C0FC755D0, file "D:\fluence\Github\mattbot\backend\app\services\notification_service.py", line 288>)
              MAKE_FUNCTION
              SET_FUNCTION_ATTRIBUTE   4 (annotations)
              STORE_NAME              36 (_decrypt_personal_phone)

318           NOP

313           LOAD_CONST              33 ((None,))

314           NOP

313           NOP

315           NOP

313           NOP

316           NOP

313           NOP

317           NOP

313           NOP

318           NOP

313           NOP

319           NOP

313           LOAD_CONST              40 (('settings_row', 'UserSettings', 'caller_info', 'str', 'summary_snippet', 'str', 'call_id', 'uuid.UUID', 'from_number', 'str | None', 'return', 'bool'))
              LOAD_CONST              25 (<code object send_urgent_sms at 0x0000024C0FB246D0, file "D:\fluence\Github\mattbot\backend\app\services\notification_service.py", line 313>)
              MAKE_FUNCTION
              SET_FUNCTION_ATTRIBUTE   4 (annotations)
              SET_FUNCTION_ATTRIBUTE   1 (defaults)
              STORE_NAME              37 (send_urgent_sms)

349           NOP

350           NOP

349           NOP

351           NOP

349           NOP

352           NOP

349           NOP

353           NOP

349           NOP

354           NOP

349           NOP

355           NOP

349           LOAD_CONST              41 (('settings_row', 'UserSettings', 'user_email', 'str', 'caller_info', 'str', 'summary_snippet', 'str', 'call_id', 'uuid.UUID', 'return', 'bool'))
              LOAD_CONST              26 (<code object send_urgent_email at 0x0000024C0FBC8B10, file "D:\fluence\Github\mattbot\backend\app\services\notification_service.py", line 349>)
              MAKE_FUNCTION
              SET_FUNCTION_ATTRIBUTE   4 (annotations)
              STORE_NAME              38 (send_urgent_email)

385           NOP

380           LOAD_CONST              33 ((None,))

381           NOP

380           NOP

382           NOP

380           NOP

383           NOP

380           NOP

384           NOP

380           NOP

385           NOP

380           NOP

386           NOP

380           LOAD_CONST              40 (('settings_row', 'UserSettings', 'caller_info', 'str', 'summary_snippet', 'str', 'call_id', 'uuid.UUID', 'from_number', 'str | None', 'return', 'bool'))
              LOAD_CONST              27 (<code object send_urgent_call at 0x0000024C0FBAABD0, file "D:\fluence\Github\mattbot\backend\app\services\notification_service.py", line 380>)
              MAKE_FUNCTION
              SET_FUNCTION_ATTRIBUTE   4 (annotations)
              SET_FUNCTION_ATTRIBUTE   1 (defaults)
              STORE_NAME              39 (send_urgent_call)

435           NOP

436           NOP

435           NOP

438           NOP

435           NOP

439           NOP

435           NOP

440           NOP

435           NOP

441           NOP

435           NOP

442           NOP

435           NOP

443           NOP

435           LOAD_CONST              42 (('db', 'AsyncSession', 'settings_row', 'UserSettings', 'user_email', 'str', 'caller_info', 'str', 'summary_snippet', 'str', 'call_id', 'uuid.UUID', 'return', 'dict[str, bool]'))
              LOAD_CONST              28 (<code object dispatch_urgent_notifications at 0x0000024C0FEDE6D0, file "D:\fluence\Github\mattbot\backend\app\services\notification_service.py", line 435>)
              MAKE_FUNCTION
              SET_FUNCTION_ATTRIBUTE   4 (annotations)
              STORE_NAME              40 (dispatch_urgent_notifications)
              RETURN_CONST             3 (None)

Disassembly of <code object build_push_payload at 0x0000024C0EEBE420, file "D:\fluence\Github\mattbot\backend\app\services\notification_service.py", line 23>:
 23           RESUME                   0

 32           BUILD_MAP                0
              STORE_FAST               3 (payload_data)

 34           LOAD_CONST               1 ('MattBot')

 35           LOAD_FAST                3 (payload_data)

 33           LOAD_CONST               2 (('title', 'data'))
              BUILD_CONST_KEY_MAP      2
              STORE_FAST               4 (base)

 38           BUILD_SET                0
              LOAD_CONST               3 (frozenset({'event_type', 'call_id', 'timestamp'}))
              SET_UPDATE               1
              STORE_FAST               5 (safe_data_keys)

 39           LOAD_FAST                1 (data)
              LOAD_ATTR                1 (items + NULL|self)
              CALL                     0
              GET_ITER
      L1:     FOR_ITER                16 (to L3)
              UNPACK_SEQUENCE          2
              STORE_FAST_STORE_FAST  103 (k, v)

 40           LOAD_FAST_LOAD_FAST    101 (k, safe_data_keys)
              CONTAINS_OP              0
              POP_JUMP_IF_TRUE         2 (to L2)
              JUMP_BACKWARD           12 (to L1)

 41   L2:     LOAD_FAST_LOAD_FAST    115 (v, payload_data)
              LOAD_FAST                6 (k)
              STORE_SUBSCR
              JUMP_BACKWARD           18 (to L1)

 39   L3:     END_FOR
              POP_TOP

 43           LOAD_CONST               4 ('call_id')
              LOAD_FAST                1 (data)
              CONTAINS_OP              0
              POP_JUMP_IF_FALSE       11 (to L4)

 44           LOAD_CONST               5 ('mattbot://call/')
              LOAD_FAST                1 (data)
              LOAD_CONST               4 ('call_id')
              BINARY_SUBSCR
              FORMAT_SIMPLE
              BUILD_STRING             2
              LOAD_FAST                3 (payload_data)
              LOAD_CONST               6 ('deep_link')
              STORE_SUBSCR

 46   L4:     LOAD_FAST                2 (privacy_mode)
              LOAD_CONST               7 ('preview')
              COMPARE_OP              88 (bool(==))
              POP_JUMP_IF_FALSE       16 (to L5)

 47           LOAD_GLOBAL              3 (_build_preview_body + NULL)
              LOAD_FAST_LOAD_FAST      1 (notification_type, data)
              CALL                     2
              LOAD_FAST                4 (base)
              LOAD_CONST               8 ('body')
              STORE_SUBSCR

 51           LOAD_FAST                4 (base)
              RETURN_VALUE

 49   L5:     LOAD_CONST               9 ('New activity')
              LOAD_FAST                4 (base)
              LOAD_CONST               8 ('body')
              STORE_SUBSCR

 51           LOAD_FAST                4 (base)
              RETURN_VALUE

Disassembly of <code object _build_preview_body at 0x0000024C11423D30, file "D:\fluence\Github\mattbot\backend\app\services\notification_service.py", line 54>:
 54           RESUME                   0

 56           LOAD_CONST               1 ('Incoming call')

 57           LOAD_CONST               2 ('Missed call')

 58           LOAD_CONST               3 ('New voicemail received')

 59           LOAD_CONST               4 ('Call summary ready')

 60           LOAD_CONST               5 ('Call was screened')

 55           LOAD_CONST               6 (('incoming_call', 'missed_call', 'voicemail', 'call_summary', 'call_screened'))
              BUILD_CONST_KEY_MAP      5
              STORE_FAST               2 (previews)

 62           LOAD_FAST                2 (previews)
              LOAD_ATTR                1 (get + NULL|self)
              LOAD_FAST                0 (notification_type)
              LOAD_CONST               7 ('New activity')
              CALL                     2
              RETURN_VALUE

Disassembly of <code object _time_in_range at 0x0000024C0EEE3DE0, file "D:\fluence\Github\mattbot\backend\app\services\notification_service.py", line 65>:
 65           RESUME                   0

 69           LOAD_FAST_LOAD_FAST      1 (start, end)
              COMPARE_OP              58 (bool(<=))
              POP_JUMP_IF_FALSE       33 (to L2)

 70           LOAD_GLOBAL              1 (bool + NULL)
              LOAD_FAST_LOAD_FAST      2 (start, current_time)
              SWAP                     2
              COPY                     2
              COMPARE_OP              42 (<=)
              COPY                     1
              TO_BOOL
              POP_JUMP_IF_FALSE        9 (to L1)
              POP_TOP
              LOAD_FAST                1 (end)
              COMPARE_OP              42 (<=)
              CALL                     1
              RETURN_VALUE
      L1:     SWAP                     2
              POP_TOP
              CALL                     1
              RETURN_VALUE

 71   L2:     LOAD_GLOBAL              1 (bool + NULL)
              LOAD_FAST_LOAD_FAST     32 (current_time, start)
              COMPARE_OP             172 (>=)
              COPY                     1
              TO_BOOL
              POP_JUMP_IF_TRUE         4 (to L3)
              POP_TOP
              LOAD_FAST_LOAD_FAST     33 (current_time, end)
              COMPARE_OP              42 (<=)
      L3:     CALL                     1
              RETURN_VALUE

Disassembly of <code object is_quiet_hours at 0x0000024C0FB699D0, file "D:\fluence\Github\mattbot\backend\app\services\notification_service.py", line 74>:
  74            RESUME                   0

  76            LOAD_FAST                0 (settings)
                LOAD_ATTR                0 (quiet_hours_enabled)
                TO_BOOL
                POP_JUMP_IF_TRUE         1 (to L1)

  77            RETURN_CONST             1 (False)

  79    L1:     LOAD_FAST                1 (now)
                POP_JUMP_IF_NOT_NONE    26 (to L2)

  80            LOAD_GLOBAL              2 (datetime)
                LOAD_ATTR                4 (now)
                PUSH_NULL
                LOAD_GLOBAL              6 (UTC)
                CALL                     1
                STORE_FAST               1 (now)

  82    L2:     LOAD_FAST                1 (now)
                LOAD_ATTR                9 (weekday + NULL|self)
                CALL                     0
                STORE_FAST               2 (current_day)

  83            LOAD_FAST                2 (current_day)
                LOAD_CONST               2 (1)
                BINARY_OP                0 (+)
                LOAD_CONST               3 (7)
                BINARY_OP                6 (%)
                STORE_FAST               3 (iso_to_js_day)

  84            LOAD_FAST                1 (now)
                LOAD_ATTR               11 (time + NULL|self)
                CALL                     0
                STORE_FAST               4 (current_time)

  86            LOAD_FAST                0 (settings)
                LOAD_ATTR               12 (quiet_hours_intervals)
                COPY                     1
                TO_BOOL
                POP_JUMP_IF_TRUE         2 (to L3)
                POP_TOP
                BUILD_LIST               0
        L3:     STORE_FAST               5 (intervals)

  87            LOAD_FAST                5 (intervals)
                TO_BOOL
                POP_JUMP_IF_FALSE      176 (to L10)

  88            LOAD_FAST                5 (intervals)
                GET_ITER
        L4:     FOR_ITER               169 (to L9)
                STORE_FAST               6 (iv)

  89            LOAD_FAST                6 (iv)
                LOAD_ATTR               15 (get + NULL|self)
                LOAD_CONST               4 ('days')
                BUILD_LIST               0
                LOAD_CONST               5 ((0, 1, 2, 3, 4, 5, 6))
                LIST_EXTEND              1
                CALL                     2
                STORE_FAST               7 (iv_days)

  90            LOAD_FAST                7 (iv_days)
                TO_BOOL
                POP_JUMP_IF_FALSE        7 (to L5)
                LOAD_FAST_LOAD_FAST     55 (iso_to_js_day, iv_days)
                CONTAINS_OP              1
                POP_JUMP_IF_FALSE        2 (to L5)

  91            JUMP_BACKWARD           37 (to L4)

  92    L5:     NOP

  93    L6:     LOAD_FAST                6 (iv)
                LOAD_CONST               6 ('start')
                BINARY_SUBSCR
                LOAD_ATTR               17 (split + NULL|self)
                LOAD_CONST               7 (':')
                CALL                     1
                STORE_FAST               8 (parts_s)

  94            LOAD_FAST                6 (iv)
                LOAD_CONST               8 ('end')
                BINARY_SUBSCR
                LOAD_ATTR               17 (split + NULL|self)
                LOAD_CONST               7 (':')
                CALL                     1
                STORE_FAST               9 (parts_e)

  95            LOAD_CONST               9 (0)
                LOAD_CONST              10 (('time',))
                IMPORT_NAME              1 (datetime)
                IMPORT_FROM              5 (time)
                STORE_FAST              10 (dt_time)
                POP_TOP

  96            LOAD_FAST               10 (dt_time)
                PUSH_NULL
                LOAD_GLOBAL             19 (int + NULL)
                LOAD_FAST                8 (parts_s)
                LOAD_CONST               9 (0)
                BINARY_SUBSCR
                CALL                     1
                LOAD_GLOBAL             19 (int + NULL)
                LOAD_FAST                8 (parts_s)
                LOAD_CONST               2 (1)
                BINARY_SUBSCR
                CALL                     1
                CALL                     2
                STORE_FAST              11 (start)

  97            LOAD_FAST               10 (dt_time)
                PUSH_NULL
                LOAD_GLOBAL             19 (int + NULL)
                LOAD_FAST                9 (parts_e)
                LOAD_CONST               9 (0)
                BINARY_SUBSCR
                CALL                     1
                LOAD_GLOBAL             19 (int + NULL)
                LOAD_FAST                9 (parts_e)
                LOAD_CONST               2 (1)
                BINARY_SUBSCR
                CALL                     1
                CALL                     2
                STORE_FAST              12 (end)

  98            LOAD_GLOBAL             21 (_time_in_range + NULL)
                LOAD_FAST_LOAD_FAST    188 (start, end)
                LOAD_FAST                4 (current_time)
                CALL                     3
                TO_BOOL
                POP_JUMP_IF_FALSE        2 (to L8)

  99    L7:     POP_TOP
                RETURN_CONST            11 (True)

  98    L8:     JUMP_BACKWARD          171 (to L4)

  88    L9:     END_FOR
                POP_TOP

 102            RETURN_CONST             1 (False)

 105   L10:     LOAD_FAST                0 (settings)
                LOAD_ATTR               28 (quiet_hours_start)
                POP_JUMP_IF_NONE        13 (to L11)
                LOAD_FAST                0 (settings)
                LOAD_ATTR               30 (quiet_hours_end)
                POP_JUMP_IF_NOT_NONE     1 (to L12)

 106   L11:     RETURN_CONST             1 (False)

 108   L12:     LOAD_FAST                0 (settings)
                LOAD_ATTR               32 (quiet_hours_days)
                COPY                     1
                TO_BOOL
                POP_JUMP_IF_TRUE         2 (to L13)
                POP_TOP
                BUILD_LIST               0
       L13:     STORE_FAST              13 (days)

 109            LOAD_FAST               13 (days)
                TO_BOOL
                POP_JUMP_IF_FALSE        6 (to L14)
                LOAD_FAST_LOAD_FAST     61 (iso_to_js_day, days)
                CONTAINS_OP              1
                POP_JUMP_IF_FALSE        1 (to L14)

 110            RETURN_CONST             1 (False)

 112   L14:     LOAD_GLOBAL             21 (_time_in_range + NULL)
                LOAD_FAST                0 (settings)
                LOAD_ATTR               28 (quiet_hours_start)
                LOAD_FAST                0 (settings)
                LOAD_ATTR               30 (quiet_hours_end)
                LOAD_FAST                4 (current_time)
                CALL                     3
                RETURN_VALUE

  --   L15:     PUSH_EXC_INFO

 100            LOAD_GLOBAL             22 (KeyError)
                LOAD_GLOBAL             24 (ValueError)
                LOAD_GLOBAL             26 (IndexError)
                BUILD_TUPLE              3
                CHECK_EXC_MATCH
                POP_JUMP_IF_FALSE        5 (to L17)
                POP_TOP

 101   L16:     POP_EXCEPT
                EXTENDED_ARG             1
                JUMP_BACKWARD          293 (to L4)

 100   L17:     RERAISE                  0

  --   L18:     COPY                     3
                POP_EXCEPT
                RERAISE                  1
ExceptionTable:
  L6 to L7 -> L15 [1]
  L15 to L16 -> L18 [2] lasti
  L17 to L18 -> L18 [2] lasti

Disassembly of <code object should_allow_call at 0x0000024C11495A10, file "D:\fluence\Github\mattbot\backend\app\services\notification_service.py", line 115>:
115           RESUME                   0

117           LOAD_GLOBAL              1 (is_quiet_hours + NULL)
              LOAD_FAST                0 (settings)
              CALL                     1
              TO_BOOL
              POP_JUMP_IF_TRUE         1 (to L1)

118           RETURN_CONST             1 (True)

119   L1:     LOAD_FAST                1 (caller_is_vip)
              COPY                     1
              TO_BOOL
              POP_JUMP_IF_FALSE       12 (to L2)
              POP_TOP
              LOAD_FAST                0 (settings)
              LOAD_ATTR                2 (quiet_hours_allow_vip)
      L2:     RETURN_VALUE

Disassembly of <code object notify_call_screened at 0x0000024C0FBAFF90, file "D:\fluence\Github\mattbot\backend\app\services\notification_service.py", line 122>:
  --            MAKE_CELL               13 (important_labels)

 122            RETURN_GENERATOR
                POP_TOP
        L1:     RESUME                   0

 134            LOAD_FAST                0 (db)
                LOAD_ATTR                1 (execute + NULL|self)

 135            LOAD_GLOBAL              3 (select + NULL)
                LOAD_GLOBAL              4 (UserSettings)
                CALL                     1
                LOAD_ATTR                7 (where + NULL|self)
                LOAD_GLOBAL              4 (UserSettings)
                LOAD_ATTR                8 (owner_user_id)
                LOAD_FAST                2 (user_id)
                COMPARE_OP              72 (==)
                CALL                     1

 134            CALL                     1
                GET_AWAITABLE            0
                LOAD_CONST               1 (None)
        L2:     SEND                     3 (to L5)
        L3:     YIELD_VALUE              1
        L4:     RESUME                   3
                JUMP_BACKWARD_NO_INTERRUPT 5 (to L2)
        L5:     END_SEND

 137            LOAD_ATTR               11 (scalar_one_or_none + NULL|self)
                CALL                     0

 133            STORE_FAST               4 (settings_row)

 139            LOAD_CONST               2 (False)
                STORE_FAST               5 (is_important)

 140            LOAD_FAST                3 (labels)
                TO_BOOL
                POP_JUMP_IF_FALSE       25 (to L6)

 141            LOAD_CONST               3 ('urgent')
                LOAD_CONST               4 ('vip')
                BUILD_SET                2
                STORE_DEREF             13 (important_labels)

 142            LOAD_GLOBAL             13 (any + NULL)
                LOAD_FAST               13 (important_labels)
                BUILD_TUPLE              1
                LOAD_CONST               5 (<code object <genexpr> at 0x0000024C11496C10, file "D:\fluence\Github\mattbot\backend\app\services\notification_service.py", line 142>)
                MAKE_FUNCTION
                SET_FUNCTION_ATTRIBUTE   8 (closure)

 143            LOAD_FAST                3 (labels)
                GET_ITER

 142            CALL                     0
                CALL                     1
                STORE_FAST               5 (is_important)

 147    L6:     LOAD_FAST                4 (settings_row)
                TO_BOOL
                POP_JUMP_IF_FALSE       58 (to L7)
                LOAD_GLOBAL             15 (is_quiet_hours + NULL)
                LOAD_FAST                4 (settings_row)
                CALL                     1
                TO_BOOL
                POP_JUMP_IF_FALSE       42 (to L7)
                LOAD_FAST                5 (is_important)
                TO_BOOL
                POP_JUMP_IF_TRUE        35 (to L7)

 148            LOAD_GLOBAL             16 (logger)
                LOAD_ATTR               19 (info + NULL|self)

 149            LOAD_CONST               6 ('Suppressing call_screened notification for %s (quiet hours)')

 150            LOAD_GLOBAL             21 (str + NULL)
                LOAD_FAST                1 (call_id)
                CALL                     1
                LOAD_CONST               1 (None)
                LOAD_CONST               7 (8)
                BINARY_SLICE

 148            CALL                     2
                POP_TOP

 152            RETURN_CONST             1 (None)

 154    L7:     LOAD_CONST               8 ('private')
                STORE_FAST               6 (privacy_mode)

 155            LOAD_FAST                4 (settings_row)
                TO_BOOL
                POP_JUMP_IF_FALSE       21 (to L9)

 156            LOAD_FAST                4 (settings_row)
                LOAD_ATTR               22 (notification_privacy_mode)
                COPY                     1
                TO_BOOL
                POP_JUMP_IF_TRUE         2 (to L8)
                POP_TOP
                LOAD_CONST               8 ('private')
        L8:     STORE_FAST               6 (privacy_mode)

 158    L9:     LOAD_GLOBAL             25 (build_push_payload + NULL)

 159            LOAD_CONST               9 ('call_screened')

 161            LOAD_GLOBAL             21 (str + NULL)
                LOAD_FAST                1 (call_id)
                CALL                     1

 162            LOAD_CONST               9 ('call_screened')

 163            LOAD_GLOBAL             26 (datetime)
                LOAD_ATTR               28 (now)
                PUSH_NULL
                LOAD_GLOBAL             30 (UTC)
                CALL                     1
                LOAD_ATTR               33 (isoformat + NULL|self)
                CALL                     0

 160            LOAD_CONST              10 (('call_id', 'event_type', 'timestamp'))
                BUILD_CONST_KEY_MAP      3

 165            LOAD_FAST                6 (privacy_mode)

 158            LOAD_CONST              11 (('notification_type', 'data', 'privacy_mode'))
                CALL_KW                  3
                STORE_FAST               7 (_payload)

 169            LOAD_FAST                0 (db)
                LOAD_ATTR                1 (execute + NULL|self)

 170            LOAD_GLOBAL              3 (select + NULL)
                LOAD_GLOBAL             34 (PushToken)
                CALL                     1

 171            LOAD_ATTR               37 (join + NULL|self)
                LOAD_GLOBAL             38 (Device)
                LOAD_GLOBAL             34 (PushToken)
                LOAD_ATTR               40 (device_id)
                LOAD_GLOBAL             38 (Device)
                LOAD_ATTR               42 (id)
                COMPARE_OP              72 (==)
                CALL                     2

 172            LOAD_ATTR                7 (where + NULL|self)

 173            LOAD_GLOBAL             38 (Device)
                LOAD_ATTR                8 (owner_user_id)
                LOAD_FAST                2 (user_id)
                COMPARE_OP              72 (==)

 174            LOAD_GLOBAL             38 (Device)
                LOAD_ATTR               44 (revoked_at)
                LOAD_ATTR               47 (is_ + NULL|self)
                LOAD_CONST               1 (None)
                CALL                     1

 175            LOAD_GLOBAL             34 (PushToken)
                LOAD_ATTR               44 (revoked_at)
                LOAD_ATTR               47 (is_ + NULL|self)
                LOAD_CONST               1 (None)
                CALL                     1

 172            CALL                     3

 169            CALL                     1
                GET_AWAITABLE            0
                LOAD_CONST               1 (None)
       L10:     SEND                     3 (to L13)
       L11:     YIELD_VALUE              1
       L12:     RESUME                   3
                JUMP_BACKWARD_NO_INTERRUPT 5 (to L10)
       L13:     END_SEND
                STORE_FAST               8 (tokens_result)

 178            LOAD_GLOBAL             49 (list + NULL)
                LOAD_FAST                8 (tokens_result)
                LOAD_ATTR               51 (scalars + NULL|self)
                CALL                     0
                LOAD_ATTR               53 (all + NULL|self)
                CALL                     0
                CALL                     1
                STORE_FAST               9 (tokens)

 180            LOAD_FAST                9 (tokens)
                TO_BOOL
                POP_JUMP_IF_TRUE        35 (to L14)

 181            LOAD_GLOBAL             16 (logger)
                LOAD_ATTR               55 (debug + NULL|self)
                LOAD_CONST              12 ('No push tokens for user %s')
                LOAD_GLOBAL             21 (str + NULL)
                LOAD_FAST                2 (user_id)
                CALL                     1
                LOAD_CONST               1 (None)
                LOAD_CONST               7 (8)
                BINARY_SLICE
                CALL                     2
                POP_TOP

 182            RETURN_CONST             1 (None)

 184   L14:     LOAD_FAST                9 (tokens)
                GET_ITER
       L15:     FOR_ITER                91 (to L18)
                STORE_FAST              10 (token)

 185            LOAD_GLOBAL             16 (logger)
                LOAD_ATTR               19 (info + NULL|self)

 186            LOAD_CONST              13 ('Would send push to device %s for call %s (provider=%s)')

 187            LOAD_GLOBAL             57 (hasattr + NULL)
                LOAD_FAST               10 (token)
                LOAD_CONST              14 ('device_id')
                CALL                     2
                TO_BOOL
                POP_JUMP_IF_FALSE       24 (to L16)
                LOAD_GLOBAL             21 (str + NULL)
                LOAD_FAST               10 (token)
                LOAD_ATTR               40 (device_id)
                CALL                     1
                LOAD_CONST               1 (None)
                LOAD_CONST               7 (8)
                BINARY_SLICE
                JUMP_FORWARD             1 (to L17)
       L16:     LOAD_CONST              15 ('unknown')

 188   L17:     LOAD_GLOBAL             21 (str + NULL)
                LOAD_FAST                1 (call_id)
                CALL                     1
                LOAD_CONST               1 (None)
                LOAD_CONST               7 (8)
                BINARY_SLICE

 189            LOAD_GLOBAL             59 (getattr + NULL)
                LOAD_FAST               10 (token)
                LOAD_CONST              16 ('provider')
                LOAD_CONST              15 ('unknown')
                CALL                     3

 185            CALL                     4
                POP_TOP
                JUMP_BACKWARD           93 (to L15)

 184   L18:     END_FOR
                POP_TOP

 195            LOAD_GLOBAL             21 (str + NULL)
                LOAD_FAST                2 (user_id)
                CALL                     1
                STORE_FAST              11 (uid)

 196            LOAD_GLOBAL             21 (str + NULL)
                LOAD_FAST                1 (call_id)
                CALL                     1
                STORE_FAST              12 (cid)

 197            LOAD_GLOBAL             61 (emit_event + NULL)

 198            LOAD_FAST               11 (uid)

 199            LOAD_CONST              17 ('CALL_ENDED')

 200            LOAD_FAST               12 (cid)

 201            LOAD_CONST              18 (1)

 202            LOAD_CONST              19 ('labels')
                LOAD_FAST                3 (labels)
                COPY                     1
                TO_BOOL
                POP_JUMP_IF_TRUE         2 (to L19)
                POP_TOP
                BUILD_LIST               0
       L19:     BUILD_MAP                1

 197            LOAD_CONST              20 (('user_id', 'event_type', 'call_id', 'seq', 'payload'))
                CALL_KW                  5
                GET_AWAITABLE            0
                LOAD_CONST               1 (None)
       L20:     SEND                     3 (to L23)
       L21:     YIELD_VALUE              1
       L22:     RESUME                   3
                JUMP_BACKWARD_NO_INTERRUPT 5 (to L20)
       L23:     END_SEND
                POP_TOP

 204            LOAD_GLOBAL             61 (emit_event + NULL)

 205            LOAD_FAST               11 (uid)

 206            LOAD_CONST              21 ('SUMMARY_READY')

 207            LOAD_FAST               12 (cid)

 208            LOAD_CONST              22 (2)

 209            BUILD_MAP                0

 204            LOAD_CONST              20 (('user_id', 'event_type', 'call_id', 'seq', 'payload'))
                CALL_KW                  5
                GET_AWAITABLE            0
                LOAD_CONST               1 (None)
       L24:     SEND                     3 (to L27)
       L25:     YIELD_VALUE              1
       L26:     RESUME                   3
                JUMP_BACKWARD_NO_INTERRUPT 5 (to L24)
       L27:     END_SEND
                POP_TOP

 211            LOAD_GLOBAL             61 (emit_event + NULL)

 212            LOAD_FAST               11 (uid)

 213            LOAD_CONST              23 ('TRANSCRIPT_READY')

 214            LOAD_FAST               12 (cid)

 215            LOAD_CONST              24 (3)

 216            BUILD_MAP                0

 211            LOAD_CONST              20 (('user_id', 'event_type', 'call_id', 'seq', 'payload'))
                CALL_KW                  5
                GET_AWAITABLE            0
                LOAD_CONST               1 (None)
       L28:     SEND                     3 (to L31)
       L29:     YIELD_VALUE              1
       L30:     RESUME                   3
                JUMP_BACKWARD_NO_INTERRUPT 5 (to L28)
       L31:     END_SEND
                POP_TOP
                RETURN_CONST             1 (None)

 134   L32:     CLEANUP_THROW
       L33:     EXTENDED_ARG             2
                JUMP_BACKWARD_NO_INTERRUPT 666 (to L5)

 169   L34:     CLEANUP_THROW
       L35:     EXTENDED_ARG             1
                JUMP_BACKWARD_NO_INTERRUPT 283 (to L13)

 197   L36:     CLEANUP_THROW
       L37:     JUMP_BACKWARD_NO_INTERRUPT 53 (to L23)

 204   L38:     CLEANUP_THROW
       L39:     JUMP_BACKWARD_NO_INTERRUPT 34 (to L27)

 211   L40:     CLEANUP_THROW
       L41:     JUMP_BACKWARD_NO_INTERRUPT 15 (to L31)

  --   L42:     CALL_INTRINSIC_1         3 (INTRINSIC_STOPITERATION_ERROR)
                RERAISE                  1
ExceptionTable:
  L1 to L3 -> L42 [0] lasti
  L3 to L4 -> L32 [2]
  L4 to L11 -> L42 [0] lasti
  L11 to L12 -> L34 [2]
  L12 to L21 -> L42 [0] lasti
  L21 to L22 -> L36 [2]
  L22 to L25 -> L42 [0] lasti
  L25 to L26 -> L38 [2]
  L26 to L29 -> L42 [0] lasti
  L29 to L30 -> L40 [2]
  L30 to L33 -> L42 [0] lasti
  L34 to L35 -> L42 [0] lasti
  L36 to L37 -> L42 [0] lasti
  L38 to L39 -> L42 [0] lasti
  L40 to L41 -> L42 [0] lasti

Disassembly of <code object <genexpr> at 0x0000024C11496C10, file "D:\fluence\Github\mattbot\backend\app\services\notification_service.py", line 142>:
  --           COPY_FREE_VARS           1

 142           RETURN_GENERATOR
               POP_TOP
       L1:     RESUME                   0
               LOAD_FAST                0 (.0)

 143           GET_ITER
       L2:     FOR_ITER                24 (to L3)
               STORE_FAST_LOAD_FAST    17 (lbl, lbl)
               LOAD_ATTR                1 (get + NULL|self)
               LOAD_CONST               0 ('label_name')
               CALL                     1
               LOAD_DEREF               2 (important_labels)
               CONTAINS_OP              0
               YIELD_VALUE              0
               RESUME                   5
               POP_TOP
               JUMP_BACKWARD           26 (to L2)
       L3:     END_FOR
               POP_TOP
               RETURN_CONST             1 (None)

  --   L4:     CALL_INTRINSIC_1         3 (INTRINSIC_STOPITERATION_ERROR)
               RERAISE                  1
ExceptionTable:
  L1 to L4 -> L4 [0] lasti

Disassembly of <code object create_and_enqueue_notification at 0x0000024C0FB5C0D0, file "D:\fluence\Github\mattbot\backend\app\services\notification_service.py", line 220>:
 220            RETURN_GENERATOR
                POP_TOP
        L1:     RESUME                   0

 231            LOAD_FAST                0 (db)
                LOAD_ATTR                1 (execute + NULL|self)

 232            LOAD_GLOBAL              3 (select + NULL)
                LOAD_GLOBAL              4 (UserSettings)
                CALL                     1
                LOAD_ATTR                7 (where + NULL|self)
                LOAD_GLOBAL              4 (UserSettings)
                LOAD_ATTR                8 (owner_user_id)
                LOAD_FAST                1 (owner_user_id)
                COMPARE_OP              72 (==)
                CALL                     1

 231            CALL                     1
                GET_AWAITABLE            0
                LOAD_CONST               1 (None)
        L2:     SEND                     3 (to L5)
        L3:     YIELD_VALUE              1
        L4:     RESUME                   3
                JUMP_BACKWARD_NO_INTERRUPT 5 (to L2)
        L5:     END_SEND

 234            LOAD_ATTR               11 (scalar_one_or_none + NULL|self)
                CALL                     0

 230            STORE_FAST               6 (settings_row)

 236            LOAD_CONST               2 ('private')
                STORE_FAST               7 (privacy_mode)

 237            LOAD_FAST                6 (settings_row)
                TO_BOOL
                POP_JUMP_IF_FALSE       21 (to L7)

 238            LOAD_FAST                6 (settings_row)
                LOAD_ATTR               12 (notification_privacy_mode)
                COPY                     1
                TO_BOOL
                POP_JUMP_IF_TRUE         2 (to L6)
                POP_TOP
                LOAD_CONST               2 ('private')
        L6:     STORE_FAST               7 (privacy_mode)

 240    L7:     LOAD_CONST               3 ('none')
                STORE_FAST               8 (quiet_hours_value)

 241            LOAD_FAST                6 (settings_row)
                TO_BOOL
                POP_JUMP_IF_FALSE       26 (to L10)
                LOAD_GLOBAL             15 (is_quiet_hours + NULL)
                LOAD_FAST                6 (settings_row)
                CALL                     1
                TO_BOOL
                POP_JUMP_IF_FALSE       10 (to L10)

 242            LOAD_FAST                3 (priority)
                LOAD_CONST               4 (('low', 'normal'))
                CONTAINS_OP              0
                POP_JUMP_IF_FALSE        2 (to L8)
                LOAD_CONST               5 ('suppressed')
                JUMP_FORWARD             1 (to L9)
        L8:     LOAD_CONST               6 ('silent')
        L9:     STORE_FAST               8 (quiet_hours_value)

 244   L10:     LOAD_GLOBAL             17 (Notification + NULL)

 245            LOAD_FAST                1 (owner_user_id)

 246            LOAD_FAST                2 (notification_type)

 247            LOAD_FAST                3 (priority)

 248            LOAD_FAST                4 (source_entity_type)

 249            LOAD_FAST                5 (source_entity_id)

 250            LOAD_FAST                7 (privacy_mode)

 251            LOAD_FAST                8 (quiet_hours_value)

 244            LOAD_CONST               7 (('owner_user_id', 'type', 'priority', 'source_entity_type', 'source_entity_id', 'privacy_mode_applied', 'quiet_hours_applied'))
                CALL_KW                  7
                STORE_FAST               9 (notification)

 253            LOAD_FAST                0 (db)
                LOAD_ATTR               19 (add + NULL|self)
                LOAD_FAST                9 (notification)
                CALL                     1
                POP_TOP

 254            LOAD_FAST                0 (db)
                LOAD_ATTR               21 (flush + NULL|self)
                CALL                     0
                GET_AWAITABLE            0
                LOAD_CONST               1 (None)
       L11:     SEND                     3 (to L14)
       L12:     YIELD_VALUE              1
       L13:     RESUME                   3
                JUMP_BACKWARD_NO_INTERRUPT 5 (to L11)
       L14:     END_SEND
                POP_TOP

 256            LOAD_FAST                0 (db)
                LOAD_ATTR                1 (execute + NULL|self)

 257            LOAD_GLOBAL              3 (select + NULL)
                LOAD_GLOBAL             22 (PushToken)
                CALL                     1

 258            LOAD_ATTR               25 (join + NULL|self)
                LOAD_GLOBAL             26 (Device)
                LOAD_GLOBAL             22 (PushToken)
                LOAD_ATTR               28 (device_id)
                LOAD_GLOBAL             26 (Device)
                LOAD_ATTR               30 (id)
                COMPARE_OP              72 (==)
                CALL                     2

 259            LOAD_ATTR                7 (where + NULL|self)

 260            LOAD_GLOBAL             26 (Device)
                LOAD_ATTR                8 (owner_user_id)
                LOAD_FAST                1 (owner_user_id)
                COMPARE_OP              72 (==)

 261            LOAD_GLOBAL             26 (Device)
                LOAD_ATTR               32 (revoked_at)
                LOAD_ATTR               35 (is_ + NULL|self)
                LOAD_CONST               1 (None)
                CALL                     1

 262            LOAD_GLOBAL             22 (PushToken)
                LOAD_ATTR               32 (revoked_at)
                LOAD_ATTR               35 (is_ + NULL|self)
                LOAD_CONST               1 (None)
                CALL                     1

 259            CALL                     3

 256            CALL                     1
                GET_AWAITABLE            0
                LOAD_CONST               1 (None)
       L15:     SEND                     3 (to L18)
       L16:     YIELD_VALUE              1
       L17:     RESUME                   3
                JUMP_BACKWARD_NO_INTERRUPT 5 (to L15)
       L18:     END_SEND
                STORE_FAST              10 (tokens_result)

 265            LOAD_GLOBAL             37 (list + NULL)
                LOAD_FAST               10 (tokens_result)
                LOAD_ATTR               39 (scalars + NULL|self)
                CALL                     0
                LOAD_ATTR               41 (all + NULL|self)
                CALL                     0
                CALL                     1
                STORE_FAST              11 (tokens)

 267            LOAD_FAST               11 (tokens)
                GET_ITER
       L19:     FOR_ITER                61 (to L20)
                STORE_FAST              12 (token)

 268            LOAD_GLOBAL             43 (NotificationDelivery + NULL)

 269            LOAD_FAST                9 (notification)
                LOAD_ATTR               30 (id)

 270            LOAD_FAST               12 (token)
                LOAD_ATTR               28 (device_id)

 271            LOAD_FAST               12 (token)
                LOAD_ATTR               44 (provider)

 268            LOAD_CONST               8 (('notification_id', 'device_id', 'provider'))
                CALL_KW                  3
                STORE_FAST              13 (delivery)

 273            LOAD_FAST                0 (db)
                LOAD_ATTR               19 (add + NULL|self)
                LOAD_FAST               13 (delivery)
                CALL                     1
                POP_TOP
                JUMP_BACKWARD           63 (to L19)

 267   L20:     END_FOR
                POP_TOP

 275            LOAD_FAST                0 (db)
                LOAD_ATTR               21 (flush + NULL|self)
                CALL                     0
                GET_AWAITABLE            0
                LOAD_CONST               1 (None)
       L21:     SEND                     3 (to L24)
       L22:     YIELD_VALUE              1
       L23:     RESUME                   3
                JUMP_BACKWARD_NO_INTERRUPT 5 (to L21)
       L24:     END_SEND
                POP_TOP

 277            LOAD_GLOBAL             46 (logger)
                LOAD_ATTR               49 (info + NULL|self)

 278            LOAD_CONST               9 ('Created notification %s (%s) for user %s with %d delivery(ies)')

 279            LOAD_GLOBAL             51 (str + NULL)
                LOAD_FAST                9 (notification)
                LOAD_ATTR               30 (id)
                CALL                     1
                LOAD_CONST               1 (None)
                LOAD_CONST              10 (8)
                BINARY_SLICE

 280            LOAD_FAST                2 (notification_type)

 281            LOAD_GLOBAL             51 (str + NULL)
                LOAD_FAST                1 (owner_user_id)
                CALL                     1
                LOAD_CONST               1 (None)
                LOAD_CONST              10 (8)
                BINARY_SLICE

 282            LOAD_GLOBAL             53 (len + NULL)
                LOAD_FAST               11 (tokens)
                CALL                     1

 277            CALL                     5
                POP_TOP

 285            LOAD_FAST                9 (notification)
                RETURN_VALUE

 231   L25:     CLEANUP_THROW
       L26:     EXTENDED_ARG             2
                JUMP_BACKWARD_NO_INTERRUPT 521 (to L5)

 254   L27:     CLEANUP_THROW
       L28:     EXTENDED_ARG             1
                JUMP_BACKWARD_NO_INTERRUPT 389 (to L14)

 256   L29:     CLEANUP_THROW
       L30:     JUMP_BACKWARD_NO_INTERRUPT 210 (to L18)

 275   L31:     CLEANUP_THROW
       L32:     JUMP_BACKWARD_NO_INTERRUPT 82 (to L24)

  --   L33:     CALL_INTRINSIC_1         3 (INTRINSIC_STOPITERATION_ERROR)
                RERAISE                  1
ExceptionTable:
  L1 to L3 -> L33 [0] lasti
  L3 to L4 -> L25 [2]
  L4 to L12 -> L33 [0] lasti
  L12 to L13 -> L27 [2]
  L13 to L16 -> L33 [0] lasti
  L16 to L17 -> L29 [2]
  L17 to L22 -> L33 [0] lasti
  L22 to L23 -> L31 [2]
  L23 to L26 -> L33 [0] lasti
  L27 to L28 -> L33 [0] lasti
  L29 to L30 -> L33 [0] lasti
  L31 to L32 -> L33 [0] lasti

Disassembly of <code object _decrypt_personal_phone at 0x0000024C0FC755D0, file "D:\fluence\Github\mattbot\backend\app\services\notification_service.py", line 288>:
 288            RESUME                   0

 291            LOAD_FAST                0 (settings_row)
                LOAD_ATTR                0 (personal_phone_ciphertext)
                STORE_FAST               1 (ct)

 292            LOAD_FAST                0 (settings_row)
                LOAD_ATTR                2 (personal_phone_nonce)
                STORE_FAST               2 (nonce)

 293            LOAD_FAST                0 (settings_row)
                LOAD_ATTR                4 (personal_phone_key_version)
                STORE_FAST               3 (kv)

 294            LOAD_FAST                1 (ct)
                TO_BOOL
                POP_JUMP_IF_FALSE       38 (to L3)
                LOAD_FAST                2 (nonce)
                TO_BOOL
                POP_JUMP_IF_FALSE       31 (to L3)
                LOAD_FAST                3 (kv)
                POP_JUMP_IF_NONE        28 (to L3)

 295            NOP

 296    L1:     LOAD_GLOBAL              7 (decrypt_field + NULL)
                LOAD_FAST_LOAD_FAST     18 (ct, nonce)
                LOAD_FAST                3 (kv)
                CALL                     3
                LOAD_ATTR                9 (decode + NULL|self)
                LOAD_CONST               2 ('utf-8')
                CALL                     1
        L2:     RETURN_VALUE

 301    L3:     LOAD_FAST                0 (settings_row)
                LOAD_ATTR               16 (urgent_notify_phone_ciphertext)
                STORE_FAST               1 (ct)

 302            LOAD_FAST                0 (settings_row)
                LOAD_ATTR               18 (urgent_notify_phone_nonce)
                STORE_FAST               2 (nonce)

 303            LOAD_FAST                0 (settings_row)
                LOAD_ATTR               20 (urgent_notify_phone_key_version)
                STORE_FAST               3 (kv)

 304            LOAD_FAST                1 (ct)
                TO_BOOL
                POP_JUMP_IF_FALSE       38 (to L6)
                LOAD_FAST                2 (nonce)
                TO_BOOL
                POP_JUMP_IF_FALSE       31 (to L6)
                LOAD_FAST                3 (kv)
                POP_JUMP_IF_NONE        28 (to L6)

 305            NOP

 306    L4:     LOAD_GLOBAL              7 (decrypt_field + NULL)
                LOAD_FAST_LOAD_FAST     18 (ct, nonce)
                LOAD_FAST                3 (kv)
                CALL                     3
                LOAD_ATTR                9 (decode + NULL|self)
                LOAD_CONST               2 ('utf-8')
                CALL                     1
        L5:     RETURN_VALUE

 310    L6:     RETURN_CONST             1 (None)

  --    L7:     PUSH_EXC_INFO

 297            LOAD_GLOBAL             10 (Exception)
                CHECK_EXC_MATCH
                POP_JUMP_IF_FALSE       24 (to L9)
                POP_TOP

 298            LOAD_GLOBAL             12 (logger)
                LOAD_ATTR               15 (exception + NULL|self)
                LOAD_CONST               3 ('Failed to decrypt personal phone')
                CALL                     1
                POP_TOP
        L8:     POP_EXCEPT
                JUMP_BACKWARD_NO_INTERRUPT 115 (to L3)

 297    L9:     RERAISE                  0

  --   L10:     COPY                     3
                POP_EXCEPT
                RERAISE                  1
       L11:     PUSH_EXC_INFO

 307            LOAD_GLOBAL             10 (Exception)
                CHECK_EXC_MATCH
                POP_JUMP_IF_FALSE       24 (to L13)
                POP_TOP

 308            LOAD_GLOBAL             12 (logger)
                LOAD_ATTR               15 (exception + NULL|self)
                LOAD_CONST               4 ('Failed to decrypt urgent notify phone')
                CALL                     1
                POP_TOP
       L12:     POP_EXCEPT

 310            RETURN_CONST             1 (None)

 307   L13:     RERAISE                  0

  --   L14:     COPY                     3
                POP_EXCEPT
                RERAISE                  1
ExceptionTable:
  L1 to L2 -> L7 [0]
  L4 to L5 -> L11 [0]
  L7 to L8 -> L10 [1] lasti
  L9 to L10 -> L10 [1] lasti
  L11 to L12 -> L14 [1] lasti
  L13 to L14 -> L14 [1] lasti

Disassembly of <code object send_urgent_sms at 0x0000024C0FB246D0, file "D:\fluence\Github\mattbot\backend\app\services\notification_service.py", line 313>:
 313            RETURN_GENERATOR
                POP_TOP
        L1:     RESUME                   0

 321            LOAD_GLOBAL              1 (_decrypt_personal_phone + NULL)
                LOAD_FAST                0 (settings_row)
                CALL                     1
                STORE_FAST               5 (phone)

 322            LOAD_FAST                5 (phone)
                TO_BOOL
                POP_JUMP_IF_TRUE        22 (to L2)

 323            LOAD_GLOBAL              2 (logger)
                LOAD_ATTR                5 (warning + NULL|self)
                LOAD_CONST               1 ('Cannot send urgent SMS: no phone configured')
                CALL                     1
                POP_TOP

 324            RETURN_CONST             2 (False)

 325    L2:     LOAD_FAST                4 (from_number)
                TO_BOOL
                POP_JUMP_IF_TRUE        22 (to L3)

 326            LOAD_GLOBAL              2 (logger)
                LOAD_ATTR                5 (warning + NULL|self)
                LOAD_CONST               3 ('Cannot send urgent SMS: no from_number available')
                CALL                     1
                POP_TOP

 327            RETURN_CONST             2 (False)

 329    L3:     NOP

 330    L4:     LOAD_CONST               4 (0)
                LOAD_CONST               5 (('_get_twilio_client',))
                IMPORT_NAME              3 (app.services.telephony_service)
                IMPORT_FROM              4 (_get_twilio_client)
                STORE_FAST               6 (_get_twilio_client)
                POP_TOP

 332            LOAD_FAST                6 (_get_twilio_client)
                PUSH_NULL
                CALL                     0
                STORE_FAST               7 (client)

 334            LOAD_CONST               6 ('URGENT CALL from ')
                LOAD_FAST                1 (caller_info)
                FORMAT_SIMPLE
                LOAD_CONST               7 (': ')
                LOAD_FAST                2 (summary_snippet)
                LOAD_CONST               8 (None)
                LOAD_CONST               9 (120)
                BINARY_SLICE
                FORMAT_SIMPLE
                LOAD_CONST              10 ('. Open MattBot for details.')
                BUILD_STRING             5

 333            STORE_FAST               8 (body)

 337            LOAD_FAST                7 (client)
                LOAD_ATTR               10 (messages)
                LOAD_ATTR               13 (create + NULL|self)

 338            LOAD_FAST                8 (body)

 339            LOAD_FAST                4 (from_number)

 340            LOAD_FAST                5 (phone)

 337            LOAD_CONST              11 (('body', 'from_', 'to'))
                CALL_KW                  3
                POP_TOP

 342            LOAD_GLOBAL              2 (logger)
                LOAD_ATTR               15 (info + NULL|self)
                LOAD_CONST              12 ('Urgent SMS sent to ***%s for call %s')
                LOAD_FAST                5 (phone)
                LOAD_CONST              13 (-4)
                LOAD_CONST               8 (None)
                BINARY_SLICE
                LOAD_GLOBAL             17 (str + NULL)
                LOAD_FAST                3 (call_id)
                CALL                     1
                LOAD_CONST               8 (None)
                LOAD_CONST              14 (8)
                BINARY_SLICE
                CALL                     3
                POP_TOP

 343    L5:     RETURN_CONST            15 (True)

  --    L6:     PUSH_EXC_INFO

 344            LOAD_GLOBAL             18 (Exception)
                CHECK_EXC_MATCH
                POP_JUMP_IF_FALSE       37 (to L8)
                POP_TOP

 345            LOAD_GLOBAL              2 (logger)
                LOAD_ATTR               21 (exception + NULL|self)
                LOAD_CONST              16 ('Failed to send urgent SMS for call %s')
                LOAD_GLOBAL             17 (str + NULL)
                LOAD_FAST                3 (call_id)
                CALL                     1
                LOAD_CONST               8 (None)
                LOAD_CONST              14 (8)
                BINARY_SLICE
                CALL                     2
                POP_TOP

 346    L7:     POP_EXCEPT
                RETURN_CONST             2 (False)

 344    L8:     RERAISE                  0

  --    L9:     COPY                     3
                POP_EXCEPT
                RERAISE                  1
       L10:     CALL_INTRINSIC_1         3 (INTRINSIC_STOPITERATION_ERROR)
                RERAISE                  1
ExceptionTable:
  L1 to L3 -> L10 [0] lasti
  L4 to L5 -> L6 [0]
  L5 to L6 -> L10 [0] lasti
  L6 to L7 -> L9 [1] lasti
  L7 to L8 -> L10 [0] lasti
  L8 to L9 -> L9 [1] lasti
  L9 to L10 -> L10 [0] lasti

Disassembly of <code object send_urgent_email at 0x0000024C0FBC8B10, file "D:\fluence\Github\mattbot\backend\app\services\notification_service.py", line 349>:
 349            RETURN_GENERATOR
                POP_TOP
        L1:     RESUME                   0

 357            LOAD_FAST                0 (settings_row)
                LOAD_ATTR                0 (urgent_notify_email_address)
                COPY                     1
                TO_BOOL
                POP_JUMP_IF_TRUE         2 (to L2)
                POP_TOP
                LOAD_FAST                1 (user_email)
        L2:     STORE_FAST               5 (to_address)

 358            LOAD_FAST                5 (to_address)
                TO_BOOL
                POP_JUMP_IF_TRUE        22 (to L3)

 359            LOAD_GLOBAL              2 (logger)
                LOAD_ATTR                5 (warning + NULL|self)
                LOAD_CONST               1 ('Cannot send urgent email: no email address available')
                CALL                     1
                POP_TOP

 360            RETURN_CONST             2 (False)

 362    L3:     NOP

 363    L4:     LOAD_CONST               3 (0)
                LOAD_CONST               4 (('send_email',))
                IMPORT_NAME              3 (app.services.email_service)
                IMPORT_FROM              4 (send_email)
                STORE_FAST               6 (send_email)
                POP_TOP

 365            LOAD_CONST               5 ('Urgent Call from ')
                LOAD_FAST                2 (caller_info)
                FORMAT_SIMPLE
                BUILD_STRING             2
                STORE_FAST               7 (subject)

 367            LOAD_CONST               6 ('You have an urgent call in MattBot.\n\nCaller: ')

 368            LOAD_FAST                2 (caller_info)
                FORMAT_SIMPLE
                LOAD_CONST               7 ('\nSummary: ')

 369            LOAD_FAST                3 (summary_snippet)
                FORMAT_SIMPLE
                LOAD_CONST               8 ('\n\nOpen the app for full details: mattbot://call/')

 370            LOAD_FAST                4 (call_id)
                FORMAT_SIMPLE

 367            BUILD_STRING             6

 366            STORE_FAST               8 (body)

 372            LOAD_FAST                6 (send_email)
                PUSH_NULL
                LOAD_FAST_LOAD_FAST     87 (to_address, subject)
                LOAD_FAST                8 (body)
                LOAD_CONST               9 (('to', 'subject', 'body'))
                CALL_KW                  3
                GET_AWAITABLE            0
                LOAD_CONST              10 (None)
        L5:     SEND                     3 (to L8)
        L6:     YIELD_VALUE              1
        L7:     RESUME                   3
                JUMP_BACKWARD_NO_INTERRUPT 5 (to L5)
        L8:     END_SEND
                POP_TOP

 373            LOAD_GLOBAL              2 (logger)
                LOAD_ATTR               11 (info + NULL|self)
                LOAD_CONST              11 ('Urgent email sent to %s for call %s')
                LOAD_FAST                5 (to_address)
                LOAD_CONST              10 (None)
                LOAD_CONST              12 (3)
                BINARY_SLICE
                LOAD_CONST              13 ('***')
                BINARY_OP                0 (+)
                LOAD_GLOBAL             13 (str + NULL)
                LOAD_FAST                4 (call_id)
                CALL                     1
                LOAD_CONST              10 (None)
                LOAD_CONST              14 (8)
                BINARY_SLICE
                CALL                     3
                POP_TOP

 374    L9:     RETURN_CONST            15 (True)

 372   L10:     CLEANUP_THROW
       L11:     JUMP_BACKWARD_NO_INTERRUPT 46 (to L8)

  --   L12:     PUSH_EXC_INFO

 375            LOAD_GLOBAL             14 (Exception)
                CHECK_EXC_MATCH
                POP_JUMP_IF_FALSE       37 (to L14)
                POP_TOP

 376            LOAD_GLOBAL              2 (logger)
                LOAD_ATTR               17 (exception + NULL|self)
                LOAD_CONST              16 ('Failed to send urgent email for call %s')
                LOAD_GLOBAL             13 (str + NULL)
                LOAD_FAST                4 (call_id)
                CALL                     1
                LOAD_CONST              10 (None)
                LOAD_CONST              14 (8)
                BINARY_SLICE
                CALL                     2
                POP_TOP

 377   L13:     POP_EXCEPT
                RETURN_CONST             2 (False)

 375   L14:     RERAISE                  0

  --   L15:     COPY                     3
                POP_EXCEPT
                RERAISE                  1
       L16:     CALL_INTRINSIC_1         3 (INTRINSIC_STOPITERATION_ERROR)
                RERAISE                  1
ExceptionTable:
  L1 to L3 -> L16 [0] lasti
  L4 to L6 -> L12 [0]
  L6 to L7 -> L10 [2]
  L7 to L9 -> L12 [0]
  L9 to L10 -> L16 [0] lasti
  L10 to L11 -> L12 [0]
  L12 to L13 -> L15 [1] lasti
  L13 to L14 -> L16 [0] lasti
  L14 to L15 -> L15 [1] lasti
  L15 to L16 -> L16 [0] lasti

Disassembly of <code object send_urgent_call at 0x0000024C0FBAABD0, file "D:\fluence\Github\mattbot\backend\app\services\notification_service.py", line 380>:
 380            RETURN_GENERATOR
                POP_TOP
        L1:     RESUME                   0

 391            LOAD_GLOBAL              1 (_decrypt_personal_phone + NULL)
                LOAD_FAST                0 (settings_row)
                CALL                     1
                STORE_FAST               5 (phone)

 392            LOAD_FAST                5 (phone)
                TO_BOOL
                POP_JUMP_IF_TRUE        22 (to L2)

 393            LOAD_GLOBAL              2 (logger)
                LOAD_ATTR                5 (warning + NULL|self)
                LOAD_CONST               1 ('Cannot send urgent call: no phone configured')
                CALL                     1
                POP_TOP

 394            RETURN_CONST             2 (False)

 395    L2:     LOAD_FAST                4 (from_number)
                TO_BOOL
                POP_JUMP_IF_TRUE        22 (to L3)

 396            LOAD_GLOBAL              2 (logger)
                LOAD_ATTR                5 (warning + NULL|self)
                LOAD_CONST               3 ('Cannot send urgent call: no from_number available')
                CALL                     1
                POP_TOP

 397            RETURN_CONST             2 (False)

 399    L3:     NOP

 400    L4:     LOAD_CONST               4 (0)
                LOAD_CONST               5 (('escape',))
                IMPORT_NAME              3 (xml.sax.saxutils)
                IMPORT_FROM              4 (escape)
                STORE_FAST               6 (xml_escape)
                POP_TOP

 402            LOAD_CONST               4 (0)
                LOAD_CONST               6 (('_get_twilio_client',))
                IMPORT_NAME              5 (app.services.telephony_service)
                IMPORT_FROM              6 (_get_twilio_client)
                STORE_FAST               7 (_get_twilio_client)
                POP_TOP

 404            LOAD_FAST                6 (xml_escape)
                PUSH_NULL
                LOAD_FAST                1 (caller_info)
                LOAD_CONST               7 (None)
                LOAD_CONST               8 (80)
                BINARY_SLICE
                CALL                     1
                STORE_FAST               8 (safe_caller)

 405            LOAD_FAST                6 (xml_escape)
                PUSH_NULL
                LOAD_FAST                2 (summary_snippet)
                LOAD_CONST               7 (None)
                LOAD_CONST               9 (200)
                BINARY_SLICE
                CALL                     1
                STORE_FAST               9 (safe_summary)

 407            LOAD_CONST              10 ('<?xml version="1.0" encoding="UTF-8"?><Response><Say voice="Polly.Joanna">You have an urgent call in Matt Bot from ')

 410            LOAD_FAST                8 (safe_caller)
                FORMAT_SIMPLE
                LOAD_CONST              11 ('. The caller said: ')

 411            LOAD_FAST                9 (safe_summary)
                FORMAT_SIMPLE
                LOAD_CONST              12 ('. Please check the app for full details.</Say><Pause length="1"/><Hangup/></Response>')

 407            BUILD_STRING             5

 406            STORE_FAST              10 (twiml)

 419            LOAD_FAST                7 (_get_twilio_client)
                PUSH_NULL
                CALL                     0
                STORE_FAST              11 (client)

 420            LOAD_FAST               11 (client)
                LOAD_ATTR               14 (calls)
                LOAD_ATTR               17 (create + NULL|self)

 421            LOAD_FAST               10 (twiml)

 422            LOAD_FAST                4 (from_number)

 423            LOAD_FAST                5 (phone)

 420            LOAD_CONST              13 (('twiml', 'from_', 'to'))
                CALL_KW                  3
                STORE_FAST              12 (call)

 425            LOAD_GLOBAL              2 (logger)
                LOAD_ATTR               19 (info + NULL|self)

 426            LOAD_CONST              14 ('Urgent alert call placed to ***%s for call %s (sid=%s)')

 427            LOAD_FAST                5 (phone)
                LOAD_CONST              15 (-4)
                LOAD_CONST               7 (None)
                BINARY_SLICE
                LOAD_GLOBAL             21 (str + NULL)
                LOAD_FAST                3 (call_id)
                CALL                     1
                LOAD_CONST               7 (None)
                LOAD_CONST              16 (8)
                BINARY_SLICE
                LOAD_FAST               12 (call)
                LOAD_ATTR               22 (sid)

 425            CALL                     4
                POP_TOP

 429    L5:     RETURN_CONST            17 (True)

  --    L6:     PUSH_EXC_INFO

 430            LOAD_GLOBAL             24 (Exception)
                CHECK_EXC_MATCH
                POP_JUMP_IF_FALSE       37 (to L8)
                POP_TOP

 431            LOAD_GLOBAL              2 (logger)
                LOAD_ATTR               27 (exception + NULL|self)
                LOAD_CONST              18 ('Failed to place urgent alert call for call %s')
                LOAD_GLOBAL             21 (str + NULL)
                LOAD_FAST                3 (call_id)
                CALL                     1
                LOAD_CONST               7 (None)
                LOAD_CONST              16 (8)
                BINARY_SLICE
                CALL                     2
                POP_TOP

 432    L7:     POP_EXCEPT
                RETURN_CONST             2 (False)

 430    L8:     RERAISE                  0

  --    L9:     COPY                     3
                POP_EXCEPT
                RERAISE                  1
       L10:     CALL_INTRINSIC_1         3 (INTRINSIC_STOPITERATION_ERROR)
                RERAISE                  1
ExceptionTable:
  L1 to L3 -> L10 [0] lasti
  L4 to L5 -> L6 [0]
  L5 to L6 -> L10 [0] lasti
  L6 to L7 -> L9 [1] lasti
  L7 to L8 -> L10 [0] lasti
  L8 to L9 -> L9 [1] lasti
  L9 to L10 -> L10 [0] lasti

Disassembly of <code object dispatch_urgent_notifications at 0x0000024C0FEDE6D0, file "D:\fluence\Github\mattbot\backend\app\services\notification_service.py", line 435>:
 435            RETURN_GENERATOR
                POP_TOP
        L1:     RESUME                   0

 448            BUILD_MAP                0
                STORE_FAST               6 (results)

 450            LOAD_CONST               1 (None)
                STORE_FAST               7 (from_number)

 451            LOAD_FAST                1 (settings_row)
                LOAD_ATTR                0 (urgent_notify_sms)
                TO_BOOL
                POP_JUMP_IF_TRUE        17 (to L2)
                LOAD_FAST                1 (settings_row)
                LOAD_ATTR                2 (urgent_notify_call)
                TO_BOOL
                POP_JUMP_IF_FALSE      140 (to L7)

 452    L2:     LOAD_CONST               2 (0)
                LOAD_CONST               3 (('UserNumber',))
                IMPORT_NAME              2 (app.models.user_number)
                IMPORT_FROM              3 (UserNumber)
                STORE_FAST               8 (UserNumber)
                POP_TOP

 454            LOAD_FAST                0 (db)
                LOAD_ATTR                9 (execute + NULL|self)

 455            LOAD_GLOBAL             11 (select + NULL)
                LOAD_FAST                8 (UserNumber)
                CALL                     1
                LOAD_ATTR               13 (where + NULL|self)

 456            LOAD_FAST                8 (UserNumber)
                LOAD_ATTR               14 (owner_user_id)
                LOAD_FAST                1 (settings_row)
                LOAD_ATTR               14 (owner_user_id)
                COMPARE_OP              72 (==)

 457            LOAD_FAST                8 (UserNumber)
                LOAD_ATTR               16 (status)
                LOAD_CONST               4 ('active')
                COMPARE_OP              72 (==)

 455            CALL                     2

 458            LOAD_ATTR               19 (limit + NULL|self)
                LOAD_CONST               5 (1)
                CALL                     1

 454            CALL                     1
                GET_AWAITABLE            0
                LOAD_CONST               1 (None)
        L3:     SEND                     3 (to L6)
        L4:     YIELD_VALUE              1
        L5:     RESUME                   3
                JUMP_BACKWARD_NO_INTERRUPT 5 (to L3)
        L6:     END_SEND

 460            LOAD_ATTR               21 (scalar_one_or_none + NULL|self)
                CALL                     0

 453            STORE_FAST               9 (num_row)

 461            LOAD_FAST                9 (num_row)
                TO_BOOL
                POP_JUMP_IF_FALSE       12 (to L7)

 462            LOAD_FAST                9 (num_row)
                LOAD_ATTR               22 (e164)
                STORE_FAST               7 (from_number)

 464    L7:     LOAD_FAST                1 (settings_row)
                LOAD_ATTR                0 (urgent_notify_sms)
                TO_BOOL
                POP_JUMP_IF_FALSE       24 (to L12)

 465            LOAD_GLOBAL             25 (send_urgent_sms + NULL)

 466            LOAD_FAST_LOAD_FAST     19 (settings_row, caller_info)
                LOAD_FAST_LOAD_FAST     69 (summary_snippet, call_id)
                LOAD_FAST                7 (from_number)

 465            CALL                     5
                GET_AWAITABLE            0
                LOAD_CONST               1 (None)
        L8:     SEND                     3 (to L11)
        L9:     YIELD_VALUE              1
       L10:     RESUME                   3
                JUMP_BACKWARD_NO_INTERRUPT 5 (to L8)
       L11:     END_SEND
                LOAD_FAST                6 (results)
                LOAD_CONST               6 ('sms')
                STORE_SUBSCR

 469   L12:     LOAD_FAST                1 (settings_row)
                LOAD_ATTR               26 (urgent_notify_email)
                TO_BOOL
                POP_JUMP_IF_FALSE       24 (to L17)

 470            LOAD_GLOBAL             29 (send_urgent_email + NULL)

 471            LOAD_FAST_LOAD_FAST     18 (settings_row, user_email)
                LOAD_FAST_LOAD_FAST     52 (caller_info, summary_snippet)
                LOAD_FAST                5 (call_id)

 470            CALL                     5
                GET_AWAITABLE            0
                LOAD_CONST               1 (None)
       L13:     SEND                     3 (to L16)
       L14:     YIELD_VALUE              1
       L15:     RESUME                   3
                JUMP_BACKWARD_NO_INTERRUPT 5 (to L13)
       L16:     END_SEND
                LOAD_FAST                6 (results)
                LOAD_CONST               7 ('email')
                STORE_SUBSCR

 474   L17:     LOAD_FAST                1 (settings_row)
                LOAD_ATTR                2 (urgent_notify_call)
                TO_BOOL
                POP_JUMP_IF_FALSE       24 (to L22)

 475            LOAD_GLOBAL             31 (send_urgent_call + NULL)

 476            LOAD_FAST_LOAD_FAST     19 (settings_row, caller_info)
                LOAD_FAST_LOAD_FAST     69 (summary_snippet, call_id)
                LOAD_FAST                7 (from_number)

 475            CALL                     5
                GET_AWAITABLE            0
                LOAD_CONST               1 (None)
       L18:     SEND                     3 (to L21)
       L19:     YIELD_VALUE              1
       L20:     RESUME                   3
                JUMP_BACKWARD_NO_INTERRUPT 5 (to L18)
       L21:     END_SEND
                LOAD_FAST                6 (results)
                LOAD_CONST               8 ('call')
                STORE_SUBSCR

 479   L22:     LOAD_FAST                6 (results)
                TO_BOOL
                POP_JUMP_IF_FALSE       54 (to L27)

 480            LOAD_CONST               2 (0)
                LOAD_CONST               9 (('audit_service',))
                IMPORT_NAME             16 (app.services)
                IMPORT_FROM             17 (audit_service)
                STORE_FAST              10 (audit_service)
                POP_TOP

 481            LOAD_FAST               10 (audit_service)
                LOAD_ATTR               37 (log_event + NULL|self)

 482            LOAD_FAST                0 (db)

 483            LOAD_FAST                1 (settings_row)
                LOAD_ATTR               14 (owner_user_id)

 484            LOAD_CONST              10 ('urgent_notification.dispatched')

 486            LOAD_GLOBAL             39 (str + NULL)
                LOAD_FAST                5 (call_id)
                CALL                     1

 487            LOAD_FAST                6 (results)

 485            LOAD_CONST              11 (('call_id', 'channels'))
                BUILD_CONST_KEY_MAP      2

 481            LOAD_CONST              12 (('owner_user_id', 'event_type', 'details'))
                CALL_KW                  4
                GET_AWAITABLE            0
                LOAD_CONST               1 (None)
       L23:     SEND                     3 (to L26)
       L24:     YIELD_VALUE              1
       L25:     RESUME                   3
                JUMP_BACKWARD_NO_INTERRUPT 5 (to L23)
       L26:     END_SEND
                POP_TOP

 491   L27:     LOAD_FAST                6 (results)
                RETURN_VALUE

 454   L28:     CLEANUP_THROW
       L29:     JUMP_BACKWARD_NO_INTERRUPT 223 (to L6)

 465   L30:     CLEANUP_THROW
       L31:     JUMP_BACKWARD_NO_INTERRUPT 154 (to L11)

 470   L32:     CLEANUP_THROW
       L33:     JUMP_BACKWARD_NO_INTERRUPT 115 (to L16)

 475   L34:     CLEANUP_THROW
       L35:     JUMP_BACKWARD_NO_INTERRUPT 76 (to L21)

 481   L36:     CLEANUP_THROW
       L37:     JUMP_BACKWARD_NO_INTERRUPT 14 (to L26)

  --   L38:     CALL_INTRINSIC_1         3 (INTRINSIC_STOPITERATION_ERROR)
                RERAISE                  1
ExceptionTable:
  L1 to L4 -> L38 [0] lasti
  L4 to L5 -> L28 [2]
  L5 to L9 -> L38 [0] lasti
  L9 to L10 -> L30 [2]
  L10 to L14 -> L38 [0] lasti
  L14 to L15 -> L32 [2]
  L15 to L19 -> L38 [0] lasti
  L19 to L20 -> L34 [2]
  L20 to L24 -> L38 [0] lasti
  L24 to L25 -> L36 [2]
  L25 to L29 -> L38 [0] lasti
  L30 to L31 -> L38 [0] lasti
  L32 to L33 -> L38 [0] lasti
  L34 to L35 -> L38 [0] lasti
  L36 to L37 -> L38 [0] lasti
